Workbook
Name _05_04_2009: #REF!
Name _05_04_2009: #REF!
Name _05_04_2009: #REF!
Name _05_04_2009: #REF!
Name _05_04_2009: #REF!
Name a: '[1]Term Outstanding Payment'!#REF!
Name a: '[1]Term Outstanding Payment'!#REF!
Name a: '[1]Term Outstanding Payment'!#REF!
Name a: '[1]Term Outstanding Payment'!#REF!
Name a: '[1]Term Outstanding Payment'!#REF!
Name AA: #REF!
Name AA: #REF!
Name AA: #REF!
Name AA: #REF!
Name AA: #REF!
Name aaa: #REF!
Name aaa: #REF!
Name aaa: #REF!
Name aaa: #REF!
Name aaa: #REF!
Name aaaaa: #REF!
Name aaaaa: #REF!
Name aaaaa: #REF!
Name aaaaa: #REF!
Name aaaaa: #REF!
Name aaaaaaaaaa: #REF!
Name aaaaaaaaaa: #REF!
Name aaaaaaaaaa: #REF!
Name aaaaaaaaaa: #REF!
Name aaaaaaaaaa: #REF!
Name AAAAAAAAAAAAA: #REF!
Name AAAAAAAAAAAAA: #REF!
Name AAAAAAAAAAAAA: #REF!
Name AAAAAAAAAAAAA: #REF!
Name AAAAAAAAAAAAA: #REF!
Name AAAAAAAAAAAAAAAAAA: #REF!
Name AAAAAAAAAAAAAAAAAA: #REF!
Name AAAAAAAAAAAAAAAAAA: #REF!
Name AAAAAAAAAAAAAAAAAA: #REF!
Name AAAAAAAAAAAAAAAAAA: #REF!
Name AAAAAAAAAAAAAAAAAAAAA: #REF!
Name AAAAAAAAAAAAAAAAAAAAA: #REF!
Name AAAAAAAAAAAAAAAAAAAAA: #REF!
Name AAAAAAAAAAAAAAAAAAAAA: #REF!
Name AAAAAAAAAAAAAAAAAAAAA: #REF!
Name AAAAAAAAAAAAAAAAAAAAAAAAAAA: #REF!
Name AAAAAAAAAAAAAAAAAAAAAAAAAAA: #REF!
Name AAAAAAAAAAAAAAAAAAAAAAAAAAA: #REF!
Name AAAAAAAAAAAAAAAAAAAAAAAAAAA: #REF!
Name AAAAAAAAAAAAAAAAAAAAAAAAAAA: #REF!
Name AAAAAAAAAAAAAAAAAAAAAAAAAAAA: #REF!
Name AAAAAAAAAAAAAAAAAAAAAAAAAAAA: #REF!
Name AAAAAAAAAAAAAAAAAAAAAAAAAAAA: #REF!
Name AAAAAAAAAAAAAAAAAAAAAAAAAAAA: #REF!
Name AAAAAAAAAAAAAAAAAAAAAAAAAAAA: #REF!
Name AAAAAAAAAAAAAAAAAAAAAAAAAAAAAA: #REF!
Name AAAAAAAAAAAAAAAAAAAAAAAAAAAAAA: #REF!
Name AAAAAAAAAAAAAAAAAAAAAAAAAAAAAA: #REF!
Name AAAAAAAAAAAAAAAAAAAAAAAAAAAAAA: #REF!
Name AAAAAAAAAAAAAAAAAAAAAAAAAAAAAA: #REF!

Sheet Public Holiday
A1: ­
A2: Tarikh | B2: Hari | C2: Cuti | D2: Negeri Berkenaan
A3: 46023 | B3: Khamis | C3: Tahun Baru | D3: Selangor
A5: 46070 | B5: Selasa | C5: Tahun Baru Cina | D5: Selangor
A7: 46071 | B7: Rabu | C7: Tahun Baru Cina Hari Kedua | D7: Selangor
A9: 46055 | B9: Ahad | C9: Hari Thaipusam | D9: Selangor
A11: 46088 | B11: Sabtu | C11: Hari Nuzul Al-Quran | D11: Selangor
A13: 46101 | B13: Jumaat | C13: Cuti Hari Raya | D13: Selangor
A15: 46102 | B15: Sabtu | C15: Hari Raya Aidilfitri | D15: Selangor
A17: 46103 | B17: Ahad | C17: Hari Raya Aidilfitri Hari Kedua | D17: Selangor
A19: 46104 | B19: Isnin | C19: Cuti Hari Raya | D19: Selangor
A21: 45778 | B21: Khamis | C21: Hari Pekerja | D21: Selangor
A23: 46169 | B23: Rabu | C23: Hari Raya Haji | D23: Selangor
A25: 46173 | B25: Ahad | C25: Hari Wesak | D25: Selangor
... A49: 46381 | B49: Jumaat | C49: Hari Krismas | D49: Selangor
A56: * Subject to change (Tertakluk kepada perubahan), TBC - To be confirmed

Sheet KDI
A1: Indicator No. | B1: Indicator | E1: Frequency of Deduction | F1: Biomedical Equipment Purchase Cost (RM) | H1: Deduction Range Value (RM) | J1: Maximum Demerit Point per Work Order
F2: From | G2: To
A3: B.1 | B3: The Company shall respond to the request within the specified time frame | E3: Per event | F3: 0.00 5,000.00 10,000.00 15,000.00 20,000.00 25,000.00 30,000.00 35,000.00 40,000.00 > 45,000.00 | G3: 4,999.99 9,999.99 14,999.99 19,999.99 24,999.99 29,999.99 34,999.99 39,999.99 44,999.99 | H3: 10.00 20.00 30.00 40.00 50.00 60.00 70.00 80.00 90.00 100.00 | J3: 1
A4: B.2 | B4: The Company shall carry out repairs to restore faulty medical equipment to a specified condition when it fails to function as per manufacturer’s specification within seven (7) working days. | E4: Per day | F4: 0.00 5,000.00 10,000.00 15,000.00 20,000.00 25,000.00 30,000.00 35,000.00 40,000.00 > 45,000.00 | G4: 4,999.99 9,999.99 14,999.99 19,999.99 24,999.99 29,999.99 34,999.99 39,999.99 44,999.99 | H4: 10.00 20.00 30.00 40.00 50.00 60.00 70.00 80.00 90.00 100.00 | J4: Number of working days for the month
A5: B.3 | B5: The Company shall carry out scheduled maintenance as per schedule in accordance to the procedure as specified in Agreement. Scheduled maintenance shall include complete safety and performance tests. | E5: Per event | F5: 0.00 5,000.00 10,000.00 15,000.00 20,000.00 25,000.00 30,000.00 35,000.00 40,000.00 45,000.00 | G5: 4,999.99 9,999.99 14,999.99 19,999.99 24,999.99 29,999.99 34,999.99 39,999.99 44,999.99 49,999.99 | H5: 10.00 20.00 30.00 40.00 50.00 60.00 70.00 80.00 90.00 100.00 | J5: 1
F6: For every RM 5,000 increment of equipment cost, an increase of RM10 will be applied subsequently
A7: B.4 | B7: The Company shall ensure biomedical equipment meets the uptime target as set in the Agreement. | E7: Per event | H7: 1st level of Uptime Target (TRKPI) | I7: 2nd level of Uptime Target (80%) | J7: 2
F8: 0.00 5,000.00 10,000.00 15,000.00 20,000.00 25,000.00 30,000.00 35,000.00 40,000.00 45,000.00 | G8: 4,999.99 9,999.99 14,999.99 19,999.99 24,999.99 29,999.99 34,999.99 39,999.99 44,999.99 49,999.99 | H8: 10.00 20.00 30.00 40.00 50.00 60.00 70.00 80.00 90.00 100.00 | I8: 20.00 40.00 60.00 80.00 100.00 120.00 140.00 160.00 180.00 200.00
F9: For every RM 5,000 increment of equipment cost, an increase of RM10 will be applied subsequently for 1st Uptime Target and an increase of RM20 for 2nd Uptime Target will be applied subsequently
A10: B.5 | B10: The Company shall attend and witness T&C and manage biomedical equipment within the warranty period. | E10: Per event | F10: 0.00 5,000.00 10,000.00 15,000.00 20,000.00 25,000.00 30,000.00 35,000.00 40,000.00 45,000.00 | G10: 4,999.99 9,999.99 14,999.99 19,999.99 24,999.99 29,999.99 34,999.99 39,999.99 44,999.99 49,999.99 | H10: 10.00 20.00 30.00 40.00 50.00 60.00 70.00 80.00 90.00 100.00 | J10: 1
F11: For every RM 5,000 increment of equipment cost, an increase of RM10 will be applied subsequently

Sheet BEMSdar
A1: MINISTRY OF HEALTH
A2: Deduction Mapping Report Biomedical Engineering Maintenance Services (BEMS)
D5: HOSPITAL NAME : | E5: Hospital Orang Asli Gombak | I5: STATE: | J5: W.P. Kuala Lumpur
D7: MONTH/YEAR : | E7: 46082 | I7: COMPANY: | J7: Ambang Wira Sdn Bhd
A9: MONTHLY SERVICE FEE (RM) : | E9: 17762.21
A11: BEMS MONTHLY FEE (RM) @ 97.5% : | E11: =E9*0.975 -> 17318.155
A13: FMS MONTHLY FEE (RM) @ 2.5% : | E13: =E9-E11 -> 444.05525
A17: No | B17: Key Deduction Indicators | I17: Frequency | L17: Deduction Value (RM) | N17: Deduction % | O17: Performance Level (%)
A19: B.1 | B19: All service requests shall be responded by the Company’s trained technical personal within the timeframe as stipulated in the Agreement. | I19: Per event | L19: ='B1-RESPONSE & B2-REPAIR'!N37 -> 0 | N19: =L19/$E$11% -> 0 | O19: =100-N19 -> 100
A20: B.2 | B20: All unscheduled maintenance works including relevant maintenance calibration, safety tests and functional checks shall be completed within seven (7) working days. | I20: Per day | L20: ='B1-RESPONSE & B2-REPAIR'!T37 -> 2200 | N20: =L20/$E$11% -> 12.703432 | O20: =100-N20 -> 87.296568
A21: B.3 | B21: Scheduled maintenance shall be carried out as per schedule and according to the procedure as specified in the Agreement. Scheduled maintenance shall include complete safety and performance tests. | I21: Per event | L21: ='B3-SCHEDULED'!L65 -> 0 | N21: =L21/$E$11% -> 0 | O21: =100-N21 -> 100
A22: B.4 | B22: All biomedical equipment shall be functioning and maintained to ensure uptime target as specified in the TRKPI are met. | I22: Per event | L22: ='B4-UPTIME'!AA37 -> 0 | N22: =L22/$E$11% -> 0 | O22: =100-N22 -> 100
A23: B.5 | B23: T&C and Warranty Management of newly introduced biomedical shall be managed and performed according to the Agreement and related acts, standards and regulations. | I23: Per event | L23: ='B5-T&C'!O23 -> 0 | N23: =L23/$E$11% -> 0 | O23: =100-N23 -> 100
A24: Total | L24: =SUM(L19:M23) -> 2200 | N24: =L24/$E$9% -> 12.385846 | O24: =100-N24 -> 87.614154
C27: Prepared by: | I27: Verified by:
C31: NUR ALIAH BINTI HUSSIN | I31: JULIWATI BINTI MATSAH
C32: Head of BEMS | I32: Facility Manager
C33: Ambang Wira Sdn Bhd- Hospital Orang Asli Gombak | I33: Ambang Wira Sdn Bhd- Hospital Orang Asli Gombak
C34: Date: | I34: Date:

Sheet B1-RESPONSE & B2-REPAIR
B2: MINISTRY OF HEALTH
B3: Deduction Mapping Report Biomedical Engineering Maintenance Services (BEMS)
B4: INDICATOR B.1 RESPONSE TIME & B.2 REPAIR TIME
A6: HOSPITAL NAME: | C6: HOSPITAL ORANG ASLI GOMBAK | I6: FIRST DATE OF THE MONTH : | L6: 1/3/2026 | P6: (For Calculation)
A8: STATE: | C8: WILAYAH PERSEKUTUAN KUALA LUMPUR | I8: LAST DATE OF THE MONTH : | L8: 31/3/2026 | P8: (For Calculation)
A10: COMPANY: | C10: AMBANG WIRA SDN BHD | I10: BEMS MONTHLY FEE (RM) @ 97.5% : | L10: =BEMSdar!$E$11 -> 17318.155
A12: MONTH/YEAR: | C12: 46082 | I12: FMS MONTHLY FEE (RM) @ 2.5% : | L12: =BEMSdar!$E$13 -> 444.05525
A14: Notes:
A15: 1) Deduction Ringgit Equivalent is based on Appendix 11 of the Agreement, Section B3 Key Deduction Indicators for BEMS
A16: 2) Deduction Value for Indicator B.1 is Deduction Ringgit Equivalent (per event)
A17: 3) Total Repair Time includes weekend & public holiday
A18: 4) Demerit Point for Indicator B.2 is calculated based on completion date against request date, less by 7 working days
A19: 5) Deduction Value for Indicator B.2 is Demerit Point multiply by Deduction Ringgit Equivalent
A21: No | B21: Asset No | C21: Asset Description | D21: Asset Purchase Price (RM) | E21: Work Order No. | F21: User Location | G21: Work Order/ Complaint Details | H21: Response Category (Emergency/ Normal) | I21: Total Response Time (minutes) | J21: Work Request Date | K21: Work Completion Date | L21: Deduction Ringgit Equivalent (RM) | M21: Indicator B.1 | P21: Indicator B.2
M22: Validate Status (Y/N) | N22: Deduction Value (RM) | O22: Remarks/ Exemption | P22: Validate Status (Y/N) | Q22: Total Repair Time (day) | R22: Last date of 7 working days (dd/mm/yy) | S22: Demerit Point | T22: Deduction Value (RM) | U22: Remarks/ Exemption
A23: Current Month (Work Order Completed)
A24: 1 | B24: HOAG 10125 | C24: PORTABLE CUTTING UNIT | D24: 29500 | E24: HOAGWIBE26002073 | F24: UNIT DENTAL | G24: DENTAL PAC SCALER TIDAK BERFUNGSI, TIADA GETARAN | H24: N | I24: 5.0069444 | J24: 46097 | K24: 46107 | L24: =IF(D24>44999.99,100,ROUNDUP((D24/4999.99)*10,-1)) -> 60 | M24: N | N24: =IF(M24="Y",L24,0) -> 0 | P24: N | Q24: =K24-J24+1 -> 11 | R24: =WORKDAY(J24,6,tarikhcuti) -> 46107 | S24: =IF(K24>R24,K24-R24,0) -> 0 | T24: =L24*S24 -> 0 | U24: Breakdown
A25: =A24+1 -> 2 | B25: HOAG 10187 | C25: ULTRASOUND SCANNER | D25: 40000 | E25: HOAGWIBE26002078 | F25: UNIT KECEMASAN | G25: MESIN ULTRASOUND - SYSTEM ERROR,TAK BOLEH ON | H25: N | I25: 5.0083333 | J25: 46097 | K25: 46107 | L25: =IF(D25>44999.99,100,ROUNDUP((D25/4999.99)*10,-1)) -> 90 | M25: N | N25: =IF(M25="Y",L25,0) -> 0 | P25: N | Q25: =K25-J25+1 -> 11 | R25: =WORKDAY(J25,6,tarikhcuti) -> 46107 | S25: =IF(K25>R25,K25-R25,0) -> 0 | T25: =L25*S25 -> 0 | U25: Breakdown
A26: =A25+1 -> 3 | B26: HOAG 10043 | C26: DEFIBRILLTOR | D26: 65000 | E26: HOAGWIBE26002169 | F26: UNIT KECEMASAN | G26: MESIN ZOLL X SERIES ECG TAK DAPAT READING | H26: N | I26: 5.0069444 | J26: 46107 | K26: 46107 | L26: =IF(D26>44999.99,100,ROUNDUP((D26/4999.99)*10,-1)) -> 100 | M26: N | N26: =IF(M26="Y",L26,0) -> 0 | P26: N | Q26: =K26-J26+1 -> 1 | R26: =WORKDAY(J26,6,tarikhcuti) -> 46115 | S26: =IF(K26>R26,K26-R26,0) -> 0 | T26: =L26*S26 -> 0 | U26: Breakdown
A27: =A26+1 -> 4 | B27: HOAG 10420 | C27: DEFIBRILLATOR | D27: 75015.73 | E27: HOAGWIBE26002196 | F27: UNIT KECEMASAN | G27: MESIN MONITOR VITAL SIGN MENUNJUKKAN BATTERY EXPIRED | H27: N | I27: 5.0020833 | J27: 46108 | K27: 46108 | L27: =IF(D27>44999.99,100,ROUNDUP((D27/4999.99)*10,-1)) -> 100 | M27: N | N27: =IF(M27="Y",L27,0) -> 0 | P27: N | Q27: =K27-J27+1 -> 1 | R27: =WORKDAY(J27,6,tarikhcuti) -> 46118 | S27: =IF(K27>R27,K27-R27,0) -> 0 | T27: =L27*S27 -> 0 | U27: Breakdown
A29: Current Month (Work Order Open)
A30: 1 | B30: HOAG 10132 | C30: ADEC OFFICER UNIT DENTAL CHAIR AND STOOL | D30: 49500 | E30: HOAGWIBE26001497 | F30: BILIK SURGERI 3 (UNIT DENTAL) | G30: TRIANGLE LOW SPEED HANDPIECE SURGERY 3 TIDAK BERFUNGSI | H30: N | I30: 5.0104167 | J30: 46082 | K30: 46112 | L30: =IF(D30>44999.99,100,ROUNDUP((D30/4999.99)*10,-1)) -> 100 | M30: N | N30: =IF(M30="Y",L30,0) -> 0 | P30: N | Q30: =K30-J30+1 -> 31 | R30: =WORKDAY(J30,6,tarikhcuti) -> 46090 | S30: =IF(K30>R30,K30-R30,0) -> 22 | T30: =L30*S30 -> 2200 | U30: Breakdown
A33: 1 | B33: HOAG 10108 | C33: ADEC OFFICER UNIT DENTAL CHAIR AND STOOL | D33: 49950 | E33: HOAGWIBE26001520 | F33: UNIT DENTAL | G33: DENTAL SUCTION PUMP EXTERNAL ROSAK | H33: N | I33: 5.0083333 | J33: 46079 | K33: 46084 | L33: =IF(D33>44999.99,100,ROUNDUP((D33/4999.99)*10,-1)) -> 100 | M33: N | N33: =IF(M33="Y",L33,0) -> 0 | P33: N | Q33: =K33-J33+1 -> 6 | R33: =WORKDAY(J33,6,tarikhcuti) -> 46087 | S33: =IF(K33>R33,K33-R33,0) -> 0 | T33: =L33*S33 -> 0 | U33: Breakdown
A35: Previous Month (Work Order Open)
A37: TOTAL DEDUCTION FOR IND. B.1: | N37: =SUM(N29:N35) -> 0 | O37: TOTAL DEDUCTION FOR IND. B.2: | T37: =SUM(T25:T36) -> 2200
J38: 43718.368 | K38: 43738.999 | L38: =K38-J38 -> 20.63125 | M38: =(8760-495)/8760 -> 0.94349315

Sheet B3-SCHEDULED
A3: MINISTRY OF HEALTH
A4: Deduction Mapping Report Biomedical Engineering Maintenance Services (BEMS)
B5: INDICATOR B.3 SCHEDULED MAINTENANCE
A7: HOSPITAL NAME : | C7: HOSPITAL ORANG ASLI GOMBAK | H7: MONTH/YEAR : | J7: =BEMSdar!E7 -> 46082
B9: STATE : | C9: WILAYAH PERSEKUTUAN KUALA LUMPUR | F9: BEMS MONTHLY FEE (RM) @ 97.5% : | J9: =BEMSdar!$E$11 -> 17318.155
B11: COMPANY : | C11: AMBANG WIRA SDN BHD | F11: FMS MONTHLY FEE (RM) @ 2.5% : | J11: =BEMSdar!$E$13 -> 444.05525
A13: Notes:
A14: 1) Deduction Ringgit Equivalent is based on Appendix 11 of the Agreement, Section B3 Key Deduction Indicators for BEMS
A15: 2) Deduction Value for Indicator B.3 is Deduction Ringgit Equivalent (per event)
A16: 3) Rescheduled Date is the final rescheduled date if there are multiple rescheduling
A17: 4) Display only asset affected by deduction
A19: No | B19: Asset No | C19: Asset Description | D19: Work Order No. | E19: User Location | F19: Scheduled Start Date | G19: Scheduled End Date | H19: Rescheduled Date | I19: Maintenance Date | J19: Validate Status (Y/N) | K19: Deduction Ringgit Equivalent (RM) | L19: Indicator B.3
L20: Deduction Value (RM) | M20: Remarks/ Exemption
A21: 1 | B21: HOAG 10188 | C21: Scanning Systems, Ultrasonic, Abdominal | D21: HOAGWOBE26001662 | E21: BILIK PEGAWAI PERUBATAN (UNIT KKIA) | F21: 46084 | G21: 46085 | I21: 46090 | J21: N | M21: PPM DONE
A22: 2 | B22: HOAG 10095 | C22: Thermometer, Electronic | D22: HOAGWOBE26001663 | E22: MAKMAL BIOKIMIA (UNIT PATOLOGI) | F22: 46090 | G22: 46091 | I22: 46092 | J22: N | M22: PPM DONE
A23: 3 | B23: HOAG 10184 | C23: Thermometer, Electronic | D23: HOAGWOBE26001664 | E23: BILIK PEMERIKSAAN (UNIT KKIA) | F23: 46091 | G23: 46092 | I23: 46092 | J23: N | M23: PPM DONE
A24: 4 | B24: HOAG 10185 | C24: Thermometer, Electronic | D24: HOAGWOBE26001665 | E24: BILIK PEMERIKSAAN (UNIT KKIA) | F24: 46091 | G24: 46092 | I24: 46092 | J24: N | M24: PPM DONE
A25: 5 | B25: HOAG 10054 | C25: DIGITAL THERMOMETER | D25: HOAGWOBE26001666 | E25: BILIK RAWATAN 1 (UNIT OPD) | F25: 46091 | G25: 46092 | I25: 46092 | J25: N | M25: PPM DONE
A26: 6 | B26: HOAG 10249 | C26: THERMOMETER,ELECTRONIC/DIGITAL (ZEAL) | D26: HOAGWOBE26001667 | E26: BILIK RAWATAN | F26: 46092 | G26: 46093 | I26: 46092 | J26: N | M26: PPM DONE
A27: 7 | B27: HOAG 10051 | C27: Thermometer, Electronic | D27: HOAGWOBE26001668 | E27: RUANG SUB-STOR & RUANG PEJABAT (UNIT FARMASI) | F27: 46093 | G27: 46094 | I27: 46093 | J27: N | M27: PPM DONE
A28: 8 | B28: HOAG10045 | C28: Thermometer, Electronic | D28: HOAGWOBE26001669 | E28: RUANG SUB-STOR & RUANG PEJABAT (UNIT FARMASI) | F28: 46093 | G28: 46094 | I28: 46093 | J28: N | M28: PPM DONE
A29: 9 | B29: HOAG10046 | C29: Thermometer, Electronic | D29: HOAGWOBE26001670 | E29: RUANG SUB-STOR & RUANG PEJABAT (UNIT FARMASI) | F29: 46093 | G29: 46094 | I29: 46093 | J29: N | M29: PPM DONE
A30: 10 | B30: HOAG 10047 | C30: Thermometer, Electronic | D30: HOAGWOBE26001671 | E30: RUANG SUB-STOR & RUANG PEJABAT (UNIT FARMASI) | F30: 46093 | G30: 46094 | I30: 46093 | J30: N | M30: PPM DONE
A31: 11 | B31: HOAG 10048 | C31: Thermometer, Electronic | D31: HOAGWOBE26001672 | E31: RUANG SUB-STOR & RUANG PEJABAT (UNIT FARMASI) | F31: 46093 | G31: 46094 | I31: 46093 | J31: N | M31: PPM DONE
A32: 12 | B32: HOAG 10049 | C32: Thermometer, Electronic | D32: HOAGWOBE26001673 | E32: RUANG SUB-STOR & RUANG PEJABAT (UNIT FARMASI) | F32: 46093 | G32: 46094 | I32: 46093 | J32: N | M32: PPM DONE
... A58: 38 | B58: HOAG 10066 | C58: Nebulizers, Nonheated | D58: HOAGWOBE26001700 | E58: BILIK OPTOMETRIST (UNIT OPD) | F58: 46108 | G58: 46109 | I58: 46108 | J58: N | M58: PPM DONE
A59: Current Month (Open)
A61: Previous Month (Closed)
A63: Previous Month (Open)
A65: TOTAL DEDUCTION FOR IND. B.3: | L65: =SUM(L20:L64) -> 0

Sheet B4-UPTIME
A1: MINISTRY OF HEALTH
A2: Deduction Mapping Report Biomedical Engineering Maintenance Services (BEMS)
A3: INDICATOR B.4 UPTIME GUARANTEE
B5: HOSPITAL NAME : | C5: HOSPITAL ORANG ASLI GOMBAK | N5: MONTH/YEAR : | U5: =BEMSdar!E7 -> 46082
B7: STATE : | C7: WILAYAH PERSEKUTUAN KUALA LUMPUR | N7: BEMS MONTHLY FEE (RM)@ 97.5% : | U7: =BEMSdar!$E$11 -> 17318.155
B9: COMPANY : | C9: AMBANG WIRA SDN BHD | N9: FMS MONTHLY FEE (RM) @ 2.5% : | U9: =BEMSdar!$E$13 -> 444.05525
A11: Notes:
A12: 1) Deduction Ringgit Equivalent is based on Appendix 11 of the Agreement, Section B3 Key Deduction Indicators for BEMS
A13: 2) Deduction Value for 1st cut off is Deduction Ringgit Equivalent (per event)
A14: 3) Deduction Value for 2nd cut off is Deduction Ringgit Equivalent (per event) multiply by 2
A15: 4) Display only asset affected by deduction
A17: No. | B17: Asset No | C17: Type Code | D17: Type Description | E17: Asset Purchase cost | F17: Asset Age | G17: TRKPI % | H17: Uptime % | T17: Deduction Ringgit Equivalent (RM) | U17: Previous Deduction (Month) | W17: Deduction for the month (Y/N) | Y17: Deduction Value (RM) | AA17: Total Deduction (RM) | AB17: Remarks
H18: Jan | I18: Feb | J18: Mar | K18: Apr | L18: May | M18: Jun | N18: Jul | O18: Aug | P18: Sep | Q18: Oct | R18: Nov | S18: Dec | U18: 1st | V18: 2nd | W18: 1st | X18: 2nd | Y18: 1st | Z18: 2nd
A19: 1 | B19: HOAG 10043 | C19: 17-882 | D19: DEFIBRILLTOR ZOLL | E19: 65000 | F19: 5-10 YRS | G19: 0.95 | H19: 0.99976592 | J19: 0.99375 | T19: =ROUNDUP((E19/4999.99)*10,-1) -> 140 | W19: N | X19: N | Y19: =IF(W19="Y",T19,0) -> 0 | Z19: =IF(X19="Y",T19*2,0) -> 0 | AA19: =Y19+Z19 -> 0
A20: =A19+1 -> 2 | B20: HOAG 10103 | C20: 17-740 | D20: HEMATOLOGY ANALYSER, | E20: 189000 | F20: >10 | G20: 0.85 | H20: 0.99976592 | T20: =ROUNDUP((E20/4999.99)*10,-1) -> 380 | W20: N | X20: N | Y20: =IF(W20="Y",T20,0) -> 0 | Z20: =IF(X20="Y",T20*2,0) -> 0 | AA20: =Y20+Z20 -> 0
A21: =A20+1 -> 3 | B21: HOAG 10242 | C21: 12-276 | D21: ANGLE POISE LAMP | E21: 150 | F21: >10 | G21: 0.85 | H21: 0.99988296 | T21: =ROUNDUP((E21/4999.99)*10,-1) -> 10 | W21: N | X21: N | Y21: =IF(W21="Y",T21,0) -> 0 | Z21: =IF(X21="Y",T21*2,0) -> 0 | AA21: =Y21+Z21 -> 0
A22: =A21+1 -> 4 | B22: HOAG 10001 | C22: 11-407 | D22: ELECTROCARDIOGRAPHS | E22: 11990 | F22: 5-10 YRS | G22: 0.92 | H22: 0.99988296 | T22: =ROUNDUP((E22/4999.99)*10,-1) -> 30 | W22: N | X22: N | Y22: =IF(W22="Y",T22,0) -> 0 | Z22: =IF(X22="Y",T22*2,0) -> 0 | AA22: =Y22+Z22 -> 0
A23: =A22+1 -> 5 | B23: HOAG 10414 | C23: 10-551 | D23: FUNDUS CAMERA | E23: 97000 | F23: < 5YRS | G23: 0.96 | H23: 0.99903846 | T23: =ROUNDUP((E23/4999.99)*10,-1) -> 200 | W23: N | X23: N | Y23: =IF(W23="Y",T23,0) -> 0 | Z23: =IF(X23="Y",T23*2,0) -> 0 | AA23: =Y23+Z23 -> 0
A24: =A23+1 -> 6 | B24: HOAG 10200 | C24: 12-636 | D24: PATIENT MONITORING EQUIP. PHILLIP GOLDWAY | E24: 24999 | F24: >10 | G24: 0.88 | H24: 0.99988296 | T24: =ROUNDUP((E24/4999.99)*10,-1) -> 50 | W24: N | X24: N | Y24: =IF(W24="Y",T24,0) -> 0 | Z24: =IF(X24="Y",T24*2,0) -> 0 | AA24: =Y24+Z24 -> 0
A25: =A24+1 -> 7 | B25: HOAG 10035 | C25: 16-495 | D25: INFUSION PUMP | E25: 3850 | F25: >10 | G25: 0.88 | H25: 0.99988296 | T25: =ROUNDUP((E25/4999.99)*10,-1) -> 10 | W25: N | X25: N | Y25: =IF(W25="Y",T25,0) -> 0 | Z25: =IF(X25="Y",T25*2,0) -> 0 | AA25: =Y25+Z25 -> 0
A26: =A25+1 -> 8 | B26: HOAG 10034 | C26: 16-495 | D26: INFUSION PUMP | E26: 3850 | F26: >10 | G26: 0.88 | H26: 0.99988296 | T26: =ROUNDUP((E26/4999.99)*10,-1) -> 10 | W26: N | X26: N | Y26: =IF(W26="Y",T26,0) -> 0 | Z26: =IF(X26="Y",T26*2,0) -> 0 | AA26: =Y26+Z26 -> 0
A27: =A26+1 -> 9 | B27: HOAG 10108 | C27: 11-165 | D27: DENTAL DELIVERY UNIT | E27: 49950 | F27: >10 | G27: 0.85 | H27: 0.99086538 | I27: 0.9779 | J27: 0.97644231 | T27: =ROUNDUP((E27/4999.99)*10,-1) -> 100 | W27: N | X27: N | Y27: =IF(W27="Y",T27,0) -> 0 | Z27: =IF(X27="Y",T27*2,0) -> 0 | AA27: =Y27+Z27 -> 0
A28: =A27+1 -> 10 | B28: HOAG 10373 | C28: 13-217 | D28: INFUSION PUMP | E28: 1400 | F28: < 5YRS | G28: 0.99 | H28: 0.99964888 | T28: =ROUNDUP((E28/4999.99)*10,-1) -> 10 | W28: N | X28: N | Y28: =IF(W28="Y",T28,0) -> 0 | Z28: =IF(X28="Y",T28*2,0) -> 0 | AA28: =Y28+Z28 -> 0
A29: =A28+1 -> 11 | B29: HOAG 10137 | C29: 15-612 | D29: WATER DISTILLER | E29: 7000 | F29: >10 | G29: 0.85 | I29: 0.99711538 | T29: =ROUNDUP((E29/4999.99)*10,-1) -> 20 | W29: N | X29: N | Y29: =IF(W29="Y",T29,0) -> 0 | Z29: =IF(X29="Y",T29*2,0) -> 0 | AA29: =Y29+Z29 -> 0
A30: =A29+1 -> 12 | B30: HOAG 10345 | C30: 12-815 | D30: OPTHALMOSCOPE | E30: 1350 | F30: >10 | G30: 0.85 | I30: 0.99471154 | T30: =ROUNDUP((E30/4999.99)*10,-1) -> 10 | W30: N | X30: N | Y30: =IF(W30="Y",T30,0) -> 0 | Z30: =IF(X30="Y",T30*2,0) -> 0 | AA30: =Y30+Z30 -> 0
A31: =A30+1 -> 13 | B31: HOAG 10217 | C31: 11-134 | D31: DEFIBRILLATOR | E31: 12490 | F31: >10 | G31: 0.88 | I31: 0.99988296 | T31: =ROUNDUP((E31/4999.99)*10,-1) -> 30 | W31: N | X31: N | Y31: =IF(W31="Y",T31,0) -> 0 | Z31: =IF(X31="Y",T31*2,0) -> 0 | AA31: =Y31+Z31 -> 0
A32: =A31+1 -> 14 | B32: HOAG 10277 | C32: 11-134 | D32: DEFIBRILLATOR | E32: 12490 | F32: >10 | G32: 0.88 | I32: 0.99988296 | T32: =ROUNDUP((E32/4999.99)*10,-1) -> 30 | W32: N | X32: N | Y32: =IF(W32="Y",T32,0) -> 0 | Z32: =IF(X32="Y",T32*2,0) -> 0 | AA32: =Y32+Z32 -> 0
A33: =A32+1 -> 15 | B33: HOAG 10132 | C33: 11-165 | D33: DENTAL DELIVERY UNIT | E33: 49500 | F33: >10 | G33: 0.85 | I33: 0.99711538 | J33: 0.98221154 | T33: =ROUNDUP((E33/4999.99)*10,-1) -> 100 | W33: N | X33: N | Y33: =IF(W33="Y",T33,0) -> 0 | Z33: =IF(X33="Y",T33*2,0) -> 0 | AA33: =Y33+Z33 -> 0
B34: HOAG 10125 | C34: 20-000 | D34: PORTABLE CUTTING UNIT | E34: 29500 | F34: >10 | G34: 0.85 | J34: 0.99471154 | T34: =ROUNDUP((E34/4999.99)*10,-1) -> 60 | W34: N | X34: N | Y34: =IF(W34="Y",T34,0) -> 0 | Z34: =IF(X34="Y",T34*2,0) -> 0 | AA34: =Y34+Z34 -> 0
B35: HOAG 10187 | C35: 16-241 | D35: ULTRASOUND SCANNER | E35: 40000 | F35: 5-10 YRS | G35: 0.92 | J35: 0.99871255 | T35: =ROUNDUP((E35/4999.99)*10,-1) -> 90 | W35: N | X35: N | Y35: =IF(W35="Y",T35,0) -> 0 | Z35: =IF(X35="Y",T35*2,0) -> 0 | AA35: =Y35+Z35 -> 0
B36: HOAG 10420 | C36: 11-134 | D36: DEFIBRILLATOR | E36: 75015.73 | F36: < 5YRS | G36: 0.99 | J36: 0.99988296 | T36: =ROUNDUP((E36/4999.99)*10,-1) -> 160 | W36: N | X36: N | Y36: =IF(W36="Y",T36,0) -> 0 | Z36: =IF(X36="Y",T36*2,0) -> 0
A37: TOTAL DEDUCTION FOR IND. B.4: | AA37: =SUM(AA19:AA36) -> 0
A39: 24 | B39: 55 | C39: =B39*A39 -> 1320 | D39: 8760 | E39: =(8760-C39)/D39 -> 0.84931507 | P39: 90 | Q39: 8760 | R39: =8760-P39 -> 8670

Sheet B5-T&C
A1: MINISTRY OF HEALTH
A2: Deduction Mapping Report Biomedical Engineering Maintenance Services (BEMS)
A3: INDICATOR B.5 TESTING & COMMISSIONING AND WARRANTY MANAGEMENT
B5: HOSPITAL NAME : | C5: HOSPITAL ORANG ASLI GOMBAK | I5: MONTH/YEAR : | K5: =BEMSdar!E7 -> 46082
B7: STATE : | C7: WILAYAH PERSEKUTUAN KUALA LUMPUR | I7: BEMS MONTHLY FEE (RM) @ 97.5 % : | K7: =BEMSdar!$E$11 -> 17318.155
B9: COMPANY : | C9: AMBANG WIRA SDN BHD | I9: FMS MONTHLY FEE (RM) @ 2.5% : | K9: =BEMSdar!$E$13 -> 444.05525
A11: Notes:
A12: 1) Deduction Ringgit Equivalent is based on Appendix 11 of the Agreement, Section B3 Key Deduction Indicators for BEMS
A13: 2) Deduction Value is Deduction Ringgit Equivalent (per event)
A14: 3) Display only asset affected by deduction
A15: 4) *May not be applicable for unregistered asset
A16: 5) **Only applicable for under warranty management deduction
A18: No | B18: Work Order/ NCR | C18: Work Order/ NCR Date | D18: Work Order/ NCR Reference No. | E18: Work Order/ NCR Description | F18: User Location | G18: T&C Date | H18: Completion Date | I18: Asset Number* | J18: Asset Description | K18: Warranty Expiry Date** | L18: Asset Purchase Price (RM) | M18: Deduction Ringgit Equivalent (RM) | N18: Validate Status (Y/N) | O18: Deduction Value (RM) | P18: Remarks
A19: Work Order Close
A20: 1 | B20: NA | C20: NA | D20: NA | E20: NA | F20: NA | G20: NA | H20: NA | I20: NA | J20: NA | K20: NA | L20: NA | M20: - | N20: N | O20: - | P20: NA
A21: Work Order Open
A22: 1 | B22: NA | C22: NA | D22: NA | E22: NA | F22: NA | G22: NA | H22: NA | I22: NA | J22: NA | K22: NA | L22: NA | M22: - | N22: N | O22: - | P22: NA
A23: TOTAL DEDUCTION FOR IND. B.5: | O23: 0

Sheet Sheet1
A3: Equipments | B3: Group | C3: Operating Hours | D3: Operating Hours/WK (Days) | E3: Uptime Equipment | F3: Uptime Equipment | G3: Uptime Equipment
E4: < 5YRS | F4: 5-10 YRS | G4: >10 YRS
A5: Therapeutics
A6: Alternating Pressure Mattress | B6: P | C6: 12 | D6: 6 | E6: 0.96 | F6: 0.92 | G6: 0.85
A7: Aneasthesia Units and Vaporizers | B7: C | C7: 24 | D7: 7 | E7: 0.99 | F7: 0.95 | G7: 0.88
A8: Aneasthesia Ventilators | B8: C | C8: 24 | D8: 7 | E8: 0.99 | F8: 0.95 | G8: 0.88
A9: Aspirators | B9: C | C9: 24 | D9: 7 | E9: 0.99 | F9: 0.95 | G9: 0.88
A10: Defibrillators | B10: C | C10: 24 | D10: 7 | E10: 0.99 | F10: 0.95 | G10: 0.88
A11: Dental Equipment | B11: P | C11: 24 | D11: 7 | E11: 0.96 | F11: 0.92 | G11: 0.85
A12: Diathermy Units | B12: C | C12: 24 | D12: 7 | E12: 0.99 | F12: 0.95 | G12: 0.88
A13: Electrosurgical Units | B13: C | C13: 24 | D13: 7 | E13: 0.99 | F13: 0.95 | G13: 0.88
A14: Heamodialysis Units | B14: C | C14: 24 | D14: 7 | E14: 0.99 | F14: 0.95 | G14: 0.88
A15: Humidifiers | B15: C | C15: 24 | D15: 7 | E15: 0.99 | F15: 0.95 | G15: 0.88
A16: Hypo/hyperthermia Units | B16: C | C16: 24 | D16: 7 | E16: 0.99 | F16: 0.95 | G16: 0.88
A17: Incubators | B17: C | C17: 24 | D17: 7 | E17: 0.99 | F17: 0.95 | G17: 0.88
... A59: Vector Cardiographs | B59: P | C59: 12 | D59: 6 | E59: 0.96 | F59: 0.92 | G59: 0.85
A60: Analysers
A61: · Amino Acid | B61: P | C61: 12 | D61: 6 | E61: 0.96 | F61: 0.92 | G61: 0.85
A62: · Bilirubinometers | B62: P | C62: 12 | D62: 6 | E62: 0.96 | F62: 0.92 | G62: 0.85
A63: · Blood Gas | B63: P | C63: 12 | D63: 6 | E63: 0.96 | F63: 0.92 | G63: 0.85
A64: · Calcium | B64: P | C64: 12 | D64: 6 | E64: 0.96 | F64: 0.92 | G64: 0.85
A65: · Clinical Chemistry | B65: P | C65: 12 | D65: 6 | E65: 0.96 | F65: 0.92 | G65: 0.85
A66: · Coagulation | B66: P | C66: 12 | D66: 6 | E66: 0.96 | F66: 0.92 | G66: 0.85
A67: · Counter, Gamma | B67: P | C67: 12 | D67: 6 | E67: 0.96 | F67: 0.92 | G67: 0.85
A68: · Electrolyte | B68: P | C68: 12 | D68: 6 | E68: 0.96 | F68: 0.92 | G68: 0.85
A69: · Immunoassay | B69: P | C69: 12 | D69: 6 | E69: 0.96 | F69: 0.92 | G69: 0.85
A70: · Glucose | B70: P | C70: 12 | D70: 6 | E70: 0.96 | F70: 0.92 | G70: 0.85
A71: · Hematology | B71: P | C71: 12 | D71: 6 | E71: 0.96 | F71: 0.92 | G71: 0.85
A72: · Platelet Aggregation | B72: P | C72: 12 | D72: 6 | E72: 0.96 | F72: 0.92 | G72: 0.85
... A84: Spectrophotometers | B84: P | C84: 12 | D84: 6 | E84: 0.96 | F84: 0.92 | G84: 0.85

Sheet Sheet2
A4: No | B4: Asset No | C4: Asset Description | D4: Asset Purchase Price (RM) | E4: Work Order No. | G4: User Location | H4: Work Order/ Complaint Details | I4: Response Category (Emergency/ Normal) | J4: Total Response Time (minutes) | K4: Work Request Date | L4: Work Completion Date | M4: Deduction Ringgit Equivalent (RM) | N4: Indicator B.1 | Q4: Indicator B.2 | W4: Contract
F5: wo | N5: Validate Status (Y/N) | O5: Deduction Value (RM) | P5: Remarks/ Exemption | Q5: Validate Status (Y/N) | R5: Total Repair Time (day) | S5: Last date of 7 working days (dd/mm/yy) | T5: Demerit Point | U5: Deduction Value (RM) | V5: Remarks/ Exemption | X5: Total Repair Time (day) | Y5: Hours | Z5: Total Hours | AA5: Total Hours / Year | AB5: Balance Uptime | AC5: Uptime Percentage | AD5: Uptime TRKPI | AE5: Uptime Deduction Yes / No
A6: 23 | B6: IKN400966 | C6: LINEAR ACCELERATOR | D6: 12049370 | E6: 1811 | G6: RT159 | H6: Lazer Double | I6: Normal | J6: 0.010416667 | K6: 43781 | L6: 43795 | M6: =IF(D6>44999.99,100,ROUNDUP((D6/4999.99)*10,-1)) -> 100 | N6: N | O6: =IF(N6="Y",M6,0) -> 0 | P6: Response On_Time | Q6: N | R6: =L6-K6+1 -> 15 | S6: =WORKDAY(K6,6,tarikhcuti) -> 43789 | T6: =IF(L6>S6,L6-S6,0) -> 6 | U6: =M6*T6 -> 600 | W6: Strands | X6: =R6 -> 15 | Y6: 24 | Z6: =X6*Y6 -> 360 | AA6: 8072 | AB6: =AA6-Z6 -> 7712 | AC6: =AB6/8072 -> 0.95540139 | AD6: 0.92 | AE6: No
A7: 1 | B7: IKN400292 | C7: Infusion Pumps, General-Purpose | D7: 10825 | E7: 1655 | G7: WAD 8A | H7: Infucient Pump-Mesin Problem | I7: Normal | J7: 0.025694444 | K7: 43774 | L7: 43799 | M7: =IF(D7>44999.99,100,ROUNDUP((D7/4999.99)*10,-1)) -> 30 | N7: N | O7: =IF(N7="Y",M7,0) -> 0 | P7: Response On_Time | Q7: Y | R7: =L7-K7+1 -> 26 | S7: =WORKDAY(K7,6,tarikhcuti) -> 43782 | T7: =IF(L7>S7,L7-S7,0) -> 17 | U7: =M7*T7 -> 510 | W7: Strands | X7: =R7 -> 26 | Y7: 24 | Z7: =X7*Y7 -> 624 | AA7: 8072 | AB7: =AA7-Z7 -> 7448 | AC7: =AB7/8072 -> 0.92269574 | AD7: 0.95 | AE7: Yes
A8: =A7+1 -> 2 | B8: IKN400978 | C8: Scanning Systems, Computed Tomography | D8: 3557530 | E8: 1172 | G8: RT | H8: sendingg image from vsim to mosaiq | I8: Normal | J8: 0.020833333 | K8: 43770 | L8: 43782 | M8: =IF(D8>44999.99,100,ROUNDUP((D8/4999.99)*10,-1)) -> 100 | N8: N | O8: =IF(N8="Y",M8,0) -> 0 | P8: Response On_Time | Q8: N | R8: =L8-K8+1 -> 13 | S8: 43763 | T8: =R8 -> 13 | U8: =M8*T8 -> 1300 | W8: Strands | X8: =R8 -> 13 | Y8: 24 | Z8: =X8*Y8 -> 312 | AA8: 8072 | AB8: =AA8-Z8 -> 7760 | AC8: =AB8/8072 -> 0.96134787 | AD8: 0.95 | AE8: No
A9: =A8+1 -> 3 | B9: IKN400973 | C9: Scanning Systems, Computed Tomography | D9: 3557530 | E9: 1173 | G9: RT | H9: sendingg image from vsim to mosaiq | I9: Normal | J9: 0.013888889 | K9: 43770 | L9: 43782 | M9: =IF(D9>44999.99,100,ROUNDUP((D9/4999.99)*10,-1)) -> 100 | N9: N | O9: =IF(N9="Y",M9,0) -> 0 | P9: Response On_Time | Q9: N | R9: =L9-K9+1 -> 13 | S9: 43763 | T9: =R9 -> 13 | U9: =M9*T9 -> 1300 | W9: Strands | X9: =R9 -> 13 | Y9: 24 | Z9: =X9*Y9 -> 312 | AA9: 8072 | AB9: =AA9-Z9 -> 7760 | AC9: =AB9/8072 -> 0.96134787 | AD9: 0.95 | AE9: No
A10: =A9+1 -> 4 | B10: IKN400151 | C10: Mattress Systems, Alternating-Pressure | D10: 28630 | E10: 1449 | G10: WAD 7A | H10: Motor ripple mattress rosak | I10: Normal | J10: 0.027777778 | K10: 43770 | L10: 43775 | M10: =IF(D10>44999.99,100,ROUNDUP((D10/4999.99)*10,-1)) -> 60 | N10: N | O10: =IF(N10="Y",M10,0) -> 0 | P10: Response On_Time | Q10: N | R10: =L10-K10+1 -> 6 | S10: 43774 | T10: =R10 -> 6 | U10: =M10*T10 -> 360 | W10: Strands | X10: =R10 -> 6 | Y10: 24 | Z10: =X10*Y10 -> 144 | AA10: 8072 | AB10: =AA10-Z10 -> 7928 | AC10: =AB10/8072 -> 0.98216056 | AD10: 0.92 | AE10: No
A11: =A10+1 -> 5 | B11: IKN400967 | C11: Linear Accelerators | D11: 12049370 | E11: 1471 | G11: RT | H11: Table verticle movement problem | I11: Normal | J11: 0.065972222 | K11: 43770 | L11: 43773 | M11: =IF(D11>44999.99,100,ROUNDUP((D11/4999.99)*10,-1)) -> 100 | N11: N | O11: =IF(N11="Y",M11,0) -> 0 | P11: Response On_Time | Q11: N | R11: =L11-K11+1 -> 4 | S11: 43775 | T11: =R11 -> 4 | U11: =M11*T11 -> 400 | W11: Strands | X11: =R11 -> 4 | Y11: 24 | Z11: =X11*Y11 -> 96 | AA11: 8072 | AB11: =AA11-Z11 -> 7976 | AC11: =AB11/8072 -> 0.98810704 | AD11: 0.92 | AE11: No
A12: =A11+1 -> 6 | B12: NB 355296 | C12: Mattress Systems, Alternating-Pressure | D12: 28630 | E12: 1476 | G12: WAD 7B | H12: Ripple Mattress tidak boleh pump | I12: Normal | J12: 0.023611111 | K12: 43770 | L12: 43775 | M12: =IF(D12>44999.99,100,ROUNDUP((D12/4999.99)*10,-1)) -> 60 | N12: N | O12: =IF(N12="Y",M12,0) -> 0 | P12: Response On_Time | Q12: N | R12: =L12-K12+1 -> 6 | S12: 43775 | T12: =R12 -> 6 | U12: =M12*T12 -> 360 | W12: #N/A | X12: =R12 -> 6 | Y12: 24 | Z12: =X12*Y12 -> 144 | AA12: 8072 | AB12: =AA12-Z12 -> 7928 | AC12: =AB12/8072 -> 0.98216056 | AD12: 0.92 | AE12: No
A13: =A12+1 -> 7 | B13: IKN400350 | C13: Sphygmomanometers, Electronic, Automatic | D13: 4510 | E13: 1496 | G13: WAD 7B | H13: BP Set warna putih rosak. | I13: Normal | J13: 0.010416667 | K13: 43770 | L13: 43775 | M13: =IF(D13>44999.99,100,ROUNDUP((D13/4999.99)*10,-1)) -> 10 | N13: N | O13: =IF(N13="Y",M13,0) -> 0 | P13: Response On_Time | Q13: N | R13: =L13-K13+1 -> 6 | S13: 43775 | T13: =R13 -> 6 | U13: =M13*T13 -> 60 | W13: Strands | X13: =R13 -> 6 | Y13: 24 | Z13: =X13*Y13 -> 144 | AA13: 8072 | AB13: =AA13-Z13 -> 7928 | AC13: =AB13/8072 -> 0.98216056 | AD13: 0.92 | AE13: No
A14: =A13+1 -> 8 | B14: IKN400775 | C14: Scanning Systems, Ultrasonic, General-Purpose | D14: 1044560 | E14: 1535 | G14: ID | H14: Ultrasound tidak keluar gambar | I14: Normal | J14: 0.017361111 | K14: 43770 | L14: 43773 | M14: =IF(D14>44999.99,100,ROUNDUP((D14/4999.99)*10,-1)) -> 100 | N14: N | O14: =IF(N14="Y",M14,0) -> 0 | P14: Response On_Time | Q14: N | R14: =L14-K14+1 -> 4 | S14: 43776 | T14: =R14 -> 4 | U14: =M14*T14 -> 400 | W14: Strands | X14: =R14 -> 4 | Y14: 24 | Z14: =X14*Y14 -> 96 | AA14: 8072 | AB14: =AA14-Z14 -> 7976 | AC14: =AB14/8072 -> 0.98810704 | AD14: 0.95 | AE14: No
A15: =A14+1 -> 9 | B15: IKN400567 | C15: Cameras, Gamma | D15: 3191750 | E15: 1550 | G15: NM | H15: MEGP detector one collision | I15: Normal | J15: 0.0034722222 | K15: 43770 | L15: 43773 | M15: =IF(D15>44999.99,100,ROUNDUP((D15/4999.99)*10,-1)) -> 100 | N15: N | O15: =IF(N15="Y",M15,0) -> 0 | P15: Response On_Time | Q15: N | R15: =L15-K15+1 -> 4 | S15: 43777 | T15: =R15 -> 4 | U15: =M15*T15 -> 400 | W15: Strands | X15: =R15 -> 4 | Y15: 24 | Z15: =X15*Y15 -> 96 | AA15: 8072 | AB15: =AA15-Z15 -> 7976 | AC15: =AB15/8072 -> 0.98810704 | AD15: 0.92 | AE15: No
A16: =A15+1 -> 10 | B16: IKN400786 | C16: Radiographic/Fluoroscopic Systems, Angiographic/Intervention | D16: 3191750 | E16: 1565 | G16: ID | H16: Request for user training at Radiology Department (Angio) on 23/10/2019. | I16: Normal | J16: 0 | K16: 43770 | L16: 43773 | M16: =IF(D16>44999.99,100,ROUNDUP((D16/4999.99)*10,-1)) -> 100 | N16: N | O16: =IF(N16="Y",M16,0) -> 0 | P16: Response On_Time | Q16: N | R16: =L16-K16+1 -> 4 | S16: 43777 | T16: =R16 -> 4 | U16: =M16*T16 -> 400 | W16: Strands | X16: =R16 -> 4 | Y16: 24 | Z16: =X16*Y16 -> 96 | AA16: 8072 | AB16: =AA16-Z16 -> 7976 | AC16: =AB16/8072 -> 0.98810704 | AD16: 0.92 | AE16: No
U17: =SUM(U6:U16) -> 6090
