Workbook
Name _05_04_2009: #REF!
Name _05_04_2009: #REF!
Name _05_04_2009: #REF!
Name _05_04_2009: #REF!
Name _05_04_2009: #REF!
Name AA: #REF!
Name AA: #REF!
Name AA: #REF!
Name AA: #REF!
Name AA: #REF!
Name aaa: #REF!
Name aaa: #REF!
Name aaa: #REF!
Name aaa: #REF!
Name aaa: #REF!
Name aaaaa: #REF!
Name aaaaa: #REF!
Name aaaaa: #REF!
Name aaaaa: #REF!
Name aaaaa: #REF!
Name aaaaaaaaaa: #REF!
Name aaaaaaaaaa: #REF!
Name aaaaaaaaaa: #REF!
Name aaaaaaaaaa: #REF!
Name aaaaaaaaaa: #REF!
Name AAAAAAAAAAAAA: #REF!
Name AAAAAAAAAAAAA: #REF!
Name AAAAAAAAAAAAA: #REF!
Name AAAAAAAAAAAAA: #REF!
Name AAAAAAAAAAAAA: #REF!
Name AAAAAAAAAAAAAAAAAA: #REF!
Name AAAAAAAAAAAAAAAAAA: #REF!
Name AAAAAAAAAAAAAAAAAA: #REF!
Name AAAAAAAAAAAAAAAAAA: #REF!
Name AAAAAAAAAAAAAAAAAA: #REF!
Name AAAAAAAAAAAAAAAAAAAAA: #REF!
Name AAAAAAAAAAAAAAAAAAAAA: #REF!
Name AAAAAAAAAAAAAAAAAAAAA: #REF!
Name AAAAAAAAAAAAAAAAAAAAA: #REF!
Name AAAAAAAAAAAAAAAAAAAAA: #REF!
Name AAAAAAAAAAAAAAAAAAAAAAAAAAA: #REF!
Name AAAAAAAAAAAAAAAAAAAAAAAAAAA: #REF!
Name AAAAAAAAAAAAAAAAAAAAAAAAAAA: #REF!
Name AAAAAAAAAAAAAAAAAAAAAAAAAAA: #REF!
Name AAAAAAAAAAAAAAAAAAAAAAAAAAA: #REF!
Name AAAAAAAAAAAAAAAAAAAAAAAAAAAA: #REF!
Name AAAAAAAAAAAAAAAAAAAAAAAAAAAA: #REF!
Name AAAAAAAAAAAAAAAAAAAAAAAAAAAA: #REF!
Name AAAAAAAAAAAAAAAAAAAAAAAAAAAA: #REF!
Name AAAAAAAAAAAAAAAAAAAAAAAAAAAA: #REF!
Name AAAAAAAAAAAAAAAAAAAAAAAAAAAAAA: #REF!
Name AAAAAAAAAAAAAAAAAAAAAAAAAAAAAA: #REF!
Name AAAAAAAAAAAAAAAAAAAAAAAAAAAAAA: #REF!
Name AAAAAAAAAAAAAAAAAAAAAAAAAAAAAA: #REF!
Name AAAAAAAAAAAAAAAAAAAAAAAAAAAAAA: #REF!
Name AAAAAAAAAAAAAAAAAAAAAAAAAAAAAAA: #REF!
Name AAAAAAAAAAAAAAAAAAAAAAAAAAAAAAA: #REF!
Name AAAAAAAAAAAAAAAAAAAAAAAAAAAAAAA: #REF!
Name AAAAAAAAAAAAAAAAAAAAAAAAAAAAAAA: #REF!
Name AAAAAAAAAAAAAAAAAAAAAAAAAAAAAAA: #REF!

Sheet MASTERLIST ASSET
A1: APPROVED LIST MASTERLIST ASSET FOR HOSPITAL SHAH ALAM 2022
A3: No. | B3: Service | C3: Period Name | D3: Hospital | E3: Department | F3: User Area | G3: Description UMDNS | H3: Asset Description | I3: Equipment Group | J3: Equipment Group | K3: Asset Type Code | L3: Qty | M3: Asset No. | N3: Purchase Cost (RM) | O3: Total Purchase Cost (RM) | P3: Status | Q3: Date Start Service | R3: Warranty Expiry Date | S3: Date Stop Service
A4: 1 | B4: BEMS | C4: P0 | D4: Hospital Shah Alam, Selangor | E4: Jabatan Kecemasan & Trauma | F4: Jabatan Kecemasan & Trauma | G4: Compressors, Medical-Air | H4: COMPRESSOR AIR (DENTAL) | I4: Therapeutic | J4: Basic | K4: 10-972 | L4: 1 | M4: KKM/JKN/HSA/10-05-01/H/15/4893 | N4: 13000 | O4: =N4*L4 -> 13000 | Q4: 46023
A5: 2 | B5: BEMS | C5: P0 | D5: Hospital Shah Alam, Selangor | E5: Jabatan Kecemasan & Trauma | F5: Jabatan Kecemasan & Trauma | G5: Compressors, Medical-Air | H5: SUCTION UNIT (DENTAL) | I5: Therapeutic | J5: Basic | K5: 10-972 | L5: 1 | M5: KKM/JKN/HSA/10-05-01/H/15/466 | N5: 14000 | O5: =N5*L5 -> 14000 | Q5: 46023
A6: 3 | B6: BEMS | C6: P0 | D6: Hospital Shah Alam, Selangor | E6: Jabatan Bedah Mulut & Pergigian Pediatrik | F6: Klinik Bedah Mulut & Klinik Pergigian Pediatrik | G6: Compressors, Medical-Air | H6: CENTRAL COMPRESSOR (DENTAL) | I6: Therapeutic | J6: Basic | K6: 10-972 | L6: 1 | M6: KKM/JKN/HSA/10-05-01/H/15/4891 | N6: 78000 | O6: =N6*L6 -> 78000 | Q6: 46023
A7: 4 | B7: BEMS | C7: P0 | D7: Hospital Shah Alam, Selangor | E7: Jabatan Bedah Mulut & Pergigian Pediatrik | F7: Klinik Bedah Mulut & Klinik Pergigian Pediatrik | G7: Compressors, Medical-Air | H7: CENTRAL SUCTION (DENTAL) | I7: Therapeutic | J7: Basic | K7: 10-972 | L7: 1 | M7: KKM/JKN/HSA/10-05-01/H/15/4886 | N7: 65000 | O7: =N7*L7 -> 65000 | Q7: 46023
A8: 5 | B8: BEMS | C8: P0 | D8: Hospital Shah Alam, Selangor | E8: Jabatan Kecemasan & Trauma | F8: Jabatan Kecemasan & Trauma | G8: Chairs, Examination/Treatment, Dentistry | H8: DENTAL CHAIR, OFFICER | I8: Therapeutic | J8: Intermediate | K8: 10-792 | L8: 1 | M8: KKM/JKN/HSA/10-05-01/H/15/4892 | N8: 89700 | O8: =N8*L8 -> 89700 | Q8: 46023
A9: 6 | B9: BEMS | C9: P0 | D9: Hospital Shah Alam, Selangor | E9: Jabatan Bedah Mulut & Pergigian Pediatrik | F9: Klinik Bedah Mulut & Klinik Pergigian Pediatrik | G9: Chairs, Examination/Treatment, Dentistry | H9: DENTAL CHAIR, OFFICER | I9: Therapeutic | J9: Intermediate | K9: 10-792 | L9: 1 | M9: KKM/JKN/HSA/10-05-01/H/15/1118 | N9: 69000 | O9: =N9*L9 -> 69000 | Q9: 46023
A10: 7 | B10: BEMS | C10: P0 | D10: Hospital Shah Alam, Selangor | E10: Jabatan Bedah Mulut & Pergigian Pediatrik | F10: Klinik Bedah Mulut & Klinik Pergigian Pediatrik | G10: Chairs, Examination/Treatment, Dentistry | H10: DENTAL CHAIR, OFFICER | I10: Therapeutic | J10: Intermediate | K10: 10-792 | L10: 1 | M10: KKM/JKN/HSA/10-05-01/H/15/1119 | N10: 69000 | O10: =N10*L10 -> 69000 | Q10: 46023
A11: 8 | B11: BEMS | C11: P0 | D11: Hospital Shah Alam, Selangor | E11: Jabatan Bedah Mulut & Pergigian Pediatrik | F11: Klinik Bedah Mulut & Klinik Pergigian Pediatrik | G11: Chairs, Examination/Treatment, Dentistry | H11: DENTAL CHAIR, OFFICER | I11: Therapeutic | J11: Intermediate | K11: 10-792 | L11: 1 | M11: KKM/JKN/HSA/10-05-01/H/15/1120 | N11: 69000 | O11: =N11*L11 -> 69000 | Q11: 46023
A12: 9 | B12: BEMS | C12: P0 | D12: Hospital Shah Alam, Selangor | E12: Jabatan Bedah Mulut & Pergigian Pediatrik | F12: Klinik Bedah Mulut & Klinik Pergigian Pediatrik | G12: Chairs, Examination/Treatment, Dentistry | H12: DENTAL CHAIR, OFFICER | I12: Therapeutic | J12: Intermediate | K12: 10-792 | L12: 1 | M12: KKM/JKN/HSA/10-05-01/H/15/1121 | N12: 69000 | O12: =N12*L12 -> 69000 | Q12: 46023
A13: 10 | B13: BEMS | C13: P0 | D13: Hospital Shah Alam, Selangor | E13: Jabatan Bedah Mulut & Pergigian Pediatrik | F13: Klinik Bedah Mulut & Klinik Pergigian Pediatrik | G13: Chairs, Examination/Treatment, Dentistry | H13: DENTAL CHAIR, OFFICER | I13: Therapeutic | J13: Intermediate | K13: 10-792 | L13: 1 | M13: KKM/JKN/HSA/10-05-01/H/15/1122 | N13: 69000 | O13: =N13*L13 -> 69000 | Q13: 46023
A14: 11 | B14: BEMS | C14: P0 | D14: Hospital Shah Alam, Selangor | E14: Jabatan Bedah Mulut & Pergigian Pediatrik | F14: Klinik Bedah Mulut & Klinik Pergigian Pediatrik | G14: Chairs, Examination/Treatment, Dentistry | H14: DENTAL CHAIR, OFFICER | I14: Therapeutic | J14: Intermediate | K14: 10-792 | L14: 1 | M14: KKM/JKN/HSA/10-05-01/H/15/1123 | N14: 69000 | O14: =N14*L14 -> 69000 | Q14: 46023
A15: 12 | B15: BEMS | C15: P0 | D15: Hospital Shah Alam, Selangor | E15: Jabatan Bedah Mulut & Pergigian Pediatrik | F15: Klinik Bedah Mulut & Klinik Pergigian Pediatrik | G15: Chairs, Examination/Treatment, Dentistry | H15: DENTAL CHAIR, OFFICER | I15: Therapeutic | J15: Intermediate | K15: 10-792 | L15: 1 | M15: KKM/JKN/HSA/10-05-01/H/15/1124 | N15: 69000 | O15: =N15*L15 -> 69000 | Q15: 46023
... A67: 64 | B67: BEMS | C67: P0 | D67: Hospital Shah Alam, Selangor | E67: Jabatan Bedah Mulut & Pergigian Pediatrik | F67: Klinik Bedah Mulut & Klinik Pergigian Pediatrik | G67: Handpieces, Dental | H67: DENTAL HANDPIECE | I67: Therapeutic | J67: Intermediate | K67: 11-161 | L67: 1 | M67: KKM/JKN/HSA/10-05-01/H/18/144 | N67: 10000 | O67: =N67*L67 -> 10000 | Q67: 46023
A68: 65 | B68: BEMS | C68: P0 | D68: Hospital Shah Alam, Selangor | E68: Jabatan Otorinolaringologi (ORL) | G68: Light Sources, Fiberoptic, Flexible Endoscopic | H68: LIGHT SOURCE FIBEROPTIC COMPACT | I68: Diagnostic | J68: Basic | K68: 12-343 | L68: 1 | M68: KKM/JKN/HSA/10-01-01/R/15/7575 | N68: 1320 | O68: =N68*L68 -> 1320 | Q68: 46023
A69: 66 | B69: BEMS | C69: P0 | D69: Hospital Shah Alam, Selangor | E69: Jabatan Pembedahan Am | F69: Unit Rawatan Perubatan Harian | G69: Light Sources, Fiberoptic, Flexible Endoscopic | H69: LIGHT SOURCE XENON 300 WATTS | I69: Diagnostic | J69: Basic | K69: 12-343 | L69: 1 | M69: KKM/JKN/HSA/10-01-01/H/15/1327 | N69: 24700 | O69: =N69*L69 -> 24700 | Q69: 46023
A70: 67 | B70: BEMS | C70: P0 | D70: Hospital Shah Alam, Selangor | E70: Jabatan Pembedahan Am | F70: Unit Rawatan Perubatan Harian | G70: Light Sources, Fiberoptic, Flexible Endoscopic | H70: LIGHT SOURCE XENON 300 WATTS | I70: Diagnostic | J70: Basic | K70: 12-343 | L70: 1 | M70: KKM/JKN/HSA/10-01-01/H/15/1328 | N70: 24700 | O70: =N70*L70 -> 24700 | Q70: 46023
A71: 68 | B71: BEMS | C71: P0 | D71: Hospital Shah Alam, Selangor | E71: Jabatan Pembedahan Am | F71: Unit Rawatan Perubatan Harian | G71: Light Sources, Fiberoptic, Flexible Endoscopic | H71: LIGHT SOURCE XENON 300 WATTS | I71: Diagnostic | J71: Basic | K71: 12-343 | L71: 1 | M71: KKM/JKN/HSA/10-01-01/H/15/1329 | N71: 24700 | O71: =N71*L71 -> 24700 | Q71: 46023
A72: 69 | B72: BEMS | C72: P0 | D72: Hospital Shah Alam, Selangor | E72: Jabatan Pembedahan Am | F72: Unit Rawatan Perubatan Harian | G72: Lavange Unit, Surgical | H72: ENDOSCOPIC FLUSHING PUMP | I72: Therapeutic | J72: Intermediate | K72: 12-306 | L72: 1 | M72: KKM/JKN/HSA/10-01-01/H/15/4083 | N72: 2430 | O72: =N72*L72 -> 2430 | Q72: 46023
A73: 70 | B73: BEMS | C73: P0 | D73: Hospital Shah Alam, Selangor | E73: Jabatan Pembedahan Am | F73: Unit Rawatan Perubatan Harian | G73: Lavange Unit, Surgical | H73: ENDOSCOPIC FLUSHING PUMP | I73: Therapeutic | J73: Intermediate | K73: 12.306 | L73: 1 | M73: KKM/JKN/HSA/10-01-01/H/15/4084 | N73: 2430 | O73: =N73*L73 -> 2430 | Q73: 46023
A74: 71 | B74: BEMS | C74: P0 | D74: Hospital Shah Alam, Selangor | E74: Jabatan Pembedahan Am | F74: Unit Rawatan Perubatan Harian | G74: Lavange Unit, Surgical | H74: ENDOSCOPIC FLUSHING PUMP | I74: Therapeutic | J74: Intermediate | K74: 12-306 | L74: 1 | M74: KKM/JKN/HSA/10-01-01/H/15/4085 | N74: 2430 | O74: =N74*L74 -> 2430 | Q74: 46023
A75: 72 | B75: BEMS | C75: P0 | D75: Hospital Shah Alam, Selangor | E75: Jabatan Anestesiologi & Rawatan Kritikal | F75: Dewan Bedah Utama (GOT) | G75: Light Sources, Fiberoptic, Flexible Endoscopic | H75: LIGHT SOURCE XENON 300 WATTS | I75: Diagnostic | J75: Basic | K75: 12-343 | L75: 1 | M75: KKM/JKN/HSA/10-01-01/H/15/1330 | N75: 24700 | O75: =N75*L75 -> 24700 | Q75: 46023
A76: 73 | B76: BEMS | C76: P0 | D76: Hospital Shah Alam, Selangor | E76: Jabatan Anestesiologi & Rawatan Kritikal | F76: Dewan Bedah Utama (GOT) | G76: Light Sources, Fiberoptic, Flexible Endoscopic | H76: LIGHT SOURCE XENON 300 WATTS | I76: Diagnostic | J76: Basic | K76: 12-343 | L76: 1 | M76: KKM/JKN/HSA/10-01-01/H/15/1331 | N76: 24700 | O76: =N76*L76 -> 24700 | Q76: 46023
A77: 74 | B77: BEMS | C77: P0 | D77: Hospital Shah Alam, Selangor | E77: Jabatan Anestesiologi & Rawatan Kritikal | F77: Dewan Bedah Utama (GOT) | G77: Light Sources, Fiberoptic, Flexible Endoscopic | H77: LIGHT SOURCE XENON 300 WATTS | I77: Diagnostic | J77: Basic | K77: 12-343 | L77: 1 | M77: KKM/JKN/HSA/10-01-01/H/15/1332 | N77: 24700 | O77: =N77*L77 -> 24700 | Q77: 46023
A78: 75 | B78: BEMS | C78: P0 | D78: Hospital Shah Alam, Selangor | E78: Jabatan Anestesiologi & Rawatan Kritikal | F78: Dewan Bedah Utama (GOT) | G78: Light Sources, Fiberoptic | H78: LIGHT GUIDE 3.5MM | I78: Diagnostic | J78: Basic | K78: 12-345 | L78: 1 | M78: KKM/JKN/HSA/10-05-01/R/15/6818 | N78: 1930 | O78: =N78*L78 -> 1930 | Q78: 46023
A79: 76 | B79: BEMS | C79: P0 | D79: Hospital Shah Alam, Selangor | E79: Jabatan Anestesiologi & Rawatan Kritikal | F79: Dewan Bedah Utama (GOT) | G79: Light Sources, Fiberoptic | H79: LIGHT GUIDE 3.5MM | I79: Diagnostic | J79: Basic | K79: 12-345 | L79: 1 | M79: KKM/JKN/HSA/10-05-01/R/15/6819 | N79: 1930 | O79: =N79*L79 -> 1930 | Q79: 46023
A80: 77 | B80: BEMS | C80: P0 | D80: Hospital Shah Alam, Selangor | E80: Jabatan Anestesiologi & Rawatan Kritikal | F80: Dewan Bedah Utama (GOT) | G80: Light Sources, Fiberoptic | H80: LIGHT GUIDE 3.5MM | I80: Diagnostic | J80: Basic | K80: 12-345 | L80: 1 | M80: KKM/JKN/HSA/10-05-01/R/15/6821 | N80: 1930 | O80: =N80*L80 -> 1930 | Q80: 46023
A81: 78 | B81: BEMS | C81: P0 | D81: Hospital Shah Alam, Selangor | E81: Jabatan Pembedahan Am | F81: Unit Rawatan Perubatan Harian | G81: Printers, Video | H81: VIDEO PRINTER | I81: Diagnostic | J81: Basic | K81: 17-508 | L81: 1 | M81: KKM/JKN/HSA/10-05-01/H/15/4086 | N81: 4870 | O81: =N81*L81 -> 4870 | Q81: 46023
A82: 79 | B82: BEMS | C82: P0 | D82: Hospital Shah Alam, Selangor | E82: Jabatan Pembedahan Am | F82: Unit Rawatan Perubatan Harian | G82: Printers, Video | H82: VIDEO PRINTER | I82: Diagnostic | J82: Basic | K82: 17-508 | L82: 1 | M82: KKM/JKN/HSA/10-05-01/H/15/4087 | N82: 4870 | O82: =N82*L82 -> 4870 | Q82: 46023
A83: 80 | B83: BEMS | C83: P0 | D83: Hospital Shah Alam, Selangor | E83: Jabatan Pembedahan Am | F83: Unit Rawatan Perubatan Harian | G83: Printers, Video | H83: VIDEO PRINTER | I83: Diagnostic | J83: Basic | K83: 17-508 | L83: 1 | M83: KKM/JKN/HSA/10-05-01/H/15/4088 | N83: 4870 | O83: =N83*L83 -> 4870 | Q83: 46023
A84: 81 | B84: BEMS | C84: P0 | D84: Hospital Shah Alam, Selangor | E84: Jabatan Kecemasan & Trauma | F84: Jabatan Kecemasan & Trauma | G84: Cast Cutters, Electric | H84: SAW PLASTER ELECTRIC C/W VACUUM | I84: Therapeutic | J84: Basic | K84: 16-340 | L84: 1 | M84: KKM/JKN/HSA/10-05-01/H/15/2826 | N84: 8500 | O84: =N84*L84 -> 8500 | Q84: 46023
A85: 82 | B85: BEMS | C85: P0 | D85: Hospital Shah Alam, Selangor | E85: Jabatan Ortopedik | F85: Wad Ortopedik | G85: Cast Cutters, Electric | H85: SAW PLASTER ELECTRIC C/W VACUUM | I85: Therapeutic | J85: Basic | K85: 16-340 | L85: 1 | M85: KKM/JKN/HSA/10-05-01/H/15/4157 | N85: 11050 | O85: =N85*L85 -> 11050 | Q85: 46023
... A229: 226 | B229: BEMS | C229: P0 | D229: Hospital Shah Alam, Selangor | E229: Jabatan Pembedahan Am | F229: Wad Pembedahan Lelaki 9A | G229: Monitors, Physiologic, Vital Signs | H229: BLOOD PRESSURE MONITOR NON INVASIVE | I229: Diagnostic | J229: Intermediate | K229: 25-209 | L229: 1 | M229: KKM/JKN/HSA/10-05-01/R/15/7154 | N229: 1855 | O229: =N229*L229 -> 1855 | Q229: 46023
A230: 227 | B230: BEMS | C230: P0 | D230: Hospital Shah Alam, Selangor | E230: Jabatan Perubatan Am | G230: Monitors, Physiologic, Vital Signs | H230: BLOOD PRESSURE MONITOR NON INVASIVE | I230: Diagnostic | J230: Intermediate | K230: 25-209 | L230: 1 | M230: KKM/JKN/HSA/10-05-01/R/15/7155 | N230: 1855 | O230: =N230*L230 -> 1855 | Q230: 46023
A231: 228 | B231: BEMS | C231: P0 | D231: Hospital Shah Alam, Selangor | E231: Jabatan Otorinolaringologi (ORL) | F231: Klinik Otorinolaringologi (ORL) | G231: Monitors, Physiologic, Vital Signs | H231: SPHYGMOMANOMETER DIGITAL BATTERY OP | I231: Diagnostic | J231: Intermediate | K231: 25-209 | L231: 1 | M231: KKM/JKN/HSA/10-05-01/R/15/7143 | N231: 1855 | O231: =N231*L231 -> 1855 | Q231: 46023
A232: 229 | B232: BEMS | C232: P0 | D232: Hospital Shah Alam, Selangor | E232: Jabatan Pediatrik | F232: Klinik Pediatrik | G232: Monitors, Physiologic, Vital Signs | H232: SPHYGMOMANOMETER DIGITAL BATTERY OP | I232: Diagnostic | J232: Intermediate | K232: 25-209 | L232: 1 | M232: KKM/JKN/HSA/10-05-01/R/15/15296 | N232: 1855 | O232: =N232*L232 -> 1855 | Q232: 46023
A233: 230 | B233: BEMS | C233: P0 | D233: Hospital Shah Alam, Selangor | E233: Jabatan Oftalmologi | F233: Klinik Oftalmologi | G233: Monitors, Physiologic, Vital Signs | H233: SPHYGMOMANOMETER DIGITAL BATTERY OP | I233: Diagnostic | J233: Intermediate | K233: 25-209 | L233: 1 | M233: KKM/JKN/HSA/10-05-01/R/15/15914 | N233: 1855 | O233: =N233*L233 -> 1855 | Q233: 46023
A234: 231 | B234: BEMS | C234: P0 | D234: Hospital Shah Alam, Selangor | E234: Jabatan Oftalmologi | F234: Klinik Oftalmologi | G234: Monitors, Physiologic, Vital Signs | H234: SPHYGMOMANOMETER DIGITAL BATTERY OP | I234: Diagnostic | J234: Intermediate | K234: 25-209 | L234: 1 | M234: KKM/JKN/HSA/10-05-01/R/15/15915 | N234: 1855 | O234: =N234*L234 -> 1855 | Q234: 46023
A235: 232 | B235: BEMS | C235: P0 | D235: Hospital Shah Alam, Selangor | E235: Jabatan Obstetrik & Ginekologi | F235: Klinik Obstetrik & Ginekologi | G235: Monitors, Physiologic, Vital Signs | H235: SPHYGMOMANOMETER DIGITAL BATTERY OP | I235: Diagnostic | J235: Intermediate | K235: 25-209 | L235: 1 | M235: KKM/JKN/HSA/10-05-01/R/15/16386 | N235: 1855 | O235: =N235*L235 -> 1855 | Q235: 46023
A236: 233 | B236: BEMS | C236: P0 | D236: Hospital Shah Alam, Selangor | E236: Jabatan Obstetrik & Ginekologi | F236: Klinik Obstetrik & Ginekologi | G236: Monitors, Physiologic, Vital Signs | H236: SPHYGMOMANOMETER DIGITAL BATTERY OP | I236: Diagnostic | J236: Intermediate | K236: 25-209 | L236: 1 | M236: KKM/JKN/HSA/10-05-01/R/15/16387 | N236: 1855 | O236: =N236*L236 -> 1855 | Q236: 46023
A237: 234 | B237: BEMS | C237: P0 | D237: Hospital Shah Alam, Selangor | E237: Jabatan Otorinolaringologi (ORL) | F237: Klinik Otorinolaringologi (ORL) | G237: Monitors, Physiologic, Vital Signs | H237: SPHYGMOMANOMETER DIGITAL BATTERY OP | I237: Diagnostic | J237: Intermediate | K237: 25-209 | L237: 1 | M237: KKM/JKN/HSA/10-05-01/R/15/16744 | N237: 1855 | O237: =N237*L237 -> 1855 | Q237: 46023
A238: 235 | B238: BEMS | C238: P0 | D238: Hospital Shah Alam, Selangor | E238: Jabatan Perubatan Am | F238: Klinik Perubatan | G238: Monitors, Physiologic, Vital Signs | H238: SPHYGMOMANOMETER DIGITAL BATTERY OP | I238: Diagnostic | J238: Intermediate | K238: 25-209 | L238: 1 | M238: KKM/JKN/HSA/10-05-01/R/15/16745 | N238: 1855 | O238: =N238*L238 -> 1855 | Q238: 46023
A239: 236 | B239: BEMS | C239: P0 | D239: Hospital Shah Alam, Selangor | E239: Jabatan Perubatan Am | F239: Klinik Perubatan | G239: Monitors, Physiologic, Vital Signs | H239: SPHYGMOMANOMETER DIGITAL BATTERY OP | I239: Diagnostic | J239: Intermediate | K239: 25-209 | L239: 1 | M239: KKM/JKN/HSA/10-05-01/R/15/16746 | N239: 1855 | O239: =N239*L239 -> 1855 | Q239: 46023
A240: 237 | B240: BEMS | C240: P0 | D240: Hospital Shah Alam, Selangor | E240: Jabatan Pediatrik | F240: Klinik Pediatrik | G240: Monitors, Physiologic, Vital Signs | H240: SPHYGMOMANOMETER DIGITAL BATTERY OP | I240: Diagnostic | J240: Intermediate | K240: 25-209 | L240: 1 | M240: KKM/JKN/HSA/10-05-01/R/15/16747 | N240: 1855 | O240: =N240*L240 -> 1855 | Q240: 46023
A241: 238 | B241: BEMS | C241: P0 | D241: Hospital Shah Alam, Selangor | E241: Jabatan Ortopedik | F241: Klinik Ortopedik | G241: Monitors, Physiologic, Vital Signs | H241: SPHYGMOMANOMETER DIGITAL BATTERY OP | I241: Diagnostic | J241: Intermediate | K241: 25-209 | L241: 1 | M241: KKM/JKN/HSA/10-05-01/R/15/16763 | N241: 1855 | O241: =N241*L241 -> 1855 | Q241: 46023
A242: 239 | B242: BEMS | C242: P0 | D242: Hospital Shah Alam, Selangor | E242: Jabatan Ortopedik | F242: Klinik Ortopedik | G242: Monitors, Physiologic, Vital Signs | H242: SPHYGMOMANOMETER DIGITAL BATTERY OP | I242: Diagnostic | J242: Intermediate | K242: 25-209 | L242: 1 | M242: KKM/JKN/HSA/10-05-01/R/15/16764 | N242: 1855 | O242: =N242*L242 -> 1855 | Q242: 46023
... A395: 392 | B395: BEMS | C395: P0 | D395: Hospital Shah Alam, Selangor | E395: Jabatan Anestesiologi & Rawatan Kritikal | F395: Unit Rawatan Rapi (ICU) | G395: Ophthalmoscopes/Otoscopes | H395: DIAGNOSTIC SET ADULT | I395: Diagnostic | J395: Basic | K395: 18-595 | L395: 1 | M395: KKM/JKN/HSA/10-05-01/R/15/7358 | N395: 1459.33 | O395: =N395*L395 -> 1459.33 | Q395: 46023
A396: 393 | B396: BEMS | C396: P0 | D396: Hospital Shah Alam, Selangor | E396: Jabatan Obstetrik & Ginekologi | G396: Ophthalmoscopes/Otoscopes | H396: DIAGNOSTIC SET ADULT | I396: Diagnostic | J396: Basic | K396: 18-595 | L396: 1 | M396: KKM/JKN/HSA/10-05-01/R/15/7359 | N396: 1459.33 | O396: =N396*L396 -> 1459.33 | Q396: 46023
A397: 394 | B397: BEMS | C397: P0 | D397: Hospital Shah Alam, Selangor | E397: Jabatan Perubatan Am | F397: Klinik Perubatan | G397: Ophthalmoscopes/Otoscopes | H397: DIAGNOSTIC SET ADULT | I397: Diagnostic | J397: Basic | K397: 18-595 | L397: 1 | M397: KKM/JKN/HSA/10-05-01/R/15/7360 | N397: 1459.33 | O397: =N397*L397 -> 1459.33 | Q397: 46023
A398: 395 | B398: BEMS | C398: P0 | D398: Hospital Shah Alam, Selangor | E398: Jabatan Perubatan Am | F398: Klinik Perubatan | G398: Ophthalmoscopes/Otoscopes | H398: DIAGNOSTIC SET ADULT | I398: Diagnostic | J398: Basic | K398: 18-595 | L398: 1 | M398: KKM/JKN/HSA/10-05-01/R/15/7361 | N398: 1459.33 | O398: =N398*L398 -> 1459.33 | Q398: 46023
A399: 396 | B399: BEMS | C399: P0 | D399: Hospital Shah Alam, Selangor | E399: Jabatan Perubatan Am | F399: Klinik Perubatan | G399: Ophthalmoscopes/Otoscopes | H399: DIAGNOSTIC SET ADULT | I399: Diagnostic | J399: Basic | K399: 18-595 | L399: 1 | M399: KKM/JKN/HSA/10-05-01/R/15/7362 | N399: 1459.33 | O399: =N399*L399 -> 1459.33 | Q399: 46023
A400: 397 | B400: BEMS | C400: P0 | D400: Hospital Shah Alam, Selangor | E400: Jabatan Perubatan Am | F400: Klinik Perubatan | G400: Ophthalmoscopes/Otoscopes | H400: DIAGNOSTIC SET ADULT | I400: Diagnostic | J400: Basic | K400: 18-595 | L400: 1 | M400: KKM/JKN/HSA/10-05-01/R/15/7363 | N400: 1459.33 | O400: =N400*L400 -> 1459.33 | Q400: 46023
A401: 398 | B401: BEMS | C401: P0 | D401: Hospital Shah Alam, Selangor | E401: Jabatan Perubatan Am | F401: Klinik Perubatan | G401: Ophthalmoscopes/Otoscopes | H401: DIAGNOSTIC SET ADULT | I401: Diagnostic | J401: Basic | K401: 18-595 | L401: 1 | M401: KKM/JKN/HSA/10-05-01/R/15/7364 | N401: 1459.33 | O401: =N401*L401 -> 1459.33 | Q401: 46023
A402: 399 | B402: BEMS | C402: P0 | D402: Hospital Shah Alam, Selangor | E402: Jabatan Perubatan Am | F402: Klinik Perubatan | G402: Ophthalmoscopes/Otoscopes | H402: DIAGNOSTIC SET ADULT | I402: Diagnostic | J402: Basic | K402: 18-595 | L402: 1 | M402: KKM/JKN/HSA/10-05-01/R/15/7365 | N402: 1459.33 | O402: =N402*L402 -> 1459.33 | Q402: 46023
A403: 400 | B403: BEMS | C403: P0 | D403: Hospital Shah Alam, Selangor | E403: Jabatan Perubatan Am | F403: Klinik Perubatan | G403: Ophthalmoscopes/Otoscopes | H403: DIAGNOSTIC SET ADULT | I403: Diagnostic | J403: Basic | K403: 18-595 | L403: 1 | M403: KKM/JKN/HSA/10-05-01/R/15/7366 | N403: 1459.33 | O403: =N403*L403 -> 1459.33 | Q403: 46023
A404: 401 | B404: BEMS | C404: P0 | D404: Hospital Shah Alam, Selangor | E404: Jabatan Perubatan Am | F404: Klinik Perubatan | G404: Ophthalmoscopes/Otoscopes | H404: DIAGNOSTIC SET ADULT | I404: Diagnostic | J404: Basic | K404: 18-595 | L404: 1 | M404: KKM/JKN/HSA/10-05-01/R/15/7367 | N404: 1459.33 | O404: =N404*L404 -> 1459.33 | Q404: 46023
A405: 402 | B405: BEMS | C405: P0 | D405: Hospital Shah Alam, Selangor | E405: Jabatan Perubatan Am | F405: Klinik Perubatan | G405: Ophthalmoscopes/Otoscopes | H405: DIAGNOSTIC SET ADULT | I405: Diagnostic | J405: Basic | K405: 18-595 | L405: 1 | M405: KKM/JKN/HSA/10-05-01/R/15/7368 | N405: 1459.33 | O405: =N405*L405 -> 1459.33 | Q405: 46023
A406: 403 | B406: BEMS | C406: P0 | D406: Hospital Shah Alam, Selangor | E406: Jabatan Perubatan Am | F406: Klinik Perubatan | G406: Ophthalmoscopes/Otoscopes | H406: DIAGNOSTIC SET ADULT | I406: Diagnostic | J406: Basic | K406: 18-595 | L406: 1 | M406: KKM/JKN/HSA/10-05-01/R/15/7369 | N406: 1459.33 | O406: =N406*L406 -> 1459.33 | Q406: 46023
A407: 404 | B407: BEMS | C407: P0 | D407: Hospital Shah Alam, Selangor | E407: Jabatan Ortopedik | F407: Klinik Ortopedik | G407: Ophthalmoscopes/Otoscopes | H407: DIAGNOSTIC SET ADULT | I407: Diagnostic | J407: Basic | K407: 18-595 | L407: 1 | M407: KKM/JKN/HSA/10-05-01/R/15/7370 | N407: 1459.33 | O407: =N407*L407 -> 1459.33 | Q407: 46023
A408: 405 | B408: BEMS | C408: P0 | D408: Hospital Shah Alam, Selangor | E408: Jabatan Ortopedik | F408: Klinik Ortopedik | G408: Ophthalmoscopes/Otoscopes | H408: DIAGNOSTIC SET ADULT | I408: Diagnostic | J408: Basic | K408: 18-595 | L408: 1 | M408: KKM/JKN/HSA/10-05-01/R/15/7371 | N408: 1459.33 | O408: =N408*L408 -> 1459.33 | Q408: 46023
... A1816: 1813 | B1816: BEMS | C1816: P0 | D1816: Hospital Shah Alam, Selangor | E1816: Jabatan Obstetrik & Ginekologi | F1816: Klinik Obstetrik & Ginekologi | G1816: Electrosurgical Units, Monopolar/Bipolar | H1816: DIATHERMY UNIT | I1816: Therapeutic | J1816: Intermediate | K1816: 18-231 | L1816: 1 | M1816: KKM/JKN/HSA/10-05-01/H/15/5398 | N1816: 11160 | O1816: =N1816*L1816 -> 11160 | Q1816: 46023
A1817: 1814 | B1817: BEMS | C1817: P0 | D1817: Hospital Shah Alam, Selangor | E1817: Jabatan Otorinolaringologi (ORL) | F1817: Klinik Otorinolaringologi (ORL) | G1817: Audiometric Booths | H1817: BOOTH SOUND ATTENUATED | I1817: Diagnostic | J1817: Intermediate | K1817: 10-229 | L1817: 1 | N1817: 148645 | O1817: =N1817*L1817 -> 148645 | Q1817: 46023
A1818: 1815 | B1818: BEMS | C1818: P0 | D1818: Hospital Shah Alam, Selangor | E1818: Jabatan Otorinolaringologi (ORL) | F1818: Klinik Otorinolaringologi (ORL) | G1818: Audiometric Booths | H1818: BOOTH SOUND ATTENUATED | I1818: Diagnostic | J1818: Intermediate | K1818: 10-229 | L1818: 1 | N1818: 148645 | O1818: =N1818*L1818 -> 148645 | Q1818: 46023
A1819: 1816 | B1819: BEMS | C1819: P0 | D1819: Hospital Shah Alam, Selangor | E1819: Jabatan Kecemasan & Trauma | F1819: Jabatan Kecemasan & Trauma | G1819: Lights, Surgical | H1819: LAMP OPERATING MINOR | I1819: Therapeutic | J1819: Basic | K1819: 12-282 | L1819: 1 | M1819: KKM/JKN/HSA/10-05-01/H/15/5390 | N1819: 30000 | O1819: =N1819*L1819 -> 30000 | Q1819: 46023
A1820: 1817 | B1820: BEMS | C1820: P0 | D1820: Hospital Shah Alam, Selangor | E1820: Jabatan Otorinolaringologi (ORL) | F1820: Klinik Otorinolaringologi (ORL) | G1820: Lights, Surgical | H1820: LAMP OPERATING MINOR | I1820: Therapeutic | J1820: Basic | K1820: 12-282 | L1820: 1 | M1820: KKM/JKN/HSA/10-05-01/H/15/5107 | N1820: 30000 | O1820: =N1820*L1820 -> 30000 | Q1820: 46023
A1821: 1818 | B1821: BEMS | C1821: P0 | D1821: Hospital Shah Alam, Selangor | E1821: Jabatan Oftalmologi | F1821: Klinik Oftalmologi | G1821: Lights, Surgical | H1821: LAMP OPERATING MINOR | I1821: Therapeutic | J1821: Basic | K1821: 12-282 | L1821: 1 | M1821: KKM/JKN/HSA/10-05-01/H/15/5108 | N1821: 30000 | O1821: =N1821*L1821 -> 30000 | Q1821: 46023
A1822: 1819 | B1822: BEMS | C1822: P0 | D1822: Hospital Shah Alam, Selangor | E1822: Jabatan Obstetrik & Ginekologi | F1822: Klinik Obstetrik & Ginekologi | G1822: Cardiotocographs | H1822: MONITOR ANTEPARTUM/TWIN W/INTEGRAL PRINTER | I1822: Diagnostic | J1822: Intermediate | K1822: 12-610 | L1822: 1 | M1822: KKM/JKN/HSA/10-05-01/H/15/4300 | N1822: 10200 | O1822: =N1822*L1822 -> 10200 | Q1822: 46023
A1823: 1820 | B1823: BEMS | C1823: P0 | D1823: Hospital Shah Alam, Selangor | E1823: Jabatan Obstetrik & Ginekologi | F1823: Pusat Kemasukan Ibu Bersalin (PAC) | G1823: Cardiotocographs | H1823: MONITOR ANTEPARTUM/TWIN W/INTEGRAL PRINTER | I1823: Diagnostic | J1823: Intermediate | K1823: 12-610 | L1823: 1 | M1823: KKM/JKN/HSA/10-05-01/H/15/4944 | N1823: 10200 | O1823: =N1823*L1823 -> 10200 | Q1823: 46023
A1824: 1821 | B1824: BEMS | C1824: P0 | D1824: Hospital Shah Alam, Selangor | E1824: Jabatan Radiologi | F1824: Jabatan Radiologi | G1824: Dosimeters, Radiation | H1824: Dosimeter | I1824: Radiology | J1824: Basic | K1824: 11-295 | L1824: 1 | M1824: KKM/JKN/HSA/10-05-01/H/15/5092 | N1824: 4000 | O1824: =N1824*L1824 -> 4000 | Q1824: 46023
A1825: 1822 | B1825: BEMS | C1825: P0 | D1825: Hospital Shah Alam, Selangor | E1825: Jabatan Radiologi | F1825: Jabatan Radiologi | G1825: Dosimeters, Radiation | H1825: Dosimeter | I1825: Radiology | J1825: Basic | K1825: 11-295 | L1825: 1 | M1825: KKM/JKN/HSA/10-05-01/H/15/5093 | N1825: 4000 | O1825: =N1825*L1825 -> 4000 | Q1825: 46023
A1826: 1823 | B1826: BEMS | C1826: P0 | D1826: Hospital Shah Alam, Selangor | E1826: Jabatan Radiologi | F1826: Jabatan Radiologi | G1826: Dosimeters, Radiation | H1826: Dosimeter | I1826: Radiology | J1826: Basic | K1826: 11-295 | L1826: 1 | M1826: KKM/JKN/HSA/10-05-01/H/15/5095 | N1826: 4000 | O1826: =N1826*L1826 -> 4000 | Q1826: 46023
A1827: 1824 | B1827: BEMS | C1827: P0 | D1827: Hospital Shah Alam, Selangor | E1827: Jabatan Radiologi | F1827: Jabatan Radiologi | G1827: Dosimeters, Radiation | H1827: Dosimeter | I1827: Radiology | J1827: Basic | K1827: 11-295 | L1827: 1 | M1827: KKM/JKN/HSA/10-05-01/H/15/5096 | N1827: 4000 | O1827: =N1827*L1827 -> 4000 | Q1827: 46023
A1828: 1825 | B1828: BEMS | C1828: P0 | D1828: Hospital Shah Alam, Selangor | E1828: Jabatan Radiologi | F1828: Jabatan Radiologi | G1828: Dosimeters, Radiation | H1828: Dosimeter | I1828: Radiology | J1828: Basic | K1828: 11-295 | L1828: 1 | M1828: KKM/JKN/HSA/10-05-01/H/15/5097 | N1828: 4000 | O1828: =N1828*L1828 -> 4000 | Q1828: 46023
A1829: 1826 | B1829: BEMS | C1829: P0 | D1829: Hospital Shah Alam, Selangor | E1829: Jabatan Radiologi | F1829: Jabatan Radiologi | G1829: Dosimeters, Radiation | H1829: Dosimeter | I1829: Radiology | J1829: Basic | K1829: 11-295 | L1829: 1 | M1829: KKM/JKN/HSA/10-05-01/H/15/5098 | N1829: 4000 | O1829: =N1829*L1829 -> 4000 | Q1829: 46023
A1830: 1827 | B1830: BEMS | C1830: P0 | D1830: Hospital Shah Alam, Selangor | E1830: Jabatan Radiologi | F1830: Jabatan Radiologi | G1830: Dosimeters, Radiation | H1830: Dosimeter | I1830: Radiology | J1830: Basic | K1830: 11-295 | L1830: 1 | M1830: KKM/JKN/HSA/10-05-01/H/15/5099 | N1830: 4000 | O1830: =N1830*L1830 -> 4000 | Q1830: 46023
... A1886: 1883 | B1886: BEMS | C1886: P0 | D1886: Hospital Shah Alam, Selangor | E1886: Unit Hemodialisis | F1886: High Dependency Ward (HDW) | G1886: Water Purification Systems, Reverse Osmosis, Hemodialysis, Portable | H1886: PORTABLE RO UNIT | I1886: Therapeutic | J1886: Intermediate | K1886: 20-683 | L1886: 1 | M1886: KKM/JKN/HSA/10-05-01/H/20/199 | N1886: 35000 | O1886: =N1886*L1886 -> 35000 | Q1886: 46023
A1887: 1884 | B1887: BEMS | C1887: P0 | D1887: Hospital Shah Alam, Selangor | E1887: Jabatan Perubatan Am | G1887: Infusion Pumps, Syringe | H1887: PUMP SYRINGE | I1887: Therapeutic | J1887: Intermediate | K1887: 13-217 | L1887: 1 | M1887: KKM/JKN/HSA/10-05-01/H/20/125 | N1887: 3150 | O1887: =N1887*L1887 -> 3150 | Q1887: 46023
A1888: 1885 | B1888: BEMS | C1888: P0 | D1888: Hospital Shah Alam, Selangor | E1888: Jabatan Perubatan Am | G1888: Infusion Pumps, Syringe | H1888: PUMP SYRINGE | I1888: Therapeutic | J1888: Intermediate | K1888: 13-217 | L1888: 1 | M1888: KKM/JKN/HSA/10-05-01/H/20/126 | N1888: 3150 | O1888: =N1888*L1888 -> 3150 | Q1888: 46023
A1889: 1886 | B1889: BEMS | C1889: P0 | D1889: Hospital Shah Alam, Selangor | E1889: Jabatan Perubatan Am | G1889: Infusion Pumps, Syringe | H1889: INFUSION PUMP | I1889: Therapeutic | J1889: Intermediate | K1889: 13-217 | L1889: 1 | M1889: KKM/JKN/HSA/10-05-01/H/20/134 | N1889: 3290 | O1889: =N1889*L1889 -> 3290 | Q1889: 46023
A1890: 1887 | B1890: BEMS | C1890: P0 | D1890: Hospital Shah Alam, Selangor | E1890: Jabatan Perubatan Am | G1890: Infusion Pumps, Syringe | H1890: INFUSION PUMP | I1890: Therapeutic | J1890: Intermediate | K1890: 13-217 | L1890: 1 | M1890: KKM/JKN/HSA/10-05-01/H/20/135 | N1890: 3290 | O1890: =N1890*L1890 -> 3290 | Q1890: 46023
A1891: 1888 | B1891: BEMS | C1891: P0 | D1891: Hospital Shah Alam, Selangor | E1891: Jabatan Pediatrik | G1891: Infusion Pumps, Syringe | H1891: INFUSION PUMP | I1891: Therapeutic | J1891: Intermediate | K1891: 13-217 | L1891: 1 | M1891: KKM/JKN/HSA/10-05-01/H/20/136 | N1891: 3180 | O1891: =N1891*L1891 -> 3180 | Q1891: 46023
A1892: 1889 | B1892: BEMS | C1892: P0 | D1892: Hospital Shah Alam, Selangor | E1892: Jabatan Pediatrik | G1892: Infusion Pumps, Syringe | H1892: INFUSION PUMP | I1892: Therapeutic | J1892: Intermediate | K1892: 13-217 | L1892: 1 | M1892: KKM/JKN/HSA/10-05-01/H/20/137 | N1892: 3180 | O1892: =N1892*L1892 -> 3180 | Q1892: 46023
A1893: 1890 | B1893: BEMS | C1893: P0 | D1893: Hospital Shah Alam, Selangor | E1893: Jabatan Pediatrik | G1893: Infusion Pumps, Syringe | H1893: INFUSION PUMP | I1893: Therapeutic | J1893: Intermediate | K1893: 13-217 | L1893: 1 | M1893: KKM/JKN/HSA/10-05-01/H/20/149 | N1893: 3000 | O1893: =N1893*L1893 -> 3000 | Q1893: 46023
A1894: 1891 | B1894: BEMS | C1894: P0 | D1894: Hospital Shah Alam, Selangor | E1894: Jabatan Pediatrik | F1894: Unit Rawatan Rapi Neonatal (NICU) | G1894: Incubators, Infant | H1894: INCUBATOR INFANT INTENSIVE CARE | I1894: Therapeutic | J1894: Intermediate | K1894: 12-113 | L1894: 1 | M1894: KKM/JKN/HSA/10-05-01/H/20/160 | N1894: 24900 | O1894: =N1894*L1894 -> 24900 | Q1894: 46023
A1895: 1892 | B1895: BEMS | C1895: P0 | D1895: Hospital Shah Alam, Selangor | E1895: Jabatan Pediatrik | F1895: Unit Rawatan Rapi Neonatal (NICU) | G1895: Incubators, Infant | H1895: INCUBATOR INFANT INTENSIVE CARE | I1895: Therapeutic | J1895: Intermediate | K1895: 12-113 | L1895: 1 | M1895: KKM/JKN/HSA/10-05-01/H/20/161 | N1895: 24900 | O1895: =N1895*L1895 -> 24900 | Q1895: 46023
A1896: 1893 | B1896: BEMS | C1896: P0 | D1896: Hospital Shah Alam, Selangor | E1896: Jabatan Pembedahan Am | F1896: Wad Pembedahan 9A | G1896: Infusion Pumps, Syringe | H1896: PUMP SYRINGE | I1896: Therapeutic | J1896: Intermediate | K1896: 13-217 | L1896: 1 | M1896: KKM/JKN/HSA/10-05-01/H/20/230 | N1896: 3000 | O1896: =N1896*L1896 -> 3000 | Q1896: 46023
A1897: 1894 | B1897: BEMS | C1897: P0 | D1897: Hospital Shah Alam, Selangor | E1897: Jabatan Pembedahan Am | F1897: Wad Pembedahan 9A | G1897: Infusion Pumps, Syringe | H1897: PUMP SYRINGE | I1897: Therapeutic | J1897: Intermediate | K1897: 13-217 | L1897: 1 | M1897: KKM/JKN/HSA/10-05-01/H/20/231 | N1897: 3000 | O1897: =N1897*L1897 -> 3000 | Q1897: 46023
A1898: 1895 | B1898: BEMS | C1898: P0 | D1898: Hospital Shah Alam, Selangor | E1898: Jabatan Obstetrik & Ginekologi | F1898: Pusat Kemasukan Ibu Bersalin (PAC) | G1898: Infusion Pumps, Syringe | H1898: PUMP SYRINGE | I1898: Therapeutic | J1898: Intermediate | K1898: 13-217 | L1898: 1 | M1898: KKM/JKN/HSA/10-05-01/H/20/232 | N1898: 3000 | O1898: =N1898*L1898 -> 3000 | Q1898: 46023
A1899: 1896 | B1899: BEMS | C1899: P0 | D1899: Hospital Shah Alam, Selangor | E1899: Jabatan Obstetrik & Ginekologi | F1899: Klinik Obstetrik Ginekologi | G1899: Infusion Pumps, Syringe | H1899: PUMP SYRINGE | I1899: Therapeutic | J1899: Intermediate | K1899: 13-217 | L1899: 1 | M1899: KKM/JKN/HSA/10-05-01/H/20/233 | N1899: 3000 | O1899: =N1899*L1899 -> 3000 | Q1899: 46023
A1900: 1897 | B1900: BEMS | C1900: P0 | D1900: Hospital Shah Alam, Selangor | E1900: Jabatan Pediatrik | F1900: Unit Rawatan Rapi Neonatal (NICU) | G1900: Humidifiers, Heated | H1900: BIPAP MACHINE | I1900: Therapeutic | J1900: Intermediate | K1900: 12-050 | L1900: 1 | M1900: KKM/JKN/HSA/10-05-01/H/20/254 | N1900: 30000 | O1900: =N1900*L1900 -> 30000 | Q1900: 46023
A1901: 1898 | B1901: BEMS | C1901: P0 | D1901: Hospital Shah Alam, Selangor | E1901: Jabatan Pembedahan Am | F1901: Wad Pembedahan Lelaki 9A | G1901: Physiologic Monitoring Systems, Acute Care | H1901: PATIENT MONITOR | I1901: Diagnostic | J1901: Intermediate | K1901: 12-647 | L1901: 1 | M1901: KKM/JKN/HSA/10-05-01/H/16/194 | N1901: 5500 | O1901: =N1901*L1901 -> 5500 | Q1901: 46023
A1902: 1899 | B1902: BEMS | C1902: P0 | D1902: Hospital Shah Alam, Selangor | E1902: Jabatan Pembedahan Am | F1902: Wad Pembedahan Lelaki 9B | G1902: Physiologic Monitoring Systems, Acute Care | H1902: PATIENT MONITOR | I1902: Diagnostic | J1902: Intermediate | K1902: 12-647 | L1902: 1 | M1902: KKM/JKN/HSA/10-05-01/H/16/195 | N1902: 5500 | O1902: =N1902*L1902 -> 5500 | Q1902: 46023
A1903: 1900 | B1903: BEMS | C1903: P0 | D1903: Hospital Shah Alam, Selangor | E1903: Jabatan Obstetrik & Ginekologi | F1903: Wad Obstetrik & Ginekologi 8A | G1903: Oximeters, Pulse | H1903: PULSE OXIMETER AND SIMULATOR | I1903: Diagnostic | J1903: Intermediate | K1903: 17-148 | L1903: 1 | M1903: KKM/JKN/HSA/10-05-01/H/20/75 | N1903: 7400 | O1903: =N1903*L1903 -> 7400 | Q1903: 46023
A1904: 1901 | B1904: BEMS | C1904: P0 | D1904: Hospital Shah Alam, Selangor | E1904: Jabatan Obstetrik & Ginekologi | F1904: Dewan Bersalin (LDU) | G1904: Oximeters, Pulse | H1904: PULSE OXIMETER AND SIMULATOR | I1904: Diagnostic | J1904: Intermediate | K1904: 17-148 | L1904: 1 | M1904: KKM/JKN/HSA/10-05-01/H/20/76 | N1904: 7400 | O1904: =N1904*L1904 -> 7400 | Q1904: 46023
A1905: 1902 | B1905: BEMS | C1905: P0 | D1905: Hospital Shah Alam, Selangor | E1905: Jabatan Obstetrik & Ginekologi | F1905: Wad Obstetrik & Ginekologi 8B | G1905: Oximeters, Pulse | H1905: PULSE OXIMETER AND SIMULATOR | I1905: Diagnostic | J1905: Intermediate | K1905: 17-148 | L1905: 1 | M1905: KKM/JKN/HSA/10-05-01/H/20/77 | N1905: 7400 | O1905: =N1905*L1905 -> 7400 | Q1905: 46023
... A2420: 2417 | B2420: BEMS | C2420: P0 | D2420: Shah Alam | E2420: Jabatan Perubatan Rehabilitasi | F2420: Klinik Rehabilitasi | G2420: Exercisers, Continuous Passive Motion Inclusive : 1)Computer (KKM/JKN/HSA/10-05-01/H/15/1065-01) 2) Monitor (KKM/JKN/HSA/10-05-01/H/15/1065-02) 3) Printer (KKM/JKN/HSA/10-05-01/H/15/1065-03) | H2420: UPPER LIMB EXERCISER - COMPUTERISED (E-LINK) | I2420: Therapeutic | J2420: Package | K2420: 11-631 | L2420: 1 | M2420: KKM/JKN/HSA/10-05-01/H/15/1065 | N2420: 113944 | O2420: =N2420*L2420 -> 113944 | Q2420: 46023

Sheet UPTIME
E2: >5 | F2: 5-10 | G2: >10
A3: Equipments | B3: Group | C3: Operating Hours | D3: Operating Hours/WK (Days) | E3: Uptime Equipment | F3: Uptime Equipment | G3: Uptime Equipment
E4: < 5YRS | F4: 5-10 YRS | G4: >10 YRS
A5: Therapeutics
A6: Alternating Pressure Mattress | B6: P | C6: 12 | D6: 6 | E6: 0.96 | F6: 0.92 | G6: 0.85
A7: Aneasthesia Units and Vaporizers | B7: C | C7: 24 | D7: 7 | E7: 0.99 | F7: 0.95 | G7: 0.88
A8: Aneasthesia Ventilators | B8: C | C8: 24 | D8: 7 | E8: 0.99 | F8: 0.95 | G8: 0.88
A9: Aspirators | B9: C | C9: 24 | D9: 7 | E9: 0.99 | F9: 0.95 | G9: 0.88
A10: Defibrillators | B10: C | C10: 24 | D10: 7 | E10: 0.99 | F10: 0.95 | G10: 0.88
A11: Dental Equipment | B11: P | C11: 24 | D11: 7 | E11: 0.96 | F11: 0.92 | G11: 0.85
A12: Diathermy Units | B12: C | C12: 24 | D12: 7 | E12: 0.99 | F12: 0.95 | G12: 0.88
A13: Electrosurgical Units | B13: C | C13: 24 | D13: 7 | E13: 0.99 | F13: 0.95 | G13: 0.88
A14: Heamodialysis Units | B14: C | C14: 24 | D14: 7 | E14: 0.99 | F14: 0.95 | G14: 0.88
A15: Humidifiers | B15: C | C15: 24 | D15: 7 | E15: 0.99 | F15: 0.95 | G15: 0.88
A16: Hypo/hyperthermia Units | B16: C | C16: 24 | D16: 7 | E16: 0.99 | F16: 0.95 | G16: 0.88
A17: Incubators | B17: C | C17: 24 | D17: 7 | E17: 0.99 | F17: 0.95 | G17: 0.88
... A59: Vector Cardiographs | B59: P | C59: 12 | D59: 6 | E59: 0.96 | F59: 0.92 | G59: 0.85
A60: Analysers
A61: · Amino Acid | B61: P | C61: 12 | D61: 6 | E61: 0.96 | F61: 0.92 | G61: 0.85
A62: · Bilirubinometers | B62: P | C62: 12 | D62: 6 | E62: 0.96 | F62: 0.92 | G62: 0.85
A63: · Blood Gas | B63: P | C63: 12 | D63: 6 | E63: 0.96 | F63: 0.92 | G63: 0.85
A64: · Calcium | B64: P | C64: 12 | D64: 6 | E64: 0.96 | F64: 0.92 | G64: 0.85
A65: · Clinical Chemistry | B65: P | C65: 12 | D65: 6 | E65: 0.96 | F65: 0.92 | G65: 0.85
A66: · Coagulation | B66: P | C66: 12 | D66: 6 | E66: 0.96 | F66: 0.92 | G66: 0.85
A67: · Counter, Gamma | B67: P | C67: 12 | D67: 6 | E67: 0.96 | F67: 0.92 | G67: 0.85
A68: · Electrolyte | B68: P | C68: 12 | D68: 6 | E68: 0.96 | F68: 0.92 | G68: 0.85
A69: · Immunoassay | B69: P | C69: 12 | D69: 6 | E69: 0.96 | F69: 0.92 | G69: 0.85
A70: · Glucose | B70: P | C70: 12 | D70: 6 | E70: 0.96 | F70: 0.92 | G70: 0.85
A71: · Hematology | B71: P | C71: 12 | D71: 6 | E71: 0.96 | F71: 0.92 | G71: 0.85
A72: · Platelet Aggregation | B72: P | C72: 12 | D72: 6 | E72: 0.96 | F72: 0.92 | G72: 0.85
... A84: Spectrophotometers | B84: P | C84: 12 | D84: 6 | E84: 0.96 | F84: 0.92 | G84: 0.85

Sheet Public Holiday
A1: Date | B1: Day | C1: Holiday
A2: 46023 | B2: Thu | C2: New Year's Day
A3: 46054 | B3: Sun | C3: Thaipusam
A4: 46070 | B4: Tue | C4: Chinese New Year
A5: 46071 | B5: Wed | C5: Chinese New Year Holiday
A6: 46088 | B6: Sat | C6: Nuzul Al-Quran
A7: 46102 | B7: Sat | C7: Hari Raya Aidilfitri
A8: 46103 | B8: Sun | C8: Hari Raya Aidilfitri Holiday
A9: 46143 | B9: Fri | C9: Labour Day
A10: 46169 | B10: Wed | C10: Hari Raya Haji
A11: 46173 | B11: Sun | C11: Wesak Day
A12: 46174 | B12: Mon | C12: Agong's Birthday
A13: 46190 | B13: Wed | C13: Awal Muharram
... A46: 45651 | B46: Wed | C46: Christmas Day

Sheet KDI
A1: Indicator No. | B1: Indicator | E1: Frequency of Deduction | F1: Biomedical Equipment Purchase Cost (RM) | H1: Deduction Range Value (RM) | J1: Maximum Demerit Point per Work Order
F2: From | G2: To
A3: B.1 | B3: The Company shall respond to the request within the specified time frame | E3: Per event | F3: 0.00 5,000.00 10,000.00 15,000.00 20,000.00 25,000.00 30,000.00 35,000.00 40,000.00 > 45,000.00 | G3: 4,999.99 9,999.99 14,999.99 19,999.99 24,999.99 29,999.99 34,999.99 39,999.99 44,999.99 | H3: 10.00 20.00 30.00 40.00 50.00 60.00 70.00 80.00 90.00 100.00 | J3: 1
A4: B.2 | B4: The Company shall carry out repairs to restore faulty medical equipment to a specified condition when it fails to function as per manufacturer’s specification within seven (7) working days. | E4: Per day | F4: 0.00 5,000.00 10,000.00 15,000.00 20,000.00 25,000.00 30,000.00 35,000.00 40,000.00 > 45,000.00 | G4: 4,999.99 9,999.99 14,999.99 19,999.99 24,999.99 29,999.99 34,999.99 39,999.99 44,999.99 | H4: 10.00 20.00 30.00 40.00 50.00 60.00 70.00 80.00 90.00 100.00 | J4: Number of working days for the month
A5: B.3 | B5: The Company shall carry out scheduled maintenance as per schedule in accordance to the procedure as specified in Agreement. Scheduled maintenance shall include complete safety and performance tests. | E5: Per event | F5: 0.00 5,000.00 10,000.00 15,000.00 20,000.00 25,000.00 30,000.00 35,000.00 40,000.00 45,000.00 | G5: 4,999.99 9,999.99 14,999.99 19,999.99 24,999.99 29,999.99 34,999.99 39,999.99 44,999.99 49,999.99 | H5: 10.00 20.00 30.00 40.00 50.00 60.00 70.00 80.00 90.00 100.00 | J5: 1
F6: For every RM 5,000 increment of equipment cost, an increase of RM10 will be applied subsequently
A7: B.4 | B7: The Company shall ensure biomedical equipment meets the uptime target as set in the Agreement. | E7: Per event | H7: 1st level of Uptime Target (TRKPI) | I7: 2nd level of Uptime Target (80%) | J7: 2
F8: 0.00 5,000.00 10,000.00 15,000.00 20,000.00 25,000.00 30,000.00 35,000.00 40,000.00 45,000.00 | G8: 4,999.99 9,999.99 14,999.99 19,999.99 24,999.99 29,999.99 34,999.99 39,999.99 44,999.99 49,999.99 | H8: 10.00 20.00 30.00 40.00 50.00 60.00 70.00 80.00 90.00 100.00 | I8: 20.00 40.00 60.00 80.00 100.00 120.00 140.00 160.00 180.00 200.00
F9: For every RM 5,000 increment of equipment cost, an increase of RM10 will be applied subsequently for 1st Uptime Target and an increase of RM20 for 2nd Uptime Target will be applied subsequently
A10: B.5 | B10: The Company shall attend and witness T&C and manage biomedical equipment within the warranty period. | E10: Per event | F10: 0.00 5,000.00 10,000.00 15,000.00 20,000.00 25,000.00 30,000.00 35,000.00 40,000.00 45,000.00 | G10: 4,999.99 9,999.99 14,999.99 19,999.99 24,999.99 29,999.99 34,999.99 39,999.99 44,999.99 49,999.99 | H10: 10.00 20.00 30.00 40.00 50.00 60.00 70.00 80.00 90.00 100.00 | J10: 1
F11: For every RM 5,000 increment of equipment cost, an increase of RM10 will be applied subsequently

Sheet KDI 2
A1: Indicator No. | B1: Indicator | E1: Frequency of Deduction | F1: Biomedical Equipment Purchase Cost (RM) | H1: Deduction Range Value (RM) | J1: Maximum Demerit Point per Work Order
F2: From | G2: To
A3: B.1 | B3: The Company shall respond to the request within the specified time frame | E3: Per event | F3: 0.00 5,000.00 10,000.00 15,000.00 20,000.00 25,000.00 30,000.00 35,000.00 40,000.00 > 45,000.00 | G3: 4,999.99 9,999.99 14,999.99 19,999.99 24,999.99 29,999.99 34,999.99 39,999.99 44,999.99 | H3: 10.00 20.00 30.00 40.00 50.00 60.00 70.00 80.00 90.00 100.00 | J3: 1
A4: B.2 | B4: The Company shall carry out repairs to restore faulty medical equipment to a specified condition when it fails to function as per manufacturer’s specification within seven (7) working days. | E4: Per day | F4: 0.00 5,000.00 10,000.00 15,000.00 20,000.00 25,000.00 30,000.00 35,000.00 40,000.00 > 45,000.00 | G4: 4,999.99 9,999.99 14,999.99 19,999.99 24,999.99 29,999.99 34,999.99 39,999.99 44,999.99 | H4: 10.00 20.00 30.00 40.00 50.00 60.00 70.00 80.00 90.00 100.00 | J4: Number of working days for the month
A5: B.3 | B5: The Company shall carry out scheduled maintenance as per schedule in accordance to the procedure as specified in Agreement. Scheduled maintenance shall include complete safety and performance tests. | E5: Per event | F5: 0.00 5,000.00 10,000.00 15,000.00 20,000.00 25,000.00 30,000.00 35,000.00 40,000.00 45,000.00 | G5: 4,999.99 9,999.99 14,999.99 19,999.99 24,999.99 29,999.99 34,999.99 39,999.99 44,999.99 49,999.99 | H5: 10.00 20.00 30.00 40.00 50.00 60.00 70.00 80.00 90.00 100.00 | J5: 1
F6: For every RM 5,000 increment of equipment cost, an increase of RM10 will be applied subsequently
A7: B.4 | B7: The Company shall ensure biomedical equipment meets the uptime target as set in the Agreement. | E7: Per event | H7: 1st level of Uptime Target (TRKPI) | I7: 2nd level of Uptime Target (80%) | J7: 2
F8: 0.00 5,000.00 10,000.00 15,000.00 20,000.00 25,000.00 30,000.00 35,000.00 40,000.00 45,000.00 | G8: 4,999.99 9,999.99 14,999.99 19,999.99 24,999.99 29,999.99 34,999.99 39,999.99 44,999.99 49,999.99 | H8: 10.00 20.00 30.00 40.00 50.00 60.00 70.00 80.00 90.00 100.00 | I8: 20.00 40.00 60.00 80.00 100.00 120.00 140.00 160.00 180.00 200.00
F9: For every RM 5,000 increment of equipment cost, an increase of RM10 will be applied subsequently for 1st Uptime Target and an increase of RM20 for 2nd Uptime Target will be applied subsequently
A10: B.5 | B10: The Company shall attend and witness T&C and manage biomedical equipment within the warranty period. | E10: Per event | F10: 0.00 5,000.00 10,000.00 15,000.00 20,000.00 25,000.00 30,000.00 35,000.00 40,000.00 45,000.00 | G10: 4,999.99 9,999.99 14,999.99 19,999.99 24,999.99 29,999.99 34,999.99 39,999.99 44,999.99 49,999.99 | H10: 10.00 20.00 30.00 40.00 50.00 60.00 70.00 80.00 90.00 100.00 | J10: 1
F11: For every RM 5,000 increment of equipment cost, an increase of RM10 will be applied subsequently

Sheet BEMSdar
A1: MINISTRY OF HEALTH
A2: Deduction Mapping Report Biomedical Engineering Maintenance Services (BEMS)
D5: HOSPITAL NAME : | E5: HOSPITAL SHAH ALAM | I5: State: | J5: SELANGOR
D7: MONTH/YEAR : | E7: 46082 | I7: Company: | J7: Ambang Wira Sdn Bhd
D9: Monthly Service Fee (RM): | E9: 361632.64
D11: Monthly Service Fee for BEMS (RM) @ 97.5%: | E11: =E9*0.975 -> 352591.82
D13: Monthly Service Fee for FMS (RM) @ 2.5%: | E13: =E9-E11 -> 9040.816
A17: No | B17: Key Deduction Indicators | I17: Frequency | L17: Deduction Value (RM) | N17: Deduction % | O17: Performance Level (%)
A19: B.1 | B19: All service requests shall be responded by the Company’s trained technical personal within the timeframe as stipulated in the Agreement. | I19: Per event | L19: ='B1-RESPONSE & B2-REPAIR'!N230 -> 0 | N19: =L19/$E$11% -> 0 | O19: =100-N19 -> 100
A20: B.2 | B20: All unscheduled maintenance works including relevant maintenance calibration, safety tests and functional checks shall be completed within seven (7) working days. | I20: Per day | L20: ='B1-RESPONSE & B2-REPAIR'!T230 -> 8670 | N20: =L20/$E$11% -> 2.4589339 | O20: =100-N20 -> 97.541066
A21: B.3 | B21: Scheduled maintenance shall be carried out as per schedule and according to the procedure as specified in the Agreement. Scheduled maintenance shall include complete safety and performance tests. | I21: Per event | L21: ='B3-SCHEDULED'!M503 -> 0 | N21: =L21/$E$11% -> 0 | O21: =100-N21 -> 100
A22: B.4 | B22: All biomedical equipment shall be functioning and maintained to ensure uptime target as specified in the TRKPI are met. | I22: Per event | L22: ='B4-UPTIME'!Z94 -> 830 | N22: =L22/$E$11% -> 0.23539967 | O22: =100-N22 -> 99.7646
A23: B.5 | B23: T&C and Warranty Management of newly introduced biomedical shall be managed and performed according to the Agreement and related acts, standards and regulations. | I23: Per event | L23: =SUM('B5-T&C'!O23) -> 0 | N23: =L23/$E$11% -> 0 | O23: =100-N23 -> 100
A24: Total | L24: =SUM(L19:M23) -> 9500 | N24: =L24/$E$9% -> 2.6269753 | O24: =100-N24 -> 97.373025
C27: Prepared by: | I27: Verified by:
C31: NOR JALILAH BINTI JUMAHAT | I31: MOHD SALLEH B. MAT SAHAT
C32: Head of BEMS | I32: Facility Manager
C33: Ambang Wira Sdn Bhd- Hospital Shah Alam | I33: Ambang Wira Sdn Bhd- Hospital Shah Alam
C34: Date: | I34: Date:

Sheet B1-RESPONSE & B2-REPAIR
B1: MINISTRY OF HEALTH
B2: Deduction Mapping Report Biomedical Engineering Maintenance Services (BEMS)
B3: INDICATOR B.1 RESPONSE TIME & B.2 REPAIR TIME
B5: HOSPITAL NAME : | C5: HOSPITAL SHAH ALAM | L5: FIRST DATE OF THE MONTH : | N5: =BEMSdar!E7 -> 46082
B7: STATE : | C7: SELANGOR | L7: LAST DATE OF THE MONTH : | N7: 46112
B9: COMPANY : | C9: AMBANG WIRA SDN BHD | L9: BEMS MONTHLY FEE (RM) @ 97.5% : | N9: =BEMSdar!E11 -> 352591.82
B11: MONTH/YEAR : | C11: =BEMSdar!E7 -> 46082 | L11: FMS MONTHLY FEE (RM) @ 2.5% : | N11: =BEMSdar!E13 -> 9040.816
A13: Notes:
A14: 1) Deduction Ringgit Equivalent is based on Appendix 11 of the Agreement, Section B3 Key Deduction Indicators for BEMS
A15: 2) Deduction Value for Indicator B.1 is Deduction Ringgit Equivalent (per event)
A16: 3) Total Repair Time includes weekend & public holiday
A17: 4) Demerit Point for Indicator B.2 is calculated based on completion date against request date, less by 7 working days
A18: 5) Deduction Value for Indicator B.2 is Demerit Point multiply by Deduction Ringgit Equivalent
A20: No | B20: Asset No | C20: Asset Description | D20: Asset Purchase Price (RM) | E20: Work Order No. | F20: User Location | G20: Work Order/ Complaint Details | H20: Response Category (Emergency/ Normal) | I20: Total Response Time (minutes) | J20: Work Request Date | K20: Work Completion Date | L20: Deduction Ringgit Equivalent (RM) | M20: Indicator B.1 | P20: Indicator B.2
M21: Validate Status (Y/N) | N21: Deduction Value (RM) | O21: Remarks/ Exemption | P21: Validate Status (Y/N) | Q21: Total Repair Time (day) | R21: Last date of 7 working days (dd/mm/yy) | S21: Demerit Point | T21: Deduction Value (RM) | U21: Remarks/ Exemption
A22: Current Month (Work Order Closed)
A23: 1 | B23: KKM/JKN/HSA/10-05-01/H/15/1121 | C23: DENTAL CHAIR, OFFICER | D23: 69000 | E23: HSASWIBE26011783 | F23: Klinik Bedah Mulut & Klinik Pergigian Pediatrik | G23: DENTAL CHAIR TIDAK BERFUNGSI DENGAN BAIK DI BILIK 4 KLINIK DENTAL (H/15/1121) | H23: NORMAL | I23: 0 days, 0 hrs, 16 mins | J23: 46083.458 | K23: 46083 | L23: =IF(D23>44999.99,100,ROUNDUP((D23/4999.99)*10,-1)) -> 100 | M23: N | N23: =IF(M23="Y",L23,0) -> 0 | P23: N | Q23: =K23-J23+1 -> 0.54236111 | R23: =WORKDAY(J23,7,'Public Holiday'!$A$2:$A$46) -> 46092 | S23: 0 | T23: =L23*S23 -> 0 | U23: BD
A24: 2 | B24: KKM/JKN/HSA/10-05-01/H/15/3629 | C24: VENTILATOR FOR NEONATES & INFANTS | D24: 53000 | E24: HSASWIBE26011786 | F24: Unit Rawatan Rapi Neonatal (NICU) | G24: OKSIGEN SENSOR VENTILATOR TIDAK BERFUNGSI DI WAD NICU (H/15/3621) | H24: NORMAL | I24: 0 days, 0 hrs, 07 mins | J24: 46083.503 | K24: 46083 | L24: =IF(D24>44999.99,100,ROUNDUP((D24/4999.99)*10,-1)) -> 100 | M24: N | N24: =IF(M24="Y",L24,0) -> 0 | P24: N | Q24: =K24-J24+1 -> 0.49652778 | R24: =WORKDAY(J24,7,'Public Holiday'!$A$2:$A$46) -> 46092 | S24: 0 | T24: =L24*S24 -> 0 | U24: BD
A25: 3 | B25: KKM/JKN/HSA/10-05-01/H/18/127 | C25: ECG (EKG) MACHINE | D25: 12000 | E25: HSASWIBE26011787 | F25: Jabatan Kecemasan & Trauma (ED) | G25: MESIN ECG TIDAK BERFUNGSI DENGAN BAIK DI BILIK NO.6 GREENZONE ED (H/18/127) | H25: NORMAL | I25: 0 days, 0 hrs, 17 mins | J25: 46083.523 | K25: 46083 | L25: =IF(D25>44999.99,100,ROUNDUP((D25/4999.99)*10,-1)) -> 30 | M25: N | N25: =IF(M25="Y",L25,0) -> 0 | P25: N | Q25: =K25-J25+1 -> 0.47708333 | R25: =WORKDAY(J25,7,'Public Holiday'!$A$2:$A$46) -> 46092 | S25: 0 | T25: =L25*S25 -> 0 | U25: BD
A26: 4 | B26: KKM/JKN/HSA/10-05-01/R/15/7037 | C26: SCALES BABY DIGITAL/ELECTRONIC W/MEASURE | D26: 1500 | E26: HSASWIBE26011866 | F26: WAD 8A (Wad Obstetrik & Ginekologi 8A) | G26: INFANT/ BABY SCALER (R/15/7037): PENIMBANG BABY TIDAK BOLEH ON DI BILIK BABY WAD 8A | H26: NORMAL | I26: 0 days, 0 hrs, 19 mins | J26: 46084.299 | K26: 46095 | L26: =IF(D26>44999.99,100,ROUNDUP((D26/4999.99)*10,-1)) -> 10 | M26: N | N26: =IF(M26="Y",L26,0) -> 0 | P26: N | Q26: =K26-J26+1 -> 11.700694 | R26: =WORKDAY(J26,7,'Public Holiday'!$A$2:$A$46) -> 46093 | S26: 0 | T26: =L26*S26 -> 0 | U26: BD
A27: 5 | B27: KKM/JKN/HSA/10-05-01/H/22/146 | C27: DEFIBRILLATOR | D27: 27500 | E27: HSASWIBE26011868 | F27: Wad Perubatan Lelaki 10A | G27: DEFIBRILLATOR (H/22/146): MESIN DEFIB TIDAK BERFUNGSI DENGAN BAIK- GRAF BACAAN ECG TIDAK JELAS DI WAD 10A | H27: NORMAL | I27: 0 days, 0 hrs, 24 mins | J27: 46084.338 | K27: 46084 | L27: =IF(D27>44999.99,100,ROUNDUP((D27/4999.99)*10,-1)) -> 60 | M27: N | N27: =IF(M27="Y",L27,0) -> 0 | P27: N | Q27: =K27-J27+1 -> 0.6625 | R27: =WORKDAY(J27,7,'Public Holiday'!$A$2:$A$46) -> 46093 | S27: 0 | T27: =L27*S27 -> 0 | U27: BD
A28: 6 | B28: KKM/JKN/HSA/10-05-10/H/21/204 | C28: ECG MACHINE | D28: 4200 | E28: HSASWIBE26011980 | F28: Unit Rawatan Rapi (ICU) | G28: ECG MACHINE (H/21/204)-MONITOR DISPLAY TIDAK KELUAR WAVE DI ICU | H28: NORMAL | I28: 0 days, 0 hrs, 40 mins | J28: 46084.679 | K28: 46084 | L28: =IF(D28>44999.99,100,ROUNDUP((D28/4999.99)*10,-1)) -> 10 | M28: N | N28: =IF(M28="Y",L28,0) -> 0 | P28: N | Q28: =K28-J28+1 -> 0.32083333 | R28: =WORKDAY(J28,7,'Public Holiday'!$A$2:$A$46) -> 46093 | S28: 0 | T28: =L28*S28 -> 0 | U28: BD
A29: 7 | B29: KKM/JKN/HSA/10-05-01/H/15/1616 | C29: VENTILATOR HIGH FREQUENCY NEONATE | D29: 64000 | E29: HSASWIBE26011998 | F29: Unit Rawatan Rapi Neonatal (NICU) | G29: INFANT VENTILATOR (H/15/1616): OKSIGEN SENSOR ROSAK DI NICU | H29: NORMAL | I29: 0 days, 0 hrs, 07 mins | J29: 46085.37 | K29: 46085 | L29: =IF(D29>44999.99,100,ROUNDUP((D29/4999.99)*10,-1)) -> 100 | M29: N | N29: =IF(M29="Y",L29,0) -> 0 | P29: N | Q29: =K29-J29+1 -> 0.62986111 | R29: =WORKDAY(J29,7,'Public Holiday'!$A$2:$A$46) -> 46094 | S29: 0 | T29: =L29*S29 -> 0 | U29: BD
A30: 8 | B30: KKM/JKN/HSA/10-05-01/H/23/42 | C30: X-RAY CARM | D30: 332177.94 | E30: HSASWIBE26012023 | F30: Dewan Bedah Utama (GOT) | G30: XRAY CARM (H/23/42): MOBILE C ARM HANDSWITCH HOLDER ROSAK DI GOT | H30: NORMAL | I30: 0 days, 0 hrs, 17 mins | J30: 46085.495 | K30: 46085 | L30: =IF(D30>44999.99,100,ROUNDUP((D30/4999.99)*10,-1)) -> 100 | M30: N | N30: =IF(M30="Y",L30,0) -> 0 | P30: N | Q30: =K30-J30+1 -> 0.50486111 | R30: =WORKDAY(J30,7,'Public Holiday'!$A$2:$A$46) -> 46094 | S30: 0 | T30: =L30*S30 -> 0 | U30: BD
A31: 9 | B31: KKM/JKN/HSA/10-05-01/H/15/2087 | C31: MONITOR 4 CH, ECG/RR/NIBP/SP02/TEMP | D31: 9000 | E31: HSASWIBE26012027 | F31: Jabatan Kecemasan & Trauma (ED) | G31: SPO2 PROB PUTUS DI KATIL 2 RESUS ED | H31: NORMAL | I31: 0 days, 0 hrs, 40 mins | J31: 46085.618 | K31: 46085 | L31: =IF(D31>44999.99,100,ROUNDUP((D31/4999.99)*10,-1)) -> 20 | M31: N | N31: =IF(M31="Y",L31,0) -> 0 | P31: N | Q31: =K31-J31+1 -> 0.38194444 | R31: =WORKDAY(J31,7,'Public Holiday'!$A$2:$A$46) -> 46094 | S31: 0 | T31: =L31*S31 -> 0 | U31: BD
A32: 10 | B32: KKM/JKN/HSA/10-05-01/H/20/179 | C32: SPOT VITAL SIGN (NIBP) | D32: 6500 | E32: HSASWIBE26012033 | F32: Wad 13 (VIP) | G32: Asset Name: Patient Monitor No asset : H/20/179 Description: Spo2 probe tidak dapat bacaan Location: Wad 13 | H32: NORMAL | I32: 0 days, 0 hrs, 33 mins | J32: 46085.713 | K32: 46085 | L32: =IF(D32>44999.99,100,ROUNDUP((D32/4999.99)*10,-1)) -> 20 | M32: N | N32: =IF(M32="Y",L32,0) -> 0 | P32: N | Q32: =K32-J32+1 -> 0.28680556 | R32: =WORKDAY(J32,7,'Public Holiday'!$A$2:$A$46) -> 46094 | S32: 0 | T32: =L32*S32 -> 0 | U32: BD
A33: 11 | B33: KKM/JKN/HSA/10-05-01/H/15/4261 | C33: LASER DIODE(RED) PHOTOCOAGULATOR | D33: 125347 | E33: HSASWIBE26012070 | F33: Klinik Oftalmologi (OPHTHAL CLINIC) | G33: LASER DIODE (RED) PHOTOCOAGULATION (H/15/4261): CERMIN MESIN LASER TERCABUT DI KLINIK MATA | H33: NORMAL | I33: 0 days, 0 hrs, 12 mins | J33: 46086.672 | K33: 46086 | L33: =IF(D33>44999.99,100,ROUNDUP((D33/4999.99)*10,-1)) -> 100 | M33: N | N33: =IF(M33="Y",L33,0) -> 0 | P33: N | Q33: =K33-J33+1 -> 0.32777778 | R33: =WORKDAY(J33,7,'Public Holiday'!$A$2:$A$46) -> 46097 | S33: 0 | T33: =L33*S33 -> 0 | U33: BD
A34: 12 | B34: KKM/JKN/HSA/10-05-01/H/23/8 | C34: ULTRASOUND SCANNER | D34: 97500 | E34: HSASWIBE26012073 | F34: PAC | G34: MESIN ULTRASOUND TIDAK BERFUNGSI DENGAN BAIK DI PAC 3 (H/23/8) | H34: NORMAL | I34: 0 days, 0 hrs, 34 mins | J34: 46086.851 | K34: 46086 | L34: =IF(D34>44999.99,100,ROUNDUP((D34/4999.99)*10,-1)) -> 100 | M34: N | N34: =IF(M34="Y",L34,0) -> 0 | P34: N | Q34: =K34-J34+1 -> 0.14861111 | R34: =WORKDAY(J34,7,'Public Holiday'!$A$2:$A$46) -> 46097 | S34: 0 | T34: =L34*S34 -> 0 | U34: BD
... A129: 107 | B129: KKM/JKNS/HSA/10-05-01/H/24/15 | C129: OTOACOUSTIC EMISSION (OAE) SCREENING SYSTEM | D129: 19900 | E129: HSASWIBE26015620 | F129: Klinik Otorinolaringologi (ORL) | G129: Asset no: H/24/15 Serial no: GI1010317 Asset description: DPOAE Screening Problem: replace OAE cable Lokasi: Klinik orl | H129: NORMAL | I129: 0 days, 0 hrs, 09 mins | J129: 46112 | K129: 46112 | L129: =IF(D129>44999.99,100,ROUNDUP((D129/4999.99)*10,-1)) -> 40 | M129: N | N129: =IF(M129="Y",L129,0) -> 0 | P129: N | Q129: =K129-J129+1 -> 1 | R129: =WORKDAY(J129,7,'Public Holiday'!$A$2:$A$46) -> 46121 | S129: 0 | T129: =L129*S129 -> 0 | U129: BREAKDOWN RIW
A130: Current Month (Work Order Open)
A131: 1 | B131: KKM/JKN/HSA/10-05-01/H/15/1586 | C131: INFANT WARMER (RADIANT) | D131: 24000 | E131: HSASWIBE26011777 | F131: Dewan Bedah Bersalin (MOT) | G131: BABY WARMER ERROR DI BILIK MOT 1 MOT (H/15/1586) | H131: NORMAL | I131: 0 days, 0 hrs, 06 mins | J131: 46083.329 | K131: 46112 | L131: =IF(D131>44999.99,100,ROUNDUP((D131/4999.99)*10,-1)) -> 50 | M131: N | N131: =IF(M131="Y",L131,0) -> 0 | P131: N | Q131: =K131-J131+1 -> 29.670833 | R131: =WORKDAY(J131,7,'Public Holiday'!$A$2:$A$46) -> 46092 | S131: 0 | T131: =L131*S131 -> 0 | U131: BD PO 71818 DRAGER
A132: 2 | B132: KKM/JKN/HSA/10-05-01/H/22/126 | C132: ULTRASOUND SCANNER | D132: 49000 | E132: HSASWIBE26011974 | F132: Dewan Bersalin (LDU) | G132: ULTRASOUND SCANNER (H/22/126)- MESIN SCAN LOOSE DI PAC 4 | H132: NORMAL | I132: 0 days, 0 hrs, 01 mins | J132: 46084.541 | K132: 46112 | L132: =IF(D132>44999.99,100,ROUNDUP((D132/4999.99)*10,-1)) -> 100 | M132: N | N132: =IF(M132="Y",L132,0) -> 0 | P132: N | Q132: =K132-J132+1 -> 28.459028 | R132: =WORKDAY(J132,7,'Public Holiday'!$A$2:$A$46) -> 46093 | S132: 0 | T132: =L132*S132 -> 0 | U132: BD, TA RIW
A133: 3 | B133: KKM/JKN/HSA/10-05-01/H/22/144 | C133: PATIENT MONITORING EQUIPMENT | D133: 8700 | E133: HSASWIBE26012132 | F133: JABATAN PEMBEDAHAN AM | G133: Asset Name: Patient Monitor No asset : H/22/144 Description: Spo2 tidak dapat bacaan Location: Wad 13 | H133: NORMAL | I133: 0 days, 0 hrs, 13 mins | J133: 46089.946 | K133: 46112 | L133: =IF(D133>44999.99,100,ROUNDUP((D133/4999.99)*10,-1)) -> 20 | M133: N | N133: =IF(M133="Y",L133,0) -> 0 | P133: N | Q133: =K133-J133+1 -> 23.054167 | R133: =WORKDAY(J133,7,'Public Holiday'!$A$2:$A$46) -> 46098 | S133: 0 | T133: =L133*S133 -> 0 | U133: BD, PO AWSB-72006 QP MANUFACTURING
A134: 4 | B134: KKM/JKN/HSA/10-05-01/H/15/470 | C134: INFANT INCUBATOR | D134: 24000 | E134: HSASWIBE26012148 | F134: Unit Rawatan Rapi Neonatal (NICU) | G134: INFANT INCUBATOR TIDAK BERFUNGSI DENGAN BAIK (H/15/470) NICU | H134: NORMAL | I134: 0 days, 0 hrs, 29 mins | J134: 46090.438 | K134: 46112 | L134: =IF(D134>44999.99,100,ROUNDUP((D134/4999.99)*10,-1)) -> 50 | M134: N | N134: =IF(M134="Y",L134,0) -> 0 | P134: N | Q134: =K134-J134+1 -> 22.561806 | R134: =WORKDAY(J134,7,'Public Holiday'!$A$2:$A$46) -> 46099 | S134: 0 | T134: =L134*S134 -> 0 | U134: BD, QUOTATION QUO-AFMAL-26068-001 RECEIVE 30/3/26
A135: 5 | B135: KKM/JKN/HSA/10-05-01/H/15/475 | C135: INFANT INCUBATOR | D135: 24000 | E135: HSASWIBE26012149 | F135: Unit Rawatan Rapi Neonatal (NICU) | G135: INFANT INCUBATOR LOCK PINTU PATAH (H/15/475) DI NICU | H135: NORMAL | I135: 0 days, 0 hrs, 30 mins | J135: 46090.44 | K135: 46112 | L135: =IF(D135>44999.99,100,ROUNDUP((D135/4999.99)*10,-1)) -> 50 | M135: N | N135: =IF(M135="Y",L135,0) -> 0 | P135: N | Q135: =K135-J135+1 -> 22.559722 | R135: =WORKDAY(J135,7,'Public Holiday'!$A$2:$A$46) -> 46099 | S135: 1 | T135: =L135*S135 -> 50 | U135: BD , PO AWSB-72503 DRAGER
A136: 6 | B136: KKM/JKN/HSA/10-05-01/H/15/2449 | C136: PATIENT WARMER (BLANKET) | D136: 6560 | E136: HSASWIBE26012333 | F136: Dewan Bedah Utama (GOT) | G136: PATIENT WARMER TIDAK PANAS DI MOT (H/15/2449) | H136: NORMAL | I136: 0 days, 0 hrs, 36 mins | J136: 46091.35 | K136: 46112 | L136: =IF(D136>44999.99,100,ROUNDUP((D136/4999.99)*10,-1)) -> 20 | M136: N | N136: =IF(M136="Y",L136,0) -> 0 | P136: N | Q136: =K136-J136+1 -> 21.65 | R136: =WORKDAY(J136,7,'Public Holiday'!$A$2:$A$46) -> 46100 | S136: 0 | T136: =L136*S136 -> 0 | U136: BD, PO 72051 IDS MEDICAL
A137: 7 | B137: KKM/JKN/HSA/10-05-01/H/17/4 | C137: ULTRASOUND SCANNER | D137: 198800 | E137: HSASWIBE26012350 | F137: Jabatan Kecemasan & Trauma (ED) | G137: MESIN UTLRASOUND SCANNER TIDAK BERFUNGSI DENGAN BAIK (GAMBAR TIDAK JELAS) DI REDZONE ED | H137: NORMAL | I137: 0 days, 0 hrs, 40 mins | J137: 46091.388 | K137: 46112 | L137: =IF(D137>44999.99,100,ROUNDUP((D137/4999.99)*10,-1)) -> 100 | M137: N | N137: =IF(M137="Y",L137,0) -> 0 | P137: N | Q137: =K137-J137+1 -> 21.611806 | R137: =WORKDAY(J137,7,'Public Holiday'!$A$2:$A$46) -> 46100 | S137: 0 | T137: =L137*S137 -> 0 | U137: BD, PROBE FAULTY. WAITING INVOICE INFINITY MEDICAL
A138: 8 | B138: KKM/JKN/HSA/10-05-01/H/15/309 | C138: VENTILATOR | D138: 31000 | E138: HSASWIBE26012381 | F138: Jabatan Kecemasan & Trauma (ED) | G138: Asset Name: Transport Ventilator No asset : H/15/309 Description: Unit tidak berfungsi dengan baik Location: ED | H138: NORMAL | I138: 0 days, 0 hrs, 29 mins | J138: 46091.417 | K138: 46112 | L138: =IF(D138>44999.99,100,ROUNDUP((D138/4999.99)*10,-1)) -> 70 | M138: N | N138: =IF(M138="Y",L138,0) -> 0 | P138: N | Q138: =K138-J138+1 -> 21.582639 | R138: =WORKDAY(J138,7,'Public Holiday'!$A$2:$A$46) -> 46100 | S138: 7 | T138: =L138*S138 -> 490 | U138: BD, PRAWSB73640 DRAGER
A139: 9 | B139: KKM/JKN/HSA/10-05-01/H/14/2 | C139: ULTRASOUND SCANNER | D139: 160000 | E139: HSASWIBE26012752 | F139: Dewan Bedah Utama (GOT) | G139: MESIN ULTRASOUND GAMBAR TIDAK KELUAR DI ICU | H139: NORMAL | I139: 0 days, 0 hrs, 30 mins | J139: 46094.349 | K139: 46112 | L139: =IF(D139>44999.99,100,ROUNDUP((D139/4999.99)*10,-1)) -> 100 | M139: N | N139: =IF(M139="Y",L139,0) -> 0 | P139: N | Q139: =K139-J139+1 -> 18.650694 | R139: =WORKDAY(J139,7,'Public Holiday'!$A$2:$A$46) -> 46105 | S139: 4 | T139: =L139*S139 -> 400 | U139: BD, WAIITNG MYLAB ALPHA INVOICE
A140: 10 | B140: KKM/JKN/HSA/10-05-01/H/16/193 | C140: DEFIBRILLATOR | D140: 65000 | E140: HSASWIBE26012814 | F140: JABATAN KECEMASAN DAN TRAUMA | G140: MESIN ZOLL-SPO2 PROBE TIDAK DETECT DI BILIK CDC ED | H140: NORMAL | I140: 0 days, 0 hrs, 30 mins | J140: 46097.38 | K140: 46112 | L140: =IF(D140>44999.99,100,ROUNDUP((D140/4999.99)*10,-1)) -> 100 | M140: N | N140: =IF(M140="Y",L140,0) -> 0 | P140: N | Q140: =K140-J140+1 -> 15.620139 | R140: =WORKDAY(J140,7,'Public Holiday'!$A$2:$A$46) -> 46106 | S140: 0 | T140: =L140*S140 -> 0 | U140: BD, PRF-439 RAPHA MEDICAL, UNIT SEND FOR REPAIR
A141: 11 | B141: KKM/JKN/HSA/10-05-01/25/115 | C141: CONTINUOUS RENAL REPLACEMENT THERAPY | D141: 0 | E141: HSASWIBE26012816 | F141: HDU | G141: H/25/115:MESIN CRRT TIDAK BERFUNGSI DENGAN BAIK DI HEMO | H141: NORMAL | I141: 0 days, 0 hrs, 08 mins | J141: 46097.397 | K141: 46112 | L141: =IF(D141>44999.99,100,ROUNDUP((D141/4999.99)*10,-1)) -> 0 | M141: N | N141: =IF(M141="Y",L141,0) -> 0 | P141: N | Q141: =K141-J141+1 -> 15.602778 | R141: =WORKDAY(J141,7,'Public Holiday'!$A$2:$A$46) -> 46106 | S141: 0 | T141: =L141*S141 -> 0 | U141: RIW, ASET NOT IN CONTRACT
A142: 12 | B142: KKM/JKN/HSA/10-05-01/H/21/187 | C142: CONTINUOUS RENAL REPLACEMENT THERAPY | D142: 117707.5 | E142: HSASWIBE26012935 | F142: Unit Rawatan Rapi (ICU) | G142: MESIN CRRT (H/21/187): DISLAY SYSTEM ERROR BATTERY DI BILIK PERALATAN HDW | H142: NORMAL | I142: 0 days, 0 hrs, 09 mins | J142: 46097.448 | K142: 46112 | L142: =IF(D142>44999.99,100,ROUNDUP((D142/4999.99)*10,-1)) -> 100 | M142: N | N142: =IF(M142="Y",L142,0) -> 0 | P142: N | Q142: =K142-J142+1 -> 15.552083 | R142: =WORKDAY(J142,7,'Public Holiday'!$A$2:$A$46) -> 46106 | S142: 0 | T142: =L142*S142 -> 0 | U142: BD, CLOSE APRIL DUE BATTERY ISSUE
A143: 13 | B143: KKM/JKN/HSA/10-05-01/H/21/264 | C143: ECG MACHINE | D143: 12000 | E143: HSASWIBE26013597 | F143: Jabatan Kecemasan & Trauma (ED) | G143: ECG MACHINE(H/21/264): ECG TIDAK BOLEH PRINT IMAGE DI REDZONE ED | H143: NORMAL | I143: 0 days, 0 hrs, 33 mins | J143: 46098.706 | K143: 46112 | L143: =IF(D143>44999.99,100,ROUNDUP((D143/4999.99)*10,-1)) -> 30 | M143: N | N143: =IF(M143="Y",L143,0) -> 0 | P143: N | Q143: =K143-J143+1 -> 14.29375 | R143: =WORKDAY(J143,7,'Public Holiday'!$A$2:$A$46) -> 46107 | S143: 2 | T143: =L143*S143 -> 60 | U143: BD, QUOTATION QEM40042 EMSTEC MEDICAL RECEIVE 30/3/26
A144: 14 | B144: KKM/JKN/HSA/10-05-01/H/15/566 | C144: ECG (EKG) MACHINE | D144: 10000 | E144: HSASWIBE26013866 | F144: Unit Rawatan Koronari (CCU) | G144: Asset: ECG machine No. Asset: H/15/566 Problem: Printer faulty Location: CCU | H144: NORMAL | I144: 0 days, 0 hrs, 30 mins | J144: 46098.816 | K144: 46112 | L144: =IF(D144>44999.99,100,ROUNDUP((D144/4999.99)*10,-1)) -> 30 | M144: N | N144: =IF(M144="Y",L144,0) -> 0 | P144: N | Q144: =K144-J144+1 -> 14.184028 | R144: =WORKDAY(J144,7,'Public Holiday'!$A$2:$A$46) -> 46107 | S144: 2 | T144: =L144*S144 -> 60 | U144: BD | V144: NO UPDATE
A145: 15 | B145: KKM/JKN/HSA/10-05-01/H/15/2470 | C145: ULTRASOUND SCANNER | D145: 150000 | E145: HSASWIBE26013877 | F145: Jabatan Pengimejan & Diagnostik | G145: MESIN ULTRASOUND TIDAK BOLEH ON DI BILIK ULTRASOUND JABATAN XRAY | H145: NORMAL | I145: 0 days, 0 hrs, 15 mins | J145: 46099.367 | K145: 46112 | L145: =IF(D145>44999.99,100,ROUNDUP((D145/4999.99)*10,-1)) -> 100 | M145: N | N145: =IF(M145="Y",L145,0) -> 0 | P145: N | Q145: =K145-J145+1 -> 13.633333 | R145: =WORKDAY(J145,7,'Public Holiday'!$A$2:$A$46) -> 46108 | S145: 1 | T145: =L145*S145 -> 100 | U145: BD
A146: 16 | B146: KKM/JKN/HSA/10-05-01/H/15/5382 | C146: RO Water Storage Tank | D146: 43000 | E146: HSASWIBE26013880 | F146: Unit Hemodialisis (HDU) | G146: FILTER RO WATER TIDAK FUNCTION DI BILIK RO UNIT HEMODIALISIS | H146: NORMAL | I146: 0 days, 0 hrs, 02 mins | J146: 46099.458 | K146: 46112 | L146: =IF(D146>44999.99,100,ROUNDUP((D146/4999.99)*10,-1)) -> 90 | M146: N | N146: =IF(M146="Y",L146,0) -> 0 | P146: N | Q146: =K146-J146+1 -> 13.541667 | R146: =WORKDAY(J146,7,'Public Holiday'!$A$2:$A$46) -> 46108 | S146: 0 | T146: =L146*S146 -> 0 | U146: BD, PRF-436 PUREMEDITECH
A147: 17 | B147: KKM/JKN/HSA/10-05-01/H/15/4337 | C147: AUTOMATED ENDOSCOPIC WASHER | D147: 92000 | E147: HSASWIBE26014203 | F147: Unit Rawatan Perubatan Harian | G147: MESIN ENDOSCOPIC KELUAR E-14 DI BILIK CUCI DAYCARE (H/15/4337) | H147: NORMAL | I147: 0 days, 0 hrs, 25 mins | J147: 46099.651 | K147: 46112 | L147: =IF(D147>44999.99,100,ROUNDUP((D147/4999.99)*10,-1)) -> 100 | M147: N | N147: =IF(M147="Y",L147,0) -> 0 | P147: N | Q147: =K147-J147+1 -> 13.349306 | R147: =WORKDAY(J147,7,'Public Holiday'!$A$2:$A$46) -> 46108 | S147: 0 | T147: =L147*S147 -> 0 | U147: BD, UNDER TROUBLESHOOTING BY OLYMPUS
A148: 18 | B148: KKM/JKN/HSA/10-05-01/H/21/68 | C148: SYRINGE INFUSION PUMP | D148: 2800 | E148: HSASWIBE26014408 | F148: Unit Rawatan Rapi (ICU) | G148: SYRINGE PUMP DISPLAY SYRINGE EMPTY DI ICU (H/21/68) | H148: NORMAL | I148: 0 days, 0 hrs, 15 mins | J148: 46100.499 | K148: 46112 | L148: =IF(D148>44999.99,100,ROUNDUP((D148/4999.99)*10,-1)) -> 10 | M148: N | N148: =IF(M148="Y",L148,0) -> 0 | P148: N | Q148: =K148-J148+1 -> 12.501389 | R148: =WORKDAY(J148,7,'Public Holiday'!$A$2:$A$46) -> 46111 | S148: 0 | T148: =L148*S148 -> 0 | U148: BD | V148: SAZLIN
A149: 19 | B149: KKM/JKN/HSA/10-05-01/H/15/652 | C149: EXTERNAL PACEMAKER | D149: 9900 | E149: HSASWIBE26014435 | F149: Unit Rawatan Koronari (CCU) | G149: Pacer not functioning di CCU H/15/652 | H149: NORMAL | I149: 0 days, 0 hrs, 15 mins | J149: 46102.606 | K149: 46112 | L149: =IF(D149>44999.99,100,ROUNDUP((D149/4999.99)*10,-1)) -> 20 | M149: N | N149: =IF(M149="Y",L149,0) -> 0 | P149: N | Q149: =K149-J149+1 -> 10.394444 | R149: =WORKDAY(J149,7,'Public Holiday'!$A$2:$A$46) -> 46112 | S149: 0 | T149: =L149*S149 -> 0 | U149: BD | V149: SAZLIN
A150: 20 | B150: KKM/JKN/HSA/10-05-01/H/15/653 | C150: TRANSCUTANEOUS/DEFIBRILLATOR PACER ANALYZER | D150: 9900 | E150: HSASWIBE26014436 | F150: Unit Rawatan Koronari (CCU) | G150: Pacer not functioning di CCU H/15/653 | H150: NORMAL | I150: 0 days, 0 hrs, 10 mins | J150: 46102.606 | K150: 46112 | L150: =IF(D150>44999.99,100,ROUNDUP((D150/4999.99)*10,-1)) -> 20 | M150: N | N150: =IF(M150="Y",L150,0) -> 0 | P150: N | Q150: =K150-J150+1 -> 10.39375 | R150: =WORKDAY(J150,7,'Public Holiday'!$A$2:$A$46) -> 46112 | S150: 0 | T150: =L150*S150 -> 0 | U150: BD | V150: SAZLIN
A151: 21 | B151: KKM/JKN/HAS/10-05-01/H/15/1119 | C151: DENTAL CHAIR | D151: 69000 | E151: HSASWIBE26014462 | F151: Klinik Bedah Mulut & Klinik Pergigian Pediatrik | G151: 4 PCS HANDPIECE DENTAL CHAIR TIDAK BERFUNGAI DI KLINIK DENTAL (H/15/1119) | H151: NORMAL | I151: 0 days, 0 hrs, 25 mins | J151: 46105.397 | K151: 46112 | L151: =IF(D151>44999.99,100,ROUNDUP((D151/4999.99)*10,-1)) -> 100 | M151: N | N151: =IF(M151="Y",L151,0) -> 0 | P151: N | Q151: =K151-J151+1 -> 7.6027778 | R151: =WORKDAY(J151,7,'Public Holiday'!$A$2:$A$46) -> 46114 | S151: 0 | T151: =L151*S151 -> 0 | U151: BD. Unit still function. Accessories only. | V151: ZUWA
A152: 22 | B152: KKM/JKN/HSA/10-05-01/H/15/802 | C152: SYRINGE INFUSION PUMP | D152: 4300 | E152: HSASWIBE26014495 | F152: Unit Rawatan Rapi Neonatal (NICU) | G152: Desc: syringe pump No asset: H/15/802 Problem: Force sensor error Location: NICU | H152: NORMAL | I152: 0 days, 0 hrs, 10 mins | J152: 46106.743 | K152: 46112 | L152: =IF(D152>44999.99,100,ROUNDUP((D152/4999.99)*10,-1)) -> 10 | M152: N | N152: =IF(M152="Y",L152,0) -> 0 | P152: N | Q152: =K152-J152+1 -> 6.2569444 | R152: =WORKDAY(J152,7,'Public Holiday'!$A$2:$A$46) -> 46115 | S152: 0 | T152: =L152*S152 -> 0 | U152: BD, WAITING QUOTATION GLOBAL HEALTHCARE | V152: IZZAH
A153: 23 | B153: KKM/JKN/HSA/10-05-01/H/15/2250 | C153: SYRINGE INFUSION PUMP | D153: 2700 | E153: HSASWIBE26014496 | F153: WAD 8A (Wad Obstetrik & Ginekologi 8A) | G153: Desc: syringe pump No asset: H/15/2250 Problem: carrier kit faulty Location: ward 8A | H153: NORMAL | I153: 0 days, 0 hrs, 25 mins | J153: 46106.747 | K153: 46112 | L153: =IF(D153>44999.99,100,ROUNDUP((D153/4999.99)*10,-1)) -> 10 | M153: N | N153: =IF(M153="Y",L153,0) -> 0 | P153: N | Q153: =K153-J153+1 -> 6.2534722 | R153: =WORKDAY(J153,7,'Public Holiday'!$A$2:$A$46) -> 46115 | S153: 0 | T153: =L153*S153 -> 0 | U153: BD, WAITING QUOTATION GLOBAL HEALTHCARE | V153: REEN
A154: 24 | B154: KKM/JKN/HSA/10-05-01/H/15/1585 | C154: WARMING UNITS, PATIENT, RADIANT, INFANT | D154: 24000 | E154: HSASWIBE26014515 | F154: Dewan Bedah Bersalin (MOT) | G154: BABY WARMER DISPLAY ERROR & TIDAK PANAS DI OT 3 GOT | H154: NORMAL | I154: 0 days,1 hrs, 08 mins | J154: 46107.536 | K154: 46112 | L154: =IF(D154>44999.99,100,ROUNDUP((D154/4999.99)*10,-1)) -> 50 | M154: N | N154: =IF(M154="Y",L154,0) -> 0 | P154: N | Q154: =K154-J154+1 -> 5.4638889 | R154: =WORKDAY(J154,7,'Public Holiday'!$A$2:$A$46) -> 46118 | S154: 0 | T154: =L154*S154 -> 0 | U154: BD, PO 71818 DRAEGER | V154: SYAMSUL
A155: 25 | B155: KKM/JKN/HSA/10-05-01/H/15/1181 | C155: INFUSION PUMP | D155: 7245 | E155: HSASWIBE26014516 | F155: Unit Rawatan Koronari (CCU) | G155: MESIN DROPMATE DISPLAY KEYBOARD DI KAUNTER NURSE WAD CCU (H/15/1181) | H155: NORMAL | I155: 0 days, 0 hrs, 25 mins | J155: 46107.578 | K155: 46112 | L155: =IF(D155>44999.99,100,ROUNDUP((D155/4999.99)*10,-1)) -> 20 | M155: N | N155: =IF(M155="Y",L155,0) -> 0 | P155: N | Q155: =K155-J155+1 -> 5.4215278 | R155: =WORKDAY(J155,7,'Public Holiday'!$A$2:$A$46) -> 46118 | S155: 0 | T155: =L155*S155 -> 0 | U155: BD
A156: 26 | B156: KKM/JKN/HSA/10-05-01/H/21/83 | C156: VENTILATOR | D156: 105000 | E156: HSASWIBE26014520 | F156: Unit Rawatan Rapi (ICU) | G156: VENTILATOR LEAKING & VALVE FAILED DI ICU (H/21/83) | H156: NORMAL | I156: 0 days, 0 hrs, 50 mins | J156: 46107.665 | K156: 46112 | L156: =IF(D156>44999.99,100,ROUNDUP((D156/4999.99)*10,-1)) -> 100 | M156: N | N156: =IF(M156="Y",L156,0) -> 0 | P156: N | Q156: =K156-J156+1 -> 5.3354167 | R156: =WORKDAY(J156,7,'Public Holiday'!$A$2:$A$46) -> 46118 | S156: 0 | T156: =L156*S156 -> 0 | U156: BD
A157: 27 | B157: KKM/JKN/HSA/10-05-01/H/23/6 | C157: ULTRASOUND SCANNER | D157: 149800 | E157: HSASWIBE26014845 | F157: Klinik Obstetrik Ginekologi (O&G CLINIC) | G157: Asset Name: Ultrasound No asset : H/23/6 Description: gambar tidak jelas Loc : klinik ong | H157: NORMAL | I157: 0 days, 0 hrs, 15 mins | J157: 46108.863 | K157: 46112 | L157: =IF(D157>44999.99,100,ROUNDUP((D157/4999.99)*10,-1)) -> 100 | M157: N | N157: =IF(M157="Y",L157,0) -> 0 | P157: N | Q157: =K157-J157+1 -> 4.1368056 | R157: =WORKDAY(J157,7,'Public Holiday'!$A$2:$A$46) -> 46119 | S157: 0 | T157: =L157*S157 -> 0 | U157: BD
A158: 28 | B158: KKM/JKN/HSA/10-05-01/H/15/1582 | C158: INFANT WARMER (RADIANT) | D158: 24000 | E158: HSASWIBE26015193 | F158: Dewan Bersalin (LDU) | G158: INFANT WARMER (H/15/1582): DISPLAY ERROR 5 DI LABOUR ROOM | H158: NORMAL | I158: 0 days, 1 hrs, 40 mins | J158: 46111.569 | K158: 46112 | L158: =IF(D158>44999.99,100,ROUNDUP((D158/4999.99)*10,-1)) -> 50 | M158: N | N158: =IF(M158="Y",L158,0) -> 0 | P158: N | Q158: =K158-J158+1 -> 1.4305556 | R158: =WORKDAY(J158,7,'Public Holiday'!$A$2:$A$46) -> 46120 | S158: 0 | T158: =L158*S158 -> 0 | U158: BD
A159: 29 | B159: KKM/JKN/HSA/10-05-01/H/15/475 | C159: INFANT INCUBATOR | D159: 24000 | E159: HSASWIBE26015251 | F159: Unit Rawatan Rapi Neonatal (NICU) | G159: INFANT INCUBATOR (H/15/475): DISPLAY MOTOR FAILER DI NICU | H159: NORMAL | I159: 0 days, 0 hrs, 25 mins | J159: 46111.649 | K159: 46112 | L159: =IF(D159>44999.99,100,ROUNDUP((D159/4999.99)*10,-1)) -> 50 | M159: N | N159: =IF(M159="Y",L159,0) -> 0 | P159: N | Q159: =K159-J159+1 -> 1.3506944 | R159: =WORKDAY(J159,7,'Public Holiday'!$A$2:$A$46) -> 46120 | S159: 0 | T159: =L159*S159 -> 0 | U159: BD
A160: 30 | B160: KKM/JKN/HSA/10-05-01/H/15/3629 | C160: INFANT VENTILATOR | D160: 53000 | E160: HSASWIBE26016109 | F160: Unit Rawatan Rapi Neonatal (NICU) | G160: MESIN DEFIB: PRINTER TAK KELUAR DI RESAS 1 REDZONE ED (H/15/3629) | H160: NORMAL | I160: 0 days, 0 hrs, 33 mins | J160: 46112.665 | K160: 46112 | L160: =IF(D160>44999.99,100,ROUNDUP((D160/4999.99)*10,-1)) -> 100 | M160: N | N160: =IF(M160="Y",L160,0) -> 0 | P160: N | Q160: =K160-J160+1 -> 0.33541667 | R160: =WORKDAY(J160,7,'Public Holiday'!$A$2:$A$46) -> 46121 | S160: 0 | T160: =L160*S160 -> 0 | U160: BD
A161: 31 | B161: KKM/JKN/HSA/10-05-01/H/15/3661 | C161: DEFIBRILLATOR W/INTERNAL/EXT PADDLES/PACEMAKER | D161: 14250 | E161: HSASWIBE26016110 | F161: Jabatan Kecemasan & Trauma (ED) | G161: MESIN DEFIB TIDAK BERFUNGSI DENGAN BAIK DI RESAS 2 REDZONE ED (H/15/11553) | H161: NORMAL | I161: 0 days, 0 hrs, 30 mins | J161: 46112.666 | K161: 46112 | L161: =IF(D161>44999.99,100,ROUNDUP((D161/4999.99)*10,-1)) -> 30 | M161: N | N161: =IF(M161="Y",L161,0) -> 0 | P161: N | Q161: =K161-J161+1 -> 0.33402778 | R161: =WORKDAY(J161,7,'Public Holiday'!$A$2:$A$46) -> 46121 | S161: 0 | T161: =L161*S161 -> 0 | U161: BD
A162: 32 | B162: KKM/JKN/HSA/10-05-01/H/21/140 | C162: Ventilators, Intensive Care, Neonatal/Pediatric | D162: 26000 | E162: HSASWIBE26012034 | F162: Wad Pediatrik | G162: Asset Name: Infant Ventilator No asset : H/21/140 Description: replace inlet filter Location: Wad 12 | H162: NORMAL | I162: 0 days, hrs, 51 mins | J162: 46085.715 | K162: 46112 | L162: =IF(D162>44999.99,100,ROUNDUP((D162/4999.99)*10,-1)) -> 60 | M162: N | N162: =IF(M162="Y",L162,0) -> 0 | P162: N | Q162: =K162-J162+1 -> 27.285417 | R162: =WORKDAY(J162,7,'Public Holiday'!$A$2:$A$46) -> 46094 | S162: 0 | T162: =L162*S162 -> 0 | U162: CLOSE APRIL, PARTS ARRIVE 13/4/26
A163: Previous Month (Workorder Closed)
A164: 1 | B164: KKM/JKN/HSA/10-05-01/H/20/129 | C164: INFUSION PUMP | D164: 3150 | E164: HSASWIBE26001426 | F164: WAD 12 (Paediatric Ward) | G164: PINTU MESIN INFUSION PUMP TIDAK BOLEH TUTUP RAPAT DI KAUNTER NURSE WAD 12 (H/20/129) | H164: Normal | I164: 0 days, 0 hrs, 08 mins | J164: 46031 | K164: 46112 | L164: =IF(D164>44999.99,100,ROUNDUP((D164/4999.99)*10,-1)) -> 10 | M164: N | N164: =IF(M164="Y",L164,0) -> 0 | P164: N | Q164: =K164-J164+1 -> 82 | R164: =WORKDAY(J164,6,'Public Holiday'!$A$2:$A$46) -> 46041 | S164: 0 | T164: =L164*S164 -> 0 | U164: CLOSE
A165: 2 | B165: =VLOOKUP(E:E,[1]CM!B:M,12,FALSE) -> KKM/JKN/HSA/10-05-01/H/23/54 | C165: Warming Units, Patient, Radiant, Infant | D165: =VLOOKUP(B:B,'[2]BEMS EQUIPMENT '!$E:$Q,13,FALSE) -> 19266 | E165: HSASWIBE26003624 | F165: WAD 8A (Wad Obstetrik & Ginekologi 8A) | G165: warmer di wad 8A. asset number : H/23/54. heater road faulty | H165: Normal | I165: 0 days, 1 hrs, 3 mins | J165: 46037 | K165: 46112 | L165: =IF(D165>44999.99,100,ROUNDUP((D165/4999.99)*10,-1)) -> 40 | M165: N | N165: =IF(M165="Y",L165,0) -> 0 | P165: N | Q165: =K165-J165+1 -> 76 | R165: =WORKDAY(J165,7,'Public Holiday'!$A$2:$A$46) -> 46048 | S165: 0 | T165: =L165*S165 -> 0 | U165: CLOSE
A166: 3 | B166: KKM/JKN/HSA/10-05-01/H/22/142 | C166: PATIENT MONITORING EQUIP | D166: 22500 | E166: HSASWIBE26004037 | F166: LEVEL 6 (Wad Multidisiplin Perempuan) | G166: (H/22/142):MESIN BP TIDAK BERFUNGSI DENGAN BAIK DI KATIL 26 WAD LEVEL 6 | H166: Normal | I166: 0 days, 0 hrs, 18 mins | J166: 46048 | K166: 46084 | L166: =IF(D166>44999.99,100,ROUNDUP((D166/4999.99)*10,-1)) -> 50 | M166: N | N166: =IF(M166="Y",L166,0) -> 0 | P166: N | Q166: =K166-J166+1 -> 37 | R166: =WORKDAY(J166,6,'Public Holiday'!$A$2:$A$46) -> 46056 | S166: 0 | T166: =L166*S166 -> 0 | U166: CLOSE
A167: 4 | B167: KKM/JKN/HSA/10-05-01/R/23/8 | C167: PORTABLE FETAL DOPPLER | D167: 1700 | E167: HSASWIBE26004022 | F167: Klinik Obstetrik Ginekologi (O&G CLINIC) | G167: PORTABLE FETAL DOPPLER(R/23/8): MESIN SCAN SETTING PROBLEM DI BILIK DOKTOR PAC 3 | H167: Normal | I167: 0 days, 0 hrs, 06 mins | J167: 46048 | K167: 46085 | L167: =IF(D167>44999.99,100,ROUNDUP((D167/4999.99)*10,-1)) -> 10 | M167: N | N167: =IF(M167="Y",L167,0) -> 0 | P167: N | Q167: =K167-J167+1 -> 38 | R167: =WORKDAY(J167,6,'Public Holiday'!$A$2:$A$46) -> 46056 | S167: 0 | T167: =L167*S167 -> 0 | U167: CLOSE
A168: 5 | B168: KKM/JKN/HSA/10-05-01/H/15/2249 | C168: SYRINGE INFUSION PUMP | D168: 2700 | E168: HSASWIBE26004034 | F168: WAD 8A (Wad Obstetrik & Ginekologi 8A) | G168: SYRINGE INFUSION PUMP (H/15/249): BATTERY TIDAK MASUK CHARGE DI WAD 8A | H168: Normal | I168: 0 days, 0 hrs, 07 mins | J168: 46048 | K168: 46111 | L168: =IF(D168>44999.99,100,ROUNDUP((D168/4999.99)*10,-1)) -> 10 | M168: N | N168: =IF(M168="Y",L168,0) -> 0 | P168: N | Q168: =K168-J168+1 -> 64 | R168: =WORKDAY(J168,6,'Public Holiday'!$A$2:$A$46) -> 46056 | S168: 0 | T168: =L168*S168 -> 0 | U168: CLOSE
A169: 6 | B169: =VLOOKUP(E:E,[1]CM!B:M,12,FALSE) -> KKM/JKN/HSA/10-05-01/H/15/1634 | C169: =VLOOKUP(B:B,'[3]SCHEDULE PPM 2026'!$D:$E,2,FALSE) -> MESIN HEMODIALYSIS | D169: =VLOOKUP(B:B,'[2]BEMS EQUIPMENT '!$E:$Q,13,FALSE) -> 36300 | E169: HSASWIBE26004351 | F169: =VLOOKUP(B:B,'[3]SCHEDULE PPM 2026'!$D:$O,12,FALSE) -> Unit Hemodialisis (HDU) | G169: Asset Name: haemodialysis machine No asset : H/15/1634 Description: battery error Location: HDU | H169: Normal | I169: 0 days, 0 hrs, 32 mins | J169: 46049 | K169: 46105 | L169: =IF(D169>44999.99,100,ROUNDUP((D169/4999.99)*10,-1)) -> 80 | M169: N | N169: =IF(M169="Y",L169,0) -> 0 | P169: N | Q169: =K169-J169+1 -> 57 | R169: =WORKDAY(J169,7,'Public Holiday'!$A$2:$A$46) -> 46058 | S169: 0 | T169: =L169*S169 -> 0 | U169: CLOSE
A170: 7 | B170: H/15/5382 | C170: Water Purification Systems, Reverse Osmosis | D170: 125000 | E170: HSASWIBE26006125 | F170: Unit Hemodialisis | G170: 2 UNIT REVERSE OSMOSIS BED WASHER TIDAK BERFUNGSI DENGAN BAIK DI UNIT HEMODIALISIS (HSAS10256) | H170: Normal | I170: 0 days, 0 hrs, 2 mins | J170: 46052 | K170: 46100 | L170: =IF(D170>44999.99,100,ROUNDUP((D170/4999.99)*10,-1)) -> 100 | M170: N | N170: =IF(M170="Y",L170,0) -> 0 | P170: N | Q170: =K170-J170+1 -> 49 | R170: =WORKDAY(J170,7,'Public Holiday'!$A$2:$A$46) -> 46063 | S170: 0 | T170: =L170*S170 -> 0 | U170: CLOSE
A171: 8 | B171: KKM/JKN/HSA/10-05-01/H/15/4298 | C171: MONITOR ANTEPARTUM W/INTEGRAL PRINTER | D171: 10200 | E171: HSASWIBE26006119 | F171: Dewan Bersalin (LDU) | G171: MESIN CTG TIDAK BERFUNGSI DENGAN BAIK (WAYAR HAMPIR TERCABUT) DI RUANG PENILAIAN 2 PAC 4 | H171: Normal | I171: 0 days, 1 hrs, 52 mins | J171: 46052 | K171: 46111 | L171: =IF(D171>44999.99,100,ROUNDUP((D171/4999.99)*10,-1)) -> 30 | M171: N | N171: =IF(M171="Y",L171,0) -> 0 | P171: N | Q171: =K171-J171+1 -> 60 | R171: =WORKDAY(J171,6,'Public Holiday'!$A$2:$A$46) -> 46062 | S171: 0 | T171: =L171*S171 -> 0 | U171: CLOSE
A172: 9 | B172: KKM/JKN/HSA/10-05-01/H/15/4038 | C172: DIALYZER REPROCESSING UNIT | D172: 48000 | E172: HSASWIBE26006579 | F172: UNIT HEMODIALISIS | G172: MESIN DIALYZER REPROSESSING UNIT TIDAK BERFUNGSI DI HEMODIALISIS (H/15/4038) | H172: Normal | I172: 0 days, 0 hrs, 16 mins | J172: 46057 | K172: 46112 | L172: =IF(D172>44999.99,100,ROUNDUP((D172/4999.99)*10,-1)) -> 100 | M172: N | N172: =IF(M172="Y",L172,0) -> 0 | P172: N | Q172: =K172-J172+1 -> 56 | R172: =WORKDAY(J172,7,'Public Holiday'!$A$2:$A$46) -> 46066 | S172: 0 | T172: =L172*S172 -> 0 | U172: CLOSE
A173: 10 | B173: KKM/JKN/HSA/10-05-01/H/16/69 | C173: FUNDUS CAMERA | D173: 99000 | E173: HSASWIBE26006885 | F173: KLINIK OFTALMOLOGI | G173: MESIN FUNDUS CAMERA POWER ERROR DI BILIK 3 KLINIK OFTAL (H/16/69) | H173: Normal | I173: 0 days, 0 hrs, 21 mins | J173: 46058 | K173: 46083 | L173: =IF(D173>44999.99,100,ROUNDUP((D173/4999.99)*10,-1)) -> 100 | M173: N | N173: =IF(M173="Y",L173,0) -> 0 | P173: N | Q173: =K173-J173+1 -> 26 | R173: =WORKDAY(J173,7,'Public Holiday'!$A$2:$A$46) -> 46069 | S173: 0 | T173: =L173*S173 -> 0 | U173: CLOSE
A174: 11 | B174: KKM/JKN/HSA/10-05-01/H/18/136 | C174: PATIENT MONITORING EQUIP.(AUTOMATIC MULTIPARAMETER) | D174: 9000 | E174: HSASWIBE26006899 | F174: JABATAN KECEMASAN & TRAUMA | G174: Asset Name: Ventilator No asset : H/18/136 Description: Expiratory flow sensor and oxygen sensor failure Location: ED | H174: Normal | I174: 0 days, 0 hrs, 15 mins | J174: 46058 | K174: 46086 | L174: =IF(D174>44999.99,100,ROUNDUP((D174/4999.99)*10,-1)) -> 20 | M174: N | N174: =IF(M174="Y",L174,0) -> 0 | P174: N | Q174: =K174-J174+1 -> 29 | R174: =WORKDAY(J174,7,'Public Holiday'!$A$2:$A$46) -> 46069 | S174: 0 | T174: =L174*S174 -> 0 | U174: CLOSE
A175: 12 | B175: KKM/JKN/HSA/10-05-01/H/21/104 | C175: INFANT VENTILATOR | D175: 130000 | E175: HSASWIBE26006920 | F175: UNIT RAWATAN RAPI NEONATAL (NICU) | G175: CABLE FLOW SENSOR VENTILATOR TIDAK BERFUNGSI DI BILIK RHU WAD NICU (H/21/104) | H175: Normal | I175: 0 days, 0 hrs, 34 mins | J175: 46059 | K175: 46096 | L175: =IF(D175>44999.99,100,ROUNDUP((D175/4999.99)*10,-1)) -> 100 | M175: N | N175: =IF(M175="Y",L175,0) -> 0 | P175: N | Q175: =K175-J175+1 -> 38 | R175: =WORKDAY(J175,7,'Public Holiday'!$A$2:$A$46) -> 46072 | S175: 0 | T175: =L175*S175 -> 0 | U175: CLOSE
A176: 13 | B176: KKM/JKN/HSA/10-05-01/H/15/949 | C176: Electrocardiographs, Multichannel, Interpretative | D176: 10000 | E176: HSASWIBE26007765 | F176: UNIT RAWATAN KORONARI (CCU) | G176: MONITOR PATIENT TIDAK BOLEH LINK DENGAN ECG DI KATIL 6 CCU | H176: Normal | I176: 0 days, 0 hrs, 52 mins | J176: 46065 | K176: 46083 | L176: =IF(D176>44999.99,100,ROUNDUP((D176/4999.99)*10,-1)) -> 30 | M176: N | N176: =IF(M176="Y",L176,0) -> 0 | P176: N | Q176: =K176-J176+1 -> 19 | R176: =WORKDAY(J176,7,'Public Holiday'!$A$2:$A$46) -> 46078 | S176: 0 | T176: =L176*S176 -> 0 | U176: CLOSE
A177: 14 | B177: KKM/JKN/HSA/10-05-01/H/16/51 | C177: TISSUE PROCESSOR | D177: 159800 | E177: HSASWIBE26008488 | F177: JABATAN PATOLOGI | G177: TISSUE PROCESSOR LEVEL SENSOR ERROR DI MAKMAL HISTO PATOLOGI (H/16/51) | H177: Normal | I177: 0 days, 0 hrs, 22 mins | J177: 46066 | K177: 46093 | L177: =IF(D177>44999.99,100,ROUNDUP((D177/4999.99)*10,-1)) -> 100 | M177: N | N177: =IF(M177="Y",L177,0) -> 0 | P177: N | Q177: =K177-J177+1 -> 28 | R177: =WORKDAY(J177,7,'Public Holiday'!$A$2:$A$46) -> 46079 | S177: 0 | T177: =L177*S177 -> 0 | U177: CLOSE
A178: 15 | B178: KKM/JKN/HSA/10-05-01/H/15/684 | C178: SYRINGE INFUSION PUMP | D178: 4300 | E178: HSASWIBE26009013 | F178: HIGH DEPENDENCY WARD (HDW) | G178: SYRINGE PUMP TIDAK BOLEH INSTALL DI ICU (H/15/684) | H178: Normal | I178: 0 days, 0 hrs, 07 mins | J178: 46076 | K178: 46084 | L178: =IF(D178>44999.99,100,ROUNDUP((D178/4999.99)*10,-1)) -> 10 | M178: N | N178: =IF(M178="Y",L178,0) -> 0 | P178: N | Q178: =K178-J178+1 -> 9 | R178: =WORKDAY(J178,7,'Public Holiday'!$A$2:$A$46) -> 46085 | S178: 0 | T178: =L178*S178 -> 0 | U178: CLOSE
A179: 16 | B179: KKM/JKN/HSA/10-05-01/H/15/727 | C179: SYRINGE INFUSION PUMP | D179: 4300 | E179: HSASWIBE26009014 | F179: UNIT RAWATAN RAPI (ICU) | G179: SYRINGE PUMP TIDAK BOLEH INSTALL DI ICU (H/15/727) | H179: Normal | I179: 0 days, 0 hrs, 06 mins | J179: 46076 | K179: 46084 | L179: =IF(D179>44999.99,100,ROUNDUP((D179/4999.99)*10,-1)) -> 10 | M179: N | N179: =IF(M179="Y",L179,0) -> 0 | P179: N | Q179: =K179-J179+1 -> 9 | R179: =WORKDAY(J179,7,'Public Holiday'!$A$2:$A$46) -> 46085 | S179: 0 | T179: =L179*S179 -> 0 | U179: CLOSE
A180: 17 | B180: KKM/JKN/HSA/10-05-01/H/20/56 | C180: ECG MACHINE | D180: 13000 | E180: HSASWIBE26011740 | F180: WAD 9B - PEMBEDAHAN PEREMPUAN | G180: 1. asset: ecg No asset: H/20/56 SN:SK-93017607 Problem: Battery depleated Model: BENEHEART R3A Location: wad 9B | H180: Normal | I180: 0 days, 0 hrs, 05 mins | J180: 46080 | K180: 46096 | L180: =IF(D180>44999.99,100,ROUNDUP((D180/4999.99)*10,-1)) -> 30 | M180: N | N180: =IF(M180="Y",L180,0) -> 0 | P180: N | Q180: =K180-J180+1 -> 17 | R180: =WORKDAY(J180,7,'Public Holiday'!$A$2:$A$46) -> 46091 | S180: 0 | T180: =L180*S180 -> 0 | U180: CLOSE
A181: 18 | B181: KKM/JKN/HSA/10-05-01/H/21/291 | C181: Phototherapy Units, Visible Light, Hyperbilirubinemia | D181: 7100 | E181: HSASWIBE26002320 | F181: Unit Rawatan Rapi Neonatal (NICU) | G181: LAMPU FOTOLIGHT TIDAK MENYALA DI NICU (H/21/291) | H181: Normal | I181: 0 days, 0 hrs, 47 mins | J181: 46034 | K181: 46082 | L181: =IF(D181>44999.99,100,ROUNDUP((D181/4999.99)*10,-1)) -> 20 | M181: N | N181: =IF(M181="Y",L181,0) -> 0 | P181: N | Q181: =K181-J181+1 -> 49 | R181: =WORKDAY(J181,7,'Public Holiday'!$A$2:$A$46) -> 46043 | S181: 0 | T181: =L181*S181 -> 0 | U181: CLOSE
A182: 19 | B182: KKM/JKN/HSA/10-05-01/H/15/4018 | C182: HEMOGLOBIN SYSTEM FOR HBA1C | D182: 67000 | E182: HSASWIBE26003468 | F182: PATHOLOGY | G182: PRIMUS PDQ HBA1C (H/15/4018)- PINTU TIDAK BOLEH TUTUP-DOOR ERROR DI LAB BIOCHEM PATOLOGI | H182: Normal | I182: 0 days, 0 hrs, 14 mins | J182: 46036 | K182: 46108 | L182: =IF(D182>44999.99,100,ROUNDUP((D182/4999.99)*10,-1)) -> 100 | M182: N | N182: =IF(M182="Y",L182,0) -> 0 | P182: N | Q182: =K182-J182+1 -> 73 | R182: =WORKDAY(J182,6,'Public Holiday'!$A$2:$A$46) -> 46044 | S182: 0 | T182: =L182*S182 -> 0 | U182: CLOSE
A183: 20 | B183: KKM/JKN/HSA/10-05-01/H/21/339 | C183: VENTILATOR (NEONATAL) | D183: 137000 | E183: HSASWIBE26003621 | F183: Unit Rawatan Rapi Neonatal (NICU) | G183: VENTILATOR NEONATAL (H/21/339) :CABLE FLOW SENSOR ROSAK DI NICU | H183: Normal | I183: 0 days, 0 hrs, 15 mins | J183: 46037 | K183: 46097 | L183: =IF(D183>44999.99,100,ROUNDUP((D183/4999.99)*10,-1)) -> 100 | M183: N | N183: =IF(M183="Y",L183,0) -> 0 | P183: Y | Q183: =K183-J183+1 -> 61 | R183: =WORKDAY(J183,6,'Public Holiday'!$A$2:$A$46) -> 46045 | S183: 0 | T183: =L183*S183 -> 0 | U183: CLOSE
A184: 21 | B184: KKM/JKN/HSA/10-05-01/H/15/790 | C184: SYRINGE INFUSION PUMP | D184: 4300 | E184: HSASWIBE26003710 | F184: Unit Rawatan Rapi Neonatal (NICU) | G184: SYRINGE INFUSION PUMP FAULT SENSOR DI NICU (H/15/790) | H184: Normal | I184: 0 days, 1 hrs, 48 mins | J184: 46040 | K184: 46098 | L184: =IF(D184>44999.99,100,ROUNDUP((D184/4999.99)*10,-1)) -> 10 | M184: N | N184: =IF(M184="Y",L184,0) -> 0 | P184: Y | Q184: =K184-J184+1 -> 59 | R184: =WORKDAY(J184,6,'Public Holiday'!$A$2:$A$46) -> 46048 | S184: 0 | T184: =L184*S184 -> 0 | U184: CLOSE
A185: 22 | B185: KKM/JKN/HSA/10-05-01/H/15/2250 | C185: Infusion Pumps, Syringe | D185: 2700 | E185: HSASWIBE26003767 | F185: Wad Obstetrik & Ginekologi 8A | G185: SYRINGE PUMP TIDAK BERFUNGSI DI WAD 8A (H/15/2250) | H185: Normal | I185: 0 days, 0 hrs, 15 mins | J185: 46041 | K185: 46111 | L185: =IF(D185>44999.99,100,ROUNDUP((D185/4999.99)*10,-1)) -> 10 | M185: N | N185: =IF(M185="Y",L185,0) -> 0 | P185: Y | Q185: =K185-J185+1 -> 71 | R185: =WORKDAY(J185,6,'Public Holiday'!$A$2:$A$46) -> 46049 | S185: 0 | T185: =L185*S185 -> 0 | U185: CLOSE
A186: 23 | B186: HSAS10016 | C186: DRILL, SURGICAL, SMALL BONE, PNEUMATIC | D186: 80900 | E186: HSASWIBE26003743 | F186: Dewan Bedah Utama (GOT) | G186: No asset:HSAS10016 Description: surgical drill, small bone Sn: 34144 Problem: hose drill adapter leaking Department: GOT | H186: Normal | I186: 0 days, 0 hrs, 17 mins | J186: 46041 | K186: 46097 | L186: =IF(D186>44999.99,100,ROUNDUP((D186/4999.99)*10,-1)) -> 100 | M186: N | N186: =IF(M186="Y",L186,0) -> 0 | P186: Y | Q186: =K186-J186+1 -> 57 | R186: =WORKDAY(J186,6,'Public Holiday'!$A$2:$A$46) -> 46049 | S186: 0 | T186: =L186*S186 -> 0 | U186: CLOSE
A187: 24 | B187: =VLOOKUP(E:E,[1]CM!B:M,12,FALSE) -> KKM/JKN/HSA/10-05-01/H/15/5043 | C187: =VLOOKUP(B:B,'[3]SCHEDULE PPM 2026'!$D:$E,2,FALSE) -> ECG (EKG) MACHINE | D187: =VLOOKUP(B:B,'[2]BEMS EQUIPMENT '!$E:$Q,13,FALSE) -> 2750 | E187: HSASWIBE26006443 | F187: =VLOOKUP(B:B,'[3]SCHEDULE PPM 2026'!$D:$O,12,FALSE) -> LEVEL 6 (Wad Multidisiplin Perempuan) | G187: Asset: ECG machine No asset: H/15/5043 Sn: SCT11486306PA Problem: ECG machine not functioning Location: Ward 6 | H187: Normal | I187: 0 days, 0 hrs, 10 mins | J187: 46052 | K187: 46085 | L187: =IF(D187>44999.99,100,ROUNDUP((D187/4999.99)*10,-1)) -> 10 | M187: N | N187: =IF(M187="Y",L187,0) -> 0 | P187: N | Q187: =K187-J187+1 -> 34 | R187: =WORKDAY(J187,7,'Public Holiday'!$A$2:$A$46) -> 46063 | S187: 0 | T187: =L187*S187 -> 0 | U187: CLOSE
A188: 25 | B188: KKM/JKN/HSA/10-05-01/H/15/1639 | C188: MESIN HEMODIALYSIS | D188: 36300 | E188: HSASWIBE26004038 | F188: Unit Hemodialisis (HDU) | G188: MESIN HEMODIALISIS (H/15/1639): PUMP ON/OFF, CONDUCTIVITY DAN TIDAK BOLEH DISINFECT DI UNIT HEMO | H188: Normal | I188: 0 days, 0 hrs, 04 mins | J188: 46048 | K188: 46105 | L188: =IF(D188>44999.99,100,ROUNDUP((D188/4999.99)*10,-1)) -> 80 | M188: N | N188: =IF(M188="Y",L188,0) -> 0 | P188: N | Q188: =K188-J188+1 -> 58 | R188: =WORKDAY(J188,6,'Public Holiday'!$A$2:$A$46) -> 46056 | S188: 0 | T188: =L188*S188 -> 0 | U188: CLOSE
A189: 26 | B189: KKM/JKN/HSA/10-05-01/H/20/56 | C189: ECG (EKG) MACHINE | D189: 6000 | E189: HSASWIBE26007757 | F189: WAD 9B - PEMBEDAHAN PEREMPUAN | G189: MESIN ECG TIDAK BOLEH BACA DI WAD 9B (H/20/56) | H189: Normal | I189: 0 days, 1 hrs, 22 mins | J189: 46065 | K189: 46093 | L189: =IF(D189>44999.99,100,ROUNDUP((D189/4999.99)*10,-1)) -> 20 | M189: N | N189: =IF(M189="Y",L189,0) -> 0 | P189: N | Q189: =K189-J189+1 -> 29 | R189: =WORKDAY(J189,7,'Public Holiday'!$A$2:$A$46) -> 46078 | S189: 0 | T189: =L189*S189 -> 0 | U189: CLOSE
A190: Previous Month (Workorder Open)
A191: 1 | B191: KKM/JKN/HSA/10-05-01/H/23/43 | C191: VIDEO HEAD IMPULSE TEST | D191: 94900.44 | E191: HSASWIBE26006493 | F191: KLINIK OTORINOLARINGOLOGI (ORL) | G191: MESIN VIDEO HEAD TIDAK BERFUNGSI DENGAN BAIK DI BILIK 6 KLINIK ORL (H/23/43) | H191: Normal | I191: 0 days, 1 hrs, 00 mins | J191: 46056 | K191: 46112 | L191: =IF(D191>44999.99,100,ROUNDUP((D191/4999.99)*10,-1)) -> 100 | M191: N | N191: =IF(M191="Y",L191,0) -> 0 | P191: N | Q191: =K191-J191+1 -> 57 | R191: =WORKDAY(J191,7,'Public Holiday'!$A$2:$A$46) -> 46065 | S191: 0 | T191: =L191*S191 -> 0 | U191: BD, PO AWSB 72056 ALLCARE
A192: 2 | B192: KKM/JKN/HSA/10-05-01/H/15/1330 | C192: LIGHT SOURCE | D192: 24700 | E192: HSASWIBE26006580 | F192: DEWAN BEDAH UTAMA (GOT) | G192: SKRU TELESKOP MELEKAT PADA CABLE LIGHT SOURCE DI OT1 GOT | H192: Normal | I192: 0 days, 0 hrs, 11 mins | J192: 46057 | K192: 46112 | L192: =IF(D192>44999.99,100,ROUNDUP((D192/4999.99)*10,-1)) -> 50 | M192: N | N192: =IF(M192="Y",L192,0) -> 0 | P192: N | Q192: =K192-J192+1 -> 56 | R192: =WORKDAY(J192,7,'Public Holiday'!$A$2:$A$46) -> 46066 | S192: 13 | T192: =L192*S192 -> 650 | U192: BD,UNIT SEND OUT TO OLYMPUS, WAITING QUOTATION AND REPORT FROM OLYMPUS
A193: 3 | B193: KKM/JKN/HSA/10-05-01/H/21/251 | C193: VOLUMETRIC PUMP | D193: 2400 | E193: HSASWIBE26006847 | F193: WAD 10A - PERUBATAN LELAKI | G193: VOLUMETRIC PUMP (H/21/251): MESIN DRIP TIDAK BERFUNGSI DENGAN BAIK DI WAD 10A | H193: Normal | I193: 0 days, 0 hrs, 12 mins | J193: 46057 | K193: 46112 | L193: =IF(D193>44999.99,100,ROUNDUP((D193/4999.99)*10,-1)) -> 10 | M193: N | N193: =IF(M193="Y",L193,0) -> 0 | P193: N | Q193: =K193-J193+1 -> 56 | R193: =WORKDAY(J193,7,'Public Holiday'!$A$2:$A$46) -> 46066 | S193: 0 | T193: =L193*S193 -> 0 | U193: BD, PO AWSB 71479 HADRATECH
A194: 4 | B194: KKM/JKN/HSA/10-05-01/H/15/1178 | C194: INFUSION PUMP | D194: 7245 | E194: HSASWIBE26006915 | F194: UNIT RAWATAN KORONARI (CCU) | G194: MESIN INFUSION PUMP TIDAK BERFUNGSI DI WAD CCU (H/15/1178) | H194: Normal | I194: 0 days, 0 hrs, 53 mins | J194: 46059 | K194: 46112 | L194: =IF(D194>44999.99,100,ROUNDUP((D194/4999.99)*10,-1)) -> 20 | M194: N | N194: =IF(M194="Y",L194,0) -> 0 | P194: N | Q194: =K194-J194+1 -> 54 | R194: =WORKDAY(J194,7,'Public Holiday'!$A$2:$A$46) -> 46072 | S194: 0 | T194: =L194*S194 -> 0 | U194: BD,PO AWSB 72140 ARAH BME
A195: 5 | B195: KKM/JKN/HSA/10-05-01/H/20/211 | C195: PHOTOTHERAPY MACHINE (LAMP) | D195: 6500 | E195: HSASWIBE26006919 | F195: UNIT RAWATAN RAPI NEONATAL (NICU) | G195: PHOTOLIGHT TIDAK MENYALA DI BILIK RHU WAD NICU (H/20/211) | H195: Normal | I195: 0 days, 0 hrs, 06 mins | J195: 46059 | K195: 46112 | L195: =IF(D195>44999.99,100,ROUNDUP((D195/4999.99)*10,-1)) -> 20 | M195: N | N195: =IF(M195="Y",L195,0) -> 0 | P195: N | Q195: =K195-J195+1 -> 54 | R195: =WORKDAY(J195,7,'Public Holiday'!$A$2:$A$46) -> 46072 | S195: 13 | T195: =L195*S195 -> 260 | U195: BD, PENDING INVOICE GETZ HEALTHCARE
A196: 6 | B196: KKM/JKN/HSA/10-05-01/H/15/4876 | C196: Lights, Surgical | D196: 82550 | E196: HSASWIBE26006958 | F196: DEWAN BEDAH UTAMA (GOT) | G196: SEMUA OT LIGHT TIDAK MENYALA DI OT 4 GOT | H196: Normal | I196: 0 days, 0 hrs, 06 mins | J196: 46060 | K196: 46112 | L196: =IF(D196>44999.99,100,ROUNDUP((D196/4999.99)*10,-1)) -> 100 | M196: N | N196: =IF(M196="Y",L196,0) -> 0 | P196: N | Q196: =K196-J196+1 -> 53 | R196: =WORKDAY(J196,7,'Public Holiday'!$A$2:$A$46) -> 46072 | S196: 0 | T196: =L196*S196 -> 0 | U196: BD, PENDING QUOTATION UPS (Loaner)
A197: 7 | B197: KKM/JKN/HSA/10-05-01/H/15/5111 | C197: TOURNIQUET PNEUMATIC ONE CUFF | D197: 11396 | E197: HSASWIBE26006963 | F197: DEWAN BEDAH UTAMA (GOT) | G197: TOURNIQUET PNEUMATIC ONE CUFF (H/15/5111): BATTERY NOT DETECTED DI KAUNTER GOT | H197: Normal | I197: 0 days, 0 hrs, 25 mins | J197: 46060 | K197: 46112 | L197: =IF(D197>44999.99,100,ROUNDUP((D197/4999.99)*10,-1)) -> 30 | M197: N | N197: =IF(M197="Y",L197,0) -> 0 | P197: N | Q197: =K197-J197+1 -> 53 | R197: =WORKDAY(J197,7,'Public Holiday'!$A$2:$A$46) -> 46072 | S197: 0 | T197: =L197*S197 -> 0 | U197: close
A198: 8 | B198: KKM/JKN/HSA/10-05-01/H/15/5114 | C198: PUMP ENTERAL FEEDING | D198: 2975 | E198: HSASWIBE26006972 | F198: UNIT RAWATAN RAPI (ICU) | G198: PUMP ENTERAL FEEDING (H/15/5114): CHARGE TIDAK MASUK DI BED 3 ICU | H198: Normal | I198: 0 days, 0 hrs, 30 mins | J198: 46061 | K198: 46112 | L198: =IF(D198>44999.99,100,ROUNDUP((D198/4999.99)*10,-1)) -> 10 | M198: N | N198: =IF(M198="Y",L198,0) -> 0 | P198: N | Q198: =K198-J198+1 -> 52 | R198: =WORKDAY(J198,7,'Public Holiday'!$A$2:$A$46) -> 46072 | S198: 0 | T198: =L198*S198 -> 0 | U198: BD, TA BER 26/010 UNDER REVIEW
A199: 9 | B199: KKM/JKN/HSA/10-05-01/H/23/57 | C199: INFANT WARMER | D199: 19266 | E199: HSASWIBE26007020 | F199: WAD 8B - OBSTETRIK & GINEKOLOGI | G199: WARMER BABY TIDAK BERFUNGSI DI BILIK STOR PERALATAN WAD 8B (H/23/57) | H199: Normal | I199: 0 days, 0 hrs, 06 mins | J199: 46062 | K199: 46112 | L199: =IF(D199>44999.99,100,ROUNDUP((D199/4999.99)*10,-1)) -> 40 | M199: N | N199: =IF(M199="Y",L199,0) -> 0 | P199: N | Q199: =K199-J199+1 -> 51 | R199: =WORKDAY(J199,7,'Public Holiday'!$A$2:$A$46) -> 46073 | S199: 0 | T199: =L199*S199 -> 0 | U199: BD, WAITING PARTS FROM INSAN DAMAI
A200: 10 | B200: KKM/JKN/HSA/10-05-01/H/15/2464 | C200: ULTRASOUND SCANNER | D200: 92700 | E200: HSASWIBE26007740 | F200: UNIT RAWATAN RAPI NEONATAL (NICU) | G200: MESIN ULTRASOUND HANG DI NICU (H/15/2464) | H200: Normal | I200: 0 days, 0 hrs, 15 mins | J200: 46064 | K200: 46112 | L200: =IF(D200>44999.99,100,ROUNDUP((D200/4999.99)*10,-1)) -> 100 | M200: N | N200: =IF(M200="Y",L200,0) -> 0 | P200: N | Q200: =K200-J200+1 -> 49 | R200: =WORKDAY(J200,7,'Public Holiday'!$A$2:$A$46) -> 46077 | S200: 0 | T200: =L200*S200 -> 0 | U200: BD, PO 71658 MAGNA, WAITING SOFTWARE DRIVER
...

Sheet B3-SCHEDULED
A3: MINISTRY OF HEALTH
A4: Deduction Mapping Report Biomedical Engineering Maintenance Services (BEMS)
B5: INDICATOR B.3 SCHEDULED MAINTENANCE
B7: HOSPITAL NAME : | C7: HOSPITAL SHAH ALAM | H7: MONTH/YEAR : | J7: =BEMSdar!E7 -> 46082
B9: STATE : | C9: SELANGOR | H9: BEMS MONTHLY FEE (RM)@ 97.5% : | J9: =BEMSdar!E11 -> 352591.82
B11: COMPANY : | C11: AMBANG WIRA SDN BHD | H11: FMS MONTHLY FEE (RM) @ 2.5% : | J11: =BEMSdar!E13 -> 9040.816
A13: Notes:
A14: 1) Deduction Ringgit Equivalent is based on Appendix 11 of the Agreement, Section B3 Key Deduction Indicators for BEMS
A15: 2) Deduction Value for Indicator B.3 is Deduction Ringgit Equivalent (per event)
A16: 3) Rescheduled Date is the final rescheduled date if there are multiple rescheduling
A17: 4) Display only asset affected by deduction
A19: No | B19: Asset No | C19: Asset Description | D19: Asset Purchase Price (RM) | E19: Work Order No. | F19: User Location | G19: Scheduled Start Date | H19: Scheduled End Date | I19: Rescheduled Date | J19: Maintenance Date | K19: Validate Status (Y/N) | L19: Deduction Ringgit Equivalent (RM) | M19: Indicator B.3
M20: Deduction Value (RM) | N20: Remarks/ Exemption
A21: Current Month (Work order closed)
A22: 1 | B22: KKM/JKN/HSA/10-05-01/R/15/16747 | C22: DIGITAL BLOOD PRESSURE | D22: 1855 | E22: HSASWOBE26012177 | F22: Klinik Pediatrik (PAEDIATRIC CLINIC) | G22: 46083 | H22: 46084 | J22: 46084 | K22: N | L22: =ROUNDUP((D22/4999.99)*10,-1) -> 10 | M22: =IF(K22="N",0,L22) -> 0 | N22: PPM DONE
A23: 5 | B23: KKM/JKN/HSA/10-05-01/R/15/16154 | C23: NEBULIZER | D23: 1950 | E23: HSASWOBE26012181 | F23: Klinik Pediatrik (PAEDIATRIC CLINIC) | G23: 46084 | H23: 46085 | J23: 46084 | K23: N | L23: =ROUNDUP((D23/4999.99)*10,-1) -> 10 | M23: =IF(K23="N",0,L23) -> 0 | N23: PPM DONE
A24: 6 | B24: KKM/JKN/HSA/10-05-01/H/15/574 | C24: ECG (EKG) MACHINE | D24: 10000 | E24: HSASWOBE26012182 | F24: WAD 12 (Paediatric Ward) | G24: 46084 | H24: 46085 | J24: 46085 | K24: N | L24: =ROUNDUP((D24/4999.99)*10,-1) -> 30 | M24: =IF(K24="N",0,L24) -> 0 | N24: PPM DONE
A25: 7 | B25: KKM/JKN/HSA/10-05-01/H/15/5358 | C25: LASER PRINTER | D25: 3499 | E25: HSASWOBE26012183 | F25: Unit Rawatan Koronari (CCU) | G25: 46084 | H25: 46085 | J25: 46084 | K25: N | L25: =ROUNDUP((D25/4999.99)*10,-1) -> 10 | M25: =IF(K25="N",0,L25) -> 0 | N25: PPM DONE
A26: 8 | B26: FA004 | C26: LASER PRINTER | D26: 3499 | E26: HSASWOBE26012184 | F26: Unit Rawatan Koronari (CCU) | G26: 46084 | H26: 46085 | J26: 46084 | K26: N | L26: =ROUNDUP((D26/4999.99)*10,-1) -> 10 | M26: =IF(K26="N",0,L26) -> 0 | N26: PPM DONE
A27: 10 | B27: KKM/JKN/HSA/10-05-01/H/15/2153 | C27: SUCTION APPARATUS | D27: 3386.5 | E27: HSASWOBE26012186 | F27: Klinik Pediatrik (PAEDIATRIC CLINIC) | G27: 46084 | H27: 46085 | J27: 46084 | K27: N | L27: =ROUNDUP((D27/4999.99)*10,-1) -> 10 | M27: =IF(K27="N",0,L27) -> 0 | N27: PPM DONE
A28: 11 | B28: KKM/JKN/HSA/10-05-01/R/15/16151 | C28: NEBULIZER | D28: 1950 | E28: HSASWOBE26012187 | F28: Klinik Pediatrik (PAEDIATRIC CLINIC) | G28: 46084 | H28: 46085 | J28: 46084 | K28: N | L28: =ROUNDUP((D28/4999.99)*10,-1) -> 10 | M28: =IF(K28="N",0,L28) -> 0 | N28: PPM DONE
A29: 12 | B29: KKM/JKN/HSA/10-05-01/R/15/16152 | C29: NEBULIZER | D29: 1950 | E29: HSASWOBE26012188 | F29: Klinik Pediatrik (PAEDIATRIC CLINIC) | G29: 46084 | H29: 46085 | J29: 46084 | K29: N | L29: =ROUNDUP((D29/4999.99)*10,-1) -> 10 | M29: =IF(K29="N",0,L29) -> 0 | N29: PPM DONE
A30: 13 | B30: KKM/JKN/HSA/10-05-01/R/15/16153 | C30: NEBULIZER | D30: 1950 | E30: HSASWOBE26012189 | F30: Klinik Pediatrik (PAEDIATRIC CLINIC) | G30: 46084 | H30: 46085 | J30: 46084 | K30: N | L30: =ROUNDUP((D30/4999.99)*10,-1) -> 10 | M30: =IF(K30="N",0,L30) -> 0 | N30: PPM DONE
A31: 14 | B31: KKM/JKN/HSA/10-05-01/H/15/1232 | C31: INFUSION PUMP | D31: 7245 | E31: HSASWOBE26012190 | F31: WAD 10B (Wad Perubatan Perempuan 10B) | G31: 46084 | H31: 46085 | J31: 46084 | K31: N | L31: =ROUNDUP((D31/4999.99)*10,-1) -> 20 | M31: =IF(K31="N",0,L31) -> 0 | N31: PPM DONE
A32: 15 | B32: KKM/JKN/HSA/10-05-01/H/15/1234 | C32: INFUSION PUMP | D32: 7245 | E32: HSASWOBE26012191 | F32: WAD 10B (Wad Perubatan Perempuan 10B) | G32: 46084 | H32: 46085 | J32: 46084 | K32: N | L32: =ROUNDUP((D32/4999.99)*10,-1) -> 20 | M32: =IF(K32="N",0,L32) -> 0 | N32: PPM DONE
A33: 16 | B33: KKM/JKN/HSA/10-05-01/H/15/1235 | C33: INFUSION PUMP | D33: 7245 | E33: HSASWOBE26012192 | F33: WAD 10B (Wad Perubatan Perempuan 10B) | G33: 46084 | H33: 46085 | J33: 46084 | K33: N | L33: =ROUNDUP((D33/4999.99)*10,-1) -> 20 | M33: =IF(K33="N",0,L33) -> 0 | N33: PPM DONE
... A70: 77 | B70: KKM/JKN/HSA/10-05-01/H/21/267 | C70: RESPIRATION HUMIDIFIER | D70: 21000 | E70: HSASWOBE26012254 | F70: Unit Rawatan Rapi (ICU) | G70: 46090 | H70: 46091 | J70: 46090 | K70: N | L70: =ROUNDUP((D70/4999.99)*10,-1) -> 50 | M70: =IF(K70="N",0,L70) -> 0 | N70: PPM DONE
A71: 78 | B71: KKM/JKN/HSA/10-05-01/H/21/233 | C71: VOLUMETRIC PUMP | D71: 2400 | E71: HSASWOBE26012255 | F71: Unit Rawatan Koronari (CCU) | G71: 46090 | H71: 46091 | J71: 46090 | K71: N | L71: =ROUNDUP((D71/4999.99)*10,-1) -> 10 | M71: =IF(K71="N",0,L71) -> 0 | N71: PPM DONE | O71: H/21/144
A72: 79 | B72: KKM/JKN/HSA/10-05-01/H/21/234 | C72: VOLUMETRIC PUMP | D72: 2400 | E72: HSASWOBE26012256 | F72: Unit Rawatan Koronari (CCU) | G72: 46090 | H72: 46091 | J72: 46090 | K72: N | L72: =ROUNDUP((D72/4999.99)*10,-1) -> 10 | M72: =IF(K72="N",0,L72) -> 0 | N72: PPM DONE
A73: 80 | B73: KKM/JKN/HSA/10-05-01/H/21/235 | C73: VOLUMETRIC PUMP | D73: 2400 | E73: HSASWOBE26012257 | F73: Unit Rawatan Koronari (CCU) | G73: 46090 | H73: 46091 | J73: 46090 | K73: N | L73: =ROUNDUP((D73/4999.99)*10,-1) -> 10 | M73: =IF(K73="N",0,L73) -> 0 | N73: PPM DONE | O73: H/21/147
A74: 81 | B74: KKM/JKN/HSA/10-05-01/H/21/236 | C74: VOLUMETRIC PUMP | D74: 2400 | E74: HSASWOBE26012258 | F74: Unit Rawatan Koronari (CCU) | G74: 46090 | H74: 46091 | J74: 46090 | K74: N | L74: =ROUNDUP((D74/4999.99)*10,-1) -> 10 | M74: =IF(K74="N",0,L74) -> 0 | N74: PPM DONE
A75: 83 | B75: KKM/JKN/HSA/10-05-01/R/15/14870 | C75: BLOOD PRESSURE MONITOR (SPHYGMOMANOMETER) | D75: 452.81 | E75: HSASWOBE26012263 | F75: Dewan Bersalin (LDU) | G75: 46091 | H75: 46092 | J75: 46091 | K75: N | L75: =ROUNDUP((D75/4999.99)*10,-1) -> 10 | M75: =IF(K75="N",0,L75) -> 0 | N75: PPM DONE
A76: 92 | B76: KKM/JKN/HSA/10-05-01/H/15/4007 | C76: PLASMA THAWER | D76: 14279 | E76: HSASWOBE26012272 | F76: PATHOLOGY | G76: 46092 | H76: 46093 | J76: 46093 | K76: N | L76: =ROUNDUP((D76/4999.99)*10,-1) -> 30 | M76: =IF(K76="N",0,L76) -> 0 | N76: PPM DONE
A77: 93 | B77: KKM/JKN/HSA/10-05-01/H/15/637 | C77: SYRINGE INFUSION PUMP | D77: 4300 | E77: HSASWOBE26012273 | F77: Unit Rawatan Koronari (CCU) | G77: 46092 | H77: 46093 | J77: 46092 | K77: N | L77: =ROUNDUP((D77/4999.99)*10,-1) -> 10 | M77: =IF(K77="N",0,L77) -> 0 | N77: PPM DONE
A78: 94 | B78: KKM/JKN/HSA/10-05-01/H/15/638 | C78: SYRINGE INFUSION PUMP | D78: 4300 | E78: HSASWOBE26012274 | F78: Unit Rawatan Koronari (CCU) | G78: 46092 | H78: 46093 | J78: 46092 | K78: N | L78: =ROUNDUP((D78/4999.99)*10,-1) -> 10 | M78: =IF(K78="N",0,L78) -> 0 | N78: PPM DONE
A79: 95 | B79: KKM/JKN/HSA/10-05-01/H/15/639 | C79: SYRINGE INFUSION PUMP | D79: 4300 | E79: HSASWOBE26012275 | F79: Unit Rawatan Koronari (CCU) | G79: 46092 | H79: 46093 | J79: 46092 | K79: N | L79: =ROUNDUP((D79/4999.99)*10,-1) -> 10 | M79: =IF(K79="N",0,L79) -> 0 | N79: PPM DONE
A80: 96 | B80: KKM/JKN/HSA/10-05-01/H/15/640 | C80: SYRINGE INFUSION PUMP | D80: 4300 | E80: HSASWOBE26012276 | F80: Unit Rawatan Koronari (CCU) | G80: 46092 | H80: 46093 | J80: 46092 | K80: N | L80: =ROUNDUP((D80/4999.99)*10,-1) -> 10 | M80: =IF(K80="N",0,L80) -> 0 | N80: PPM DONE
A81: 97 | B81: KKM/JKN/HSA/10-05-01/H/15/641 | C81: SYRINGE INFUSION PUMP | D81: 4300 | E81: HSASWOBE26012277 | F81: Unit Rawatan Koronari (CCU) | G81: 46092 | H81: 46093 | J81: 46092 | K81: N | L81: =ROUNDUP((D81/4999.99)*10,-1) -> 10 | M81: =IF(K81="N",0,L81) -> 0 | N81: PPM DONE
A82: 105 | B82: KKM/JKN/HSA/10-05-01/R/15/16750 | C82: ELECTRICAL NERVE STIMULATOR | D82: 949 | E82: HSASWOBE26012285 | F82: Jabatan Perubatan Rehabilitasi | G82: 46092 | H82: 46093 | J82: 46093 | K82: N | L82: =ROUNDUP((D82/4999.99)*10,-1) -> 10 | M82: =IF(K82="N",0,L82) -> 0 | N82: PPM DONE
A83: 106 | B83: KKM/JKN/HSA/10-05-01/R/15/16157 | C83: NEBULIZER | D83: 1950 | E83: HSASWOBE26012286 | F83: Wad 13 (VIP) | G83: 46092 | H83: 46093 | J83: 46092 | K83: N | L83: =ROUNDUP((D83/4999.99)*10,-1) -> 10 | M83: =IF(K83="N",0,L83) -> 0 | N83: PPM DONE
A84: 107 | B84: KKM/JKN/HSA/10-05-01/R/15/16158 | C84: NEBULIZER | D84: 1950 | E84: HSASWOBE26012287 | F84: Wad 13 (VIP) | G84: 46092 | H84: 46093 | J84: 46092 | K84: N | L84: =ROUNDUP((D84/4999.99)*10,-1) -> 10 | M84: =IF(K84="N",0,L84) -> 0 | N84: PPM DONE
A85: 108 | B85: KKM/JKN/HSA/10-05-01/R/15/16159 | C85: NEBULIZER | D85: 1950 | E85: HSASWOBE26012288 | F85: Wad 13 (VIP) | G85: 46092 | H85: 46093 | J85: 46092 | K85: N | L85: =ROUNDUP((D85/4999.99)*10,-1) -> 10 | M85: =IF(K85="N",0,L85) -> 0 | N85: PPM DONE
... A189: 283 | B189: KKM/JKN/HSA/10-05-01/H/21/265 | C189: DEFIBRILLATOR PACER ANALYZER | D189: 16500 | E189: HSASWOBE26012709 | F189: (Multidiscipline Ward) MDW | G189: 46092 | H189: 46093 | J189: 46092 | K189: N | L189: =ROUNDUP((D189/4999.99)*10,-1) -> 40 | M189: =IF(K189="N",0,L189) -> 0 | N189: PPM DONE
A190: Current Month (Work order open)
A191: 1 | B191: KKM/JKN/HSA/10-05-01/H/15/4999 | C191: MOBILE X-RAY MACHINE (H/15/4999) | D191: 105500 | E191: HSASWOBE26012178 | F191: Jabatan Pengimejan & Diagnostik | G191: 46083 | H191: 46084 | K191: N | L191: =ROUNDUP((D191/4999.99)*10,-1) -> 220 | M191: =IF(K191="N",0,L191) -> 0 | N191: RESCHEDULE
A192: 2 | B192: KKM/JKN/HSA/10-05-01/H/15/2535 | C192: MOBILE X-RAY MACHINE | D192: 105500 | E192: HSASWOBE26012179 | F192: Jabatan Pengimejan & Diagnostik | G192: 46084 | H192: 46085 | K192: N | L192: =ROUNDUP((D192/4999.99)*10,-1) -> 220 | M192: =IF(K192="N",0,L192) -> 0 | N192: RESCHEDULE
A193: 3 | B193: KKM/JKN/HSA/10-05-01/H/15/2537 | C193: MOBILE X-RAY MACHINE | D193: 105500 | E193: HSASWOBE26012180 | F193: Unit Rawatan Rapi Neonatal (NICU) | G193: 46084 | H193: 46085 | K193: N | L193: =ROUNDUP((D193/4999.99)*10,-1) -> 220 | M193: =IF(K193="N",0,L193) -> 0 | N193: RESCHEDULE
A194: 4 | B194: KKM/JKN/HSA/10-05-01/H/15/4298 | C194: CARDIOTOCOGRAPH MACHINE | D194: 10200 | E194: HSASWOBE26012185 | F194: Dewan Bersalin (LDU) | G194: 46084 | H194: 46085 | K194: N | L194: =ROUNDUP((D194/4999.99)*10,-1) -> 30 | M194: =IF(K194="N",0,L194) -> 0 | N194: RESCHEDULE
A195: 5 | B195: KKM/JKN/HSA/10-05-01/R/15/16156 | C195: NEBULIZER | D195: 1950 | E195: HSASWOBE26012196 | F195: LEVEL 6 (Wad Multidisiplin Perempuan) | G195: 46084 | H195: 46085 | K195: N | L195: =ROUNDUP((D195/4999.99)*10,-1) -> 10 | M195: =IF(K195="N",0,L195) -> 0 | N195: RESCHEDULE
A196: 6 | B196: KKM/JKN/HSA/10-05-01/R/15/16150 | C196: NEBULIZER | D196: 1950 | E196: HSASWOBE26012197 | F196: Klinik Ortopedik (ORTHO CLINIC) | G196: 46084 | H196: 46085 | K196: N | L196: =ROUNDUP((D196/4999.99)*10,-1) -> 10 | M196: =IF(K196="N",0,L196) -> 0 | N196: RESCHEDULE
A197: 7 | B197: KKM/JKN/HSA/10-05-01/H/15/811 | C197: SYRINGE INFUSION PUMP | D197: 4300 | E197: HSASWOBE26012203 | F197: Unit Rawatan Rapi Neonatal (NICU) | G197: 46085 | H197: 46086 | K197: N | L197: =ROUNDUP((D197/4999.99)*10,-1) -> 10 | M197: =IF(K197="N",0,L197) -> 0 | N197: RESCHEDULE
A198: 8 | B198: KKM/JKN/HSA/10-05-01/H/15/812 | C198: SYRINGE INFUSION PUMP | D198: 4300 | E198: HSASWOBE26012204 | F198: Unit Rawatan Rapi Neonatal (NICU) | G198: 46085 | H198: 46086 | K198: N | L198: =ROUNDUP((D198/4999.99)*10,-1) -> 10 | M198: =IF(K198="N",0,L198) -> 0 | N198: RESCHEDULE
A199: 9 | B199: KKM/JKN/HSA/10-05-01/H/15/5040 | C199: ELECTROSURGICAL UNIT | D199: 33286.5 | E199: HSASWOBE26012210 | F199: Dewan Bedah Bersalin (MOT) | G199: 46086 | H199: 46087 | K199: N | L199: =ROUNDUP((D199/4999.99)*10,-1) -> 70 | M199: =IF(K199="N",0,L199) -> 0 | N199: RESCHEDULE
A200: 10 | B200: KKM/JKN/HSA/10-05-01/H/15/807 | C200: SYRINGE INFUSION PUMP | D200: 4300 | E200: HSASWOBE26012211 | F200: Unit Rawatan Rapi Neonatal (NICU) | G200: 46086 | H200: 46087 | K200: N | L200: =ROUNDUP((D200/4999.99)*10,-1) -> 10 | M200: =IF(K200="N",0,L200) -> 0 | N200: RESCHEDULE
A201: 11 | B201: KKM/JKN/HSA/10-05-01/H/15/808 | C201: SYRINGE INFUSION PUMP | D201: 4300 | E201: HSASWOBE26012212 | F201: Unit Rawatan Rapi Neonatal (NICU) | G201: 46086 | H201: 46087 | K201: N | L201: =ROUNDUP((D201/4999.99)*10,-1) -> 10 | M201: =IF(K201="N",0,L201) -> 0 | N201: RESCHEDULE
A202: 12 | B202: KKM/JKN/HSA/10-05-01/H/15/809 | C202: SYRINGE INFUSION PUMP | D202: 4300 | E202: HSASWOBE26012213 | F202: Unit Rawatan Rapi Neonatal (NICU) | G202: 46086 | H202: 46087 | K202: N | L202: =ROUNDUP((D202/4999.99)*10,-1) -> 10 | M202: =IF(K202="N",0,L202) -> 0 | N202: RESCHEDULE
... A305: 115 | B305: KKM/JKN/HSA/10-05-01/H/21/79 | C305: VENTILATOR | D305: 105000 | E305: HSASWOBE26012483 | F305: Unit Rawatan Rapi (ICU) | G305: 46108 | H305: 46109 | K305: N | L305: =ROUNDUP((D305/4999.99)*10,-1) -> 220 | M305: =IF(K305="N",0,L305) -> 0 | N305: RESCHEDULE
A306: Previous Month (Work order closed)
A307: 16 | B307: KKM/JKN/HSA/10-05-01/H/20/238 | C307: PATIENT MONITORING EQUIP.(AUTOMATIC MULTIPARAMETER) | D307: 9980 | E307: HSASWOBE26006618 | F307: PAC | G307: 46055 | H307: 46056 | J307: 46111 | K307: N | L307: =ROUNDUP((D307/4999.99)*10,-1) -> 20 | M307: =IF(K307="N",0,L307) -> 0 | N307: PPM DONE
A308: 17 | B308: KKM/JKN/HSA/10-05-01/H/20/247 | C308: KEELER VANTAGE PLUS WIRELESS BIO & CHARGER | D308: 12000 | E308: HSASWOBE26006621 | F308: Klinik Oftalmologi (OPHTHAL CLINIC) | G308: 46055 | H308: 46056 | J308: 46083 | K308: N | L308: =ROUNDUP((D308/4999.99)*10,-1) -> 30 | M308: =IF(K308="N",0,L308) -> 0 | N308: PPM DONE
A309: 18 | B309: KKM/JKN/HSA/10-05-01/H/20/248 | C309: KEELER VANTAGE PLUS WIRELESS BIO & CHARGER | D309: 12000 | E309: HSASWOBE26006622 | F309: Klinik Oftalmologi (OPHTHAL CLINIC) | G309: 46055 | H309: 46056 | J309: 46083 | K309: N | L309: =ROUNDUP((D309/4999.99)*10,-1) -> 30 | M309: =IF(K309="N",0,L309) -> 0 | N309: PPM DONE
A310: 20 | B310: KKM/JKN/HSA/10-05-01/H/20/256 | C310: SPOT VITAL SIGN (NIBP) | D310: 5500 | E310: HSASWOBE26006624 | F310: Jabatan Perubatan Rehabilitasi | G310: 46055 | H310: 46056 | J310: 46090 | K310: N | L310: =ROUNDUP((D310/4999.99)*10,-1) -> 20 | M310: =IF(K310="N",0,L310) -> 0 | N310: PPM DONE
A311: 68 | B311: KKM/JKN/HSA/10-05-01/R/15/15056 | C311: BALANCES ELECTRONICS | D311: 1240 | E311: HSASWOBE26006714 | F311: PATHOLOGY | G311: 46065 | H311: 46066 | J311: 46090 | K311: N | L311: =ROUNDUP((D311/4999.99)*10,-1) -> 10 | M311: =IF(K311="N",0,L311) -> 0 | N311: PPM DONE
A312: 69 | B312: KKM/JKN/HSA/10-05-01/R/15/15057 | C312: BALANCES ELECTRONICS | D312: 1740 | E312: HSASWOBE26006717 | F312: PATHOLOGY | G312: 46065 | H312: 46066 | J312: 46090 | K312: N | L312: =ROUNDUP((D312/4999.99)*10,-1) -> 10 | M312: =IF(K312="N",0,L312) -> 0 | N312: PPM DONE
A313: 79 | B313: KKM/JKN/HSA/10-05-01/H/15/769 | C313: FETAL HEART MONITOR (DAPTONE) | D313: 11565 | E313: HSASWOBE26006741 | F313: Dewan Bersalin (LDU) | G313: 46069 | H313: 46070 | J313: 46083 | K313: N | L313: =ROUNDUP((D313/4999.99)*10,-1) -> 30 | M313: =IF(K313="N",0,L313) -> 0 | N313: ASET BER
A314: 81 | B314: KKM/JKN/HSA/10-05-01/H/15/427 | C314: DIAGNOSTIC SET | D314: 2024.23 | E314: HSASWOBE26006748 | F314: Jabatan Kecemasan & Trauma (ED) | G314: 46069 | H314: 46070 | J314: 46090 | K314: N | L314: =ROUNDUP((D314/4999.99)*10,-1) -> 10 | M314: =IF(K314="N",0,L314) -> 0 | N314: PPM NOT DONE, NOT AT LOCATION
A315: 82 | B315: KKM/JKN/HSA/10-05-01/H/16/101 | C315: DENTAL DELIVERY UNIT ( VACUUM SYSTEM) | D315: 36915 | E315: HSASWOBE26006750 | F315: Klinik Bedah Mulut & Klinik Pergigian Pediatrik | G315: 46069 | H315: 46070 | J315: 46083 | K315: N | L315: =ROUNDUP((D315/4999.99)*10,-1) -> 80 | M315: =IF(K315="N",0,L315) -> 0 | N315: PPM DONE
A316: 99 | B316: KKM/JKN/HSA/10-05-01/H/15/462 | C316: SYRINGE INFUSION PUMP | D316: 4300 | E316: HSASWOBE26006787 | F316: High Dependency Ward (HDW) | G316: 46073 | H316: 46074 | J316: 46097 | K316: N | L316: =ROUNDUP((D316/4999.99)*10,-1) -> 10 | M316: =IF(K316="N",0,L316) -> 0 | N316: PPM DONE
A317: 101 | B317: KKM/JKN/HSA/10-05-01/H/15/761 | C317: FETAL HEART MONITOR (DAPTONE) | D317: 11565 | E317: HSASWOBE26006790 | F317: Dewan Bersalin (LDU) | G317: 46073 | H317: 46074 | J317: 46087 | K317: N | L317: =ROUNDUP((D317/4999.99)*10,-1) -> 30 | M317: =IF(K317="N",0,L317) -> 0 | N317: PPM NOT DONE, BER
A318: 103 | B318: KKM/JKN/HSA/10-05-01/H/15/765 | C318: FETAL HEART MONITOR (DAPTONE) | D318: 11565 | E318: HSASWOBE26006792 | F318: Dewan Bersalin (LDU) | G318: 46073 | H318: 46074 | J318: 46087 | K318: N | L318: =ROUNDUP((D318/4999.99)*10,-1) -> 30 | M318: =IF(K318="N",0,L318) -> 0 | N318: PPM NOT DONE, BER
... A327: 136 | B327: KKM/JKN/HSA/10-05-01/H/15/4296 | C327: CARDIOTOCOGRAPH MACHINE | D327: 10200 | E327: HSASWOBE26006860 | F327: PAC | G327: 46080 | H327: 46081 | J327: 46087 | K327: N | L327: =ROUNDUP((D327/4999.99)*10,-1) -> 30 | M327: =IF(K327="N",0,L327) -> 0 | N327: PPM NOT DONE, BER
A328: 15 | B328: KKM/JKN/HSA/10-05-01/H/21/347 | C328: =VLOOKUP(B:B,'[3]SCHEDULE PPM 2026'!$D:$E,2, FALSE) -> OXYGEN CONCENTRATOR | D328: =VLOOKUP(B:B,'[2]BEMS EQUIPMENT '!$E:$Q,13,FALSE) -> 4199 | E328: HSASWOBE26002920 | F328: =VLOOKUP(B:B,'[3]SCHEDULE PPM 2026'!$D:$O,12,FALSE) -> Jabatan Kecemasan & Trauma (ED) | G328: =VLOOKUP(B:B,'[3]SCHEDULE PPM 2026'!$D:$J,7,FALSE) -> 46028 | H328: 46029 | J328: 46087 | K328: N | L328: =ROUNDUP((D328/4999.99)*10,-1) -> 10 | M328: =IF(K328="N",0,L328) -> 0 | N328: PPM DONE
A329: 17 | B329: KKM/JKN/HSA/10-05-01/H/21/343 | C329: =VLOOKUP(B:B,'[3]SCHEDULE PPM 2026'!$D:$E,2, FALSE) -> OXYGEN CONCENTRATOR | D329: =VLOOKUP(B:B,'[2]BEMS EQUIPMENT '!$E:$Q,13,FALSE) -> 4199 | E329: HSASWOBE26002924 | F329: =VLOOKUP(B:B,'[3]SCHEDULE PPM 2026'!$D:$O,12,FALSE) -> Jabatan Kecemasan & Trauma (ED) | G329: =VLOOKUP(B:B,'[3]SCHEDULE PPM 2026'!$D:$J,7,FALSE) -> 46028 | H329: 46029 | J329: 46087 | K329: N | L329: =ROUNDUP((D329/4999.99)*10,-1) -> 10 | M329: =IF(K329="N",0,L329) -> 0 | N329: PPM DONE
A330: 43 | B330: KKM/JKN/HSA/10-05-01/H/21/140 | C330: =VLOOKUP(B:B,'[4]SCHEDULE PPM 2026'!$D:$E,2, FALSE) -> INFANT VENTILATOR | D330: =VLOOKUP(B:B,'[2]BEMS EQUIPMENT '!$E:$Q,13,FALSE) -> 26000 | E330: HSASWOBE26003003 | F330: =VLOOKUP(B:B,'[3]SCHEDULE PPM 2026'!$D:$O,12,FALSE) -> WAD 12 (Paediatric Ward) | G330: =VLOOKUP(B:B,'[3]SCHEDULE PPM 2026'!$D:$J,7,FALSE) -> 46035 | H330: 46036 | J330: 46108 | K330: N | L330: =ROUNDUP((D330/4999.99)*10,-1) -> 60 | M330: =IF(K330="N",0,L330) -> 0 | N330: PPM DONE
A331: 55 | B331: KKM/JKN/HSA/10-05-01/R/22/17 | C331: =VLOOKUP(B:B,'[4]SCHEDULE PPM 2026'!$D:$E,2, FALSE) -> FETAL HEART MONITOR | D331: =VLOOKUP(B:B,'[2]BEMS EQUIPMENT '!$E:$Q,13,FALSE) -> 950 | E331: HSASWOBE26003022 | F331: =VLOOKUP(B:B,'[3]SCHEDULE PPM 2026'!$D:$O,12,FALSE) -> Klinik Obstetrik Ginekologi (O&G CLINIC) | G331: =VLOOKUP(B:B,'[3]SCHEDULE PPM 2026'!$D:$J,7,FALSE) -> 46036 | H331: 46037 | J331: 46099 | K331: N | L331: =ROUNDUP((D331/4999.99)*10,-1) -> 10 | M331: =IF(K331="N",0,L331) -> 0 | N331: PPM NOT DONE, NOT AT LOCATION
A332: 56 | B332: KKM/JKN/HSA/10-05-01/R/22/19 | C332: =VLOOKUP(B:B,'[4]SCHEDULE PPM 2026'!$D:$E,2, FALSE) -> FETAL HEART MONITOR | D332: =VLOOKUP(B:B,'[2]BEMS EQUIPMENT '!$E:$Q,13,FALSE) -> 950 | E332: HSASWOBE26003023 | F332: =VLOOKUP(B:B,'[3]SCHEDULE PPM 2026'!$D:$O,12,FALSE) -> Klinik Obstetrik Ginekologi (O&G CLINIC) | G332: =VLOOKUP(B:B,'[3]SCHEDULE PPM 2026'!$D:$J,7,FALSE) -> 46036 | H332: 46037 | J332: 46099 | K332: N | L332: =ROUNDUP((D332/4999.99)*10,-1) -> 10 | M332: =IF(K332="N",0,L332) -> 0 | N332: PPM NOT DONE, NOT AT LOCATION
A333: 79 | B333: KKM/JKN/HSA/10-05-01/H/15/447 | C333: =VLOOKUP(B:B,'[3]SCHEDULE PPM 2026'!$D$6:$E$2196,2, FALSE) -> SYRINGE INFUSION PUMP | D333: =VLOOKUP(B:B,'[2]BEMS EQUIPMENT '!$E:$Q,13,FALSE) -> 4300 | E333: HSASWOBE26003087 | F333: =VLOOKUP(B:B,'[3]SCHEDULE PPM 2026'!$D:$O,12,FALSE) -> Jabatan Kecemasan & Trauma (ED) | G333: =VLOOKUP(B:B,'[3]SCHEDULE PPM 2026'!$D:$J,7,FALSE) -> 46041 | H333: 46042 | J333: 46083 | K333: N | L333: =ROUNDUP((D333/4999.99)*10,-1) -> 10 | M333: =IF(K333="N",0,L333) -> 0 | N333: PPM DONE
A334: 93 | B334: KKM/JKN/HSA/10-05-01/R/15/15103 | C334: =VLOOKUP(B:B,'[3]SCHEDULE PPM 2026'!$D$6:$E$2196,2, FALSE) -> PORTABLE FETAL DOPPLER/CAPNOGRAPH | D334: =VLOOKUP(B:B,'[2]BEMS EQUIPMENT '!$E:$Q,13,FALSE) -> 580 | E334: HSASWOBE26003114 | F334: =VLOOKUP(B:B,'[3]SCHEDULE PPM 2026'!$D:$O,12,FALSE) -> Klinik Obstetrik Ginekologi (O&G CLINIC) | G334: =VLOOKUP(B:B,'[3]SCHEDULE PPM 2026'!$D:$J,7,FALSE) -> 46044 | H334: 46045 | J334: 46106 | K334: N | L334: =ROUNDUP((D334/4999.99)*10,-1) -> 10 | M334: =IF(K334="N",0,L334) -> 0 | N334: PPM NOT DONE, NOT AT LOCATION
A335: 111 | B335: KKM/JKN/HSA/10-05-01/R/15/15105 | C335: =VLOOKUP(B:B,'[3]SCHEDULE PPM 2026'!$D$6:$E$2196,2, FALSE) -> PORTABLE FETAL DOPPLER/CAPNOGRAPH | D335: 0 | E335: HSASWOBE26003157 | F335: =VLOOKUP(B:B,'[3]SCHEDULE PPM 2026'!$D:$O,12,FALSE) -> Klinik Obstetrik Ginekologi (O&G CLINIC) | G335: =VLOOKUP(B:B,'[3]SCHEDULE PPM 2026'!$D:$J,7,FALSE) -> 46049 | H335: 46050 | J335: 46105 | K335: N | L335: =ROUNDUP((D335/4999.99)*10,-1) -> 0 | M335: =IF(K335="N",0,L335) -> 0 | N335: PPM NOT DONE, NOT AT LOCATION
A336: 120 | B336: KKM/JKN/HSA/10-05-01/R/15/16387 | C336: =VLOOKUP(B:B,'[3]SCHEDULE PPM 2026'!$D$6:$E$2196,2, FALSE) -> BLOOD PRESSURE MONITOR NON INVASIVE | D336: 1855 | E336: HSASWOBE26003176 | F336: =VLOOKUP(B:B,'[3]SCHEDULE PPM 2026'!$D:$O,12,FALSE) -> Klinik Obstetrik Ginekologi (O&G CLINIC) | G336: =VLOOKUP(B:B,'[3]SCHEDULE PPM 2026'!$D:$J,7,FALSE) -> 46052 | H336: 46053 | J336: 46108 | K336: N | L336: =ROUNDUP((D336/4999.99)*10,-1) -> 10 | M336: =IF(K336="N",0,L336) -> 0 | N336: PPM NOT DONE, NOT AT LOCATION
A337: Previous Month (Work order open)
A338: 1 | B338: KKM/JKN/HSA/10-05-01/H/15/1166 | C338: =VLOOKUP(B:B,'[3]SCHEDULE PPM 2026'!$D$6:$E$2196,2, FALSE) -> SURGICAL MICROSCOPE | D338: =VLOOKUP(B:B,'[2]BEMS EQUIPMENT '!$E:$Q,13,FALSE) -> 265900 | E338: HSASWOBE26002869 | F338: =VLOOKUP(B:B,'[3]SCHEDULE PPM 2026'!$D:$O,12,FALSE) -> Dewan Bedah Utama (GOT) | G338: =VLOOKUP(B:B,'[3]SCHEDULE PPM 2026'!$D:$J,7,FALSE) -> 46024 | H338: 46025 | K338: N | L338: =ROUNDUP((D338/4999.99)*10,-1) -> 540 | M338: =IF(K338="N",0,L338) -> 0 | N338: RESCHEDULE
A339: 2 | B339: KKM/JKN/HSA/10-05-01/H/15/4249 | C339: =VLOOKUP(B:B,'[3]SCHEDULE PPM 2026'!$D$6:$E$2196,2, FALSE) -> HEMODIALYSIS MACHINE | D339: =VLOOKUP(B:B,'[2]BEMS EQUIPMENT '!$E:$Q,13,FALSE) -> 36300 | E339: HSASWOBE26002896 | F339: =VLOOKUP(B:B,'[3]SCHEDULE PPM 2026'!$D:$O,12,FALSE) -> Unit Hemodialisis (HDU) | G339: =VLOOKUP(B:B,'[3]SCHEDULE PPM 2026'!$D:$J,7,FALSE) -> 46027 | H339: 46028 | K339: N | L339: =ROUNDUP((D339/4999.99)*10,-1) -> 80 | M339: =IF(K339="N",0,L339) -> 0 | N339: RESCHEDULE
A340: 5 | B340: KKM/JKN/HSA/10-05-01/H/15/1012 | C340: =VLOOKUP(B:B,'[3]SCHEDULE PPM 2026'!$D$6:$E$2196,2, FALSE) -> NASOPHARYNGOSCOPE FIBEROPTIC | D340: 32850 | E340: HSASWOBE26002904 | F340: =VLOOKUP(B:B,'[3]SCHEDULE PPM 2026'!$D:$O,12,FALSE) -> Klinik Otorinolaringologi (ORL) (ENT CLINIC) | G340: =VLOOKUP(B:B,'[3]SCHEDULE PPM 2026'!$D:$J,7,FALSE) -> 46028 | H340: 46029 | K340: N | L340: =ROUNDUP((D340/4999.99)*10,-1) -> 70 | M340: =IF(K340="N",0,L340) -> 0 | N340: RESCHEDULE
A341: 11 | B341: KKM/JKN/HSA/10-05-01/R/15/6958 | C341: =VLOOKUP(B:B,'[3]SCHEDULE PPM 2026'!$D$6:$E$2196,2, FALSE) -> WEIGHING SCALE TOP LOADING | D341: =VLOOKUP(B:B,'[2]BEMS EQUIPMENT '!$E:$Q,13,FALSE) -> 540 | E341: HSASWOBE26002913 | F341: =VLOOKUP(B:B,'[3]SCHEDULE PPM 2026'!$D:$O,12,FALSE) -> Unit Rawatan Rapi Neonatal (NICU) | G341: =VLOOKUP(B:B,'[3]SCHEDULE PPM 2026'!$D:$J,7,FALSE) -> 46028 | H341: 46029 | K341: N | L341: =ROUNDUP((D341/4999.99)*10,-1) -> 10 | M341: =IF(K341="N",0,L341) -> 0 | N341: RESCHEDULE
A342: 19 | B342: KKM/JKN/HSA/10-05-01/H/15/439 | C342: =VLOOKUP(B:B,'[3]SCHEDULE PPM 2026'!$D$6:$E$2196,2, FALSE) -> SYRINGE INFUSION PUMP | D342: =VLOOKUP(B:B,'[2]BEMS EQUIPMENT '!$E:$Q,13,FALSE) -> 4300 | E342: HSASWOBE26002927 | F342: =VLOOKUP(B:B,'[3]SCHEDULE PPM 2026'!$D:$O,12,FALSE) -> Jabatan Kecemasan & Trauma (ED) | G342: =VLOOKUP(B:B,'[3]SCHEDULE PPM 2026'!$D:$J,7,FALSE) -> 46029 | H342: 46030 | K342: N | L342: =ROUNDUP((D342/4999.99)*10,-1) -> 10 | M342: =IF(K342="N",0,L342) -> 0 | N342: RESCHEDULE
A343: 22 | B343: KKM/JKN/HSA/10-05-01/H/21/328 | C343: =VLOOKUP(B:B,'[3]SCHEDULE PPM 2026'!$D:$E,2, FALSE) -> INKUBATOR | D343: =VLOOKUP(B:B,'[2]BEMS EQUIPMENT '!$E:$Q,13,FALSE) -> 28000 | E343: HSASWOBE26002938 | F343: =VLOOKUP(B:B,'[3]SCHEDULE PPM 2026'!$D:$O,12,FALSE) -> Unit Rawatan Rapi Neonatal (NICU) | G343: =VLOOKUP(B:B,'[3]SCHEDULE PPM 2026'!$D:$J,7,FALSE) -> 46030 | H343: 46031 | K343: N | L343: =ROUNDUP((D343/4999.99)*10,-1) -> 60 | M343: =IF(K343="N",0,L343) -> 0 | N343: RESCHEDULE
A344: 23 | B344: KKM/JKN/HSA/10-05-01/R/15/14861 | C344: =VLOOKUP(B:B,'[3]SCHEDULE PPM 2026'!$D$6:$E$2196,2, FALSE) -> BLOOD PRESSURE MONITOR (SPHYGMOMANOMETER) | D344: =VLOOKUP(B:B,'[2]BEMS EQUIPMENT '!$E:$Q,13,FALSE) -> 452.81 | E344: HSASWOBE26002950 | F344: =VLOOKUP(B:B,'[3]SCHEDULE PPM 2026'!$D:$O,12,FALSE) -> Klinik Obstetrik Ginekologi (O&G CLINIC) | G344: =VLOOKUP(B:B,'[3]SCHEDULE PPM 2026'!$D:$J,7,FALSE) -> 46031 | H344: 46032 | K344: N | L344: =ROUNDUP((D344/4999.99)*10,-1) -> 10 | M344: =IF(K344="N",0,L344) -> 0 | N344: RESCHEDULE
A345: 24 | B345: KKM/JKN/HSA/10-05-01/R/15/14862 | C345: =VLOOKUP(B:B,'[3]SCHEDULE PPM 2026'!$D$6:$E$2196,2, FALSE) -> BLOOD PRESSURE MONITOR (SPHYGMOMANOMETER) | D345: =VLOOKUP(B:B,'[2]BEMS EQUIPMENT '!$E:$Q,13,FALSE) -> 452.81 | E345: HSASWOBE26002951 | F345: =VLOOKUP(B:B,'[3]SCHEDULE PPM 2026'!$D:$O,12,FALSE) -> Klinik Obstetrik Ginekologi (O&G CLINIC) | G345: =VLOOKUP(B:B,'[3]SCHEDULE PPM 2026'!$D:$J,7,FALSE) -> 46031 | H345: 46032 | K345: N | L345: =ROUNDUP((D345/4999.99)*10,-1) -> 10 | M345: =IF(K345="N",0,L345) -> 0 | N345: RESCHEDULE
A346: 29 | B346: KKM/JKN/HSA/10-05-01/H/21/106 | C346: =VLOOKUP(B:B,'[4]SCHEDULE PPM 2026'!$D:$E,2, FALSE) -> INFANT VENTILATOR | D346: 130000 | E346: HSASWOBE26002969 | F346: =VLOOKUP(B:B,'[3]SCHEDULE PPM 2026'!$D:$O,12,FALSE) -> Unit Rawatan Rapi Neonatal (NICU) | G346: =VLOOKUP(B:B,'[3]SCHEDULE PPM 2026'!$D:$J,7,FALSE) -> 46031 | H346: 46032 | K346: N | L346: =ROUNDUP((D346/4999.99)*10,-1) -> 270 | M346: =IF(K346="N",0,L346) -> 0 | N346: RESCHEDULE
A347: 35 | B347: KKM/JKN/HSA/10-05-01/H/22/86 | C347: =VLOOKUP(B:B,'[4]SCHEDULE PPM 2026'!$D:$E,2, FALSE) -> INFANT WARMER RADIANT | D347: =VLOOKUP(B:B,'[2]BEMS EQUIPMENT '!$E:$Q,13,FALSE) -> 23950 | E347: HSASWOBE26002978 | F347: =VLOOKUP(B:B,'[3]SCHEDULE PPM 2026'!$D:$O,12,FALSE) -> Unit Rawatan Rapi Neonatal (NICU) | G347: =VLOOKUP(B:B,'[3]SCHEDULE PPM 2026'!$D:$J,7,FALSE) -> 46031 | H347: 46032 | K347: N | L347: =ROUNDUP((D347/4999.99)*10,-1) -> 50 | M347: =IF(K347="N",0,L347) -> 0 | N347: RESCHEDULE
A348: 38 | B348: KKM/JKN/HSA/10-05-01/R/15/14863 | C348: =VLOOKUP(B:B,'[3]SCHEDULE PPM 2026'!$D$6:$E$2196,2, FALSE) -> BLOOD PRESSURE MONITOR (SPHYGMOMANOMETER) | D348: =VLOOKUP(B:B,'[2]BEMS EQUIPMENT '!$E:$Q,13,FALSE) -> 452.81 | E348: HSASWOBE26002997 | F348: =VLOOKUP(B:B,'[3]SCHEDULE PPM 2026'!$D:$O,12,FALSE) -> Dewan Bersalin (LDU) | G348: =VLOOKUP(B:B,'[3]SCHEDULE PPM 2026'!$D:$J,7,FALSE) -> 46035 | H348: 46036 | K348: N | L348: =ROUNDUP((D348/4999.99)*10,-1) -> 10 | M348: =IF(K348="N",0,L348) -> 0 | N348: RESCHEDULE
A349: 46 | B349: KKM/JKN/HSA/10-05-01/H/21/336 | C349: =VLOOKUP(B:B,'[4]SCHEDULE PPM 2026'!$D:$E,2, FALSE) -> PATIENT MONITOR EQUIPMENT / VITAL SIGN MONITOR | D349: =VLOOKUP(B:B,'[2]BEMS EQUIPMENT '!$E:$Q,13,FALSE) -> 19610 | E349: HSASWOBE26003006 | F349: =VLOOKUP(B:B,'[3]SCHEDULE PPM 2026'!$D:$O,12,FALSE) -> WAD 12 (Paediatric Ward) | G349: =VLOOKUP(B:B,'[3]SCHEDULE PPM 2026'!$D:$J,7,FALSE) -> 46035 | H349: 46036 | K349: N | L349: =ROUNDUP((D349/4999.99)*10,-1) -> 40 | M349: =IF(K349="N",0,L349) -> 0 | N349: RESCHEDULE
A350: 48 | B350: KKM/JKN/HSA/10-05-01/R/15/14876 | C350: =VLOOKUP(B:B,'[3]SCHEDULE PPM 2026'!$D$6:$E$2196,2, FALSE) -> BLOOD PRESSURE MONITOR (SPHYGMOMANOMETER) | D350: =VLOOKUP(B:B,'[2]BEMS EQUIPMENT '!$E:$Q,13,FALSE) -> 452.81 | E350: HSASWOBE26003014 | F350: =VLOOKUP(B:B,'[3]SCHEDULE PPM 2026'!$D:$O,12,FALSE) -> Klinik Obstetrik Ginekologi (O&G CLINIC) | G350: =VLOOKUP(B:B,'[3]SCHEDULE PPM 2026'!$D:$J,7,FALSE) -> 46036 | H350: 46037 | K350: N | L350: =ROUNDUP((D350/4999.99)*10,-1) -> 10 | M350: =IF(K350="N",0,L350) -> 0 | N350: RESCHEDULE
A351: 49 | B351: KKM/JKN/HSA/10-05-01/R/15/14877 | C351: =VLOOKUP(B:B,'[3]SCHEDULE PPM 2026'!$D$6:$E$2196,2, FALSE) -> BLOOD PRESSURE MONITOR (SPHYGMOMANOMETER) | D351: =VLOOKUP(B:B,'[2]BEMS EQUIPMENT '!$E:$Q,13,FALSE) -> 452.81 | E351: HSASWOBE26003015 | F351: =VLOOKUP(B:B,'[3]SCHEDULE PPM 2026'!$D:$O,12,FALSE) -> WAD 8A (Wad Obstetrik & Ginekologi 8A) | G351: =VLOOKUP(B:B,'[3]SCHEDULE PPM 2026'!$D:$J,7,FALSE) -> 46036 | H351: 46037 | K351: N | L351: =ROUNDUP((D351/4999.99)*10,-1) -> 10 | M351: =IF(K351="N",0,L351) -> 0 | N351: RESCHEDULE
A352: 52 | B352: KKM/JKN/HSA/10-05-01/H/15/4235 | C352: =VLOOKUP(B:B,'[3]SCHEDULE PPM 2026'!$D$6:$E$2196,2, FALSE) -> PUMP BREAST ELECTRIC | D352: =VLOOKUP(B:B,'[2]BEMS EQUIPMENT '!$E:$Q,13,FALSE) -> 12740 | E352: HSASWOBE26003018 | F352: =VLOOKUP(B:B,'[3]SCHEDULE PPM 2026'!$D:$O,12,FALSE) -> Unit Rawatan Rapi Neonatal (NICU) | G352: =VLOOKUP(B:B,'[3]SCHEDULE PPM 2026'!$D:$J,7,FALSE) -> 46036 | H352: 46037 | K352: N | L352: =ROUNDUP((D352/4999.99)*10,-1) -> 30 | M352: =IF(K352="N",0,L352) -> 0 | N352: RESCHEDULE
A353: 53 | B353: KKM/JKN/HSA/10-05-01/H/21/138 | C353: =VLOOKUP(B:B,'[4]SCHEDULE PPM 2026'!$D:$E,2, FALSE) -> VOLUMETRIC PUMP | D353: 5300 | E353: HSASWOBE26003020 | F353: =VLOOKUP(B:B,'[3]SCHEDULE PPM 2026'!$D:$O,12,FALSE) -> Unit Rawatan Rapi (ICU) | G353: =VLOOKUP(B:B,'[3]SCHEDULE PPM 2026'!$D:$J,7,FALSE) -> 46036 | H353: 46037 | K353: N | L353: =ROUNDUP((D353/4999.99)*10,-1) -> 20 | M353: =IF(K353="N",0,L353) -> 0 | N353: RESCHEDULE
A354: 54 | B354: KKM/JKN/HSA/10-05-01/H/22/328 | C354: =VLOOKUP(B:B,'[4]SCHEDULE PPM 2026'!$D:$E,2, FALSE) -> INCUBATOR | D354: =VLOOKUP(B:B,'[2]BEMS EQUIPMENT '!$E:$Q,13,FALSE) -> 28000 | E354: HSASWOBE26003021 | F354: =VLOOKUP(B:B,'[3]SCHEDULE PPM 2026'!$D:$O,12,FALSE) -> Unit Rawatan Rapi Neonatal (NICU) | G354: =VLOOKUP(B:B,'[3]SCHEDULE PPM 2026'!$D:$J,7,FALSE) -> 46036 | H354: 46037 | K354: N | L354: =ROUNDUP((D354/4999.99)*10,-1) -> 60 | M354: =IF(K354="N",0,L354) -> 0 | N354: RESCHEDULE
A355: 57 | B355: KKM/JKN/HSA/10-05-01/R/22/16 | C355: =VLOOKUP(B:B,'[4]SCHEDULE PPM 2026'!$D:$E,2, FALSE) -> FETAL HEART MONITOR | D355: =VLOOKUP(B:B,'[2]BEMS EQUIPMENT '!$E:$Q,13,FALSE) -> 950 | E355: HSASWOBE26003024 | F355: =VLOOKUP(B:B,'[3]SCHEDULE PPM 2026'!$D:$O,12,FALSE) -> PAC | G355: =VLOOKUP(B:B,'[3]SCHEDULE PPM 2026'!$D:$J,7,FALSE) -> 46036 | H355: 46037 | K355: N | L355: =ROUNDUP((D355/4999.99)*10,-1) -> 10 | M355: =IF(K355="N",0,L355) -> 0 | N355: RESCHEDULE
A356: 58 | B356: KKM/JKN/HSA/10-05-01/R/22/18 | C356: =VLOOKUP(B:B,'[4]SCHEDULE PPM 2026'!$D:$E,2, FALSE) -> FETAL HEART MONITOR | D356: =VLOOKUP(B:B,'[2]BEMS EQUIPMENT '!$E:$Q,13,FALSE) -> 950 | E356: HSASWOBE26003025 | F356: =VLOOKUP(B:B,'[3]SCHEDULE PPM 2026'!$D:$O,12,FALSE) -> PAC | G356: =VLOOKUP(B:B,'[3]SCHEDULE PPM 2026'!$D:$J,7,FALSE) -> 46036 | H356: 46037 | K356: N | L356: =ROUNDUP((D356/4999.99)*10,-1) -> 10 | M356: =IF(K356="N",0,L356) -> 0 | N356: RESCHEDULE
...

Sheet B4-UPTIME
A1: MINISTRY OF HEALTH
A2: Deduction Mapping Report Biomedical Engineering Maintenance Services (BEMS)
A3: INDICATOR B.4 UPTIME GUARANTEE
C5: HOSPITAL SHAH ALAM | P5: MONTH/YEAR : | Q5: =BEMSdar!E7 -> 46082
C7: SELANGOR | M7: BEMS MONTHLY FEE (RM)@ 97.5% : | Q7: =BEMSdar!E11 -> 352591.82
C9: AMBANG WIRA SDN BHD | M9: FMS MONTHLY FEE (RM) @ 2.5% : | Q9: =BEMSdar!E13 -> 9040.816
B11: Notes:
B12: 1) Deduction Ringgit Equivalent is based on Appendix 11 of the Agreement, Section B3 Key Deduction Indicators for BEMS
B13: 2) Deduction Value for 1st cut off is Deduction Ringgit Equivalent (per event)
B14: 3) Deduction Value for 2nd cut off is Deduction Ringgit Equivalent (per event) multiply by 2
B15: 4) Display only asset affected by deduction
A17: No. | B17: Asset No | C17: Type Description | D17: Asset Purchase cost | E17: Asset Age | F17: TRKPI % | G17: Uptime % | S17: Deduction Ringgit Equivalent (RM) | T17: Previous Deduction (Month) | V17: Deduction for the month (Y/N) | X17: Deduction Value (RM) | Z17: Total Deduction (RM) | AA17: Remarks
G18: Jan | H18: Feb | I18: Mar | J18: Apr | K18: May | L18: Jun | M18: Jul | N18: Aug | O18: Sep | P18: Oct | Q18: Nov | R18: Dec | T18: 1st | U18: 2nd | V18: 1st | W18: 2nd | X18: 1st | Y18: 2nd
A19: 1 | B19: KKM/JKN/HSA/10-05-01/H/15/2458 | C19: AUDIOMETER | D19: ='B1-RESPONSE & B2-REPAIR'!D213 -> 43690 | E19: 11 | F19: 0.88 | G19: 0.92876712 | H19: 0.85205479 | I19: 0.76712329 | S19: =ROUNDUP((D19/4999.99)*10,-1) -> 90 | T19: Y | W19: Y | X19: =IF(V19="Y",S19,0) -> 0 | Y19: =IF(W19="Y",S19*2,0) -> 180 | Z19: =X19+Y19 -> 180 | AA19: BELUM CLOSE
A20: 2 | B20: KKM/JKN/HSA/10-05-01/H/15/2538 | C20: MAMMOGRAPHY WITH BIOPSY, DIGITAL | D20: ='B1-RESPONSE & B2-REPAIR'!D214 -> 990000 | E20: 11 | F20: 0.85 | G20: 0.9369863 | I20: 0.77534247 | S20: =ROUNDUP((D20/4999.99)*10,-1) -> 1990 | T20: N | W20: N | X20: =IF(V20="Y",S20,0) -> 0 | Y20: =IF(W20="Y",S20*2,0) -> 0 | Z20: =X20+Y20 -> 0 | AA20: BELUM CLOSE, RIW
A21: 3 | B21: KKM/JKN/HSA/10-05-01/H/20/129 | C21: INFUSION PUMP | D21: ='B1-RESPONSE & B2-REPAIR'!D164 -> 3150 | E21: 6 | F21: 0.95 | G21: 0.9369863 | H21: 0.86027397 | I21: 0.77534247 | S21: =ROUNDUP((D21/4999.99)*10,-1) -> 10 | T21: Y | W21: Y | X21: =IF(V21="Y",S21,0) -> 0 | Y21: =IF(W21="Y",S21*2,0) -> 20 | Z21: =X21+Y21 -> 20 | AA21: BELUM CLOSE
A22: 4 | B22: KKM/JKN/HSA/10-05-01/H/20/268 | C22: Ventilators, Intensive Care, Neonatal/Pediatric | D22: ='B1-RESPONSE & B2-REPAIR'!D215 -> 50000 | E22: 6 | F22: 0.95 | G22: 0.93972603 | H22: 0.8630137 | I22: 0.77808219 | S22: =ROUNDUP((D22/4999.99)*10,-1) -> 110 | T22: Y | W22: Y | X22: =IF(V22="Y",S22,0) -> 0 | Y22: =IF(W22="Y",S22*2,0) -> 220 | Z22: =X22+Y22 -> 220 | AA22: BELUM CLOSE
A23: 5 | B23: KKM/JKN/HSA/10-05-01/H/21/291 | C23: Phototherapy Units, Visible Light, Hyperbilirubinemia | D23: ='B1-RESPONSE & B2-REPAIR'!D181 -> 7100 | E23: 5 | F23: 0.99 | G23: 0.94520548 | H23: 0.86849315 | I23: 0.86575342 | S23: =ROUNDUP((D23/4999.99)*10,-1) -> 20 | T23: Y | W23: N | X23: =IF(V23="Y",S23,0) -> 0 | Y23: =IF(W23="Y",S23*2,0) -> 0 | Z23: =X23+Y23 -> 0 | AA23: CLOSE
A24: 6 | B24: KKM/JKN/HSA/10-05-01/H/22/84 | C24: PHOTOTHERAPY MACHINE | D24: ='B1-RESPONSE & B2-REPAIR'!D216 -> 7100 | E24: 4 | F24: 0.99 | G24: 0.94520548 | H24: 0.86849315 | I24: 0.78356164 | S24: =ROUNDUP((D24/4999.99)*10,-1) -> 20 | T24: Y | W24: Y | X24: =IF(V24="Y",S24,0) -> 0 | Y24: =IF(W24="Y",S24*2,0) -> 40 | Z24: =X24+Y24 -> 40 | AA24: BELUM CLOSE
A25: 7 | B25: KKM/JKN/HSA/10-05-01/H/15/1609 | C25: INFANT VENTILATOR | D25: 53000 | E25: 11 | F25: 0.88 | G25: 0.94520548 | S25: =ROUNDUP((D25/4999.99)*10,-1) -> 110 | T25: N | V25: N | X25: =IF(V25="Y",S25,0) -> 0 | Y25: =IF(W25="Y",S25*2,0) -> 0 | Z25: =X25+Y25 -> 0 | AA25: CLOSE
A26: 8 | B26: KKM/JKN/HSA/10-05-01/H/15/4018 | C26: HEMOGLOBIN SYSTEM FOR HBA1C | D26: ='B1-RESPONSE & B2-REPAIR'!D182 -> 67000 | E26: 11 | F26: 0.85 | G26: 0.95068493 | H26: 0.8739726 | I26: 0.8 | S26: =ROUNDUP((D26/4999.99)*10,-1) -> 140 | T26: Y | W26: N | X26: =IF(V26="Y",S26,0) -> 0 | Y26: =IF(W26="Y",S26*2,0) -> 0 | Z26: =X26+Y26 -> 0 | AA26: CLOSE 27/3/26
A27: 9 | B27: KKM/JKN/HSA/10-05-01/H/21/339 | C27: VENTILATOR (NEONATAL) | D27: ='B1-RESPONSE & B2-REPAIR'!D183 -> 137000 | E27: 5 | F27: 0.99 | G27: 0.95342466 | H27: 0.87671233 | I27: 0.83287671 | S27: =ROUNDUP((D27/4999.99)*10,-1) -> 280 | T27: Y | W27: N | X27: =IF(V27="Y",S27,0) -> 0 | Y27: =IF(W27="Y",S27*2,0) -> 0 | Z27: =X27+Y27 -> 0 | AA27: CLOSE
A28: 10 | B28: KKM/JKN/HSA/10-05-01/H/15/581 | C28: PATIENT MONITORING EQUIP.(AUTOMATIC MULTIPARAMETER) | D28: ='B1-RESPONSE & B2-REPAIR'!D184 -> 4300 | E28: 11 | F28: 0.88 | G28: 0.95616438 | H28: 0.89041096 | S28: =ROUNDUP((D28/4999.99)*10,-1) -> 10 | T28: Y | W28: N | X28: =IF(V28="Y",S28,0) -> 0 | Y28: =IF(W28="Y",S28*2,0) -> 0 | Z28: =X28+Y28 -> 0 | AA28: CLOSE
A29: 11 | B29: KKM/JKN/HSA/10-05-01/H/15/479 | C29: INFANT INCUBATOR | D29: 24000 | E29: 11 | F29: 0.88 | H29: 0.95616438 | I29: 0.90136986 | S29: =ROUNDUP((D29/4999.99)*10,-1) -> 50 | T29: N | V29: N | X29: =IF(V29="Y",S29,0) -> 0 | Y29: =IF(W29="Y",S29*2,0) -> 0 | Z29: =X29+Y29 -> 0 | AA29: BELUM CLOSE
A30: 12 | B30: KKM/JKN/HSA/10-05-01/H/17/4 | C30: ULTRASOUND SCANNER/MINDRAY M9 | D30: 198800 | E30: 9 | F30: 0.92 | H30: 0.95890411 | I30: 0.94078957 | S30: =ROUNDUP((D30/4999.99)*10,-1) -> 400 | T30: N | V30: N | X30: =IF(V30="Y",S30,0) -> 0 | Y30: =IF(W30="Y",S30*2,0) -> 0 | Z30: =X30+Y30 -> 0 | AA30: BELUM CLOSE
A31: 13 | B31: KKM/JKN/HSA/10-05-01/H/15/790 | C31: SYRINGE INFUSION PUMP | D31: ='B1-RESPONSE & B2-REPAIR'!D184 -> 4300 | E31: 11 | F31: 0.88 | G31: 0.96164384 | H31: 0.88493151 | I31: 0.83835616 | S31: =ROUNDUP((D31/4999.99)*10,-1) -> 10 | T31: N | V31: Y | X31: =IF(V31="Y",S31,0) -> 10 | Y31: =IF(W31="Y",S31*2,0) -> 0 | Z31: =X31+Y31 -> 10 | AA31: CLOSE 17/3/26
A32: 14 | B32: HSAS10016 | C32: DRILL, SURGICAL, SMALL BONE, PNEUMATIC | D32: ='B1-RESPONSE & B2-REPAIR'!D186 -> 80900 | E32: 10 | F32: 0.95 | G32: 0.96438356 | H32: 0.88767123 | I32: 0.84383562 | S32: =ROUNDUP((D32/4999.99)*10,-1) -> 170 | T32: N | V32: Y | X32: =IF(V32="Y",S32,0) -> 170 | Y32: =IF(W32="Y",S32*2,0) -> 0 | Z32: =X32+Y32 -> 170 | AA32: BELUM CLOSE
A33: 15 | B33: KKM/JKN/HSA/10-05-01/H/15/312 | C33: VENTILATOR | D33: ='B1-RESPONSE & B2-REPAIR'!D217 -> 50000 | E33: 11 | F33: 0.88 | G33: 0.96438356 | H33: 0.88767123 | I33: 0.80273973 | S33: =ROUNDUP((D33/4999.99)*10,-1) -> 110 | T33: N | V33: Y | X33: =IF(V33="Y",S33,0) -> 110 | Y33: =IF(W33="Y",S33*2,0) -> 0 | Z33: =X33+Y33 -> 110 | AA33: BELUM CLOSE
A34: 16 | B34: KKM/JKN/HSA/10-05-01/H/15/985 | C34: ELECTROSURGICAL UNIT | D34: ='B1-RESPONSE & B2-REPAIR'!D218 -> 20328 | E34: 11 | F34: 0.88 | G34: 0.96438356 | H34: 0.88767123 | I34: 0.80273973 | S34: =ROUNDUP((D34/4999.99)*10,-1) -> 50 | T34: N | V34: Y | X34: =IF(V34="Y",S34,0) -> 50 | Y34: =IF(W34="Y",S34*2,0) -> 0 | Z34: =X34+Y34 -> 50 | AA34: BELUM CLOSE
A35: 17 | B35: KKM/JKN/HSA/10-05-01/H/15/2250 | C35: Infusion Pumps, Syringe | D35: ='B1-RESPONSE & B2-REPAIR'!D185 -> 2700 | E35: 11 | F35: 0.88 | G35: 0.96438356 | H35: 0.88767123 | I35: 0.80547945 | S35: =ROUNDUP((D35/4999.99)*10,-1) -> 10 | T35: N | V35: Y | X35: =IF(V35="Y",S35,0) -> 10 | Y35: =IF(W35="Y",S35*2,0) -> 0 | Z35: =X35+Y35 -> 10 | AA35: CLOSE 30/3/26
A36: 18 | B36: KKM/JKN/HSA/10-05-01/H/19/17 | C36: PULSE OXIMETER AND SIMULATOR | D36: ='B1-RESPONSE & B2-REPAIR'!D219 -> 5450 | E36: 7 | F36: 0.95 | G36: 0.96712329 | H36: 0.89041096 | I36: 0.80547945 | S36: =ROUNDUP((D36/4999.99)*10,-1) -> 20 | T36: N | V36: Y | X36: =IF(V36="Y",S36,0) -> 20 | Y36: =IF(W36="Y",S36*2,0) -> 0 | Z36: =X36+Y36 -> 20 | AA36: BELUM CLOSE
A37: 19 | B37: KKM/JKN/HSA/10-05-01/H/15/1236 | C37: INFUSION PUMP | D37: 7245 | E37: 11 | F37: 0.88 | G37: 0.96712329 | S37: =ROUNDUP((D37/4999.99)*10,-1) -> 20 | T37: N | X37: =IF(V37="Y",S37,0) -> 0 | Y37: =IF(W37="Y",S37*2,0) -> 0 | Z37: =X37+Y37 -> 0 | AA37: CLOSE
A38: 20 | B38: KKM/JKN/HSA/10-05-01/H/15/1235 | C38: INFUSION PUMP | D38: 7245 | E38: 11 | F38: 0.88 | G38: 0.96712329 | S38: =ROUNDUP((D38/4999.99)*10,-1) -> 20 | T38: N | X38: =IF(V38="Y",S38,0) -> 0 | Y38: =IF(W38="Y",S38*2,0) -> 0 | Z38: =X38+Y38 -> 0 | AA38: CLOSE
A39: 21 | B39: KKM/JKN/HSA/10-05-01/H/16/85 | C39: PULSE OXIMETER AND SIMULATOR | D39: ='B1-RESPONSE & B2-REPAIR'!D220 -> 7400 | E39: 10 | F39: 0.88 | G39: 0.96986301 | H39: 0.89315068 | I39: 0.80821918 | S39: =ROUNDUP((D39/4999.99)*10,-1) -> 20 | T39: N | V39: N | X39: =IF(V39="Y",S39,0) -> 0 | Y39: =IF(W39="Y",S39*2,0) -> 0 | Z39: =X39+Y39 -> 0 | AA39: BELUM CLOSE
A40: 22 | B40: KKM/JKN/HSA/10-05-01/H/15/3630 | C40: INFANT VENTILATOR | D40: 53000 | E40: 11 | F40: 0.88 | G40: 0.96986301 | S40: =ROUNDUP((D40/4999.99)*10,-1) -> 110 | V40: N | X40: =IF(V40="Y",S40,0) -> 0 | Y40: =IF(W40="Y",S40*2,0) -> 0 | Z40: =X40+Y40 -> 0 | AA40: CLOSE
A41: 23 | B41: KKM/JKN/HSA/10-05-01/H/15/315 | C41: VENTILATOR | D41: ='B1-RESPONSE & B2-REPAIR'!D221 -> 50000 | E41: 11 | F41: 0.95 | G41: 0.97260274 | H41: 0.89589041 | I41: 0.8109589 | S41: =ROUNDUP((D41/4999.99)*10,-1) -> 110 | T41: N | V41: N | X41: =IF(V41="Y",S41,0) -> 0 | Y41: =IF(W41="Y",S41*2,0) -> 0 | Z41: =X41+Y41 -> 0 | AA41: BELUM CLOSE
A42: 24 | B42: KKM/JKN/HSA/10-05-01/H/15/559 | C42: INFANT INCUBATOR | D42: 68000 | E42: 11 | F42: 0.88 | G42: 0.97260274 | S42: =ROUNDUP((D42/4999.99)*10,-1) -> 140 | T42: N | X42: =IF(V42="Y",S42,0) -> 0 | Y42: =IF(W42="Y",S42*2,0) -> 0 | Z42: =X42+Y42 -> 0 | AA42: CLOSE
A43: 25 | B43: KKM/JKN/HSA/10-05-01/H/16/135 | C43: PHOTOTHERAPY MACHINE (LAMP) | D43: ='B1-RESPONSE & B2-REPAIR'!D222 -> 7100 | E43: 10 | F43: 0.95 | G43: 0.97260274 | H43: 0.89589041 | I43: 0.8109589 | S43: =ROUNDUP((D43/4999.99)*10,-1) -> 20 | V43: N | X43: =IF(V43="Y",S43,0) -> 0 | Y43: =IF(W43="Y",S43*2,0) -> 0 | Z43: =X43+Y43 -> 0 | AA43: BELUM CLOSE
A44: 26
A45: 27
A46: 28
A47: 29
A48: 30
A49: 31
A50: 32
A51: 33
A52: 34
A53: 35
A54: 36
A55: 37
... A71: 53
A72: 54 | B72: KKM/JKN/HSA/10-05-01/R/23/8 | C72: PORTABLE FETAL DOPPLER | D72: 1700 | E72: 3 | F72: 0.99 | G72: 0.98630137 | H72: 0.90684932 | I72: 0.89589041 | S72: =ROUNDUP((D72/4999.99)*10,-1) -> 10 | T72: N | V72: N | X72: =IF(V72="Y",S72,0) -> 0 | Y72: =IF(W72="Y",S72*2,0) -> 0 | Z72: =X72+Y72 -> 0 | AA72: CLOSE
A73: 55 | B73: KKM/JKN/HSA/10-05-01/H/22/142 | C73: PATIENT MONITORING EQUIP | D73: 22500 | E73: 4 | F73: 0.99 | H73: 0.90684932 | I73: 0.89863014 | S73: =ROUNDUP((D73/4999.99)*10,-1) -> 50 | T73: N | V73: N | X73: =IF(V73="Y",S73,0) -> 0 | Y73: =IF(W73="Y",S73*2,0) -> 0 | Z73: =X73+Y73 -> 0 | AA73: CLOSE 3/3/26
A74: 56 | B74: KKM/JKN/HSA/10-05-01/H/23/54 | C74: Warming Units, Patient, Radiant, Infant | D74: 19266 | E74: 3 | F74: 0.96 | H74: 0.87671233 | S74: =ROUNDUP((D74/4999.99)*10,-1) -> 40 | T74: Y | W74: N | X74: =IF(V74="Y",S74,0) -> 0 | Y74: =IF(W74="Y",S74*2,0) -> 0 | Z74: =X74+Y74 -> 0 | AA74: CLOSE
A75: 57 | B75: KKM/JKN/HSA/10-05-01/H/23/43 | C75: VIDEO HEAD IMPULSE TEST | D75: 94900.44 | E75: 3 | F75: 0.99 | H75: 0.92876712 | I75: 0.84383562 | S75: =ROUNDUP((D75/4999.99)*10,-1) -> 190 | T75: Y | W75: N | X75: =IF(V75="Y",S75,0) -> 0 | Y75: =IF(W75="Y",S75*2,0) -> 0 | Z75: =X75+Y75 -> 0 | AA75: BELUM CLOSE
A76: 58 | B76: KKM/JKN/HSA/10-05-01/H/21/251 | C76: VOLUMETRIC PUMP | D76: 2400 | E76: 5 | F76: 0.95 | H76: 0.93150685 | I76: 0.84657534 | S76: =ROUNDUP((D76/4999.99)*10,-1) -> 10 | T76: Y | W76: N | X76: =IF(V76="Y",S76,0) -> 0 | Y76: =IF(W76="Y",S76*2,0) -> 0 | Z76: =X76+Y76 -> 0 | AA76: BELUM CLOSE
A77: 59 | B77: KKM/JKN/HSA/10-05-01/H/20/211 | C77: PHOTOTHERAPY MACHINE (LAMP) | D77: 6500 | E77: 6 | F77: 0.95 | H77: 0.9369863 | I77: 0.85205479 | S77: =ROUNDUP((D77/4999.99)*10,-1) -> 20 | T77: Y | W77: N | X77: =IF(V77="Y",S77,0) -> 0 | Y77: =IF(W77="Y",S77*2,0) -> 0 | Z77: =X77+Y77 -> 0
A78: 60 | B78: KKM/JKN/HSA/10-05-01/H/21/104 | C78: INFANT VENTILATOR | D78: 130000 | E78: 5 | F78: 0.99 | H78: 0.9369863 | I78: 0.89589041 | S78: =ROUNDUP((D78/4999.99)*10,-1) -> 270 | T78: Y | W78: N | X78: =IF(V78="Y",S78,0) -> 0 | Y78: =IF(W78="Y",S78*2,0) -> 0 | Z78: =X78+Y78 -> 0 | AA78: CLOSE 5/3/26
A79: 61 | B79: KKM/JKN/HSA/10-05-01/H/23/57 | C79: INFANT WARMER | D79: 19266 | E79: 3 | F79: 0.96 | H79: 0.94520548 | I79: 0.86027397 | S79: =ROUNDUP((D79/4999.99)*10,-1) -> 40 | T79: Y | W79: N | X79: =IF(V79="Y",S79,0) -> 0 | Y79: =IF(W79="Y",S79*2,0) -> 0 | Z79: =X79+Y79 -> 0 | AA79: BELUM CLOSE
A80: 62 | B80: KKM/JKN/HSA/10-05-01/H/23/50 | C80: INFANT WARMER | D80: 19266 | E80: 3 | F80: 0.96 | H80: 0.95342466 | I80: 0.86849315 | S80: =ROUNDUP((D80/4999.99)*10,-1) -> 40 | T80: Y | W80: N | X80: =IF(V80="Y",S80,0) -> 0 | Y80: =IF(W80="Y",S80*2,0) -> 0 | Z80: =X80+Y80 -> 0 | AA80: BELUM CLOSE
A81: 63 | B81: KKM/JKN/HSA/10-05-01/H/21/29 | C81: VENTILATOR | D81: 105000 | E81: 5 | F81: 0.99 | H81: 0.96438356 | I81: 0.87945205 | S81: =ROUNDUP((D81/4999.99)*10,-1) -> 220 | T81: Y | W81: N | X81: =IF(V81="Y",S81,0) -> 0 | Y81: =IF(W81="Y",S81*2,0) -> 0 | Z81: =X81+Y81 -> 0 | AA81: BELUM CLOSE
A82: 64 | B82: KKM/JKN/HSA/10-05-01/R/15/7037 | C82: SCALES BABY DIGITAL/ELECTRONIC W/MEASURE | D82: 1500 | E82: 11 | F82: 0.88 | I82: 0.9679433 | S82: =ROUNDUP((D82/4999.99)*10,-1) -> 10 | V82: N | X82: =IF(V82="Y",S82,0) -> 0 | Y82: =IF(W82="Y",S82*2,0) -> 0 | Z82: =X82+Y82 -> 0 | AA82: BELUM CLOSE
A83: 65 | B83: KKM/JKN/HSA/10-05-01/H/23/55 | C83: INFANT WARMER | D83: 19266 | E83: 3 | F83: 0.96 | I83: 0.95146309 | S83: =ROUNDUP((D83/4999.99)*10,-1) -> 40 | V83: N | X83: =IF(V83="Y",S83,0) -> 0 | Y83: =IF(W83="Y",S83*2,0) -> 0 | Z83: =X83+Y83 -> 0 | AA83: BELUM CLOSE
A84: 66 | B84: KKM/JKN/HSA/10-05-01/H/15/2542 | C84: COMPUTER RADIOGRAPHY (MULTI LOADER & WORKSTATION) | D84: 125000 | E84: 11 | F84: 0.88 | I84: 0.97928082 | S84: =ROUNDUP((D84/4999.99)*10,-1) -> 260 | V84: N | X84: =IF(V84="Y",S84,0) -> 0 | Y84: =IF(W84="Y",S84*2,0) -> 0 | Z84: =X84+Y84 -> 0 | AA84: BELUM CLOSE
A85: 67 | B85: KKM/JKN/HSA/10-05-01/H/23/36 | C85: INFANT INCUBATOR | D85: 49000 | E85: 3 | F85: 0.99 | I85: 0.9444825 | S85: =ROUNDUP((D85/4999.99)*10,-1) -> 100 | V85: N | X85: =IF(V85="Y",S85,0) -> 0 | Y85: =IF(W85="Y",S85*2,0) -> 0 | Z85: =X85+Y85 -> 0 | AA85: BELUM CLOSE
A86: 68 | B86: KKM/JKN/HSA/10-05-01/H/15/4036 | C86: DIALYZER REPROCESSING SYSTEM | D86: 48000 | E86: 11 | F86: 0.88 | I86: 0.94621575 | S86: =ROUNDUP((D86/4999.99)*10,-1) -> 100 | V86: N | X86: =IF(V86="Y",S86,0) -> 0 | Y86: =IF(W86="Y",S86*2,0) -> 0 | Z86: =X86+Y86 -> 0 | AA86: BELUM CLOSE
A87: 69 | B87: KKM/JKN/HSA/10-05-01/R/23/9 | C87: PORTABLE FETAL DOPPLER | D87: 1700 | E87: 3 | F87: 0.99 | I87: 0.97675799 | S87: =ROUNDUP((D87/4999.99)*10,-1) -> 10 | V87: N | X87: =IF(V87="Y",S87,0) -> 0 | Y87: =IF(W87="Y",S87*2,0) -> 0 | Z87: =X87+Y87 -> 0 | AA87: BELUM CLOSE
A88: 70 | B88: KKM/JKN/HSA/10-05-01/H/15/1586 | C88: INFANT WARMER (RADIANT) | D88: 24000 | E88: 11 | F88: 0.85 | I88: 0.91871005 | S88: =ROUNDUP((D88/4999.99)*10,-1) -> 50 | V88: N | X88: =IF(V88="Y",S88,0) -> 0 | Y88: =IF(W88="Y",S88*2,0) -> 0 | Z88: =X88+Y88 -> 0 | AA88: BELUM CLOSE
A89: 71 | B89: KKM/JKN/HSA/10-05-01/H/22/126 | C89: ULTRASOUND SCANNER | D89: 49000 | E89: 4 | F89: 0.96 | I89: 0.92203006 | S89: =ROUNDUP((D89/4999.99)*10,-1) -> 100 | V89: Y | X89: =IF(V89="Y",S89,0) -> 100 | Y89: =IF(W89="Y",S89*2,0) -> 0 | Z89: =X89+Y89 -> 100 | AA89: BELUM CLOSE
A90: 72 | B90: KKM/JKN/HSA/10-05-01/H/22/144 | C90: PATIENT MONITORING EQUIPMENT | D90: 8700 | E90: 4 | F90: 0.99 | I90: 0.9368379 | S90: =ROUNDUP((D90/4999.99)*10,-1) -> 20 | V90: Y | X90: =IF(V90="Y",S90,0) -> 20 | Y90: =IF(W90="Y",S90*2,0) -> 0 | Z90: =X90+Y90 -> 20 | AA90: BELUM CLOSE
A91: 73 | B91: KKM/JKN/HSA/10-05-01/H/15/470 | C91: INFANT INCUBATOR | D91: 24000 | E91: 11 | F91: 0.88 | I91: 0.93818683 | S91: =ROUNDUP((D91/4999.99)*10,-1) -> 50 | V91: N | X91: =IF(V91="Y",S91,0) -> 0 | Y91: =IF(W91="Y",S91*2,0) -> 0 | Z91: =X91+Y91 -> 0 | AA91: BELUM CLOSE
A92: 74 | B92: KKM/JKN/HSA/10-05-01/H/15/475 | C92: INFANT INCUBATOR | D92: 24000 | E92: 11 | F92: 0.88 | I92: 0.93819254 | S92: =ROUNDUP((D92/4999.99)*10,-1) -> 50 | V92: N | X92: =IF(V92="Y",S92,0) -> 0 | Y92: =IF(W92="Y",S92*2,0) -> 0 | Z92: =X92+Y92 -> 0 | AA92: BELUM CLOSE
A93: 75 | B93: KKM/JKN/HSA/10-05-01/H/15/2449 | C93: PATIENT WARMER (BLANKET) | D93: 6560 | E93: 11 | F93: 0.85 | I93: 0.94068493 | S93: =ROUNDUP((D93/4999.99)*10,-1) -> 20 | V93: N | X93: =IF(V93="Y",S93,0) -> 0 | Y93: =IF(W93="Y",S93*2,0) -> 0 | Z93: =X93+Y93 -> 0 | AA93: BELUM CLOSE
A94: TOTAL DEDUCTION FOR IND. B.4: | Z94: =SUM(Z19:Z81) -> 830

Sheet B5-T&C
A1: MINISTRY OF HEALTH
A2: Deduction Mapping Report Biomedical Engineering Maintenance Services (BEMS)
A3: INDICATOR B.5 TESTING & COMMISSIONING AND WARRANTY MANAGEMENT
B5: HOSPITAL NAME : | C5: HOSPITAL SHAH ALAM | I5: MONTH/YEAR : | J5: =BEMSdar!E7 -> 46082
B7: STATE : | C7: SELANGOR | F7: BEMS MONTHLY FEE (RM) @ 97.5 % : | J7: =BEMSdar!E11 -> 352591.82
B9: COMPANY : | C9: AMBANG WIRA SDN BHD | F9: FMS MONTHLY FEE (RM) @ 2.5% : | J9: =BEMSdar!E13 -> 9040.816
A11: Notes:
A12: 1) Deduction Ringgit Equivalent is based on Appendix 11 of the Agreement, Section B3 Key Deduction Indicators for BEMS
A13: 2) Deduction Value is Deduction Ringgit Equivalent (per event)
A14: 3) Display only asset affected by deduction
A15: 4) *May not be applicable for unregistered asset
A16: 5) **Only applicable for under warranty management deduction
A18: No | B18: Work Order/ NCR | C18: Work Order/ NCR Date | D18: Work Order/ NCR Reference No. | E18: Work Order/ NCR Description | F18: User Location | G18: T&C Date | H18: Completion Date | I18: Asset Number* | J18: Asset Description | K18: Warranty Expiry Date** | L18: Asset Purchase Price (RM) | M18: Deduction Ringgit Equivalent (RM) | N18: Validate Status (Y/N) | O18: Deduction Value (RM) | P18: Remarks
A19: Work Order Closed
A20: 1 | B20: HSASWIBE26006661 | C20: 46057 | E20: TNC MESIN OCT DI KLINIK OFTAL | F20: KLINIK OFTALMOLOGI | G20: 46057 | H20: 46083 | I20: H/16/120 | J20: SPECTRAL IMAGING SYSTEM | K20: NA | L20: 0 | N20: N | O20: - | P20: CLOSE, POSTPONE OTHER DATE
A21: Work Order Open
A22: 1
A23: TOTAL DEDUCTION FOR IND. B.5: | O23: 0

Sheet Sheet2
A4: No | B4: Asset No | C4: Asset Description | D4: Asset Purchase Price (RM) | E4: Work Order No. | G4: User Location | H4: Work Order/ Complaint Details | I4: Response Category (Emergency/ Normal) | J4: Total Response Time (minutes) | K4: Work Request Date | L4: Work Completion Date | M4: Deduction Ringgit Equivalent (RM) | N4: Indicator B.1 | Q4: Indicator B.2 | W4: Contract
F5: wo | N5: Validate Status (Y/N) | O5: Deduction Value (RM) | P5: Remarks/ Exemption | Q5: Validate Status (Y/N) | R5: Total Repair Time (day) | S5: Last date of 7 working days (dd/mm/yy) | T5: Demerit Point | U5: Deduction Value (RM) | V5: Remarks/ Exemption | X5: Total Repair Time (day) | Y5: Hours | Z5: Total Hours | AA5: Total Hours / Year | AB5: Balance Uptime | AC5: Uptime Percentage | AD5: Uptime TRKPI | AE5: Uptime Deduction Yes / No
A6: 23 | B6: IKN400966 | C6: LINEAR ACCELERATOR | D6: 12049370 | E6: 1811 | G6: RT159 | H6: Lazer Double | I6: Normal | J6: 0.010416667 | K6: 43781 | L6: 43795 | M6: =IF(D6>44999.99,100,ROUNDUP((D6/4999.99)*10,-1)) -> 100 | N6: N | O6: =IF(N6="Y",M6,0) -> 0 | P6: Response On_Time | Q6: N | R6: =L6-K6+1 -> 15 | S6: =WORKDAY(K6,6,tarikhcuti) -> 43789 | T6: =IF(L6>S6,L6-S6,0) -> 6 | U6: =M6*T6 -> 600 | W6: Strands | X6: =R6 -> 15 | Y6: 24 | Z6: =X6*Y6 -> 360 | AA6: 8072 | AB6: =AA6-Z6 -> 7712 | AC6: =AB6/8072 -> 0.95540139 | AD6: 0.92 | AE6: No
A7: 1 | B7: IKN400292 | C7: Infusion Pumps, General-Purpose | D7: 10825 | E7: 1655 | G7: WAD 8A | H7: Infucient Pump-Mesin Problem | I7: Normal | J7: 0.025694444 | K7: 43774 | L7: 43799 | M7: =IF(D7>44999.99,100,ROUNDUP((D7/4999.99)*10,-1)) -> 30 | N7: N | O7: =IF(N7="Y",M7,0) -> 0 | P7: Response On_Time | Q7: Y | R7: =L7-K7+1 -> 26 | S7: =WORKDAY(K7,6,tarikhcuti) -> 43782 | T7: =IF(L7>S7,L7-S7,0) -> 17 | U7: =M7*T7 -> 510 | W7: Strands | X7: =R7 -> 26 | Y7: 24 | Z7: =X7*Y7 -> 624 | AA7: 8072 | AB7: =AA7-Z7 -> 7448 | AC7: =AB7/8072 -> 0.92269574 | AD7: 0.95 | AE7: Yes
A8: =A7+1 -> 2 | B8: IKN400978 | C8: Scanning Systems, Computed Tomography | D8: 3557530 | E8: 1172 | G8: RT | H8: sendingg image from vsim to mosaiq | I8: Normal | J8: 0.020833333 | K8: 43770 | L8: 43782 | M8: =IF(D8>44999.99,100,ROUNDUP((D8/4999.99)*10,-1)) -> 100 | N8: N | O8: =IF(N8="Y",M8,0) -> 0 | P8: Response On_Time | Q8: N | R8: =L8-K8+1 -> 13 | S8: 43763 | T8: =R8 -> 13 | U8: =M8*T8 -> 1300 | W8: Strands | X8: =R8 -> 13 | Y8: 24 | Z8: =X8*Y8 -> 312 | AA8: 8072 | AB8: =AA8-Z8 -> 7760 | AC8: =AB8/8072 -> 0.96134787 | AD8: 0.95 | AE8: No
A9: =A8+1 -> 3 | B9: IKN400973 | C9: Scanning Systems, Computed Tomography | D9: 3557530 | E9: 1173 | G9: RT | H9: sendingg image from vsim to mosaiq | I9: Normal | J9: 0.013888889 | K9: 43770 | L9: 43782 | M9: =IF(D9>44999.99,100,ROUNDUP((D9/4999.99)*10,-1)) -> 100 | N9: N | O9: =IF(N9="Y",M9,0) -> 0 | P9: Response On_Time | Q9: N | R9: =L9-K9+1 -> 13 | S9: 43763 | T9: =R9 -> 13 | U9: =M9*T9 -> 1300 | W9: Strands | X9: =R9 -> 13 | Y9: 24 | Z9: =X9*Y9 -> 312 | AA9: 8072 | AB9: =AA9-Z9 -> 7760 | AC9: =AB9/8072 -> 0.96134787 | AD9: 0.95 | AE9: No
A10: =A9+1 -> 4 | B10: IKN400151 | C10: Mattress Systems, Alternating-Pressure | D10: 28630 | E10: 1449 | G10: WAD 7A | H10: Motor ripple mattress rosak | I10: Normal | J10: 0.027777778 | K10: 43770 | L10: 43775 | M10: =IF(D10>44999.99,100,ROUNDUP((D10/4999.99)*10,-1)) -> 60 | N10: N | O10: =IF(N10="Y",M10,0) -> 0 | P10: Response On_Time | Q10: N | R10: =L10-K10+1 -> 6 | S10: 43774 | T10: =R10 -> 6 | U10: =M10*T10 -> 360 | W10: Strands | X10: =R10 -> 6 | Y10: 24 | Z10: =X10*Y10 -> 144 | AA10: 8072 | AB10: =AA10-Z10 -> 7928 | AC10: =AB10/8072 -> 0.98216056 | AD10: 0.92 | AE10: No
A11: =A10+1 -> 5 | B11: IKN400967 | C11: Linear Accelerators | D11: 12049370 | E11: 1471 | G11: RT | H11: Table verticle movement problem | I11: Normal | J11: 0.065972222 | K11: 43770 | L11: 43773 | M11: =IF(D11>44999.99,100,ROUNDUP((D11/4999.99)*10,-1)) -> 100 | N11: N | O11: =IF(N11="Y",M11,0) -> 0 | P11: Response On_Time | Q11: N | R11: =L11-K11+1 -> 4 | S11: 43775 | T11: =R11 -> 4 | U11: =M11*T11 -> 400 | W11: Strands | X11: =R11 -> 4 | Y11: 24 | Z11: =X11*Y11 -> 96 | AA11: 8072 | AB11: =AA11-Z11 -> 7976 | AC11: =AB11/8072 -> 0.98810704 | AD11: 0.92 | AE11: No
A12: =A11+1 -> 6 | B12: NB 355296 | C12: Mattress Systems, Alternating-Pressure | D12: 28630 | E12: 1476 | G12: WAD 7B | H12: Ripple Mattress tidak boleh pump | I12: Normal | J12: 0.023611111 | K12: 43770 | L12: 43775 | M12: =IF(D12>44999.99,100,ROUNDUP((D12/4999.99)*10,-1)) -> 60 | N12: N | O12: =IF(N12="Y",M12,0) -> 0 | P12: Response On_Time | Q12: N | R12: =L12-K12+1 -> 6 | S12: 43775 | T12: =R12 -> 6 | U12: =M12*T12 -> 360 | W12: #N/A | X12: =R12 -> 6 | Y12: 24 | Z12: =X12*Y12 -> 144 | AA12: 8072 | AB12: =AA12-Z12 -> 7928 | AC12: =AB12/8072 -> 0.98216056 | AD12: 0.92 | AE12: No
A13: =A12+1 -> 7 | B13: IKN400350 | C13: Sphygmomanometers, Electronic, Automatic | D13: 4510 | E13: 1496 | G13: WAD 7B | H13: BP Set warna putih rosak. | I13: Normal | J13: 0.010416667 | K13: 43770 | L13: 43775 | M13: =IF(D13>44999.99,100,ROUNDUP((D13/4999.99)*10,-1)) -> 10 | N13: N | O13: =IF(N13="Y",M13,0) -> 0 | P13: Response On_Time | Q13: N | R13: =L13-K13+1 -> 6 | S13: 43775 | T13: =R13 -> 6 | U13: =M13*T13 -> 60 | W13: Strands | X13: =R13 -> 6 | Y13: 24 | Z13: =X13*Y13 -> 144 | AA13: 8072 | AB13: =AA13-Z13 -> 7928 | AC13: =AB13/8072 -> 0.98216056 | AD13: 0.92 | AE13: No
A14: =A13+1 -> 8 | B14: IKN400775 | C14: Scanning Systems, Ultrasonic, General-Purpose | D14: 1044560 | E14: 1535 | G14: ID | H14: Ultrasound tidak keluar gambar | I14: Normal | J14: 0.017361111 | K14: 43770 | L14: 43773 | M14: =IF(D14>44999.99,100,ROUNDUP((D14/4999.99)*10,-1)) -> 100 | N14: N | O14: =IF(N14="Y",M14,0) -> 0 | P14: Response On_Time | Q14: N | R14: =L14-K14+1 -> 4 | S14: 43776 | T14: =R14 -> 4 | U14: =M14*T14 -> 400 | W14: Strands | X14: =R14 -> 4 | Y14: 24 | Z14: =X14*Y14 -> 96 | AA14: 8072 | AB14: =AA14-Z14 -> 7976 | AC14: =AB14/8072 -> 0.98810704 | AD14: 0.95 | AE14: No
A15: =A14+1 -> 9 | B15: IKN400567 | C15: Cameras, Gamma | D15: 3191750 | E15: 1550 | G15: NM | H15: MEGP detector one collision | I15: Normal | J15: 0.0034722222 | K15: 43770 | L15: 43773 | M15: =IF(D15>44999.99,100,ROUNDUP((D15/4999.99)*10,-1)) -> 100 | N15: N | O15: =IF(N15="Y",M15,0) -> 0 | P15: Response On_Time | Q15: N | R15: =L15-K15+1 -> 4 | S15: 43777 | T15: =R15 -> 4 | U15: =M15*T15 -> 400 | W15: Strands | X15: =R15 -> 4 | Y15: 24 | Z15: =X15*Y15 -> 96 | AA15: 8072 | AB15: =AA15-Z15 -> 7976 | AC15: =AB15/8072 -> 0.98810704 | AD15: 0.92 | AE15: No
A16: =A15+1 -> 10 | B16: IKN400786 | C16: Radiographic/Fluoroscopic Systems, Angiographic/Intervention | D16: 3191750 | E16: 1565 | G16: ID | H16: Request for user training at Radiology Department (Angio) on 23/10/2019. | I16: Normal | J16: 0 | K16: 43770 | L16: 43773 | M16: =IF(D16>44999.99,100,ROUNDUP((D16/4999.99)*10,-1)) -> 100 | N16: N | O16: =IF(N16="Y",M16,0) -> 0 | P16: Response On_Time | Q16: N | R16: =L16-K16+1 -> 4 | S16: 43777 | T16: =R16 -> 4 | U16: =M16*T16 -> 400 | W16: Strands | X16: =R16 -> 4 | Y16: 24 | Z16: =X16*Y16 -> 96 | AA16: 8072 | AB16: =AA16-Z16 -> 7976 | AC16: =AB16/8072 -> 0.98810704 | AD16: 0.92 | AE16: No
U17: =SUM(U6:U16) -> 6090
