Workbook
Name _05_04_2009: #REF!
Name _05_04_2009: #REF!
Name _05_04_2009: #REF!
Name _05_04_2009: #REF!
Name _05_04_2009: #REF!
Name a: '[1]Term Outstanding Payment'!#REF!
Name a: '[1]Term Outstanding Payment'!#REF!
Name a: '[1]Term Outstanding Payment'!#REF!
Name a: '[1]Term Outstanding Payment'!#REF!
Name a: '[1]Term Outstanding Payment'!#REF!
Name AA: #REF!
Name AA: #REF!
Name AA: #REF!
Name AA: #REF!
Name AA: #REF!
Name aaa: #REF!
Name aaa: #REF!
Name aaa: #REF!
Name aaa: #REF!
Name aaa: #REF!
Name aaaaa: #REF!
Name aaaaa: #REF!
Name aaaaa: #REF!
Name aaaaa: #REF!
Name aaaaa: #REF!
Name aaaaaaaaaa: #REF!
Name aaaaaaaaaa: #REF!
Name aaaaaaaaaa: #REF!
Name aaaaaaaaaa: #REF!
Name AAAAAAAAAAAAA: #REF!
Name AAAAAAAAAAAAA: #REF!
Name AAAAAAAAAAAAA: #REF!
Name AAAAAAAAAAAAA: #REF!
Name AAAAAAAAAAAAAAAAAA: #REF!
Name AAAAAAAAAAAAAAAAAA: #REF!
Name AAAAAAAAAAAAAAAAAA: #REF!
Name AAAAAAAAAAAAAAAAAA: #REF!
Name AAAAAAAAAAAAAAAAAAAAA: #REF!
Name AAAAAAAAAAAAAAAAAAAAA: #REF!
Name AAAAAAAAAAAAAAAAAAAAA: #REF!
Name AAAAAAAAAAAAAAAAAAAAA: #REF!
Name AAAAAAAAAAAAAAAAAAAAAAAAAAA: #REF!
Name AAAAAAAAAAAAAAAAAAAAAAAAAAA: #REF!
Name AAAAAAAAAAAAAAAAAAAAAAAAAAA: #REF!
Name AAAAAAAAAAAAAAAAAAAAAAAAAAA: #REF!
Name AAAAAAAAAAAAAAAAAAAAAAAAAAAA: #REF!
Name AAAAAAAAAAAAAAAAAAAAAAAAAAAA: #REF!
Name AAAAAAAAAAAAAAAAAAAAAAAAAAAA: #REF!
Name AAAAAAAAAAAAAAAAAAAAAAAAAAAA: #REF!
Name AAAAAAAAAAAAAAAAAAAAAAAAAAAAAA: #REF!
Name AAAAAAAAAAAAAAAAAAAAAAAAAAAAAA: #REF!
Name AAAAAAAAAAAAAAAAAAAAAAAAAAAAAA: #REF!
Name AAAAAAAAAAAAAAAAAAAAAAAAAAAAAA: #REF!
Name AAAAAAAAAAAAAAAAAAAAAAAAAAAAAAA: #REF!
Name AAAAAAAAAAAAAAAAAAAAAAAAAAAAAAA: #REF!
Name AAAAAAAAAAAAAAAAAAAAAAAAAAAAAAA: #REF!
Name AAAAAAAAAAAAAAAAAAAAAAAAAAAAAAA: #REF!
Name AAAAAAAAAAAAAAAAAAAAAAAAAAAAAAAAA: #REF!
Name AAAAAAAAAAAAAAAAAAAAAAAAAAAAAAAAA: #REF!
Name AAAAAAAAAAAAAAAAAAAAAAAAAAAAAAAAA: #REF!

Sheet KDI
A1: Indicator No. | B1: Indicator | E1: Frequency of Deduction | F1: Biomedical Equipment Purchase Cost (RM) | H1: Deduction Range Value (RM) | J1: Maximum Demerit Point per Work Order
F2: From | G2: To
A3: B.1 | B3: The Company shall respond to the request within the specified time frame | E3: Per event | F3: 0.00 5,000.00 10,000.00 15,000.00 20,000.00 25,000.00 30,000.00 35,000.00 40,000.00 > 45,000.00 | G3: 4,999.99 9,999.99 14,999.99 19,999.99 24,999.99 29,999.99 34,999.99 39,999.99 44,999.99 | H3: 10.00 20.00 30.00 40.00 50.00 60.00 70.00 80.00 90.00 100.00 | J3: 1
A4: B.2 | B4: The Company shall carry out repairs to restore faulty medical equipment to a specified condition when it fails to function as per manufacturer’s specification within seven (7) working days. | E4: Per day | F4: 0.00 5,000.00 10,000.00 15,000.00 20,000.00 25,000.00 30,000.00 35,000.00 40,000.00 > 45,000.00 | G4: 4,999.99 9,999.99 14,999.99 19,999.99 24,999.99 29,999.99 34,999.99 39,999.99 44,999.99 | H4: 10.00 20.00 30.00 40.00 50.00 60.00 70.00 80.00 90.00 100.00 | J4: Number of working days for the month
A5: B.3 | B5: The Company shall carry out scheduled maintenance as per schedule in accordance to the procedure as specified in Agreement. Scheduled maintenance shall include complete safety and performance tests. | E5: Per event | F5: 0.00 5,000.00 10,000.00 15,000.00 20,000.00 25,000.00 30,000.00 35,000.00 40,000.00 45,000.00 | G5: 4,999.99 9,999.99 14,999.99 19,999.99 24,999.99 29,999.99 34,999.99 39,999.99 44,999.99 49,999.99 | H5: 10.00 20.00 30.00 40.00 50.00 60.00 70.00 80.00 90.00 100.00 | J5: 1
F6: For every RM 5,000 increment of equipment cost, an increase of RM10 will be applied subsequently
A7: B.4 | B7: The Company shall ensure biomedical equipment meets the uptime target as set in the Agreement. | E7: Per event | H7: 1st level of Uptime Target (TRKPI) | I7: 2nd level of Uptime Target (80%) | J7: 2
F8: 0.00 5,000.00 10,000.00 15,000.00 20,000.00 25,000.00 30,000.00 35,000.00 40,000.00 45,000.00 | G8: 4,999.99 9,999.99 14,999.99 19,999.99 24,999.99 29,999.99 34,999.99 39,999.99 44,999.99 49,999.99 | H8: 10.00 20.00 30.00 40.00 50.00 60.00 70.00 80.00 90.00 100.00 | I8: 20.00 40.00 60.00 80.00 100.00 120.00 140.00 160.00 180.00 200.00
F9: For every RM 5,000 increment of equipment cost, an increase of RM10 will be applied subsequently for 1st Uptime Target and an increase of RM20 for 2nd Uptime Target will be applied subsequently
A10: B.5 | B10: The Company shall attend and witness T&C and manage biomedical equipment within the warranty period. | E10: Per event | F10: 0.00 5,000.00 10,000.00 15,000.00 20,000.00 25,000.00 30,000.00 35,000.00 40,000.00 45,000.00 | G10: 4,999.99 9,999.99 14,999.99 19,999.99 24,999.99 29,999.99 34,999.99 39,999.99 44,999.99 49,999.99 | H10: 10.00 20.00 30.00 40.00 50.00 60.00 70.00 80.00 90.00 100.00 | J10: 1
F11: For every RM 5,000 increment of equipment cost, an increase of RM10 will be applied subsequently

Sheet Public Holiday
A1: ­
A2: Tarikh | B2: Hari | C2: Cuti | D2: Negeri Berkenaan
A4: 45658 | B4: Rabu | C4: Tahun Baru | D4: Putrajaya
A6: 45686 | B6: Rabu | C6: Tahun Baru Cina | D6: Putrajaya
A8: 45687 | B8: Khamis | C8: Tahun Baru Cina Hari Kedua | D8: Putrajaya
A10: 45689 | B10: Sabtu | C10: Hari Wilayah Persekutuan | D10: Putrajaya
A12: 45699 | B12: Selasa | C12: Hari Thaipusam | D12: Putrajaya
A14: 45734 | B14: Selasa | C14: Hari Nuzul Al-Quran | D14: Putrajaya
A16: 45748 | B16: Selasa | C16: Hari Raya Aidilfitri | D16: Putrajaya
A18: 45749 | B18: Rabu | C18: Hari Raya Aidilfitri Hari Kedua | D18: Putrajaya
A20: 45778 | B20: Khamis | C20: Hari Pekerja | D20: Putrajaya
A22: 45789 | B22: Isnin | C22: Hari Wesak | D22: Putrajaya
A24: 45810 | B24: Isnin | C24: Hari Keputeraan YDP Agong | D24: Putrajaya
A26: 45815 | B26: Sabtu | C26: Hari Raya Haji | D26: Putrajaya
... A42: 46016 | B42: Khamis | C42: Hari Krismas | D42: Putrajaya
A45: * Subject to change (Tertakluk kepada perubahan), TBC - To be confirmed

Sheet BEMSdar
A1: MINISTRY OF HEALTH
A2: Deduction Mapping Report Biomedical Engineering Maintenance Services (BEMS)
D5: HOSPITAL NAME : | E5: Institut Kanser Negara | I5: STATE: | J5: W.P. Putrajaya
D7: MONTH/YEAR : | E7: 46023 | I7: COMPANY: | J7: Ambang Wira Sdn Bhd
A9: MONTHLY SERVICE FEE (RM) : | E9: 1474733.1
A11: BEMS MONTHLY FEE (RM) @ 97.5% : | E11: =97.5%*E9 -> 1437864.8
A13: FMS MONTHLY FEE (RM) @ 2.5% : | E13: =2.5%*E9 -> 36868.327
A17: No | B17: Key Deduction Indicators | I17: Frequency | L17: Deduction Value (RM) | N17: Deduction % | O17: Performance Level (%)
A19: B.1 | B19: All service requests shall be responded by the Company’s trained technical personal within the timeframe as stipulated in the Agreement. | I19: Per event | L19: ='B1&B2 UNSCHEDULED'!O122 -> 40 | N19: 0 | O19: =100-N19 -> 100
A20: B.2 | B20: All unscheduled maintenance works including relevant maintenance calibration, safety tests and functional checks shall be completed within seven (7) working days. | I20: Per day | L20: ='B1&B2 UNSCHEDULED'!U122 -> 2850 | N20: =L20/$E$11% -> 0.19821057 | O20: =100-N20 -> 99.801789
A21: B.3 | B21: Scheduled maintenance shall be carried out as per schedule and according to the procedure as specified in the Agreement. Scheduled maintenance shall include complete safety and performance tests. | I21: Per event | L21: ='B3-SCHEDULED'!L131 -> 800 | N21: =L21/$E$11% -> 0.055638055 | O21: =100-N21 -> 99.944362
A22: B.4 | B22: All biomedical equipment shall be functioning and maintained to ensure uptime target as specified in the TRKPI are met. | I22: Per event | L22: ='B4-UPTIME '!AA35 -> 0 | N22: =L22/$E$11% -> 0 | O22: =100-N22 -> 100
A23: B.5 | B23: T&C and Warranty Management of newly introduced biomedical shall be managed and performed according to the Agreement and related acts, standards and regulations. | I23: Per event | L23: ='B5-T&C'!O21 -> 0 | N23: =L23/$E$11% -> 0 | O23: =100-N23 -> 100
A24: Total | L24: =SUM(L19:M23) -> 3690 | N24: =SUM(N19:N23) -> 0.25384863 | O24: =100-N24 -> 99.746151
C27: Prepared by: | I27: Verified by:
C31: Siti Norsaliana Binti Abu Khalid | I31: Mohd Shahrulnizam bin Tarmizi
C32: Head of BEMS | I32: Facility Manager
C33: Ambang Wira Sdn Bhd- Institut Kanser Negara | I33: Ambang Wira Sdn Bhd- Institut Kanser Negara
C34: Date: | I34: Date:

Sheet B1&B2 UNSCHEDULED
A2: MINISTRY OF HEALTH
A3: Deduction Mapping Report Biomedical Engineering Maintenance Services (BEMS)
A4: INDICATOR B.1 RESPONSE TIME & B.2 REPAIR TIME
A6: HOSPITAL NAME: | C6: INSTITUT KANSER NEGARA | I6: FIRST DATE OF THE MONTH : | M6: 46023 | Q6: (For Calculation)
A8: STATE: | C8: WILAYAH PERSEKUTUAN PUTRAJAYA | I8: LAST DATE OF THE MONTH : | M8: 46053 | Q8: (For Calculation)
A10: COMPANY: | C10: AMBANG WIRA SDN BHD | I10: BEMS MONTHLY FEE (RM) @ 97.5% : | M10: =BEMSdar!E11 -> 1437864.8
A12: MONTH/YEAR: | C12: 46023 | I12: FMS MONTHLY FEE (RM) @ 2.5% : | M12: =BEMSdar!E13 -> 36868.327
A14: Notes:
A15: 1) Deduction Ringgit Equivalent is based on Appendix 11 of the Agreement, Section B3 Key Deduction Indicators for BEMS
A16: 2) Deduction Value for Indicator B.1 is Deduction Ringgit Equivalent (per event)
A17: 3) Total Repair Time includes weekend & public holiday
A18: 4) Demerit Point for Indicator B.2 is calculated based on completion date against request date, less by 7 working days
A19: 5) Deduction Value for Indicator B.2 is Demerit Point multiply by Deduction Ringgit Equivalent
A21: No | B21: Asset No | C21: Asset Description | D21: Asset Purchase Price (RM) | E21: Work Order No. | F21: User Location | G21: Work Order/ Complaint Details | H21: Response Category (Emergency/ Normal) | I21: Total Response Time (minutes) | J21: Work Request Date | K21: Response Time (Minutes) | L21: Work Completion Date | M21: Deduction Ringgit Equivalent (RM) | N21: Indicator B.1 | Q21: Indicator B.2
N22: Validate Status (Y/N) | O22: Deduction Value (RM) | P22: Remarks/ Exemption | Q22: Validate Status (Y/N) | R22: Total Repair Time (day) | S22: Last date of 7 working days (dd/mm/yy) | T22: Demerit Point | U22: Deduction Value (RM) | V22: Remarks/ Exemption
A23: Current Month (Work Order Completed)
A24: 1 | B24: IKN400404 | C24: =VLOOKUP(B24,[13]AssetDetails_UEM!$A$3:$AH$1849,6,FALSE) -> Sphygmomanometers, Electronic, Automatic | D24: =VLOOKUP(B24,[13]AssetDetails_UEM!$A$3:$AK$1849,22,FALSE) -> 4510 | E24: IKNWIBE26000053 | F24: 06WD146 | G24: BP ALARM , CALL FOR SERVICE | H24: Normal | I24: 0 days, 0 hrs, 13 mins | J24: 02-Jan-2026 08:17:00 | K24: 02-Jan-2026 08:30:00 | L24: 08-Jan-2026 11:10:00 | M24: =IF(D24>44999.99,100,ROUNDUP((D24/4999.99)*10,-1)) -> 10 | N24: N | O24: ='[14]B1& B2 UNSCHEDULED'!$O$24 -> 0 | Q24: N | R24: =IF(L24="",AKHIR-J24,L24-J24+1) -> 7.1201389 | S24: =WORKDAY(J24,6,AKHIR) -> 46034 | T24: 0 | U24: =IF(Q24="N",0,M24*T24) -> 0 | V24: P - qe:12,DO PERFORMANCE TEST PASSED , UNIT READY TO USE
A25: 2 | B25: IKN400741 | C25: =VLOOKUP(B25,[13]AssetDetails_UEM!$A$3:$AH$1849,6,FALSE) -> Analyzers, Laboratory, Microbiology, Blood Culture, Automate | D25: =VLOOKUP(B25,[13]AssetDetails_UEM!$A$3:$AK$1849,22,FALSE) -> 342820 | E25: IKNWIBE26000058 | F25: 04LA126 | G25: THERMOMETER OUT OF BATTERY | H25: Normal | I25: 0 days, 0 hrs, 7 mins | J25: 02-Jan-2026 10:33:00 | K25: 02-Jan-2026 10:40:00 | L25: 02-Jan-2026 16:00:00 | M25: =IF(D25>44999.99,100,ROUNDUP((D25/4999.99)*10,-1)) -> 100 | N25: N | O25: ='[14]B1& B2 UNSCHEDULED'!$O$24 -> 0 | Q25: N | R25: =IF(L25="",AKHIR-J25,L25-J25+1) -> 1.2270833 | S25: =WORKDAY(J25,6,AKHIR) -> 46034 | T25: 0 | U25: =IF(Q25="N",0,M25*T25) -> 0 | V25: M-REPLACE NEW BATTERY ,TESTING OKAY AND FUNCTIONING
A26: 3 | B26: IKN400403 | C26: =VLOOKUP(B26,[13]AssetDetails_UEM!$A$3:$AH$1849,6,FALSE) -> Sphygmomanometers, Electronic, Automatic | D26: =VLOOKUP(B26,[13]AssetDetails_UEM!$A$3:$AK$1849,22,FALSE) -> 4510 | E26: IKNWIBE26000069 | F26: 06WD146 | G26: CUFF KOYAK | H26: Normal | I26: 0 days, 0 hrs, 0 mins | J26: 02-Jan-2026 11:30:00 | K26: 02-Jan-2026 11:30:00 | L26: 02-Jan-2026 12:00:00 | M26: =IF(D26>44999.99,100,ROUNDUP((D26/4999.99)*10,-1)) -> 10 | N26: N | O26: ='[14]B1& B2 UNSCHEDULED'!$O$24 -> 0 | Q26: N | R26: =IF(L26="",AKHIR-J26,L26-J26+1) -> 1.0208333 | S26: =WORKDAY(J26,6,AKHIR) -> 46034 | T26: 0 | U26: =IF(Q26="N",0,M26*T26) -> 0 | V26: P-REQUEST FOR LARGE CUFF. TESTING OKAY AND FUNCTIONING
A27: 4 | B27: IKN400262 | C27: =VLOOKUP(B27,[13]AssetDetails_UEM!$A$3:$AH$1849,6,FALSE) -> Oximeters, Pulse | D27: =VLOOKUP(B27,[13]AssetDetails_UEM!$A$3:$AK$1849,22,FALSE) -> 5410 | E27: IKNWIBE26000094 | F27: 08WG113 | G27: MACHINE SPO2 NOT FUNCTIONING / OUT OF BATTERY | H27: Normal | I27: 0 days, 0 hrs, 45 mins | J27: 04-Jan-2026 11:15:00 | K27: 04-Jan-2026 12:00:00 | L27: 04-Jan-2026 13:00:00 | M27: =IF(D27>44999.99,100,ROUNDUP((D27/4999.99)*10,-1)) -> 20 | N27: N | O27: ='[14]B1& B2 UNSCHEDULED'!$O$24 -> 0 | Q27: N | R27: =IF(L27="",AKHIR-J27,L27-J27+1) -> 1.0729167 | S27: =WORKDAY(J27,7,AKHIR) -> 46035 | T27: 0 | U27: =IF(Q27="N",0,M27*T27) -> 0 | V27: M-REPLACE NEW BATTERY .TESTED OKAY AND CAN FUNCTIONING
A28: 5 | B28: IKN400774 | C28: =VLOOKUP(B28,[13]AssetDetails_UEM!$A$3:$AH$1849,6,FALSE) -> Scanning Systems, Computed Tomography | D28: =VLOOKUP(B28,[13]AssetDetails_UEM!$A$3:$AK$1849,22,FALSE) -> 4605710 | E28: IKNWIBE26000163 | F28: 03ID156 | G28: IMAGE UNABLE TO BE SEND TO PACS, SENDING INFO TO RADIMETRIC FAILED | H28: Normal | I28: 0 days, 0 hrs, 15 mins | J28: 05-Jan-2026 11:33:00 | K28: 46027.49 | L28: 05-Jan-2026 12:00:00 | M28: =IF(D28>44999.99,100,ROUNDUP((D28/4999.99)*10,-1)) -> 100 | N28: N | O28: ='[14]B1& B2 UNSCHEDULED'!$O$24 -> 0 | Q28: N | R28: =IF(L28="",AKHIR-J28,L28-J28+1) -> 1.01875 | S28: =WORKDAY(J28,6,AKHIR) -> 46035 | T28: 0 | U28: =IF(Q28="N",0,M28*T28) -> 0 | V28: L- VENDOR COME AND SETTLE REDIMETRIC ISSUE, TESTED OKAY
A29: 6 | B29: IKN400681 | C29: =VLOOKUP(B29,[13]AssetDetails_UEM!$A$3:$AH$1849,6,FALSE) -> Sphygmomanometers, Electronic, Automatic | D29: =VLOOKUP(B29,[13]AssetDetails_UEM!$A$3:$AK$1849,22,FALSE) -> 336 | E29: IKNWIBE26000172 | F29: 04TC127 | G29: CHARGER CABLE FAULTY | H29: Normal | I29: 0 days, 0 hrs, 49 mins | J29: 05-Jan-2026 15:36:00 | K29: 05-Jan-2026 16:25:00 | L29: 12-Jan-2026 16:30:00 | M29: =IF(D29>44999.99,100,ROUNDUP((D29/4999.99)*10,-1)) -> 10 | N29: N | O29: ='[14]B1& B2 UNSCHEDULED'!$O$24 -> 0 | Q29: N | R29: =IF(L29="",AKHIR-J29,L29-J29+1) -> 8.0375 | S29: =WORKDAY(J29,6,AKHIR) -> 46035 | T29: 0 | U29: =IF(Q29="N",0,M29*T29) -> 0 | V29: AN- REPLACE NEW CABLE, UNIT TEST FUNCTIONING IN GOOD CONDITION
A30: 7 | B30: IKN400758 | C30: =VLOOKUP(B30,[13]AssetDetails_UEM!$A$3:$AH$1849,6,FALSE) -> Analyzers, Laboratory, Urine, Automated | D30: =VLOOKUP(B30,[13]AssetDetails_UEM!$A$3:$AK$1849,22,FALSE) -> 36080 | E30: IKNWIBE26000232 | F30: 04LA132 | G30: ALARM LIGHT BLINKING, NOT PROPER SHUTDOWN | H30: Normal | I30: 0 days, 1 hrs, 1 mins | J30: 06-Jan-2026 08:59:00 | K30: 06-Jan-2026 10:00:00 | L30: 06-Jan-2026 10:30:00 | M30: =IF(D30>44999.99,100,ROUNDUP((D30/4999.99)*10,-1)) -> 80 | N30: N | O30: ='[14]B1& B2 UNSCHEDULED'!$O$24 -> 0 | Q30: N | R30: =IF(L30="",AKHIR-J30,L30-J30+1) -> 1.0631944 | S30: =WORKDAY(J30,6,AKHIR) -> 46036 | T30: 0 | U30: =IF(Q30="N",0,M30*T30) -> 0 | V30: AN- RESTART SOFTWARE UNIT (TAUFIQ BEMS)
A31: 8 | B31: IKN400756 | C31: =VLOOKUP(B31,[13]AssetDetails_UEM!$A$3:$AH$1849,6,FALSE) -> Analyzers, Laboratory, Hematology, Coagulation, Automated | D31: =VLOOKUP(B31,[13]AssetDetails_UEM!$A$3:$AK$1849,22,FALSE) -> 105860 | E31: IKNWIBE26000233 | F31: 04LA132 | G31: SAMPLE TUBING MOVING UP WHEN SAMPLE SYRINGE MOVING UPWARD, SAMPLE CAP DEFECT | H31: Normal | I31: 0 days, 0 hrs, 33 mins | J31: 06-Jan-2026 09:27:00 | K31: 06-Jan-2026 10:00:00 | L31: 06-Jan-2026 16:00:00 | M31: =IF(D31>44999.99,100,ROUNDUP((D31/4999.99)*10,-1)) -> 100 | N31: N | O31: ='[14]B1& B2 UNSCHEDULED'!$O$24 -> 0 | Q31: N | R31: =IF(L31="",AKHIR-J31,L31-J31+1) -> 1.2729167 | S31: =WORKDAY(J31,6,AKHIR) -> 46036 | T31: 0 | U31: =IF(Q31="N",0,M31*T31) -> 0 | V31: AN- REPLACE ANOTHER CAP (TAUFIK BEMS)
A32: 9 | B32: IKN401519 | C32: =VLOOKUP(B32,[13]AssetDetails_UEM!$A$3:$AH$1849,6,FALSE) -> Analyzers, Physiologic, Body Composition | D32: =VLOOKUP(B32,[13]AssetDetails_UEM!$A$3:$AK$1849,22,FALSE) -> 9500 | E32: IKNWIBE26000331 | F32: 03DU103 | G32: PERFORM YEARLY CALIBRATION | H32: Normal | I32: 0 days, 0 hrs, 10 mins | J32: 07-Jan-2026 10:00:00 | K32: 46029.424 | L32: 07-Jan-2026 11:40:00 | M32: =IF(D32>44999.99,100,ROUNDUP((D32/4999.99)*10,-1)) -> 20 | N32: N | O32: ='[14]B1& B2 UNSCHEDULED'!$O$24 -> 0 | Q32: N | R32: =IF(L32="",AKHIR-J32,L32-J32+1) -> 1.0694444 | S32: =WORKDAY(J32,6,AKHIR) -> 46037 | T32: 0 | U32: =IF(Q32="N",0,M32*T32) -> 0 | V32: L, QE:16-CALIBRATION DONE BY SIRIM , REFER TO CALIBRATION SERTIFICATION AS ATTACHED
A33: 10 | B33: IKN400877 | C33: =VLOOKUP(B33,[13]AssetDetails_UEM!$A$3:$AH$1849,6,FALSE) -> Concentrators, Oxygen | D33: =VLOOKUP(B33,[13]AssetDetails_UEM!$A$3:$AK$1849,22,FALSE) -> 5000 | E33: IKNWIBE26000332 | F33: 04PC109 | G33: REQ- PERFORMANCE CHECK | H33: Normal | I33: 0 days, 0 hrs, 30 mins | J33: 07-Jan-2026 11:00:00 | K33: 07-Jan-2026 11:30:00 | L33: 07-Jan-2026 12:00:00 | M33: =IF(D33>44999.99,100,ROUNDUP((D33/4999.99)*10,-1)) -> 20 | N33: N | O33: ='[14]B1& B2 UNSCHEDULED'!$O$24 -> 0 | Q33: N | R33: =IF(L33="",AKHIR-J33,L33-J33+1) -> 1.0416667 | S33: =WORKDAY(J33,6,AKHIR) -> 46037 | T33: 0 | U33: =IF(Q33="N",0,M33*T33) -> 0 | V33: AN- PERFORMANCE CHECKING DONE AS PER HEPPM CHECKLIST ATTACHED
A34: 11 | B34: IKN402009 | C34: =VLOOKUP(B34,[13]AssetDetails_UEM!$A$3:$AH$1849,6,FALSE) -> Concentrators, Oxygen | D34: =VLOOKUP(B34,[13]AssetDetails_UEM!$A$3:$AK$1849,22,FALSE) -> 3400 | E34: IKNWIBE26000333 | F34: 04PC109 | G34: REQ- PERFORMANCE CHECK | H34: Normal | I34: 0 days, 0 hrs, 30 mins | J34: 07-Jan-2026 11:00:00 | K34: 07-Jan-2026 11:30:00 | L34: 07-Jan-2026 12:00:00 | M34: =IF(D34>44999.99,100,ROUNDUP((D34/4999.99)*10,-1)) -> 10 | N34: N | O34: ='[14]B1& B2 UNSCHEDULED'!$O$24 -> 0 | Q34: N | R34: =IF(L34="",AKHIR-J34,L34-J34+1) -> 1.0416667 | S34: =WORKDAY(J34,6,AKHIR) -> 46037 | T34: 0 | U34: =IF(Q34="N",0,M34*T34) -> 0 | V34: AN- PERFORMANCE CHECKING DONE AS PER HEPPM CHECKLIST ATTACHED (ST BEMS TAUFIK)
A35: 12 | B35: IKN400950 | C35: =VLOOKUP(B35,[13]AssetDetails_UEM!$A$3:$AH$1849,6,FALSE) -> Monitors, Physiologic, Vital Signs | D35: =VLOOKUP(B35,[13]AssetDetails_UEM!$A$3:$AK$1849,22,FALSE) -> 18765 | E35: IKNWIBE26000407 | F35: 03MC107 | G35: BATTERY DEPLATED | H35: Normal | I35: 0 days, 3 hrs, 30 mins | J35: 08-Jan-2026 14:00:00 | K35: 08-Jan-2026 17:30:00 | L35: 08-Jan-2026 19:00:00 | M35: =IF(D35>44999.99,100,ROUNDUP((D35/4999.99)*10,-1)) -> 40 | N35: Y | O35: =M35 -> 40 | Q35: N | R35: =IF(L35="",AKHIR-J35,L35-J35+1) -> 1.2083333 | S35: =WORKDAY(J35,6,AKHIR) -> 46038 | T35: 0 | U35: =IF(Q35="N",0,M35*T35) -> 0 | V35: M-REPLACE NEW BATTERY ,TESTED OKAY AND FUNCTIONING
A36: 13 | B36: IKN400289 | C36: =VLOOKUP(B36,[13]AssetDetails_UEM!$A$3:$AH$1849,6,FALSE) -> Infusion Pumps, General-Purpose | D36: =VLOOKUP(B36,[13]AssetDetails_UEM!$A$3:$AK$1849,22,FALSE) -> 10825 | E36: IKNWIBE26000411 | F36: 08WH121 | G36: CHARGER ADPTER BROKEN | H36: Normal | I36: 0 days, 0 hrs, 23 mins | J36: 08-Jan-2026 16:02:00 | K36: 08-Jan-2026 16:25:00 | L36: 15-Jan-2026 16:00:00 | M36: =IF(D36>44999.99,100,ROUNDUP((D36/4999.99)*10,-1)) -> 30 | N36: N | O36: ='[14]B1& B2 UNSCHEDULED'!$O$24 -> 0 | Q36: N | R36: =IF(L36="",AKHIR-J36,L36-J36+1) -> 7.9986111 | S36: =WORKDAY(J36,6,AKHIR) -> 46038 | T36: 0 | U36: =IF(Q36="N",0,M36*T36) -> 0 | V36: M-REPLACE NEW CHARGER ADPATER.TESTED MACHINE PASSED. (8/1/2026-16:25 UNTILL 15/1/2026-16:00)
A37: 14 | B37: IKN401010 | C37: =VLOOKUP(B37,[13]AssetDetails_UEM!$A$3:$AH$1849,6,FALSE) -> Gastroscopes, Flexible, Video | D37: =VLOOKUP(B37,[13]AssetDetails_UEM!$A$3:$AK$1849,22,FALSE) -> 118230 | E37: IKNWIBE26000477 | F37: IKN401010 | G37: WIPER NOT FUNCTIONING- MDC ARAS 3 | H37: Normal | I37: 0 days, 0 hrs, 10 mins | J37: 09-Jan-2026 10:00:00 | K37: 46031.424 | L37: 46035.625 | M37: =IF(D37>44999.99,100,ROUNDUP((D37/4999.99)*10,-1)) -> 100 | N37: N | O37: ='[14]B1& B2 UNSCHEDULED'!$O$24 -> 0 | Q37: N | R37: =IF(L37="",AKHIR-J37,L37-J37+1) -> 5.2083333 | S37: =WORKDAY(J37,6,AKHIR) -> 46041 | T37: 13 | U37: =IF(Q37="N",0,M37*T37) -> 0 | V37: PARTS CANNOT BE REPAIR. UNDER BER (OBSOLATE PARTS).
A38: 15 | B38: IKN400967 | C38: =VLOOKUP(B38,[13]AssetDetails_UEM!$A$3:$AH$1849,6,FALSE) -> Linear Accelerators | D38: =VLOOKUP(B38,[13]AssetDetails_UEM!$A$3:$AK$1849,22,FALSE) -> 12049370 | E38: IKNWIBE26000586 | F38: 01RT165 | G38: VACUUM TARGET VALUE BELOW 5.5 | H38: Normal | I38: 0 days, 0 hrs, 20 mins | J38: 12-Jan-2026 08:10:00 | K38: 12-Jan-2026 08:30:00 | L38: 13-Jan-2026 09:15:00 | M38: =IF(D38>44999.99,100,ROUNDUP((D38/4999.99)*10,-1)) -> 100 | N38: N | O38: ='[14]B1& B2 UNSCHEDULED'!$O$24 -> 0 | Q38: N | R38: =IF(L38="",AKHIR-J38,L38-J38+1) -> 2.0451389 | S38: =WORKDAY(J38,6,AKHIR) -> 46042 | T38: 0 | U38: =IF(Q38="N",0,M38*T38) -> 0 | V38: P - RESET VACUUM CIRCUIT BREAKER 3 TIMES. THE VALUE INCREASE UNTIL 6.2. TESTED OKAY
A39: 16 | B39: IKN400850 | C39: =VLOOKUP(B39,[13]AssetDetails_UEM!$A$3:$AH$1849,6,FALSE) -> Brachytherapy Applicators, Afterloading | D39: =VLOOKUP(B39,[13]AssetDetails_UEM!$A$3:$AK$1849,22,FALSE) -> 3420120 | E39: IKNWIBE26000587 | F39: 01RT243 | G39: HDR CANNOT CONNECT TO CAMERA | H39: Normal | I39: 0 days, 0 hrs, 20 mins | J39: 12-Jan-2026 08:20:00 | K39: 12-Jan-2026 08:40:00 | L39: 12-Jan-2026 09:00:00 | M39: =IF(D39>44999.99,100,ROUNDUP((D39/4999.99)*10,-1)) -> 100 | N39: N | O39: ='[14]B1& B2 UNSCHEDULED'!$O$24 -> 0 | Q39: N | R39: =IF(L39="",AKHIR-J39,L39-J39+1) -> 1.0277778 | S39: =WORKDAY(J39,6,AKHIR) -> 46042 | T39: 0 | U39: =IF(Q39="N",0,M39*T39) -> 0 | V39: P QE:12 - RESET CABLE TO CAMERA, CHECK I.P ADDRESS. UNIT TEST AND FUNCTIONING. ADVICE BY VENDOR THRU CALL
A40: 17 | B40: IKN400493 | C40: =VLOOKUP(B40,[13]AssetDetails_UEM!$A$3:$AH$1849,6,FALSE) -> Defibrillators, External, Manual | D40: =VLOOKUP(B40,[13]AssetDetails_UEM!$A$3:$AK$1849,22,FALSE) -> 45000 | E40: IKNWIBE26000597 | F40: 05WB133 | G40: N/A | H40: Normal | I40: 0 days, 0 hrs, 12 mins | J40: 12-Jan-2026 10:28:00 | K40: 12-Jan-2026 10:40:00 | L40: 12-Jan-2026 11:20:00 | M40: =IF(D40>44999.99,100,ROUNDUP((D40/4999.99)*10,-1)) -> 100 | N40: N | O40: ='[14]B1& B2 UNSCHEDULED'!$O$24 -> 0 | Q40: N | R40: =IF(L40="",AKHIR-J40,L40-J40+1) -> 1.0361111 | S40: =WORKDAY(J40,6,AKHIR) -> 46042 | T40: 0 | U40: =IF(Q40="N",0,M40*T40) -> 0 | V40: L, QE:16-REPLACE NEW ECG 3 LEAD
A41: 18 | B41: IKN400494 | C41: =VLOOKUP(B41,[13]AssetDetails_UEM!$A$3:$AH$1849,6,FALSE) -> Sphygmomanometers, Electronic, Automatic | D41: =VLOOKUP(B41,[13]AssetDetails_UEM!$A$3:$AK$1849,22,FALSE) -> 4510 | E41: IKNWIBE26000756 | F41: 05WB143 | G41: CUFF CONNECTOR BROKEN | H41: Normal | I41: 0 days, 0 hrs, 0 mins | J41: 14-Jan-2026 07:50:00 | K41: 14-Jan-2026 07:50:00 | L41: 14-Jan-2026 09:00:00 | M41: =IF(D41>44999.99,100,ROUNDUP((D41/4999.99)*10,-1)) -> 10 | N41: N | O41: ='[14]B1& B2 UNSCHEDULED'!$O$24 -> 0 | Q41: N | R41: =IF(L41="",AKHIR-J41,L41-J41+1) -> 1.0486111 | S41: =WORKDAY(J41,6,AKHIR) -> 46044 | T41: 0 | U41: =IF(Q41="N",0,M41*T41) -> 0 | V41: L, QE:16-REPLACE NEW CUFF CONNECTOR , UNIT TEST AND FUCTIONING IN GOOD CONDITION
A42: 19 | B42: IKN400967 | C42: =VLOOKUP(B42,[13]AssetDetails_UEM!$A$3:$AH$1849,6,FALSE) -> Linear Accelerators | D42: =VLOOKUP(B42,[13]AssetDetails_UEM!$A$3:$AK$1849,22,FALSE) -> 12049370 | E42: IKNWIBE26000757 | F42: 01RT165 | G42: VACUUM PRESSURE WERE BELOW THE RANGE TARGETED | H42: Normal | I42: 0 days, 0 hrs, 18 mins | J42: 14-Jan-2026 08:47:00 | K42: 14-Jan-2026 09:05:00 | L42: 19-Jan-2026 08:20:00 | M42: =IF(D42>44999.99,100,ROUNDUP((D42/4999.99)*10,-1)) -> 100 | N42: N | O42: ='[14]B1& B2 UNSCHEDULED'!$O$24 -> 0 | Q42: N | R42: =IF(L42="",AKHIR-J42,L42-J42+1) -> 5.98125 | S42: =WORKDAY(J42,6,AKHIR) -> 46044 | T42: 0 | U42: =IF(Q42="N",0,M42*T42) -> 0 | V42: P - PLANNED WITH VENDOR / SUPPLIER FOR PARTS REPLACEMENT
A43: 20 | B43: IKN400308 | C43: =VLOOKUP(B43,[13]AssetDetails_UEM!$A$3:$AH$1849,6,FALSE) -> Defibrillators, External, Manual | D43: =VLOOKUP(B43,[13]AssetDetails_UEM!$A$3:$AK$1849,22,FALSE) -> 45000 | E43: IKNWIBE26000760 | F43: 08WH133 | G43: MACHINE NOT DETECT PATIENT LEAD | H43: Normal | I43: 0 days, 0 hrs, 23 mins | J43: 14-Jan-2026 09:07:00 | K43: 14-Jan-2026 09:30:00 | L43: 14-Jan-2026 11:30:00 | M43: =IF(D43>44999.99,100,ROUNDUP((D43/4999.99)*10,-1)) -> 100 | N43: N | O43: ='[14]B1& B2 UNSCHEDULED'!$O$24 -> 0 | Q43: N | R43: =IF(L43="",AKHIR-J43,L43-J43+1) -> 1.0993056 | S43: =WORKDAY(J43,6,AKHIR) -> 46044 | T43: 0 | U43: =IF(Q43="N",0,M43*T43) -> 0 | V43: L, QE:16-SETTING AND RECALIBRATE UNIT WITH TESTER, TEST PASSED UNIT OBSERVED
A44: 21 | B44: IKN400965 | C44: =VLOOKUP(B44,[13]AssetDetails_UEM!$A$3:$AH$1849,6,FALSE) -> Linear Accelerators | D44: =VLOOKUP(B44,[13]AssetDetails_UEM!$A$3:$AK$1849,22,FALSE) -> 19351760 | E44: IKNWIBE26000763 | F44: 01RT177 | G44: DOSE VALUE LESS THAN EXPECTED CAUSED ERROr BY INCREASE THE DOSE VALVE | H44: Normal | I44: 0 days, 0 hrs, 6 mins | J44: 14-Jan-2026 10:24:00 | K44: 14-Jan-2026 10:30:00 | L44: 15-Jan-2026 08:30:00 | M44: =IF(D44>44999.99,100,ROUNDUP((D44/4999.99)*10,-1)) -> 100 | N44: N | O44: ='[14]B1& B2 UNSCHEDULED'!$O$24 -> 0 | Q44: N | R44: =IF(L44="",AKHIR-J44,L44-J44+1) -> 1.9208333 | S44: =WORKDAY(J44,6,AKHIR) -> 46044 | T44: 0 | U44: =IF(Q44="N",0,M44*T44) -> 0 | V44: M-AFTER TUNING AND MAKE CALIBRATION BY THE MVCT OKAY AND NORMAL.CAN BE AS USUAL
A45: 22 | B45: IKN401034 | C45: =VLOOKUP(B45,[13]AssetDetails_UEM!$A$3:$AH$1849,6,FALSE) -> Physiologic Monitoring Systems, Acute Care | D45: =VLOOKUP(B45,[13]AssetDetails_UEM!$A$3:$AK$1849,22,FALSE) -> 119690 | E45: IKNWIBE26000765 | F45: 05OT123 | G45: CUFF NEED TO REPLACED | H45: Normal | I45: 0 days, 0 hrs, 0 mins | J45: 14-Jan-2026 10:30:00 | K45: 14-Jan-2026 10:30:00 | L45: 14-Jan-2026 11:00:00 | M45: =IF(D45>44999.99,100,ROUNDUP((D45/4999.99)*10,-1)) -> 100 | N45: N | O45: ='[14]B1& B2 UNSCHEDULED'!$O$24 -> 0 | Q45: N | R45: =IF(L45="",AKHIR-J45,L45-J45+1) -> 1.0208333 | S45: =WORKDAY(J45,6,AKHIR) -> 46044 | T45: 0 | U45: =IF(Q45="N",0,M45*T45) -> 0 | V45: L, QE:16-REPLACE NEW CUFF, UNIT TESTE AND FUCTIONING IN GOOD CONDITION
A46: 23 | B46: IKN400404 | C46: =VLOOKUP(B46,[13]AssetDetails_UEM!$A$3:$AH$1849,6,FALSE) -> Sphygmomanometers, Electronic, Automatic | D46: =VLOOKUP(B46,[13]AssetDetails_UEM!$A$3:$AK$1849,22,FALSE) -> 4510 | E46: IKNWIBE26000766 | F46: 06WD146 | G46: CUFF BP LEAKING | H46: Normal | I46: 0 days, 0 hrs, 8 mins | J46: 14-Jan-2026 11:22:00 | K46: 14-Jan-2026 11:30:00 | L46: 14-Jan-2026 13:50:00 | M46: =IF(D46>44999.99,100,ROUNDUP((D46/4999.99)*10,-1)) -> 10 | N46: N | O46: ='[14]B1& B2 UNSCHEDULED'!$O$24 -> 0 | Q46: N | R46: =IF(L46="",AKHIR-J46,L46-J46+1) -> 1.1027778 | S46: =WORKDAY(J46,6,AKHIR) -> 46044 | T46: 0 | U46: =IF(Q46="N",0,M46*T46) -> 0 | V46: L- REPAIR TUBING DO PERFORMANCE TEST PASSED UNIT READY TO USE
A47: 24 | B47: IKN402231 | C47: Physiologic Monitoring Systems, Acute Care | D47: 10200 | E47: IKNWIBE26000788 | F47: 01AE111 | G47: USER REQUEST | H47: Normal | I47: 0 days, 0 hrs, 0 mins | J47: 14-Jan-2026 15:00:00 | K47: 14-Jan-2026 15:00:00 | L47: 14-Jan-2026 17:00:00 | M47: =IF(D47>44999.99,100,ROUNDUP((D47/4999.99)*10,-1)) -> 30 | N47: N | O47: ='[14]B1& B2 UNSCHEDULED'!$O$24 -> 0 | Q47: N | R47: =IF(L47="",AKHIR-J47,L47-J47+1) -> 1.0833333 | S47: =WORKDAY(J47,6,AKHIR) -> 46044 | T47: 0 | U47: =IF(Q47="N",0,M47*T47) -> 0 | V47: L, QE:16-INSTALL THE BASE OF THE PATIENT MONITOR IN THE AMBULANCE, THE PATIENT MONITOR AS TRANSPORT (USE IN THE EMERGENCY AND IN AMBULANCE)
A48: 25 | B48: IKN400528 | C48: =VLOOKUP(B48,[13]AssetDetails_UEM!$A$3:$AH$1849,6,FALSE) -> Aspirators | D48: =VLOOKUP(B48,[13]AssetDetails_UEM!$A$3:$AK$1849,22,FALSE) -> 2165 | E48: IKNWIBE26000859 | F48: 04PC109 | G48: UNIT FUNCTIONING IN GOOD CONDITION | H48: Normal | I48: 0 days, 0 hrs, 30 mins | J48: 15-Jan-2026 10:30:00 | K48: 15-Jan-2026 11:00:00 | L48: 15-Jan-2026 11:15:00 | M48: =IF(D48>44999.99,100,ROUNDUP((D48/4999.99)*10,-1)) -> 10 | N48: N | O48: ='[14]B1& B2 UNSCHEDULED'!$O$24 -> 0 | Q48: N | R48: =IF(L48="",AKHIR-J48,L48-J48+1) -> 1.03125 | S48: =WORKDAY(J48,6,AKHIR) -> 46045 | T48: 0 | U48: =IF(Q48="N",0,M48*T48) -> 0 | V48: M-REQUEST PERFORMANCE CHECK PERFORMANCE CHECKING DONE AS PER HEPPM CHECKLIST ATTACHED
A49: 26 | B49: IKN400967 | C49: =VLOOKUP(B49,[13]AssetDetails_UEM!$A$3:$AH$1849,6,FALSE) -> Linear Accelerators | D49: =VLOOKUP(B49,[13]AssetDetails_UEM!$A$3:$AK$1849,22,FALSE) -> 12049370 | E49: IKNWIBE26000985 | F49: 01RT165 | G49: VACUUM PRESSURE WERE INTERMITTENT OUT OF RANGE | H49: Normal | I49: 0 days, 0 hrs, 25 mins | J49: 16-Jan-2026 08:35:00 | K49: 16-Jan-2026 09:00:00 | L49: 19-Jan-2026 08:20:00 | M49: =IF(D49>44999.99,100,ROUNDUP((D49/4999.99)*10,-1)) -> 100 | N49: N | O49: ='[14]B1& B2 UNSCHEDULED'!$O$24 -> 0 | Q49: N | R49: =IF(L49="",AKHIR-J49,L49-J49+1) -> 3.9895833 | S49: =WORKDAY(J49,6,AKHIR) -> 46048 | T49: 0 | U49: =IF(Q49="N",0,M49*T49) -> 0 | V49: P - REPLACE NEW VACUUM PUMP BY VENDOR AND DO THE PERFORMANCE TEST. ALL TESTED AND PASSED. UNIT RETURNED TO FUNCTIONALITY
A50: 27 | B50: IKN400850 | C50: =VLOOKUP(B50,[13]AssetDetails_UEM!$A$3:$AH$1849,6,FALSE) -> Brachytherapy Applicators, Afterloading | D50: =VLOOKUP(B50,[13]AssetDetails_UEM!$A$3:$AK$1849,22,FALSE) -> 3420120 | E50: IKNWIBE26000990 | F50: 01RT243 | G50: HDR RADIATION MONITOR DETECTED A HIGH RADIATION VALUE | H50: Normal | I50: 0 days, 0 hrs, 8 mins | J50: 16-Jan-2026 09:52:00 | K50: 16-Jan-2026 10:00:00 | L50: 16-Jan-2026 14:30:00 | M50: =IF(D50>44999.99,100,ROUNDUP((D50/4999.99)*10,-1)) -> 100 | N50: N | O50: ='[14]B1& B2 UNSCHEDULED'!$O$24 -> 0 | Q50: N | R50: =IF(L50="",AKHIR-J50,L50-J50+1) -> 1.1930556 | S50: =WORKDAY(J50,6,AKHIR) -> 46048 | T50: 0 | U50: =IF(Q50="N",0,M50*T50) -> 0 | V50: P - QE15: ADJUST BIL SENSOR. REDO TESTING PROCEDURE USING DAILY QA AND EXTERNAL READING WERE WITHIN THE CONTROL EXPOSURE
A51: 28 | B51: IKN400213 | C51: =VLOOKUP(B51,[13]AssetDetails_UEM!$A$3:$AH$1849,6,FALSE) -> Sphygmomanometers, Electronic, Automatic | D51: =VLOOKUP(B51,[13]AssetDetails_UEM!$A$3:$AK$1849,22,FALSE) -> 4510 | E51: IKNWIBE26001006 | F51: 09WJ136 | G51: UNIT INTERMITTENLY SHOW READING | H51: Normal | I51: 0 days, 11 hrs, 27 mins | J51: 16-Jan-2026 22:27:00 | K51: 16-Jan-2026 11:00:00 | L51: 20-Jan-2026 12:30:00 | M51: =IF(D51>44999.99,100,ROUNDUP((D51/4999.99)*10,-1)) -> 10 | N51: N | O51: ='[14]B1& B2 UNSCHEDULED'!$O$24 -> 0 | Q51: N | R51: =IF(L51="",AKHIR-J51,L51-J51+1) -> 4.5854167 | S51: =WORKDAY(J51,6,AKHIR) -> 46048 | T51: 0 | U51: =IF(Q51="N",0,M51*T51) -> 0 | V51: TIGHTEN TUBING , CHECK CONNECTION TUBING AND CUFF. DO PERFORMANCE TEST PASSED. UNIT READY FOR USE
A52: 29 | B52: IKN400458 | C52: =VLOOKUP(B52,[13]AssetDetails_UEM!$A$3:$AH$1849,6,FALSE) -> Sphygmomanometers, Electronic, Automatic | D52: =VLOOKUP(B52,[13]AssetDetails_UEM!$A$3:$AK$1849,22,FALSE) -> 7770 | E52: IKNWIBE26001013 | F52: 06WC107 | G52: MACHINE READING BP HIGH AND LEAKAGE | H52: Normal | I52: 0 days, 0 hrs, 53 mins | J52: 17-Jan-2026 13:37:00 | K52: 17-Jan-2026 14:30:00 | L52: 20-Jan-2026 12:15:00 | M52: =IF(D52>44999.99,100,ROUNDUP((D52/4999.99)*10,-1)) -> 20 | N52: N | O52: ='[14]B1& B2 UNSCHEDULED'!$O$24 -> 0 | Q52: N | R52: =IF(L52="",AKHIR-J52,L52-J52+1) -> 3.9430556 | S52: =WORKDAY(J52,6,AKHIR) -> 46048 | T52: 0 | U52: =IF(Q52="N",0,M52*T52) -> 0 | V52: P - QE12: DO LEAKAGE TESTING , CHANGE CUFF. TESTED PASSED
A53: 30 | B53: IKN400491 | C53: =VLOOKUP(B53,[13]AssetDetails_UEM!$A$3:$AH$1849,6,FALSE) -> Physiologic Monitoring Systems, Acute Care | D53: =VLOOKUP(B53,[13]AssetDetails_UEM!$A$3:$AK$1849,22,FALSE) -> 44510 | E53: IKNWIBE26001031 | F53: 05WB113 | G53: NEED FURTHER CHECK | H53: Normal | I53: 0 days, 0 hrs, 20 mins | J53: 18-Jan-2026 14:40:00 | K53: 18-Jan-2026 15:00:00 | L53: 20-Jan-2026 10:00:00 | M53: =IF(D53>44999.99,100,ROUNDUP((D53/4999.99)*10,-1)) -> 90 | N53: N | O53: ='[14]B1& B2 UNSCHEDULED'!$O$24 -> 0 | Q53: N | R53: =IF(L53="",AKHIR-J53,L53-J53+1) -> 2.8055556 | S53: =WORKDAY(J53,6,AKHIR) -> 46048 | T53: 0 | U53: =IF(Q53="N",0,M53*T53) -> 0 | V53: P - QE:12 , REPLACE NEW BATTERY AND PULSE OXIMETER
A54: 31 | B54: IKN402210 | C54: =VLOOKUP(B54,[13]AssetDetails_UEM!$A$3:$AH$1849,6,FALSE) -> #N/A | D54: =VLOOKUP(B54,[13]AssetDetails_UEM!$A$3:$AK$1849,22,FALSE) -> #N/A | E54: IKNWIBE26001032 | F54: 03ID111 | G54: ISSUE, TABLE PRODUCE UNUSUAL SOUND | H54: Normal | I54: 0 days, 0 hrs, 10 mins | J54: 18-Jan-2026 14:50:00 | K54: 46040.625 | L54: 18-Jan-2026 19:00:00 | M54: =IF(D54>44999.99,100,ROUNDUP((D54/4999.99)*10,-1)) -> #N/A | N54: N | O54: ='[14]B1& B2 UNSCHEDULED'!$O$24 -> 0 | Q54: N | R54: =IF(L54="",AKHIR-J54,L54-J54+1) -> 1.1736111 | S54: =WORKDAY(J54,6,AKHIR) -> 46048 | T54: 0 | U54: =IF(Q54="N",0,M54*T54) -> 0 | V54: L- VENDOR REPLACED ASET VERTICAL LIFT DRIVE FIX , TESTED , FUCTIONING OKAY
A55: 32 | B55: IKN400967 | C55: =VLOOKUP(B55,[13]AssetDetails_UEM!$A$3:$AH$1849,6,FALSE) -> Linear Accelerators | D55: =VLOOKUP(B55,[13]AssetDetails_UEM!$A$3:$AK$1849,22,FALSE) -> 12049370 | E55: IKNWIBE26001087 | F55: 01RT165 | G55: QA NOT PASSED DUE TO SIDELINE | H55: Normal | I55: 0 days, 0 hrs, 23 mins | J55: 19-Jan-2026 08:37:00 | K55: 19-Jan-2026 09:00:00 | L55: 19-Jan-2026 10:45:00 | M55: =IF(D55>44999.99,100,ROUNDUP((D55/4999.99)*10,-1)) -> 100 | N55: N | O55: ='[14]B1& B2 UNSCHEDULED'!$O$24 -> 0 | Q55: N | R55: =IF(L55="",AKHIR-J55,L55-J55+1) -> 1.0888889 | S55: =WORKDAY(J55,6,AKHIR) -> 46049 | T55: 0 | U55: =IF(Q55="N",0,M55*T55) -> 0 | V55: P - THIS ISSUE WERE HANDLED BY HOSPITAL PHYSICIST
A56: 33 | B56: IKN400031 | C56: =VLOOKUP(B56,[13]AssetDetails_UEM!$A$3:$AH$1849,6,FALSE) -> Electrocardiographs, Multichannel, Interpretative | D56: =VLOOKUP(B56,[13]AssetDetails_UEM!$A$3:$AK$1849,22,FALSE) -> 31270 | E56: IKNWIBE26001094 | F56: 05IC106 | G56: BANANA CLIP BROKEN | H56: Normal | I56: 0 days, 0 hrs, 15 mins | J56: 19-Jan-2026 09:30:00 | K56: 19-Jan-2026 09:45:00 | L56: 19-Jan-2026 10:00:00 | M56: =IF(D56>44999.99,100,ROUNDUP((D56/4999.99)*10,-1)) -> 70 | N56: N | O56: ='[14]B1& B2 UNSCHEDULED'!$O$24 -> 0 | Q56: N | R56: =IF(L56="",AKHIR-J56,L56-J56+1) -> 1.0208333 | S56: =WORKDAY(J56,6,AKHIR) -> 46049 | T56: 0 | U56: =IF(Q56="N",0,M56*T56) -> 0 | V56: P - QE11A:BANANA CLIP IS UNDER MEDICAL STORE , ADVICE USER TO CLAIM FROM MEDICAL STOREW
A57: 34 | B57: IKN400460 | C57: =VLOOKUP(B57,[13]AssetDetails_UEM!$A$3:$AH$1849,6,FALSE) -> Physiologic Monitoring Systems, Acute Care | D57: =VLOOKUP(B57,[13]AssetDetails_UEM!$A$3:$AK$1849,22,FALSE) -> 44510 | E57: IKNWIBE26001102 | F57: 06WC113 | G57: CUFF BP LEAKING | H57: Normal | I57: 0 days, 0 hrs, 28 mins | J57: 19-Jan-2026 12:02:00 | K57: 19-Jan-2026 12:30:00 | L57: 19-Jan-2026 13:15:00 | M57: =IF(D57>44999.99,100,ROUNDUP((D57/4999.99)*10,-1)) -> 90 | N57: N | O57: ='[14]B1& B2 UNSCHEDULED'!$O$24 -> 0 | Q57: N | R57: =IF(L57="",AKHIR-J57,L57-J57+1) -> 1.0506944 | S57: =WORKDAY(J57,6,AKHIR) -> 46049 | T57: 0 | U57: =IF(Q57="N",0,M57*T57) -> 0 | V57: L, QE:16- UNIT REPLACED CUFF, PERFORMANCE TEST PASSED, UNIT READY FOR USED
A58: 35 | B58: IKN400486 | C58: =VLOOKUP(B58,[13]AssetDetails_UEM!$A$3:$AH$1849,6,FALSE) -> Mattress Systems, Alternating-Pressure | D58: =VLOOKUP(B58,[13]AssetDetails_UEM!$A$3:$AK$1849,22,FALSE) -> 28630 | E58: IKNWIBE26001108 | F58: 05WB113 | G58: POWER SUPPLY CORD NOT FUCTIONING | H58: Normal | I58: 0 days, 0 hrs, 19 mins | J58: 19-Jan-2026 13:26:00 | K58: 19-Jan-2026 13:45:00 | L58: 19-Jan-2026 14:45:00 | M58: =IF(D58>44999.99,100,ROUNDUP((D58/4999.99)*10,-1)) -> 60 | N58: N | O58: ='[14]B1& B2 UNSCHEDULED'!$O$24 -> 0 | Q58: N | R58: =IF(L58="",AKHIR-J58,L58-J58+1) -> 1.0548611 | S58: =WORKDAY(J58,6,AKHIR) -> 46049 | T58: 0 | U58: =IF(Q58="N",0,M58*T58) -> 0 | V58: L, QE:16-REPLACE NEW POWER SUPPLY CARD, UNIT TEST AND FUNCTIONING IN GOOD CONDITION
A59: 36 | B59: NA | C59: =VLOOKUP(B59,[13]AssetDetails_UEM!$A$3:$AH$1849,6,FALSE) -> #N/A | D59: =VLOOKUP(B59,[13]AssetDetails_UEM!$A$3:$AK$1849,22,FALSE) -> #N/A | E59: IKNWIBE26001113 | F59: 05OT120 | G59: NEED FURTHER CHECK | H59: Normal | I59: 0 days, 0 hrs, 10 mins | J59: 19-Jan-2026 15:50:00 | K59: 19-Jan-2026 16:00:00 | L59: 19-Jan-2026 17:00:00 | M59: =IF(D59>44999.99,100,ROUNDUP((D59/4999.99)*10,-1)) -> #N/A | N59: N | O59: ='[14]B1& B2 UNSCHEDULED'!$O$24 -> 0 | Q59: N | R59: =IF(L59="",AKHIR-J59,L59-J59+1) -> 1.0486111 | S59: =WORKDAY(J59,6,AKHIR) -> 46049 | T59: 0 | U59: =IF(Q59="N",0,M59*T59) -> 0 | V59: P - QE:11 , UNIT IS CLINICAL SET AND NOT UNDER BEMS. ADVICE USER THAT THIS UNIT IS NOT UNDER BEMS.
A60: 37 | B60: NA | C60: Linear Accelerators | D60: =VLOOKUP(B60,[13]AssetDetails_UEM!$A$3:$AK$1849,22,FALSE) -> #N/A | E60: IKNWIBE26001181 | F60: 01RT183 | G60: MLC ERROR - LINAC 5 (KKM/IKN/H/25/152) | H60: Normal | I60: 0 days, 0 hrs, 18 mins | J60: 20-Jan-2026 07:53:00 | K60: 20-Jan-2026 07:53:00 | L60: 46043.34 | M60: =IF(D60>44999.99,100,ROUNDUP((D60/4999.99)*10,-1)) -> #N/A | N60: N | O60: ='[14]B1& B2 UNSCHEDULED'!$O$24 -> 0 | Q60: N | R60: =IF(L60="",AKHIR-J60,L60-J60+1) -> 2.0118056 | S60: =WORKDAY(J60,6,AKHIR) -> 46050 | T60: 2 | U60: =IF(Q60="N",0,M60*T60) -> 0 | V60: MLC LEAF B PRIMARY AND SECONDARY FAULTY. REPLACED PARTS AND TESTED OK UNIT RETURNED TO PULL FUNCTIONING.
A61: 38 | B61: IKN400308 | C61: =VLOOKUP(B61,[13]AssetDetails_UEM!$A$3:$AH$1849,6,FALSE) -> Defibrillators, External, Manual | D61: =VLOOKUP(B61,[13]AssetDetails_UEM!$A$3:$AK$1849,22,FALSE) -> 45000 | E61: IKNWIBE26001284 | F61: 08WH133 | G61: ECG LEAD INTERMITTENTLY DETECT | H61: Normal | I61: 0 days, 1 hrs, 2 mins | J61: 21-Jan-2026 06:58:00 | K61: 21-Jan-2026 08:00:00 | L61: 21-Jan-2026 08:15:00 | M61: =IF(D61>44999.99,100,ROUNDUP((D61/4999.99)*10,-1)) -> 100 | N61: N | O61: ='[14]B1& B2 UNSCHEDULED'!$O$24 -> 0 | Q61: N | R61: =IF(L61="",AKHIR-J61,L61-J61+1) -> 1.0534722 | S61: =WORKDAY(J61,6,AKHIR) -> 46051 | T61: 0 | U61: =IF(Q61="N",0,M61*T61) -> 0 | V61: L, QE:16-REPLACED ECG LEAD TESTED FUCTIONING OKAY
A62: 39 | B62: IKN402111 | C62: =VLOOKUP(B62,[13]AssetDetails_UEM!$A$3:$AH$1849,6,FALSE) -> Infusion Pumps, General-Purpose | D62: =VLOOKUP(B62,[13]AssetDetails_UEM!$A$3:$AK$1849,22,FALSE) -> 3500 | E62: IKNWIBE26001293 | F62: 05WB113 | G62: UNIT GIVE ALARM WHEN USE ALTERNATING MODE , NEED FURTHER CHECK. | H62: Normal | I62: 0 days, 0 hrs, 15 mins | J62: 21-Jan-2026 08:45:00 | K62: 21-Jan-2026 09:00:00 | L62: 21-Jan-2026 10:00:00 | M62: =IF(D62>44999.99,100,ROUNDUP((D62/4999.99)*10,-1)) -> 10 | N62: N | O62: ='[14]B1& B2 UNSCHEDULED'!$O$24 -> 0 | Q62: N | R62: =IF(L62="",AKHIR-J62,L62-J62+1) -> 1.0520833 | S62: =WORKDAY(J62,6,AKHIR) -> 46051 | T62: 0 | U62: =IF(Q62="N",0,M62*T62) -> 0 | V62: P - QE12B: CHECK AND ADJUST ALL CONNECTOR OF ALL CELL ON THE RIPPLE MATTRESS
A63: 40 | B63: IKN400293 | C63: =VLOOKUP(B63,[13]AssetDetails_UEM!$A$3:$AH$1849,6,FALSE) -> Oximeters, Pulse | D63: =VLOOKUP(B63,[13]AssetDetails_UEM!$A$3:$AK$1849,22,FALSE) -> 5410 | E63: IKNWIBE26001303 | F63: 08WH121 | G63: BATTERY FAULTY | H63: Normal | I63: 0 days, 0 hrs, 45 mins | J63: 21-Jan-2026 14:45:00 | K63: 21-Jan-2026 15:30:00 | L63: 28-Jan-2026 16:00:00 | M63: =IF(D63>44999.99,100,ROUNDUP((D63/4999.99)*10,-1)) -> 20 | N63: N | O63: ='[14]B1& B2 UNSCHEDULED'!$O$24 -> 0 | Q63: N | R63: =IF(L63="",AKHIR-J63,L63-J63+1) -> 8.0520833 | S63: =WORKDAY(J63,6,AKHIR) -> 46051 | T63: 0 | U63: =IF(Q63="N",0,M63*T63) -> 0 | V63: P-QE:12, REPLACE BATTERY , TEST OK. UNIT FUNCTIONING WELL
A64: 41 | B64: IKN400575 | C64: =VLOOKUP(B64,[13]AssetDetails_UEM!$A$3:$AH$1849,6,FALSE) -> Sphygmomanometers, Electronic, Automatic | D64: =VLOOKUP(B64,[13]AssetDetails_UEM!$A$3:$AK$1849,22,FALSE) -> 336 | E64: IKNWIBE26001304 | F64: 03NM185 | G64: CUFF ADULT LARGE TEAR | H64: Normal | I64: 0 days, 0 hrs, 10 mins | J64: 21-Jan-2026 15:00:00 | K64: 21-Jan-2026 15:10:00 | L64: 21-Jan-2026 15:30:00 | M64: =IF(D64>44999.99,100,ROUNDUP((D64/4999.99)*10,-1)) -> 10 | N64: N | O64: ='[14]B1& B2 UNSCHEDULED'!$O$24 -> 0 | Q64: N | R64: =IF(L64="",AKHIR-J64,L64-J64+1) -> 1.0208333 | S64: =WORKDAY(J64,6,AKHIR) -> 46051 | T64: 0 | U64: =IF(Q64="N",0,M64*T64) -> 0 | V64: L- REPLACED CUFF ADULT LARGE . TESTED OKEY
A65: 42 | B65: IKN401237 | C65: =VLOOKUP(B65,[13]AssetDetails_UEM!$A$3:$AH$1849,6,FALSE) -> Electrocardiographs, Multichannel, Interpretative | D65: =VLOOKUP(B65,[13]AssetDetails_UEM!$A$3:$AK$1849,22,FALSE) -> 5590.2 | E65: IKNWIBE26001328 | F65: 03NM108 | G65: REPORTED ECG INCORRECT | H65: Normal | I65: 0 days, 0 hrs, 35 mins | J65: 21-Jan-2026 16:15:00 | K65: 21-Jan-2026 16:50:00 | L65: 27-Jan-2026 15:00:00 | M65: =IF(D65>44999.99,100,ROUNDUP((D65/4999.99)*10,-1)) -> 20 | N65: N | O65: ='[14]B1& B2 UNSCHEDULED'!$O$24 -> 0 | Q65: N | R65: =IF(L65="",AKHIR-J65,L65-J65+1) -> 6.9479167 | S65: =WORKDAY(J65,6,AKHIR) -> 46051 | T65: 0 | U65: =IF(Q65="N",0,M65*T65) -> 0 | V65: P-QE:12,SUSPECTED ECG BULB NOT PROPERLY CLEAND SINCE TESTE WITH TESTER, UNIT FUNCTIONING OKAY. REPLACED ECG BULB
A66: 43 | B66: IKN400967 | C66: =VLOOKUP(B66,[13]AssetDetails_UEM!$A$3:$AH$1849,6,FALSE) -> Linear Accelerators | D66: =VLOOKUP(B66,[13]AssetDetails_UEM!$A$3:$AK$1849,22,FALSE) -> 12049370 | E66: IKNWIBE26001400 | F66: 01RT165 | G66: WATER TEMPERATURE LOW-LINAC 2 | H66: Normal | I66: 0 days, 0 hrs, 14 mins | J66: 22-Jan-2026 07:46:00 | K66: 46044.333 | L66: 46044.604 | M66: =IF(D66>44999.99,100,ROUNDUP((D66/4999.99)*10,-1)) -> 100 | N66: N | O66: ='[14]B1& B2 UNSCHEDULED'!$O$24 -> 0 | Q66: N | R66: =IF(L66="",AKHIR-J66,L66-J66+1) -> 1.2805556 | S66: =WORKDAY(J66,6,AKHIR) -> 46052 | T66: 0 | U66: =IF(Q66="N",0,M66*T66) -> 0 | V66: CHILLER SETTING INTERUPTED DUE DISMANTLED LINAC 1 PUT BACKUP CHILLER IN ALTERNATING MODE AND UNIT BACK TO FULL FUNCTIONALITY.
A67: 44 | B67: IKN400956 | C67: =VLOOKUP(B67,[13]AssetDetails_UEM!$A$3:$AH$1849,6,FALSE) -> Linear Accelerators | D67: =VLOOKUP(B67,[13]AssetDetails_UEM!$A$3:$AK$1849,22,FALSE) -> 21961900 | E67: IKNWIBE26001402 | F67: 01RT172 | G67: ERROR GFRL -LINAC 3 | H67: Normal | I67: 0 days, 0 hrs, 03 mins | J67: 22-Jan-2026 08:12:00 | K67: 46044.344 | L67: 46044.444 | M67: =IF(D67>44999.99,100,ROUNDUP((D67/4999.99)*10,-1)) -> 100 | N67: N | O67: ='[14]B1& B2 UNSCHEDULED'!$O$24 -> 0 | Q67: N | R67: =IF(L67="",AKHIR-J67,L67-J67+1) -> 1.1027778 | S67: =WORKDAY(J67,6,AKHIR) -> 46052 | U67: =IF(Q67="N",0,M67*T67) -> 0 | V67: ALL ENERGIES INTERLOCK GRFL TRIGGERED ERROR. REPLACED BY VENDOR GUN POWER SUPPLY AND UNIT RETURNED TO FUNCTIONALITY .
A68: 45 | B68: IKN400069 | C68: =VLOOKUP(B68,[13]AssetDetails_UEM!$A$3:$AH$1849,6,FALSE) -> Circulatory Assist Units, Venous Return | D68: =VLOOKUP(B68,[13]AssetDetails_UEM!$A$3:$AK$1849,22,FALSE) -> 13470 | E68: IKNWIBE26001419 | F68: 05IC111 | G68: NEED FURTHER CHECK , AC PLUG POINT WEAR AND FEAR | H68: Normal | I68: 0 days, 0 hrs, 43 mins | J68: 22-Jan-2026 12:17:00 | K68: 22-Jan-2026 13:00:00 | L68: 22-Jan-2026 14:00:00 | M68: =IF(D68>44999.99,100,ROUNDUP((D68/4999.99)*10,-1)) -> 30 | N68: N | O68: ='[14]B1& B2 UNSCHEDULED'!$O$24 -> 0 | Q68: N | R68: =IF(L68="",AKHIR-J68,L68-J68+1) -> 1.0715278 | S68: =WORKDAY(J68,6,AKHIR) -> 46052 | T68: 0 | U68: =IF(Q68="N",0,M68*T68) -> 0 | V68: P - QE12A: REPLACE NEW AC PLUG POINT , UNIT TEST AND FUNCTIONING IN GOOD CONDITION
A69: 46 | B69: IKN400347 | C69: =VLOOKUP(B69,[13]AssetDetails_UEM!$A$3:$AH$1849,6,FALSE) -> Physiologic Monitoring Systems, Acute Care | D69: =VLOOKUP(B69,[13]AssetDetails_UEM!$A$3:$AK$1849,22,FALSE) -> 44510 | E69: IKNWIBE26001421 | F69: 07WF121 | G69: BP CUFF CANNOT INFLATE ,UNDER MONITORING | H69: Normal | I69: 0 days, 0 hrs, 25 mins | J69: 22-Jan-2026 12:55:00 | K69: 22-Jan-2026 13:20:00 | L69: 26-Jan-2026 15:00:00 | M69: =IF(D69>44999.99,100,ROUNDUP((D69/4999.99)*10,-1)) -> 90 | N69: N | O69: ='[14]B1& B2 UNSCHEDULED'!$O$24 -> 0 | Q69: N | R69: =IF(L69="",AKHIR-J69,L69-J69+1) -> 5.0868056 | S69: =WORKDAY(J69,6,AKHIR) -> 46052 | T69: 0 | U69: =IF(Q69="N",0,M69*T69) -> 0 | V69: M-RE SEAT THE CONNECTOR HOSE, TESTED OKAY AND SUFF CAN INFLATE WELL
A70: 47 | B70: IKN400210 | C70: =VLOOKUP(B70,[13]AssetDetails_UEM!$A$3:$AH$1849,6,FALSE) -> Electrocardiographs, Multichannel, Interpretative | D70: =VLOOKUP(B70,[13]AssetDetails_UEM!$A$3:$AK$1849,22,FALSE) -> 25260 | E70: IKNWIBE26001422 | F70: 09WJ130 | G70: ECG LEAD NOT FULLY DETECTED | H70: Normal | I70: 0 days, 0 hrs, 24 mins | J70: 22-Jan-2026 13:06:00 | K70: 22-Jan-2026 13:30:00 | L70: 23-Jan-2026 12:30:00 | M70: =IF(D70>44999.99,100,ROUNDUP((D70/4999.99)*10,-1)) -> 60 | N70: N | O70: ='[14]B1& B2 UNSCHEDULED'!$O$24 -> 0 | Q70: N | R70: =IF(L70="",AKHIR-J70,L70-J70+1) -> 1.975 | S70: =WORKDAY(J70,6,AKHIR) -> 46052 | T70: 0 | U70: =IF(Q70="N",0,M70*T70) -> 0 | V70: L, QE:12-CHECK ECG LEAD CONTINUITY , ALL DETECTED, TEST MACHINE PASSED
A71: 48 | B71: IKN400404 | C71: Sphygmomanometers, Electronic, Automatic | D71: 4510 | E71: IKNWIBE26001511 | F71: 06WD142 | G71: BP CUFF LEAKING | H71: Normal | I71: 0 days, 1 hrs, 37 mins | J71: 23-Jan-2026 16:13:00 | K71: 23-Jan-2026 17:50:00 | L71: 26-Jan-2026 08:30:00 | M71: =IF(D71>44999.99,100,ROUNDUP((D71/4999.99)*10,-1)) -> 10 | N71: N | O71: ='[14]B1& B2 UNSCHEDULED'!$O$24 -> 0 | Q71: N | R71: =IF(L71="",AKHIR-J71,L71-J71+1) -> 3.6784722 | S71: =WORKDAY(J71,6,AKHIR) -> 46055 | T71: 0 | U71: =IF(Q71="N",0,M71*T71) -> 0 | V71: P - QE12: REPLACE NEW BOCUFF, DO TEST PASSED. UNIT READY FOR USE
A72: 49 | B72: IKN400965 | C72: =VLOOKUP(B72,[13]AssetDetails_UEM!$A$3:$AH$1849,6,FALSE) -> Linear Accelerators | D72: =VLOOKUP(B72,[13]AssetDetails_UEM!$A$3:$AK$1849,22,FALSE) -> 19351760 | E72: IKNWIBE26001512 | F72: 01RT177 | G72: MESIN TOMOTERAPI MAGNETRON ARCHING BILIK 4- RADIOTERAPI ARAS 1 | H72: Normal | I72: 0 days, 0 hrs, 12 mins | J72: 23-Jan-2026 16:18:00 | K72: 46045.688 | L72: 46046.31 | M72: =IF(D72>44999.99,100,ROUNDUP((D72/4999.99)*10,-1)) -> 100 | N72: N | O72: ='[14]B1& B2 UNSCHEDULED'!$O$24 -> 0 | Q72: N | R72: =IF(L72="",AKHIR-J72,L72-J72+1) -> 1.63125 | S72: =WORKDAY(J72,6,AKHIR) -> 46055 | T72: 0 | U72: =IF(Q72="N",0,M72*T72) -> 0 | V72: UNIT SHOWS MFL AND AOM ERROR DUE TO ARCHING MAGNETRON REPLACED MAGNETRON TUNED MFL AND AOM THEN CALIBRATED DCS. TESTED OK AND UNIT RETURNED TO FUNCTIONING.
A73: 50 | B73: IKN400762 | C73: =VLOOKUP(B73,[13]AssetDetails_UEM!$A$3:$AH$1849,6,FALSE) -> Analyzers, Laboratory, Immunoassay, Chemiluminescent | D73: =VLOOKUP(B73,[13]AssetDetails_UEM!$A$3:$AK$1849,22,FALSE) -> 1443450 | E73: IKNWIBE26001530 | F73: 04LA133 | G73: MODULE 1 REAGENT SUPPLY CENTER TEMPERATURE ABOVE MAX RANGE | H73: Normal | I73: 0 days, 0 hrs, 11 mins | J73: 24-Jan-2026 12:49:00 | K73: 24-Jan-2026 13:00:00 | L73: 24-Jan-2026 15:00:00 | M73: =IF(D73>44999.99,100,ROUNDUP((D73/4999.99)*10,-1)) -> 100 | N73: N | O73: ='[14]B1& B2 UNSCHEDULED'!$O$24 -> 0 | Q73: N | R73: =IF(L73="",AKHIR-J73,L73-J73+1) -> 1.0909722 | S73: =WORKDAY(J73,6,AKHIR) -> 46055 | T73: 0 | U73: =IF(Q73="N",0,M73*T73) -> 0 | V73: P - QE12A: RESTART THE UNIT , CHECK TEMPERATURE STATUS OK
A74: 51 | B74: IKN400293 | C74: =VLOOKUP(B74,[13]AssetDetails_UEM!$A$3:$AH$1849,6,FALSE) -> Oximeters, Pulse | D74: =VLOOKUP(B74,[13]AssetDetails_UEM!$A$3:$AK$1849,22,FALSE) -> 5410 | E74: IKNWIBE26001533 | F74: 08WH121 | G74: REPORTED NOT READING | H74: Normal | I74: 0 days, 1 hrs, 58 mins | J74: 25-Jan-2026 08:02:00 | K74: 25-Jan-2026 10:00:00 | L74: 26-Jan-2026 10:00:00 | M74: =IF(D74>44999.99,100,ROUNDUP((D74/4999.99)*10,-1)) -> 20 | N74: N | O74: ='[14]B1& B2 UNSCHEDULED'!$O$24 -> 0 | Q74: N | R74: =IF(L74="",AKHIR-J74,L74-J74+1) -> 2.0819444 | S74: =WORKDAY(J74,6,AKHIR) -> 46055 | T74: 0 | U74: =IF(Q74="N",0,M74*T74) -> 0 | V74: L, QE:16- TEST UNIT FUNCTIONING OKEY, FIXED SWITCH UNDER MONITORING
A75: 52 | B75: IKN400377 | C75: =VLOOKUP(B75,[13]AssetDetails_UEM!$A$3:$AH$1849,6,FALSE) -> Mattress Systems, Alternating-Pressure | D75: =VLOOKUP(B75,[13]AssetDetails_UEM!$A$3:$AK$1849,22,FALSE) -> 28630 | E75: IKNWIBE26001535 | F75: 07WE113 | G75: MATTRESSD TUBING DETECHED | H75: Normal | I75: 0 days, 0 hrs, 10 mins | J75: 25-Jan-2026 12:20:00 | K75: 25-Jan-2026 12:30:00 | L75: 26-Jan-2026 10:00:00 | M75: =IF(D75>44999.99,100,ROUNDUP((D75/4999.99)*10,-1)) -> 60 | N75: N | O75: ='[14]B1& B2 UNSCHEDULED'!$O$24 -> 0 | Q75: N | R75: =IF(L75="",AKHIR-J75,L75-J75+1) -> 1.9027778 | S75: =WORKDAY(J75,6,AKHIR) -> 46055 | T75: 0 | U75: =IF(Q75="N",0,M75*T75) -> 0 | V75: L, QE:16-DETACHED BACK THE TUBING TESTED UNIT FUCTIONING OKEY
A76: 53 | B76: IKN400967 | C76: =VLOOKUP(B76,[13]AssetDetails_UEM!$A$3:$AH$1849,6,FALSE) -> Linear Accelerators | D76: =VLOOKUP(B76,[13]AssetDetails_UEM!$A$3:$AK$1849,22,FALSE) -> 12049370 | E76: IKNWIBE26001602 | F76: 01RT165 | G76: WATER PRESSURE LOW READING (6) AND 6MB PHOTON OUTPUT -RADIOTERAPI ARAS 1 | H76: Normal | I76: 0 days, 0 hrs, 10 mins | J76: 26-Jan-2026 08:05:00 | K76: 46048.344 | L76: 46048.441 | M76: =IF(D76>44999.99,100,ROUNDUP((D76/4999.99)*10,-1)) -> 100 | N76: N | O76: ='[14]B1& B2 UNSCHEDULED'!$O$24 -> 0 | Q76: N | R76: =IF(L76="",AKHIR-J76,L76-J76+1) -> 1.1041667 | S76: =WORKDAY(J76,6,AKHIR)+1 -> 46057 | T76: 0 | U76: =IF(Q76="N",0,M76*T76) -> 0 | V76: WATER GAUGE SHOWED THE PRESSURE BELOW FROM THE RANGE FILL UO THE WATER AND MONITOR THE PRESSURE. WATER PRESSURE BACK INTO RANGE AND TESTED OK.
A77: 54 | B77: IKN400741 | C77: =VLOOKUP(B77,[13]AssetDetails_UEM!$A$3:$AH$1849,6,FALSE) -> Analyzers, Laboratory, Microbiology, Blood Culture, Automate | D77: =VLOOKUP(B77,[13]AssetDetails_UEM!$A$3:$AK$1849,22,FALSE) -> 342820 | E77: IKNWIBE26001603 | F77: 04LA126 | G77: BECTEC ALARM NERBUNYI | H77: Normal | I77: 0 days, 0 hrs, 8 mins | J77: 26-Jan-2026 08:12:00 | K77: 26-Jan-2026 08:20:00 | L77: 27-Jan-2026 09:20:00 | M77: =IF(D77>44999.99,100,ROUNDUP((D77/4999.99)*10,-1)) -> 100 | N77: N | O77: ='[14]B1& B2 UNSCHEDULED'!$O$24 -> 0 | Q77: N | R77: =IF(L77="",AKHIR-J77,L77-J77+1) -> 2.0472222 | S77: =WORKDAY(J77,6,AKHIR)+1 -> 46057 | T77: 0 | U77: =IF(Q77="N",0,M77*T77) -> 0 | V77: M-RESTART THE UNIT,SELF CHECK ,TEST FUNCTIOING OK
A78: 55 | B78: IKN402004 | C78: =VLOOKUP(B78,[13]AssetDetails_UEM!$A$3:$AH$1849,6,FALSE) -> Scanning Systems, Laser, Optical Tomography | D78: =VLOOKUP(B78,[13]AssetDetails_UEM!$A$3:$AK$1849,22,FALSE) -> 2185000 | E78: IKNWIBE26001607 | F78: 01RT172 | G78: CATALYST MONITOR VGA LOW SIGNAL- NOVALIS LINAC 3- RADIOTERAPI ARAS 1 | H78: Normal | I78: 0 days, 1 hrs, 27 mins | J78: 26-Jan-2026 08:23:00 | K78: 46048.41 | L78: 46049.698 | M78: =IF(D78>44999.99,100,ROUNDUP((D78/4999.99)*10,-1)) -> 100 | N78: N | O78: ='[14]B1& B2 UNSCHEDULED'!$O$24 -> 0 | Q78: N | R78: =IF(L78="",AKHIR-J78,L78-J78+1) -> 2.3486111 | S78: =WORKDAY(J78,6,AKHIR)+1 -> 46057 | T78: 0 | U78: =IF(Q78="N",0,M78*T78) -> 0 | V78: CATALYST DISPLAY BLANK. TIGHTED ALL CABLE AND CONNECTORS THROUGH THE SYNGO TESTED OK AND UNIT LEFT IN FUNCTIONING.
A79: 56 | B79: IKN400965 | C79: =VLOOKUP(B79,[13]AssetDetails_UEM!$A$3:$AH$1849,6,FALSE) -> Linear Accelerators | D79: =VLOOKUP(B79,[13]AssetDetails_UEM!$A$3:$AK$1849,22,FALSE) -> 19351760 | E79: IKNWIBE26001625 | F79: 01RT177 | G79: MESIN TOMOTERAPI LASER RIGHT MISSING - RADIOTERAPI ARAS 1 | H79: Normal | I79: 0 days, 0 hrs, 16 mins | J79: 26-Jan-2026 14:44:00 | K79: 46048.625 | L79: 46048.708 | M79: =IF(D79>44999.99,100,ROUNDUP((D79/4999.99)*10,-1)) -> 100 | N79: N | O79: ='[14]B1& B2 UNSCHEDULED'!$O$24 -> 0 | Q79: N | R79: =IF(L79="",AKHIR-J79,L79-J79+1) -> 1.0944444 | S79: =WORKDAY(J79,6,AKHIR)+1 -> 46057 | T79: 0 | U79: =IF(Q79="N",0,M79*T79) -> 0 | V79: RIGHT LASER NOT APPEAR DURING TREATMENT THIS MAY OCCUR DUE TO PLAN ISSUES WHEN THE RED LASER NOT APPEAR. TESTED OK AND UNIT RETURNED IN FUNCTIONING.
A80: 57 | B80: IKN401439 | C80: =VLOOKUP(B80,[13]AssetDetails_UEM!$A$3:$AH$1849,6,FALSE) -> Scales, Patient, Floor | D80: =VLOOKUP(B80,[13]AssetDetails_UEM!$A$3:$AK$1849,22,FALSE) -> 9380 | E80: IKNWIBE26001673 | F80: 03WA117 | G80: REPORTED HEIGHT AND WEIGHT INCORRECT | H80: Normal | I80: 0 days, 0 hrs, 15 mins | J80: 26-Jan-2026 16:15:00 | K80: 26-Jan-2026 16:30:00 | L80: 29-Jan-2026 09:00:00 | M80: =IF(D80>44999.99,100,ROUNDUP((D80/4999.99)*10,-1)) -> 20 | N80: N | O80: ='[14]B1& B2 UNSCHEDULED'!$O$24 -> 0 | Q80: N | R80: =IF(L80="",AKHIR-J80,L80-J80+1) -> 3.6979167 | S80: =WORKDAY(J80,6,AKHIR)+1 -> 46057 | T80: 0 | U80: =IF(Q80="N",0,M80*T80) -> 0 | V80: P QE:10, TESTED HEIGHT FUNCTIONING OKAY. TESTED WEIGHT, FOR WEIGHT EXCEEDING 50KG, THE READING WILL BE BELOW 200G WHICH IS BELOW THE ACTUAL VALUE. THIS UNDER ACCEPTABLE TOLARANCE.
A81: 58 | B81: IKN400757 | C81: =VLOOKUP(B81,[13]AssetDetails_UEM!$A$3:$AH$1849,6,FALSE) -> Analyzers, Laboratory, Hematology, Cell Counting, Automated | D81: =VLOOKUP(B81,[13]AssetDetails_UEM!$A$3:$AK$1849,22,FALSE) -> 565350 | E81: IKNWIBE26001771 | F81: 04LA131 | G81: ALARM REPLACE GLASS SPREDER | H81: Normal | I81: 0 days, 0 hrs, 22 mins | J81: 27-Jan-2026 09:08:00 | K81: 27-Jan-2026 09:30:00 | L81: 28-Jan-2026 09:30:00 | M81: =IF(D81>44999.99,100,ROUNDUP((D81/4999.99)*10,-1)) -> 100 | N81: N | O81: ='[14]B1& B2 UNSCHEDULED'!$O$24 -> 0 | Q81: N | R81: =IF(L81="",AKHIR-J81,L81-J81+1) -> 2.0152778 | S81: =WORKDAY(J81,6,AKHIR)+1 -> 46058 | T81: 0 | U81: =IF(Q81="N",0,M81*T81) -> 0 | V81: P - QE12A: REPLACE GLASS SPREDER. TEST FUNCTIONING OK
A82: 59 | B82: IKN400602 | C82: =VLOOKUP(B82,[13]AssetDetails_UEM!$A$3:$AH$1849,6,FALSE) -> Sphygmomanometers, Electronic, Automatic | D82: =VLOOKUP(B82,[13]AssetDetails_UEM!$A$3:$AK$1849,22,FALSE) -> 4510 | E82: IKNWIBE26001775 | F82: 04DO111 | G82: BP CUFF BOCOR | H82: Normal | I82: 0 days, 0 hrs, 25 mins | J82: 27-Jan-2026 09:35:00 | K82: 27-Jan-2026 10:00:00 | L82: 27-Jan-2026 10:30:00 | M82: =IF(D82>44999.99,100,ROUNDUP((D82/4999.99)*10,-1)) -> 10 | N82: N | O82: ='[14]B1& B2 UNSCHEDULED'!$O$24 -> 0 | Q82: N | R82: =IF(L82="",AKHIR-J82,L82-J82+1) -> 1.0381944 | S82: =WORKDAY(J82,6,AKHIR)+1 -> 46058 | T82: 0 | U82: =IF(Q82="N",0,M82*T82) -> 0 | V82: M-REPLACE NEW BP CUFF.TEST FUNCTIONING OK
A83: 60 | B83: IKN400171 | C83: =VLOOKUP(B83,[13]AssetDetails_UEM!$A$3:$AH$1849,6,FALSE) -> Ventilators, Intensive Care | D83: =VLOOKUP(B83,[13]AssetDetails_UEM!$A$3:$AK$1849,22,FALSE) -> 151560 | E83: IKNWIBE26001781 | F83: 05IC131 | G83: OXYGEN SENSOR FAILE. NEED TO REPLACE OXYGEN SENSOR | H83: Normal | I83: 0 days, 0 hrs, 8 mins | J83: 27-Jan-2026 11:07:00 | K83: 27-Jan-2026 11:15:00 | L83: 27-Jan-2026 12:00:00 | M83: =IF(D83>44999.99,100,ROUNDUP((D83/4999.99)*10,-1)) -> 100 | N83: N | O83: ='[14]B1& B2 UNSCHEDULED'!$O$24 -> 0 | Q83: N | R83: =IF(L83="",AKHIR-J83,L83-J83+1) -> 1.0368056 | S83: =WORKDAY(J83,6,AKHIR)+1 -> 46058 | T83: 0 | U83: =IF(Q83="N",0,M83*T83) -> 0 | V83: P-REPLACE NEW OXYGEN SENSOR, DEVICE CHECK PASSED, AIRTIGHT CHECK
A84: 61 | B84: IKN400774 | C84: =VLOOKUP(B84,[13]AssetDetails_UEM!$A$3:$AH$1849,6,FALSE) -> Scanning Systems, Computed Tomography | D84: =VLOOKUP(B84,[13]AssetDetails_UEM!$A$3:$AK$1849,22,FALSE) -> 4605710 | E84: IKNWIBE26001785 | F84: 03ID156 | G84: POPUP XC ERROR DURING CTA LIVE CASE | H84: Normal | I84: 0 days, 0 hrs, 15 mins | J84: 27-Jan-2026 11:00:00 | K84: 27-Jan-2026 11:15:00 | L84: 27-Jan-2026 13:00:00 | M84: =IF(D84>44999.99,100,ROUNDUP((D84/4999.99)*10,-1)) -> 100 | N84: N | O84: ='[14]B1& B2 UNSCHEDULED'!$O$24 -> 0 | Q84: N | R84: =IF(L84="",AKHIR-J84,L84-J84+1) -> 1.0833333 | S84: =WORKDAY(J84,6,AKHIR)+1 -> 46058 | T84: 0 | U84: =IF(Q84="N",0,M84*T84) -> 0 | V84: M-FULLY SHUTDOWN UNIT AND CONTINUE CASE.UNIT TESTED FUNCTIONING OKAY
A85: 62 | B85: IKN402188 | C85: =VLOOKUP(B85,[13]AssetDetails_UEM!$A$3:$AH$1849,6,FALSE) -> Nebulizers, Nonheated | D85: =VLOOKUP(B85,[13]AssetDetails_UEM!$A$3:$AK$1849,22,FALSE) -> 277509 | E85: IKNWIBE26001788 | F85: 03NM150 | G85: REPORTED BY USER ERROR -CRUBICLE FAILED TO REACH FULL TEMPERATURE- | H85: Normal | I85: 0 days, 0 hrs, 10 mins | J85: 27-Jan-2026 09:00:00 | K85: 27-Jan-2026 09:10:00 | L85: 27-Jan-2026 15:30:00 | M85: =IF(D85>44999.99,100,ROUNDUP((D85/4999.99)*10,-1)) -> 100 | N85: N | O85: ='[14]B1& B2 UNSCHEDULED'!$O$24 -> 0 | Q85: N | R85: =IF(L85="",AKHIR-J85,L85-J85+1) -> 1.2708333 | S85: =WORKDAY(J85,6,AKHIR)+1 -> 46058 | T85: 0 | U85: =IF(Q85="N",0,M85*T85) -> 0 | V85: M-VENDOR CHECKED AND CHANGED- CONTACT AND HOLDER ASSEMBLY KIT-.TESTED FEW TIMES.UNIT FUNCTIONING OKAY
A86: 63 | B86: IKN402180 | C86: =VLOOKUP(B86,[13]AssetDetails_UEM!$A$3:$AH$1849,6,FALSE) -> Scanning Systems, Computed Tomography/ Positron Emission Tomography | D86: =VLOOKUP(B86,[13]AssetDetails_UEM!$A$3:$AK$1849,22,FALSE) -> 3413750 | E86: IKNWIBE26001793 | F86: 03NM158 | G86: SCANNING WITH BODY CONTOUR OPTION IS DISABLED | H86: Normal | I86: 0 days, 0 hrs, 10 mins | J86: 27-Jan-2026 16:50:00 | K86: 27-Jan-2026 17:00:00 | L86: 28-Jan-2026 10:00:00 | M86: =IF(D86>44999.99,100,ROUNDUP((D86/4999.99)*10,-1)) -> 100 | N86: N | O86: ='[14]B1& B2 UNSCHEDULED'!$O$24 -> 0 | Q86: N | R86: =IF(L86="",AKHIR-J86,L86-J86+1) -> 1.7152778 | S86: =WORKDAY(J86,6,AKHIR)+1 -> 46058 | T86: 0 | U86: =IF(Q86="N",0,M86*T86) -> 0 | V86: M-VENDOR VERIFY THE ERROR LOGS AND PERFORM THE POWER CYCLE.RUN DUMMY SCAN USING PHANTOM,PASSED NO PSD ERROR
A87: 64 | B87: IKN402210 | C87: Magnetic Resonance Imaging (MRI) | D87: 10494120 | E87: IKNWIBE26001796 | F87: 03ID111 | G87: SYNGO VIA UPGRADE | H87: Normal | I87: 0 days, 0 hrs, 10 mins | J87: 27-Jan-2026 15:30:00 | K87: 27-Jan-2026 15:40:00 | L87: 27-Jan-2026 20:00:00 | M87: =IF(D87>44999.99,100,ROUNDUP((D87/4999.99)*10,-1)) -> 100 | N87: N | O87: ='[14]B1& B2 UNSCHEDULED'!$O$24 -> 0 | Q87: N | R87: =IF(L87="",AKHIR-J87,L87-J87+1) -> 1.1875 | S87: =WORKDAY(J87,6,AKHIR)+1 -> 46058 | T87: 0 | U87: =IF(Q87="N",0,M87*T87) -> 0 | V87: M-UPDATE COMPLETED BY VENDOR FOR SYNGO.VIA.TESTED FUNCTIONING OKAY
A88: 65 | B88: IKN400293 | C88: =VLOOKUP(B88,[13]AssetDetails_UEM!$A$3:$AH$1849,6,FALSE) -> Oximeters, Pulse | D88: =VLOOKUP(B88,[13]AssetDetails_UEM!$A$3:$AK$1849,22,FALSE) -> 5410 | E88: IKNWIBE26001893 | F88: 08WH121 | G88: UNIT BLINKING AND NO READING APPEAR. CAUSES BATTERYLOW | H88: Normal | I88: 0 days, 0 hrs, 23 mins | J88: 28-Jan-2026 09:37:00 | K88: 28-Jan-2026 10:00:00 | L88: 21-Jan-2026 11:00:00 | M88: =IF(D88>44999.99,100,ROUNDUP((D88/4999.99)*10,-1)) -> 20 | N88: N | O88: ='[14]B1& B2 UNSCHEDULED'!$O$24 -> 0 | Q88: N | R88: =IF(L88="",AKHIR-J88,L88-J88+1) -> -5.9423611 | S88: =WORKDAY(J88,6,AKHIR)+1 -> 46059 | T88: 0 | U88: =IF(Q88="N",0,M88*T88) -> 0 | V88: P - QE:12 , REPLACE BATTERY , TEST OK. UNIT FUNCTIONING WELL , CLEAN UNIT.
A89: 66 | B89: IKN402210 | C89: Magnetic Resonance Imaging (MRI) | D89: 10494120 | E89: IKNWIBE26001900 | F89: 03ID111 | G89: MACHINE NOT SCANNING | H89: Normal | I89: 0 days, 0 hrs, 15 mins | J89: 28-Jan-2026 12:30:00 | K89: 28-Jan-2026 12:45:00 | L89: 28-Jan-2026 13:20:00 | M89: =IF(D89>44999.99,100,ROUNDUP((D89/4999.99)*10,-1)) -> 100 | N89: N | O89: ='[14]B1& B2 UNSCHEDULED'!$O$24 -> 0 | Q89: N | R89: =IF(L89="",AKHIR-J89,L89-J89+1) -> 1.0347222 | S89: =WORKDAY(J89,6,AKHIR)+1 -> 46059 | T89: 0 | U89: =IF(Q89="N",0,M89*T89) -> 0 | V89: P-RESTART SYSTEM & SYSTEM ABLE TO CONTINUE SCANNING. UNIT FUNCTIONING OKAY
A90: 67 | B90: IKN400631 | C90: =VLOOKUP(B90,[13]AssetDetails_UEM!$A$3:$AH$1849,6,FALSE) -> Infusion Pumps, General-Purpose | D90: =VLOOKUP(B90,[13]AssetDetails_UEM!$A$3:$AK$1849,22,FALSE) -> 10825 | E90: IKNWIBE26001909 | F90: 04DO120 | G90: CHARGER FAULTY | H90: Normal | I90: 0 days, 0 hrs, 13 mins | J90: 28-Jan-2026 15:47:00 | K90: 28-Jan-2026 16:00:00 | L90: 28-Jan-2026 16:15:00 | M90: =IF(D90>44999.99,100,ROUNDUP((D90/4999.99)*10,-1)) -> 30 | N90: N | O90: ='[14]B1& B2 UNSCHEDULED'!$O$24 -> 0 | Q90: N | R90: =IF(L90="",AKHIR-J90,L90-J90+1) -> 1.0194444 | S90: =WORKDAY(J90,6,AKHIR)+1 -> 46059 | T90: 0 | U90: =IF(Q90="N",0,M90*T90) -> 0 | V90: L, QE:12-REPLACE CHARGER
A91: 68 | B91: IKN400620 | C91: =VLOOKUP(B91,[13]AssetDetails_UEM!$A$3:$AH$1849,6,FALSE) -> Infusion Pumps, General-Purpose | D91: =VLOOKUP(B91,[13]AssetDetails_UEM!$A$3:$AK$1849,22,FALSE) -> 10825 | E91: IKNWIBE26001910 | F91: 04DO119 | G91: CHARGER FAULTY | H91: Normal | I91: 0 days, 0 hrs, 23 mins | J91: 28-Jan-2026 15:57:00 | K91: 28-Jan-2026 16:20:00 | L91: 28-Jan-2026 16:45:00 | M91: =IF(D91>44999.99,100,ROUNDUP((D91/4999.99)*10,-1)) -> 30 | N91: N | O91: ='[14]B1& B2 UNSCHEDULED'!$O$24 -> 0 | Q91: N | R91: =IF(L91="",AKHIR-J91,L91-J91+1) -> 1.0333333 | S91: =WORKDAY(J91,6,AKHIR)+1 -> 46059 | T91: 0 | U91: =IF(Q91="N",0,M91*T91) -> 0 | V91: L, QE:16-REPLACE CHARGER
A92: 69 | B92: IKN400610 | C92: =VLOOKUP(B92,[13]AssetDetails_UEM!$A$3:$AH$1849,6,FALSE) -> Infusion Pumps, General-Purpose | D92: =VLOOKUP(B92,[13]AssetDetails_UEM!$A$3:$AK$1849,22,FALSE) -> 10825 | E92: IKNWIBE26001912 | F92: 04DO118 | G92: CHARGER FAULTY | H92: Normal | I92: 0 days, 0 hrs, 16 mins | J92: 28-Jan-2026 16:04:00 | K92: 28-Jan-2026 16:20:00 | L92: 28-Jan-2026 16:35:00 | M92: =IF(D92>44999.99,100,ROUNDUP((D92/4999.99)*10,-1)) -> 30 | N92: N | O92: ='[14]B1& B2 UNSCHEDULED'!$O$24 -> 0 | Q92: N | R92: =IF(L92="",AKHIR-J92,L92-J92+1) -> 1.0215278 | S92: =WORKDAY(J92,6,AKHIR)+1 -> 46059 | T92: 0 | U92: =IF(Q92="N",0,M92*T92) -> 0 | V92: L, QE:16-REPLACE CHARGER
A93: 70 | B93: IKN400303 | C93: =VLOOKUP(B93,[13]AssetDetails_UEM!$A$3:$AH$1849,6,FALSE) -> Mattress Systems, Alternating-Pressure | D93: =VLOOKUP(B93,[13]AssetDetails_UEM!$A$3:$AK$1849,22,FALSE) -> 28630 | E93: IKNWIBE26001924 | F93: 08WH121 | G93: UNIT BROKEN , NOT FULLY INFLATE | H93: Normal | I93: 0 days, 1 hrs, 17 mins | J93: 28-Jan-2026 19:58:00 | K93: 28-Jan-2026 21:15:00 | L93: 28-Jan-2026 23:15:00 | M93: =IF(D93>44999.99,100,ROUNDUP((D93/4999.99)*10,-1)) -> 60 | N93: N | O93: ='[14]B1& B2 UNSCHEDULED'!$O$24 -> 0 | Q93: N | R93: =IF(L93="",AKHIR-J93,L93-J93+1) -> 1.1368056 | S93: =WORKDAY(J93,6,AKHIR)+1 -> 46059 | T93: 0 | U93: =IF(Q93="N",0,M93*T93) -> 0 | V93: P - QE:12 , CHECK AND TIGHTEN TUBING , CHECK PHYSICAL CONDITION. OK TEST UNIT UNTIL FULLY INFLATE , PASSED UNIT READY FOR USE
A94: 71 | B94: IKN400741 | C94: =VLOOKUP(B94,[13]AssetDetails_UEM!$A$3:$AH$1849,6,FALSE) -> Analyzers, Laboratory, Microbiology, Blood Culture, Automate | D94: =VLOOKUP(B94,[13]AssetDetails_UEM!$A$3:$AK$1849,22,FALSE) -> 342820 | E94: IKNWIBE26001998 | F94: 04LA126 | G94: GRINDING SOUND WHEN MOTOR MOVING DUE TO RUSTY | H94: Normal | I94: 0 days, 0 hrs, 11 mins | J94: 29-Jan-2026 16:49:00 | K94: 29-Jan-2026 17:00:00 | L94: 30-Jan-2026 21:00:00 | M94: =IF(D94>44999.99,100,ROUNDUP((D94/4999.99)*10,-1)) -> 100 | N94: N | O94: ='[14]B1& B2 UNSCHEDULED'!$O$24 -> 0 | Q94: N | R94: =IF(L94="",AKHIR-J94,L94-J94+1) -> 2.1743056 | S94: =WORKDAY(J94,6,AKHIR)+3 -> 46062 | T94: 0 | U94: =IF(Q94="N",0,M94*T94) -> 0 | V94: L, QE:16- LUBRICATE THE MOTOR
A95: 72 | B95: IKN400945 | C95: =VLOOKUP(B95,[13]AssetDetails_UEM!$A$3:$AH$1849,6,FALSE) -> Recorders, Tape, Video | D95: =VLOOKUP(B95,[13]AssetDetails_UEM!$A$3:$AK$1849,22,FALSE) -> 4000 | E95: IKNWIBE26002054 | F95: 03MC127 | G95: WIRE CAMERA BESI BENGKOK BILIK 7 - MDC ARAS 3 | H95: Normal | I95: 0 days, 0 hrs, 09 mins | J95: 30-Jan-2026 09:26:00 | K95: 46052.399 | L95: 46059.635 | M95: =IF(D95>44999.99,100,ROUNDUP((D95/4999.99)*10,-1)) -> 10 | N95: N | O95: ='[14]B1& B2 UNSCHEDULED'!$O$24 -> 0 | Q95: N | R95: =IF(L95="",AKHIR-J95,L95-J95+1) -> 8.2423611 | S95: =WORKDAY(J95,6,AKHIR)+1 -> 46063 | T95: 0 | U95: =IF(Q95="N",0,M95*T95) -> 0 | V95: REPLACE NEW CABLE, TESTED OKAY AND DATA CAN TRANSFER TO PC.
A96: Current Month (Work Order Open)
A97: 1 | B97: IKN400440 | C97: =VLOOKUP(B97,[13]AssetDetails_UEM!$A$3:$AH$1849,6,FALSE) -> Sphygmomanometers, Electronic, Automatic | D97: =VLOOKUP(B97,[13]AssetDetails_UEM!$A$3:$AK$1849,22,FALSE) -> 4510 | E97: IKNWIBE26001002 | F97: 06WC143 | G97: MACHINE BP TIDAK BERFUNGSI -6A | H97: Normal | I97: 0 days, 1 hrs, 10 mins | J97: 16-Jan-2026 20:20:00 | K97: 46038.896 | M97: =IF(D97>44999.99,100,ROUNDUP((D97/4999.99)*10,-1)) -> 10 | N97: N | O97: ='[14]B1& B2 UNSCHEDULED'!$O$24 -> 0 | Q97: Y | R97: =IF(L97="",AKHIR-J97,L97-J97+1) -> 14.152778 | S97: =WORKDAY(J97,6,AKHIR) -> 46048 | T97: 7 | U97: 0 | V97: WAITING PARTS PO71329(25/1/26) LOAN GIVEN ETA : 2 TO 4 WEEKS.
A98: 2 | B98: IKN400645 | C98: =VLOOKUP(B98,[13]AssetDetails_UEM!$A$3:$AH$1849,6,FALSE) -> Infusion Pumps, General-Purpose | D98: =VLOOKUP(B98,[13]AssetDetails_UEM!$A$3:$AK$1849,22,FALSE) -> 10825 | E98: IKNWIBE26001911 | F98: 04DO121 | G98: INFUSION PUMP CHARGER NOT FUNCTION - DAYCARE ARAS 4 | H98: Normal | I98: 0 days, 0 hrs, 30 mins | J98: 28-Jan-2026 16:00:00 | K98: 46050.688 | M98: =IF(D98>44999.99,100,ROUNDUP((D98/4999.99)*10,-1)) -> 30 | N98: N | O98: ='[14]B1& B2 UNSCHEDULED'!$O$24 -> 0 | Q98: N | R98: =IF(L98="",AKHIR-J98,L98-J98+1) -> 2.3333333 | S98: =WORKDAY(J98,6,AKHIR)+1 -> 46059 | T98: 0 | U98: =IF(Q98="N",0,M98*T98) -> 0 | V98: CHARGER FAULTY REPLECEMENT. CLOSED ON 3 FEB 2026
A99: 3 | B99: IKN401714 | C99: =VLOOKUP(B99,[13]AssetDetails_UEM!$A$3:$AH$1849,6,FALSE) -> Infusion Pumps, General-Purpose | D99: =VLOOKUP(B99,[13]AssetDetails_UEM!$A$3:$AK$1849,22,FALSE) -> 5800 | E99: IKNWIBE26001913 | F99: 04DO111 | G99: INFUSION PUMP CHARGER NOT FUNCTION - DAYCARE ARAS 4 | H99: Normal | I99: 0 days, 0 hrs, 22 mins | J99: 28-Jan-2026 16:08:00 | K99: 46050.688 | M99: =IF(D99>44999.99,100,ROUNDUP((D99/4999.99)*10,-1)) -> 20 | N99: N | O99: ='[14]B1& B2 UNSCHEDULED'!$O$24 -> 0 | Q99: N | R99: =IF(L99="",AKHIR-J99,L99-J99+1) -> 2.3277778 | S99: =WORKDAY(J99,6,AKHIR)+1 -> 46059 | T99: 0 | U99: =IF(Q99="N",0,M99*T99) -> 0 | V99: CHARGER FAULTY REPLECEMENT. CLOSED ON 3 FEB 2026
A100: Previous Month (Work Order Closed)
A101: 1 | B101: IKN400031 | C101: =VLOOKUP(B101,[13]AssetDetails_UEM!$A$3:$AH$1849,6,FALSE) -> Electrocardiographs, Multichannel, Interpretative | D101: =VLOOKUP(B101,[13]AssetDetails_UEM!$A$3:$AK$1849,22,FALSE) -> 31270 | E101: IKNWIBE25021001 | F101: 05IC106 | G101: MESIN ECG WIRE CABLE ROSAK -ICU ARAS 5 | H101: NORMAL | I101: 0 days, 1 hrs, 12 mins | J101: 15-Nov-2025 08:18:00 | K101: 45976.396 | L101: 09-Jan-2026 16:00:00 | M101: =IF(D101>44999.99,100,ROUNDUP((D101/4999.99)*10,-1)) -> 70 | N101: N | O101: ='[14]B1& B2 UNSCHEDULED'!$O$24 -> 0 | Q101: Y | R101: =IF(L101="",AKHIR-J101,L101-J101+1) -> 56.320833 | S101: =WORKDAY(J101,6,AKHIR)+1 -> 45986 | T101: 9 | U101: 0 | V101: REPLACE NEW CABLE ON 9/1/26
A102: 2 | B102: IKN400312 | C102: =VLOOKUP(B102,[13]AssetDetails_UEM!$A$3:$AH$1849,6,FALSE) -> Monitors, Physiologic, Vital Signs | D102: =VLOOKUP(B102,[13]AssetDetails_UEM!$A$3:$AK$1849,22,FALSE) -> 7770 | E102: IKNWIBE25021278 | F102: 08WH143 | G102: SPO2 MACHINE TIDAK BERFUNGSI- WAD 8B | H102: NORMAL | I102: 0 days, 0 hrs, 32 mins | J102: 19-Nov-2025 17:58:00 | K102: 45980.771 | L102: 05-Jan-2026 11:17:00 | M102: =IF(D102>44999.99,100,ROUNDUP((D102/4999.99)*10,-1)) -> 20 | N102: N | O102: ='[14]B1& B2 UNSCHEDULED'!$O$24 -> 0 | Q102: Y | R102: =IF(L102="",AKHIR-J102,L102-J102+1) -> 47.721528 | S102: =WORKDAY(J102,6,AKHIR) -> 45988 | T102: 5 | U102: 0 | V102: RECONNECT AND RESEAT ALL CABLE BOARD
A103: 3 | B103: IKN400535 | C103: =VLOOKUP(B103,[13]AssetDetails_UEM!$A$3:$AH$1849,6,FALSE) -> Sphygmomanometers, Electronic, Automatic | D103: =VLOOKUP(B103,[13]AssetDetails_UEM!$A$3:$AK$1849,22,FALSE) -> 7770 | E103: IKNWIBE25021750 | F103: 03WA116 | G103: MACHINE CANNOT TURN ON | H103: NORMAL | I103: 0 days, 0 hrs, 30 mins | J103: 26-Nov-2025 12:45:00 | K103: 45987.552 | L103: 15-Dec-2025 14:00:00 | M103: =IF(D103>44999.99,100,ROUNDUP((D103/4999.99)*10,-1)) -> 20 | N103: N | O103: ='[14]B1& B2 UNSCHEDULED'!$O$24 -> 0 | Q103: Y | R103: =IF(L103="",AKHIR-J103,L103-J103+1) -> 20.052083 | S103: =WORKDAY(J103,6,AKHIR) -> 45995 | T103: 15 | U103: 0 | V103: REPLACED BATTERY AND PNEUMATIC MANIFOLD. TESTED UNIT FUNCTIONING OKAY.
A104: 4 | B104: IKN400098 | C104: =VLOOKUP(B104,[13]AssetDetails_UEM!$A$3:$AH$1849,6,FALSE) -> Infusion Pumps, Syringe | D104: =VLOOKUP(B104,[13]AssetDetails_UEM!$A$3:$AK$1849,22,FALSE) -> 10225 | E104: IKNWIBE25021896 | F104: 05IC112 | G104: SYRINGE PUMP BERBUNYI ALARM - ICU ARAS 5 | H104: NORMAL | I104: 0 days, 0 hrs, 30 mins | J104: 28-Nov-2025 10:21:00 | K104: 45989.452 | L104: 46052.625 | M104: =IF(D104>44999.99,100,ROUNDUP((D104/4999.99)*10,-1)) -> 30 | N104: N | O104: ='[14]B1& B2 UNSCHEDULED'!$O$24 -> 0 | Q104: Y | R104: =IF(L104="",AKHIR-J104,L104-J104+1) -> 64.19375 | S104: =WORKDAY(J104,6,AKHIR) -> 45999 | T104: 30 | U104: 0 | V104: BATTERY DEPLETED, REPLACED NEW BATTERY AND TESTED OK.
A105: 5 | B105: IKN401043 | C105: =VLOOKUP(B105,[13]AssetDetails_UEM!$A$3:$AH$1849,6,FALSE) -> Physiologic Monitoring Systems, Acute Care | D105: =VLOOKUP(B105,[13]AssetDetails_UEM!$A$3:$AK$1849,22,FALSE) -> 87400 | E105: IKNWIBE25023511 | F105: 05OT159 | G105: CABLE SPO2 AND PROBE CANNOT FUNCTION - GOT ARAS 5 | H105: NORMAL | I105: 0 days, 0 hrs, 10 mins | J105: 23-Dec-2025 12:50:00 | K105: 23-Dec-2025 13:00:00 | L105: 02-Jan-2026 11:15:00 | M105: =IF(D105>44999.99,100,ROUNDUP((D105/4999.99)*10,-1)) -> 100 | N105: N | O105: ='[14]B1& B2 UNSCHEDULED'!$O$24 -> 0 | Q105: Y | R105: =IF(L105="",AKHIR-J105,L105-J105+1) -> 10.934028 | S105: =WORKDAY(J105,6,AKHIR) -> 46022 | T105: 2 | U105: 0 | V105: REPLACE NEW SPO2 PROBE
A106: 7 | B106: IKN401070 | C106: =VLOOKUP(B106,[13]AssetDetails_UEM!$A$3:$AH$1849,6,FALSE) -> Light Sources, Fiberoptic, Flexible Endoscopic | D106: =VLOOKUP(B106,[13]AssetDetails_UEM!$A$3:$AK$1849,22,FALSE) -> 52460 | E106: IKNWIBE25023842 | F106: 03MC108 | G106: CM-LIGHT SOURCE XENON LAMP REPLACEMENT | H106: NORMAL | I106: 0 days, 0 hrs, 10 mins | J106: 29-Dec-2025 15:00:00 | K106: 29-Dec-2025 15:10:00 | L106: 06-Jan-2026 15:00:00 | M106: =IF(D106>44999.99,100,ROUNDUP((D106/4999.99)*10,-1)) -> 100 | N106: N | O106: ='[14]B1& B2 UNSCHEDULED'!$O$24 -> 0 | Q106: N | R106: =IF(L106="",AKHIR-J106,L106-J106+1) -> 9 | S106: =WORKDAY(J106,6,AKHIR) -> 46028 | T106: 0 | U106: =IF(Q106="N",0,M106*T106) -> 0 | V106: P - REPLACE NEW LIGHT BULB (ILHAN: 29/12/2025 - 15:30 SEHINGGA 6/1/2026 -15:00)
A107: 8 | B107: IKN400229 | C107: Infusion Pumps, General-Purpose | D107: 10825 | E107: IKNWIBE25023843 | F107: 09WJ126 | G107: CM-BATTERY REPLACEMENT | H107: NORMAL | I107: 0 days, 0 hrs, 10 mins | J107: 29-Dec-2025 10:00:00 | K107: 29-Dec-2025 10:10:00 | L107: 03-Feb-2026 16:30:00 | M107: 30 | N107: N | O107: 0 | Q107: N | R107: =IF(L107="",AKHIR-J107,L107-J107+1) -> 37.270833 | S107: =WORKDAY(J107,6,AKHIR) -> 46028 | T107: 0 | U107: =IF(Q107="N",0,M107*T107) -> 0 | V107: P - QE12: , REPLACE NEW SET OF BATTERY
...

Sheet B3-SCHEDULED
A3: MINISTRY OF HEALTH
A4: Deduction Mapping Report Biomedical Engineering Maintenance Services (BEMS)
A5: INDICATOR B.3 SCHEDULED MAINTENANCE
A7: HOSPITAL NAME : | C7: INSTITUT KANSER NEGARA | H7: MONTH/YEAR : | J7: 46023
B9: STATE : | C9: WILAYAH PERSEKUTUAN PUTRAJAYA | G9: BEMS MONTHLY FEE (RM) @ 97.5% : | J9: =[15]BEMSdar!E11 -> 1437864.8
B11: COMPANY : | C11: AMBANG WIRA SDN BHD | G11: FMS MONTHLY FEE (RM) @ 2.5% : | J11: =[15]BEMSdar!E13 -> 36868.327
A13: Notes:
A14: 1) Deduction Ringgit Equivalent is based on Appendix 11 of the Agreement, Section B3 Key Deduction Indicators for BEMS
A15: 2) Deduction Value for Indicator B.3 is Deduction Ringgit Equivalent (per event)
A16: 3) Rescheduled Date is the final rescheduled date if there are multiple rescheduling
A17: 4) Display only asset affected by deduction
A19: No | B19: Asset No | C19: Asset Description | D19: Asset Purchase Price (RM) | E19: Work Order No. | F19: User Location | G19: Scheduled Start Date | H19: Maintenance Date | I19: Rescheduled Date | J19: Validate Status (Y/N) | K19: Deduction Ringgit Equivalent (RM) | L19: Indicator B.3
L20: Deduction Value (RM) | M20: Remarks/ Exemption
A21: Current Month (Closed) | M21: =PROPER(#REF!) -> #REF!
A22: 1 | B22: IKN400803 | C22: Ventilators, Transport | D22: =VLOOKUP(B22,[13]AssetDetails_UEM!$A$3:$X$1848,22,FALSE) -> 60150 | E22: IKNWOBE26000241 | F22: 01RT233 | G22: 13-Jan-2026 00:00:00 | H22: 13-Jan-2026 10:00:00 | I22: NA | J22: N | K22: =ROUNDUP((D22/4999.99)*10,-1) -> 130 | L22: =IF(J22="N",0,K22) -> 0 | M22: L, QE:16-MAINTAINANCE DONE AS PER HEPPM CHECKLIST ATTACHED
A23: 2 | B23: IKN400804 | C23: Intubation Scopes, Flexible Fiberoptic | D23: =VLOOKUP(B23,[13]AssetDetails_UEM!$A$3:$X$1848,22,FALSE) -> 38360 | E23: IKNWOBE26000242 | F23: 05OT169 | G23: 13-Jan-2026 00:00:00 | H23: 13-Jan-2026 12:20:00 | I23: NA | J23: N | K23: =ROUNDUP((D23/4999.99)*10,-1) -> 80 | L23: =IF(J23="N",0,K23) -> 0 | M23: L, QE:16-MAINTAINANCE DONE AS PER HEPPM CHECKLIST ATTACHED
A24: 3 | B24: IKN400805 | C24: Intubation Scopes, Flexible Fiberoptic | D24: =VLOOKUP(B24,[13]AssetDetails_UEM!$A$3:$X$1848,22,FALSE) -> 38575 | E24: IKNWOBE26000243 | F24: 05OT169 | G24: 13-Jan-2026 00:00:00 | H24: 13-Jan-2026 14:10:00 | I24: NA | J24: N | K24: =ROUNDUP((D24/4999.99)*10,-1) -> 80 | L24: =IF(J24="N",0,K24) -> 0 | M24: L, QE:16-MAINTAINANCE DONE AS PER HEPPM CHECKLIST ATTACHED
A25: 4 | B25: IKN401013 | C25: Television Systems, Endoscope | D25: =VLOOKUP(B25,[13]AssetDetails_UEM!$A$3:$X$1848,22,FALSE) -> 10000 | E25: IKNWOBE26000244 | F25: 05OT167 | G25: 13-Jan-2026 00:00:00 | H25: 13-Jan-2026 14:00:00 | I25: NA | J25: N | K25: =ROUNDUP((D25/4999.99)*10,-1) -> 30 | L25: =IF(J25="N",0,K25) -> 0 | M25: L, QE:16-MAINTAINANCE DONE AS PER ROUTINE INSPECTION CHECKLIST ATTACHED
A26: 5 | B26: IKN401014 | C26: Light Sources, Fiberoptic | D26: =VLOOKUP(B26,[13]AssetDetails_UEM!$A$3:$X$1848,22,FALSE) -> 50000 | E26: IKNWOBE26000245 | F26: 05OT167 | G26: 13-Jan-2026 00:00:00 | H26: 13-Jan-2026 14:30:00 | I26: NA | J26: N | K26: =ROUNDUP((D26/4999.99)*10,-1) -> 110 | L26: =IF(J26="N",0,K26) -> 0 | M26: L, QE:16-MAINTAINANCE DONE AS PER HEPPM CHECKLIST ATTACHED
A27: 6 | B27: IKN400541 | C27: Defibrillators, External, Manual | D27: =VLOOKUP(B27,[13]AssetDetails_UEM!$A$3:$X$1848,22,FALSE) -> 45000 | E27: IKNWOBE26000246 | F27: 03WA121 | G27: 13-Jan-2026 00:00:00 | H27: 13-Jan-2026 14:15:00 | I27: NA | J27: N | K27: =ROUNDUP((D27/4999.99)*10,-1) -> 100 | L27: =IF(J27="N",0,K27) -> 0 | M27: L, QE:16-PPM COMPLETE AS PER CHECKLIST UNIT TESTED OKEY
A28: 7 | B28: IKN400841 | C28: Anesthesia Units | D28: =VLOOKUP(B28,[13]AssetDetails_UEM!$A$3:$X$1848,22,FALSE) -> 144345 | E28: IKNWOBE26000247 | F28: 01RT278 | G28: 13-Jan-2026 00:00:00 | H28: 13-Jan-2026 08:00:00 | I28: NA | J28: N | K28: =ROUNDUP((D28/4999.99)*10,-1) -> 290 | L28: =IF(J28="N",0,K28) -> 0 | M28: L, QE:16-MAINTAINANCE DONE AS PER HEPPM CHECKLIST ATTACHED
A29: 8 | B29: IKN400959 | C29: Anesthesia Units | D29: =VLOOKUP(B29,[13]AssetDetails_UEM!$A$3:$X$1848,22,FALSE) -> 144345 | E29: IKNWOBE26000248 | F29: 01RT212 | G29: 13-Jan-2026 00:00:00 | H29: 13-Jan-2026 10:00:00 | I29: NA | J29: N | K29: =ROUNDUP((D29/4999.99)*10,-1) -> 290 | L29: =IF(J29="N",0,K29) -> 0 | M29: L, QE:16-MAINTAINANCE DONE AS PER HEPPM CHECKLIST ATTACHED
A30: 9 | B30: IKN400587 | C30: Defibrillator/Pacemakers, External | D30: =VLOOKUP(B30,[13]AssetDetails_UEM!$A$3:$X$1848,22,FALSE) -> 45000 | E30: IKNWOBE26000251 | F30: 03NM164 | G30: 15-Jan-2026 00:00:00 | H30: 15-Jan-2026 12:00:00 | I30: NA | J30: N | K30: =ROUNDUP((D30/4999.99)*10,-1) -> 100 | L30: =IF(J30="N",0,K30) -> 0 | M30: L, QE:16-PPM COMPLETE AS PER CHECKLIST, UNIT FUCTIONING OKEY
A31: 10 | B31: IKN400777 | C31: Anesthesia Units | D31: =VLOOKUP(B31,[13]AssetDetails_UEM!$A$3:$X$1848,22,FALSE) -> 144345 | E31: IKNWOBE26000252 | F31: 03ID167 | G31: 15-Jan-2026 00:00:00 | H31: 15-Jan-2026 17:30:00 | I31: NA | J31: N | K31: =ROUNDUP((D31/4999.99)*10,-1) -> 290 | L31: =IF(J31="N",0,K31) -> 0 | M31: L, QE:16-MAINTAINANCE DONE AS PER HEPPM CHECKLIST ATTACHED
A32: 11 | B32: IKN401011 | C32: Nasopharyngoscopes | D32: =VLOOKUP(B32,[13]AssetDetails_UEM!$A$3:$X$1848,22,FALSE) -> 59362 | E32: IKNWOBE26000253 | F32: 05OT167 | G32: 15-Jan-2026 00:00:00 | H32: 15-Jan-2026 09:00:00 | I32: NA | J32: N | K32: =ROUNDUP((D32/4999.99)*10,-1) -> 120 | L32: =IF(J32="N",0,K32) -> 0 | M32: L, QE:16-MAINTAINANCE DONE AS PER HEPPM CHECKLIST ATTACHED
A33: 12 | B33: IKN400004 | C33: Electrocardiographs, Multichannel, Interpretative | D33: =VLOOKUP(B33,[13]AssetDetails_UEM!$A$3:$X$1848,22,FALSE) -> 25260 | E33: IKNWOBE26000256 | F33: 01AE110 | G33: 16-Jan-2026 00:00:00 | H33: 46038.688 | I33: NA | J33: N | K33: =ROUNDUP((D33/4999.99)*10,-1) -> 60 | L33: =IF(J33="N",0,K33) -> 0 | M33: MAINTENANCE DONE ACCORDING TO HEPPM CHECKLIST ATTACHED.
A34: 13 | B34: IKN400493 | C34: Defibrillators, External, Manual | D34: =VLOOKUP(B34,[13]AssetDetails_UEM!$A$3:$X$1848,22,FALSE) -> 45000 | E34: IKNWOBE26000257 | F34: 05WB133 | G34: 16-Jan-2026 00:00:00 | H34: 16-Jan-2026 14:30:00 | I34: NA | J34: N | K34: =ROUNDUP((D34/4999.99)*10,-1) -> 100 | L34: =IF(J34="N",0,K34) -> 0 | M34: L, QE:16-MAINTAINANCE DONE AS PER HEPPM CHECKLIST ATTACHED
A35: 14 | B35: IKN400828 | C35: Anesthesia Units | D35: =VLOOKUP(B35,[13]AssetDetails_UEM!$A$3:$X$1848,22,FALSE) -> 144345 | E35: IKNWOBE26000258 | F35: 01RT275 | G35: 16-Jan-2026 00:00:00 | H35: 16-Jan-2026 14:00:00 | I35: NA | J35: N | K35: =ROUNDUP((D35/4999.99)*10,-1) -> 290 | L35: =IF(J35="N",0,K35) -> 0 | M35: L, QE:16-MAINTAINANCE DONE AS PER HEPPM CHECKLIST ATTACHED
A36: 15 | B36: IKN400835 | C36: Electrosurgical Units, Monopolar/Bipolar | D36: =VLOOKUP(B36,[13]AssetDetails_UEM!$A$3:$X$1848,22,FALSE) -> 97190 | E36: IKNWOBE26000259 | F36: 01RT275 | G36: 16-Jan-2026 00:00:00 | H36: 16-Jan-2026 10:00:00 | I36: NA | J36: N | K36: =ROUNDUP((D36/4999.99)*10,-1) -> 200 | L36: =IF(J36="N",0,K36) -> 0 | M36: L, QE:16-MAINTAINANCE DONE AS PER HEPPM CHECKLIST ATTACHED
A37: 16 | B37: IKN402050 | C37: Electrocardiographs, Multichannel, Non-Interpretative | D37: =VLOOKUP(B37,[13]AssetDetails_UEM!$A$3:$X$1848,22,FALSE) -> 12900 | E37: IKNWOBE26000260 | F37: 01AE106 | G37: 16-Jan-2026 00:00:00 | H37: 16-Jan-2026 15:00:00 | I37: NA | J37: N | K37: =ROUNDUP((D37/4999.99)*10,-1) -> 30 | L37: =IF(J37="N",0,K37) -> 0 | M37: L, QE:16-MAINTAINANCE DONE AS PER CHECKLIST ATTACHED
A38: 17 | B38: IKN400798 | C38: Radiographic Systems, Digital | D38: =VLOOKUP(B38,[13]AssetDetails_UEM!$A$3:$X$1848,22,FALSE) -> 1958605 | E38: IKNWOBE26000899 | F38: 03ID181 | G38: 46045 | H38: 27-Jan-2026 10:00:00 | I38: 46052 | J38: N | K38: =ROUNDUP((D38/4999.99)*10,-1) -> 3920 | L38: =IF(J38="N",0,K38) -> 0 | M38: M,QE:16-PPM COMPLETED BY VENDOR.UNIT FUNCTIONING OKAY
A39: 18 | B39: IKN400799 | C39: Radiographic Systems, Digital | D39: =VLOOKUP(B39,[13]AssetDetails_UEM!$A$3:$X$1848,22,FALSE) -> 1958605 | E39: IKNWOBE26000900 | F39: 03ID186 | G39: 46046 | H39: 26-Jan-2026 10:00:00 | I39: 46052 | J39: N | K39: =ROUNDUP((D39/4999.99)*10,-1) -> 3920 | L39: =IF(J39="N",0,K39) -> 0 | M39: M,QE:16-PPM COMPLETED BY VENDOR .UNIT FUNCTIONING OKAY
A40: 19 | B40: IKN401005 | C40: Oxygen Monitors | D40: =VLOOKUP(B40,[13]AssetDetails_UEM!$A$3:$X$1848,22,FALSE) -> 3079 | E40: IKNWOBE26000868 | F40: 05OT165 | G40: 19-Jan-2026 00:00:00 | H40: 19-Jan-2026 09:00:00 | I40: NA | J40: N | K40: =ROUNDUP((D40/4999.99)*10,-1) -> 10 | L40: =IF(J40="N",0,K40) -> 0 | M40: P, QE16: MAINTENANCE DONE AS PER HEPPM CHECKLIST ATTACHED
A41: 20 | B41: IKN400001 | C41: Defibrillators, External, Manual | D41: =VLOOKUP(B41,[13]AssetDetails_UEM!$A$3:$X$1848,22,FALSE) -> 45000 | E41: IKNWOBE26000870 | F41: 01AE112 | G41: 20-Jan-2026 00:00:00 | H41: 46042.542 | I41: NA | J41: N | K41: =ROUNDUP((D41/4999.99)*10,-1) -> 100 | L41: =IF(J41="N",0,K41) -> 0 | M41: MAINTENANCE DONE ACCORDING TO HEPPM CHECKLIST ATTACHED.
A42: 21 | B42: IKN400562 | C42: Defibrillators, External, Manual | D42: =VLOOKUP(B42,[13]AssetDetails_UEM!$A$3:$X$1848,22,FALSE) -> 45000 | E42: IKNWOBE26000871 | F42: 03NM155 | G42: 20-Jan-2026 00:00:00 | H42: 20-Jan-2026 14:00:00 | I42: NA | J42: N | K42: =ROUNDUP((D42/4999.99)*10,-1) -> 100 | L42: =IF(J42="N",0,K42) -> 0 | M42: L, QE:16-PPM COMPLETE AS PER CHECKLIST, UNIT TESTED OKEY
A43: 22 | B43: IKN400723 | C43: Microscopes, Light, Laboratory, Fluorescence | D43: =VLOOKUP(B43,[13]AssetDetails_UEM!$A$3:$X$1848,22,FALSE) -> 169530 | E43: IKNWOBE26000872 | F43: 04LA114 | G43: 20-Jan-2026 00:00:00 | H43: 20-Jan-2026 15:00:00 | I43: NA | J43: N | K43: =ROUNDUP((D43/4999.99)*10,-1) -> 340 | L43: =IF(J43="N",0,K43) -> 0 | M43: L, QE:16-MAINTAINANCE DONE AS PER HEPPM CHECKLIST ATTACHED
A44: 23 | B44: IKN402183 | C44: Physiologic Monitoring Systems, Acute Care | D44: =VLOOKUP(B44,[13]AssetDetails_UEM!$A$3:$X$1848,22,FALSE) -> RM100,00.00 | E44: IKNWOBE26000874 | F44: 03NM158 | G44: 20-Jan-2026 00:00:00 | H44: 20-Feb-2026 15:00:00 | I44: NA | J44: N | K44: =ROUNDUP((D44/4999.99)*10,-1) -> #VALUE! | L44: =IF(J44="N",0,K44) -> 0 | M44: L, QE:16-PPM COMPLETE AS PER CHECKLIST. UNIT FUCTIONING OKEY
A45: 24 | B45: IKN402184 | C45: Physiologic Monitoring Systems, Acute Care | D45: =VLOOKUP(B45,[13]AssetDetails_UEM!$A$3:$X$1848,22,FALSE) -> RM100,00.00 | E45: IKNWOBE26000875 | F45: 03NM161 | G45: 20-Jan-2026 00:00:00 | H45: 20-Jan-2026 16:00:00 | I45: NA | J45: N | K45: =ROUNDUP((D45/4999.99)*10,-1) -> #VALUE! | L45: =IF(J45="N",0,K45) -> 0 | M45: L, QE:16-PPM COMPLETE AS PER CHECKLIST. UNIT FUCTIONING OKEY
A46: 25 | B46: IKN400023 | C46: Warming Units, Blood/Solution | D46: =VLOOKUP(B46,[13]AssetDetails_UEM!$A$3:$X$1848,22,FALSE) -> 4990 | E46: IKNWOBE26000877 | F46: 01AE110 | G46: 21-Jan-2026 00:00:00 | H46: 21-Jan-2026 15:00:00 | I46: NA | J46: N | K46: =ROUNDUP((D46/4999.99)*10,-1) -> 10 | L46: =IF(J46="N",0,K46) -> 0 | M46: L, QE:16-MAINTAINANCE DONE AS PERCHECKLIST ATTACHED
A47: 26 | B47: IKN400024 | C47: Warming Units, Blood/Solution | D47: =VLOOKUP(B47,[13]AssetDetails_UEM!$A$3:$X$1848,22,FALSE) -> 4990 | E47: IKNWOBE26000878 | F47: 01AE110 | G47: 21-Jan-2026 00:00:00 | H47: 21-Jan-2026 16:00:00 | I47: NA | J47: N | K47: =ROUNDUP((D47/4999.99)*10,-1) -> 10 | L47: =IF(J47="N",0,K47) -> 0 | M47: N-QE:16 MAINTENANCE DONE AS PER CHECKLIST ATTACHED
A48: 27 | B48: IKN400537 | C48: Defibrillators, External, Manual | D48: =VLOOKUP(B48,[13]AssetDetails_UEM!$A$3:$X$1848,22,FALSE) -> 45000 | E48: IKNWOBE26000879 | F48: 03WA117 | G48: 21-Jan-2026 00:00:00 | H48: 21-Jan-2026 15:40:00 | I48: NA | J48: N | K48: =ROUNDUP((D48/4999.99)*10,-1) -> 100 | L48: =IF(J48="N",0,K48) -> 0 | M48: L, QE:16- PPM COMPLETE AS PER CHECKLIST ATTACHED
A49: 28 | B49: IKN400612 | C49: Infusion Pumps, General-Purpose | D49: =VLOOKUP(B49,[13]AssetDetails_UEM!$A$3:$X$1848,22,FALSE) -> 10825 | E49: IKNWOBE26000880 | F49: 04DO118 | G49: 21-Jan-2026 00:00:00 | H49: 21-Jan-2026 15:00:00 | I49: NA | J49: N | K49: =ROUNDUP((D49/4999.99)*10,-1) -> 30 | L49: =IF(J49="N",0,K49) -> 0 | M49: M,QE:16-PPM DONE AS PERCHEKLIST
A50: 29 | B50: IKN401009 | C50: Colonoscopes, Video | D50: =VLOOKUP(B50,[13]AssetDetails_UEM!$A$3:$X$1848,22,FALSE) -> 143382 | E50: IKNWOBE26000881 | F50: 03MC108 | G50: 21-Jan-2026 00:00:00 | H50: 21-Jan-2026 15:00:00 | I50: NA | J50: N | K50: =ROUNDUP((D50/4999.99)*10,-1) -> 290 | L50: =IF(J50="N",0,K50) -> 0 | M50: M,QE:16-PPM COMPLETED AS HEPPM CHECKLIST
A51: 30 | B51: IKN401070 | C51: Light Sources, Fiberoptic, Flexible Endoscopic | D51: =VLOOKUP(B51,[13]AssetDetails_UEM!$A$3:$X$1848,22,FALSE) -> 52460 | E51: IKNWOBE26000882 | F51: 03MC108 | G51: 21-Jan-2026 00:00:00 | H51: 21-Jan-2026 15:00:00 | I51: NA | J51: N | K51: =ROUNDUP((D51/4999.99)*10,-1) -> 110 | L51: =IF(J51="N",0,K51) -> 0 | M51: M,QE:16-PPM COMPLETED AS HEPPM CHECKLIST
A52: 31 | B52: IKN401075 | C52: Electrosurgical Units, Monopolar/Bipolar | D52: =VLOOKUP(B52,[13]AssetDetails_UEM!$A$3:$X$1848,22,FALSE) -> 20000 | E52: IKNWOBE26000884 | F52: 03MC108 | G52: 21-Jan-2026 00:00:00 | H52: 21-Jan-2026 15:00:00 | I52: NA | J52: N | K52: =ROUNDUP((D52/4999.99)*10,-1) -> 50 | L52: =IF(J52="N",0,K52) -> 0 | M52: M,QE:16-PPM NOT COMPLETED AND ASSEST UNDER BER
A53: 32 | B53: IKN402130 | C53: Analyzers, laboratory, blood gas/ pH/ electrolyte | D53: =VLOOKUP(B53,[13]AssetDetails_UEM!$A$3:$X$1848,22,FALSE) -> 79500 | E53: IKNWOBE26000885 | F53: 04LA138 | G53: 21-Jan-2026 00:00:00 | H53: 21-Jan-2026 15:00:00 | I53: NA | J53: N | K53: =ROUNDUP((D53/4999.99)*10,-1) -> 160 | L53: =IF(J53="N",0,K53) -> 0 | M53: L, QE:16-MAINTAINANCE DONE AS PER HEPPM CHECKLIST ATTACHED
... A65: 44 | B65: IKN401238 | C65: Radiation Survey Meters, Geiger-Muller | D65: =VLOOKUP(B65,[13]AssetDetails_UEM!$A$3:$X$1848,22,FALSE) -> 20000 | E65: IKNWOBE26000897 | F65: 03ID169 | G65: 23-Jan-2026 00:00:00 | H65: 23-Jan-2026 09:00:00 | I65: NA | J65: N | K65: =ROUNDUP((D65/4999.99)*10,-1) -> 50 | L65: =IF(J65="N",0,K65) -> 0 | M65: L, QE:16-CALIBRATION COMPLETE BY VENDOR, UNIT TESTED OKEY
A66: 45 | B66: IKN401246 | C66: Computers, Radiotherapy Planning System | D66: =VLOOKUP(B66,[13]AssetDetails_UEM!$A$3:$X$1848,22,FALSE) -> 2403940 | E66: IKNWOBE26000898 | F66: 01RT156 | G66: 23-Jan-2026 00:00:00 | H66: 46045.375 | I66: NA | J66: N | K66: =ROUNDUP((D66/4999.99)*10,-1) -> 4810 | L66: =IF(J66="N",0,K66) -> 0 | M66: MAINTENANCE DONE ACCORDING TO HEPPM CHECKLIST ATTACHED.
A67: 46 | D67: =VLOOKUP(B67,[13]AssetDetails_UEM!$A$3:$X$1848,22,FALSE) -> #N/A | E67: IKNWOBE26001210 | F67: 05IC106 | G67: 46042 | H67: 20-Jan-2026 20:00:00 | I67: NA | J67: N | K67: =ROUNDUP((D67/4999.99)*10,-1) -> #N/A | L67: =IF(J67="N",0,K67) -> 0 | M67: P, QE:16 - MAINTANANCE DONE AS PER HEPPM CHECKLIST ATTACHED
A68: 47 | B68: IKN400266 | C68: Defibrillators, External, Manual | D68: =VLOOKUP(B68,[13]AssetDetails_UEM!$A$3:$X$1848,22,FALSE) -> 45000 | E68: IKNWOBE26001307 | F68: 08WG133 | G68: 27-Jan-2026 00:00:00 | H68: 27-Jan-2026 12:15:00 | I68: NA | J68: N | K68: =ROUNDUP((D68/4999.99)*10,-1) -> 100 | L68: =IF(J68="N",0,K68) -> 0 | M68: M,QE:16-PPM DONE AS PERCHECKLIST
A69: 48 | B69: IKN400810 | C69: Aspirators | D69: =VLOOKUP(B69,[13]AssetDetails_UEM!$A$3:$X$1848,22,FALSE) -> 7580 | E69: IKNWOBE26001308 | F69: 01RT233 | G69: 27-Jan-2026 00:00:00 | H69: 27-Jan-2026 08:15:00 | I69: NA | J69: N | K69: =ROUNDUP((D69/4999.99)*10,-1) -> 20 | L69: =IF(J69="N",0,K69) -> 0 | M69: P-QE:16, MAINTENANCE DONE A PER CHECKLIST ATTACHED
A70: 49 | B70: IKN400812 | C70: Defibrillators, External, Manual | D70: =VLOOKUP(B70,[13]AssetDetails_UEM!$A$3:$X$1848,22,FALSE) -> 45000 | E70: IKNWOBE26001309 | F70: 01RT237 | G70: 27-Jan-2026 00:00:00 | H70: 27-Jan-2026 09:00:00 | I70: NA | J70: N | K70: =ROUNDUP((D70/4999.99)*10,-1) -> 100 | L70: =IF(J70="N",0,K70) -> 0 | M70: P - QE:16 , MAINTENANCE DONE AS PER HEPPM CHECKLIST ATTACHED
A71: 50 | B71: IKN400826 | C71: Warming Units, Patient, Forced-Air | D71: =VLOOKUP(B71,[13]AssetDetails_UEM!$A$3:$X$1848,22,FALSE) -> 15515 | E71: IKNWOBE26001310 | F71: 01RT239 | G71: 27-Jan-2026 00:00:00 | H71: 27-Jan-2026 10:00:00 | I71: NA | J71: N | K71: =ROUNDUP((D71/4999.99)*10,-1) -> 40 | L71: =IF(J71="N",0,K71) -> 0 | M71: P - QE:16 , MAINTENANCE DONE AS PER HEPPM CHECKLIST ATTACHED
A72: 51 | B72: IKN400827 | C72: Warming Units, Blood/Solution | D72: =VLOOKUP(B72,[13]AssetDetails_UEM!$A$3:$X$1848,22,FALSE) -> 15395 | E72: IKNWOBE26001311 | F72: 01RT275 | G72: 27-Jan-2026 00:00:00 | H72: 27-Jan-2026 11:00:00 | I72: NA | J72: N | K72: =ROUNDUP((D72/4999.99)*10,-1) -> 40 | L72: =IF(J72="N",0,K72) -> 0 | M72: P - QE:16 , MAINTENANCE DONE AS PER HEPPM CHECKLIST ATTACHED
A73: 52 | B73: IKN400836 | C73: Warming Units, Blanket | D73: =VLOOKUP(B73,[13]AssetDetails_UEM!$A$3:$X$1848,22,FALSE) -> 15515 | E73: IKNWOBE26001312 | F73: 01RT275 | G73: 27-Jan-2026 00:00:00 | H73: 27-Jan-2026 12:00:00 | I73: NA | J73: N | K73: =ROUNDUP((D73/4999.99)*10,-1) -> 40 | L73: =IF(J73="N",0,K73) -> 0 | M73: P - QE:16 , MAINTENANCE DONE AS PER HEPPM CHECKLLIST ATTACHED
A74: 53 | B74: IKN400853 | C74: Warming Units, Blanket | D74: =VLOOKUP(B74,[13]AssetDetails_UEM!$A$3:$X$1848,22,FALSE) -> 15515 | E74: IKNWOBE26001313 | F74: 01RT278 | G74: 27-Jan-2026 00:00:00 | H74: 27-Jan-2026 12:30:00 | I74: NA | J74: N | K74: =ROUNDUP((D74/4999.99)*10,-1) -> 40 | L74: =IF(J74="N",0,K74) -> 0 | M74: P - QE:16 , MAINTENANCE DONE AS PER HEPPM CHECKLIST ATTACHED
A75: 54 | B75: IKN400153 | C75: Television Monitors | D75: =VLOOKUP(B75,[13]AssetDetails_UEM!$A$3:$X$1848,22,FALSE) -> 2700 | E75: IKNWOBE26001315 | F75: 05IC110 | G75: 28-Jan-2026 00:00:00 | H75: 46050.34 | I75: NA | J75: N | K75: =ROUNDUP((D75/4999.99)*10,-1) -> 10 | L75: =IF(J75="N",0,K75) -> 0 | M75: ROUTINE INSPECTION DONE AS PER CHECKLIST ATTACHED.
A76: 55 | B76: IKN400154 | C76: Television Monitors | D76: =VLOOKUP(B76,[13]AssetDetails_UEM!$A$3:$X$1848,22,FALSE) -> 2700 | E76: IKNWOBE26001316 | F76: 05IC117 | G76: 28-Jan-2026 00:00:00 | H76: 46050.361 | I76: NA | J76: N | K76: =ROUNDUP((D76/4999.99)*10,-1) -> 10 | L76: =IF(J76="N",0,K76) -> 0 | M76: ROUTINE INSPECTION DONE AS PER CHECKLIST ATTACHED.
A77: 56 | B77: IKN400155 | C77: Television Monitors | D77: =VLOOKUP(B77,[13]AssetDetails_UEM!$A$3:$X$1848,22,FALSE) -> 2700 | E77: IKNWOBE26001317 | F77: 05IC128 | G77: 28-Jan-2026 00:00:00 | H77: 46050.368 | I77: NA | J77: N | K77: =ROUNDUP((D77/4999.99)*10,-1) -> 10 | L77: =IF(J77="N",0,K77) -> 0 | M77: ROUTINE INSPECTION DONE AS PER CHECKLIST ATTACHED.
A78: 57 | B78: IKN400156 | C78: Television Monitors | D78: =VLOOKUP(B78,[13]AssetDetails_UEM!$A$3:$X$1848,22,FALSE) -> 2700 | E78: IKNWOBE26001318 | F78: 05IC130 | G78: 28-Jan-2026 00:00:00 | H78: 46050.375 | I78: NA | J78: N | K78: =ROUNDUP((D78/4999.99)*10,-1) -> 10 | L78: =IF(J78="N",0,K78) -> 0 | M78: ROUTINE INSPECTION DONE AS PER CHECKLIST ATTACHED.
A79: 58 | B79: IKN400157 | C79: Aspirators | D79: =VLOOKUP(B79,[13]AssetDetails_UEM!$A$3:$X$1848,22,FALSE) -> 10705 | E79: IKNWOBE26001319 | F79: 05IC106 | G79: 28-Jan-2026 00:00:00 | H79: 46050.382 | I79: NA | J79: N | K79: =ROUNDUP((D79/4999.99)*10,-1) -> 30 | L79: =IF(J79="N",0,K79) -> 0 | M79: MAINTENANCE DONE ACCORDING TO HEPPM CHECKLIST ATTACHED.
A80: 59 | B80: IKN400158 | C80: Aspirators | D80: =VLOOKUP(B80,[13]AssetDetails_UEM!$A$3:$X$1848,22,FALSE) -> 10705 | E80: IKNWOBE26001320 | F80: 05IC106 | G80: 28-Jan-2026 00:00:00 | H80: 46050.417 | I80: NA | J80: N | K80: =ROUNDUP((D80/4999.99)*10,-1) -> 30 | L80: =IF(J80="N",0,K80) -> 0 | M80: MAINTENANCE DONE ACCORDING TO HEPPM CHECKLIST ATTACHED.
A81: 60 | B81: IKN400316 | C81: Electrocardiographs, Multichannel, Interpretative | D81: =VLOOKUP(B81,[13]AssetDetails_UEM!$A$3:$X$1848,22,FALSE) -> 25260 | E81: IKNWOBE26001321 | F81: 07WF107 | G81: 28-Jan-2026 00:00:00 | H81: 28-Jan-2026 10:45:00 | I81: NA | J81: N | K81: =ROUNDUP((D81/4999.99)*10,-1) -> 60 | L81: =IF(J81="N",0,K81) -> 0 | M81: L, QE:16-PPM COMPLETED AS HEPPM CHECKLIST
A82: 61 | B82: IKN400920 | C82: Defibrillators, External, Manual | D82: =VLOOKUP(B82,[13]AssetDetails_UEM!$A$3:$X$1848,22,FALSE) -> 45000 | E82: IKNWOBE26001322 | F82: 03MC124 | G82: 28-Jan-2026 00:00:00 | H82: 28-Jan-2026 09:30:00 | I82: NA | J82: N | K82: =ROUNDUP((D82/4999.99)*10,-1) -> 100 | L82: =IF(J82="N",0,K82) -> 0 | M82: L, QE:16-PPM COMPLETED AS PER HEPPM CHECKLIST
A83: 62 | B83: IKN401087 | C83: Physiologic Monitoring Systems, Acute Care | D83: =VLOOKUP(B83,[13]AssetDetails_UEM!$A$3:$X$1848,22,FALSE) -> 22000 | E83: IKNWOBE26001323 | F83: 01AE108 | G83: 28-Jan-2026 00:00:00 | H83: 46050.458 | I83: NA | J83: N | K83: =ROUNDUP((D83/4999.99)*10,-1) -> 50 | L83: =IF(J83="N",0,K83) -> 0 | M83: MAINTENANCE NOT DONE DUE TO UNIT UNDER BEYOND ECONOMIC REPAIR. PLEASE REFER REPORT ATTACHED.
A84: 63 | B84: IKN400208 | C84: Aspirators | D84: =VLOOKUP(B84,[13]AssetDetails_UEM!$A$3:$X$1848,22,FALSE) -> 5052 | E84: IKNWOBE26001324 | F84: 09WJ130 | G84: 29-Jan-2026 00:00:00 | H84: 29-Jan-2026 15:00:00 | I84: NA | J84: N | K84: =ROUNDUP((D84/4999.99)*10,-1) -> 20 | L84: =IF(J84="N",0,K84) -> 0 | M84: PPM DONE AS PERCHECKLIST
A85: 64 | B85: IKN400613 | C85: Infusion Pumps, General-Purpose | D85: =VLOOKUP(B85,[13]AssetDetails_UEM!$A$3:$X$1848,22,FALSE) -> 10825 | E85: IKNWOBE26001326 | F85: 04DO118 | G85: 29-Jan-2026 00:00:00 | H85: 29-Jan-2026 10:30:00 | I85: NA | J85: N | K85: =ROUNDUP((D85/4999.99)*10,-1) -> 30 | L85: =IF(J85="N",0,K85) -> 0 | M85: P - PPM DONE AS PERCHECKLIST
A86: 65 | B86: IKN400614 | C86: Infusion Pumps, General-Purpose | D86: =VLOOKUP(B86,[13]AssetDetails_UEM!$A$3:$X$1848,22,FALSE) -> 10825 | E86: IKNWOBE26001327 | F86: 04DO118 | G86: 29-Jan-2026 00:00:00 | H86: 29-Jan-2026 09:00:00 | I86: NA | J86: N | K86: =ROUNDUP((D86/4999.99)*10,-1) -> 30 | L86: =IF(J86="N",0,K86) -> 0 | M86: PPM DONE AS PERCHECKLIST
A87: 66 | B87: IKN400356 | C87: Electrocardiographs, Multichannel, Interpretative | D87: =VLOOKUP(B87,[13]AssetDetails_UEM!$A$3:$X$1848,22,FALSE) -> 25260 | E87: IKNWOBE26001329 | F87: 07WE107 | G87: 30-Jan-2026 00:00:00 | H87: 30-Jan-2026 08:30:00 | I87: NA | J87: N | K87: =ROUNDUP((D87/4999.99)*10,-1) -> 60 | L87: =IF(J87="N",0,K87) -> 0 | M87: L, QE:16-PPM COMPLETED AS HEPPM CHECKLIST
A88: 67 | B88: IKN400615 | C88: Infusion Pumps, General-Purpose | D88: =VLOOKUP(B88,[13]AssetDetails_UEM!$A$3:$X$1848,22,FALSE) -> 10825 | E88: IKNWOBE26001330 | F88: 04DO118 | G88: 30-Jan-2026 00:00:00 | H88: 30-Jan-2026 15:00:00 | I88: NA | J88: N | K88: =ROUNDUP((D88/4999.99)*10,-1) -> 30 | L88: =IF(J88="N",0,K88) -> 0 | M88: PPM DONE AS PERCHECKLIST
A89: 68 | B89: IKN402149 | C89: Electrosurgical Units, Monopolar | D89: =VLOOKUP(B89,[13]AssetDetails_UEM!$A$3:$X$1848,22,FALSE) -> 111330 | E89: IKNWOBE26001334 | F89: 05OT161 | G89: 30-Jan-2026 00:00:00 | H89: 46052.583 | I89: NA | J89: N | K89: =ROUNDUP((D89/4999.99)*10,-1) -> 230 | L89: =IF(J89="N",0,K89) -> 0 | M89: MAINTENANCE DONE ACCORDING TO HEPPM CHECKLIST ATTACHED.
A90: 69 | B90: IKN402150 | C90: Infusion Pumps, Syringe | D90: =VLOOKUP(B90,[13]AssetDetails_UEM!$A$3:$X$1848,22,FALSE) -> 12000 | E90: IKNWOBE26001335 | F90: 05IC115 | G90: 30-Jan-2026 00:00:00 | H90: 46052.333 | I90: NA | J90: N | K90: =ROUNDUP((D90/4999.99)*10,-1) -> 30 | L90: =IF(J90="N",0,K90) -> 0 | M90: MAINTENANCE DONE ACCORDING TO HEPPM CHECKLIST ATTACHED.
A91: 70 | B91: IKN402151 | C91: Analyzers, Laboratory, Blood Gas/pH | D91: =VLOOKUP(B91,[13]AssetDetails_UEM!$A$3:$X$1848,22,FALSE) -> 49000 | E91: IKNWOBE26001336 | F91: 05IC122 | G91: 30-Jan-2026 00:00:00 | H91: 46052.375 | I91: NA | J91: N | K91: =ROUNDUP((D91/4999.99)*10,-1) -> 100 | L91: =IF(J91="N",0,K91) -> 0 | M91: MAINTENANCE DONE ACCORDING TO HEPPM CHECKLIST ATTACHED.
A92: 71 | B92: IKN400565 | C92: Physiologic Monitoring Systems, Stress Exercise | D92: 138350 | E92: IKNWOBE26001325 | F92: 03NM155 | G92: 46051 | H92: 29/1/2026 15:30:00 PM | I92: NA | J92: N | K92: =ROUNDUP((D92/4999.99)*10,-1) -> 280 | L92: =IF(J92="N",0,K92) -> 0 | M92: MAINTENANCE DONE ACCORDING TO HEPPM CHECKLIST ATTACHED.
A93: 72 | B93: IKN400691 | C93: Defibrillators, External, Manual | D93: =VLOOKUP(B93,[13]AssetDetails_UEM!$A$3:$X$1848,22,FALSE) -> 45000 | E93: IKNWOBE25023988 | F93: 04PY130 | G93: 09-Jan-2026 00:00:00 | H93: 46031.375 | I93: NA | J93: N | K93: =ROUNDUP((D93/4999.99)*10,-1) -> 100 | L93: =IF(J93="N",0,K93) -> 0 | M93: MAINTENANCE DONE ACCORDING TO HEPPM CHECKLIST ATTACHED.
A94: Current Month (Open)
A95: 1 | B95: IKN401071 | C95: Video Image Processors, Endoscopic | D95: =VLOOKUP(B95,[13]AssetDetails_UEM!$A$3:$X$1848,22,FALSE) -> 80000 | E95: IKNWOBE26000883 | F95: 03MC108 | G95: 21-Jan-2026 00:00:00 | H95: - | J95: N | K95: =ROUNDUP((D95/4999.99)*10,-1) -> 170 | L95: =IF(J95="N",0,K95) -> 0 | M95: Rescheduled Unit under repair sent to Olympus for troubleshoot
A96: 2 | B96: IKN400689 | C96: Cryosurgical Units, General-Purpose | D96: =VLOOKUP(B96,[13]AssetDetails_UEM!$A$3:$X$1848,22,FALSE) -> 968448 | E96: IKNWOBE26001331 | F96: 03ID164 | G96: 30-Jan-2026 00:00:00 | H96: - | J96: N | K96: =ROUNDUP((D96/4999.99)*10,-1) -> 1940 | L96: =IF(J96="N",0,K96) -> 0 | M96: Rescheduled VENDOR NOT AVAILABLE Proposed for BER
A97: Previous Month (Closed)
A98: 1 | B98: IKN401222 | C98: Pipetters | D98: =VLOOKUP(B98,[13]AssetDetails_UEM!$A$3:$X$1848,22,FALSE) -> 1323 | E98: IKNWOBE25022048 | F98: 03NM139 | G98: 46003 | H98: 14-Jan-2026 08:00:00 | I98: 46038 | J98: N | K98: =ROUNDUP((D98/4999.99)*10,-1) -> 10 | L98: =IF(J98="N",0,K98) -> 0 | M98: Sent for calibration DN: 15/12/2025 DUE: 08/12/2025 (OUT FOR CALIBRATE) PO: 10128625 (8/10/2025)L- QE:16 CALIBRATION BY VENDOR. UNIT FUNCTIONING OKAY
A99: 2 | B99: IKN401224 | C99: Pipetters | D99: =VLOOKUP(B99,[13]AssetDetails_UEM!$A$3:$X$1848,22,FALSE) -> 1323 | E99: IKNWOBE25022049 | F99: 03NM139 | G99: 12-Dec-2025 | H99: 14-Jan-2026 09:00:00 | I99: 46038 | J99: N | K99: =ROUNDUP((D99/4999.99)*10,-1) -> 10 | L99: =IF(J99="N",0,K99) -> 0 | M99: Sent for calibration DN: 15/12/2025 DUE: 08/12/2025 (OUT FOR CALIBRATE) PO: 10128625 (8/10/2025)L, QE:16-CALIBRATION COMPLETE BY VENDOR . UNIT FUNCTIONING OKAY
A100: 3 | B100: IKN401226 | C100: Pipetters | D100: =VLOOKUP(B100,[13]AssetDetails_UEM!$A$3:$X$1848,22,FALSE) -> 1323 | E100: IKNWOBE25022050 | F100: 03NM139 | G100: 46003 | H100: 14-Jan-2026 10:00:00 | I100: 46038 | J100: N | K100: =ROUNDUP((D100/4999.99)*10,-1) -> 10 | L100: =IF(J100="N",0,K100) -> 0 | M100: Sent for calibration DN: 15/12/2025 DUE: 08/12/2025 (OUT FOR CALIBRATE) PO: 10128625 (8/10/2025)L, QE:16-CALIBRATION COMPLETE BY VENDOR, UNIT FUNCTIONING OKAY
A101: 4 | B101: IKN401124 | C101: Pipetters | D101: =VLOOKUP(B101,[13]AssetDetails_UEM!$A$3:$X$1848,22,FALSE) -> 596 | E101: IKNWOBE25022051 | F101: 03NM154 | G101: 46003 | H101: 14-Jan-2026 11:00:00 | I101: 46038 | J101: N | K101: =ROUNDUP((D101/4999.99)*10,-1) -> 10 | L101: =IF(J101="N",0,K101) -> 0 | M101: Sent for calibration DN: 15/12/2025 DUE: 08/12/2026 PO: 10128625 (8/10/2025)L, QE:16-CALIBRATION COMPLETE BY VENDOR, UNIT FUNCTIONING OKAY
A102: 5 | B102: IKN401125 | C102: Pipetters | D102: =VLOOKUP(B102,[13]AssetDetails_UEM!$A$3:$X$1848,22,FALSE) -> 762 | E102: IKNWOBE25022052 | F102: 03NM154 | G102: 46003 | H102: 14-Jan-2026 12:00:00 | I102: 46038 | J102: N | K102: =ROUNDUP((D102/4999.99)*10,-1) -> 10 | L102: =IF(J102="N",0,K102) -> 0 | M102: Sent for calibration DN: 15/12/2025 DUE: 08/12/2026 PO: 10128625 (8/10/2025)L, QE:16-CALIBRATION COMPLETE BY VENDOR, UNIT TESTED FUNCTIONING OKAY
A103: 6 | B103: IKN400990 | C103: Radiation Monitors | D103: =VLOOKUP(B103,[13]AssetDetails_UEM!$A$3:$X$1848,22,FALSE) -> 23270 | E103: IKNWOBE25021542 | F103: 03NM143 | G103: 05-Dec-2025 | H103: 14-Jan-2026 16:00:00 | I103: 46031 | J103: N | K103: =ROUNDUP((D103/4999.99)*10,-1) -> 50 | L103: =IF(J103="N",0,K103) -> 0 | M103: Sent for calibration DN: 5/12/2025 DUE:31/12/25 PO: 10128425 (8/10/2025) L, QE:16- PPM NOT DONE , REFER ATTACHMENT
A104: 7 | B104: IKN401698 | C104: Dynamometers | D104: =VLOOKUP(B104,[13]AssetDetails_UEM!$A$3:$X$1848,22,FALSE) -> 2298 | E104: IKNWOBE25023171 | F104: 03DU102 | G104: 24-Dec-2025 | H104: 12-Jan-2026 12:00:00 | I104: 46029 | J104: N | K104: =ROUNDUP((D104/4999.99)*10,-1) -> 10 | L104: =IF(J104="N",0,K104) -> 0 | M104: Sent for calibration DN: 3/12/2025 DUE: PO: 11148525 (27/11/2025)PPM SERVICE AND CALIBRATION DONE BY UCAL TECH. REFER TO CALIBRATION CERTIFICATE AS ATTACHED.
A105: Previous Month (Open)
A106: 1 | B106: IKN400996 | C106: Radiation Monitors | D106: =VLOOKUP(B106,[13]AssetDetails_UEM!$A$3:$X$1848,22,FALSE) -> 54570 | E106: IKNWOBE25020791 | F106: 03NM132 | G106: 45982.447 | H106: - | I106: 46031 | J106: N | K106: =ROUNDUP((D106/4999.99)*10,-1) -> 110 | L106: =IF(J106="N",0,K106) -> 0 | M106: Unit sent for calibration DN:21/11/25 DUE:6/12/25
A107: 2 | B107: IKN401195 | C107: Radiation Survey Meters, Ionization Chamber | D107: =VLOOKUP(B107,[13]AssetDetails_UEM!$A$3:$X$1848,22,FALSE) -> 6810 | E107: IKNWOBE25018986 | F107: 01RT213 | G107: 45952 | H107: - | I107: 46029 | J107: N | K107: =ROUNDUP((D107/4999.99)*10,-1) -> 20 | L107: =IF(J107="N",0,K107) -> 0 | M107: Unit sent for calibration DN:10/12/2025
A108: 3 | B108: IKN402147 | C108: Testers | D108: =VLOOKUP(B108,[13]AssetDetails_UEM!$A$3:$X$1848,22,FALSE) -> 142000 | E108: IKNWOBE25018200 | F108: 01RT131 | G108: 45939 | H108: - | I108: 46030 | J108: N | K108: =ROUNDUP((D108/4999.99)*10,-1) -> 290 | L108: =IF(J108="N",0,K108) -> 0 | M108: Rescheduled under breakdown (IKNWIBE25013055). Sent for calibration DN:31/12/2025 (Nagase)
A109: 4 | B109: IKN401277 | C109: Testers | D109: =VLOOKUP(B109,[13]AssetDetails_UEM!$A$3:$X$1848,22,FALSE) -> 40000 | E109: IKNWOBE25002671 | F109: 01RT213 | G109: 45707 | H109: - | I109: 46037 | J109: N | K109: =ROUNDUP((D109/4999.99)*10,-1) -> 90 | L109: =IF(J109="N",0,K109) -> 0 | M109: Sent for calibration DN:31/12/2025 (Nagase)
A110: 5 | B110: IKN401692 | C110: Testers | D110: =VLOOKUP(B110,[13]AssetDetails_UEM!$A$3:$X$1848,22,FALSE) -> 30000 | E110: IKNWOBE25009298 | F110: 01RT213 | G110: 45807 | H110: - | I110: 46030 | J110: N | K110: =ROUNDUP((D110/4999.99)*10,-1) -> 70 | L110: =IF(J110="N",0,K110) -> 0 | M110: Sent for calibration. DN:27/11/2025
A111: 6 | B111: IKN401365 | C111: Testers | D111: =VLOOKUP(B111,[13]AssetDetails_UEM!$A$3:$X$1848,22,FALSE) -> 400000 | E111: IKNWOBE25011527 | F111: 01RT213 | G111: 45841 | H111: - | I111: 46031 | J111: N | K111: =ROUNDUP((D111/4999.99)*10,-1) -> 810 | L111: =IF(J111="N",0,K111) -> 0 | M111: Sent for calibration DN:2/12/2025
A112: 7 | B112: IKN401274 | C112: Testers | D112: =VLOOKUP(B112,[13]AssetDetails_UEM!$A$3:$X$1848,22,FALSE) -> 40000 | E112: IKNWOBE25015424 | F112: 01RT213 | G112: 45898 | H112: - | I112: 46031 | J112: N | K112: =ROUNDUP((D112/4999.99)*10,-1) -> 90 | L112: =IF(J112="N",0,K112) -> 0 | M112: Sent for calibration DN:31/12/2025 (Nagase)
A113: 8 | B113: IKN401279 | C113: Testers | D113: =VLOOKUP(B113,[13]AssetDetails_UEM!$A$3:$X$1848,22,FALSE) -> 40000 | E113: IKNWOBE25015425 | F113: 01RT213 | G113: 45898 | H113: - | I113: 46031 | J113: N | K113: =ROUNDUP((D113/4999.99)*10,-1) -> 90 | L113: =IF(J113="N",0,K113) -> 0 | M113: Sent for calibration DN:31/12/2025 (Nagase)
A114: 9 | B114: IKN401282 | C114: Testers | D114: =VLOOKUP(B114,[13]AssetDetails_UEM!$A$3:$X$1848,22,FALSE) -> 40000 | E114: IKNWOBE25015426 | F114: 01RT213 | G114: 45898 | H114: - | I114: 46031 | J114: N | K114: =ROUNDUP((D114/4999.99)*10,-1) -> 90 | L114: =IF(J114="N",0,K114) -> 0 | M114: Sent for calibration DN:31/12/2025 (Nagase)
A115: 10 | B115: IKN401278 | C115: Testers | D115: =VLOOKUP(B115,[13]AssetDetails_UEM!$A$3:$X$1848,22,FALSE) -> 40000 | E115: IKNWOBE24018322 | F115: 01RT213 | G115: 45665 | H115: - | I115: 46036 | J115: N | K115: =ROUNDUP((D115/4999.99)*10,-1) -> 90 | L115: =IF(J115="N",0,K115) -> 0 | M115: Sent for calibration DN:31/12/2025 (Nagase)
A116: 11 | B116: IKN401366 | C116: Testers | D116: =VLOOKUP(B116,[13]AssetDetails_UEM!$A$3:$X$1848,22,FALSE) -> 100000 | E116: IKNWOBE25016423 | F116: 01RT213 | G116: 45911 | H116: - | I116: 46030 | J116: N | K116: =ROUNDUP((D116/4999.99)*10,-1) -> 210 | L116: =IF(J116="N",0,K116) -> 0 | M116: Sent for calibration DN:31/12/2025 (Nagase)
A117: 12 | B117: IKN401708 | C117: Testers | D117: =VLOOKUP(B117,[13]AssetDetails_UEM!$A$3:$X$1848,22,FALSE) -> 100000 | E117: IKNWOBE25016424 | F117: 01RT213 | G117: 45918 | H117: - | I117: 46030 | J117: N | K117: =ROUNDUP((D117/4999.99)*10,-1) -> 210 | L117: =IF(J117="N",0,K117) -> 0 | M117: Sent for calibration DN:31/12/2025 (Nagase)
... A120: 15 | B120: IKN401199 | C120: Densitometers | D120: =VLOOKUP(B120,[13]AssetDetails_UEM!$A$3:$X$1848,22,FALSE) -> 5000 | E120: IKNWOBE25017724 | F120: 03NM170 | G120: 45933 | H120: - | I120: 46038 | J120: N | K120: =ROUNDUP((D120/4999.99)*10,-1) -> 20 | L120: =IF(J120="N",0,K120) -> 0 | M120: Rescheduled Unit sent for calibration DN:6/10/25. Unit breakdown during calibration
...

Sheet B4-UPTIME 
A1: MINISTRY OF HEALTH
A2: Deduction Mapping Report Biomedical Engineering Maintenance Services (BEMS)
A3: INDICATOR B.4 UPTIME GUARANTEE
B5: HOSPITAL NAME : | C5: INSTITUT KANSER NEGARA | N5: MONTH/YEAR : | U5: 46023
B7: STATE : | C7: WILAYAH PERSEKUTUAN PUTRAJAYA | N7: BEMS MONTHLY FEE (RM)@ 97.5% : | U7: =BEMSdar!E11 -> 1437864.8
B9: COMPANY : | C9: AMBANG WIRA SDN BHD | N9: FMS MONTHLY FEE (RM) @ 2.5% : | U9: =BEMSdar!E13 -> 36868.327
A11: Notes:
A12: 1) Deduction Ringgit Equivalent is based on Appendix 11 of the Agreement, Section B3 Key Deduction Indicators for BEMS
A13: 2) Deduction Value for 1st cut off is Deduction Ringgit Equivalent (per event)
A14: 3) Deduction Value for 2nd cut off is Deduction Ringgit Equivalent (per event) multiply by 2
A15: 4) Display only asset affected by deduction
A17: No. | B17: Asset No | C17: Type Code | D17: Type Description | E17: Asset Purchase cost (RM) | F17: Asset Age | G17: TRKPI % | H17: Uptime % | T17: Deduction Ringgit Equivalent (RM) | U17: Previous Deduction (Month) | W17: Deduction for the month (Y/N) | Y17: Deduction Value (RM) | AA17: Total Deduction (RM) | AB17: Remarks
H18: Jan | I18: Feb | J18: Mar | K18: Apr | L18: May | M18: Jun | N18: Jul | O18: Aug | P18: Sep | Q18: Oct | R18: Nov | S18: Dec | U18: 1st | V18: 2nd | W18: 1st | X18: 2nd | Y18: 1st | Z18: 2nd
A19: 1 | B19: IKN400440 | C19: 16-173 | D19: Sphygmomanometers, Electronic, Automatic | E19: 4510 | F19: 13 | G19: 0.88 | H19: 99.82733 | T19: =ROUNDUP((E19/4999.99)*10,-1) -> 10 | U19: N | V19: N | W19: N | X19: N | Y19: =IF(W19="Y",T19,0) -> 0 | Z19: =IF(X19="Y",T19*2,0) -> 0 | AA19: =Y19+Z19 -> 0
A20: 2 | B20: IKN400645 | C20: 13-215 | D20: Infusion Pumps, General-Purpose | E20: 10825 | F20: 13 | G20: 0.88 | H20: 99.961971 | T20: =ROUNDUP((E20/4999.99)*10,-1) -> 30 | U20: N | V20: N | W20: N | X20: N | Y20: =IF(W20="Y",T20,0) -> 0 | Z20: =IF(X20="Y",T20*2,0) -> 0 | AA20: =Y20+Z20 -> 0
A21: 3 | B21: IKN401714 | C21: 13-215 | D21: Infusion Pumps, General-Purpose | E21: 5800 | F21: 8 | G21: 0.95 | H21: 99.962034 | T21: =ROUNDUP((E21/4999.99)*10,-1) -> 20 | U21: Y | V21: Y | W21: N | X21: N | Y21: =IF(W21="Y",T21,0) -> 0 | Z21: =IF(X21="Y",T21*2,0) -> 0 | AA21: =Y21+Z21 -> 0
A22: 4 | B22: IKN400446 | C22: 13-215 | D22: Infusion Pumps, General-Purpose | E22: 10825 | F22: 13 | G22: 0.88 | H22: 99.059561 | T22: =ROUNDUP((E22/4999.99)*10,-1) -> 30 | U22: N | V22: N | W22: N | X22: N | Y22: =IF(W22="Y",T22,0) -> 0 | Z22: =IF(X22="Y",T22*2,0) -> 0 | AA22: =Y22+Z22 -> 0
A23: 5 | B23: IKN400366 | C23: 13-215 | D23: Infusion Pumps, General-Purpose | E23: 10825 | F23: 13 | G23: 0.88 | H23: 99.082187 | T23: =ROUNDUP((E23/4999.99)*10,-1) -> 30 | U23: N | V23: N | W23: N | X23: N | Y23: =IF(W23="Y",T23,0) -> 0 | Z23: =IF(X23="Y",T23*2,0) -> 0 | AA23: =Y23+Z23 -> 0
A24: 6 | B24: IKN402165 | C24: 13-215 | D24: Infusion Pumps, General-Purpose | E24: 10825 | F24: 13 | G24: 0.88 | H24: 99.139282 | T24: =ROUNDUP((E24/4999.99)*10,-1) -> 30 | U24: N | V24: N | W24: N | X24: N | Y24: =IF(W24="Y",T24,0) -> 0 | Z24: =IF(X24="Y",T24*2,0) -> 0 | AA24: =Y24+Z24 -> 0
A25: 7 | B25: IKN400565 | C25: 12-649 | D25: Physiologic Monitoring Systems, Stress Exercise | E25: 138350 | F25: 13 | G25: 0.88 | H25: 99.17824 | T25: =ROUNDUP((E25/4999.99)*10,-1) -> 280 | U25: N | V25: N | W25: N | X25: N | Y25: =IF(W25="Y",T25,0) -> 0 | Z25: =IF(X25="Y",T25*2,0) -> 0 | AA25: =Y25+Z25 -> 0
A26: 8 | B26: IKN400439 | C26: 16-173 | D26: Sphygmomanometers, Electronic, Automatic | E26: 4510 | F26: 13 | G26: 0.88 | H26: 99.188573 | T26: =ROUNDUP((E26/4999.99)*10,-1) -> 10 | U26: N | V26: N | W26: N | X26: N | Y26: =IF(W26="Y",T26,0) -> 0 | Z26: =IF(X26="Y",T26*2,0) -> 0 | AA26: =Y26+Z26 -> 0
A27: 9 | B27: IKN401076 | C27: 12-306 | D27: Lavage Units, Surgical | E27: 5000 | F27: 13 | G27: 0.85 | H27: 99.248469 | T27: =ROUNDUP((E27/4999.99)*10,-1) -> 20 | U27: N | V27: N | W27: N | X27: N | Y27: =IF(W27="Y",T27,0) -> 0 | Z27: =IF(X27="Y",T27*2,0) -> 0 | AA27: =Y27+Z27 -> 0
A28: 10 | B28: IKN402147 | C28: 15-605 | D28: Testers (Ion Chamber Set) | E28: 142000 | F28: 4 | G28: 0.96 | H28: 97.751902 | T28: =ROUNDUP((E28/4999.99)*10,-1) -> 290 | U28: N | V28: N | W28: N | X28: N | Y28: =IF(W28="Y",T28,0) -> 0 | Z28: =IF(X28="Y",T28*2,0) -> 0 | AA28: =Y28+Z28 -> 0
A29: 11 | B29: IKN401071 | C29: 18-034 | D29: Video Image Processors, Endoscopic | E29: 80000 | F29: 13 | G29: 0.88 | H29: 99.473871 | T29: =ROUNDUP((E29/4999.99)*10,-1) -> 170 | U29: Y | V29: Y | W29: N | X29: N | Y29: =IF(W29="Y",T29,0) -> 0 | Z29: =IF(X29="Y",T29*2,0) -> 0 | AA29: =Y29+Z29 -> 0
A30: 12 | B30: IKN402081 | C30: 13-215 | D30: Infusion Pumps, General-Purpose | E30: 3500 | F30: 5 | G30: 0.95 | H30: 99.49708 | T30: =ROUNDUP((E30/4999.99)*10,-1) -> 10 | U30: N | V30: N | W30: N | X30: N | Y30: =IF(W30="Y",T30,0) -> 0 | Z30: =IF(X30="Y",T30*2,0) -> 0 | AA30: =Y30+Z30 -> 0
... A34: 16 | B34: IKN400782 | C34: 17-679 | D34: Laser Imagers | E34: 83100 | F34: 13 | G34: 0.85 | H34: 99.640291 | T34: =ROUNDUP((E34/4999.99)*10,-1) -> 170 | U34: N | V34: N | W34: N | X34: N | Y34: =IF(W34="Y",T34,0) -> 0 | Z34: =IF(X34="Y",T34*2,0) -> 0 | AA34: =Y34+Z34 -> 0
A35: TOTAL DEDUCTION FOR IND. B.4: | AA35: =SUM(AA19:AA34) -> 0
