Workbook
Name _05_04_2009: #REF!
Name _05_04_2009: #REF!
Name _05_04_2009: #REF!
Name _05_04_2009: #REF!
Name _05_04_2009: #REF!
Name a: '[1]Term Outstanding Payment'!#REF!
Name a: '[1]Term Outstanding Payment'!#REF!
Name a: '[1]Term Outstanding Payment'!#REF!
Name a: '[1]Term Outstanding Payment'!#REF!
Name a: '[1]Term Outstanding Payment'!#REF!
Name AA: #REF!
Name AA: #REF!
Name AA: #REF!
Name AA: #REF!
Name AA: #REF!
Name aaa: #REF!
Name aaa: #REF!
Name aaa: #REF!
Name aaa: #REF!
Name aaa: #REF!
Name aaaaa: #REF!
Name aaaaa: #REF!
Name aaaaa: #REF!
Name aaaaa: #REF!
Name aaaaa: #REF!
Name aaaaaaaaaa: #REF!
Name aaaaaaaaaa: #REF!
Name aaaaaaaaaa: #REF!
Name aaaaaaaaaa: #REF!
Name AAAAAAAAAAAAA: #REF!
Name AAAAAAAAAAAAA: #REF!
Name AAAAAAAAAAAAA: #REF!
Name AAAAAAAAAAAAA: #REF!
Name AAAAAAAAAAAAAAAAAA: #REF!
Name AAAAAAAAAAAAAAAAAA: #REF!
Name AAAAAAAAAAAAAAAAAA: #REF!
Name AAAAAAAAAAAAAAAAAA: #REF!
Name AAAAAAAAAAAAAAAAAAAAA: #REF!
Name AAAAAAAAAAAAAAAAAAAAA: #REF!
Name AAAAAAAAAAAAAAAAAAAAA: #REF!
Name AAAAAAAAAAAAAAAAAAAAA: #REF!
Name AAAAAAAAAAAAAAAAAAAAAAAAAAA: #REF!
Name AAAAAAAAAAAAAAAAAAAAAAAAAAA: #REF!
Name AAAAAAAAAAAAAAAAAAAAAAAAAAA: #REF!
Name AAAAAAAAAAAAAAAAAAAAAAAAAAA: #REF!
Name AAAAAAAAAAAAAAAAAAAAAAAAAAAA: #REF!
Name AAAAAAAAAAAAAAAAAAAAAAAAAAAA: #REF!
Name AAAAAAAAAAAAAAAAAAAAAAAAAAAA: #REF!
Name AAAAAAAAAAAAAAAAAAAAAAAAAAAA: #REF!
Name AAAAAAAAAAAAAAAAAAAAAAAAAAAAAA: #REF!
Name AAAAAAAAAAAAAAAAAAAAAAAAAAAAAA: #REF!
Name AAAAAAAAAAAAAAAAAAAAAAAAAAAAAA: #REF!
Name AAAAAAAAAAAAAAAAAAAAAAAAAAAAAA: #REF!
Name AAAAAAAAAAAAAAAAAAAAAAAAAAAAAAA: #REF!
Name AAAAAAAAAAAAAAAAAAAAAAAAAAAAAAA: #REF!
Name AAAAAAAAAAAAAAAAAAAAAAAAAAAAAAA: #REF!
Name AAAAAAAAAAAAAAAAAAAAAAAAAAAAAAA: #REF!
Name AAAAAAAAAAAAAAAAAAAAAAAAAAAAAAAAA: #REF!
Name AAAAAAAAAAAAAAAAAAAAAAAAAAAAAAAAA: #REF!
Name AAAAAAAAAAAAAAAAAAAAAAAAAAAAAAAAA: #REF!

Sheet BEMSdar
A1: MINISTRY OF HEALTH
A2: Deduction Mapping Report Biomedical Engineering Maintenance Services (BEMS)
D5: HOSPITAL NAME : | E5: Institut Kanser Negara | I5: STATE: | J5: W.P. Putrajaya
D7: MONTH/YEAR : | E7: 46113 | I7: COMPANY: | J7: Ambang Wira Sdn Bhd
A9: MONTHLY SERVICE FEE (RM) : | E9: 1363910.9
A11: BEMS MONTHLY FEE (RM) @ 97.5% : | E11: =97.5%*E9 -> 1329813.2
A13: FMS MONTHLY FEE (RM) @ 2.5% : | E13: =2.5%*E9 -> 34097.773
A17: No | B17: Key Deduction Indicators | I17: Frequency | L17: Deduction Value (RM) | N17: Deduction % | O17: Performance Level (%)
A19: B.1 | B19: All service requests shall be responded by the Company’s trained technical personal within the timeframe as stipulated in the Agreement. | I19: Per event | L19: 0 | N19: 0 | O19: =100-N19 -> 100
A20: B.2 | B20: All unscheduled maintenance works including relevant maintenance calibration, safety tests and functional checks shall be completed within seven (7) working days. | I20: Per day | L20: ='B1&B2 UNSCHEDULED'!U122 -> 1600 | N20: =L20/$E$11% -> 0.12031765 | O20: =100-N20 -> 99.879682
A21: B.3 | B21: Scheduled maintenance shall be carried out as per schedule and according to the procedure as specified in the Agreement. Scheduled maintenance shall include complete safety and performance tests. | I21: Per event | L21: ='B3-SCHEDULED'!L313 -> 0 | N21: =L21/$E$11% -> 0 | O21: =100-N21 -> 100
A22: B.4 | B22: All biomedical equipment shall be functioning and maintained to ensure uptime target as specified in the TRKPI are met. | I22: Per event | L22: 0 | N22: =L22/$E$11% -> 0 | O22: =100-N22 -> 100
A23: B.5 | B23: T&C and Warranty Management of newly introduced biomedical shall be managed and performed according to the Agreement and related acts, standards and regulations. | I23: Per event | L23: ='B5-T&C'!O24 -> 0 | N23: =L23/$E$11% -> 0 | O23: =100-N23 -> 100
A24: Total | L24: =SUM(L19:M23) -> 1600 | N24: =SUM(N19:N23) -> 0.12031765 | O24: =100-N24 -> 99.879682
C27: Prepared by: | I27: Verified by:
C31: Siti Norsaliana Binti Abu Khalid | I31: Mohd Shahrulnizam bin Tarmizi
C32: Head of BEMS | I32: Facility Manager
C33: Ambang Wira Sdn Bhd- Institut Kanser Negara | I33: Ambang Wira Sdn Bhd- Institut Kanser Negara
C34: Date: | I34: Date:

Sheet B1&B2 UNSCHEDULED
A2: MINISTRY OF HEALTH
A3: Deduction Mapping Report Biomedical Engineering Maintenance Services (BEMS)
A4: INDICATOR B.1 RESPONSE TIME & B.2 REPAIR TIME
A6: HOSPITAL NAME: | C6: INSTITUT KANSER NEGARA | I6: FIRST DATE OF THE MONTH : | M6: 46113 | Q6: (For Calculation)
A8: STATE: | C8: WILAYAH PERSEKUTUAN PUTRAJAYA | I8: LAST DATE OF THE MONTH : | M8: 46142 | Q8: (For Calculation)
A10: COMPANY: | C10: AMBANG WIRA SDN BHD | I10: BEMS MONTHLY FEE (RM) @ 97.5% : | M10: =BEMSdar!E11 -> 1329813.2
A12: MONTH/YEAR: | C12: 46082 | I12: FMS MONTHLY FEE (RM) @ 2.5% : | M12: =BEMSdar!E13 -> 34097.773
A14: Notes:
A15: 1) Deduction Ringgit Equivalent is based on Appendix 11 of the Agreement, Section B3 Key Deduction Indicators for BEMS
A16: 2) Deduction Value for Indicator B.1 is Deduction Ringgit Equivalent (per event)
A17: 3) Total Repair Time includes weekend & public holiday
A18: 4) Demerit Point for Indicator B.2 is calculated based on completion date against request date, less by 7 working days
A19: 5) Deduction Value for Indicator B.2 is Demerit Point multiply by Deduction Ringgit Equivalent
A21: No | B21: Asset No | C21: Asset Description | D21: Asset Purchase Price (RM) | E21: Work Order No. | F21: User Location | G21: Work Order/ Complaint Details | H21: Response Category (Emergency/ Normal) | I21: Total Response Time (minutes) | J21: Work Request Date | K21: Response Time (Minutes) | L21: Work Completion Date | M21: Deduction Ringgit Equivalent (RM) | N21: Indicator B.1 | Q21: Indicator B.2
N22: Validate Status (Y/N) | O22: Deduction Value (RM) | P22: Remarks/ Exemption | Q22: Validate Status (Y/N) | R22: Total Repair Time (day) | S22: Last date of 7 working days (dd/mm/yy) | T22: Demerit Point | U22: Deduction Value (RM) | V22: Remarks/ Exemption
A23: Current Month (Work Order Completed)
A24: 1 | B24: IKN400756 | C24: =VLOOKUP(B24,[13]AssetDetails_UEM!$A$3:$AH$1849,6,FALSE) -> Analyzers, Laboratory, Hematology, Coagulation, Automated | D24: =VLOOKUP(B24,[13]AssetDetails_UEM!$A$3:$AK$1849,22,FALSE) -> 105860 | E24: IKNWIBE26006151 | F24: 04LA132 | G24: CUVETTE STUCK AT MOTOR | H24: Normal | I24: 0 days, 0 hrs, 23 mins | J24: 01-Apr-2026 14:07:00 | K24: 01-Apr-2026 14:30:00 | L24: 01-Apr-2026 16:30:00 | M24: =IF(D24>44999.99,100,ROUNDUP((D24/4999.99)*10,-1)) -> 100 | N24: N | O24: ='[14]B1& B2 UNSCHEDULED'!$O$24 -> 0 | Q24: N | R24: =IF(L24="",AKHIR-J24,L24-J24+1) -> 1.0993056 | S24: =WORKDAY(J24,6,AKHIR) -> 46121 | T24: 0 | U24: =IF(Q24="N",0,M24*T24) -> 0 | V24: P - QE:12, REMOVE CUVETTE FROM MOTR. RESTART THE UNIT
A25: 2 | B25: IKN400756 | C25: =VLOOKUP(B25,[13]AssetDetails_UEM!$A$3:$AH$1849,6,FALSE) -> Analyzers, Laboratory, Hematology, Coagulation, Automated | D25: =VLOOKUP(B25,[13]AssetDetails_UEM!$A$3:$AK$1849,22,FALSE) -> 105860 | E25: IKNWIBE26006247 | F25: 04LA132 | G25: WRONG POSITIONING CUVETTE | H25: Normal | I25: 0 days, 0 hrs, 10 mins | J25: 02-Apr-2026 10:24:00 | K25: 46114.44 | L25: 02-Apr-2026 15:30:00 | M25: =IF(D25>44999.99,100,ROUNDUP((D25/4999.99)*10,-1)) -> 100 | N25: N | O25: ='[14]B1& B2 UNSCHEDULED'!$O$24 -> 0 | Q25: N | R25: =IF(L25="",AKHIR-J25,L25-J25+1) -> 1.2125 | S25: =WORKDAY(J25,6,AKHIR) -> 46122 | T25: 0 | U25: =IF(Q25="N",0,M25*T25) -> 0 | V25: AK- ADJUST CUVETTE POSITION INFORM USER TO ADJUST CUVETTE POSITIONING
A26: 3 | B26: IKN400286 | C26: =VLOOKUP(B26,[13]AssetDetails_UEM!$A$3:$AH$1849,6,FALSE) -> Infusion Pumps, Syringe | D26: =VLOOKUP(B26,[13]AssetDetails_UEM!$A$3:$AK$1849,22,FALSE) -> 10225 | E26: IKNWIBE26006251 | F26: 08WH121 | G26: USER TRAINING FOR INFUSION PUMPS, SYRINGE | H26: User Training | I26: 0 days, 0 hrs, 10 mins | J26: 02-Apr-2026 14:30:00 | K26: 46114.611 | L26: 46114.653 | M26: =IF(D26>44999.99,100,ROUNDUP((D26/4999.99)*10,-1)) -> 30 | N26: N | O26: ='[14]B1& B2 UNSCHEDULED'!$O$24 -> 0 | Q26: N | R26: =IF(L26="",AKHIR-J26,L26-J26+1) -> 1.0486111 | S26: =WORKDAY(J26,6,AKHIR) -> 46122 | T26: 0 | U26: =IF(Q26="N",0,M26*T26) -> 0 | V26: DONE DO THE USER TRAINING FOR INFUSION PUMPS, SYRINGE
A27: 4 | B27: IKN400349 | C27: =VLOOKUP(B27,[13]AssetDetails_UEM!$A$3:$AH$1849,6,FALSE) -> Sphygmomanometers, Electronic, Automatic | D27: =VLOOKUP(B27,[13]AssetDetails_UEM!$A$3:$AK$1849,22,FALSE) -> 4510 | E27: IKNWIBE26006256 | F27: 07WF143 | G27: CUFF LEAKING.UNABLE TO PUMP | H27: Normal | I27: 0 days, 0 hrs, 56 mins | J27: 02-Apr-2026 16:34:00 | K27: 02-Apr-2026 17:30:00 | L27: 02-Apr-2026 18:10:00 | M27: =IF(D27>44999.99,100,ROUNDUP((D27/4999.99)*10,-1)) -> 10 | N27: N | O27: ='[14]B1& B2 UNSCHEDULED'!$O$24 -> 0 | Q27: N | R27: =IF(L27="",AKHIR-J27,L27-J27+1) -> 1.0666667 | S27: =WORKDAY(J27,6,AKHIR) -> 46122 | T27: 0 | U27: =IF(Q27="N",0,M27*T27) -> 0 | V27: M-REPLACE CUFF. TESTED OKAY AND FUNCTIONING
A28: 5 | B28: IKN402179 | C28: =VLOOKUP(B28,[13]AssetDetails_UEM!$A$3:$AH$1849,6,FALSE) -> Scanning Systems, Computed Tomography/ Positron Emission Tomography | D28: =VLOOKUP(B28,[13]AssetDetails_UEM!$A$3:$AK$1849,22,FALSE) -> 3410390 | E28: IKNWIBE26006261 | F28: 03NM161 | G28: PREDICTIVE MAINTENANCE SPECT CT | H28: Corrective Maintenance (CM) | I28: 0 days, 0 hrs, 10 mins | J28: 02-Apr-2026 14:00:00 | K28: 46114.59 | L28: 02-Apr-2026 20:00:00 | M28: =IF(D28>44999.99,100,ROUNDUP((D28/4999.99)*10,-1)) -> 100 | N28: N | O28: ='[14]B1& B2 UNSCHEDULED'!$O$24 -> 0 | Q28: N | R28: =IF(L28="",AKHIR-J28,L28-J28+1) -> 1.25 | S28: =WORKDAY(J28,6,AKHIR) -> 46122 | T28: 0 | U28: =IF(Q28="N",0,M28*T28) -> 0 | V28: L, QE:15-PLANNED PREDECTIVE MAINTENANCE AND INSTALLED PATIENT TABLE ELEVATION LOCKING MECHANISM BY VENDOR, TESTED OKAY
A29: 6 | B29: IKN400586 | C29: =VLOOKUP(B29,[13]AssetDetails_UEM!$A$3:$AH$1849,6,FALSE) -> Oximeters, Pulse | D29: =VLOOKUP(B29,[13]AssetDetails_UEM!$A$3:$AK$1849,22,FALSE) -> 11120 | E29: IKNWIBE26006262 | F29: 03NM108 | G29: UNIT UNDER BREAKDOWN | H29: Corrective Maintenance (CM) | I29: 0 days, 1 hrs, 40 mins | J29: 02-Apr-2026 13:00:00 | K29: 46114.611 | L29: 09-Apr-2026 15:00:00 | M29: =IF(D29>44999.99,100,ROUNDUP((D29/4999.99)*10,-1)) -> 30 | N29: N | O29: ='[14]B1& B2 UNSCHEDULED'!$O$24 -> 0 | Q29: N | R29: 6 | S29: =WORKDAY(J29,6,AKHIR) -> 46122 | T29: 0 | U29: =IF(Q29="N",0,M29*T29) -> 0 | V29: L, QE:12-REPLACED BATTERY AMD SPO2 PROBE TESTED OKAY
A30: 7 | B30: IKN400413 | C30: =VLOOKUP(B30,[13]AssetDetails_UEM!$A$3:$AH$1849,6,FALSE) -> Sphygmomanometers, Electronic, Automatic | D30: =VLOOKUP(B30,[13]AssetDetails_UEM!$A$3:$AK$1849,22,FALSE) -> 7770 | E30: IKNWIBE26006349 | F30: 06WD124 | G30: BP SET CANNOT READING | H30: Normal | I30: 0 days, 0 hrs, 28 mins | J30: 03-Apr-2026 11:47:00 | K30: 03-Apr-2026 12:15:00 | L30: 03-Apr-2026 18:50:00 | M30: =IF(D30>44999.99,100,ROUNDUP((D30/4999.99)*10,-1)) -> 20 | N30: N | O30: ='[14]B1& B2 UNSCHEDULED'!$O$24 -> 0 | Q30: N | R30: 5 | S30: =WORKDAY(J30,6,AKHIR) -> 46125 | T30: 0 | U30: =IF(Q30="N",0,M30*T30) -> 0 | V30: L, QE:12- UNIT KEEP PUMPING READING BP NOT APPEAR ERROR 803, UNIT FOUND LACK OF AIR , CHECK TUBING MAKE SURE NO COGGED, TEST UNIT AIR, BP READING APPEAR, UNIT FIT TO USE
A31: 8 | B31: IKN402180 | C31: =VLOOKUP(B31,[13]AssetDetails_UEM!$A$3:$AH$1849,6,FALSE) -> Scanning Systems, Computed Tomography/ Positron Emission Tomography | D31: =VLOOKUP(B31,[13]AssetDetails_UEM!$A$3:$AK$1849,22,FALSE) -> 3413750 | E31: IKNWIBE26006360 | F31: 03NM158 | G31: PREDICTIVE MAINTENANCE SPECT CT | H31: Corrective Maintenance (CM) | I31: 0 days, 0 hrs, 10 mins | J31: 03-Apr-2026 14:00:00 | K31: 46115.59 | L31: 03-Apr-2026 20:00:00 | M31: =IF(D31>44999.99,100,ROUNDUP((D31/4999.99)*10,-1)) -> 100 | N31: N | O31: ='[14]B1& B2 UNSCHEDULED'!$O$24 -> 0 | Q31: N | R31: =IF(L31="",AKHIR-J31,L31-J31+1) -> 1.25 | S31: =WORKDAY(J31,6,AKHIR) -> 46125 | T31: 0 | U31: =IF(Q31="N",0,M31*T31) -> 0 | V31: L, QE:15-PLANNED PREDECTIVE MAINTENANCE AND INSTALLED PATIENT TABLE ELEVATION LOCKING MECHANISM BY VENDOR, TESTED OKAY
A32: 9 | B32: IKN402237 | C32: Tester | D32: 40001 | E32: IKNWIBE26006556 | F32: 01AE111 | G32: USER TRAINING FOR SIMULATOR MULTIPARAMETER | H32: User Training | I32: 0 days, 0 hrs, 10 mins | J32: 07-Apr-2026 08:30:00 | K32: 46119.361 | L32: 46119.396 | M32: =IF(D32>44999.99,100,ROUNDUP((D32/4999.99)*10,-1)) -> 90 | N32: N | O32: ='[14]B1& B2 UNSCHEDULED'!$O$24 -> 0 | Q32: N | R32: =IF(L32="",AKHIR-J32,L32-J32+1) -> 1.0416667 | S32: =WORKDAY(J32,6,AKHIR) -> 46127 | T32: 0 | U32: =IF(Q32="N",0,M32*T32) -> 0 | V32: DONE DO THE USER TRAINING FOR SIMULATOR MULTIPARAMETER
A33: 10 | B33: IKN400016 | C33: =VLOOKUP(B33,[13]AssetDetails_UEM!$A$3:$AH$1849,6,FALSE) -> Infusion Pumps, General-Purpose | D33: =VLOOKUP(B33,[13]AssetDetails_UEM!$A$3:$AK$1849,22,FALSE) -> 10825 | E33: IKNWIBE26006559 | F33: 01AE119 | G33: USER TRAINING FOR INFUSION PUMPS, SYRINGE | H33: User Training | I33: 0 days, 0 hrs, 05 mins | J33: 07-Apr-2026 09:30:00 | K33: 46119.399 | L33: 46119.438 | M33: =IF(D33>44999.99,100,ROUNDUP((D33/4999.99)*10,-1)) -> 30 | N33: N | O33: ='[14]B1& B2 UNSCHEDULED'!$O$24 -> 0 | Q33: N | R33: 7 | S33: =WORKDAY(J33,6,AKHIR) -> 46127 | T33: 0 | U33: =IF(Q33="N",0,M33*T33) -> 0 | V33: DONE DO THE USER TRAINING FOR INFUSION PUMPS, SYRINGE
A34: 11 | B34: IKN400741 | C34: =VLOOKUP(B34,[13]AssetDetails_UEM!$A$3:$AH$1849,6,FALSE) -> Analyzers, Laboratory, Microbiology, Blood Culture, Automate | D34: =VLOOKUP(B34,[13]AssetDetails_UEM!$A$3:$AK$1849,22,FALSE) -> 342820 | E34: IKNWIBE26006562 | F34: 04LA126 | G34: LOW THERMOMETER BATTERY | H34: Normal | I34: 0 days, 0 hrs, 13 mins | J34: 07-Apr-2026 09:17:00 | K34: 07-Apr-2026 09:30:00 | L34: 07-Apr-2026 10:30:00 | M34: =IF(D34>44999.99,100,ROUNDUP((D34/4999.99)*10,-1)) -> 100 | N34: N | O34: ='[14]B1& B2 UNSCHEDULED'!$O$24 -> 0 | Q34: N | R34: =IF(L34="",AKHIR-J34,L34-J34+1) -> 1.0506944 | S34: =WORKDAY(J34,6,AKHIR) -> 46127 | T34: 0 | U34: =IF(Q34="N",0,M34*T34) -> 0 | V34: M-REPLACE LR41H ALKALINE BUTTON CELL BATTERY
A35: 12 | B35: IKN400224 | C35: =VLOOKUP(B35,[13]AssetDetails_UEM!$A$3:$AH$1849,6,FALSE) -> Infusion Pumps, Syringe | D35: =VLOOKUP(B35,[13]AssetDetails_UEM!$A$3:$AK$1849,22,FALSE) -> 10225 | E35: IKNWIBE26006570 | F35: 09WJ201 | G35: USER TRAINING FOR INFUSION PUMPS, SYRINGE | H35: User Training | I35: 0 days, 0 hrs, 06 mins | J35: 07-Apr-2026 14:30:00 | K35: 46119.608 | L35: 46119.65 | M35: =IF(D35>44999.99,100,ROUNDUP((D35/4999.99)*10,-1)) -> 30 | N35: N | O35: ='[14]B1& B2 UNSCHEDULED'!$O$24 -> 0 | Q35: N | R35: =IF(L35="",AKHIR-J35,L35-J35+1) -> 1.0458333 | S35: =WORKDAY(J35,6,AKHIR) -> 46127 | T35: 0 | U35: =IF(Q35="N",0,M35*T35) -> 0 | V35: DONE DO THE USER TRAINING FOR INFUSION PUMPS, SYRINGE
A36: 13 | B36: IKN400298 | C36: =VLOOKUP(B36,[13]AssetDetails_UEM!$A$3:$AH$1849,6,FALSE) -> Mattress Systems, Alternating-Pressure | D36: =VLOOKUP(B36,[13]AssetDetails_UEM!$A$3:$AK$1849,22,FALSE) -> 28630 | E36: IKNWIBE26006629 | F36: 08WH121 | G36: RIPPLE MATTRESS CONNECTOR ROSAK - WAD 8B | H36: Normal | I36: 0 days, 0 hrs, 55 mins | J36: 08-Apr-2026 07:05:00 | K36: 08-Apr-2026 08:00:00 | L36: 08-Apr-2026 09:30:00 | M36: =IF(D36>44999.99,100,ROUNDUP((D36/4999.99)*10,-1)) -> 60 | N36: N | O36: ='[14]B1& B2 UNSCHEDULED'!$O$24 -> 0 | Q36: N | R36: =IF(L36="",AKHIR-J36,L36-J36+1) -> 1.1006944 | S36: =WORKDAY(J36,6,AKHIR) -> 46128 | T36: 0 | U36: =IF(Q36="N",0,M36*T36) -> 0 | V36: L- REPLACE NEW COVER HOSE TEST ON MATTRESS , MAKE SURE NO LEAKING , UNIT OKAY READY FOR USE
A37: 14 | B37: IKN400277 | C37: =VLOOKUP(B37,[13]AssetDetails_UEM!$A$3:$AH$1849,6,FALSE) -> Electrocardiographs, Multichannel, Interpretative | D37: =VLOOKUP(B37,[13]AssetDetails_UEM!$A$3:$AK$1849,22,FALSE) -> 25260 | E37: IKNWIBE26006637 | F37: 08WH107 | G37: MESIN ECG BACAAN GRAF TIDAK KELUAR - 8B ARAS 8 | H37: Normal | I37: 0 days, 0 hrs, 52 mins | J37: 08-Apr-2026 10:08:00 | K37: 08-Apr-2026 11:00:00 | L37: 09-Apr-2026 18:50:00 | M37: =IF(D37>44999.99,100,ROUNDUP((D37/4999.99)*10,-1)) -> 60 | N37: N | O37: ='[14]B1& B2 UNSCHEDULED'!$O$24 -> 0 | Q37: N | R37: =IF(L37="",AKHIR-J37,L37-J37+1) -> 2.3625 | S37: =WORKDAY(J37,6,AKHIR) -> 46128 | T37: 0 | U37: =IF(Q37="N",0,M37*T37) -> 0 | V37: L, QE:12-CHANGE UNIT 2 HOUR DO PERFORMANCE TEST UNTIL CLEAN ECG , IT FULLY DETECT AND SHOW FULL GRAPH , UNIT READY FOR USE
A38: 15 | B38: IKN400300 | C38: =VLOOKUP(B38,[13]AssetDetails_UEM!$A$3:$AH$1849,6,FALSE) -> Mattress Systems, Alternating-Pressure | D38: =VLOOKUP(B38,[13]AssetDetails_UEM!$A$3:$AK$1849,22,FALSE) -> 28630 | E38: IKNWIBE26006648 | F38: 08WH121 | G38: TUBING ROSAK | H38: Normal | I38: 0 days, 0 hrs, 47 mins | J38: 08-Apr-2026 16:53:00 | K38: 46120.736 | L38: 08-Apr-2026 18:40:00 | M38: =IF(D38>44999.99,100,ROUNDUP((D38/4999.99)*10,-1)) -> 60 | N38: N | O38: ='[14]B1& B2 UNSCHEDULED'!$O$24 -> 0 | Q38: N | R38: =IF(L38="",AKHIR-J38,L38-J38+1) -> 1.0743056 | S38: =WORKDAY(J38,6,AKHIR) -> 46128 | T38: 0 | U38: =IF(Q38="N",0,M38*T38) -> 0 | V38: L, QE:12-REPLACE NEW COVER HOSE, TEST ON MATTRESS, MAKE SURE NO LELAKING , UNIT OKAY READY FOR USE
A39: 16 | B39: IKN400956 | C39: =VLOOKUP(B39,[13]AssetDetails_UEM!$A$3:$AH$1849,6,FALSE) -> Linear Accelerators | D39: =VLOOKUP(B39,[13]AssetDetails_UEM!$A$3:$AK$1849,22,FALSE) -> 21961900 | E39: IKNWIBE26006701 | F39: 01RT172 | G39: MLC ERROR INTERMITTEN | H39: Normal | I39: 0 days, 0 hrs, 35 mins | J39: 09-Apr-2026 08:15:00 | K39: 46121.368 | L39: 46121.438 | M39: =IF(D39>44999.99,100,ROUNDUP((D39/4999.99)*10,-1)) -> 100 | N39: N | O39: ='[14]B1& B2 UNSCHEDULED'!$O$24 -> 0 | Q39: N | R39: =IF(L39="",AKHIR-J39,L39-J39+1) -> 1.09375 | S39: =WORKDAY(J39,6,AKHIR) -> 46129 | T39: 0 | U39: =IF(Q39="N",0,M39*T39) -> 0 | V39: BE SIDE LEAF STUCK, REPLACE HALF HD MOTOR FOR SIDE B LEAF
A40: 17 | B40: IKN400442 | C40: =VLOOKUP(B40,[13]AssetDetails_UEM!$A$3:$AH$1849,6,FALSE) -> Infusion Pumps, Syringe | D40: =VLOOKUP(B40,[13]AssetDetails_UEM!$A$3:$AK$1849,22,FALSE) -> 10225 | E40: IKNWIBE26006714 | F40: 06WC113 | G40: USER TRAINING FOR INFUSION PUMPS, SYRINGE | H40: User Training | I40: 0 days, 0 hrs, 06 mins | J40: 09-Apr-2026 14:30:00 | K40: 46121.608 | L40: 46121.65 | M40: =IF(D40>44999.99,100,ROUNDUP((D40/4999.99)*10,-1)) -> 30 | N40: N | O40: ='[14]B1& B2 UNSCHEDULED'!$O$24 -> 0 | Q40: N | R40: =IF(L40="",AKHIR-J40,L40-J40+1) -> 1.0458333 | S40: =WORKDAY(J40,6,AKHIR) -> 46129 | T40: 0 | U40: =IF(Q40="N",0,M40*T40) -> 0 | V40: DONE DO THE USER TRAINING FOR INFUSION PUMPS, SYRINGE
A41: 18 | B41: IKN400605 | C41: =VLOOKUP(B41,[13]AssetDetails_UEM!$A$3:$AH$1849,6,FALSE) -> Infusion Pumps, General-Purpose | D41: =VLOOKUP(B41,[13]AssetDetails_UEM!$A$3:$AK$1849,22,FALSE) -> 10825 | E41: IKNWIBE26006717 | F41: 04DO111 | G41: CHARGER FAULTY | H41: Normal | I41: 0 days, 0 hrs, 31 mins | J41: 09-Apr-2026 15:29:00 | K41: 09-Apr-2026 16:00:00 | L41: 09-Apr-2026 16:30:00 | M41: =IF(D41>44999.99,100,ROUNDUP((D41/4999.99)*10,-1)) -> 30 | N41: N | O41: ='[14]B1& B2 UNSCHEDULED'!$O$24 -> 0 | Q41: N | R41: =IF(L41="",AKHIR-J41,L41-J41+1) -> 1.0423611 | S41: =WORKDAY(J41,6,AKHIR) -> 46129 | T41: 0 | U41: =IF(Q41="N",0,M41*T41) -> 0 | V41: M-REPLACE ANOTHER CHARGER
A42: 19 | B42: IKN400300 | C42: =VLOOKUP(B42,[13]AssetDetails_UEM!$A$3:$AH$1849,6,FALSE) -> Mattress Systems, Alternating-Pressure | D42: =VLOOKUP(B42,[13]AssetDetails_UEM!$A$3:$AK$1849,22,FALSE) -> 28630 | E42: IKNWIBE26006804 | F42: 08WH121 | G42: CONNECTOR RIPPLE MATTRESS ROSAK | H42: Normal | I42: 0 days, 0 hrs, 31 mins | J42: 10-Apr-2026 18:59:00 | K42: 10-Apr-2026 19:30:00 | L42: 13-Apr-2026 15:00:00 | M42: =IF(D42>44999.99,100,ROUNDUP((D42/4999.99)*10,-1)) -> 60 | N42: N | O42: ='[14]B1& B2 UNSCHEDULED'!$O$24 -> 0 | Q42: N | R42: =IF(L42="",AKHIR-J42,L42-J42+1) -> 3.8340278 | S42: =WORKDAY(J42,6,AKHIR) -> 46132 | T42: 0 | U42: =IF(Q42="N",0,M42*T42) -> 0 | V42: L, QE:12-REPLACE NOW COVER HOSE, TEST ON MATTRESS MAKE SURE NO LEAKING ,UNIT FUNCTIONING OKAY READY FOR USE
A43: 20 | B43: IKN400300 | C43: =VLOOKUP(B43,[13]AssetDetails_UEM!$A$3:$AH$1849,6,FALSE) -> Mattress Systems, Alternating-Pressure | D43: =VLOOKUP(B43,[13]AssetDetails_UEM!$A$3:$AK$1849,22,FALSE) -> 28630 | E43: IKNWIBE26006824 | F43: 08WH121 | G43: BUTTON TRANSPORT RIPPLE MATTRESS TERCABUT | H43: Normal | I43: 0 days, 0 hrs, 9 mins | J43: 12-Apr-2026 00:51:00 | K43: 12-Apr-2026 01:00:00 | L43: 13-Apr-2026 17:00:00 | M43: =IF(D43>44999.99,100,ROUNDUP((D43/4999.99)*10,-1)) -> 60 | N43: N | O43: ='[14]B1& B2 UNSCHEDULED'!$O$24 -> 0 | Q43: N | R43: =IF(L43="",AKHIR-J43,L43-J43+1) -> 2.6729167 | S43: =WORKDAY(J43,6,AKHIR) -> 46132 | T43: 0 | U43: =IF(Q43="N",0,M43*T43) -> 0 | V43: L, QE:12-BUTTON TRANSPORT RIPPLE MATTRESS INSTALL BUTTON, MAKE SURE FIT TO USE, TEST UNIT OKAY
A44: 21 | B44: IKN400967 | C44: =VLOOKUP(B44,[13]AssetDetails_UEM!$A$3:$AH$1849,6,FALSE) -> Linear Accelerators | D44: =VLOOKUP(B44,[13]AssetDetails_UEM!$A$3:$AK$1849,22,FALSE) -> 12049370 | E44: IKNWIBE26006881 | F44: 01RT165 | G44: LINAC VACUUM TARGET DROP | H44: Normal | I44: 0 days, 0 hrs, 08 mins | J44: 13-Apr-2026 08:22:00 | K44: 46125.354 | L44: 46125.396 | M44: =IF(D44>44999.99,100,ROUNDUP((D44/4999.99)*10,-1)) -> 100 | N44: N | O44: ='[14]B1& B2 UNSCHEDULED'!$O$24 -> 0 | Q44: N | R44: =IF(L44="",AKHIR-J44,L44-J44+1) -> 1.0472222 | S44: =WORKDAY(J44,6,AKHIR) -> 46133 | T44: 0 | U44: =IF(Q44="N",0,M44*T44) -> 0 | V44: RESET VACUUM BREAKER AND LET HOLD FOR 10 MINUTES. UNIT RETURN TO NORMAL CONDITION AND TESTED PASS.
A45: 22 | B45: IKN400762 | C45: =VLOOKUP(B45,[13]AssetDetails_UEM!$A$3:$AH$1849,6,FALSE) -> Analyzers, Laboratory, Immunoassay, Chemiluminescent | D45: =VLOOKUP(B45,[13]AssetDetails_UEM!$A$3:$AK$1849,22,FALSE) -> 1443450 | E45: IKNWIBE26006887 | F45: 04LA133 | G45: MOTOR RUSTY MAKE NOUSY SOUND | H45: Normal | I45: 0 days, 0 hrs, 7 mins | J45: 13-Apr-2026 09:03:00 | K45: 13-Apr-2026 09:10:00 | L45: 13-Apr-2026 09:30:00 | M45: =IF(D45>44999.99,100,ROUNDUP((D45/4999.99)*10,-1)) -> 100 | N45: N | O45: ='[14]B1& B2 UNSCHEDULED'!$O$24 -> 0 | Q45: N | R45: =IF(L45="",AKHIR-J45,L45-J45+1) -> 1.01875 | S45: =WORKDAY(J45,6,AKHIR) -> 46133 | T45: 0 | U45: =IF(Q45="N",0,M45*T45) -> 0 | V45: M-CLEAN MOTOR WITH LUBRICATE , CLEAN IT
A46: 23 | B46: IKN400304 | C46: =VLOOKUP(B46,[13]AssetDetails_UEM!$A$3:$AH$1849,6,FALSE) -> Incubators, Laboratory, Thermocycling | D46: =VLOOKUP(B46,[13]AssetDetails_UEM!$A$3:$AK$1849,22,FALSE) -> 16240 | E46: IKNWIBE26006909 | F46: 04LA126 | G46: PASANG DATA LOGGER | H46: Normal | I46: 0 days, 1 hrs, 2 mins | J46: 13-Apr-2026 12:58:00 | K46: 13-Apr-2026 14:00:00 | L46: 13-Apr-2026 14:30:00 | M46: =IF(D46>44999.99,100,ROUNDUP((D46/4999.99)*10,-1)) -> 40 | N46: N | O46: ='[14]B1& B2 UNSCHEDULED'!$O$24 -> 0 | Q46: N | R46: =IF(L46="",AKHIR-J46,L46-J46+1) -> 1.0638889 | S46: =WORKDAY(J46,6,AKHIR) -> 46133 | T46: 0 | U46: =IF(Q46="N",0,M46*T46) -> 0 | V46: L, QE:12-INSTALL DATA LOGGER
A47: 24 | B47: IKN400741 | C47: =VLOOKUP(B47,[13]AssetDetails_UEM!$A$3:$AH$1849,6,FALSE) -> Analyzers, Laboratory, Microbiology, Blood Culture, Automate | D47: =VLOOKUP(B47,[13]AssetDetails_UEM!$A$3:$AK$1849,22,FALSE) -> 342820 | E47: IKNWIBE26006910 | F47: 04LA126 | G47: PASANG DATA LOGGER | H47: Normal | I47: 0 days, 0 hrs, 23 mins | J47: 13-Apr-2026 13:07:00 | K47: 13-Apr-2026 13:30:00 | L47: 13-Apr-2026 14:00:00 | M47: =IF(D47>44999.99,100,ROUNDUP((D47/4999.99)*10,-1)) -> 100 | N47: N | O47: ='[14]B1& B2 UNSCHEDULED'!$O$24 -> 0 | Q47: N | R47: =IF(L47="",AKHIR-J47,L47-J47+1) -> 1.0368056 | S47: =WORKDAY(J47,6,AKHIR) -> 46133 | T47: 0 | U47: =IF(Q47="N",0,M47*T47) -> 0 | V47: L, QE:12-INSTALL DATA LOGGER
A48: 25 | B48: IKN400736 | C48: =VLOOKUP(B48,[13]AssetDetails_UEM!$A$3:$AH$1849,6,FALSE) -> Incubators, Laboratory, Thermocycling | D48: =VLOOKUP(B48,[13]AssetDetails_UEM!$A$3:$AK$1849,22,FALSE) -> 16240 | E48: IKNWIBE26006911 | F48: 04LA126 | G48: PASANG DATA LOGGER | H48: Normal | I48: 0 days, 0 hrs, 4 mins | J48: 13-Apr-2026 13:11:00 | K48: 13-Apr-2026 13:15:00 | L48: 13-Apr-2026 13:45:00 | M48: =IF(D48>44999.99,100,ROUNDUP((D48/4999.99)*10,-1)) -> 40 | N48: N | O48: ='[14]B1& B2 UNSCHEDULED'!$O$24 -> 0 | Q48: N | R48: =IF(L48="",AKHIR-J48,L48-J48+1) -> 1.0236111 | S48: =WORKDAY(J48,6,AKHIR) -> 46133 | T48: 0 | U48: =IF(Q48="N",0,M48*T48) -> 0 | V48: L, QE:12-INSTALL DATA LOGGER
A49: 26 | B49: IKN400737 | C49: =VLOOKUP(B49,[13]AssetDetails_UEM!$A$3:$AH$1849,6,FALSE) -> Incubators, Laboratory, Thermocycling | D49: =VLOOKUP(B49,[13]AssetDetails_UEM!$A$3:$AK$1849,22,FALSE) -> 16240 | E49: IKNWIBE26006912 | F49: 04LA126 | G49: PASANG DATA LOGGER | H49: Normal | I49: 0 days, 1 hrs, 16 mins | J49: 13-Apr-2026 13:14:00 | K49: 13-Apr-2026 14:30:00 | L49: 13-Apr-2026 15:00:00 | M49: =IF(D49>44999.99,100,ROUNDUP((D49/4999.99)*10,-1)) -> 40 | N49: N | O49: ='[14]B1& B2 UNSCHEDULED'!$O$24 -> 0 | Q49: N | R49: =IF(L49="",AKHIR-J49,L49-J49+1) -> 1.0736111 | S49: =WORKDAY(J49,6,AKHIR) -> 46133 | T49: 0 | U49: =IF(Q49="N",0,M49*T49) -> 0 | V49: L, QE:12-INSTALL DATA LOGGER
A50: 27 | B50: IKN400919 | C50: =VLOOKUP(B50,[13]AssetDetails_UEM!$A$3:$AH$1849,6,FALSE) -> Sphygmomanometers, Electronic, Automatic | D50: =VLOOKUP(B50,[13]AssetDetails_UEM!$A$3:$AK$1849,22,FALSE) -> 4510 | E50: IKNWIBE26006975 | F50: 03MC108 | G50: PASANG DATA LOGGER | H50: Normal | I50: 0 days, 0 hrs, 18 mins | J50: 14-Apr-2026 08:42:00 | K50: 14-Apr-2026 09:00:00 | L50: 14-Apr-2026 09:20:00 | M50: =IF(D50>44999.99,100,ROUNDUP((D50/4999.99)*10,-1)) -> 10 | N50: N | O50: ='[14]B1& B2 UNSCHEDULED'!$O$24 -> 0 | Q50: N | R50: =IF(L50="",AKHIR-J50,L50-J50+1) -> 1.0263889 | S50: =WORKDAY(J50,6,AKHIR) -> 46134 | T50: 0 | U50: =IF(Q50="N",0,M50*T50) -> 0 | V50: L, QE:16- REPLACE CUFF , TESTTED OKAY AND FUNCTIONING
A51: 28 | B51: IKN402004 | C51: =VLOOKUP(B51,[13]AssetDetails_UEM!$A$3:$AH$1849,6,FALSE) -> Scanning Systems, Laser, Optical Tomography | D51: =VLOOKUP(B51,[13]AssetDetails_UEM!$A$3:$AK$1849,22,FALSE) -> 2185000 | E51: IKNWIBE26006977 | F51: 01RT172 | G51: SENTINEL PC HANG | H51: Normal | I51: 0 days, 0 hrs, 14 mins | J51: 14-Apr-2026 09:16:00 | K51: 46126.396 | L51: 46126.448 | M51: =IF(D51>44999.99,100,ROUNDUP((D51/4999.99)*10,-1)) -> 100 | N51: N | O51: ='[14]B1& B2 UNSCHEDULED'!$O$24 -> 0 | Q51: N | R51: =IF(L51="",AKHIR-J51,L51-J51+1) -> 1.0618056 | S51: =WORKDAY(J51,6,AKHIR) -> 46134 | T51: 0 | U51: =IF(Q51="N",0,M51*T51) -> 0 | V51: INACTIVATE THE PATIENT DATA SELECTED AND STORED/ARCHIVE TO EXTERNAL DISK. TESTED-PASS AND UNIT LEFT WITH GOOD WORKING CONDITION.
A52: 29 | B52: IKN400589 | C52: =VLOOKUP(B52,[13]AssetDetails_UEM!$A$3:$AH$1849,6,FALSE) -> Counters, Gamma | D52: =VLOOKUP(B52,[13]AssetDetails_UEM!$A$3:$AK$1849,22,FALSE) -> 144820 | E52: IKNWIBE26006985 | F52: 03NM154 | G52: GAMMA COUNTER SCREEN BLANK | H52: Normal | I52: 0 days, 0 hrs, 10 mins | J52: 14-Apr-2026 11:40:00 | K52: 14-Apr-2026 11:50:00 | L52: 14-Apr-2026 12:30:00 | M52: =IF(D52>44999.99,100,ROUNDUP((D52/4999.99)*10,-1)) -> 100 | N52: N | O52: ='[14]B1& B2 UNSCHEDULED'!$O$24 -> 0 | Q52: N | R52: =IF(L52="",AKHIR-J52,L52-J52+1) -> 1.0347222 | S52: =WORKDAY(J52,6,AKHIR) -> 46134 | T52: 0 | U52: =IF(Q52="N",0,M52*T52) -> 0 | V52: L, QE:12- RESET CABLE , RESET MADICINE , TESTED AND THE SCREEN FUNCTIONING AND IN GOOD CONDITION
A53: 30 | B53: IKN400347 | C53: =VLOOKUP(B53,[13]AssetDetails_UEM!$A$3:$AH$1849,6,FALSE) -> Physiologic Monitoring Systems, Acute Care | D53: =VLOOKUP(B53,[13]AssetDetails_UEM!$A$3:$AK$1849,22,FALSE) -> 44510 | E53: IKNWIBE26006997 | F53: 07WF121 | G53: WIRE CUFF MACHINE BP ROSAK | H53: Normal | I53: 0 days, 0 hrs, 31 mins | J53: 14-Apr-2026 13:59:00 | K53: 14-Apr-2026 14:30:00 | L53: 14-Apr-2026 15:15:00 | M53: =IF(D53>44999.99,100,ROUNDUP((D53/4999.99)*10,-1)) -> 90 | N53: N | O53: ='[14]B1& B2 UNSCHEDULED'!$O$24 -> 0 | Q53: N | R53: =IF(L53="",AKHIR-J53,L53-J53+1) -> 1.0527778 | S53: =WORKDAY(J53,6,AKHIR) -> 46134 | T53: 0 | U53: =IF(Q53="N",0,M53*T53) -> 0 | V53: L, QE:12- REPLACE NEW HOSE CONNECTOR, TESTED OKAY AND FUNCTION
A54: 31 | B54: IKN400956 | C54: =VLOOKUP(B54,[13]AssetDetails_UEM!$A$3:$AH$1849,6,FALSE) -> Linear Accelerators | D54: =VLOOKUP(B54,[13]AssetDetails_UEM!$A$3:$AK$1849,22,FALSE) -> 21961900 | E54: IKNWIBE26007061 | F54: 01RT172 | G54: MACHINE NOVALIS KELUAR ERROR 'UDR1','UDR2'. | H54: Normal | I54: 0 days, 0 hrs, 27 mins | J54: 15-Apr-2026 07:33:00 | K54: 46127.333 | L54: 46127.396 | M54: =IF(D54>44999.99,100,ROUNDUP((D54/4999.99)*10,-1)) -> 100 | N54: N | O54: ='[14]B1& B2 UNSCHEDULED'!$O$24 -> 0 | Q54: N | R54: =IF(L54="",AKHIR-J54,L54-J54+1) -> 1.08125 | S54: =WORKDAY(J54,6,AKHIR) -> 46135 | T54: 0 | U54: =IF(Q54="N",0,M54*T54) -> 0 | V54: UDR1' AND 'UDR2' INTERLOCK SHOW UP DURING ENERGIZE 100MU, 6MV. WARM-UP MACHINE LITTLE BIT MORE BECAUSE ITS TOO COLD. TESTED-PASS AND MACHINE LEFT WITH FULL FUNCTIONALITY.
A55: 32 | B55: IKN400762 | C55: =VLOOKUP(B55,[13]AssetDetails_UEM!$A$3:$AH$1849,6,FALSE) -> Analyzers, Laboratory, Immunoassay, Chemiluminescent | D55: =VLOOKUP(B55,[13]AssetDetails_UEM!$A$3:$AK$1849,22,FALSE) -> 1443450 | E55: IKNWIBE26007065 | F55: 04LA133 | G55: LEAKING | H55: Normal | I55: 0 days, 0 hrs, 30 mins | J55: 15-Apr-2026 08:30:00 | K55: 15-Apr-2026 09:00:00 | L55: 15-Apr-2026 10:00:00 | M55: =IF(D55>44999.99,100,ROUNDUP((D55/4999.99)*10,-1)) -> 100 | N55: N | O55: ='[14]B1& B2 UNSCHEDULED'!$O$24 -> 0 | Q55: N | R55: =IF(L55="",AKHIR-J55,L55-J55+1) -> 1.0625 | S55: =WORKDAY(J55,6,AKHIR) -> 46135 | T55: 0 | U55: =IF(Q55="N",0,M55*T55) -> 0 | V55: L, QE:12-CHECK LEAKING , TUBING -TEST FUNCTIONING OKAY
A56: 33 | B56: IKN401237 | C56: =VLOOKUP(B56,[13]AssetDetails_UEM!$A$3:$AH$1849,6,FALSE) -> Electrocardiographs, Multichannel, Interpretative | D56: =VLOOKUP(B56,[13]AssetDetails_UEM!$A$3:$AK$1849,22,FALSE) -> 5590.2 | E56: IKNWIBE26007067 | F56: 03NM108 | G56: MACHINE ECG NOT FUNCTION- KLINIK NUKLEAR ARAS 3 | H56: Normal | I56: 0 days, 0 hrs, 36 mins | J56: 15-Apr-2026 08:54:00 | K56: 15-Apr-2026 09:30:00 | L56: 15-Apr-2026 10:30:00 | M56: =IF(D56>44999.99,100,ROUNDUP((D56/4999.99)*10,-1)) -> 20 | N56: N | O56: ='[14]B1& B2 UNSCHEDULED'!$O$24 -> 0 | Q56: N | R56: =IF(L56="",AKHIR-J56,L56-J56+1) -> 1.0666667 | S56: =WORKDAY(J56,6,AKHIR) -> 46135 | T56: 0 | U56: =IF(Q56="N",0,M56*T56) -> 0 | V56: L, QE:12- CLEAN ECG LEAD DO TEST UNIT , GRAPH OKAY, PRINT SHOW NORMAL GRAPH , UNIT FIT TO USE, UNIT UNDER OBSERVATION
A57: 34 | B57: IKN401412 | C57: =VLOOKUP(B57,[13]AssetDetails_UEM!$A$3:$AH$1849,6,FALSE) -> Scales, Patient, Floor | D57: =VLOOKUP(B57,[13]AssetDetails_UEM!$A$3:$AK$1849,22,FALSE) -> 9380 | E57: IKNWIBE26007069 | F57: 08WG143 | G57: REQ-CALIBRATE SCALES- 8A | H57: Normal | I57: 0 days, 0 hrs, 38 mins | J57: 15-Apr-2026 09:22:00 | K57: 15-Apr-2026 10:00:00 | L57: 15-Apr-2026 11:00:00 | M57: =IF(D57>44999.99,100,ROUNDUP((D57/4999.99)*10,-1)) -> 20 | N57: N | O57: ='[14]B1& B2 UNSCHEDULED'!$O$24 -> 0 | Q57: N | R57: =IF(L57="",AKHIR-J57,L57-J57+1) -> 1.0680556 | S57: =WORKDAY(J57,6,AKHIR) -> 46135 | T57: 0 | U57: =IF(Q57="N",0,M57*T57) -> 0 | V57: L, QE:12-UNIT FOUND STARTING NUMBER 4 , RESET NUM 0.0 TECT WEIGHT 1.25KG OKAY , UNIT FIT TO USE
A58: 35 | B58: IKN400223 | C58: =VLOOKUP(B58,[13]AssetDetails_UEM!$A$3:$AH$1849,6,FALSE) -> Electrocardiographs, Multichannel, Interpretative | D58: =VLOOKUP(B58,[13]AssetDetails_UEM!$A$3:$AK$1849,22,FALSE) -> 25260 | E58: IKNWIBE26007089 | F58: 09WJ222 | G58: MACHINE ECG 'SCREEN MACHINE FAULTY'-9A | H58: Normal | I58: 0 days, 1 hrs, 20 mins | J58: 15-Apr-2026 14:10:00 | K58: 15-Apr-2026 15:30:00 | L58: 15-Apr-2026 16:30:00 | M58: =IF(D58>44999.99,100,ROUNDUP((D58/4999.99)*10,-1)) -> 60 | N58: N | O58: ='[14]B1& B2 UNSCHEDULED'!$O$24 -> 0 | Q58: N | R58: =IF(L58="",AKHIR-J58,L58-J58+1) -> 1.0972222 | S58: =WORKDAY(J58,6,AKHIR) -> 46135 | T58: 0 | U58: =IF(Q58="N",0,M58*T58) -> 0 | V58: L, QE:12-FOUND SCREEN NOT CLEAR HAS LINE AND DOT, BUT STILL FUNCTIONING, TRY TO REPAIR THE SCREEN TIGHTEN THE CABLE MAKE SURE IT WELL , TIGHT LINE ON SCREEN , SCREEN LESS AND UNIT FIT TO USE
A59: 36 | B59: IKN400973 | C59: =VLOOKUP(B59,[13]AssetDetails_UEM!$A$3:$AH$1849,6,FALSE) -> Scanning Systems, Computed Tomography | D59: =VLOOKUP(B59,[13]AssetDetails_UEM!$A$3:$AK$1849,22,FALSE) -> 3557530 | E59: IKNWIBE26007092 | F59: 01RT118 | G59: UPS FAILURE. | H59: Normal | I59: 0 days, 0 hrs, 02 mins | J59: 15-Apr-2026 16:13:00 | K59: 46127.677 | L59: 46127.719 | M59: =IF(D59>44999.99,100,ROUNDUP((D59/4999.99)*10,-1)) -> 100 | N59: N | O59: ='[14]B1& B2 UNSCHEDULED'!$O$24 -> 0 | Q59: Y | R59: =IF(L59="",AKHIR-J59,L59-J59+1) -> 1.0430556 | S59: 46111 | T59: 0 | U59: =IF(Q59="N",0,M59*T59) -> 0 | V59: UPS BATTERY DEPLETED. REPLACED WITH NEW UPS AND TESTED-PASS. UNIT LEFT IN GOOD WORKING CONDITION.
A60: 37 | B60: IKN400967 | C60: =VLOOKUP(B60,[13]AssetDetails_UEM!$A$3:$AH$1849,6,FALSE) -> Linear Accelerators | D60: =VLOOKUP(B60,[13]AssetDetails_UEM!$A$3:$AK$1849,22,FALSE) -> 12049370 | E60: IKNWIBE26007154 | F60: 01RT165 | G60: WATER TEMPERATURE HIGH | H60: Normal | I60: 0 days, 0 hrs, 09 mins | J60: 16-Apr-2026 08:21:00 | K60: 46128.354 | L60: 46128.385 | M60: =IF(D60>44999.99,100,ROUNDUP((D60/4999.99)*10,-1)) -> 100 | N60: N | O60: ='[14]B1& B2 UNSCHEDULED'!$O$24 -> 0 | Q60: N | R60: =IF(L60="",AKHIR-J60,L60-J60+1) -> 1.0375231 | S60: =WORKDAY(J60,6,AKHIR) -> 46136 | T60: 0 | U60: =IF(Q60="N",0,M60*T60) -> 0 | V60: CHILLER UNIT WATER VALVE STUCK. RESET CHILLER VALVE AND BACK TO NORMAL CONDITION. TESTED-PASS AND UNIT L;EFT IN FULLY FUNCTIONAL
A61: 38 | B61: IKN400199 | C61: =VLOOKUP(B61,[13]AssetDetails_UEM!$A$3:$AH$1849,6,FALSE) -> Mattress Systems, Alternating-Pressure | D61: =VLOOKUP(B61,[13]AssetDetails_UEM!$A$3:$AK$1849,22,FALSE) -> 28630 | E61: IKNWIBE26007155 | F61: 09WJ126 | G61: RIPPLE MATTRESS TIDAK KEMBANG-DI KATIL 7 9A | H61: Normal | I61: 0 days, 0 hrs, 29 mins | J61: 16-Apr-2026 08:31:00 | K61: 16-Apr-2026 09:00:00 | L61: 16-Apr-2026 10:30:00 | M61: =IF(D61>44999.99,100,ROUNDUP((D61/4999.99)*10,-1)) -> 60 | N61: N | O61: ='[14]B1& B2 UNSCHEDULED'!$O$24 -> 0 | Q61: N | R61: =IF(L61="",AKHIR-J61,L61-J61+1) -> 1.0826389 | S61: =WORKDAY(J61,6,AKHIR) -> 46136 | T61: 0 | U61: =IF(Q61="N",0,M61*T61) -> 0 | V61: L, QE:12-FOUND UNIT INFLATE WELL BUT NOT CONSTANT AND DEFLATED , INSPECT TUBING HAS LEAKING , TIGHTEN TUBING , MICHINE TEST OKAY MATTRESS INFLATE IN GOOD CONDITON UNTIL READY FOR USE
A62: 39 | B62: KKM/H/IKN/25/353 | C62: Linear Accelerators | D62: Rm 20,550.421.50 | E62: IKNWIBE26007169 | F62: 01RT183 | G62: CCHU ERROR | H62: Normal | I62: 0 days, 0 hrs, 04 mins | J62: 16-Apr-2026 12:56:00 | K62: 46128.542 | L62: 46128.583 | M62: =IF(D62>44999.99,100,ROUNDUP((D62/4999.99)*10,-1)) -> 100 | N62: N | O62: ='[14]B1& B2 UNSCHEDULED'!$O$24 -> 0 | Q62: N | R62: =IF(L62="",AKHIR-J62,L62-J62+1) -> 1.0444444 | S62: =WORKDAY(J62,6,AKHIR) -> 46136 | T62: 0 | U62: =IF(Q62="N",0,M62*T62) -> 0 | V62: LONGITUDIAL CABLE GLITCH FROM COUCH RAIL. REPLACED WITH NEW CABLE AND TESTED-PASS. UNIT LEFT IN GOOD WORKING CONDITION.
A63: 40 | B63: IKN400798 | C63: =VLOOKUP(B63,[13]AssetDetails_UEM!$A$3:$AH$1849,6,FALSE) -> Radiographic Systems, Digital | D63: =VLOOKUP(B63,[13]AssetDetails_UEM!$A$3:$AK$1849,22,FALSE) -> 1958605 | E63: IKNWIBE26007174 | F63: 03ID181 | G63: MACHINE XRAY HANG- RADIOLOGI ARAS 3 | H63: Normal | I63: 0 days, 0 hrs, 13 mins | J63: 16-Apr-2026 16:17:00 | K63: 16-Apr-2026 16:30:00 | L63: 16-Apr-2026 17:30:00 | M63: =IF(D63>44999.99,100,ROUNDUP((D63/4999.99)*10,-1)) -> 100 | N63: N | O63: ='[14]B1& B2 UNSCHEDULED'!$O$24 -> 0 | Q63: N | R63: =IF(L63="",AKHIR-J63,L63-J63+1) -> 1.0506944 | S63: =WORKDAY(J63,6,AKHIR) -> 46136 | T63: 0 | U63: =IF(Q63="N",0,M63*T63) -> 0 | V63: L, QE:12-RESTART MACHINE AND DELETE OLD PATIENT WORKLIST . RESTART, TESTED UNIT FUNCTIONING OKAY, SCANNING PATIENT SUCCESSFUL
A64: 41 | B64: IKN402093 | C64: =VLOOKUP(B64,[13]AssetDetails_UEM!$A$3:$AH$1849,6,FALSE) -> Infusion Pumps, General-Purpose | D64: =VLOOKUP(B64,[13]AssetDetails_UEM!$A$3:$AK$1849,22,FALSE) -> 3500 | E64: IKNWIBE26007177 | F64: 04DO119 | G64: INFUSION PUMP ROSAK | H64: Normal | I64: 0 days, 0 hrs, 40 mins | J64: 16-Apr-2026 16:55:00 | K64: 46128.733 | L64: 46128.771 | M64: =IF(D64>44999.99,100,ROUNDUP((D64/4999.99)*10,-1)) -> 10 | N64: N | O64: ='[14]B1& B2 UNSCHEDULED'!$O$24 -> 0 | Q64: N | R64: =IF(L64="",AKHIR-J64,L64-J64+1) -> 1.0659722 | S64: =WORKDAY(J64,6,AKHIR) -> 46136 | T64: 0 | U64: =IF(Q64="N",0,M64*T64) -> 0 | V64: UNIT TIMING OUT AND NOT TALLY. SET TIME RUN UNIT AND TESTED OK
A65: 42 | B65: IKN401713 | C65: =VLOOKUP(B65,[13]AssetDetails_UEM!$A$3:$AH$1849,6,FALSE) -> Infusion Pumps, General-Purpose | D65: =VLOOKUP(B65,[13]AssetDetails_UEM!$A$3:$AK$1849,22,FALSE) -> 5800 | E65: IKNWIBE26007230 | F65: 04DO111 | G65: CABLE DIRTY. SPLIT WITH BLOOD | H65: Normal | I65: 0 days, 0 hrs, 20 mins | J65: 17-Apr-2026 10:40:00 | K65: 17-Apr-2026 11:00:00 | L65: 17-Apr-2026 15:00:00 | M65: =IF(D65>44999.99,100,ROUNDUP((D65/4999.99)*10,-1)) -> 20 | N65: N | O65: ='[14]B1& B2 UNSCHEDULED'!$O$24 -> 0 | Q65: N | R65: =IF(L65="",AKHIR-J65,L65-J65+1) -> 1.1805556 | S65: =WORKDAY(J65,6,AKHIR) -> 46139 | T65: 0 | U65: =IF(Q65="N",0,M65*T65) -> 0 | V65: M-CLEAM RIBBON CABLE USING CONTACK LENS. TECT FUNCTIONING PAUSED.NEED TO CLEAN EACH TIME AFTER USUNG
A66: 43 | B66: IKN400494 | C66: =VLOOKUP(B66,[13]AssetDetails_UEM!$A$3:$AH$1849,6,FALSE) -> Sphygmomanometers, Electronic, Automatic | D66: =VLOOKUP(B66,[13]AssetDetails_UEM!$A$3:$AK$1849,22,FALSE) -> 4510 | E66: IKNWIBE26007265 | F66: 05WB143 | G66: NOT FUNCTIONING | H66: Normal | I66: 0 days, 1 hrs, 2 mins | J66: 19-Apr-2026 07:28:00 | K66: 19-Apr-2026 08:30:00 | L66: 19-Apr-2026 08:40:00 | M66: =IF(D66>44999.99,100,ROUNDUP((D66/4999.99)*10,-1)) -> 10 | N66: N | O66: ='[14]B1& B2 UNSCHEDULED'!$O$24 -> 0 | Q66: N | R66: =IF(L66="",AKHIR-J66,L66-J66+1) -> 1.05 | S66: =WORKDAY(J66,6,AKHIR) -> 46139 | T66: 0 | U66: =IF(Q66="N",0,M66*T66) -> 0 | V66: L, QE:12-REPLACED CUFFS, TESTED OKAY
A67: 44 | B67: KKM/H/IKN/25/353 | C67: LINAC Accelerators | D67: Rm 20,550.421.50 | E67: IKNWIBE26007334 | F67: 01RT183 | G67: LINAC 5 KELUAR BGM MODE | H67: Normal | I67: 0 days, 0 hrs, 15 mins | J67: 20-Apr-2026 08:10:00 | K67: 46132.344 | L67: 46132.375 | M67: =IF(D67>44999.99,100,ROUNDUP((D67/4999.99)*10,-1)) -> 100 | N67: N | O67: ='[14]B1& B2 UNSCHEDULED'!$O$24 -> 0 | Q67: N | R67: =IF(L67="",AKHIR-J67,L67-J67+1) -> 1.0347222 | S67: =WORKDAY(J67,6,AKHIR) -> 46140 | T67: 0 | U67: =IF(Q67="N",0,M67*T67) -> 0 | V67: REBOOT WHOLE SYSTEM AND SYSTEM BACK TO NORMAL CONDITIONS. UNIT LEFT WITH FULLY FUNCTIONAL.
A68: 45 | B68: IKN400967 | C68: =VLOOKUP(B68,[13]AssetDetails_UEM!$A$3:$AH$1849,6,FALSE) -> Linear Accelerators | D68: =VLOOKUP(B68,[13]AssetDetails_UEM!$A$3:$AK$1849,22,FALSE) -> 12049370 | E68: IKNWIBE26007336 | F68: 01RT165 | G68: LINAC 2, WATER PRESSURE LOW | H68: Normal | I68: 0 days, 0 hrs, 05 mins | J68: 20-Apr-2026 08:20:00 | K68: 46132.351 | L68: 46132.406 | M68: =IF(D68>44999.99,100,ROUNDUP((D68/4999.99)*10,-1)) -> 100 | N68: N | O68: ='[14]B1& B2 UNSCHEDULED'!$O$24 -> 0 | Q68: N | R68: =IF(L68="",AKHIR-J68,L68-J68+1) -> 1.0590278 | S68: =WORKDAY(J68,6,AKHIR) -> 46140 | T68: 0 | U68: =IF(Q68="N",0,M68*T68) -> 0 | V68: ADDING PRESSURE BACK TO NORMAL RANGE WHILE TRACING THE LEAKAGE. FOUND THAT EXPENSION VESSEL PRESSURE MALFUNCTION. REPLACED AND TESTED-PASS
A69: 46 | B69: IKN400755 | C69: =VLOOKUP(B69,[13]AssetDetails_UEM!$A$3:$AH$1849,6,FALSE) -> Analyzers, Laboratory, Hematology, Coagulation, Automated | D69: =VLOOKUP(B69,[13]AssetDetails_UEM!$A$3:$AK$1849,22,FALSE) -> 105860 | E69: IKNWIBE26007338 | F69: 04LA132 | G69: ROTOR NOT AUTO PICKUP DUE REM NOT ENABLE | H69: Normal | I69: 0 days, 0 hrs, 13 mins | J69: 20-Apr-2026 09:17:00 | K69: 20-Apr-2026 09:30:00 | L69: 20-Apr-2026 09:45:00 | M69: =IF(D69>44999.99,100,ROUNDUP((D69/4999.99)*10,-1)) -> 100 | N69: N | O69: ='[14]B1& B2 UNSCHEDULED'!$O$24 -> 0 | Q69: N | R69: =IF(L69="",AKHIR-J69,L69-J69+1) -> 1.0194444 | S69: =WORKDAY(J69,6,AKHIR) -> 46140 | T69: 0 | U69: =IF(Q69="N",0,M69*T69) -> 0 | V69: L, QE:12- ENABLE REM OPTION. RUN TECT FUNCTIONING
A70: 47 | B70: IKN400956 | C70: =VLOOKUP(B70,[13]AssetDetails_UEM!$A$3:$AH$1849,6,FALSE) -> Linear Accelerators | D70: =VLOOKUP(B70,[13]AssetDetails_UEM!$A$3:$AK$1849,22,FALSE) -> 21961900 | E70: IKNWIBE26007345 | F70: 01RT172 | G70: NOVALIS COMUNICATION ERROR AUTO SHUTDOWN | H70: Normal | I70: 0 days, 0 hrs, 04 mins | J70: 20-Apr-2026 11:34:00 | K70: 46132.485 | L70: 46132.512 | M70: =IF(D70>44999.99,100,ROUNDUP((D70/4999.99)*10,-1)) -> 100 | N70: N | O70: ='[14]B1& B2 UNSCHEDULED'!$O$24 -> 0 | Q70: N | R70: =IF(L70="",AKHIR-J70,L70-J70+1) -> 1.0305556 | S70: =WORKDAY(J70,6,AKHIR) -> 46140 | T70: 0 | U70: =IF(Q70="N",0,M70*T70) -> 0 | V70: RESET AND REINITIALIZED WHOLE SYSTEM, ALL WORKING IN NORMAL CONDITION. NO INTERLOCKS SHOW UP AND TESTED-PASS. UNIT LEFT IN GOOD WORKING CONDITION.
A71: 48 | B71: IKN401713 | C71: =VLOOKUP(B71,[13]AssetDetails_UEM!$A$3:$AH$1849,6,FALSE) -> Infusion Pumps, General-Purpose | D71: =VLOOKUP(B71,[13]AssetDetails_UEM!$A$3:$AK$1849,22,FALSE) -> 5800 | E71: IKNWIBE26007351 | F71: 04DO111 | G71: KEYPAD NOT FUNCTIONING | H71: Normal | I71: 0 days, 0 hrs, 14 mins | J71: 20-Apr-2026 15:16:00 | K71: 20-Apr-2026 15:30:00 | L71: 22-Apr-2026 10:00:00 | M71: =IF(D71>44999.99,100,ROUNDUP((D71/4999.99)*10,-1)) -> 20 | N71: N | O71: ='[14]B1& B2 UNSCHEDULED'!$O$24 -> 0 | Q71: N | R71: =IF(L71="",AKHIR-J71,L71-J71+1) -> 2.7805556 | S71: =WORKDAY(J71,6,AKHIR) -> 46140 | T71: 0 | U71: =IF(Q71="N",0,M71*T71) -> 0 | V71: L, QE:12-CHANGE ANOTHER KEYPAD, TESTED FUNCTIONING PASSED
A72: 49 | B72: IKN400967 | C72: =VLOOKUP(B72,[13]AssetDetails_UEM!$A$3:$AH$1849,6,FALSE) -> Linear Accelerators | D72: =VLOOKUP(B72,[13]AssetDetails_UEM!$A$3:$AK$1849,22,FALSE) -> 12049370 | E72: IKNWIBE26007412 | F72: 01RT165 | G72: BACAAN VACUUM DROP | H72: Normal | I72: 0 days, 0 hrs, 06 mins | J72: 21-Apr-2026 08:14:00 | K72: 46133.347 | L72: 46133.385 | M72: =IF(D72>44999.99,100,ROUNDUP((D72/4999.99)*10,-1)) -> 100 | N72: N | O72: ='[14]B1& B2 UNSCHEDULED'!$O$24 -> 0 | Q72: N | R72: =IF(L72="",AKHIR-J72,L72-J72+1) -> 1.0423611 | S72: =WORKDAY(J72,6,AKHIR) -> 46141 | T72: 0 | U72: =IF(Q72="N",0,M72*T72) -> 0 | V72: RESTART VACUUM FROM ISOLATOR AND WAIT UNTIL 10 MINUTES TO TURN ON AGAIN. TESTED-PASS AND VACUUM VALUE SUSTAIN. UNIT LEFT IN GOOD WORKING CONDITION.
A73: 50 | B73: IKN402166 | C73: =VLOOKUP(B73,[13]AssetDetails_UEM!$A$3:$AH$1849,6,FALSE) -> Mattress Systems, Alternating-Pressure | D73: =VLOOKUP(B73,[13]AssetDetails_UEM!$A$3:$AK$1849,22,FALSE) -> 4000 | E73: IKNWIBE26007474 | F73: 05WB149 | G73: RIPPLE MATTRESS NOT ABLE TO INFLATE WELL | H73: Normal | I73: 0 days, 0 hrs, 2 mins | J73: 21-Apr-2026 11:58:00 | K73: 21-Apr-2026 12:00:00 | L73: 21-Apr-2026 16:00:00 | M73: =IF(D73>44999.99,100,ROUNDUP((D73/4999.99)*10,-1)) -> 10 | N73: N | O73: ='[14]B1& B2 UNSCHEDULED'!$O$24 -> 0 | Q73: N | R73: =IF(L73="",AKHIR-J73,L73-J73+1) -> 1.1680556 | S73: =WORKDAY(J73,6,AKHIR) -> 46141 | T73: 0 | U73: =IF(Q73="N",0,M73*T73) -> 0 | V73: AN- RE-SEAT HOSE CONNECTOR, TESTED OKAY MONITOR FOR ONE DAY AND ABLE TO ONFLATE WELL
A74: 51 | B74: IKN400873 | C74: =VLOOKUP(B74,[13]AssetDetails_UEM!$A$3:$AH$1849,6,FALSE) -> Warming Units, Patient, Forced-Air | D74: =VLOOKUP(B74,[13]AssetDetails_UEM!$A$3:$AK$1849,22,FALSE) -> 4950 | E74: IKNWIBE26007478 | F74: 01RT172 | G74: WARMER TIDAK PANAS | H74: Normal | I74: 0 days, 0 hrs, 11 mins | J74: 21-Apr-2026 11:59:00 | K74: 46133.507 | L74: 46133.604 | M74: =IF(D74>44999.99,100,ROUNDUP((D74/4999.99)*10,-1)) -> 10 | N74: N | O74: ='[14]B1& B2 UNSCHEDULED'!$O$24 -> 0 | Q74: N | R74: =IF(L74="",AKHIR-J74,L74-J74+1) -> 1.1048611 | S74: =WORKDAY(J74,6,AKHIR) -> 46141 | T74: 0 | U74: =IF(Q74="N",0,M74*T74) -> 0 | V74: CLEAN AND RESIT HEATER CONNECTION. RECALIBRATED AND TESTED-PASS. UNIT RETURNED WITH FULL FUNCTIONALITY.
A75: 52 | B75: IKN400425 | C75: =VLOOKUP(B75,[13]AssetDetails_UEM!$A$3:$AH$1849,6,FALSE) -> Infusion Pumps, Syringe | D75: =VLOOKUP(B75,[13]AssetDetails_UEM!$A$3:$AK$1849,22,FALSE) -> 10225 | E75: IKNWIBE26007562 | F75: 06WD124 | G75: USER TRAINING FOR INFUSION PUMPS, SYRINGE | H75: User Training | I75: 0 days, 0 hrs, 10 mins | J75: 21-Apr-2026 14:30:00 | K75: 46133.611 | L75: 46133.653 | M75: =IF(D75>44999.99,100,ROUNDUP((D75/4999.99)*10,-1)) -> 30 | N75: N | O75: ='[14]B1& B2 UNSCHEDULED'!$O$24 -> 0 | Q75: N | R75: =IF(L75="",AKHIR-J75,L75-J75+1) -> 1.0486111 | S75: =WORKDAY(J75,6,AKHIR) -> 46141 | T75: 0 | U75: =IF(Q75="N",0,M75*T75) -> 0 | V75: DONE DO THE USER TRAINING FOR INFUSION PUMPS, SYRINGE
A76: 53 | B76: IKN401353 | C76: =VLOOKUP(B76,[13]AssetDetails_UEM!$A$3:$AH$1849,6,FALSE) -> Radiographic/Fluoroscopic Units, Mobile | D76: =VLOOKUP(B76,[13]AssetDetails_UEM!$A$3:$AK$1849,22,FALSE) -> 399000 | E76: IKNWIBE26007600 | F76: 05OT159 | G76: MACHINE CANNOT RUN TURN ON- | H76: Normal | I76: 0 days, 0 hrs, 10 mins | J76: 21-Apr-2026 12:45:00 | K76: 21-Apr-2026 12:55:00 | L76: 21-Apr-2026 21:50:00 | M76: =IF(D76>44999.99,100,ROUNDUP((D76/4999.99)*10,-1)) -> 100 | N76: N | O76: ='[14]B1& B2 UNSCHEDULED'!$O$24 -> 0 | Q76: N | R76: =IF(L76="",AKHIR-J76,L76-J76+1) -> 1.3784722 | S76: =WORKDAY(J76,6,AKHIR) -> 46141 | T76: 0 | U76: =IF(Q76="N",0,M76*T76) -> 0 | V76: L, QE:12-CONFIRM POWER FSUPPLY INTERRUPTED , TEAM FEMS SATTLE THE ISSUE , TESTED UNIT FUNCHTIONING OKAY , UNDER MONITORING
A77: 54 | B77: IKN400247 | C77: =VLOOKUP(B77,[13]AssetDetails_UEM!$A$3:$AH$1849,6,FALSE) -> Infusion Pumps, General-Purpose | D77: =VLOOKUP(B77,[13]AssetDetails_UEM!$A$3:$AK$1849,22,FALSE) -> 10825 | E77: IKNWIBE26007611 | F77: 08WG113 | G77: CHARGER INFUSION PUMP CANNOT FUNCTION | H77: Normal | I77: 0 days, 0 hrs, 22 mins | J77: 21-Apr-2026 17:58:00 | K77: 21-Apr-2026 18:20:00 | L77: 21-Apr-2026 18:40:00 | M77: =IF(D77>44999.99,100,ROUNDUP((D77/4999.99)*10,-1)) -> 30 | N77: N | O77: ='[14]B1& B2 UNSCHEDULED'!$O$24 -> 0 | Q77: N | R77: =IF(L77="",AKHIR-J77,L77-J77+1) -> 1.0291667 | S77: =WORKDAY(J77,6,AKHIR) -> 46141 | T77: 0 | U77: =IF(Q77="N",0,M77*T77) -> 0 | V77: L, QE:12- REPLACED POWER SUPPLY SP UK III , TESTED OKAY
A78: 55 | B78: KKM/H/IKN/25/353 | C78: Linear Accelerators | D78: Rm 20,550.421.50 | E78: IKNWIBE26007668 | F78: 01RT183 | G78: LINAC 5 SERVER OFFLINE | H78: Normal | I78: 0 days, 0 hrs, 07 mins | J78: 22-Apr-2026 08:02:00 | K78: 46134.341 | L78: 46134.403 | M78: =IF(D78>44999.99,100,ROUNDUP((D78/4999.99)*10,-1)) -> 100 | N78: N | O78: ='[14]B1& B2 UNSCHEDULED'!$O$24 -> 0 | Q78: N | R78: =IF(L78="",AKHIR-J78,L78-J78+1) -> 1.0680556 | S78: =WORKDAY(J78,6,AKHIR) -> 46143 | T78: 0 | U78: =IF(Q78="N",0,M78*T78) -> 0 | V78: NETWORK SWITCH FAULTY. REPLACED WITH NEW NETWORK SWITCH AND TESTED-PASS. UNIT LEFT IN FULL FUNCTIONALITY.
A79: 56 | B79: IKN401044 | C79: =VLOOKUP(B79,[13]AssetDetails_UEM!$A$3:$AH$1849,6,FALSE) -> Physiologic Monitoring Systems, Acute Care | D79: =VLOOKUP(B79,[13]AssetDetails_UEM!$A$3:$AK$1849,22,FALSE) -> 54100 | E79: IKNWIBE26007669 | F79: 05OT169 | G79: NOT FUNCTIONING | H79: Normal | I79: 0 days, 0 hrs, 10 mins | J79: 22-Apr-2026 09:20:00 | K79: 46134.396 | L79: 46135.417 | M79: =IF(D79>44999.99,100,ROUNDUP((D79/4999.99)*10,-1)) -> 100 | N79: N | O79: ='[14]B1& B2 UNSCHEDULED'!$O$24 -> 0 | Q79: N | R79: =IF(L79="",AKHIR-J79,L79-J79+1) -> 2.0277778 | S79: =WORKDAY(J79,6,AKHIR) -> 46143 | T79: 0 | U79: =IF(Q79="N",0,M79*T79) -> 0 | V79: RESET BATTERY AND TESTED GOOD FUNCTIONING.
A80: 57 | B80: IKN400475 | C80: Infusion Pumps, Syringe | D80: =VLOOKUP(B80,[13]AssetDetails_UEM!$A$3:$AK$1849,22,FALSE) -> 10225 | E80: IKNWIBE26007678 | F80: 08WG113 | G80: USER TRAINING FOR INFUSION PUMPS, SYRINGE | H80: User Training | I80: 0 days, 0 hrs, 20 mins | J80: 22-Apr-2026 14:30:00 | K80: 46134.618 | L80: 46134.66 | M80: =IF(D80>44999.99,100,ROUNDUP((D80/4999.99)*10,-1)) -> 30 | N80: N | O80: ='[14]B1& B2 UNSCHEDULED'!$O$24 -> 0 | Q80: N | R80: =IF(L80="",AKHIR-J80,L80-J80+1) -> 1.0555556 | S80: =WORKDAY(J80,6,AKHIR) -> 46143 | T80: 0 | U80: =IF(Q80="N",0,M80*T80) -> 0 | V80: DONE DO THE USER TRAINING FOR INFUSION PUMPS, SYRINGE
A81: 58 | B81: IKN400743 | C81: =VLOOKUP(B81,[13]AssetDetails_UEM!$A$3:$AH$1849,6,FALSE) -> Carbon Dioxide Monitors, Laboratory Incubator | D81: =VLOOKUP(B81,[13]AssetDetails_UEM!$A$3:$AK$1849,22,FALSE) -> 56180 | E81: IKNWIBE26007681 | F81: 04LA126 | G81: REQ- TUKAR CYLINDER GAS OXYGEN -UNIT MIKRO PATOLGI ARAS 4 | H81: Normal | I81: 0 days, 0 hrs, 04 mins | J81: 22-Apr-2026 15:36:00 | K81: 46134.653 | L81: 46134.667 | M81: =IF(D81>44999.99,100,ROUNDUP((D81/4999.99)*10,-1)) -> 100 | N81: N | O81: ='[14]B1& B2 UNSCHEDULED'!$O$24 -> 0 | Q81: N | R81: =IF(L81="",AKHIR-J81,L81-J81+1) -> 1.0166667 | S81: =WORKDAY(J81,6,AKHIR) -> 46143 | T81: 0 | U81: =IF(Q81="N",0,M81*T81) -> 0 | V81: REPLACE NEW TANK AND OK
A82: 59 | B82: IKN401246 | C82: =VLOOKUP(B82,[13]AssetDetails_UEM!$A$3:$AH$1849,6,FALSE) -> Computers, Radiotherapy Planning System | D82: =VLOOKUP(B82,[13]AssetDetails_UEM!$A$3:$AK$1849,22,FALSE) -> 2403940 | E82: IKNWIBE26007682 | F82: 01RT156 | G82: CM-MONACO MONTHLY CHECKING | H82: Corrective Maintenance (CM) | I82: 0 days, 0 hrs, 02 mins | J82: 22-Apr-2026 11:30:00 | K82: 46134.481 | L82: 46134.544 | M82: =IF(D82>44999.99,100,ROUNDUP((D82/4999.99)*10,-1)) -> 100 | N82: N | O82: ='[14]B1& B2 UNSCHEDULED'!$O$24 -> 0 | Q82: N | R82: =IF(L82="",AKHIR-J82,L82-J82+1) -> 1.0652778 | S82: =WORKDAY(J82,6,AKHIR) -> 46143 | T82: 0 | U82: =IF(Q82="N",0,M82*T82) -> 0 | V82: MONTHLY CHECKING FOR TPS MONACO.
A83: 60 | B83: IKN400774 | C83: =VLOOKUP(B83,[13]AssetDetails_UEM!$A$3:$AH$1849,6,FALSE) -> Scanning Systems, Computed Tomography | D83: =VLOOKUP(B83,[13]AssetDetails_UEM!$A$3:$AK$1849,22,FALSE) -> 4605710 | E83: IKNWIBE26007683 | F83: 03ID156 | G83: CM- Myrian Monthly checking | H83: Corrective Maintenance (CM) | I83: 0 days, 0 hrs, 15 mins | J83: 22-Apr-2026 11:30:00 | K83: 22-Apr-2026 11:45:00 | L83: 22-Apr-2026 13:10:00 | M83: =IF(D83>44999.99,100,ROUNDUP((D83/4999.99)*10,-1)) -> 100 | N83: N | O83: ='[14]B1& B2 UNSCHEDULED'!$O$24 -> 0 | Q83: N | R83: =IF(L83="",AKHIR-J83,L83-J83+1) -> 1.0694444 | S83: =WORKDAY(J83,6,AKHIR) -> 46143 | T83: 0 | U83: =IF(Q83="N",0,M83*T83) -> 0 | V83: L, QE:14- MYRIAN MONTHLY CHECKING COMPLETE BY VENDOR . TESTED OKAY
A84: 61 | B84: IKN400798 | C84: =VLOOKUP(B84,[13]AssetDetails_UEM!$A$3:$AH$1849,6,FALSE) -> Radiographic Systems, Digital | D84: =VLOOKUP(B84,[13]AssetDetails_UEM!$A$3:$AK$1849,22,FALSE) -> 1958605 | E84: IKNWIBE26007767 | F84: 03ID181 | G84: ONE OF DETECTOR CANNOT USE | H84: Normal | I84: 0 days, 0 hrs, 15 mins | J84: 23-Apr-2026 15:10:00 | K84: 23-Apr-2026 15:25:00 | L84: 24-Apr-2026 14:20:00 | M84: =IF(D84>44999.99,100,ROUNDUP((D84/4999.99)*10,-1)) -> 100 | N84: N | O84: ='[14]B1& B2 UNSCHEDULED'!$O$24 -> 0 | Q84: N | R84: =IF(L84="",AKHIR-J84,L84-J84+1) -> 1.9652778 | S84: =WORKDAY(J84,6,AKHIR) -> 46146 | T84: 0 | U84: =IF(Q84="N",0,M84*T84) -> 0 | V84: AN- VENDOR CALIBRATE THE DETECTOR, TESTED OKAY. QAP PASSED
A85: 62 | B85: IKN402261 | C85: ECG MACHINE | D85: 12700 | E85: IKNWIBE26007826 | F85: 01RT111 | G85: USER TRAINING FOR ECG MACHINE | H85: User Training | I85: 0 days, 0 hrs, 05 mins | J85: 24-Apr-2026 15:30:00 | K85: 46136.649 | L85: 46136.688 | M85: =IF(D85>44999.99,100,ROUNDUP((D85/4999.99)*10,-1)) -> 30 | N85: N | O85: ='[14]B1& B2 UNSCHEDULED'!$O$24 -> 0 | Q85: N | R85: =IF(L85="",AKHIR-J85,L85-J85+1) -> 1.0416667 | S85: =WORKDAY(J85,6,AKHIR) -> 46147 | T85: 0 | U85: =IF(Q85="N",0,M85*T85) -> 0 | V85: DONE DO THE USER TRAINING FOR ECG MACHINE
A86: 63 | B86: IKN400762 | C86: =VLOOKUP(B86,[13]AssetDetails_UEM!$A$3:$AH$1849,6,FALSE) -> Analyzers, Laboratory, Immunoassay, Chemiluminescent | D86: =VLOOKUP(B86,[13]AssetDetails_UEM!$A$3:$AK$1849,22,FALSE) -> 1443450 | E86: IKNWIBE26007835 | F86: 04LA133 | G86: USER REQUEST-CLEAN WASTE LINE | H86: Normal | I86: 0 days, 0 hrs, 10 mins | J86: 24-Apr-2026 17:30:00 | K86: 24-Apr-2026 17:40:00 | L86: 24-Apr-2026 18:40:00 | M86: =IF(D86>44999.99,100,ROUNDUP((D86/4999.99)*10,-1)) -> 100 | N86: N | O86: ='[14]B1& B2 UNSCHEDULED'!$O$24 -> 0 | Q86: N | R86: =IF(L86="",AKHIR-J86,L86-J86+1) -> 1.0486111 | S86: =WORKDAY(J86,6,AKHIR) -> 46147 | T86: 0 | U86: =IF(Q86="N",0,M86*T86) -> 0 | V86: L, QE:12-CLEAR, CLEAN WASTE LINE PREVENT BLOCKAGE
A87: 64 | B87: IKN400755 | C87: =VLOOKUP(B87,[13]AssetDetails_UEM!$A$3:$AH$1849,6,FALSE) -> Analyzers, Laboratory, Hematology, Coagulation, Automated | D87: =VLOOKUP(B87,[13]AssetDetails_UEM!$A$3:$AK$1849,22,FALSE) -> 105860 | E87: IKNWIBE26007883 | F87: 04LA132 | G87: MESIN ELITE PRO ERROR NO FLUSH -OPTIC ERROR PATOLOGI ARAS 4 | H87: Normal | I87: 0 days, 0 hrs, 9 mins | J87: 25-Apr-2026 10:21:00 | K87: 25-Apr-2026 10:30:00 | L87: 27-Apr-2026 11:25:00 | M87: =IF(D87>44999.99,100,ROUNDUP((D87/4999.99)*10,-1)) -> 100 | N87: N | O87: ='[14]B1& B2 UNSCHEDULED'!$O$24 -> 0 | Q87: N | R87: =IF(L87="",AKHIR-J87,L87-J87+1) -> 3.0444444 | S87: =WORKDAY(J87,6,AKHIR) -> 46147 | T87: 0 | U87: =IF(Q87="N",0,M87*T87) -> 0 | V87: L, QE:12-ADJUST THE SAMPLE PROBE, ALLIGN , PROBE WITH SPECIAL TOOLS
A88: 65 | B88: IKN400305 | C88: =VLOOKUP(B88,[13]AssetDetails_UEM!$A$3:$AH$1849,6,FALSE) -> Sphygmomanometers, Electronic, Automatic | D88: =VLOOKUP(B88,[13]AssetDetails_UEM!$A$3:$AK$1849,22,FALSE) -> 4510 | E88: IKNWIBE26007888 | F88: 08WH143 | G88: RODA TAYAR MESIN BP PECAH/ROSAK - WAD 8B | H88: Normal | I88: 0 days, 0 hrs, 29 mins | J88: 26-Apr-2026 08:31:00 | K88: 26-Apr-2026 09:00:00 | L88: 28-Apr-2026 10:00:00 | M88: =IF(D88>44999.99,100,ROUNDUP((D88/4999.99)*10,-1)) -> 10 | N88: N | O88: ='[14]B1& B2 UNSCHEDULED'!$O$24 -> 0 | Q88: N | R88: =IF(L88="",AKHIR-J88,L88-J88+1) -> 3.0618056 | S88: =WORKDAY(J88,6,AKHIR) -> 46147 | T88: 0 | U88: =IF(Q88="N",0,M88*T88) -> 0 | V88: L, QE:12- REPLACE NEW TROLEY WHEEL , TEST PULL AND PUSH OK, NOT STUCK AT ALL, UNIT READY FOR USE
A89: 66 | B89: IKN400276 | C89: =VLOOKUP(B89,[13]AssetDetails_UEM!$A$3:$AH$1849,6,FALSE) -> Aspirators | D89: =VLOOKUP(B89,[13]AssetDetails_UEM!$A$3:$AK$1849,22,FALSE) -> 5052 | E89: IKNWIBE26007891 | F89: 08WH107 | G89: RODA MESIN PECAH - WAD 8B | H89: Normal | I89: 0 days, 0 hrs, 10 mins | J89: 26-Apr-2026 10:50:00 | K89: 26-Apr-2026 11:00:00 | L89: 26-Apr-2026 09:00:00 | M89: =IF(D89>44999.99,100,ROUNDUP((D89/4999.99)*10,-1)) -> 20 | N89: N | O89: ='[14]B1& B2 UNSCHEDULED'!$O$24 -> 0 | Q89: N | R89: =IF(L89="",AKHIR-J89,L89-J89+1) -> 0.92361111 | S89: =WORKDAY(J89,6,AKHIR) -> 46147 | T89: 0 | U89: =IF(Q89="N",0,M89*T89) -> 0 | V89: L, QE:16-REPLACE NEW TROLEY WHEEL , TEST PUSH AND PULL UNIT OK
A90: 67 | B90: IKN400766 | C90: =VLOOKUP(B90,[13]AssetDetails_UEM!$A$3:$AH$1849,6,FALSE) -> Radiographic Units, Mobile | D90: =VLOOKUP(B90,[13]AssetDetails_UEM!$A$3:$AK$1849,22,FALSE) -> 1149550 | E90: IKNWIBE26007892 | F90: 03ID106 | G90: REQUEST CHECK DETECTOR | H90: Normal | I90: 0 days, 0 hrs, 2 mins | J90: 26-Apr-2026 13:08:00 | K90: 26-Apr-2026 13:10:00 | L90: 27-Apr-2026 12:30:00 | M90: =IF(D90>44999.99,100,ROUNDUP((D90/4999.99)*10,-1)) -> 100 | N90: N | O90: ='[14]B1& B2 UNSCHEDULED'!$O$24 -> 0 | Q90: N | R90: =IF(L90="",AKHIR-J90,L90-J90+1) -> 1.9736111 | S90: =WORKDAY(J90,6,AKHIR) -> 46147 | T90: 0 | U90: =IF(Q90="N",0,M90*T90) -> 0 | V90: L, QE:7-VEBDOR PERFORMED DARK CALIBRATION AND XRAY CALIBRATION PASSED , IMAGE QUALITY OKAY , UNIT FUNCTIONING OKAY
A91: 68 | B91: IKN400967 | C91: =VLOOKUP(B91,[13]AssetDetails_UEM!$A$3:$AH$1849,6,FALSE) -> Linear Accelerators | D91: =VLOOKUP(B91,[13]AssetDetails_UEM!$A$3:$AK$1849,22,FALSE) -> 12049370 | E91: IKNWIBE26007943 | F91: 01RT165 | G91: LINAC 2 VACUUM TARGET DROP | H91: Normal | I91: 0 days, 0 hrs, 12 mins | J91: 27-Apr-2026 08:28:00 | K91: 46139.361 | L91: 46139.41 | M91: =IF(D91>44999.99,100,ROUNDUP((D91/4999.99)*10,-1)) -> 100 | N91: N | O91: ='[14]B1& B2 UNSCHEDULED'!$O$24 -> 0 | Q91: N | R91: =IF(L91="",AKHIR-J91,L91-J91+1) -> 1.0569444 | S91: =WORKDAY(J91,6,AKHIR) -> 46148 | T91: 0 | U91: =IF(Q91="N",0,M91*T91) -> 0 | V91: RECONDITIONING VACUUM AND RESET THROUGH ISOLATOR. TESTED-PASS AND UNIT LEFT IN GOOD WORKING CONDTION.
A92: 69 | B92: IKN401035 | C92: =VLOOKUP(B92,[13]AssetDetails_UEM!$A$3:$AH$1849,6,FALSE) -> Electrosurgical Units, Monopolar/Bipolar | D92: =VLOOKUP(B92,[13]AssetDetails_UEM!$A$3:$AK$1849,22,FALSE) -> 132310 | E92: IKNWIBE26007956 | F92: 05OT123 | G92: NOT FUNCTION | H92: Normal | I92: 0 days, 0 hrs, 23 mins | J92: 27-Apr-2026 10:52:00 | K92: 27-Apr-2026 11:15:00 | L92: 27-Apr-2026 16:00:00 | M92: =IF(D92>44999.99,100,ROUNDUP((D92/4999.99)*10,-1)) -> 100 | N92: N | O92: ='[14]B1& B2 UNSCHEDULED'!$O$24 -> 0 | Q92: N | R92: =IF(L92="",AKHIR-J92,L92-J92+1) -> 1.2138889 | S92: =WORKDAY(J92,6,AKHIR) -> 46148 | T92: 0 | U92: =IF(Q92="N",0,M92*T92) -> 0 | V92: L, QE:14-TESTED UNIT USING FSU ANALYZER, ALL MODE FUNCTIONING IN GOOD CONDITONG
A93: 70 | B93: IKN400530 | C93: =VLOOKUP(B93,[13]AssetDetails_UEM!$A$3:$AH$1849,6,FALSE) -> Aspirators | D93: =VLOOKUP(B93,[13]AssetDetails_UEM!$A$3:$AK$1849,22,FALSE) -> 2165 | E93: IKNWIBE26008145 | F93: 04PC109 | G93: SUCTION LOW PRESSURE | H93: Normal | I93: 0 days, 0 hrs, 5 mins | J93: 29-Apr-2026 10:30:00 | K93: 29-Apr-2026 10:35:00 | L93: 29-Apr-2026 11:30:00 | M93: =IF(D93>44999.99,100,ROUNDUP((D93/4999.99)*10,-1)) -> 10 | N93: N | O93: ='[14]B1& B2 UNSCHEDULED'!$O$24 -> 0 | Q93: N | R93: =IF(L93="",AKHIR-J93,L93-J93+1) -> 1.0416667 | S93: =WORKDAY(J93,6,AKHIR) -> 46150 | T93: 0 | U93: =IF(Q93="N",0,M93*T93) -> 0 | V93: L, QE:16-DONE PERFORMANCE CHECKING
A94: 71 | B94: IKN400956 | C94: =VLOOKUP(B94,[13]AssetDetails_UEM!$A$3:$AH$1849,6,FALSE) -> Linear Accelerators | D94: =VLOOKUP(B94,[13]AssetDetails_UEM!$A$3:$AK$1849,22,FALSE) -> 21961900 | E94: IKNWIBE26008151 | F94: 01RT172 | G94: NOVALIS MLC ERROR | H94: Normal | I94: 0 days, 1 hrs, 12 mins | J94: 29-Apr-2026 14:14:00 | K94: 46141.643 | L94: 46141.667 | M94: =IF(D94>44999.99,100,ROUNDUP((D94/4999.99)*10,-1)) -> 100 | N94: N | O94: ='[14]B1& B2 UNSCHEDULED'!$O$24 -> 0 | Q94: N | R94: =IF(L94="",AKHIR-J94,L94-J94+1) -> 1.0736111 | S94: =WORKDAY(J94,6,AKHIR) -> 46150 | T94: 0 | U94: =IF(Q94="N",0,M94*T94) -> 0 | V94: REINITIALISED AND CLEAN MLC. UNIT WERE TESTED-OK AND UNIT LEFT IN GOOD WORKING CONDITION.
A95: 72 | B95: IKN400004 | C95: =VLOOKUP(B95,[13]AssetDetails_UEM!$A$3:$AH$1849,6,FALSE) -> Electrocardiographs, Multichannel, Interpretative | D95: =VLOOKUP(B95,[13]AssetDetails_UEM!$A$3:$AK$1849,22,FALSE) -> 25260 | E95: IKNWIBE26008221 | F95: 01AE110 | G95: WIRE MACHINE ECG CANNOT DETECT | H95: Normal | I95: 0 days, 0 hrs, 06 mins | J95: 30-Apr-2026 10:49:00 | K95: 46142.455 | L95: 46142.5 | M95: =IF(D95>44999.99,100,ROUNDUP((D95/4999.99)*10,-1)) -> 60 | N95: N | O95: ='[14]B1& B2 UNSCHEDULED'!$O$24 -> 0 | Q95: N | R95: =IF(L95="",AKHIR-J95,L95-J95+1) -> 1.0493056 | S95: =WORKDAY(J95,6,AKHIR) -> 46150 | T95: 0 | U95: =IF(Q95="N",0,M95*T95) -> 0 | V95: REPLACED WITH NEW TRUNK AND LEAD CABLE, TESTED-PASS. UNIT LEFT IN FULL FUNCTIONALITY.
A96: 73 | B96: IKN400956 | C96: =VLOOKUP(B96,[13]AssetDetails_UEM!$A$3:$AH$1849,6,FALSE) -> Linear Accelerators | D96: =VLOOKUP(B96,[13]AssetDetails_UEM!$A$3:$AK$1849,22,FALSE) -> 21961900 | E96: IKNWIBE26008226 | F96: 01RT172 | G96: NOVALIS MLC PROBLEM | H96: Normal | I96: 0 days, 0 hrs, 13 mins | J96: 30-Apr-2026 15:47:00 | K96: 46142.667 | L96: 46142.708 | M96: =IF(D96>44999.99,100,ROUNDUP((D96/4999.99)*10,-1)) -> 100 | N96: N | O96: ='[14]B1& B2 UNSCHEDULED'!$O$24 -> 0 | Q96: N | R96: =IF(L96="",AKHIR-J96,L96-J96+1) -> 1.0506944 | S96: =WORKDAY(J96,6,AKHIR) -> 46150 | T96: 0 | U96: =IF(Q96="N",0,M96*T96) -> 0 | V96: SWAP BOTH SIDE MOTOR DRIVER AND HEAD TRANSCEIVER BOARD. REINITIALIZE MLC AND TESTED-OK. UNIT LEFT IN GOOD WORKING CONDITION.
A97: 74 | B97: IKN400215 | C97: =VLOOKUP(B97,[13]AssetDetails_UEM!$A$3:$AH$1849,6,FALSE) -> Sphygmomanometers, Electronic, Automatic | D97: =VLOOKUP(B97,[13]AssetDetails_UEM!$A$3:$AK$1849,22,FALSE) -> 4510 | E97: IKNWIBE26008236 | F97: 09WJ205 | G97: CM- BUTTON ON NOT FUNCTIONING | H97: Corrective Maintenance (CM) | I97: 0 days, 0 hrs, 30 mins | J97: 30-Apr-2026 14:00:00 | K97: 30-Apr-2026 14:30:00 | L97: 30-Apr-2026 18:40:00 | M97: =IF(D97>44999.99,100,ROUNDUP((D97/4999.99)*10,-1)) -> 10 | N97: N | O97: ='[14]B1& B2 UNSCHEDULED'!$O$24 -> 0 | Q97: N | R97: =IF(L97="",AKHIR-J97,L97-J97+1) -> 1.1944444 | S97: =WORKDAY(J97,6,AKHIR) -> 46150 | T97: 0 | U97: =IF(Q97="N",0,M97*T97) -> 0 | V97: L, QE:16-REPAIRS UNIT CLEAN WITH CONTACT CLEANER, TEST BUTTON OK PASSED UNIT READY TO USE
A98: Current Month (Work Order Open)
A99: 1 | B99: IKN400200 | C99: =VLOOKUP(B99,[13]AssetDetails_UEM!$A$3:$AH$1849,6,FALSE) -> Mattress Systems, Alternating-Pressure | D99: =VLOOKUP(B99,[13]AssetDetails_UEM!$A$3:$AK$1849,22,FALSE) -> 28630 | E99: IKNWIBE26006149 | F99: 09WJ126 | G99: MESIN RIPPLE MATTRESS ROSAK | H99: Normal | I99: 0 days, 0 hrs, 20 mins | J99: 46113.535 | K99: 46113.552 | L99: 46142.552 | M99: =IF(D99>44999.99,100,ROUNDUP((D99/4999.99)*10,-1)) -> 60 | N99: N | O99: ='[14]B1& B2 UNSCHEDULED'!$O$24 -> 0 | Q99: n | R99: =IF(L99="",AKHIR-J99,L99-J99+1) -> 30.017361 | S99: =WORKDAY(J99,6,AKHIR) -> 46121 | T99: 21 | U99: =IF(Q99="N",0,M99*T99) -> 0 | V99: PROB: DOUBLE COMPRESSOR ASSEMBLY FAULTY REQ QUO DATE : 6/4/2026 QUO DATE : 30/4/2026 PO: AWSB 72180. Loaner 9/4/26
A100: 2 | B100: IKN402139 | C100: =VLOOKUP(B100,[13]AssetDetails_UEM!$A$3:$AH$1849,6,FALSE) -> Bronchoscopes, Flexible | D100: =VLOOKUP(B100,[13]AssetDetails_UEM!$A$3:$AK$1849,22,FALSE) -> 58000 | E100: IKNWIBE26006568 | F100: 05IC115 | G100: ANGULATION NOT FUNCTIONING PROPERLY | H100: Normal | I100: 0 days, 0 hrs, 30 mins | J100: 46119.479 | K100: 46119.5 | L100: 46142.552 | M100: =IF(D100>44999.99,100,ROUNDUP((D100/4999.99)*10,-1)) -> 100 | N100: N | O100: ='[14]B1& B2 UNSCHEDULED'!$O$24 -> 0 | Q100: n | R100: =IF(L100="",AKHIR-J100,L100-J100+1) -> 24.072917 | S100: =WORKDAY(J100,6,AKHIR) -> 46127 | T100: 15 | U100: 0 | V100: PROB: ANGULATION PROBLEM DN : 7/4/2026 (DONE GIVE LOANER UNIT) STATUS : SEND TO VENDOR (HOSPIMETRIX SDN BHD) FOR FURTHER TROUBLESHOOT. | W100: Vendor Training
A101: 3 | B101: IKN400973 | C101: =VLOOKUP(B101,[13]AssetDetails_UEM!$A$3:$AH$1849,6,FALSE) -> Scanning Systems, Computed Tomography | D101: =VLOOKUP(B101,[13]AssetDetails_UEM!$A$3:$AK$1849,22,FALSE) -> 3557530 | E101: IKNWIBE26006779 | F101: 01RT118 | G101: LASER PUDAR BAHAGIAN KANAN | H101: Normal | I101: 0 days, 1 hrs, 03 mins | J101: 10-Apr-2026 09:57:00 | K101: 46122.458 | L101: 46142.552 | M101: =IF(D101>44999.99,100,ROUNDUP((D101/4999.99)*10,-1)) -> 100 | N101: N | O101: ='[14]B1& B2 UNSCHEDULED'!$O$24 -> 0 | Q101: Y | R101: =IF(L101="",AKHIR-J101,L101-J101+1) -> 21.1375 | S101: =WORKDAY(J101,6,AKHIR) -> 46132 | T101: 4 | U101: =IF(Q101="N",0,M101*T101) -> 400 | V101: PROB: LASER MODULE FAULTY QUO DATE : 14/4/2026 FROM VENDOR DELTA PO DATE : 24/4/2026 (PO:AWSB-72348) ETA : END MAY 2026 | W101: date last 20 ke 24
A102: 4 | B102: IKN401261 | C102: =VLOOKUP(B102,[13]AssetDetails_UEM!$A$3:$AH$1849,6,FALSE) -> Mattress Systems, Alternating-Pressure | D102: =VLOOKUP(B102,[13]AssetDetails_UEM!$A$3:$AK$1849,22,FALSE) -> 28630 | E102: IKNWIBE26007972 | F102: 05WB113 | G102: MESIN RIPPLE MATTRESS KEMPIS | H102: Normal | I102: 0 days, 0 hrs, 37 mins | J102: 27-Apr-2026 19:00:00 | K102: 46139.817 | L102: 46142.552 | M102: =IF(D102>44999.99,100,ROUNDUP((D102/4999.99)*10,-1)) -> 60 | N102: N | O102: ='[14]B1& B2 UNSCHEDULED'!$O$24 -> 0 | Q102: N | R102: =IF(L102="",AKHIR-J102,L102-J102+1) -> 3.7604167 | S102: =WORKDAY(J102,6,AKHIR) -> 46148 | T102: 0 | U102: =IF(Q102="N",0,M102*T102) -> 0 | V102: PROB: SHUTTER VALVE FAULTY QUO DATE :Waiting Quot
A103: 5 | B103: IKN400762 | C103: =VLOOKUP(B103,[13]AssetDetails_UEM!$A$3:$AH$1849,6,FALSE) -> Analyzers, Laboratory, Immunoassay, Chemiluminescent | D103: =VLOOKUP(B103,[13]AssetDetails_UEM!$A$3:$AK$1849,22,FALSE) -> 1443450 | E103: IKNWIBE26006790 | F103: 04LA133 | G103: MESIN ARKITEK LEAKING PATOLOGI | H103: Normal | I103: 0 days, 0 hrs, 53 mins | J103: 10-Apr-2026 14:07:00 | K103: 46122.625 | L103: 46142.552 | M103: =IF(D103>44999.99,100,ROUNDUP((D103/4999.99)*10,-1)) -> 100 | N103: N | O103: ='[14]B1& B2 UNSCHEDULED'!$O$24 -> 0 | Q103: Y | R103: =IF(L103="",AKHIR-J103,L103-J103+1) -> 20.963889 | S103: =WORKDAY(J103,6,AKHIR) -> 46132 | T103: 10 | U103: 400 | V103: PROB: RO BOTTLE CRACK QUO DATE : 16/4/2026 (Q3121389) PO DATE : 24/4/2026 (AWSB-72351) ETA : Middle May 2026
A104: 6 | B104: IKN400565 | C104: =VLOOKUP(B104,[13]AssetDetails_UEM!$A$3:$AH$1849,6,FALSE) -> Physiologic Monitoring Systems, Stress Exercise | D104: =VLOOKUP(B104,[13]AssetDetails_UEM!$A$3:$AK$1849,22,FALSE) -> 138350 | E104: IKNWIBE26008075 | F104: 03NM155 | G104: ECG- CABLE NOT DETECT | H104: Normal | I104: 0 days, 0 hrs, 10 mins | J104: 28-Apr-2026 09:10:00 | K104: 46140.389 | M104: =IF(D104>44999.99,100,ROUNDUP((D104/4999.99)*10,-1)) -> 100 | N104: N | O104: ='[14]B1& B2 UNSCHEDULED'!$O$24 -> 0 | Q104: N | R104: 8 | S104: =WORKDAY(J104,6,AKHIR) -> 46149 | T104: 0 | U104: =IF(Q104="N",0,M104*T104) -> 0 | V104: PROB : ECG FAULTY QUO DATE : 28/4/2026 PO DATE : 5/5/2026 (AWSB-72179) STATUS : WAITING PARTS FROM VENDOR RICHONE ETA : Middle May 2026
A105: 7 | B105: IKN401353 | C105: =VLOOKUP(B105,[13]AssetDetails_UEM!$A$3:$AH$1849,6,FALSE) -> Radiographic/Fluoroscopic Units, Mobile | D105: =VLOOKUP(B105,[13]AssetDetails_UEM!$A$3:$AK$1849,22,FALSE) -> 399000 | E105: IKNWIBE26008078 | F105: 05OT159 | G105: MACHINE CANNOT SHOOT | H105: Normal | I105: 0 days, 0 hrs, 10 mins | J105: 28-Apr-2026 10:30:00 | K105: 46140.444 | L105: 46142.552 | M105: =IF(D105>44999.99,100,ROUNDUP((D105/4999.99)*10,-1)) -> 100 | N105: N | O105: ='[14]B1& B2 UNSCHEDULED'!$O$24 -> 0 | Q105: N | R105: =IF(L105="",AKHIR-J105,L105-J105+1) -> 3.1145833 | S105: =WORKDAY(J105,6,AKHIR) -> 46149 | T105: 0 | U105: =IF(Q105="N",0,M105*T105) -> 0 | V105: PROB : INVERTER ERROR Waiting Quot Part STATUS : STILL UNDER TROUBLESHOOTING BY SPECIALIST 29/4/26 VENDOR TITAN ON 6 &8/5/2026
A106: 8 | B106: IKN400758 | C106: =VLOOKUP(B106,[13]AssetDetails_UEM!$A$3:$AH$1849,6,FALSE) -> Analyzers, Laboratory, Urine, Automated | D106: =VLOOKUP(B106,[13]AssetDetails_UEM!$A$3:$AK$1849,22,FALSE) -> 36080 | E106: IKNWIBE26008154 | F106: 04LA132 | G106: MACHINE IRIS STRIP | H106: Normal | I106: 0 days, 0 hrs, 30 mins | J106: 46141.646 | K106: 46141.667 | L106: 46148.667 | M106: =IF(D106>44999.99,100,ROUNDUP((D106/4999.99)*10,-1)) -> 80 | N106: N | O106: ='[14]B1& B2 UNSCHEDULED'!$O$24 -> 0 | Q106: N | R106: 7 | S106: =WORKDAY(J106,6,AKHIR) -> 46150 | T106: 0 | U106: =IF(Q106="N",0,M106*T106) -> 0 | V106: STRIP CONVEYOR STUCK, DONE CLEAN THE MOTOR AND TESTED OK | W106: CLOSED, PREVIOUS BM
A107: 9 | B107: IKN401071 | C107: =VLOOKUP(B107,[13]AssetDetails_UEM!$A$3:$AH$1849,6,FALSE) -> Video Image Processors, Endoscopic | D107: =VLOOKUP(B107,[13]AssetDetails_UEM!$A$3:$AK$1849,22,FALSE) -> 80000 | E107: IKNWIBE26008234 | F107: 03MC108 | G107: RUSTED METAL ON THE TOWER SCOPE IS REQUESTED TO BE REPAINTED | H107: Normal | I107: 0 days, 0 hrs, 10 mins | J107: 30-Apr-2026 17:00:00 | K107: 46142.715 | L107: 01-May-2026 12:00:00 | M107: =IF(D107>44999.99,100,ROUNDUP((D107/4999.99)*10,-1)) -> 100 | N107: N | O107: ='[14]B1& B2 UNSCHEDULED'!$O$24 -> 0 | Q107: N | R107: =IF(L107="",AKHIR-J107,L107-J107+1) -> 1.7916667 | S107: =WORKDAY(J107,6,AKHIR) -> 46150 | T107: 0 | U107: =IF(Q107="N",0,M107*T107) -> 0 | V107: M-PAINT AS PER REQUESTED | W107: CLOSED, PREVIOUS BM
...

Sheet B3-SCHEDULED
A3: MINISTRY OF HEALTH
A4: Deduction Mapping Report Biomedical Engineering Maintenance Services (BEMS)
A5: INDICATOR B.3 SCHEDULED MAINTENANCE
A7: HOSPITAL NAME : | C7: INSTITUT KANSER NEGARA | H7: MONTH/YEAR : | J7: 46113
B9: STATE : | C9: WILAYAH PERSEKUTUAN PUTRAJAYA | G9: BEMS MONTHLY FEE (RM) @ 97.5% : | J9: =BEMSdar!E11 -> 1329813.2
B11: COMPANY : | C11: AMBANG WIRA SDN BHD | G11: FMS MONTHLY FEE (RM) @ 2.5% : | J11: =BEMSdar!E13 -> 34097.773
A13: Notes:
A14: 1) Deduction Ringgit Equivalent is based on Appendix 11 of the Agreement, Section B3 Key Deduction Indicators for BEMS
A15: 2) Deduction Value for Indicator B.3 is Deduction Ringgit Equivalent (per event)
A16: 3) Rescheduled Date is the final rescheduled date if there are multiple rescheduling
A17: 4) Display only asset affected by deduction
A19: No | B19: Asset No | C19: Asset Description | D19: Asset Purchase Price (RM) | E19: Work Order No. | F19: User Location | G19: Scheduled Start Date | H19: Maintenance Date | I19: Rescheduled Date | J19: Validate Status (Y/N) | K19: Deduction Ringgit Equivalent (RM) | L19: Indicator B.3
L20: Deduction Value (RM) | M20: Remarks/ Exemption
A21: Current Month (Closed)
A22: 1 | B22: IKN400174 | C22: Warming Units, Blood/Solution | D22: =VLOOKUP(B22,[13]AssetDetails_UEM!$A$3:$X$1848,22,FALSE) -> 4950 | E22: IKNWOBE26005092 | F22: 03ID156 | G22: 01-Apr-2026 00:00:00 | H22: 01-Apr-2026 15:30:00 | I22: NA | J22: N | K22: =ROUNDUP((D22/4999.99)*10,-1) -> 10 | L22: =IF(J22="N",0,K22) -> 0 | M22: L, QE:16-PPM COMPLETE AS PER CHECKLIST , UNIT TESTED OKAY
A23: 2 | B23: IKN400333 | C23: Infusion Pumps, General-Purpose | D23: =VLOOKUP(B23,[13]AssetDetails_UEM!$A$3:$X$1848,22,FALSE) -> 10825 | E23: IKNWOBE26005093 | F23: 07WF121 | G23: 46113 | H23: 46125.625 | I23: 46134 | J23: N | K23: =ROUNDUP((D23/4999.99)*10,-1) -> 30 | L23: =IF(J23="N",0,K23) -> 0 | M23: Rescheduled Unit in used Done on 13 Apr 2026
A24: 3 | B24: IKN400561 | C24: Centrifuges, Tabletop | D24: =VLOOKUP(B24,[13]AssetDetails_UEM!$A$3:$X$1848,22,FALSE) -> 24060 | E24: IKNWOBE26005094 | F24: 03NM154 | G24: 01-Apr-2026 00:00:00 | H24: 01-Apr-2026 14:00:00 | I24: NA | J24: N | K24: =ROUNDUP((D24/4999.99)*10,-1) -> 50 | L24: =IF(J24="N",0,K24) -> 0 | M24: L, QE:16-PPM COMPLETE AS PER CHECKLIST , UNIT TESTED OKAY
A25: 4 | B25: IKN400715 | C25: Centrifuges, Tabletop, Low-Speed, Nonrefrigerated, Blood Ban | D25: =VLOOKUP(B25,[13]AssetDetails_UEM!$A$3:$X$1848,22,FALSE) -> 5170 | E25: IKNWOBE26005095 | F25: 04LA140 | G25: 01-Apr-2026 00:00:00 | H25: 01-Apr-2026 15:00:00 | I25: NA | J25: N | K25: =ROUNDUP((D25/4999.99)*10,-1) -> 20 | L25: =IF(J25="N",0,K25) -> 0 | M25: M,QE:16-PPM DONE AS PER HEPPM CHECKLIST ATTACHED
A26: 5 | B26: IKN401016 | C26: Recorders, Tape, Video | D26: =VLOOKUP(B26,[13]AssetDetails_UEM!$A$3:$X$1848,22,FALSE) -> 20000 | E26: IKNWOBE26005096 | F26: 05OT167 | G26: 01-Apr-2026 00:00:00 | H26: 01-Apr-2026 09:00:00 | I26: NA | J26: N | K26: =ROUNDUP((D26/4999.99)*10,-1) -> 50 | L26: =IF(J26="N",0,K26) -> 0 | M26: L, QE:16-ROUTINE INSPECTION DONE AS PER CHECKLIST ATTACHED UNIT FUNCTIONING IN GOOD CONDITION
A27: 6 | B27: IKN401061 | C27: Stimulators, Electrical, Peripheral Nerve, Analgesic, Transc | D27: =VLOOKUP(B27,[13]AssetDetails_UEM!$A$3:$X$1848,22,FALSE) -> 6570 | E27: IKNWOBE26005097 | F27: 05OT123 | G27: 01-Apr-2026 00:00:00 | H27: 01-Apr-2026 09:30:00 | I27: NA | J27: N | K27: =ROUNDUP((D27/4999.99)*10,-1) -> 20 | L27: =IF(J27="N",0,K27) -> 0 | M27: L, QE:16-MAINTAINANCE DONE AS PER HEPPM CHECKLIST ATTACHED UNIT FUNCTIONING IN GOOD CONDITION
A28: 7 | B28: IKN401068 | C28: Aspirators | D28: =VLOOKUP(B28,[13]AssetDetails_UEM!$A$3:$X$1848,22,FALSE) -> 10705 | E28: IKNWOBE26005098 | F28: 05OT169 | G28: 01-Apr-2026 00:00:00 | H28: 01-Apr-2026 11:30:00 | I28: NA | J28: N | K28: =ROUNDUP((D28/4999.99)*10,-1) -> 30 | L28: =IF(J28="N",0,K28) -> 0 | M28: L, QE:16-MAINTAINANCE DONE AS PER HEPPM CHECKLIST ATTACHED UNIT FUNCTIONING IN GOOD CONDITION
A29: 8 | B29: IKN401097 | C29: Lights, Surgical | D29: =VLOOKUP(B29,[13]AssetDetails_UEM!$A$3:$X$1848,22,FALSE) -> 10585 | E29: IKNWOBE26005099 | F29: 05IC114 | G29: 01-Apr-2026 00:00:00 | H29: 01-Apr-2026 08:00:00 | I29: NA | J29: N | K29: =ROUNDUP((D29/4999.99)*10,-1) -> 30 | L29: =IF(J29="N",0,K29) -> 0 | M29: L, QE:16-MAINTAINANCE DONE AS PER HEPPM CHECKLIST ATTACHED UNIT FUNCTIONING IN GOOD CONDITION
A30: 9 | B30: IKN400449 | C30: Infusion Pumps, General-Purpose | D30: =VLOOKUP(B30,[13]AssetDetails_UEM!$A$3:$X$1848,22,FALSE) -> 10825 | E30: IKNWOBE26005100 | F30: 06WC113 | G30: 02-Apr-2026 00:00:00 | H30: 02-Apr-2026 14:00:00 | I30: NA | J30: N | K30: =ROUNDUP((D30/4999.99)*10,-1) -> 30 | L30: =IF(J30="N",0,K30) -> 0 | M30: L, QE:16-PPM DONE AS PERCHEKLIST
A31: 10 | B31: IKN400586 | C31: Oximeters, Pulse | D31: =VLOOKUP(B31,[13]AssetDetails_UEM!$A$3:$X$1848,22,FALSE) -> 11120 | E31: IKNWOBE26005101 | F31: 03NM108 | G31: 09-Apr-2026 00:00:00 | H31: 09-Apr-2026 14:00:00 | I31: NA | J31: N | K31: =ROUNDUP((D31/4999.99)*10,-1) -> 30 | L31: =IF(J31="N",0,K31) -> 0 | M31: L, QE:16-PPM COMPLETE AS PER CHECKLIST , UNIT TESTED OKAY
A32: 11 | B32: IKN400609 | C32: Balances, Electronic, Analytical | D32: =VLOOKUP(B32,[13]AssetDetails_UEM!$A$3:$X$1848,22,FALSE) -> 4000 | E32: IKNWOBE26005102 | F32: 04DO114 | G32: 02-Apr-2026 00:00:00 | H32: 02-Apr-2026 10:00:00 | I32: NA | J32: N | K32: =ROUNDUP((D32/4999.99)*10,-1) -> 10 | L32: =IF(J32="N",0,K32) -> 0 | M32: M,QE:16-PPM DONE AS PER VENDOR CHECKLIST ATTACHED
A33: 12 | B33: IKN400678 | C33: Aspirators | D33: =VLOOKUP(B33,[13]AssetDetails_UEM!$A$3:$X$1848,22,FALSE) -> 5052 | E33: IKNWOBE26005103 | F33: 04TC119 | G33: 02-Apr-2026 00:00:00 | H33: 02-Apr-2026 11:00:00 | I33: NA | J33: N | K33: =ROUNDUP((D33/4999.99)*10,-1) -> 20 | L33: =IF(J33="N",0,K33) -> 0 | M33: L, QE:16-PPM DONE AS PER HEPPM CHECKLIST ATTACHED
A34: 13 | B34: IKN400704 | C34: Centrifuges, Tabletop | D34: =VLOOKUP(B34,[13]AssetDetails_UEM!$A$3:$X$1848,22,FALSE) -> 24060 | E34: IKNWOBE26005104 | F34: 04LA137 | G34: 02-Apr-2026 00:00:00 | H34: 02-Apr-2026 18:30:00 | I34: NA | J34: N | K34: =ROUNDUP((D34/4999.99)*10,-1) -> 50 | L34: =IF(J34="N",0,K34) -> 0 | M34: M,QE:16-PPM DONE AS PER HEPPM CHECKLIST ATTACHED
A35: 14 | B35: IKN400708 | C35: Centrifuges, Tabletop | D35: =VLOOKUP(B35,[13]AssetDetails_UEM!$A$3:$X$1848,22,FALSE) -> 24060 | E35: IKNWOBE26005105 | F35: 04LA130 | G35: 02-Apr-2026 00:00:00 | H35: 02-Apr-2026 16:30:00 | I35: NA | J35: N | K35: =ROUNDUP((D35/4999.99)*10,-1) -> 50 | L35: =IF(J35="N",0,K35) -> 0 | M35: M,QE:16-PPM DONE AS PER HEPPM CHECKLIST ATTACHED
... A47: 26 | B47: IKN401510 | C47: Balances, Electronic | D47: =VLOOKUP(B47,[13]AssetDetails_UEM!$A$3:$X$1848,22,FALSE) -> 660 | E47: IKNWOBE26005117 | F47: 01KT106 | G47: 02-Apr-2026 00:00:00 | H47: 02-Apr-2026 10:30:00 | I47: NA | J47: N | K47: =ROUNDUP((D47/4999.99)*10,-1) -> 10 | L47: =IF(J47="N",0,K47) -> 0 | M47: AN- QE:16. PPM HAS BEEN COMPLETED AS PER HEPPM CHECKLIST
A48: 27 | B48: IKN401518 | C48: Scales, Patient, Floor | D48: =VLOOKUP(B48,[13]AssetDetails_UEM!$A$3:$X$1848,22,FALSE) -> 3515 | E48: IKNWOBE26005118 | F48: 03DU103 | G48: 02-Apr-2026 00:00:00 | H48: 46114.646 | I48: NA | J48: N | K48: =ROUNDUP((D48/4999.99)*10,-1) -> 10 | L48: =IF(J48="N",0,K48) -> 0 | M48: AN- QE:16. PPM HAS BEEN COMPLETED AS PER HEPPM CHECKLIST
A49: 28 | B49: IKN401544 | C49: Scales, Clinical, Laboratory | D49: =VLOOKUP(B49,[13]AssetDetails_UEM!$A$3:$X$1848,22,FALSE) -> 3500 | E49: IKNWOBE26005119 | F49: 05PF146 | G49: 02-Apr-2026 00:00:00 | H49: 02-Apr-2026 14:30:00 | I49: NA | J49: N | K49: =ROUNDUP((D49/4999.99)*10,-1) -> 10 | L49: =IF(J49="N",0,K49) -> 0 | M49: AN- QE:16. PPM HAS BEEN COMPLETED AS PER HEPPM CHECKLIST
A50: 29 | B50: IKN401545 | C50: Balances, Electronic | D50: =VLOOKUP(B50,[13]AssetDetails_UEM!$A$3:$X$1848,22,FALSE) -> 5490 | E50: IKNWOBE26005120 | F50: 05PF112 | G50: 02-Apr-2026 00:00:00 | H50: 02-Apr-2026 12:30:00 | I50: NA | J50: N | K50: =ROUNDUP((D50/4999.99)*10,-1) -> 20 | L50: =IF(J50="N",0,K50) -> 0 | M50: AN- QE:16. PPM HAS BEEN COMPLETED AS PER HEPPM CHECKLIST
A51: 30 | B51: IKN401581 | C51: Balances, Electronic | D51: =VLOOKUP(B51,[13]AssetDetails_UEM!$A$3:$X$1848,22,FALSE) -> 3380 | E51: IKNWOBE26005121 | F51: 01KT101 | G51: 02-Apr-2026 00:00:00 | H51: 02-Apr-2026 11:30:00 | I51: NA | J51: N | K51: =ROUNDUP((D51/4999.99)*10,-1) -> 10 | L51: =IF(J51="N",0,K51) -> 0 | M51: AN- QE:16. PPM HAS BEEN COMPLETED AS PER HEPPM CHECKLIST
A52: 31 | B52: IKN401656 | C52: Balances, Electronic | D52: =VLOOKUP(B52,[13]AssetDetails_UEM!$A$3:$X$1848,22,FALSE) -> 1500 | E52: IKNWOBE26005122 | F52: 05OT120 | G52: 02-Apr-2026 00:00:00 | H52: 02-Apr-2026 10:00:00 | I52: NA | J52: N | K52: =ROUNDUP((D52/4999.99)*10,-1) -> 10 | L52: =IF(J52="N",0,K52) -> 0 | M52: L, QE:16-MAINTAINANCE DONE AS CALIBRATION CERTIFICATE ATTACHED UNIT FUNCTIONING IN GOOD CONDITION
A53: 32 | B53: IKN401691 | C53: Scales, Patient, Floor | D53: =VLOOKUP(B53,[13]AssetDetails_UEM!$A$3:$X$1848,22,FALSE) -> 3300 | E53: IKNWOBE26005123 | F53: 04HP128 | G53: 02-Apr-2026 00:00:00 | H53: 46114.688 | I53: NA | J53: N | K53: =ROUNDUP((D53/4999.99)*10,-1) -> 10 | L53: =IF(J53="N",0,K53) -> 0 | M53: PPM DONE AS A PERCHECKLIST
A54: 33 | B54: IKN401734 | C54: Balances, Electronic, Analytical | D54: =VLOOKUP(B54,[13]AssetDetails_UEM!$A$3:$X$1848,22,FALSE) -> 6617 | E54: IKNWOBE26005124 | F54: 03NM153 | G54: 02-Apr-2026 00:00:00 | H54: 02-Apr-2026 15:40:00 | I54: NA | J54: N | K54: =ROUNDUP((D54/4999.99)*10,-1) -> 20 | L54: =IF(J54="N",0,K54) -> 0 | M54: L, QE:16-CALIBRATION COMPLETE BY VENDOR , UNIT TESTED OKAY
A55: 34 | B55: IKN401999 | C55: Balances, Electronic | D55: =VLOOKUP(B55,[13]AssetDetails_UEM!$A$3:$X$1848,22,FALSE) -> 3850 | E55: IKNWOBE26005125 | F55: 05PF110 | G55: 02-Apr-2026 00:00:00 | H55: 02-Apr-2026 13:30:00 | I55: NA | J55: N | K55: =ROUNDUP((D55/4999.99)*10,-1) -> 10 | L55: =IF(J55="N",0,K55) -> 0 | M55: AN- QE:16. PPM HAS BEEN COMPLETED AS PER HEPPM CHECKLIST
A56: 35 | B56: IKN402055 | C56: Fluorometers | D56: =VLOOKUP(B56,[13]AssetDetails_UEM!$A$3:$X$1848,22,FALSE) -> 16800 | E56: IKNWOBE26005126 | F56: 04LA120 | G56: 02-Apr-2026 00:00:00 | H56: 02-Apr-2026 15:00:00 | I56: NA | J56: N | K56: =ROUNDUP((D56/4999.99)*10,-1) -> 40 | L56: =IF(J56="N",0,K56) -> 0 | M56: L, QE:16-PPM DONE AS PER HEPPM CHECKLIST
A57: 36 | B57: IKN401109 | C57: Lights, Surgical | D57: =VLOOKUP(B57,[13]AssetDetails_UEM!$A$3:$X$1848,22,FALSE) -> 10585 | E57: IKNWOBE26005127 | F57: 09WJ130 | G57: 02-Apr-2026 00:00:00 | H57: 02-Apr-2026 11:00:00 | I57: NA | J57: N | K57: =ROUNDUP((D57/4999.99)*10,-1) -> 30 | L57: =IF(J57="N",0,K57) -> 0 | M57: L, QE:16-PPM DONE AS PERCHEKLIST
A58: 37 | B58: IKN400774 | C58: Scanning Systems, Computed Tomography | D58: =VLOOKUP(B58,[13]AssetDetails_UEM!$A$3:$X$1848,22,FALSE) -> 4605710 | E58: IKNWOBE26005128 | F58: 03ID156 | G58: 03-Apr-2026 00:00:00 | H58: 03-Apr-2026 08:00:00 | I58: NA | J58: N | K58: =ROUNDUP((D58/4999.99)*10,-1) -> 9220 | L58: =IF(J58="N",0,K58) -> 0 | M58: L, QE:16-PPM NOT DONE, UNIT UNDER BER
A59: 38 | B59: IKN400764 | C59: Balances, Electronic | D59: =VLOOKUP(B59,[13]AssetDetails_UEM!$A$3:$X$1848,22,FALSE) -> 6260 | E59: IKNWOBE26005129 | F59: 04LA126 | G59: 03-Apr-2026 00:00:00 | H59: 03-Apr-2026 10:00:00 | I59: NA | J59: N | K59: =ROUNDUP((D59/4999.99)*10,-1) -> 20 | L59: =IF(J59="N",0,K59) -> 0 | M59: AN- QE:10. PPM NOT DONE, UNIT PROPOSED FOR BER
A60: 39 | B60: IKN400807 | C60: Lights, Surgical | D60: =VLOOKUP(B60,[13]AssetDetails_UEM!$A$3:$X$1848,22,FALSE) -> 165550 | E60: IKNWOBE26005130 | F60: 01RT275 | G60: 03-Apr-2026 00:00:00 | H60: 03-Apr-2026 08:00:00 | I60: NA | J60: N | K60: =ROUNDUP((D60/4999.99)*10,-1) -> 340 | L60: =IF(J60="N",0,K60) -> 0 | M60: L, QE:16-MAINTAINANCE DONE AS PER HEPPM CHECKLIST ATTACHED UNIT FUNCTIONING IN GOOD CONDITION
A61: 40 | B61: IKN400808 | C61: Lights, Surgical | D61: =VLOOKUP(B61,[13]AssetDetails_UEM!$A$3:$X$1848,22,FALSE) -> 165550 | E61: IKNWOBE26005131 | F61: 01RT278 | G61: 03-Apr-2026 00:00:00 | H61: 03-Apr-2026 09:00:00 | I61: NA | J61: N | K61: =ROUNDUP((D61/4999.99)*10,-1) -> 340 | L61: =IF(J61="N",0,K61) -> 0 | M61: L, QE:16-MAINTAINANCE DONE AS PER HEPPM CHECKLIST ATTACHED UNIT FUNCTIONING IN GOOD CONDITION
A62: 41 | B62: IKN400809 | C62: Lights, Surgical | D62: =VLOOKUP(B62,[13]AssetDetails_UEM!$A$3:$X$1848,22,FALSE) -> 5050 | E62: IKNWOBE26005132 | F62: 01RT233 | G62: 03-Apr-2026 00:00:00 | H62: 03-Apr-2026 10:00:00 | I62: NA | J62: N | K62: =ROUNDUP((D62/4999.99)*10,-1) -> 20 | L62: =IF(J62="N",0,K62) -> 0 | M62: L, QE:16-MAINTAINANCE DONE AS PER HEPPM CHECKLIST ATTACHED UNIT FUNCTIONING IN GOOD CONDITION
A63: 42 | B63: IKN400845 | C63: Infusion Pumps, Syringe | D63: =VLOOKUP(B63,[13]AssetDetails_UEM!$A$3:$X$1848,22,FALSE) -> 10225 | E63: IKNWOBE26005133 | F63: 01RT278 | G63: 03-Apr-2026 00:00:00 | H63: 03-Apr-2026 11:00:00 | I63: NA | J63: N | K63: =ROUNDUP((D63/4999.99)*10,-1) -> 30 | L63: =IF(J63="N",0,K63) -> 0 | M63: L, QE:16-MAINTAINANCE DONE AS PER HEPPM CHECKLIST ATTACHED UNIT FUNCTIONING IN GOOD CONDITION
A64: 43 | B64: IKN400846 | C64: Infusion Pumps, Syringe | D64: =VLOOKUP(B64,[13]AssetDetails_UEM!$A$3:$X$1848,22,FALSE) -> 10225 | E64: IKNWOBE26005134 | F64: 01RT278 | G64: 03-Apr-2026 00:00:00 | H64: 03-Apr-2026 12:00:00 | I64: NA | J64: N | K64: =ROUNDUP((D64/4999.99)*10,-1) -> 30 | L64: =IF(J64="N",0,K64) -> 0 | M64: L, QE:16-MAINTAINANCE DONE AS PER HEPPM CHECKLIST ATTACHED UNIT FUNCTIONING IN GOOD CONDITION
A65: 44 | B65: IKN400847 | C65: Infusion Pumps, Patient-Controlled Analgesic | D65: =VLOOKUP(B65,[13]AssetDetails_UEM!$A$3:$X$1848,22,FALSE) -> 9622 | E65: IKNWOBE26005135 | F65: 01RT278 | G65: 03-Apr-2026 00:00:00 | H65: 03-Apr-2026 14:00:00 | I65: NA | J65: N | K65: =ROUNDUP((D65/4999.99)*10,-1) -> 20 | L65: =IF(J65="N",0,K65) -> 0 | M65: L, QE:16-MAINTAINANCE DONE AS PER HEPPM CHECKLIST ATTACHED UNIT FUNCTIONING IN GOOD CONDITION
... A67: 46 | B67: IKN400882 | C67: Sphygmomanometers, Electronic, Automatic | D67: =VLOOKUP(B67,[13]AssetDetails_UEM!$A$3:$X$1848,22,FALSE) -> 7770 | E67: IKNWOBE26005137 | F67: 03OC133 | G67: 03-Apr-2026 00:00:00 | H67: 03-Apr-2026 14:00:00 | I67: NA | J67: N | K67: =ROUNDUP((D67/4999.99)*10,-1) -> 20 | L67: =IF(J67="N",0,K67) -> 0 | M67: L, QE:16-PPM COMPLETE AS PER CHECKLIST , UNIT TESTED OKAY
A68: 47 | B68: IKN401617 | C68: Aspirators | D68: =VLOOKUP(B68,[13]AssetDetails_UEM!$A$3:$X$1848,22,FALSE) -> 4900 | E68: IKNWOBE26005138 | F68: 03MC107 | G68: 03-Apr-2026 00:00:00 | H68: 46115.625 | I68: NA | J68: N | K68: =ROUNDUP((D68/4999.99)*10,-1) -> 10 | L68: =IF(J68="N",0,K68) -> 0 | M68: AN- QE:16 PPM DONE AS A PERCHECKLIST
A69: 48 | B69: IKN401618 | C69: Compressors, Medical-Air | D69: =VLOOKUP(B69,[13]AssetDetails_UEM!$A$3:$X$1848,22,FALSE) -> 7000 | E69: IKNWOBE26005139 | F69: 03MC107 | G69: 03-Apr-2026 00:00:00 | H69: 46115.667 | I69: NA | J69: N | K69: =ROUNDUP((D69/4999.99)*10,-1) -> 20 | L69: =IF(J69="N",0,K69) -> 0 | M69: AN- QE:16. PPM HAS BEEN COMPLETED AS PER HEPPM CHECKLIST
A70: 49 | B70: IKN401108 | C70: Lights, Surgical | D70: =VLOOKUP(B70,[13]AssetDetails_UEM!$A$3:$X$1848,22,FALSE) -> 10585 | E70: IKNWOBE26005141 | F70: 09WJ126 | G70: 03-Apr-2026 00:00:00 | H70: 03-Apr-2026 10:00:00 | I70: NA | J70: N | K70: =ROUNDUP((D70/4999.99)*10,-1) -> 30 | L70: =IF(J70="N",0,K70) -> 0 | M70: L, QE:16-PPM DONE AS PERCHEKLIST
A71: 50 | B71: IKN400305 | C71: Sphygmomanometers, Electronic, Automatic | D71: =VLOOKUP(B71,[13]AssetDetails_UEM!$A$3:$X$1848,22,FALSE) -> 4510 | E71: IKNWOBE26005142 | F71: 08WH143 | G71: 06-Apr-2026 00:00:00 | H71: 06-Apr-2026 08:00:00 | I71: NA | J71: N | K71: =ROUNDUP((D71/4999.99)*10,-1) -> 10 | L71: =IF(J71="N",0,K71) -> 0 | M71: L, QE:16-PPM DONE AS PERCHEKLIST
A72: 51 | B72: IKN400310 | C72: Sphygmomanometers, Electronic, Automatic | D72: =VLOOKUP(B72,[13]AssetDetails_UEM!$A$3:$X$1848,22,FALSE) -> 4510 | E72: IKNWOBE26005143 | F72: 08WH143 | G72: 06-Apr-2026 00:00:00 | H72: 06-Apr-2026 09:00:00 | I72: NA | J72: N | K72: =ROUNDUP((D72/4999.99)*10,-1) -> 10 | L72: =IF(J72="N",0,K72) -> 0 | M72: L, QE:16-PPM DONE AS PERCHEKLIST
A73: 52 | B73: IKN400417 | C73: Infusion Pumps, General-Purpose | D73: =VLOOKUP(B73,[13]AssetDetails_UEM!$A$3:$X$1848,22,FALSE) -> 10825 | E73: IKNWOBE26005144 | F73: 06WD153 | G73: 06-Apr-2026 00:00:00 | H73: 06-Apr-2026 10:00:00 | I73: NA | J73: N | K73: =ROUNDUP((D73/4999.99)*10,-1) -> 30 | L73: =IF(J73="N",0,K73) -> 0 | M73: L, QE:16-PPM DONE AS PERCHEKLIST
A74: 53 | B74: IKN400418 | C74: Infusion Pumps, General-Purpose | D74: =VLOOKUP(B74,[13]AssetDetails_UEM!$A$3:$X$1848,22,FALSE) -> 10825 | E74: IKNWOBE26005145 | F74: 06WD153 | G74: 06-Apr-2026 00:00:00 | H74: 06-Apr-2026 11:00:00 | I74: NA | J74: N | K74: =ROUNDUP((D74/4999.99)*10,-1) -> 30 | L74: =IF(J74="N",0,K74) -> 0 | M74: L, QE:16-PPM DONE AS PERCHEKLIST
A75: 54 | B75: IKN400421 | C75: Infusion Pumps, General-Purpose | D75: =VLOOKUP(B75,[13]AssetDetails_UEM!$A$3:$X$1848,22,FALSE) -> 10825 | E75: IKNWOBE26005146 | F75: 06WD153 | G75: 06-Apr-2026 00:00:00 | H75: 06-Apr-2026 14:30:00 | I75: NA | J75: N | K75: =ROUNDUP((D75/4999.99)*10,-1) -> 30 | L75: =IF(J75="N",0,K75) -> 0 | M75: L, QE:16-PPM DONE AS PERCHEKLIST
A76: 55 | B76: IKN400422 | C76: Infusion Pumps, General-Purpose | D76: =VLOOKUP(B76,[13]AssetDetails_UEM!$A$3:$X$1848,22,FALSE) -> 10825 | E76: IKNWOBE26005147 | F76: 06WD153 | G76: 06-Apr-2026 00:00:00 | H76: 06-Apr-2026 16:00:00 | I76: NA | J76: N | K76: =ROUNDUP((D76/4999.99)*10,-1) -> 30 | L76: =IF(J76="N",0,K76) -> 0 | M76: L, QE:12-UNIT UNDER REIMBURSE, REFER ATTACH REPORT LP/ AWSB/IKN/BEMS/ASSET PROPASED FOR BER
A77: 56 | B77: IKN400427 | C77: Infusion Pumps, General-Purpose | D77: =VLOOKUP(B77,[13]AssetDetails_UEM!$A$3:$X$1848,22,FALSE) -> 10825 | E77: IKNWOBE26005148 | F77: 06WD153 | G77: 06-Apr-2026 00:00:00 | H77: 06-Apr-2026 17:30:00 | I77: NA | J77: N | K77: =ROUNDUP((D77/4999.99)*10,-1) -> 30 | L77: =IF(J77="N",0,K77) -> 0 | M77: L, QE:16-PPM DONE AS PERCHEKLIST
A78: 57 | B78: IKN400445 | C78: Infusion Pumps, Syringe | D78: =VLOOKUP(B78,[13]AssetDetails_UEM!$A$3:$X$1848,22,FALSE) -> 10225 | E78: IKNWOBE26005149 | F78: 06WC113 | G78: 06-Apr-2026 00:00:00 | H78: 06-Apr-2026 13:00:00 | I78: NA | J78: N | K78: =ROUNDUP((D78/4999.99)*10,-1) -> 30 | L78: =IF(J78="N",0,K78) -> 0 | M78: L, QE:16-PPM DONE AS PERCHEKLIST
A79: 58 | B79: IKN400617 | C79: Warming Units, Patient, Forced-Air | D79: =VLOOKUP(B79,[13]AssetDetails_UEM!$A$3:$X$1848,22,FALSE) -> 15515 | E79: IKNWOBE26005150 | F79: 04DO118 | G79: 06-Apr-2026 00:00:00 | H79: 06-Apr-2026 17:30:00 | I79: NA | J79: N | K79: =ROUNDUP((D79/4999.99)*10,-1) -> 40 | L79: =IF(J79="N",0,K79) -> 0 | M79: M,QE:16-PPM DONE AS PER HEPPM CHECKLIST ATTACHED
A80: 59 | B80: IKN400618 | C80: Warming Units, Patient, Forced-Air | D80: =VLOOKUP(B80,[13]AssetDetails_UEM!$A$3:$X$1848,22,FALSE) -> 15515 | E80: IKNWOBE26005151 | F80: 04DO118 | G80: 06-Apr-2026 00:00:00 | H80: 06-Apr-2026 17:50:00 | I80: NA | J80: N | K80: =ROUNDUP((D80/4999.99)*10,-1) -> 40 | L80: =IF(J80="N",0,K80) -> 0 | M80: M,QE:16-PPM DONE AS PER HEPPM CHECKLIST ATTACHED
A81: 60 | B81: IKN400627 | C81: Warming Units, Patient, Forced-Air | D81: =VLOOKUP(B81,[13]AssetDetails_UEM!$A$3:$X$1848,22,FALSE) -> 15515 | E81: IKNWOBE26005152 | F81: 04DO119 | G81: 06-Apr-2026 00:00:00 | H81: 06-Apr-2026 18:00:00 | I81: NA | J81: N | K81: =ROUNDUP((D81/4999.99)*10,-1) -> 40 | L81: =IF(J81="N",0,K81) -> 0 | M81: M,QE:16-PPM DONE AS PER HEPPM CHECKLIST ATTACHED
... A85: 64 | B85: IKN400661 | C85: Warming Units, Patient, Forced-Air | D85: =VLOOKUP(B85,[13]AssetDetails_UEM!$A$3:$X$1848,22,FALSE) -> 15515 | E85: IKNWOBE26005156 | F85: 04DO138 | G85: 06-Apr-2026 00:00:00 | H85: 06-Apr-2026 19:00:00 | I85: NA | J85: N | K85: =ROUNDUP((D85/4999.99)*10,-1) -> 40 | L85: =IF(J85="N",0,K85) -> 0 | M85: M,QE:16-PPM DONE AS PER HEPPM CHECKLIST ATTACHED
A86: 65 | B86: IKN400824 | C86: Sphygmomanometers, Electronic, Automatic | D86: =VLOOKUP(B86,[13]AssetDetails_UEM!$A$3:$X$1848,22,FALSE) -> 4510 | E86: IKNWOBE26005157 | F86: 01RT243 | G86: 06-Apr-2026 00:00:00 | H86: 46118.458 | I86: NA | J86: N | K86: =ROUNDUP((D86/4999.99)*10,-1) -> 10 | L86: =IF(J86="N",0,K86) -> 0 | M86: PPM DONE AS A PERCHECKLIST
A87: 66 | B87: IKN400825 | C87: Sphygmomanometers, Electronic, Automatic | D87: =VLOOKUP(B87,[13]AssetDetails_UEM!$A$3:$X$1848,22,FALSE) -> 4510 | E87: IKNWOBE26005158 | F87: 01RT243 | G87: 06-Apr-2026 00:00:00 | H87: 46118.5 | I87: NA | J87: N | K87: =ROUNDUP((D87/4999.99)*10,-1) -> 10 | L87: =IF(J87="N",0,K87) -> 0 | M87: PPM DONE AS A PERCHECKLIST
A88: 67 | B88: IKN400246 | C88: Infusion Pumps, General-Purpose | D88: =VLOOKUP(B88,[13]AssetDetails_UEM!$A$3:$X$1848,22,FALSE) -> 10825 | E88: IKNWOBE26005160 | F88: 08WG113 | G88: 07-Apr-2026 00:00:00 | H88: 07-Apr-2026 14:00:00 | I88: NA | J88: N | K88: =ROUNDUP((D88/4999.99)*10,-1) -> 30 | L88: =IF(J88="N",0,K88) -> 0 | M88: L, QE:16-PPM DONE AS PERCHEKLIST
A89: 68 | B89: IKN400416 | C89: Infusion Pumps, General-Purpose | D89: =VLOOKUP(B89,[13]AssetDetails_UEM!$A$3:$X$1848,22,FALSE) -> 10825 | E89: IKNWOBE26005161 | F89: 06WD153 | G89: 07-Apr-2026 00:00:00 | H89: 07-Apr-2026 08:00:00 | I89: NA | J89: N | K89: =ROUNDUP((D89/4999.99)*10,-1) -> 30 | L89: =IF(J89="N",0,K89) -> 0 | M89: L, QE:12-PPM DONE AS PERCHECKLIST
A90: 69 | B90: IKN400424 | C90: Infusion Pumps, General-Purpose | D90: =VLOOKUP(B90,[13]AssetDetails_UEM!$A$3:$X$1848,22,FALSE) -> 10825 | E90: IKNWOBE26005162 | F90: 06WD153 | G90: 07-Apr-2026 00:00:00 | H90: 07-Apr-2026 09:00:00 | I90: NA | J90: N | K90: =ROUNDUP((D90/4999.99)*10,-1) -> 30 | L90: =IF(J90="N",0,K90) -> 0 | M90: L, QE:12-PPM DONE AS PERCHECKLIST
A91: 70 | B91: IKN400527 | C91: Aspirators | D91: =VLOOKUP(B91,[13]AssetDetails_UEM!$A$3:$X$1848,22,FALSE) -> 2165 | E91: IKNWOBE26005163 | F91: 04PC109 | G91: 07-Apr-2026 00:00:00 | H91: 07-Apr-2026 11:00:00 | I91: NA | J91: N | K91: =ROUNDUP((D91/4999.99)*10,-1) -> 10 | L91: =IF(J91="N",0,K91) -> 0 | M91: L, QE:16-MAINTAINANCE DONE AS PER HEPPM CHECKLIST
A92: 71 | B92: IKN400528 | C92: Aspirators | D92: =VLOOKUP(B92,[13]AssetDetails_UEM!$A$3:$X$1848,22,FALSE) -> 2165 | E92: IKNWOBE26005164 | F92: 04PC109 | G92: 07-Apr-2026 00:00:00 | H92: 07-Apr-2026 14:00:00 | I92: NA | J92: N | K92: =ROUNDUP((D92/4999.99)*10,-1) -> 10 | L92: =IF(J92="N",0,K92) -> 0 | M92: AN- QE:16. PPM DONE AS PER HEPPM CHECKLIST
A93: 72 | B93: IKN400529 | C93: Aspirators | D93: =VLOOKUP(B93,[13]AssetDetails_UEM!$A$3:$X$1848,22,FALSE) -> 2165 | E93: IKNWOBE26005165 | F93: 04PC109 | G93: 07-Apr-2026 00:00:00 | H93: 07-Apr-2026 10:00:00 | I93: NA | J93: N | K93: =ROUNDUP((D93/4999.99)*10,-1) -> 10 | L93: =IF(J93="N",0,K93) -> 0 | M93: L, QE:16-MAINTAINANCE DONE AS PER HEPPM CHECKLIST
A94: 73 | B94: IKN400579 | C94: Radiation Monitors | D94: =VLOOKUP(B94,[13]AssetDetails_UEM!$A$3:$X$1848,22,FALSE) -> 23270 | E94: IKNWOBE26005166 | F94: 01NW105 | G94: 07-Apr-2026 00:00:00 | H94: 07-Apr-2026 08:30:00 | I94: NA | J94: N | K94: =ROUNDUP((D94/4999.99)*10,-1) -> 50 | L94: =IF(J94="N",0,K94) -> 0 | M94: AN- QE:16, CALIBRATION DONE BY TRACERCO ASIA AS PER CALIBRATION CERTIFICATE ATTACHED
A95: 74 | B95: IKN400712 | C95: Centrifuges, Tabletop, Low-Speed, Nonrefrigerated, Blood Ban | D95: =VLOOKUP(B95,[13]AssetDetails_UEM!$A$3:$X$1848,22,FALSE) -> 5170 | E95: IKNWOBE26005167 | F95: 04LA140 | G95: 07-Apr-2026 00:00:00 | H95: 07-Apr-2026 18:00:00 | I95: NA | J95: N | K95: =ROUNDUP((D95/4999.99)*10,-1) -> 20 | L95: =IF(J95="N",0,K95) -> 0 | M95: M,QE:16-PPM DONE AS PER HEPPM CHECKLIST ATTACHED
A96: 75 | B96: IKN400713 | C96: Centrifuges, Tabletop | D96: =VLOOKUP(B96,[13]AssetDetails_UEM!$A$3:$X$1848,22,FALSE) -> 14435 | E96: IKNWOBE26005168 | F96: 04LA132 | G96: 07-Apr-2026 00:00:00 | H96: 07-Apr-2026 18:30:00 | I96: NA | J96: N | K96: =ROUNDUP((D96/4999.99)*10,-1) -> 30 | L96: =IF(J96="N",0,K96) -> 0 | M96: M,QE:16-PPM DONE AS PER HEPPM CHECKLIST ATTACHED
A97: 76 | B97: IKN400716 | C97: Centrifuges, Tabletop | D97: =VLOOKUP(B97,[13]AssetDetails_UEM!$A$3:$X$1848,22,FALSE) -> 14435 | E97: IKNWOBE26005169 | F97: 04LA132 | G97: 07-Apr-2026 00:00:00 | H97: 07-Apr-2026 17:30:00 | I97: NA | J97: N | K97: =ROUNDUP((D97/4999.99)*10,-1) -> 30 | L97: =IF(J97="N",0,K97) -> 0 | M97: M,QE:16-PPM DONE AS PER HEPPM CHECKLIST ATTACHED
A98: 77 | B98: IKN400763 | C98: Mixers, Clinical Laboratory | D98: =VLOOKUP(B98,[13]AssetDetails_UEM!$A$3:$X$1848,22,FALSE) -> 1200 | E98: IKNWOBE26005170 | F98: 04LA126 | G98: 07-Apr-2026 00:00:00 | H98: 07-Apr-2026 16:00:00 | I98: NA | J98: N | K98: =ROUNDUP((D98/4999.99)*10,-1) -> 10 | L98: =IF(J98="N",0,K98) -> 0 | M98: M,QE:16-PPM DONE AS PER HEPPM CHECKLIST ATTACHED
A99: 78 | B99: IKN400829 | C99: Infusion Pumps, Syringe | D99: =VLOOKUP(B99,[13]AssetDetails_UEM!$A$3:$X$1848,22,FALSE) -> 10225 | E99: IKNWOBE26005171 | F99: 01RT275 | G99: 07-Apr-2026 00:00:00 | H99: 07-Apr-2026 10:00:00 | I99: NA | J99: N | K99: =ROUNDUP((D99/4999.99)*10,-1) -> 30 | L99: =IF(J99="N",0,K99) -> 0 | M99: AN- QE:16, MAINTENANCE DONE AS PER HEPPM CHECKLIST ATTACHED, UNIT FUNCTIONING IN GOOD CONDITION
... A104: 83 | B104: IKN402171 | C104: Microscopes, Light, Laboratory, Inverted Stage | D104: =VLOOKUP(B104,[13]AssetDetails_UEM!$A$3:$X$1848,22,FALSE) -> 15864 | E104: IKNWOBE26005180 | F104: 04LA127 | G104: 07-Apr-2026 00:00:00 | H104: 07-Apr-2026 19:00:00 | I104: NA | J104: N | K104: =ROUNDUP((D104/4999.99)*10,-1) -> 40 | L104: =IF(J104="N",0,K104) -> 0 | M104: M,QE:16-PPM DONE AS PER HEPPM CHECKLIST ATTACHED
A105: 84 | B105: IKN400956 | C105: Linear Accelerators | D105: =VLOOKUP(B105,[13]AssetDetails_UEM!$A$3:$X$1848,22,FALSE) -> 21961900 | E105: IKNWOBE26005183 | F105: 01RT172 | G105: 10-Apr-2026 00:00:00 | H105: 46125.333 | I105: NA | J105: N | K105: =ROUNDUP((D105/4999.99)*10,-1) -> 43930 | L105: =IF(J105="N",0,K105) -> 0 | M105: M,QE:16- PPM DONE AS A PERCHECKLIST
A106: 85 | B106: IKN400492 | C106: Balances, Electronic, Analytical | D106: =VLOOKUP(B106,[13]AssetDetails_UEM!$A$3:$X$1848,22,FALSE) -> 6250 | E106: IKNWOBE26005184 | F106: 03NM142 | G106: 10-Apr-2026 00:00:00 | H106: 02-Apr-2026 14:00:00 | I106: NA | J106: N | K106: =ROUNDUP((D106/4999.99)*10,-1) -> 20 | L106: =IF(J106="N",0,K106) -> 0 | M106: L, QE:16-CALIBRATION COMPLETE BY VENDOR , UNIT TESTED OKAY
A107: 86 | B107: IKN401234 | C107: Balances, Electronic, Analytical | D107: =VLOOKUP(B107,[13]AssetDetails_UEM!$A$3:$X$1848,22,FALSE) -> 6250 | E107: IKNWOBE26005186 | F107: 03NM138 | G107: 10-Apr-2026 00:00:00 | H107: 02-Apr-2026 14:50:00 | I107: NA | J107: N | K107: =ROUNDUP((D107/4999.99)*10,-1) -> 20 | L107: =IF(J107="N",0,K107) -> 0 | M107: L, QE:16-CALIBRATION COMPLETE BY VENDOR , UNIT TESTED OKAY
A108: 87 | B108: IKN400774 | C108: Scanning Systems, Computed Tomography | D108: =VLOOKUP(B108,[13]AssetDetails_UEM!$A$3:$X$1848,22,FALSE) -> 4605710 | E108: IKNWOBE26005193 | F108: 03ID156 | G108: 13-Apr-2026 00:00:00 | H108: 13-Apr-2026 09:00:00 | I108: NA | J108: N | K108: =ROUNDUP((D108/4999.99)*10,-1) -> 9220 | L108: =IF(J108="N",0,K108) -> 0 | M108: L, QE:16-MACHINE ALREADY DISMANTLE . PPM NOT DONE
A109: 88 | B109: IKN400464 | C109: Sphygmomanometers, Electronic, Automatic | D109: =VLOOKUP(B109,[13]AssetDetails_UEM!$A$3:$X$1848,22,FALSE) -> 7770 | E109: IKNWOBE26005194 | F109: 01AE112 | G109: 13-Apr-2026 00:00:00 | H109: 46125.458 | I109: NA | J109: N | K109: =ROUNDUP((D109/4999.99)*10,-1) -> 20 | L109: =IF(J109="N",0,K109) -> 0 | M109: PPM DONE AS A PERCHECKLIST
A110: 89 | B110: IKN402116 | C110: Analyzers, Laboratory, Breath, Carbon Monoxide | D110: =VLOOKUP(B110,[13]AssetDetails_UEM!$A$3:$X$1848,22,FALSE) -> 3950 | E110: IKNWOBE26005195 | F110: 04HP104 | G110: 13-Apr-2026 00:00:00 | H110: 13-Apr-2026 15:00:00 | I110: NA | J110: N | K110: =ROUNDUP((D110/4999.99)*10,-1) -> 10 | L110: =IF(J110="N",0,K110) -> 0 | M110: L, QE:16 -PPM COMPLETE AS PER HEPPM CHECKLIST
A111: 90 | B111: IKN400152 | C111: Mattress Systems, Alternating-Pressure | D111: =VLOOKUP(B111,[13]AssetDetails_UEM!$A$3:$X$1848,22,FALSE) -> 28630 | E111: IKNWOBE26005196 | F111: 07WF121 | G111: 14-Apr-2026 00:00:00 | H111: 14-Apr-2026 10:00:00 | I111: NA | J111: N | K111: =ROUNDUP((D111/4999.99)*10,-1) -> 60 | L111: =IF(J111="N",0,K111) -> 0 | M111: AN- QE:16. PPM HAS BEEN COMPLETED AS PER HEPPM CHECKLIST
A112: 91 | B112: IKN402239 | C112: Scanning Systems, Ultrasonic, Cardiac | D112: 239500 | E112: IKNWOBE26005197 | F112: 01RT118 | G112: 14-Apr-2026 00:00:00 | H112: 14-Apr-2026 15:30:00 | I112: NA | J112: N | K112: =ROUNDUP((D112/4999.99)*10,-1) -> 480 | L112: =IF(J112="N",0,K112) -> 0 | M112: L, QE:16-PPM COMPLETE BY VENDOR , UNIT TESTED OKAY
A113: 92 | B113: IKN400032 | C113: Infusion/ Monitoring Line Organizer System | D113: =VLOOKUP(B113,[13]AssetDetails_UEM!$A$3:$X$1848,22,FALSE) -> 84200 | E113: IKNWOBE26005198 | F113: 05IC111 | G113: 15-Apr-2026 00:00:00 | H113: 15-Apr-2026 08:00:00 | I113: NA | J113: N | K113: =ROUNDUP((D113/4999.99)*10,-1) -> 170 | L113: =IF(J113="N",0,K113) -> 0 | M113: AN- QE:16, MAINTENANCE DONE AS PER HEPPM CHECKLIST ATTACHED, UNIT FUNCTIONING IN GOOD CONDITION
A114: 93 | B114: IKN400079 | C114: Pumps, Enteral Feeding | D114: =VLOOKUP(B114,[13]AssetDetails_UEM!$A$3:$X$1848,22,FALSE) -> 6615 | E114: IKNWOBE26005199 | F114: 05IC111 | G114: 15-Apr-2026 00:00:00 | H114: 15-Apr-2026 18:40:00 | I114: NA | J114: N | K114: =ROUNDUP((D114/4999.99)*10,-1) -> 20 | L114: =IF(J114="N",0,K114) -> 0 | M114: AN- QE:16, MAINTENANCE DONE AS PER HEPPM CHERCKLIST ATTACHED, UNIT FUNCTIONING IN GOOD CONDITION
A115: 94 | B115: IKN400087 | C115: Infusion Pumps, Syringe | D115: =VLOOKUP(B115,[13]AssetDetails_UEM!$A$3:$X$1848,22,FALSE) -> 10225 | E115: IKNWOBE26005200 | F115: 05IC111 | G115: 15-Apr-2026 00:00:00 | H115: 15-Apr-2026 17:40:00 | I115: NA | J115: N | K115: =ROUNDUP((D115/4999.99)*10,-1) -> 30 | L115: =IF(J115="N",0,K115) -> 0 | M115: AN- QE:16. MAINTENANCE DONE AS PER HEPPM CHECKLIST ATTACHED, UNIT FUNCTIONING IN GOOD CONDITION
A116: 95 | B116: IKN400088 | C116: Infusion Pumps, Syringe | D116: =VLOOKUP(B116,[13]AssetDetails_UEM!$A$3:$X$1848,22,FALSE) -> 10225 | E116: IKNWOBE26005201 | F116: 05IC111 | G116: 15-Apr-2026 00:00:00 | H116: 15-Apr-2026 16:00:00 | I116: NA | J116: N | K116: =ROUNDUP((D116/4999.99)*10,-1) -> 30 | L116: =IF(J116="N",0,K116) -> 0 | M116: AN- QE:16, MAINTENANCE DONE AS PER HEPPM CHECKLIST ATTACHED, UNIT FUNCTIONING IN GOOD CONDITION
A117: 96 | B117: IKN400089 | C117: Infusion Pumps, Syringe | D117: =VLOOKUP(B117,[13]AssetDetails_UEM!$A$3:$X$1848,22,FALSE) -> 10225 | E117: IKNWOBE26005202 | F117: 05IC111 | G117: 15-Apr-2026 00:00:00 | H117: 15-Apr-2026 15:00:00 | I117: NA | J117: N | K117: =ROUNDUP((D117/4999.99)*10,-1) -> 30 | L117: =IF(J117="N",0,K117) -> 0 | M117: AN- QE:16. MAITENANCE DONE AS PER HEPPM CHECKLIST ATTACHED, UNIT FUNCTIONING IN GOOD CONDITION
A118: 97 | B118: IKN400090 | C118: Infusion Pumps, Syringe | D118: =VLOOKUP(B118,[13]AssetDetails_UEM!$A$3:$X$1848,22,FALSE) -> 10225 | E118: IKNWOBE26005203 | F118: 05IC111 | G118: 15-Apr-2026 00:00:00 | H118: 15-Apr-2026 14:00:00 | I118: NA | J118: N | K118: =ROUNDUP((D118/4999.99)*10,-1) -> 30 | L118: =IF(J118="N",0,K118) -> 0 | M118: AN- QE:16. MAINTENANCE DONE AS PER HEPPM CHECKLIST ATTACHED, UNIT FUNCTIONING IN GOOD CONDITION
A119: 98 | B119: IKN400091 | C119: Infusion Pumps, Syringe | D119: =VLOOKUP(B119,[13]AssetDetails_UEM!$A$3:$X$1848,22,FALSE) -> 10225 | E119: IKNWOBE26005204 | F119: 05IC111 | G119: 15-Apr-2026 00:00:00 | H119: 15-Apr-2026 12:00:00 | I119: NA | J119: N | K119: =ROUNDUP((D119/4999.99)*10,-1) -> 30 | L119: =IF(J119="N",0,K119) -> 0 | M119: AN- QE:16. MAINTENANCE DONE AS PER HEPPM CHECKLIST ATTACHED, UNIT FUNCTIONING IN GOOD CONDITION
A120: 99 | B120: IKN400092 | C120: Infusion Pumps, Syringe | D120: =VLOOKUP(B120,[13]AssetDetails_UEM!$A$3:$X$1848,22,FALSE) -> 10225 | E120: IKNWOBE26005205 | F120: 05IC111 | G120: 15-Apr-2026 00:00:00 | H120: 15-Apr-2026 11:00:00 | I120: NA | J120: N | K120: =ROUNDUP((D120/4999.99)*10,-1) -> 30 | L120: =IF(J120="N",0,K120) -> 0 | M120: AN- QE:16. MAINTENANCE DONE ACCORDING TO HEPPM CHECKLIST ATTACHED, UNIT FUNCTIONING IN GOOD CONDITION
A121: 100 | B121: IKN400135 | C121: Infusion Pumps, General-Purpose | D121: =VLOOKUP(B121,[13]AssetDetails_UEM!$A$3:$X$1848,22,FALSE) -> 10825 | E121: IKNWOBE26005206 | F121: 05IC111 | G121: 15-Apr-2026 00:00:00 | H121: 15-Apr-2026 10:00:00 | I121: NA | J121: N | K121: =ROUNDUP((D121/4999.99)*10,-1) -> 30 | L121: =IF(J121="N",0,K121) -> 0 | M121: AN QE:16, MAINTENANCE DONE AS PER HEPPM CHECKLIST ATTACHED, UNIT FUNCTIONING IN GOOD CONDITION
A122: 101 | B122: IKN400136 | C122: Infusion Pumps, General-Purpose | D122: =VLOOKUP(B122,[13]AssetDetails_UEM!$A$3:$X$1848,22,FALSE) -> 10825 | E122: IKNWOBE26005207 | F122: 05IC111 | G122: 15-Apr-2026 00:00:00 | H122: 15-Apr-2026 09:00:00 | I122: NA | J122: N | K122: =ROUNDUP((D122/4999.99)*10,-1) -> 30 | L122: =IF(J122="N",0,K122) -> 0 | M122: AN- QE:16. MAINTENANCE DONE AS PER HEPPM CHECKLIST ATTACHED, UNIT FUNCTIONING IN GOOD CONDITION
A123: 102 | B123: IKN400338 | C123: Mattress Systems, Alternating-Pressure | D123: =VLOOKUP(B123,[13]AssetDetails_UEM!$A$3:$X$1848,22,FALSE) -> 28630 | E123: IKNWOBE26005208 | F123: 07WF121 | G123: 15-Apr-2026 00:00:00 | H123: 15-Apr-2026 08:00:00 | I123: NA | J123: N | K123: =ROUNDUP((D123/4999.99)*10,-1) -> 60 | L123: =IF(J123="N",0,K123) -> 0 | M123: AN- QE:16. PPM HAS BEEN COMPLETED AS PER HEPPM CHECKLIST
A124: 103 | B124: IKN400339 | C124: Mattress Systems, Alternating-Pressure | D124: =VLOOKUP(B124,[13]AssetDetails_UEM!$A$3:$X$1848,22,FALSE) -> 28630 | E124: IKNWOBE26005209 | F124: 07WF121 | G124: 15-Apr-2026 00:00:00 | H124: 15-Apr-2026 10:00:00 | I124: NA | J124: N | K124: =ROUNDUP((D124/4999.99)*10,-1) -> 60 | L124: =IF(J124="N",0,K124) -> 0 | M124: AN- QE:16. PPM HAS BEEN COMPLETED AS PER HEPPM CHECKLIST
... A142: 121 | B142: IKN400426 | C142: Infusion Pumps, Syringe | D142: =VLOOKUP(B142,[13]AssetDetails_UEM!$A$3:$X$1848,22,FALSE) -> 10825 | E142: IKNWOBE26005227 | F142: 06WD153 | G142: 17-Apr-2026 00:00:00 | H142: 17-Apr-2026 15:00:00 | I142: NA | J142: N | K142: =ROUNDUP((D142/4999.99)*10,-1) -> 30 | L142: =IF(J142="N",0,K142) -> 0 | M142: L, QE:12-PPM DONE AS PERCHECKLIST
A143: 122 | B143: IKN400626 | C143: Warming Units, Patient, Forced-Air | D143: =VLOOKUP(B143,[13]AssetDetails_UEM!$A$3:$X$1848,22,FALSE) -> 15515 | E143: IKNWOBE26005228 | F143: 01RT243 | G143: 17-Apr-2026 00:00:00 | H143: 46129.417 | I143: NA | J143: N | K143: =ROUNDUP((D143/4999.99)*10,-1) -> 40 | L143: =IF(J143="N",0,K143) -> 0 | M143: PPM DONE AS AS PERCHECKLIST
...

Sheet B4-UPTIME
A1: MINISTRY OF HEALTH
A2: Deduction Mapping Report Biomedical Engineering Maintenance Services (BEMS)
A3: INDICATOR B.4 UPTIME GUARANTEE
B5: HOSPITAL NAME : | C5: INSTITUT KANSER NEGARA | N5: MONTH/YEAR : | U5: 46113
B7: STATE : | C7: WILAYAH PERSEKUTUAN PUTRAJAYA | N7: BEMS MONTHLY FEE (RM)@ 97.5% : | U7: =[15]BEMSdar!E11 -> 1437864.8
B9: COMPANY : | C9: AMBANG WIRA SDN BHD | N9: FMS MONTHLY FEE (RM) @ 2.5% : | U9: =[15]BEMSdar!E13 -> 36868.327
A11: Notes:
A12: 1) Deduction Ringgit Equivalent is based on Appendix 11 of the Agreement, Section B3 Key Deduction Indicators for BEMS
A13: 2) Deduction Value for 1st cut off is Deduction Ringgit Equivalent (per event)
A14: 3) Deduction Value for 2nd cut off is Deduction Ringgit Equivalent (per event) multiply by 2
A15: 4) Display only asset affected by deduction
A17: No. | B17: Asset No | C17: Type Code | D17: Type Description | E17: Asset Purchase cost (RM) | F17: Asset Age | G17: TRKPI % | H17: Uptime % | T17: Deduction Ringgit Equivalent (RM) | U17: Previous Deduction (Month) | W17: Deduction for the month (Y/N) | Y17: Deduction Value (RM) | AA17: Total Deduction (RM) | AB17: Remarks
H18: Jan | I18: Feb | J18: Mar | K18: Apr | L18: May | M18: Jun | N18: Jul | O18: Aug | P18: Sep | Q18: Oct | R18: Nov | S18: Dec | U18: 1st | V18: 2nd | W18: 1st | X18: 2nd | Y18: 1st | Z18: 2nd
A19: 1 | B19: IKN400440 | C19: 16-173 | D19: Sphygmomanometers, Electronic, Automatic | E19: 4510 | F19: 13 | G19: 88 | H19: 99.82733 | I19: 99.78 | J19: - | K19: - | T19: =ROUNDUP((E19/4999.99)*10,-1) -> 10 | U19: N | V19: N | W19: N | X19: N | Y19: =IF(W19="Y",T19,0) -> 0 | Z19: =IF(X19="Y",T19*2,0) -> 0 | AA19: =Y19+Z19 -> 0
A20: 2 | B20: IKN400645 | C20: 13-215 | D20: Infusion Pumps, General-Purpose | E20: 10825 | F20: 13 | G20: 88 | H20: 99.961971 | I20: 99.93 | J20: - | K20: - | T20: =ROUNDUP((E20/4999.99)*10,-1) -> 30 | U20: N | V20: N | W20: N | X20: N | Y20: =IF(W20="Y",T20,0) -> 0 | Z20: =IF(X20="Y",T20*2,0) -> 0 | AA20: =Y20+Z20 -> 0
A21: 3 | B21: IKN401714 | C21: 13-215 | D21: Infusion Pumps, General-Purpose | E21: 5800 | F21: 8 | G21: 95 | H21: 99.962034 | I21: 99.93 | J21: - | K21: - | T21: =ROUNDUP((E21/4999.99)*10,-1) -> 20 | U21: Y | V21: Y | W21: N | X21: N | Y21: =IF(W21="Y",T21,0) -> 0 | Z21: =IF(X21="Y",T21*2,0) -> 0 | AA21: =Y21+Z21 -> 0
A22: 4 | B22: IKN400446 | C22: 13-215 | D22: Infusion Pumps, General-Purpose | E22: 10825 | F22: 13 | G22: 88 | H22: 99.65 | I22: 99.68 | J22: 98.553172 | K22: - | T22: =ROUNDUP((E22/4999.99)*10,-1) -> 30 | U22: N | V22: N | W22: N | X22: N | Y22: =IF(W22="Y",T22,0) -> 0 | Z22: =IF(X22="Y",T22*2,0) -> 0 | AA22: =Y22+Z22 -> 0
A23: 5 | B23: IKN400366 | C23: 13-215 | D23: Infusion Pumps, General-Purpose | E23: 10825 | F23: 13 | G23: 88 | H23: 99.65 | I23: 99.68 | J23: 99.330998 | K23: 99.04 | T23: =ROUNDUP((E23/4999.99)*10,-1) -> 30 | U23: N | V23: N | W23: N | X23: N | Y23: =IF(W23="Y",T23,0) -> 0 | Z23: =IF(X23="Y",T23*2,0) -> 0 | AA23: =Y23+Z23 -> 0
A24: 6 | B24: IKN402165 | C24: 13-215 | D24: Infusion Pumps, General-Purpose | E24: 10825 | F24: 13 | G24: 88 | H24: 99.65 | I24: 99.45 | J24: - | K24: - | T24: =ROUNDUP((E24/4999.99)*10,-1) -> 30 | U24: N | V24: N | W24: N | X24: N | Y24: =IF(W24="Y",T24,0) -> 0 | Z24: =IF(X24="Y",T24*2,0) -> 0 | AA24: =Y24+Z24 -> 0
A25: 7 | B25: IKN400565 | C25: 12-649 | D25: Physiologic Monitoring Systems, Stress Exercise | E25: 138350 | F25: 13 | G25: 88 | H25: 99.65 | I25: 99.56 | J25: - | K25: - | T25: =ROUNDUP((E25/4999.99)*10,-1) -> 280 | U25: N | V25: N | W25: N | X25: N | Y25: =IF(W25="Y",T25,0) -> 0 | Z25: =IF(X25="Y",T25*2,0) -> 0 | AA25: =Y25+Z25 -> 0
A26: 8 | B26: IKN400439 | C26: 16-173 | D26: Sphygmomanometers, Electronic, Automatic | E26: 4510 | F26: 13 | G26: 88 | H26: 99.65 | I26: 99.53 | J26: - | K26: - | T26: =ROUNDUP((E26/4999.99)*10,-1) -> 10 | U26: N | V26: N | W26: N | X26: N | Y26: =IF(W26="Y",T26,0) -> 0 | Z26: =IF(X26="Y",T26*2,0) -> 0 | AA26: =Y26+Z26 -> 0
A27: 9 | B27: IKN401076 | C27: 12-306 | D27: Lavage Units, Surgical | E27: 5000 | F27: 13 | G27: 85 | H27: 99.65 | I27: 99.35 | J27: - | K27: - | T27: =ROUNDUP((E27/4999.99)*10,-1) -> 20 | U27: N | V27: N | W27: N | X27: N | Y27: =IF(W27="Y",T27,0) -> 0 | Z27: =IF(X27="Y",T27*2,0) -> 0 | AA27: =Y27+Z27 -> 0
A28: 10 | B28: IKN402147 | C28: 15-605 | D28: Testers (Ion Chamber Set) | E28: 142000 | F28: 4 | G28: 96 | H28: 99.65 | I28: 99.39 | J28: - | K28: - | T28: =ROUNDUP((E28/4999.99)*10,-1) -> 290 | U28: N | V28: N | W28: N | X28: N | Y28: =IF(W28="Y",T28,0) -> 0 | Z28: =IF(X28="Y",T28*2,0) -> 0 | AA28: =Y28+Z28 -> 0
A29: 11 | B29: IKN401071 | C29: 18-034 | D29: Video Image Processors, Endoscopic | E29: 80000 | F29: 13 | G29: 88 | H29: 99.65 | I29: 99.35 | J29: - | K29: - | T29: =ROUNDUP((E29/4999.99)*10,-1) -> 170 | U29: Y | V29: Y | W29: N | X29: N | Y29: =IF(W29="Y",T29,0) -> 0 | Z29: =IF(X29="Y",T29*2,0) -> 0 | AA29: =Y29+Z29 -> 0
A30: 12 | B30: IKN402081 | C30: 13-215 | D30: Infusion Pumps, General-Purpose | E30: 3500 | F30: 5 | G30: 95 | H30: 99.65 | I30: 99.68 | J30: 99.330998 | K30: 98.99 | T30: =ROUNDUP((E30/4999.99)*10,-1) -> 10 | U30: N | V30: N | W30: N | X30: N | Y30: =IF(W30="Y",T30,0) -> 0 | Z30: =IF(X30="Y",T30*2,0) -> 0 | AA30: =Y30+Z30 -> 0
A31: 13 | B31: IKN401353 | C31: 11-758 | D31: Radiographic/Fluoroscopic Units, Mobile | E31: 399000 | F31: 10 | G31: 88 | H31: 99.65 | I31: - | J31: - | K31: - | T31: =ROUNDUP((E31/4999.99)*10,-1) -> 800 | U31: N | V31: N | W31: N | X31: N | Y31: =IF(W31="Y",T31,0) -> 0 | Z31: =IF(X31="Y",T31*2,0) -> 0 | AA31: =Y31+Z31 -> 0
A32: 14 | B32: IKN400422 | C32: 13-215 | D32: Infusion Pumps, General-Purpose | E32: 10825 | F32: 13 | G32: 88 | H32: 99.65 | I32: 99.68 | J32: 99.330998 | K32: 98.87 | T32: =ROUNDUP((E32/4999.99)*10,-1) -> 30 | U32: Y | V32: N | W32: N | X32: N | Y32: =IF(W32="Y",T32,0) -> 0 | Z32: =IF(X32="Y",T32*2,0) -> 0 | AA32: =Y32+Z32 -> 0 | AB32: RW
A33: 15 | B33: IKN400482 | C33: 13-215 | D33: Infusion Pumps, General-Purpose | E33: 10825 | F33: 13 | G33: 88 | H33: 99.65 | I33: 99.61 | J33: - | K33: - | T33: =ROUNDUP((E33/4999.99)*10,-1) -> 30 | U33: N | V33: N | W33: N | X33: N | Y33: =IF(W33="Y",T33,0) -> 0 | Z33: =IF(X33="Y",T33*2,0) -> 0 | AA33: =Y33+Z33 -> 0
A34: 16 | B34: IKN400782 | C34: 17-679 | D34: Laser Imagers | E34: 83100 | F34: 13 | G34: 85 | H34: 99.65 | I34: 99.51 | J34: - | K34: - | T34: =ROUNDUP((E34/4999.99)*10,-1) -> 170 | U34: N | V34: N | W34: N | X34: N | Y34: =IF(W34="Y",T34,0) -> 0 | Z34: =IF(X34="Y",T34*2,0) -> 0 | AA34: =Y34+Z34 -> 0
A35: 17 | B35: IKN400653 | C35: 16-173 | D35: Sphygmomanometers, Electronic, Automatic | E35: 4510 | F35: 12 | G35: 88 | H35: - | I35: 99.8 | J35: 99.385529 | K35: 99.37 | T35: =ROUNDUP((E35/4999.99)*10,-1) -> 10 | U35: N | V35: N | W35: N | X35: N | Y35: =IF(W35="Y",T35,0) -> 0 | Z35: =IF(X35="Y",T35*2,0) -> 0 | AA35: =Y35+Z35 -> 0
A36: 18 | B36: IKN400171 | C36: 17-429 | D36: Ventilators, Intensive Care | E36: 151560 | F36: 12 | G36: 88 | H36: - | I36: 99.78 | J36: 99.425417 | K36: 99.08 | T36: =ROUNDUP((E36/4999.99)*10,-1) -> 310 | U36: N | V36: N | W36: N | X36: N | Y36: =IF(W36="Y",T36,0) -> 0 | Z36: =IF(X36="Y",T36*2,0) -> 0 | AA36: =Y36+Z36 -> 0
A37: 19 | B37: IKN400168 | C37: 17-429 | D37: Ventilators, Intensive Care | E37: 151560 | F37: 12 | G37: 88 | H37: - | I37: 99.9 | J37: 99.550176 | K37: 99.21 | T37: =ROUNDUP((E37/4999.99)*10,-1) -> 310 | U37: Y | V37: Y | W37: N | X37: N | Y37: =IF(W37="Y",T37,0) -> 0 | Z37: =IF(X37="Y",T37*2,0) -> 0 | AA37: =Y37+Z37 -> 0
A38: 20 | B38: IKN402184 | C38: 12-647 | D38: Physiologic Monitoring Systems, Acute Care | E38: 100000 | F38: 2 | G38: 99 | H38: - | I38: - | J38: 99.677138 | K38: 99.5 | T38: =ROUNDUP((E38/4999.99)*10,-1) -> 210 | U38: N | V38: N | W38: N | X38: N | Y38: =IF(W38="Y",T38,0) -> 0 | Z38: =IF(X38="Y",T38*2,0) -> 0 | AA38: =Y38+Z38 -> 0
A39: 21 | B39: IKN400787 | C39: 13-272 | D39: Radiographic Units, Mobile | E39: 1149550 | F39: 13 | G39: 88 | H39: - | I39: - | J39: 99.824328 | K39: 99.48 | T39: =ROUNDUP((E39/4999.99)*10,-1) -> 2300 | U39: N | V39: N | W39: N | X39: N | Y39: =IF(W39="Y",T39,0) -> 0 | Z39: =IF(X39="Y",T39*2,0) -> 0 | AA39: =Y39+Z39 -> 0
A40: 22 | B40: IKN400937 | C40: 16-173 | D40: Sphygmomanometers, Electronic, Automatic | E40: 336 | F40: 13 | G40: 88 | H40: - | I40: - | J40: 99.916396 | K40: 99.58 | T40: =ROUNDUP((E40/4999.99)*10,-1) -> 10 | U40: Y | V40: N | W40: N | X40: N | Y40: =IF(W40="Y",T40,0) -> 0 | Z40: =IF(X40="Y",T40*2,0) -> 0 | AA40: =Y40+Z40 -> 0
A41: 23 | B41: IKN401007 | C41: 15-999 | D41: Washers, Flexible Endoscope | E41: 126300 | F41: 13 | G41: 85 | H41: - | I41: - | J41: 99.925846 | K41: 99.59 | T41: =ROUNDUP((E41/4999.99)*10,-1) -> 260 | U41: N | V41: N | W41: N | X41: N | Y41: =IF(W41="Y",T41,0) -> 0 | Z41: =IF(X41="Y",T41*2,0) -> 0 | AA41: =Y41+Z41 -> 0
A42: 24 | B42: IKN400293 | C42: 17-148 | D42: Oximeters, Pulse | E42: 5410 | F42: 13 | G42: 88 | H42: - | I42: - | J42: 99.935425 | K42: 99.93 | T42: =ROUNDUP((E42/4999.99)*10,-1) -> 20 | U42: Y | V42: N | W42: N | X42: N
A43: 25 | B43: IKN400029 | C43: 12-647 | D43: Physiologic Monitoring Systems, Acute Care | E43: 105850 | F43: 13 | G43: 88 | H43: - | I43: - | J43: 99.946764 | K43: 99.95 | T43: =ROUNDUP((E43/4999.99)*10,-1) -> 220 | U43: N | V43: N | W43: N | X43: N | Y43: =IF(W43="Y",T43,0) -> 0 | Z43: =IF(X43="Y",T43*2,0) -> 0 | AA43: =Y43+Z43 -> 0
A44: 26 | B44: IKN400722 | C44: 15-104 | D44: Analyzers, Laboratory, Hematology, Platelet Aggregation | E44: 42100 | F44: 13 | G44: 85 | H44: - | I44: - | J44: 99.981897 | K44: 99.91 | T44: =ROUNDUP((E44/4999.99)*10,-1) -> 90 | U44: N | V44: N | W44: N | X44: N | Y44: =IF(W44="Y",T44,0) -> 0 | Z44: =IF(X44="Y",T44*2,0) -> 0 | AA44: =Y44+Z44 -> 0
A45: 27 | B45: IKN400200 | C45: 18-147 | D45: Mattress Systems, Alternating-Pressure | E45: 28630 | F45: 13 | G45: 85 | H45: - | I45: - | J45: - | K45: 99.664774 | T45: =ROUNDUP((E45/4999.99)*10,-1) -> 60 | U45: N | V45: N | W45: N | X45: N | Y45: =IF(W45="Y",T45,0) -> 0 | Z45: =IF(X45="Y",T45*2,0) -> 0 | AA45: =Y45+Z45 -> 0
A46: 28 | B46: IKN402139 | C46: 15-073 | D46: Bronchoscopes, Flexible | E46: 58000 | F46: 4 | G46: 96 | H46: - | I46: - | J46: - | K46: 99.732224 | T46: =ROUNDUP((E46/4999.99)*10,-1) -> 120 | U46: N | V46: N | W46: N | X46: N | Y46: =IF(W46="Y",T46,0) -> 0 | Z46: =IF(X46="Y",T46*2,0) -> 0 | AA46: =Y46+Z46 -> 0
A47: 29 | B47: IKN400973 | C47: 13-469 | D47: Scanning Systems, Computed Tomography | E47: 3557530 | F47: 13 | G47: 85 | H47: - | I47: - | J47: - | K47: 99.765565 | T47: =ROUNDUP((E47/4999.99)*10,-1) -> 7120 | U47: N | V47: N | W47: N | X47: N | Y47: =IF(W47="Y",T47,0) -> 0 | Z47: =IF(X47="Y",T47*2,0) -> 0 | AA47: =Y47+Z47 -> 0
A48: 30 | B48: IKN401261 | C48: 18-147 | D48: Mattress Systems, Alternating-Pressure | E48: 28630 | F48: 13 | G48: 85 | H48: - | I48: - | J48: - | K48: 99.963397 | T48: =ROUNDUP((E48/4999.99)*10,-1) -> 60 | U48: N | V48: N | W48: N | X48: N | Y48: =IF(W48="Y",T48,0) -> 0 | Z48: =IF(X48="Y",T48*2,0) -> 0 | AA48: =Y48+Z48 -> 0
A49: 31 | B49: IKN400762 | C49: 17-916 | D49: Analyzers, Laboratory, Immunoassay, Chemiluminescent | E49: 1443450 | F49: 13 | G49: 85 | H49: - | I49: - | J49: - | K49: 99.767538 | T49: =ROUNDUP((E49/4999.99)*10,-1) -> 2890 | U49: N | V49: N | W49: N | X49: N | Y49: =IF(W49="Y",T49,0) -> 0 | Z49: =IF(X49="Y",T49*2,0) -> 0 | AA49: =Y49+Z49 -> 0
A50: 32 | B50: IKN400565 | C50: 12-649 | D50: Physiologic Monitoring Systems, Stress Exercise | E50: 138350 | F50: 13 | G50: 88 | H50: - | I50: - | J50: - | K50: 99.97013 | T50: =ROUNDUP((E50/4999.99)*10,-1) -> 280 | U50: N | V50: N | W50: N | X50: N | Y50: =IF(W50="Y",T50,0) -> 0 | Z50: =IF(X50="Y",T50*2,0) -> 0 | AA50: =Y50+Z50 -> 0
A51: 33 | B51: IKN401353 | C51: 11-758 | D51: Radiographic/Fluoroscopic Units, Mobile | E51: 399000 | F51: 10 | G51: 88 | H51: - | I51: - | J51: - | K51: 99.970764 | T51: =ROUNDUP((E51/4999.99)*10,-1) -> 800 | U51: N | V51: N | W51: N | X51: N | Y51: =IF(W51="Y",T51,0) -> 0 | Z51: =IF(X51="Y",T51*2,0) -> 0 | AA51: =Y51+Z51 -> 0
A52: 34 | B52: IKN400758 | C52: 16-378 | D52: Analyzers, Laboratory, Urine, Automated | E52: 36080 | F52: 13 | G52: 85 | H52: - | I52: - | J52: - | K52: 99.984552 | T52: =ROUNDUP((E52/4999.99)*10,-1) -> 80 | U52: N | V52: N | W52: N | X52: N | Y52: =IF(W52="Y",T52,0) -> 0 | Z52: =IF(X52="Y",T52*2,0) -> 0 | AA52: =Y52+Z52 -> 0
A53: 35 | B53: IKN401071 | C53: 18-034 | D53: Video Image Processors, Endoscopic | E53: 80000 | F53: 13 | G53: 88 | H53: - | I53: - | J53: - | K53: 99.996679 | T53: =ROUNDUP((E53/4999.99)*10,-1) -> 170 | U53: N | V53: N | W53: N | X53: N | Y53: =IF(W53="Y",T53,0) -> 0 | Z53: =IF(X53="Y",T53*2,0) -> 0 | AA53: =Y53+Z53 -> 0
A54: TOTAL DEDUCTION FOR IND. B.4: | AA54: =SUM(AA19:AA34) -> 0
I102: 0 days, 1 hrs, 8 mins | K102: 31-Mar-2026 09:30:00 | L102: 31-Mar-2026 10:00:00 | V102: M-REPLACE NEW BATTERY ,UNIT TEST FUNCTIONING WELL. UNIT PROPOSE TO BER DUE TO AUDATED TECHNOLOGY
V105: PO : ETA :
V106: CHARGER FAULTY WAITING PARTS FROM VENDOR (B BROUN) PO : ETA :
V107: LCD BOARD FAULTY WAITING PARTS FROM VENDOR PO : ETA :
