Workbook
Name _05_04_2009: #REF!
Name _05_04_2009: #REF!
Name _05_04_2009: #REF!
Name _05_04_2009: #REF!
Name _05_04_2009: #REF!
Name a: '[1]Term Outstanding Payment'!#REF!
Name a: '[1]Term Outstanding Payment'!#REF!
Name a: '[1]Term Outstanding Payment'!#REF!
Name a: '[1]Term Outstanding Payment'!#REF!
Name a: '[1]Term Outstanding Payment'!#REF!
Name AA: #REF!
Name AA: #REF!
Name AA: #REF!
Name AA: #REF!
Name AA: #REF!
Name aaa: #REF!
Name aaa: #REF!
Name aaa: #REF!
Name aaa: #REF!
Name aaa: #REF!
Name aaaaa: #REF!
Name aaaaa: #REF!
Name aaaaa: #REF!
Name aaaaa: #REF!
Name aaaaa: #REF!
Name aaaaaaaaaa: #REF!
Name aaaaaaaaaa: #REF!
Name aaaaaaaaaa: #REF!
Name aaaaaaaaaa: #REF!
Name AAAAAAAAAAAAA: #REF!
Name AAAAAAAAAAAAA: #REF!
Name AAAAAAAAAAAAA: #REF!
Name AAAAAAAAAAAAA: #REF!
Name AAAAAAAAAAAAAAAAAA: #REF!
Name AAAAAAAAAAAAAAAAAA: #REF!
Name AAAAAAAAAAAAAAAAAA: #REF!
Name AAAAAAAAAAAAAAAAAA: #REF!
Name AAAAAAAAAAAAAAAAAAAAA: #REF!
Name AAAAAAAAAAAAAAAAAAAAA: #REF!
Name AAAAAAAAAAAAAAAAAAAAA: #REF!
Name AAAAAAAAAAAAAAAAAAAAA: #REF!
Name AAAAAAAAAAAAAAAAAAAAAAAAAAA: #REF!
Name AAAAAAAAAAAAAAAAAAAAAAAAAAA: #REF!
Name AAAAAAAAAAAAAAAAAAAAAAAAAAA: #REF!
Name AAAAAAAAAAAAAAAAAAAAAAAAAAA: #REF!
Name AAAAAAAAAAAAAAAAAAAAAAAAAAAA: #REF!
Name AAAAAAAAAAAAAAAAAAAAAAAAAAAA: #REF!
Name AAAAAAAAAAAAAAAAAAAAAAAAAAAA: #REF!
Name AAAAAAAAAAAAAAAAAAAAAAAAAAAA: #REF!
Name AAAAAAAAAAAAAAAAAAAAAAAAAAAAAA: #REF!
Name AAAAAAAAAAAAAAAAAAAAAAAAAAAAAA: #REF!
Name AAAAAAAAAAAAAAAAAAAAAAAAAAAAAA: #REF!
Name AAAAAAAAAAAAAAAAAAAAAAAAAAAAAA: #REF!
Name AAAAAAAAAAAAAAAAAAAAAAAAAAAAAAA: #REF!
Name AAAAAAAAAAAAAAAAAAAAAAAAAAAAAAA: #REF!
Name AAAAAAAAAAAAAAAAAAAAAAAAAAAAAAA: #REF!
Name AAAAAAAAAAAAAAAAAAAAAAAAAAAAAAA: #REF!
Name AAAAAAAAAAAAAAAAAAAAAAAAAAAAAAAAA: #REF!
Name AAAAAAAAAAAAAAAAAAAAAAAAAAAAAAAAA: #REF!
Name AAAAAAAAAAAAAAAAAAAAAAAAAAAAAAAAA: #REF!

Sheet BEMSdar
A1: MINISTRY OF HEALTH
A2: Deduction Mapping Report Biomedical Engineering Maintenance Services (BEMS)
D5: HOSPITAL NAME : | E5: Institut Kanser Negara | I5: STATE: | J5: W.P. Putrajaya
D7: MONTH/YEAR : | E7: 46143 | I7: COMPANY: | J7: Ambang Wira Sdn Bhd
A9: MONTHLY SERVICE FEE (RM) : | E9: 1363910.9
A11: BEMS MONTHLY FEE (RM) @ 97.5% : | E11: =97.5%*E9 -> 1329813.2
A13: FMS MONTHLY FEE (RM) @ 2.5% : | E13: =2.5%*E9 -> 34097.773
A17: No | B17: Key Deduction Indicators | I17: Frequency | L17: Deduction Value (RM) | N17: Deduction % | O17: Performance Level (%)
A19: B.1 | B19: All service requests shall be responded by the Company’s trained technical personal within the timeframe as stipulated in the Agreement. | I19: Per event | L19: 0 | N19: 0 | O19: =100-N19 -> 100
A20: B.2 | B20: All unscheduled maintenance works including relevant maintenance calibration, safety tests and functional checks shall be completed within seven (7) working days. | I20: Per day | L20: ='B1&B2 UNSCHEDULED'!U106 -> 13280 | N20: =L20/$E$11% -> 0.99863653 | O20: =100-N20 -> 99.001363
A21: B.3 | B21: Scheduled maintenance shall be carried out as per schedule and according to the procedure as specified in the Agreement. Scheduled maintenance shall include complete safety and performance tests. | I21: Per event | L21: ='B3-SCHEDULED'!L216 -> 0 | N21: =L21/$E$11% -> 0 | O21: =100-N21 -> 100
A22: B.4 | B22: All biomedical equipment shall be functioning and maintained to ensure uptime target as specified in the TRKPI are met. | I22: Per event | L22: 0 | N22: =L22/$E$11% -> 0 | O22: =100-N22 -> 100
A23: B.5 | B23: T&C and Warranty Management of newly introduced biomedical shall be managed and performed according to the Agreement and related acts, standards and regulations. | I23: Per event | L23: ='B5-T&C'!O24 -> 0 | N23: =L23/$E$11% -> 0 | O23: =100-N23 -> 100
A24: Total | L24: =SUM(L19:M23) -> 13280 | N24: =SUM(N19:N23) -> 0.99863653 | O24: =100-N24 -> 99.001363
C27: Prepared by: | I27: Verified by:
C31: Siti Norsaliana Binti Abu Khalid | I31: Mohd Shahrulnizam bin Tarmizi
C32: Head of BEMS | I32: Facility Manager
C33: Ambang Wira Sdn Bhd- Institut Kanser Negara | I33: Ambang Wira Sdn Bhd- Institut Kanser Negara
C34: Date: | I34: Date:

Sheet B1&B2 UNSCHEDULED
A2: MINISTRY OF HEALTH
A3: Deduction Mapping Report Biomedical Engineering Maintenance Services (BEMS)
A4: INDICATOR B.1 RESPONSE TIME & B.2 REPAIR TIME
A6: HOSPITAL NAME: | C6: INSTITUT KANSER NEGARA | I6: FIRST DATE OF THE MONTH : | M6: 46143 | Q6: (For Calculation)
A8: STATE: | C8: WILAYAH PERSEKUTUAN PUTRAJAYA | I8: LAST DATE OF THE MONTH : | M8: 46173 | Q8: (For Calculation)
A10: COMPANY: | C10: AMBANG WIRA SDN BHD | I10: BEMS MONTHLY FEE (RM) @ 97.5% : | M10: =BEMSdar!E11 -> 1329813.2
A12: MONTH/YEAR: | C12: 46143 | I12: FMS MONTHLY FEE (RM) @ 2.5% : | M12: =BEMSdar!E13 -> 34097.773
A14: Notes:
A15: 1) Deduction Ringgit Equivalent is based on Appendix 11 of the Agreement, Section B3 Key Deduction Indicators for BEMS
A16: 2) Deduction Value for Indicator B.1 is Deduction Ringgit Equivalent (per event)
A17: 3) Total Repair Time includes weekend & public holiday
A18: 4) Demerit Point for Indicator B.2 is calculated based on completion date against request date, less by 7 working days
A19: 5) Deduction Value for Indicator B.2 is Demerit Point multiply by Deduction Ringgit Equivalent
A21: No | B21: Asset No | C21: Asset Description | D21: Asset Purchase Price (RM) | E21: Work Order No. | F21: User Location | G21: Work Order/ Complaint Details | H21: Response Category (Emergency/ Normal) | I21: Total Response Time (minutes) | J21: Work Request Date | K21: Response Time (Minutes) | L21: Work Completion Date | M21: Deduction Ringgit Equivalent (RM) | N21: Indicator B.1 | Q21: Indicator B.2
N22: Validate Status (Y/N) | O22: Deduction Value (RM) | P22: Remarks/ Exemption | Q22: Validate Status (Y/N) | R22: Total Repair Time (day) | S22: Last date of 7 working days (dd/mm/yy) | T22: Demerit Point | U22: Deduction Value (RM) | V22: Remarks/ Exemption
A23: Current Month (Work Order Completed)
A24: 1 | B24: IKN400755 | C24: =VLOOKUP(B24,[13]AssetDetails_UEM!$A$3:$AH$1849,6,FALSE) -> Analyzers, Laboratory, Hematology, Coagulation, Automated | D24: =VLOOKUP(B24,[13]AssetDetails_UEM!$A$3:$AK$1849,22,FALSE) -> 105860 | E24: IKNWIBE26008258 | F24: 04LA132 | G24: MESIN ACL ELITE PRO ALARM SAMPLE LEVEL LOW - PATOLOGI ARAS 4 | H24: Normal | I24: 0 days, 0 hrs, 20 mins | J24: 02-May-2026 09:40:00 | K24: 02-May-2026 10:00:00 | L24: 08-May-2026 11:00:00 | M24: =IF(D24>44999.99,100,ROUNDUP((D24/4999.99)*10,-1)) -> 100 | N24: N | O24: ='[14]B1& B2 UNSCHEDULED'!$O$24 -> 0 | Q24: N | R24: 6 | S24: =WORKDAY(J24,6,AKHIR) -> 46153 | T24: 0 | U24: =IF(Q24="N",0,M24*T24) -> 0 | V24: M-RUN CALIBRATION , QC, ALLIGNMENT THE PROBE, TEST FUNCTIONING OK
A25: 2 | B25: IKN400342 | C25: =VLOOKUP(B25,[13]AssetDetails_UEM!$A$3:$AH$1849,6,FALSE) -> Mattress Systems, Alternating-Pressure | D25: =VLOOKUP(B25,[13]AssetDetails_UEM!$A$3:$AK$1849,22,FALSE) -> 28630 | E25: IKNWIBE26008371 | F25: 07WF121 | G25: RIPPLE MATTRESS CONNECTOR TUBING ROSAK - WAD 7B | H25: Normal | I25: 0 days, 0 hrs, 5 mins | J25: 04-May-2026 20:40:00 | K25: 04-May-2026 20:45:00 | L25: 05-May-2026 19:30:00 | M25: =IF(D25>44999.99,100,ROUNDUP((D25/4999.99)*10,-1)) -> 60 | N25: N | O25: ='[14]B1& B2 UNSCHEDULED'!$O$24 -> 0 | Q25: N | R25: =IF(L25="",AKHIR-J25,L25-J25+1) -> 1.9513889 | S25: =WORKDAY(J25,6,AKHIR) -> 46154 | T25: 0 | U25: =IF(Q25="N",0,M25*T25) -> 0 | V25: L, QE:12-RE -SEAT CONNECTOR HOSE , MONITORING FOR 1 DAY TESTED OKAY
A26: 3 | B26: IKN400965 | C26: =VLOOKUP(B26,[13]AssetDetails_UEM!$A$3:$AH$1849,6,FALSE) -> Linear Accelerators | D26: =VLOOKUP(B26,[13]AssetDetails_UEM!$A$3:$AK$1849,22,FALSE) -> 19351760 | E26: IKNWIBE26008469 | F26: 01RT177 | G26: MACHINE TOMOTHERAPHY MLC PROBLEM- RT | H26: Normal | I26: 0 days, 0 hrs, 3 mins | J26: 05-May-2026 16:37:00 | K26: 05-May-2026 16:40:00 | L26: 05-May-2026 21:00:00 | M26: =IF(D26>44999.99,100,ROUNDUP((D26/4999.99)*10,-1)) -> 100 | N26: N | O26: ='[14]B1& B2 UNSCHEDULED'!$O$24 -> 0 | Q26: N | R26: =IF(L26="",AKHIR-J26,L26-J26+1) -> 1.1826389 | S26: =WORKDAY(J26,6,AKHIR) -> 46155 | T26: 0 | U26: =IF(Q26="N",0,M26*T26) -> 0 | V26: L, QE:12-REPLACED WITH NEW UPS BATTERIES AND TESTED PDU TURNED ON UNIT LEFT
A27: 4 | B27: IKN400231 | C27: =VLOOKUP(B27,[13]AssetDetails_UEM!$A$3:$AH$1849,6,FALSE) -> Infusion Pumps, General-Purpose | D27: =VLOOKUP(B27,[13]AssetDetails_UEM!$A$3:$AK$1849,22,FALSE) -> 10825 | E27: IKNWIBE26008530 | F27: 09WJ126 | G27: MACHINE INFUSION PUMP BUTTON WARNA HIJAU PATAH- WAD 9A | H27: Normal | I27: 0 days, 0 hrs, 12 mins | J27: 06-May-2026 10:48:00 | K27: 46148.458 | L27: 46149.396 | M27: =IF(D27>44999.99,100,ROUNDUP((D27/4999.99)*10,-1)) -> 30 | N27: N | O27: ='[14]B1& B2 UNSCHEDULED'!$O$24 -> 0 | Q27: N | R27: =IF(L27="",AKHIR-J27,L27-J27+1) -> 1.9458333 | S27: =WORKDAY(J27,6,AKHIR) -> 46156 | T27: 0 | U27: =IF(Q27="N",0,M27*T27) -> 0 | V27: NO PHYSICAL DAMAGE ON UNIT, USER MISSUNDERTAND THE LOCK ON IV LINE AS A PART OF THE MACHINE. UNIT OK
A28: 5 | B28: IKN400366 | C28: =VLOOKUP(B28,[13]AssetDetails_UEM!$A$3:$AH$1849,6,FALSE) -> Infusion Pumps, General-Purpose | D28: =VLOOKUP(B28,[13]AssetDetails_UEM!$A$3:$AK$1849,22,FALSE) -> 10825 | E28: IKNWIBE26008551 | F28: 07WE113 | G28: WAYAR CHARGER INFUSION PUMP TERCABUT- WAD 7A | H28: Normal | I28: 0 days, 0 hrs, 9 mins | J28: 06-May-2026 17:24:00 | K28: 46148.733 | L28: 14-May-2026 11:30:00 | M28: =IF(D28>44999.99,100,ROUNDUP((D28/4999.99)*10,-1)) -> 30 | N28: N | O28: ='[14]B1& B2 UNSCHEDULED'!$O$24 -> 0 | Q28: N | R28: 7 | S28: =WORKDAY(J28,6,AKHIR) -> 46156 | T28: 0 | U28: =IF(Q28="N",0,M28*T28) -> 0 | V28: L, QE:12-REPLACE NEW CHARGER , TESTED AND ABLE TO CHANGE THE MACHINE
A29: 6 | B29: IKN400288 | C29: =VLOOKUP(B29,[13]AssetDetails_UEM!$A$3:$AH$1849,6,FALSE) -> Infusion Pumps, General-Purpose | D29: =VLOOKUP(B29,[13]AssetDetails_UEM!$A$3:$AK$1849,22,FALSE) -> 10825 | E29: IKNWIBE26008552 | F29: 08WH121 | G29: MACHINE INFUSION PUMP ROSAK (ERROR 2035)- WAD 8B | H29: Normal | I29: 0 days, 0 hrs, 41 mins | J29: 06-May-2026 17:49:00 | K29: 06-May-2026 18:30:00 | L29: 08-May-2026 18:45:00 | M29: =IF(D29>44999.99,100,ROUNDUP((D29/4999.99)*10,-1)) -> 30 | N29: N | O29: ='[14]B1& B2 UNSCHEDULED'!$O$24 -> 0 | Q29: N | R29: =IF(L29="",AKHIR-J29,L29-J29+1) -> 3.0388889 | S29: =WORKDAY(J29,6,AKHIR) -> 46156 | T29: 0 | U29: =IF(Q29="N",0,M29*T29) -> 0 | V29: L, QE:10-REPAIR MACHINE CLEAN THE MOTOR DRIVER,ROTATE CLOCKWISE, CLEAN USING CONTACT CLEANER , MAKE SURE MOTOR FUNCTIONING WELL, TEST MACHINE PASSER, MOTOR DRIVER FUNCTIONING WELL, DOOR CLOSE WELL , UNIT READY FOR USE
A30: 7 | B30: IKN400956 | C30: =VLOOKUP(B30,[13]AssetDetails_UEM!$A$3:$AH$1849,6,FALSE) -> Linear Accelerators | D30: =VLOOKUP(B30,[13]AssetDetails_UEM!$A$3:$AK$1849,22,FALSE) -> 21961900 | E30: IKNWIBE26008603 | F30: 01RT172 | G30: SPEAKER MACHINE NOVALIS ROSAK- RT | H30: Normal | I30: 0 days, 0 hrs, 21 mins | J30: 07-May-2026 08:09:00 | K30: 07-May-2026 08:30:00 | L30: 07-May-2026 18:00:00 | M30: =IF(D30>44999.99,100,ROUNDUP((D30/4999.99)*10,-1)) -> 100 | N30: N | O30: ='[14]B1& B2 UNSCHEDULED'!$O$24 -> 0 | Q30: N | R30: =IF(L30="",AKHIR-J30,L30-J30+1) -> 1.4104167 | S30: =WORKDAY(J30,6,AKHIR) -> 46157 | T30: 0 | U30: =IF(Q30="N",0,M30*T30) -> 0 | V30: L, QE:1- REPLACED WHOLE SYSTEM SPEAKER AND TESTED OKAY . UNIT LEFT WITH GOOD WORKING CONDITION
A31: 8 | B31: IKN400199 | C31: =VLOOKUP(B31,[13]AssetDetails_UEM!$A$3:$AH$1849,6,FALSE) -> Mattress Systems, Alternating-Pressure | D31: =VLOOKUP(B31,[13]AssetDetails_UEM!$A$3:$AK$1849,22,FALSE) -> 28630 | E31: IKNWIBE26008698 | F31: 09WJ130 | G31: RIPPLE MATTRESS TIDAK KEMBANG- WAD 9A (ASSET NUM: NB355553) | H31: Normal | I31: 0 days, 0 hrs, 29 mins | J31: 08-May-2026 13:31:00 | K31: 08-May-2026 14:00:00 | L31: 08-May-2026 17:00:00 | M31: =IF(D31>44999.99,100,ROUNDUP((D31/4999.99)*10,-1)) -> 60 | N31: N | O31: ='[14]B1& B2 UNSCHEDULED'!$O$24 -> 0 | Q31: N | R31: =IF(L31="",AKHIR-J31,L31-J31+1) -> 1.1451389 | S31: =WORKDAY(J31,6,AKHIR) -> 46160 | T31: 0 | U31: =IF(Q31="N",0,M31*T31) -> 0 | V31: L, QE:12-TIGHTEN TUBING , MAKE SURE NO LEAKING , TEST MATTRESS PASSED, UNIT READY FOR USE
A32: 9 | B32: IKN400198 | C32: =VLOOKUP(B32,[13]AssetDetails_UEM!$A$3:$AH$1849,6,FALSE) -> Mattress Systems, Alternating-Pressure | D32: =VLOOKUP(B32,[13]AssetDetails_UEM!$A$3:$AK$1849,22,FALSE) -> 28630 | E32: IKNWIBE26008699 | F32: 09WJ126 | G32: RIPPLE MATTRESS TIDAK KEMBANG- WAD 9A | H32: Normal | I32: 0 days, 0 hrs, 26 mins | J32: 08-May-2026 14:49:00 | K32: 08-May-2026 15:15:00 | L32: 08-May-2026 16:15:00 | M32: =IF(D32>44999.99,100,ROUNDUP((D32/4999.99)*10,-1)) -> 60 | N32: N | O32: ='[14]B1& B2 UNSCHEDULED'!$O$24 -> 0 | Q32: N | R32: =IF(L32="",AKHIR-J32,L32-J32+1) -> 1.0597222 | S32: =WORKDAY(J32,6,AKHIR) -> 46160 | T32: 0 | U32: =IF(Q32="N",0,M32*T32) -> 0 | V32: L, QE:12-TIGHTEN TUBING , MAKE SURE NO LEAKING , TEST MATTRESS PASSED, UNIT FULLY INFLATE AND READY FOR USE
A33: 10 | B33: IKN402180 | C33: =VLOOKUP(B33,[13]AssetDetails_UEM!$A$3:$AH$1849,6,FALSE) -> Scanning Systems, Computed Tomography/ Positron Emission Tomography | D33: =VLOOKUP(B33,[13]AssetDetails_UEM!$A$3:$AK$1849,22,FALSE) -> 3413750 | E33: IKNWIBE26008704 | F33: 03NM158 | G33: ENHANCED QC FAILED- KLINIK NUKLEAR | H33: Normal | I33: 0 days, 0 hrs, 10 mins | J33: 08-May-2026 11:00:00 | K33: 08-May-2026 11:10:00 | L33: 08-May-2026 17:00:00 | M33: =IF(D33>44999.99,100,ROUNDUP((D33/4999.99)*10,-1)) -> 100 | N33: N | O33: ='[14]B1& B2 UNSCHEDULED'!$O$24 -> 0 | Q33: N | R33: =IF(L33="",AKHIR-J33,L33-J33+1) -> 1.25 | S33: =WORKDAY(J33,6,AKHIR) -> 46160 | T33: 0 | U33: =IF(Q33="N",0,M33*T33) -> 0 | V33: L, QE:12- VENDOR TROUBLESHOOT RUN DETECTOR CALIBRATION AND CREATED NEW MAP FOR CO57 FLOOD FOURCE , UNIT FUNCTIONING OKAY
A34: 11 | B34: IKN400267 | C34: =VLOOKUP(B34,[13]AssetDetails_UEM!$A$3:$AH$1849,6,FALSE) -> Sphygmomanometers, Electronic, Automatic | D34: =VLOOKUP(B34,[13]AssetDetails_UEM!$A$3:$AK$1849,22,FALSE) -> 4510 | E34: IKNWIBE26008805 | F34: 08WG143 | G34: BP CUFF LEAKING- WAD 8A | H34: Normal | I34: 0 days, 0 hrs, 19 mins | J34: 11-May-2026 09:11:00 | K34: 11-May-2026 09:30:00 | L34: 11-May-2026 10:00:00 | M34: =IF(D34>44999.99,100,ROUNDUP((D34/4999.99)*10,-1)) -> 10 | N34: N | O34: ='[14]B1& B2 UNSCHEDULED'!$O$24 -> 0 | Q34: N | R34: =IF(L34="",AKHIR-J34,L34-J34+1) -> 1.0340278 | S34: =WORKDAY(J34,6,AKHIR) -> 46161 | T34: 0 | U34: =IF(Q34="N",0,M34*T34) -> 0 | V34: L, QE:12-TEST UNIT, CUFF INFLATE WELL, UNIT READY FOR USE
A35: 12 | B35: IKN400300 | C35: =VLOOKUP(B35,[13]AssetDetails_UEM!$A$3:$AH$1849,6,FALSE) -> Mattress Systems, Alternating-Pressure | D35: =VLOOKUP(B35,[13]AssetDetails_UEM!$A$3:$AK$1849,22,FALSE) -> 28630 | E35: IKNWIBE26008806 | F35: 08WH121 | G35: RIPPLE MATTRESS ROSAK- WAD 8B | H35: Normal | I35: 0 days, 0 hrs, 21 mins | J35: 11-May-2026 09:39:00 | K35: 11-May-2026 10:00:00 | L35: 11-May-2026 12:00:00 | M35: =IF(D35>44999.99,100,ROUNDUP((D35/4999.99)*10,-1)) -> 60 | N35: N | O35: ='[14]B1& B2 UNSCHEDULED'!$O$24 -> 0 | Q35: N | R35: =IF(L35="",AKHIR-J35,L35-J35+1) -> 1.0979167 | S35: =WORKDAY(J35,6,AKHIR) -> 46161 | T35: 0 | U35: =IF(Q35="N",0,M35*T35) -> 0 | V35: L, QE:12-TIGHTEN TUBING ,UNIT INFLATE OKAY, TEST PASSED, UNIT READY FOR USE, NO LEAKING AT ALL
A36: 13 | B36: IKN402009 | C36: =VLOOKUP(B36,[13]AssetDetails_UEM!$A$3:$AH$1849,6,FALSE) -> Concentrators, Oxygen | D36: =VLOOKUP(B36,[13]AssetDetails_UEM!$A$3:$AK$1849,22,FALSE) -> 3400 | E36: IKNWIBE26009008 | F36: 04PC109 | G36: CM- REQ FOR PERFORMANCE CHECK | H36: Corrective Maintenance (CM) | I36: 0 days, 0 hrs, 10 mins | J36: 11-May-2026 16:00:00 | K36: 11-May-2026 16:10:00 | L36: 11-May-2026 17:10:00 | M36: =IF(D36>44999.99,100,ROUNDUP((D36/4999.99)*10,-1)) -> 10 | N36: N | O36: ='[14]B1& B2 UNSCHEDULED'!$O$24 -> 0 | Q36: N | R36: =IF(L36="",AKHIR-J36,L36-J36+1) -> 1.0486111 | S36: =WORKDAY(J36,6,AKHIR) -> 46161 | T36: 0 | U36: =IF(Q36="N",0,M36*T36) -> 0 | V36: AN- DONE PERFORMANCE CHECKING AS PER CHECKLIST ATTACHED
A37: 14 | B37: IKN402187 | C37: =VLOOKUP(B37,[13]AssetDetails_UEM!$A$3:$AH$1849,6,FALSE) -> Ultrasound | D37: 164800 | E37: IKNWIBE26009013 | F37: 03ID162 | G37: CM- MONITOR FAULTY | H37: Corrective Maintenance (CM) | I37: 0 days, 0 hrs, 5 mins | J37: 11-May-2026 14:00:00 | K37: 11-May-2026 14:05:00 | L37: 11-May-2026 16:00:00 | M37: =IF(D37>44999.99,100,ROUNDUP((D37/4999.99)*10,-1)) -> 100 | N37: N | O37: ='[14]B1& B2 UNSCHEDULED'!$O$24 -> 0 | Q37: N | R37: =IF(L37="",AKHIR-J37,L37-J37+1) -> 1.0833333 | S37: =WORKDAY(J37,6,AKHIR) -> 46161 | T37: 0 | U37: =IF(Q37="N",0,M37*T37) -> 0 | V37: L, QE:12-REPLACE NEW MONITOR WARRANTY TESTSED OKAY
A38: 15 | B38: IKN401237 | C38: =VLOOKUP(B38,[13]AssetDetails_UEM!$A$3:$AH$1849,6,FALSE) -> Electrocardiographs, Multichannel, Interpretative | D38: =VLOOKUP(B38,[13]AssetDetails_UEM!$A$3:$AK$1849,22,FALSE) -> 5590.2 | E38: IKNWIBE26009079 | F38: 03NM108 | G38: MACHINE ECG ERROR- KLINIK NUKLEAR | H38: Normal | I38: 0 days, 0 hrs, 16 mins | J38: 12-May-2026 10:59:00 | K38: 12-May-2026 11:15:00 | L38: 12-May-2026 13:00:00 | M38: =IF(D38>44999.99,100,ROUNDUP((D38/4999.99)*10,-1)) -> 20 | N38: N | O38: ='[14]B1& B2 UNSCHEDULED'!$O$24 -> 0 | Q38: N | R38: =IF(L38="",AKHIR-J38,L38-J38+1) -> 1.0840278 | S38: =WORKDAY(J38,6,AKHIR) -> 46162 | T38: 0 | U38: =IF(Q38="N",0,M38*T38) -> 0 | V38: L, QE:12- ADVICE USER TO USE ALL LIMB CLISTO PATIENT FIXED AND ENSURE ALL LIMB CLIP IN GOOD CONDITION , TESTED USING ANALYSER AND TO PERSON OKAY. IU
A39: 16 | B39: IKN402179 | C39: =VLOOKUP(B39,[13]AssetDetails_UEM!$A$3:$AH$1849,6,FALSE) -> Scanning Systems, Computed Tomography/ Positron Emission Tomography | D39: =VLOOKUP(B39,[13]AssetDetails_UEM!$A$3:$AK$1849,22,FALSE) -> 3410390 | E39: IKNWIBE26009088 | F39: 03NM161 | G39: CM- PREDICTIVE MAINTENANCE XELERIS | H39: Corrective Maintenance (CM) | I39: 0 days, 0 hrs, 15 mins | J39: 12-May-2026 10:00:00 | K39: 12-May-2026 10:15:00 | L39: 12-May-2026 13:15:00 | M39: =IF(D39>44999.99,100,ROUNDUP((D39/4999.99)*10,-1)) -> 100 | N39: N | O39: ='[14]B1& B2 UNSCHEDULED'!$O$24 -> 0 | Q39: N | R39: =IF(L39="",AKHIR-J39,L39-J39+1) -> 1.1354167 | S39: =WORKDAY(J39,6,AKHIR) -> 46162 | T39: 0 | U39: =IF(Q39="N",0,M39*T39) -> 0 | V39: L, QE:12-XELAERIS MAINTAINANCE COMPLETE BY VENDOR TESTED OKAY
A40: 17 | B40: IKN402180 | C40: =VLOOKUP(B40,[13]AssetDetails_UEM!$A$3:$AH$1849,6,FALSE) -> Scanning Systems, Computed Tomography/ Positron Emission Tomography | D40: =VLOOKUP(B40,[13]AssetDetails_UEM!$A$3:$AK$1849,22,FALSE) -> 3413750 | E40: IKNWIBE26009089 | F40: 03NM158 | G40: CM- PREDICTIVE MAINTENANCE XELERIS | H40: Corrective Maintenance (CM) | I40: 0 days, 0 hrs, 15 mins | J40: 12-May-2026 10:00:00 | K40: 12-May-2026 10:15:00 | L40: 12-May-2026 16:00:00 | M40: =IF(D40>44999.99,100,ROUNDUP((D40/4999.99)*10,-1)) -> 100 | N40: N | O40: ='[14]B1& B2 UNSCHEDULED'!$O$24 -> 0 | Q40: N | R40: =IF(L40="",AKHIR-J40,L40-J40+1) -> 1.25 | S40: =WORKDAY(J40,6,AKHIR) -> 46162 | T40: 0 | U40: =IF(Q40="N",0,M40*T40) -> 0 | V40: L, QE:12-XELERIS MAINTAINANACE COMPLETE BY VENDOR TEST OKAY
A41: 18 | B41: IKN400007 | C41: =VLOOKUP(B41,[13]AssetDetails_UEM!$A$3:$AH$1849,6,FALSE) -> Physiologic Monitoring Systems, Acute Care | D41: =VLOOKUP(B41,[13]AssetDetails_UEM!$A$3:$AK$1849,22,FALSE) -> 87400 | E41: IKNWIBE26009091 | F41: 01AE118 | G41: MACHINE SPO2 ROSAK- ACCU | H41: Normal | I41: 0 days, 0 hrs, 05 mins | J41: 12-May-2026 13:00:00 | K41: 46154.545 | L41: 46154.562 | M41: =IF(D41>44999.99,100,ROUNDUP((D41/4999.99)*10,-1)) -> 100 | N41: N | O41: ='[14]B1& B2 UNSCHEDULED'!$O$24 -> 0 | Q41: N | R41: =IF(L41="",AKHIR-J41,L41-J41+1) -> 1.0208333 | S41: =WORKDAY(J41,6,AKHIR) -> 46162 | T41: 0 | U41: =IF(Q41="N",0,M41*T41) -> 0 | V41: SPO2 SENSOR CABLE TEAR OFF, REPLACED WITH NEW SPO2 SENSOR AND TESTED PASS.UNIT RETURN WITH FULL FUNCTIONING.
A42: 19 | B42: IKN400446 | C42: =VLOOKUP(B42,[13]AssetDetails_UEM!$A$3:$AH$1849,6,FALSE) -> Infusion Pumps, General-Purpose | D42: =VLOOKUP(B42,[13]AssetDetails_UEM!$A$3:$AK$1849,22,FALSE) -> 10825 | E42: IKNWIBE26009165 | F42: 06WC113 | G42: INFUSION PUMP TIDAK BOLEH CLOSE- WAD 6A | H42: Normal | I42: 0 days, 0 hrs, 39 mins | J42: 13-May-2026 11:21:00 | K42: 13-May-2026 12:00:00 | L42: 13-May-2026 15:00:00 | M42: =IF(D42>44999.99,100,ROUNDUP((D42/4999.99)*10,-1)) -> 30 | N42: N | O42: ='[14]B1& B2 UNSCHEDULED'!$O$24 -> 0 | Q42: N | R42: =IF(L42="",AKHIR-J42,L42-J42+1) -> 1.1520833 | S42: =WORKDAY(J42,6,AKHIR) -> 46163 | T42: 0 | U42: =IF(Q42="N",0,M42*T42) -> 0 | V42: L, QE:12-UNIT CONNECT TO POWER SUPPLY , RESET MACHINE , TEST CLOSER DOOR MACHINE PASSED , UNIT READY FOR USE
A43: 20 | B43: IKN402180 | C43: =VLOOKUP(B43,[13]AssetDetails_UEM!$A$3:$AH$1849,6,FALSE) -> Scanning Systems, Computed Tomography/ Positron Emission Tomography | D43: =VLOOKUP(B43,[13]AssetDetails_UEM!$A$3:$AK$1849,22,FALSE) -> 3413750 | E43: IKNWIBE26009181 | F43: 03NM158 | G43: XELERIS CANNOT BOOT UP- KLINIK PERUBATAN NUKLEAR | H43: Normal | I43: 0 days, 0 hrs, 15 mins | J43: 13-May-2026 14:00:00 | K43: 13-May-2026 14:15:00 | L43: 13-May-2026 15:30:00 | M43: =IF(D43>44999.99,100,ROUNDUP((D43/4999.99)*10,-1)) -> 100 | N43: N | O43: ='[14]B1& B2 UNSCHEDULED'!$O$24 -> 0 | Q43: N | R43: =IF(L43="",AKHIR-J43,L43-J43+1) -> 1.0625 | S43: =WORKDAY(J43,6,AKHIR) -> 46163 | T43: 0 | U43: =IF(Q43="N",0,M43*T43) -> 0 | V43: L, QE:16-VENDOR TROUBLESHOOT PERFORMED LFC AND CONFIGURE TESTED OKAY
A44: 21 | B44: IKN400044 | C44: =VLOOKUP(B44,[13]AssetDetails_UEM!$A$3:$AH$1849,6,FALSE) -> Physiologic Monitoring Systems, Acute Care | D44: =VLOOKUP(B44,[13]AssetDetails_UEM!$A$3:$AK$1849,22,FALSE) -> 119690 | E44: IKNWIBE26009182 | F44: 05IC113 | G44: BP CUFF LEAKING - ICU | H44: Normal | I44: 0 days, 0 hrs, 8 mins | J44: 13-May-2026 15:52:00 | K44: 13-May-2026 16:00:00 | L44: 13-May-2026 16:15:00 | M44: =IF(D44>44999.99,100,ROUNDUP((D44/4999.99)*10,-1)) -> 100 | N44: N | O44: ='[14]B1& B2 UNSCHEDULED'!$O$24 -> 0 | Q44: N | R44: =IF(L44="",AKHIR-J44,L44-J44+1) -> 1.0159722 | S44: =WORKDAY(J44,6,AKHIR) -> 46163 | T44: 0 | U44: =IF(Q44="N",0,M44*T44) -> 0 | V44: L, QE:12-REPLACE NEW CUFF ,AND PULSE OXIMETER PROBE UNIT FUNCTIONING IN GOOD CONDITION
A45: 22 | B45: IKN400348 | C45: =VLOOKUP(B45,[13]AssetDetails_UEM!$A$3:$AH$1849,6,FALSE) -> Physiologic Monitoring Systems, Acute Care | D45: =VLOOKUP(B45,[13]AssetDetails_UEM!$A$3:$AK$1849,22,FALSE) -> 44510 | E45: IKNWIBE26009187 | F45: 07WF121 | G45: CM- REPLACE POWER CORD | H45: Corrective Maintenance (CM) | I45: 0 days, 0 hrs, 10 mins | J45: 13-May-2026 17:00:00 | K45: 13-May-2026 17:10:00 | L45: 13-May-2026 17:40:00 | M45: =IF(D45>44999.99,100,ROUNDUP((D45/4999.99)*10,-1)) -> 90 | N45: N | O45: ='[14]B1& B2 UNSCHEDULED'!$O$24 -> 0 | Q45: N | R45: =IF(L45="",AKHIR-J45,L45-J45+1) -> 1.0277778 | S45: =WORKDAY(J45,6,AKHIR) -> 46163 | T45: 0 | U45: =IF(Q45="N",0,M45*T45) -> 0 | V45: L, QE:16-REPLACE NEW POWER CARD , TESTED AND FUNCTIONING
A46: 23 | B46: IKN401246 | C46: =VLOOKUP(B46,[13]AssetDetails_UEM!$A$3:$AH$1849,6,FALSE) -> Computers, Radiotherapy Planning System | D46: =VLOOKUP(B46,[13]AssetDetails_UEM!$A$3:$AK$1849,22,FALSE) -> 2403940 | E46: IKNWIBE26009257 | F46: 01RT156 | G46: CM- MONACO MONTHLY CHECKING | H46: Normal | I46: 0 days, 0 hrs, 10 mins | J46: 14-May-2026 13:00:00 | K46: 46156.549 | L46: 14-May-2026 14:01:00 | M46: =IF(D46>44999.99,100,ROUNDUP((D46/4999.99)*10,-1)) -> 100 | N46: N | O46: ='[14]B1& B2 UNSCHEDULED'!$O$24 -> 0 | Q46: N | R46: =IF(L46="",AKHIR-J46,L46-J46+1) -> 1.0423611 | S46: =WORKDAY(J46,6,AKHIR) -> 46164 | T46: 0 | U46: =IF(Q46="N",0,M46*T46) -> 0 | V46: L, QE:12- MONTHLY CHECKING DONE AS PER CHECKLIST ATTACHED
A47: 24 | B47: IKN400774 | C47: =VLOOKUP(B47,[13]AssetDetails_UEM!$A$3:$AH$1849,6,FALSE) -> Scanning Systems, Computed Tomography | D47: =VLOOKUP(B47,[13]AssetDetails_UEM!$A$3:$AK$1849,22,FALSE) -> 4605710 | E47: IKNWIBE26009258 | F47: 03ID156 | G47: CM- MYRIAN MONTHLY CHECKING | H47: Corrective Maintenance (CM) | I47: 0 days, 0 hrs, 4 mins | J47: 14-May-2026 12:00:00 | K47: 14-May-2026 12:04:00 | L47: 14-May-2026 14:03:00 | M47: =IF(D47>44999.99,100,ROUNDUP((D47/4999.99)*10,-1)) -> 100 | N47: N | O47: ='[14]B1& B2 UNSCHEDULED'!$O$24 -> 0 | Q47: N | R47: =IF(L47="",AKHIR-J47,L47-J47+1) -> 1.0854167 | S47: =WORKDAY(J47,6,AKHIR) -> 46164 | T47: 0 | U47: =IF(Q47="N",0,M47*T47) -> 0 | V47: L, QE:12-MAYRIAN MONTHLY CHECKING COMPLETE BY VENDOR
A48: 25 | B48: IKN400878 | C48: =VLOOKUP(B48,[13]AssetDetails_UEM!$A$3:$AH$1849,6,FALSE) -> Concentrators, Oxygen | D48: =VLOOKUP(B48,[13]AssetDetails_UEM!$A$3:$AK$1849,22,FALSE) -> 5000 | E48: IKNWIBE26009263 | F48: 04PC109 | G48: CM- PERFORMANCE CHECK Concentrators, Oxygen | H48: Corrective Maintenance (CM) | I48: 0 days, 0 hrs, 15 mins | J48: 14-May-2026 15:00:00 | K48: 14-May-2026 15:15:00 | L48: 14-May-2026 16:15:00 | M48: =IF(D48>44999.99,100,ROUNDUP((D48/4999.99)*10,-1)) -> 20 | N48: N | O48: ='[14]B1& B2 UNSCHEDULED'!$O$24 -> 0 | Q48: N | R48: =IF(L48="",AKHIR-J48,L48-J48+1) -> 1.0520833 | S48: =WORKDAY(J48,6,AKHIR) -> 46164 | T48: 0 | U48: =IF(Q48="N",0,M48*T48) -> 0 | V48: L, QE:12-DONE PERFORMANCE CHECKING
A49: 26 | B49: IKN400497 | C49: =VLOOKUP(B49,[13]AssetDetails_UEM!$A$3:$AH$1849,6,FALSE) -> Concentrators, Oxygen | D49: =VLOOKUP(B49,[13]AssetDetails_UEM!$A$3:$AK$1849,22,FALSE) -> 5773 | E49: IKNWIBE26009264 | F49: 04PC109 | G49: CM- PERFORMANCE CHECK Concentrators, Oxygen | H49: Corrective Maintenance (CM) | I49: 0 days, 0 hrs, 10 mins | J49: 14-May-2026 15:00:00 | K49: 14-May-2026 15:10:00 | L49: 14-May-2026 16:10:00 | M49: =IF(D49>44999.99,100,ROUNDUP((D49/4999.99)*10,-1)) -> 20 | N49: N | O49: ='[14]B1& B2 UNSCHEDULED'!$O$24 -> 0 | Q49: N | R49: =IF(L49="",AKHIR-J49,L49-J49+1) -> 1.0486111 | S49: =WORKDAY(J49,6,AKHIR) -> 46164 | T49: 0 | U49: =IF(Q49="N",0,M49*T49) -> 0 | V49: L, QE:12- DONE PERFORMANCE CHECKING
A50: 27 | B50: IKN400348 | C50: =VLOOKUP(B50,[13]AssetDetails_UEM!$A$3:$AH$1849,6,FALSE) -> Physiologic Monitoring Systems, Acute Care | D50: =VLOOKUP(B50,[13]AssetDetails_UEM!$A$3:$AK$1849,22,FALSE) -> 44510 | E50: IKNWIBE26009337 | F50: 07WF121 | G50: BP SET TIDAK BOLEH CHARGER-7B | H50: Normal | I50: 0 days, 0 hrs, 32 mins | J50: 15-May-2026 12:28:00 | K50: 15-May-2026 13:00:00 | L50: 15-May-2026 18:00:00 | M50: =IF(D50>44999.99,100,ROUNDUP((D50/4999.99)*10,-1)) -> 90 | N50: N | O50: ='[14]B1& B2 UNSCHEDULED'!$O$24 -> 0 | Q50: N | R50: =IF(L50="",AKHIR-J50,L50-J50+1) -> 1.2305556 | S50: =WORKDAY(J50,6,AKHIR) -> 46167 | T50: 0 | U50: =IF(Q50="N",0,M50*T50) -> 0 | V50: L, QE:12-ALREADY REPLACED NEW POWER CARD, STILL SAME , THE MACHINE NOT ABLE TO CHANGE , LED CHANGING INDICATOR NOT BLINKING , UNDER TROUBLESHOOTING. CHECK FUSE IN THE SMPS BOARD, CHECK POWER CARD CONNECTION , RESEAT CABLE TESTED OKAY AND ABLE TO CHANGE LED BLINKING.
A51: 28 | B51: IKN400967 | C51: =VLOOKUP(B51,[13]AssetDetails_UEM!$A$3:$AH$1849,6,FALSE) -> Linear Accelerators | D51: =VLOOKUP(B51,[13]AssetDetails_UEM!$A$3:$AK$1849,22,FALSE) -> 12049370 | E51: IKNWIBE26009435 | F51: 01RT165 | G51: MACHINE LINAC2 VACUUM VALUE DROP (-4.72)- RT | H51: Normal | I51: 0 days, 0 hrs, 7 mins | J51: 18-May-2026 08:31:00 | K51: 18-May-2026 08:38:00 | L51: 18-May-2026 09:16:00 | M51: =IF(D51>44999.99,100,ROUNDUP((D51/4999.99)*10,-1)) -> 100 | N51: N | O51: ='[14]B1& B2 UNSCHEDULED'!$O$24 -> 0 | Q51: N | R51: =IF(L51="",AKHIR-J51,L51-J51+1) -> 1.03125 | S51: =WORKDAY(J51,6,AKHIR) -> 46168 | T51: 0 | U51: =IF(Q51="N",0,M51*T51) -> 0 | V51: L, QE:12-ADD WATER PRESSURE AND RESET VACCUM SYSTEM . RETURNED TO FUNCTIONING
A52: 29 | B52: IKN400267 | C52: =VLOOKUP(B52,[13]AssetDetails_UEM!$A$3:$AH$1849,6,FALSE) -> Sphygmomanometers, Electronic, Automatic | D52: =VLOOKUP(B52,[13]AssetDetails_UEM!$A$3:$AK$1849,22,FALSE) -> 4510 | E52: IKNWIBE26009515 | F52: 08WG143 | G52: MACHINE BP LEAKING- WAD 8A | H52: Normal | I52: 0 days, 0 hrs, 26 mins | J52: 19-May-2026 09:34:00 | K52: 19-May-2026 10:00:00 | L52: 19-May-2026 11:00:00 | M52: =IF(D52>44999.99,100,ROUNDUP((D52/4999.99)*10,-1)) -> 10 | N52: N | O52: ='[14]B1& B2 UNSCHEDULED'!$O$24 -> 0 | Q52: N | R52: =IF(L52="",AKHIR-J52,L52-J52+1) -> 1.0597222 | S52: =WORKDAY(J52,6,AKHIR) -> 46169 | T52: 0 | U52: =IF(Q52="N",0,M52*T52) -> 0 | V52: L, QE:12-REPLACE NEW CUFF ADULT , TEST UNIT PASSED, UNIT READY TO USE
A53: 30 | B53: IKN400410 | C53: =VLOOKUP(B53,[13]AssetDetails_UEM!$A$3:$AH$1849,6,FALSE) -> Mattress Systems, Alternating-Pressure | D53: =VLOOKUP(B53,[13]AssetDetails_UEM!$A$3:$AK$1849,22,FALSE) -> 28630 | E53: IKNWIBE26009519 | F53: 06WD153 | G53: RIPPLE MATTRESS TIDAK KEMBANG - WAD 6B | H53: Normal | I53: 0 days, 0 hrs, 39 mins | J53: 19-May-2026 11:21:00 | K53: 19-May-2026 12:00:00 | L53: 19-May-2026 14:00:00 | M53: =IF(D53>44999.99,100,ROUNDUP((D53/4999.99)*10,-1)) -> 60 | N53: N | O53: ='[14]B1& B2 UNSCHEDULED'!$O$24 -> 0 | Q53: N | R53: =IF(L53="",AKHIR-J53,L53-J53+1) -> 1.1104167 | S53: =WORKDAY(J53,6,AKHIR) -> 46169 | T53: 0 | U53: =IF(Q53="N",0,M53*T53) -> 0 | V53: L, QE:12-TIGHTEN THE TUBING , MAKE SURE NO LEAKCAGE , TEST MATTRESS FULLY INFLATE PASSED , UNIT READY TO USE
A54: 31 | B54: IKN400782 | C54: =VLOOKUP(B54,[13]AssetDetails_UEM!$A$3:$AH$1849,6,FALSE) -> Laser Imagers | D54: =VLOOKUP(B54,[13]AssetDetails_UEM!$A$3:$AK$1849,22,FALSE) -> 83100 | E54: IKNWIBE26009527 | F54: 03ID178 | G54: CM- DISPLAY FAULTY | H54: Corrective Maintenance (CM) | I54: 0 days, 0 hrs, 5 mins | J54: 19-May-2026 15:00:00 | K54: 19-May-2026 15:05:00 | L54: 19-May-2026 16:00:00 | M54: =IF(D54>44999.99,100,ROUNDUP((D54/4999.99)*10,-1)) -> 100 | N54: N | O54: ='[14]B1& B2 UNSCHEDULED'!$O$24 -> 0 | Q54: N | R54: =IF(L54="",AKHIR-J54,L54-J54+1) -> 1.0416667 | S54: =WORKDAY(J54,6,AKHIR) -> 46169 | T54: 0 | U54: =IF(Q54="N",0,M54*T54) -> 0 | V54: SH, QE:12-VENDOR TROUBLESHOOT AND RESETTHE MONITOR CABLE . TESTED OKAY
A55: 32 | B55: IKN400340 | C55: =VLOOKUP(B55,[13]AssetDetails_UEM!$A$3:$AH$1849,6,FALSE) -> Mattress Systems, Alternating-Pressure | D55: =VLOOKUP(B55,[13]AssetDetails_UEM!$A$3:$AK$1849,22,FALSE) -> 28630 | E55: IKNWIBE26009540 | F55: 07WF121 | G55: RIPPLE MATTRESS TIDAK KEMBANG - WAD 7B | H55: Normal | I55: 0 days, 0 hrs, 11 mins | J55: 19-May-2026 20:19:00 | K55: 19-May-2026 20:30:00 | L55: 46168.792 | M55: =IF(D55>44999.99,100,ROUNDUP((D55/4999.99)*10,-1)) -> 60 | N55: N | O55: ='[14]B1& B2 UNSCHEDULED'!$O$24 -> 0 | Q55: N | R55: 6 | S55: =WORKDAY(J55,6,AKHIR) -> 46169 | T55: 0 | U55: =IF(Q55="N",0,M55*T55) -> 0 | V55: L, QE:12- TIGHTEN CONNECTOR INSIDE, THE MATTRESS, TESTED FULL INFLATED , TRIED SWAP THE COMPRESSOR , THIGHTEN ALL THE HOSE CONNECTOR INSIDE THE MACHINE, STILL THE MATTRESS NOT FECT ALTERNATE BUT FULLY INFLATE , THEN THE ALARM KEEP BUZZING , TRIED SWAP THE ROTOR ASSEMBLY BECAUSE THIS IS THE CHEMICAL PART FOR ALTERNATE THE METTERSS PRESSURE, TESTED OKAY ABLE TO ALTERNATE THE MATTRESS AIR PRESURRE , FUNCTIONING ALARM SILENT
A56: 33 | B56: IKN400349 | C56: =VLOOKUP(B56,[13]AssetDetails_UEM!$A$3:$AH$1849,6,FALSE) -> Sphygmomanometers, Electronic, Automatic | D56: =VLOOKUP(B56,[13]AssetDetails_UEM!$A$3:$AK$1849,22,FALSE) -> 4510 | E56: IKNWIBE26009591 | F56: 07WF143 | G56: RODA BP SET SUSAH BERGERAK- WAD 7B | H56: Normal | I56: 0 days, 0 hrs, 17 mins | J56: 20-May-2026 07:43:00 | K56: 20-May-2026 08:00:00 | L56: 20-May-2026 15:30:00 | M56: =IF(D56>44999.99,100,ROUNDUP((D56/4999.99)*10,-1)) -> 10 | N56: N | O56: ='[14]B1& B2 UNSCHEDULED'!$O$24 -> 0 | Q56: N | R56: =IF(L56="",AKHIR-J56,L56-J56+1) -> 1.3243056 | S56: =WORKDAY(J56,6,AKHIR) -> 46170 | T56: 0 | U56: =IF(Q56="N",0,M56*T56) -> 0 | V56: L, QE:12-REPLACE NEW CASTOR ,TESTING OKAY AND THE CASTOR ABLE TO MOVE SMOOTHLY
A57: 34 | B57: IKN400099 | C57: =VLOOKUP(B57,[13]AssetDetails_UEM!$A$3:$AH$1849,6,FALSE) -> Infusion Pumps, Syringe | D57: =VLOOKUP(B57,[13]AssetDetails_UEM!$A$3:$AK$1849,22,FALSE) -> 10225 | E57: IKNWIBE26009598 | F57: 05IC113 | G57: KEPALA CHARGER INFUSION PUMP TIDAK BERFUNGSI- ICU | H57: Normal | I57: 0 days, 0 hrs, 8 mins | J57: 20-May-2026 10:52:00 | K57: 20-May-2026 11:00:00 | L57: 20-May-2026 11:15:00 | M57: =IF(D57>44999.99,100,ROUNDUP((D57/4999.99)*10,-1)) -> 30 | N57: N | O57: ='[14]B1& B2 UNSCHEDULED'!$O$24 -> 0 | Q57: Y | R57: =IF(L57="",AKHIR-J57,L57-J57+1) -> 1.0159722 | S57: 46111 | T57: 0 | U57: =IF(Q57="N",0,M57*T57) -> 0 | V57: L, QE:12-UNIT TEST AND FUNCTIONING AND WORKING IN GOOD CONDITION
A58: 35 | B58: IKN400741 | C58: =VLOOKUP(B58,[13]AssetDetails_UEM!$A$3:$AH$1849,6,FALSE) -> Analyzers, Laboratory, Microbiology, Blood Culture, Automate | D58: =VLOOKUP(B58,[13]AssetDetails_UEM!$A$3:$AK$1849,22,FALSE) -> 342820 | E58: IKNWIBE26009599 | F58: 04LA126 | G58: THERMOMETER BACTEC HABIS BATTERY- MIKROBIOLOGI LAB | H58: Normal | I58: 0 days, 0 hrs, 34 mins | J58: 20-May-2026 11:26:00 | K58: 20-May-2026 12:00:00 | L58: 20-May-2026 13:00:00 | M58: =IF(D58>44999.99,100,ROUNDUP((D58/4999.99)*10,-1)) -> 100 | N58: N | O58: ='[14]B1& B2 UNSCHEDULED'!$O$24 -> 0 | Q58: N | R58: =IF(L58="",AKHIR-J58,L58-J58+1) -> 1.0652778 | S58: =WORKDAY(J58,6,AKHIR) -> 46170 | T58: 0 | U58: =IF(Q58="N",0,M58*T58) -> 0 | V58: L, QE:12- REPLACE ALKALINE BATTERY 1-5 V LR 41 H
A59: 36 | B59: IKN400956 | C59: =VLOOKUP(B59,[13]AssetDetails_UEM!$A$3:$AH$1849,6,FALSE) -> Linear Accelerators | D59: =VLOOKUP(B59,[13]AssetDetails_UEM!$A$3:$AK$1849,22,FALSE) -> 21961900 | E59: IKNWIBE26009663 | F59: 01RT172 | G59: MACHINE NOVALIS -MAJA RAWATAN TIDAK BOLEH GERAK 'INTERLOCK HWFA'-LINAC 3 | H59: Normal | I59: 0 days, 0 hrs, 23 mins | J59: 21-May-2026 08:07:00 | K59: 21-May-2026 08:30:00 | L59: 21-May-2026 09:00:00 | M59: =IF(D59>44999.99,100,ROUNDUP((D59/4999.99)*10,-1)) -> 100 | N59: N | O59: ='[14]B1& B2 UNSCHEDULED'!$O$24 -> 0 | Q59: N | R59: =IF(L59="",AKHIR-J59,L59-J59+1) -> 1.0368056 | S59: =WORKDAY(J59,6,AKHIR) -> 46171 | T59: 0 | U59: =IF(Q59="N",0,M59*T59) -> 0 | V59: L, QE:12-RESET EMERGENCY BUTTON AND GENERATOR , UNIT RETURNED TO FUNCTIONING AND TESTED OKAY
A60: 37 | B60: IKN400967 | C60: =VLOOKUP(B60,[13]AssetDetails_UEM!$A$3:$AH$1849,6,FALSE) -> Linear Accelerators | D60: =VLOOKUP(B60,[13]AssetDetails_UEM!$A$3:$AK$1849,22,FALSE) -> 12049370 | E60: IKNWIBE26009669 | F60: 01RT165 | G60: VACCUM TARGET DROP(5.3) -LINAC 2 | H60: Normal | I60: 0 days, 0 hrs, 6 mins | J60: 21-May-2026 09:12:00 | K60: 21-May-2026 09:18:00 | L60: 21-May-2026 11:00:00 | M60: =IF(D60>44999.99,100,ROUNDUP((D60/4999.99)*10,-1)) -> 100 | N60: N | O60: ='[14]B1& B2 UNSCHEDULED'!$O$24 -> 0 | Q60: N | R60: =IF(L60="",AKHIR-J60,L60-J60+1) -> 1.075 | S60: =WORKDAY(J60,6,AKHIR) -> 46171 | T60: 0 | U60: =IF(Q60="N",0,M60*T60) -> 0 | V60: L, QE:12-RECONDITIONING AND RESET VACCUM SYSTEM. TESTED OK AND STABLE , UNIT LEFT WITH GOOD WORKING CONDITION
A61: 38 | B61: IKN400978 | C61: =VLOOKUP(B61,[13]AssetDetails_UEM!$A$3:$AH$1849,6,FALSE) -> Scanning Systems, Computed Tomography | D61: =VLOOKUP(B61,[13]AssetDetails_UEM!$A$3:$AK$1849,22,FALSE) -> 3557530 | E61: IKNWIBE26009676 | F61: 01RT116 | G61: CT SIM 1'TABLE UNLOCK AND MACHINE OFF' | H61: Normal | I61: 0 days, 0 hrs, 15 mins | J61: 21-May-2026 11:17:00 | K61: 46163.481 | L61: 46163.75 | M61: =IF(D61>44999.99,100,ROUNDUP((D61/4999.99)*10,-1)) -> 100 | N61: N | O61: ='[14]B1& B2 UNSCHEDULED'!$O$24 -> 0 | Q61: N | R61: =IF(L61="",AKHIR-J61,L61-J61+1) -> 1.2798611 | S61: =WORKDAY(J61,6,AKHIR) -> 46171 | T61: 0 | U61: =IF(Q61="N",0,M61*T61) -> 0 | V61: CAUCH STUCK AT CERTAIN ANGLE. RAILING BELT LOST TENSION AND DISJOINTED FROM COUPLING CLAMP. RE-JOIN THE BELT AND DO TENSION ADJUSTMENT/ALLIGMENT.
A62: 39 | B62: IKN402228 | C62: Scales, Patient, Floor | D62: 6500 | E62: IKNWIBE26009690 | F62: 03OC133 | G62: CM-VERIFY THE RESULT ACCURACY | H62: Corrective Maintenance (CM) | I62: 0 days, 0 hrs, 10 mins | J62: 21-May-2026 15:00:00 | K62: 21-May-2026 15:10:00 | L62: 21-May-2026 17:00:00 | M62: =IF(D62>44999.99,100,ROUNDUP((D62/4999.99)*10,-1)) -> 20 | N62: N | O62: ='[14]B1& B2 UNSCHEDULED'!$O$24 -> 0 | Q62: N | R62: =IF(L62="",AKHIR-J62,L62-J62+1) -> 1.0833333 | S62: =WORKDAY(J62,6,AKHIR) -> 46171 | T62: 0 | U62: =IF(Q62="N",0,M62*T62) -> 0 | V62: L, QE:12-VENDOR TROUBLESHOOT AND DONE CALIBRATION TESTED OKAY
A63: 40 | B63: IKN401461 | C63: =VLOOKUP(B63,[13]AssetDetails_UEM!$A$3:$AH$1849,6,FALSE) -> Scales, Patient, Floor | D63: =VLOOKUP(B63,[13]AssetDetails_UEM!$A$3:$AK$1849,22,FALSE) -> 9380 | E63: IKNWIBE26009691 | F63: 03OC133 | G63: CM-VERIFY THE RESULT ACCURACY | H63: Corrective Maintenance (CM) | I63: 0 days, 0 hrs, 10 mins | J63: 21-May-2026 15:00:00 | K63: 21-May-2026 15:10:00 | L63: 21-May-2026 16:30:00 | M63: =IF(D63>44999.99,100,ROUNDUP((D63/4999.99)*10,-1)) -> 20 | N63: N | O63: ='[14]B1& B2 UNSCHEDULED'!$O$24 -> 0 | Q63: N | R63: =IF(L63="",AKHIR-J63,L63-J63+1) -> 1.0625 | S63: =WORKDAY(J63,6,AKHIR) -> 46171 | T63: 0 | U63: =IF(Q63="N",0,M63*T63) -> 0 | V63: L, QE:12- TEST USING STANDARD WEIGHT , FROUND WEIGHLESS THAN 60KG , THE DISPLAYED RESULT LOWER BY 200G, FOR WEIGHT MORE THAN 60KG, THE DISPLAYED RESULT IS LOWER BY 400G, THIS MODEL ALREADY ADSELECTED, AND CA SENT 24/12/2025
A64: 41 | B64: IKN401223 | C64: =VLOOKUP(B64,[13]AssetDetails_UEM!$A$3:$AH$1849,6,FALSE) -> Pipetters | D64: =VLOOKUP(B64,[13]AssetDetails_UEM!$A$3:$AK$1849,22,FALSE) -> 1323 | E64: IKNWIBE26009692 | F64: 03NM139 | G64: CM- YEARLY CALIBRATION | H64: Corrective Maintenance (CM) | I64: 0 days, 0 hrs, 10 mins | J64: 21-May-2026 10:00:00 | K64: 21-May-2026 10:10:00 | L64: 21-May-2026 11:10:00 | M64: =IF(D64>44999.99,100,ROUNDUP((D64/4999.99)*10,-1)) -> 10 | N64: N | O64: ='[14]B1& B2 UNSCHEDULED'!$O$24 -> 0 | Q64: N | R64: =IF(L64="",AKHIR-J64,L64-J64+1) -> 1.0486111 | S64: =WORKDAY(J64,6,AKHIR) -> 46171 | T64: 0 | U64: =IF(Q64="N",0,M64*T64) -> 0 | V64: L, QE:15-YEARLY CALIBRATION DONE BY VENDOR, CALIBRATION PASSED
A65: 42 | B65: IKN401225 | C65: =VLOOKUP(B65,[13]AssetDetails_UEM!$A$3:$AH$1849,6,FALSE) -> Pipetters | D65: =VLOOKUP(B65,[13]AssetDetails_UEM!$A$3:$AK$1849,22,FALSE) -> 1323 | E65: IKNWIBE26009693 | F65: 03NM139 | G65: CM- YEARLY CALIBRATION | H65: Corrective Maintenance (CM) | I65: 0 days, 0 hrs, 10 mins | J65: 21-May-2026 10:00:00 | K65: 21-May-2026 10:10:00 | L65: 21-May-2026 11:10:00 | M65: =IF(D65>44999.99,100,ROUNDUP((D65/4999.99)*10,-1)) -> 10 | N65: N | O65: ='[14]B1& B2 UNSCHEDULED'!$O$24 -> 0 | Q65: N | R65: =IF(L65="",AKHIR-J65,L65-J65+1) -> 1.0486111 | S65: =WORKDAY(J65,6,AKHIR) -> 46171 | T65: 0 | U65: =IF(Q65="N",0,M65*T65) -> 0 | V65: L, QE:15-YEARLY CALIBRATION DONE BY VENDOR, CALIBRATION PASSED
A66: 43 | B66: IKN401227 | C66: =VLOOKUP(B66,[13]AssetDetails_UEM!$A$3:$AH$1849,6,FALSE) -> Pipetters | D66: =VLOOKUP(B66,[13]AssetDetails_UEM!$A$3:$AK$1849,22,FALSE) -> 1323 | E66: IKNWIBE26009694 | F66: 03NM139 | G66: CM- YEARLY CALIBRATION | H66: Corrective Maintenance (CM) | I66: 0 days, 0 hrs, 10 mins | J66: 21-May-2026 10:00:00 | K66: 21-May-2026 10:10:00 | L66: 21-May-2026 11:10:00 | M66: =IF(D66>44999.99,100,ROUNDUP((D66/4999.99)*10,-1)) -> 10 | N66: N | O66: ='[14]B1& B2 UNSCHEDULED'!$O$24 -> 0 | Q66: N | R66: =IF(L66="",AKHIR-J66,L66-J66+1) -> 1.0486111 | S66: =WORKDAY(J66,6,AKHIR) -> 46171 | T66: 0 | U66: =IF(Q66="N",0,M66*T66) -> 0 | V66: L, QE:15-YEARLY CALIBRATION DONE BY VENDOR, CALIBRATION PASSED
A67: 44 | B67: IKN401229 | C67: =VLOOKUP(B67,[13]AssetDetails_UEM!$A$3:$AH$1849,6,FALSE) -> Pipetters | D67: =VLOOKUP(B67,[13]AssetDetails_UEM!$A$3:$AK$1849,22,FALSE) -> 1323 | E67: IKNWIBE26009695 | F67: 03WA125 | G67: CM- YEARLY CALIBRATION | H67: Corrective Maintenance (CM) | I67: 0 days, 0 hrs, 10 mins | J67: 21-May-2026 10:00:00 | K67: 21-May-2026 10:10:00 | L67: 21-May-2026 11:10:00 | M67: =IF(D67>44999.99,100,ROUNDUP((D67/4999.99)*10,-1)) -> 10 | N67: N | O67: ='[14]B1& B2 UNSCHEDULED'!$O$24 -> 0 | Q67: N | R67: =IF(L67="",AKHIR-J67,L67-J67+1) -> 1.0486111 | S67: =WORKDAY(J67,6,AKHIR) -> 46171 | T67: 0 | U67: =IF(Q67="N",0,M67*T67) -> 0 | V67: L, QE:15-YEARLY CALIBRATION DONE BY VENDOR, CALIBRATION PASSED
A68: 45 | B68: IKN401231 | C68: =VLOOKUP(B68,[13]AssetDetails_UEM!$A$3:$AH$1849,6,FALSE) -> Pipetters | D68: =VLOOKUP(B68,[13]AssetDetails_UEM!$A$3:$AK$1849,22,FALSE) -> 3250 | E68: IKNWIBE26009696 | F68: 03NM154 | G68: CM- YEARLY CALIBRATION | H68: Corrective Maintenance (CM) | I68: 0 days, 0 hrs, 10 mins | J68: 21-May-2026 10:00:00 | K68: 21-May-2026 10:10:00 | L68: 21-May-2026 11:10:00 | M68: =IF(D68>44999.99,100,ROUNDUP((D68/4999.99)*10,-1)) -> 10 | N68: N | O68: ='[14]B1& B2 UNSCHEDULED'!$O$24 -> 0 | Q68: N | R68: =IF(L68="",AKHIR-J68,L68-J68+1) -> 1.0486111 | S68: =WORKDAY(J68,6,AKHIR) -> 46171 | T68: 0 | U68: =IF(Q68="N",0,M68*T68) -> 0 | V68: L, QE:15-YEARLY CALIBRATION DONE BY VENDOR, CALIBRATION PASSED
A69: 46 | B69: IKN400232 | C69: =VLOOKUP(B69,[13]AssetDetails_UEM!$A$3:$AH$1849,6,FALSE) -> Infusion Pumps, General-Purpose | D69: =VLOOKUP(B69,[13]AssetDetails_UEM!$A$3:$AK$1849,22,FALSE) -> 10825 | E69: IKNWIBE26009700 | F69: 09WJ126 | G69: INFUSION PUMP ROSAK WATER NOT RUNNING - WAD 9A | H69: Normal | I69: 0 days, 0 hrs, 12 mins | J69: 21-May-2026 20:18:00 | K69: 46163.854 | L69: 46167.562 | M69: =IF(D69>44999.99,100,ROUNDUP((D69/4999.99)*10,-1)) -> 30 | N69: N | O69: ='[14]B1& B2 UNSCHEDULED'!$O$24 -> 0 | Q69: N | R69: =IF(L69="",AKHIR-J69,L69-J69+1) -> 4.7166667 | S69: =WORKDAY(J69,6,AKHIR) -> 46171 | T69: 0 | U69: =IF(Q69="N",0,M69*T69) -> 0 | V69: DO PERFORMANCE TEST WITH IN 4 HOURS, DEMONSTRATED ACCEPTABLE INFUSION ACCURACY. UNIT TESTED OKAY
A70: 47 | B70: IKN400762 | C70: =VLOOKUP(B70,[13]AssetDetails_UEM!$A$3:$AH$1849,6,FALSE) -> Analyzers, Laboratory, Immunoassay, Chemiluminescent | D70: =VLOOKUP(B70,[13]AssetDetails_UEM!$A$3:$AK$1849,22,FALSE) -> 1443450 | E70: IKNWIBE26009774 | F70: 04LA133 | G70: MACHINE ARCHITECT' ASPIRATION ERROR' | H70: Normal | I70: 0 days, 0 hrs, 9 mins | J70: 22-May-2026 15:51:00 | K70: 22-May-2026 16:00:00 | L70: 22-May-2026 17:00:00 | M70: =IF(D70>44999.99,100,ROUNDUP((D70/4999.99)*10,-1)) -> 100 | N70: N | O70: ='[14]B1& B2 UNSCHEDULED'!$O$24 -> 0 | Q70: N | R70: =IF(L70="",AKHIR-J70,L70-J70+1) -> 1.0479167 | S70: =WORKDAY(J70,6,AKHIR) -> 46174 | T70: 0 | U70: =IF(Q70="N",0,M70*T70) -> 0 | V70: L, QE:12-REPLACE PROBE , TEST FUNCTIONING OKAY
A71: 48 | B71: IKN401581 | C71: =VLOOKUP(B71,[13]AssetDetails_UEM!$A$3:$AH$1849,6,FALSE) -> Balances, Electronic | D71: =VLOOKUP(B71,[13]AssetDetails_UEM!$A$3:$AK$1849,22,FALSE) -> 3380 | E71: IKNWIBE26009782 | F71: 01KT101 | G71: PANJANGKAN WIYER PENIMBANG-SAJIAN ARAS 1 | H71: Normal | I71: 0 days, 0 hrs, 32 mins | J71: 22-May-2026 17:48:00 | K71: 22-May-2026 18:20:00 | L71: 28-May-2026 09:30:00 | M71: =IF(D71>44999.99,100,ROUNDUP((D71/4999.99)*10,-1)) -> 10 | N71: N | O71: ='[14]B1& B2 UNSCHEDULED'!$O$24 -> 0 | Q71: N | R71: 5 | S71: =WORKDAY(J71,6,AKHIR) -> 46174 | T71: 0 | U71: =IF(Q71="N",0,M71*T71) -> 0 | V71: L, QE:12- NEXT VISIT , USER ALREADY CHANGE THE LOCATION OF THE BALANCES , NO NEED TO CHANGE THE LENGTH OF THE POWER LEAD
A72: 49 | B72: IKN400308 | C72: =VLOOKUP(B72,[13]AssetDetails_UEM!$A$3:$AH$1849,6,FALSE) -> Defibrillators, External, Manual | D72: =VLOOKUP(B72,[13]AssetDetails_UEM!$A$3:$AK$1849,22,FALSE) -> 45000 | E72: IKNWIBE26009802 | F72: 08WH133 | G72: PATIENT LEAD MACHINE DEFIBRILLATORS NOT DETECT - WAD 8B | H72: Normal | I72: 0 days, 0 hrs, 10 mins | J72: 23-May-2026 06:21:00 | K72: 46165.272 | L72: 23-May-2026 09:00:00 | M72: =IF(D72>44999.99,100,ROUNDUP((D72/4999.99)*10,-1)) -> 100 | N72: N | O72: ='[14]B1& B2 UNSCHEDULED'!$O$24 -> 0 | Q72: N | R72: =IF(L72="",AKHIR-J72,L72-J72+1) -> 1.1104167 | S72: =WORKDAY(J72,6,AKHIR) -> 46174 | T72: 0 | U72: =IF(Q72="N",0,M72*T72) -> 0 | V72: L, QE:12- CHECK WITH ECG TESTER, TEST FUNCTIONING OKAY
A73: 50 | B73: IKN400798 | C73: =VLOOKUP(B73,[13]AssetDetails_UEM!$A$3:$AH$1849,6,FALSE) -> Radiographic Systems, Digital | D73: =VLOOKUP(B73,[13]AssetDetails_UEM!$A$3:$AK$1849,22,FALSE) -> 1958605 | E73: IKNWIBE26009808 | F73: 03ID181 | G73: MACHINE GENERAL XRAY TIDAK BERFUNGSI-RADIOLOGI | H73: Normal | I73: 0 days, 0 hrs, 12 mins | J73: 24-May-2026 06:58:00 | K73: 46166.299 | L73: 24-May-2026 09:00:00 | M73: =IF(D73>44999.99,100,ROUNDUP((D73/4999.99)*10,-1)) -> 100 | N73: N | O73: ='[14]B1& B2 UNSCHEDULED'!$O$24 -> 0 | Q73: N | R73: =IF(L73="",AKHIR-J73,L73-J73+1) -> 1.0847222 | S73: =WORKDAY(J73,6,AKHIR) -> 46174 | T73: 0 | U73: =IF(Q73="N",0,M73*T73) -> 0 | V73: L, QE:12-CHECK SUPPLY WITH FEMS ,TEST FUNCTIONING OKAY
A74: 51 | B74: IKN400755 | C74: =VLOOKUP(B74,[13]AssetDetails_UEM!$A$3:$AH$1849,6,FALSE) -> Analyzers, Laboratory, Hematology, Coagulation, Automated | D74: =VLOOKUP(B74,[13]AssetDetails_UEM!$A$3:$AK$1849,22,FALSE) -> 105860 | E74: IKNWIBE26009875 | F74: 04LA132 | G74: MACHINE ACL ALARM ROTOR ERROR- LAB | H74: Normal | I74: 0 days, 0 hrs, 22 mins | J74: 25-May-2026 09:38:00 | K74: 25-May-2026 10:00:00 | L74: 25-May-2026 10:20:00 | M74: =IF(D74>44999.99,100,ROUNDUP((D74/4999.99)*10,-1)) -> 100 | N74: N | O74: ='[14]B1& B2 UNSCHEDULED'!$O$24 -> 0 | Q74: N | R74: =IF(L74="",AKHIR-J74,L74-J74+1) -> 1.0291667 | S74: =WORKDAY(J74,6,AKHIR) -> 46175 | T74: 0 | U74: =IF(Q74="N",0,M74*T74) -> 0 | V74: L, QE:12- SETTING AUTO PICKUP ROTOR, TEST FUNCTIONING OKAY
A75: 52 | B75: IKN401472 | C75: =VLOOKUP(B75,[13]AssetDetails_UEM!$A$3:$AH$1849,6,FALSE) -> Scales, Patient, Floor | D75: =VLOOKUP(B75,[13]AssetDetails_UEM!$A$3:$AK$1849,22,FALSE) -> 9380 | E75: IKNWIBE26009880 | F75: 09WJ136 | G75: PENIMBANG TIDAK BOLEH ON- WAD 9A | H75: Normal | I75: 0 days, 0 hrs, 47 mins | J75: 25-May-2026 10:13:00 | K75: 25-May-2026 11:00:00 | L75: 25-May-2026 12:30:00 | M75: =IF(D75>44999.99,100,ROUNDUP((D75/4999.99)*10,-1)) -> 20 | N75: N | O75: ='[14]B1& B2 UNSCHEDULED'!$O$24 -> 0 | Q75: N | R75: =IF(L75="",AKHIR-J75,L75-J75+1) -> 1.0951389 | S75: =WORKDAY(J75,6,AKHIR) -> 46175 | T75: 0 | U75: =IF(Q75="N",0,M75*T75) -> 0 | V75: L, QE:12- RESET PLUG, ALL PLUG WALL CAN USE, ON MACHINE OK, UNIT READY FOR USE
A76: 53 | B76: IKN400527 | C76: =VLOOKUP(B76,[13]AssetDetails_UEM!$A$3:$AH$1849,6,FALSE) -> Aspirators | D76: =VLOOKUP(B76,[13]AssetDetails_UEM!$A$3:$AK$1849,22,FALSE) -> 2165 | E76: IKNWIBE26009895 | F76: 04PC109 | G76: CM- REQ PERFORMANCE CHECK | H76: Corrective Maintenance (CM) | I76: 0 days, 0 hrs, 30 mins | J76: 25-May-2026 15:00:00 | K76: 25-May-2026 15:30:00 | L76: 25-May-2026 16:30:00 | M76: =IF(D76>44999.99,100,ROUNDUP((D76/4999.99)*10,-1)) -> 10 | N76: N | O76: ='[14]B1& B2 UNSCHEDULED'!$O$24 -> 0 | Q76: N | R76: =IF(L76="",AKHIR-J76,L76-J76+1) -> 1.0625 | S76: =WORKDAY(J76,6,AKHIR) -> 46175 | T76: 0 | U76: =IF(Q76="N",0,M76*T76) -> 0 | V76: L, QE:12-DONE PERFORMING CHECKING
A77: 54 | B77: IKN400978 | C77: =VLOOKUP(B77,[13]AssetDetails_UEM!$A$3:$AH$1849,6,FALSE) -> Scanning Systems, Computed Tomography | D77: =VLOOKUP(B77,[13]AssetDetails_UEM!$A$3:$AK$1849,22,FALSE) -> 3557530 | E77: IKNWIBE26009962 | F77: 01RT116 | G77: MACHINE CT SIM 1 IMAGE TIDAK DAPAT DIHANTAR KE SYNGUGO.VIA- RT | H77: Normal | I77: 0 days, 0 hrs, 06 mins | J77: 26-May-2026 12:36:00 | K77: 46168.529 | L77: 46168.583 | M77: =IF(D77>44999.99,100,ROUNDUP((D77/4999.99)*10,-1)) -> 100 | N77: N | O77: ='[14]B1& B2 UNSCHEDULED'!$O$24 -> 0 | Q77: N | R77: =IF(L77="",AKHIR-J77,L77-J77+1) -> 1.0583333 | S77: =WORKDAY(J77,6,AKHIR) -> 46176 | T77: 0 | U77: =IF(Q77="N",0,M77*T77) -> 0 | V77: SERVER CONFLIT, RESTART SYNGO-VIO SERVER AND CONFIGURATE. TESTED OK AND UNIT LEFT.
A78: 55 | B78: IKN400875 | C78: =VLOOKUP(B78,[13]AssetDetails_UEM!$A$3:$AH$1849,6,FALSE) -> Concentrators, Oxygen | D78: =VLOOKUP(B78,[13]AssetDetails_UEM!$A$3:$AK$1849,22,FALSE) -> 5000 | E78: IKNWIBE26009967 | F78: 04PC109 | G78: CM- REQ FOR PERFORMANCE CHECK | H78: Corrective Maintenance (CM) | I78: 0 days, 0 hrs, 5 mins | J78: 26-May-2026 13:00:00 | K78: 26-May-2026 13:05:00 | L78: 26-May-2026 14:05:00 | M78: =IF(D78>44999.99,100,ROUNDUP((D78/4999.99)*10,-1)) -> 20 | N78: N | O78: ='[14]B1& B2 UNSCHEDULED'!$O$24 -> 0 | Q78: N | R78: =IF(L78="",AKHIR-J78,L78-J78+1) -> 1.0451389 | S78: =WORKDAY(J78,6,AKHIR) -> 46176 | T78: 0 | U78: =IF(Q78="N",0,M78*T78) -> 0 | V78: AN- DONE PERFORMANCE CHECKING
A79: 56 | B79: IKN400762 | C79: =VLOOKUP(B79,[13]AssetDetails_UEM!$A$3:$AH$1849,6,FALSE) -> Analyzers, Laboratory, Immunoassay, Chemiluminescent | D79: =VLOOKUP(B79,[13]AssetDetails_UEM!$A$3:$AK$1849,22,FALSE) -> 1443450 | E79: IKNWIBE26009968 | F79: 04LA133 | G79: MACHINE ARCHITECT LEAKING - PATOLOGI | H79: Normal | I79: 0 days, 0 hrs, 6 mins | J79: 26-May-2026 14:59:00 | K79: 26-May-2026 15:05:00 | L79: 26-May-2026 16:05:00 | M79: =IF(D79>44999.99,100,ROUNDUP((D79/4999.99)*10,-1)) -> 100 | N79: N | O79: ='[14]B1& B2 UNSCHEDULED'!$O$24 -> 0 | Q79: N | R79: =IF(L79="",AKHIR-J79,L79-J79+1) -> 1.0458333 | S79: =WORKDAY(J79,6,AKHIR) -> 46176 | T79: 0 | U79: =IF(Q79="N",0,M79*T79) -> 0 | V79: AN- CLEAN LEVEL SENSOR FROM WASTE DIRTY. TEST FUNCTIONING OKAY
A80: 57 | B80: IKN400755 | C80: =VLOOKUP(B80,[13]AssetDetails_UEM!$A$3:$AH$1849,6,FALSE) -> Analyzers, Laboratory, Hematology, Coagulation, Automated | D80: =VLOOKUP(B80,[13]AssetDetails_UEM!$A$3:$AK$1849,22,FALSE) -> 105860 | E80: IKNWIBE26009975 | F80: 04LA132 | G80: MESIN COAG PROBLEM PROBE- PATOLOGI ARAS 4 | H80: Normal | I80: 0 days, 0 hrs, 30 mins | J80: 26-May-2026 20:00:00 | K80: 46168.854 | L80: 46169.458 | M80: =IF(D80>44999.99,100,ROUNDUP((D80/4999.99)*10,-1)) -> 100 | N80: N | O80: ='[14]B1& B2 UNSCHEDULED'!$O$24 -> 0 | Q80: N | R80: =IF(L80="",AKHIR-J80,L80-J80+1) -> 1.625 | S80: =WORKDAY(J80,6,AKHIR) -> 46176 | T80: 0 | U80: =IF(Q80="N",0,M80*T80) -> 0 | V80: PROBE ALLIGNMENT FAULTY, DO PROBE ALLIGNMENT ADJUSTMENT, TEST FUNCTIONING OK.
A81: 58 | B81: IKN400967 | C81: =VLOOKUP(B81,[13]AssetDetails_UEM!$A$3:$AH$1849,6,FALSE) -> Linear Accelerators | D81: =VLOOKUP(B81,[13]AssetDetails_UEM!$A$3:$AK$1849,22,FALSE) -> 12049370 | E81: IKNWIBE26010047 | F81: 01RT165 | G81: SVI DAN KV PLANA NOT DETECTED- LINAC 2- RT | H81: Normal | I81: 0 days, 0 hrs, 09 mins | J81: 28-May-2026 09:44:00 | K81: 46170.41 | L81: 46170.604 | M81: =IF(D81>44999.99,100,ROUNDUP((D81/4999.99)*10,-1)) -> 100 | N81: N | O81: ='[14]B1& B2 UNSCHEDULED'!$O$24 -> 0 | Q81: N | R81: =IF(L81="",AKHIR-J81,L81-J81+1) -> 1.1986111 | S81: =WORKDAY(J81,6,AKHIR) -> 46178 | T81: 0 | U81: =IF(Q81="N",0,M81*T81) -> 0 | V81: REPLACED KV ARM MICROSWITHES AND TESTED OK. UNIT LEFT WITH FULL FUNCTIONING.
A82: 59 | B82: IKN400976 | C82: =VLOOKUP(B82,[13]AssetDetails_UEM!$A$3:$AH$1849,6,FALSE) -> Laser Imagers | D82: =VLOOKUP(B82,[13]AssetDetails_UEM!$A$3:$AK$1849,22,FALSE) -> 83100 | E82: IKNWIBE26010048 | F82: 01RT117 | G82: MACHINE LINAC 2 TABLE LONG- RT | H82: Normal | I82: 0 days, 0 hrs, 10 mins | J82: 28-May-2026 10:00:00 | K82: 46170.424 | L82: 46170.944 | M82: =IF(D82>44999.99,100,ROUNDUP((D82/4999.99)*10,-1)) -> 100 | N82: N | O82: ='[14]B1& B2 UNSCHEDULED'!$O$24 -> 0 | Q82: N | R82: =IF(L82="",AKHIR-J82,L82-J82+1) -> 1.5277778 | S82: =WORKDAY(J82,6,AKHIR) -> 46178 | T82: 0 | U82: =IF(Q82="N",0,M82*T82) -> 0 | V82: REPLACED FINE POT AND NO INHIBIT POP-UP. TESTED OK AND UNIT LEFT WITH GOOD WORKING CONDITION.
A83: 60 | B83: IKN401362 | C83: =VLOOKUP(B83,[13]AssetDetails_UEM!$A$3:$AH$1849,6,FALSE) -> Pumps, Enteral Feeding | D83: =VLOOKUP(B83,[13]AssetDetails_UEM!$A$3:$AK$1849,22,FALSE) -> 2500 | E83: IKNWIBE26010125 | F83: 03DU103 | G83: FEEDING PUMP KELUAR 8888- WAD 5A | H83: Normal | I83: 0 days, 0 hrs, 04 mins | J83: 30-May-2026 16:16:00 | K83: 46172.681 | L83: 46173.812 | M83: =IF(D83>44999.99,100,ROUNDUP((D83/4999.99)*10,-1)) -> 10 | N83: N | O83: ='[14]B1& B2 UNSCHEDULED'!$O$24 -> 0 | Q83: N | R83: =IF(L83="",AKHIR-J83,L83-J83+1) -> 2.1347222 | S83: =WORKDAY(J83,6,AKHIR) -> 46181 | T83: 0 | U83: =IF(Q83="N",0,M83*T83) -> 0 | V83: L, QE:12-TEST ALL THE BUTTON ENTER MODE, TESTED OKAY NO ERROR. ASK USER TO USE THEN STILL POPUP THE ERROR . DISMANTLE THE UNIT , RESEAT ALL CABLE , TRY TO CHANGE THE BATTERY BECAUSE THE BATTERY IS DAMAGED, TRIED TO RUN THE UNIT FOR 2 HOUR , NO ERROR , POP UP . USER ALREADY TESTED MACHINE , ALL OKAY AND FUNCTIONING.
A84: Current Month (Work Order Open)
A85: 1 | B85: IKN400828 | C85: =VLOOKUP(B85,[13]AssetDetails_UEM!$A$3:$AH$1849,6,FALSE) -> Anesthesia Units | D85: =VLOOKUP(B85,[13]AssetDetails_UEM!$A$3:$AK$1849,22,FALSE) -> 144345 | E85: IKNWIBE26009338 | F85: 01RT275 | G85: GA MACHINE OXYGEN PIPE LINE LOW PRESSURE DETECTECT - BOT ARAS1 | H85: Normal | I85: 0 days, 0 hrs, 49 mins | J85: 46157.633 | K85: 46157.667 | L85: 46173.667 | M85: =IF(D85>44999.99,100,ROUNDUP((D85/4999.99)*10,-1)) -> 100 | N85: N | O85: ='[14]B1& B2 UNSCHEDULED'!$O$24 -> 0 | Q85: Y | R85: =IF(L85="",AKHIR-J85,L85-J85+1) -> 17.034028 | S85: =WORKDAY(J85,6,AKHIR) -> 46167 | T85: 0 | U85: =IF(Q85="N",0,M85*T85) -> 0 | V85: PROB :LOW PRESSURE DETECTED QUO DATE : 17/5/2026 (DRAEGER) PO DATE : 20/5/2026 (AWSB-900123) ETA : END JUNE STATUS:Waiting Parts
A86: 2 | B86: IKN400756 | C86: =VLOOKUP(B86,[13]AssetDetails_UEM!$A$3:$AH$1849,6,FALSE) -> Analyzers, Laboratory, Hematology, Coagulation, Automated | D86: =VLOOKUP(B86,[13]AssetDetails_UEM!$A$3:$AK$1849,22,FALSE) -> 105860 | E86: IKNWIBE26009521 | F86: 04LA132 | G86: MACHINE ACL TOP KELUAR ERROR READING OUT OF FENCE- LAB- HEMATOLOGI | H86: Normal | I86: 0 days, 0 hrs, 12 mins | J86: 19-May-2026 12:18:00 | K86: 46161.521 | L86: 46173.667 | M86: =IF(D86>44999.99,100,ROUNDUP((D86/4999.99)*10,-1)) -> 100 | N86: N | O86: ='[14]B1& B2 UNSCHEDULED'!$O$24 -> 0 | Q86: N | R86: =IF(L86="",AKHIR-J86,L86-J86+1) -> 13.154167 | S86: =WORKDAY(J86,6,AKHIR) -> 46169 | T86: 0 | U86: =IF(Q86="N",0,M86*T86) -> 0 | V86: PROB :ASSY LED FAULTY QUO DATE : 20/5/2026 (STRAITS SCIENTIFIC) PO DATE : 25/5/2026(AWSB-900124) ETA : 4-6 WEEKS (EARLY JUNE) STATUS: WAITING PARTS
A87: 3 | B87: IKN400579 | C87: =VLOOKUP(B87,[13]AssetDetails_UEM!$A$3:$AH$1849,6,FALSE) -> Radiation Monitors | D87: =VLOOKUP(B87,[13]AssetDetails_UEM!$A$3:$AK$1849,22,FALSE) -> 23270 | E87: IKNWIBE26009686 | F87: 01NW105 | G87: READING NOT ACCURATE | H87: Normal | I87: 0 days, 0 hrs, 10 mins | J87: 21-May-2026 14:00:00 | K87: 46163.59 | L87: 46173.667 | M87: =IF(D87>44999.99,100,ROUNDUP((D87/4999.99)*10,-1)) -> 50 | N87: N | O87: ='[14]B1& B2 UNSCHEDULED'!$O$24 -> 0 | Q87: N | R87: =IF(L87="",AKHIR-J87,L87-J87+1) -> 11.083333 | S87: =WORKDAY(J87,6,AKHIR) -> 46171 | T87: 0 | U87: =IF(Q87="N",0,M87*T87) -> 0 | V87: PROB :READING NOT ACCURATE QUO DATE : 21-05-2026 (H&A MEDICAL) SR NO : E.26.0078 (22-05-2026) PO DATE : 26/5/2026(AWSB-900125) ETA : END JUNE STATUS: SEND TO GERMAN FOR TROUBLESHOOT
A88: 4 | B88: IKN400997 | C88: =VLOOKUP(B88,[13]AssetDetails_UEM!$A$3:$AH$1849,6,FALSE) -> Radiation Monitors | D88: =VLOOKUP(B88,[13]AssetDetails_UEM!$A$3:$AK$1849,22,FALSE) -> 112855 | E88: IKNWIBE26010058 | F88: 03NM132 | G88: MACHINE HAND FOOD MONITOR ERROR, MACHINE DETECT CONTAMINATION LIFE HAND, BILA CHECK GUNA SERVER METER TIADA CONTAMINATION- JAB PERUBATAN NUKLEAR | H88: Normal | I88: 0 days, 0 hrs, 15 mins | J88: 28-May-2026 16:25:00 | K88: 46170.694 | L88: 46173.667 | M88: =IF(D88>44999.99,100,ROUNDUP((D88/4999.99)*10,-1)) -> 100 | N88: N | O88: ='[14]B1& B2 UNSCHEDULED'!$O$24 -> 0 | Q88: N | R88: =IF(L88="",AKHIR-J88,L88-J88+1) -> 3.9826389 | S88: =WORKDAY(J88,6,AKHIR) -> 46178 | T88: 0 | U88: =IF(Q88="N",0,M88*T88) -> 0 | V88: PROB :LEFT HAND DETECTOR INTERMITTENT DETECT STATUS: UNDER TROUBLESHOOT BY GUIDING FROM SUPPLIER NUVIA Instruments GmbH
A89: 5 | B89: IKN400563 | C89: =VLOOKUP(B89,[13]AssetDetails_UEM!$A$3:$AH$1849,6,FALSE) -> Radiation Monitors | D89: =VLOOKUP(B89,[13]AssetDetails_UEM!$A$3:$AK$1849,22,FALSE) -> 112855 | E89: IKNWIBE26010111 | F89: 01NW106 | G89: CM- FALSE MESSAGE | H89: Corrective Maintenance (CM) | I89: 0 days, 0 hrs, 10 mins | J89: 29-May-2026 10:30:00 | K89: 46171.444 | L89: 46173.667 | M89: =IF(D89>44999.99,100,ROUNDUP((D89/4999.99)*10,-1)) -> 100 | N89: N | O89: ='[14]B1& B2 UNSCHEDULED'!$O$24 -> 0 | Q89: N | R89: =IF(L89="",AKHIR-J89,L89-J89+1) -> 3.2291667 | S89: =WORKDAY(J89,6,AKHIR) -> 46181 | T89: 0 | U89: =IF(Q89="N",0,M89*T89) -> 0 | V89: PROB :FALSE MESSAGE STATUS: UNDER TROUBLESHOOT BY GUIDING FROM SUPPLIER NUVIA Instruments GmbH
A90: Previous Month (Work Order Closed)
A91: 1 | B91: IKN400171 | C91: =VLOOKUP(B91,[13]AssetDetails_UEM!$A$3:$AH$1849,6,FALSE) -> Ventilators, Intensive Care | D91: =VLOOKUP(B91,[13]AssetDetails_UEM!$A$3:$AK$1849,22,FALSE) -> 151560 | E91: IKNWIBE26002579 | F91: 05IC131 | G91: DEVICE FAILURE | H91: Normal | I91: 0 days, 0 hrs, 10 mins | J91: 09-Feb-2026 09:00:00 | K91: 46062.382 | L91: 46153.493 | M91: =IF(D91>44999.99,100,ROUNDUP((D91/4999.99)*10,-1)) -> 100 | N91: N | O91: ='[14]B1& B2 UNSCHEDULED'!$O$24 -> 0 | Q91: Y | R91: =IF(L91="",AKHIR-J91,L91-J91+1) -> 92.118056 | S91: =WORKDAY(J91,6,AKHIR) -> 46070 | T91: 10 | U91: =IF(Q91="N",0,M91*T91) -> 1000 | V91: Quotation received : 9/02/26 PO Date : 17/2/26 Waiting Parts (from German) ETA : Middle May 2026 SH QE12-INSTALLED NEW REP-KIT LP PNEUMUTIKCONT 42dXL PCB board,reload new software unit test and functioning in good condition
A92: 2 | B92: IKN400168 | C92: =VLOOKUP(B92,[13]AssetDetails_UEM!$A$3:$AH$1849,6,FALSE) -> Ventilators, Intensive Care | D92: =VLOOKUP(B92,[13]AssetDetails_UEM!$A$3:$AK$1849,22,FALSE) -> 151560 | E92: IKNWIBE26003259 | F92: 05IC115 | G92: LCD BLANK - ICU ARAS 5 | H92: Normal | I92: 0 days, 0 hrs, 10 mins | J92: 20-Feb-2026 10:00:00 | K92: 46073.424 | L92: 46153.792 | M92: =IF(D92>44999.99,100,ROUNDUP((D92/4999.99)*10,-1)) -> 100 | N92: N | O92: ='[14]B1& B2 UNSCHEDULED'!$O$24 -> 0 | Q92: Y | R92: =IF(L92="",AKHIR-J92,L92-J92+1) -> 81.375 | S92: =WORKDAY(J92,6,AKHIR) -> 46083 | T92: 10 | U92: =IF(Q92="N",0,M92*T92) -> 1000 | V92: Quotation received : 25-26/02/26 PO Date : 26/2/26 Waiting Parts (Display board) ETA : Middle May 2026 L, QE:12- INSTALED NEW KIT DISPLAY , REPLACED NEW OXYGEN SENSOR , UNIT TEST AND FUNCTIONING IN GOOD CONDITION
A93: 3 | B93: IKN400787 | C93: =VLOOKUP(B93,[13]AssetDetails_UEM!$A$3:$AH$1849,6,FALSE) -> Radiographic Units, Mobile | D93: =VLOOKUP(B93,[13]AssetDetails_UEM!$A$3:$AK$1849,22,FALSE) -> 1149550 | E93: IKNWIBE26005007 | F93: 03ID106 | G93: CM - TUBE HEAD NOT FULLY LOCK | H93: Corrective Maintenance (CM) | I93: 0 days, 0 hrs, 10 mins | J93: 16-Mar-2026 14:00:00 | K93: 46097.59 | L93: 46156.667 | M93: =IF(D93>44999.99,100,ROUNDUP((D93/4999.99)*10,-1)) -> 100 | N93: N | O93: ='[14]B1& B2 UNSCHEDULED'!$O$24 -> 0 | Q93: Y | R93: =IF(L93="",AKHIR-J93,L93-J93+1) -> 60.083333 | S93: =WORKDAY(J93,6,AKHIR)+2 -> 46107 | T93: 13 | U93: =IF(Q93="N",0,M93*T93) -> 1300 | V93: PROBLEM : TUBE HEAD NOT FULLY LOCK SR NO : 122557 (16/3/2026) & 122558 (5/5/2026) STATUS : WAITING PARTS FROM VENDOR (CARESTREAM) L, QE:12-VENDOR TROUBLESHOOT AND NEED TO ESCALATE TO PRINCIPLE FOR FURTHER TROUBLESHHOOT . VENDOR REPLACE PART , TESTED TUBE HEAD STILL ABLE TO MOVE WHEN EXTRAFORCE APPLIED , VENDOR PERFORMED TAU BRAKE ADJUSTMENT , TESTED TO RELEASED THE BRAKE AND ABSERVE THE TUBE HEAD NO TUBE DROP OR MOVEMENT
A94: 4 | B94: IKN400937 | C94: =VLOOKUP(B94,[13]AssetDetails_UEM!$A$3:$AH$1849,6,FALSE) -> Sphygmomanometers, Electronic, Automatic | D94: =VLOOKUP(B94,[13]AssetDetails_UEM!$A$3:$AK$1849,22,FALSE) -> 336 | E94: IKNWIBE26005651 | F94: 03MC127 | G94: BP Set Screen Blinking - MBC Aras 3 | H94: Normal | I94: 0 days, 0 hrs, 04 mins | J94: 24-Mar-2026 16:04:00 | K94: 46105.674 | L94: 15-May-2026 16:00:00 | M94: =IF(D94>44999.99,100,ROUNDUP((D94/4999.99)*10,-1)) -> 10 | N94: N | O94: ='[14]B1& B2 UNSCHEDULED'!$O$24 -> 0 | Q94: Y | R94: =IF(L94="",AKHIR-J94,L94-J94+1) -> 52.997222 | S94: =WORKDAY(J94,5,AKHIR) -> 46112 | T94: 14 | U94: =IF(Q94="N",0,M94*T94) -> 140 | V94: WAITING PARTS FROM VENDOR (Welch Allyn) PROBLEM : LCD BOARD FAULTY Quotation:30/3/2026 PO: 71520, 31/3/2026 ETA : Middle May 2026 L, QE:16- DISMANTLE MACHINE, FOUND OUT LCD BOARD FAILURE CAUSE BLINKING , REPLACE NEW LCD BOARD ,FUNCTION AND TESTED FIT TO USE FUNCTIONING
A95: 5 | B95: IKN401353 | C95: =VLOOKUP(B95,[13]AssetDetails_UEM!$A$3:$AH$1849,6,FALSE) -> Radiographic/Fluoroscopic Units, Mobile | D95: =VLOOKUP(B95,[13]AssetDetails_UEM!$A$3:$AK$1849,22,FALSE) -> 399000 | E95: IKNWIBE26008078 | F95: 05OT159 | G95: MACHINE CANNOT SHOOT | H95: Normal | I95: 0 days, 0 hrs, 10 mins | J95: 28-Apr-2026 10:30:00 | K95: 46140.444 | L95: 46154.667 | M95: =IF(D95>44999.99,100,ROUNDUP((D95/4999.99)*10,-1)) -> 100 | N95: N | O95: ='[14]B1& B2 UNSCHEDULED'!$O$24 -> 0 | Q95: Y | R95: =IF(L95="",AKHIR-J95,L95-J95+1) -> 15.229167 | S95: =WORKDAY(J95,6,AKHIR) -> 46148 | T95: 5 | U95: =IF(Q95="N",0,M95*T95) -> 500 | V95: PROB : INVERTER ERROR ,QUO DATE:30/4/2026 STATUS : UNDER TROUBLESHOOTING BY SPECIALIST VENDOR TITAN ON 6,8 &12/5/2026 L, QE:12- FUTHER TROUBLESHOOT BY VENDOR AND FOUND PIN AT CONNECTOR PLUG WAS BURNED. PIN WAS REPLACED. TESTED OK
A96: 6 | B96: IKN400758 | C96: =VLOOKUP(B96,[13]AssetDetails_UEM!$A$3:$AH$1849,6,FALSE) -> Analyzers, Laboratory, Urine, Automated | D96: =VLOOKUP(B96,[13]AssetDetails_UEM!$A$3:$AK$1849,22,FALSE) -> 36080 | E96: IKNWIBE26008154 | F96: 04LA132 | G96: MACHINE IRIS STRIP | H96: Normal | I96: 0 days, 0 hrs, 30 mins | J96: 46141.646 | K96: 46141.667 | L96: 46148.667 | M96: =IF(D96>44999.99,100,ROUNDUP((D96/4999.99)*10,-1)) -> 80 | N96: N | O96: ='[14]B1& B2 UNSCHEDULED'!$O$24 -> 0 | Q96: N | R96: 7 | S96: =WORKDAY(J96,6,AKHIR) -> 46149 | T96: 0 | U96: =IF(Q96="N",0,M96*T96) -> 0 | V96: STRIP CONVEYOR STUCK, DONE CLEAN THE MOTOR AND TESTED OK
A97: 7 | B97: IKN401071 | C97: =VLOOKUP(B97,[13]AssetDetails_UEM!$A$3:$AH$1849,6,FALSE) -> Video Image Processors, Endoscopic | D97: =VLOOKUP(B97,[13]AssetDetails_UEM!$A$3:$AK$1849,22,FALSE) -> 80000 | E97: IKNWIBE26008234 | F97: 03MC108 | G97: RUSTED METAL ON THE TOWER SCOPE IS REQUESTED TO BE REPAINTED | H97: Normal | I97: 0 days, 0 hrs, 10 mins | J97: 30-Apr-2026 17:00:00 | K97: 46142.715 | L97: 01-May-2026 12:00:00 | M97: =IF(D97>44999.99,100,ROUNDUP((D97/4999.99)*10,-1)) -> 100 | N97: N | O97: ='[14]B1& B2 UNSCHEDULED'!$O$24 -> 0 | Q97: N | R97: =IF(L97="",AKHIR-J97,L97-J97+1) -> 1.7916667 | S97: =WORKDAY(J97,6,AKHIR) -> 46150 | T97: 0 | U97: =IF(Q97="N",0,M97*T97) -> 0 | V97: M-PAINT AS PER REQUESTED
A98: Previous Month (Work Order Open)
A99: 1 | B99: IKN401007 | C99: =VLOOKUP(B99,[13]AssetDetails_UEM!$A$3:$AH$1849,6,FALSE) -> Washers, Flexible Endoscope | D99: =VLOOKUP(B99,[13]AssetDetails_UEM!$A$3:$AK$1849,22,FALSE) -> 126300 | E99: IKNWIBE26005707 | F99: 03MC111 | G99: MESIN REPROCESSING KELUAR ERROR E61 | H99: Normal | I99: 0 days, 0 hrs, 17 mins | J99: 46106.499 | K99: 46106.51 | L99: 46173.958 | M99: =IF(D99>44999.99,100,ROUNDUP((D99/4999.99)*10,-1)) -> 100 | N99: N | O99: ='[14]B1& B2 UNSCHEDULED'!$O$24 -> 0 | Q99: N | R99: =IF(L99="",AKHIR-J99,L99-J99+1) -> 68.459734 | S99: =WORKDAY(J99,5,AKHIR) -> 46113 | T99: 30 | U99: =IF(Q99="N",0,M99*T99) -> 0 | V99: VENDOR DONE TROUBLESHOOT ON 26/3/2026 & 6/4/2026 (OLYMPUS) PROBLEM : THE SENSOR FAULTY. QUOTATION RECEIVED : 10/4/2026 (SOW000876) & 24/4/2026 (280001613) PO DATE : AWSB-72253 & AWSB-72586 ETA : End June 2026. Loan unit given 15/4/25 | W99: 6-15 April 8hari
A100: 2 | B100: IKN400200 | C100: =VLOOKUP(B100,[13]AssetDetails_UEM!$A$3:$AH$1849,6,FALSE) -> Mattress Systems, Alternating-Pressure | D100: =VLOOKUP(B100,[13]AssetDetails_UEM!$A$3:$AK$1849,22,FALSE) -> 28630 | E100: IKNWIBE26006149 | F100: 09WJ126 | G100: MESIN RIPPLE MATTRESS ROSAK | H100: Normal | I100: 0 days, 0 hrs, 20 mins | J100: 46113.535 | K100: 46113.552 | L100: 46173.958 | M100: =IF(D100>44999.99,100,ROUNDUP((D100/4999.99)*10,-1)) -> 60 | N100: N | O100: ='[14]B1& B2 UNSCHEDULED'!$O$24 -> 0 | Q100: N | R100: =IF(L100="",AKHIR-J100,L100-J100+1) -> 61.423623 | S100: =WORKDAY(J100,6,AKHIR) -> 46121 | T100: 30 | U100: =IF(Q100="N",0,M100*T100) -> 0 | V100: PROB: DOUBLE COMPRESSOR ASSEMBLY FAULTY REQ QUO DATE : 6/4/2026 QUO DATE : 30/4/2026 PO: AWSB 72180. Loaner 9/4/26
A101: 3 | B101: IKN402139 | C101: =VLOOKUP(B101,[13]AssetDetails_UEM!$A$3:$AH$1849,6,FALSE) -> Bronchoscopes, Flexible | D101: =VLOOKUP(B101,[13]AssetDetails_UEM!$A$3:$AK$1849,22,FALSE) -> 58000 | E101: IKNWIBE26006568 | F101: 05IC115 | G101: ANGULATION NOT FUNCTIONING PROPERLY | H101: Normal | I101: 0 days, 0 hrs, 30 mins | J101: 46119.479 | K101: 46119.5 | L101: 46173.958 | M101: =IF(D101>44999.99,100,ROUNDUP((D101/4999.99)*10,-1)) -> 100 | N101: N | O101: ='[14]B1& B2 UNSCHEDULED'!$O$24 -> 0 | Q101: N | R101: =IF(L101="",AKHIR-J101,L101-J101+1) -> 55.479178 | S101: =WORKDAY(J101,6,AKHIR) -> 46127 | T101: 30 | U101: 0 | V101: PROB: ANGULATION PROBLEM DN : 7/4/2026 (DONE GIVE LOANER UNIT) STATUS : SEND TO VENDOR (HOSPIMETRIX SDN BHD) FOR FURTHER TROUBLESHOOT. | W101: waiting update from vendor by email. Done arrived at malaysia yesterday
A102: 4 | B102: IKN400973 | C102: =VLOOKUP(B102,[13]AssetDetails_UEM!$A$3:$AH$1849,6,FALSE) -> Scanning Systems, Computed Tomography | D102: =VLOOKUP(B102,[13]AssetDetails_UEM!$A$3:$AK$1849,22,FALSE) -> 3557530 | E102: IKNWIBE26006779 | F102: 01RT118 | G102: LASER PUDAR BAHAGIAN KANAN | H102: Normal | I102: 0 days, 0 hrs, 23 mins | J102: 10-Apr-2026 09:57:00 | K102: 46122.431 | L102: 46173.958 | M102: =IF(D102>44999.99,100,ROUNDUP((D102/4999.99)*10,-1)) -> 100 | N102: N | O102: ='[14]B1& B2 UNSCHEDULED'!$O$24 -> 0 | Q102: Y | R102: =IF(L102="",AKHIR-J102,L102-J102+1) -> 52.543762 | S102: =WORKDAY(J102,6,AKHIR) -> 46132 | T102: 30 | U102: =IF(Q102="N",0,M102*T102) -> 3000 | V102: PROB: LASER MODULE FAULTY QUO DATE : 14/4/2026 FROM VENDOR DELTA PO DATE : 24/4/2026 (PO:AWSB-72348) ETA : END June 2026
A103: 5 | B103: IKN400762 | C103: =VLOOKUP(B103,[13]AssetDetails_UEM!$A$3:$AH$1849,6,FALSE) -> Analyzers, Laboratory, Immunoassay, Chemiluminescent | D103: =VLOOKUP(B103,[13]AssetDetails_UEM!$A$3:$AK$1849,22,FALSE) -> 1443450 | E103: IKNWIBE26006790 | F103: 04LA133 | G103: MESIN ARKITEK LEAKING PATOLOGI | H103: Normal | I103: 0 days, 0 hrs, 53 mins | J103: 10-Apr-2026 14:07:00 | K103: 46122.625 | L103: 46173.958 | M103: =IF(D103>44999.99,100,ROUNDUP((D103/4999.99)*10,-1)) -> 100 | N103: N | O103: ='[14]B1& B2 UNSCHEDULED'!$O$24 -> 0 | Q103: Y | R103: =IF(L104="",AKHIR-J104,L104-J104+1) -> 34.666678 | S103: =WORKDAY(J104,6,AKHIR) -> 46147 | T103: 25 | U103: =IF(Q103="N",0,M103*T103) -> 2500 | V103: PROB: RO BOTTLE CRACK QUO DATE : 16/4/2026 (Q3121389) PO DATE : 24/4/2026 (AWSB-72351) ETA :Waiting date manufacture
A104: 6 | B104: IKN401261 | C104: =VLOOKUP(B104,[13]AssetDetails_UEM!$A$3:$AH$1849,6,FALSE) -> Mattress Systems, Alternating-Pressure | D104: =VLOOKUP(B104,[13]AssetDetails_UEM!$A$3:$AK$1849,22,FALSE) -> 28630 | E104: IKNWIBE26007972 | F104: 05WB113 | G104: MESIN RIPPLE MATTRESS KEMPIS | H104: Normal | I104: 0 days, 0 hrs, 37 mins | J104: 27-Apr-2026 19:00:00 | K104: 46139.817 | L104: 46173.458 | M104: =IF(D104>44999.99,100,ROUNDUP((D104/4999.99)*10,-1)) -> 60 | N104: N | O104: ='[14]B1& B2 UNSCHEDULED'!$O$24 -> 0 | Q104: Y | R104: =IF(L105="",AKHIR-J105,L105-J105+1) -> 32.618056 | S104: =WORKDAY(J105,6,AKHIR) -> 46148 | T104: 24 | U104: =IF(Q104="N",0,M104*T104) -> 1440 | V104: PROB: SHUTTER VALVE FAULTY QUO DATE :13-05-2026 PO DATE: 15/5/2026 (AWSB-900126) ETA:2-3 MONTHS WAITING PARTS
A105: 7 | B105: IKN400565 | C105: =VLOOKUP(B105,[13]AssetDetails_UEM!$A$3:$AH$1849,6,FALSE) -> Physiologic Monitoring Systems, Stress Exercise | D105: =VLOOKUP(B105,[13]AssetDetails_UEM!$A$3:$AK$1849,22,FALSE) -> 138350 | E105: IKNWIBE26008075 | F105: 03NM155 | G105: ECG- CABLE NOT DETECT | H105: Normal | I105: 0 days, 0 hrs, 10 mins | J105: 28-Apr-2026 09:10:00 | K105: 46140.389 | M105: =IF(D105>44999.99,100,ROUNDUP((D105/4999.99)*10,-1)) -> 100 | N105: N | O105: ='[14]B1& B2 UNSCHEDULED'!$O$24 -> 0 | Q105: Y | R105: 8 | S105: =WORKDAY(J105,6,AKHIR) -> 46148 | T105: 24 | U105: =IF(Q105="N",0,M105*T105) -> 2400 | V105: PROB : ECG FAULTY QUO DATE : 28/4/2026 PO DATE : 5/5/2026 (AWSB-72179) STATUS : WAITING PARTS FROM VENDOR RICHONE ETA : Middle June 2026 Asset EOL
A106: TOTAL DEDUCTION FOR IND. B.1: | O106: - | P106: TOTAL DEDUCTION FOR IND. B.2: | U106: =SUM(U24:U105) -> 13280

Sheet B3-SCHEDULED
A3: MINISTRY OF HEALTH
A4: Deduction Mapping Report Biomedical Engineering Maintenance Services (BEMS)
A5: INDICATOR B.3 SCHEDULED MAINTENANCE
A7: HOSPITAL NAME : | C7: INSTITUT KANSER NEGARA | H7: MONTH/YEAR : | J7: 46143
B9: STATE : | C9: WILAYAH PERSEKUTUAN PUTRAJAYA | G9: BEMS MONTHLY FEE (RM) @ 97.5% : | J9: =BEMSdar!E11 -> 1329813.2
B11: COMPANY : | C11: AMBANG WIRA SDN BHD | G11: FMS MONTHLY FEE (RM) @ 2.5% : | J11: =BEMSdar!E13 -> 34097.773
A13: Notes:
A14: 1) Deduction Ringgit Equivalent is based on Appendix 11 of the Agreement, Section B3 Key Deduction Indicators for BEMS
A15: 2) Deduction Value for Indicator B.3 is Deduction Ringgit Equivalent (per event)
A16: 3) Rescheduled Date is the final rescheduled date if there are multiple rescheduling
A17: 4) Display only asset affected by deduction
A19: No | B19: Asset No | C19: Asset Description | D19: Asset Purchase Price (RM) | E19: Work Order No. | F19: User Location | G19: Scheduled Start Date | H19: Maintenance Date | I19: Rescheduled Date | J19: Validate Status (Y/N) | K19: Deduction Ringgit Equivalent (RM) | L19: Indicator B.3
L20: Deduction Value (RM) | M20: Remarks/ Exemption
A21: Current Month (Closed)
A22: 1 | B22: IKN400699 | C22: Analgesia Units, Inhalation | D22: =VLOOKUP(B22,[13]AssetDetails_UEM!$A$3:$X$1848,22,FALSE) -> 96230 | E22: IKNWOBE26007422 | F22: 04PY130 | G22: 02-May-2026 00:00:00 | H22: 02-May-2026 10:00:00 | I22: NA | J22: N | K22: =ROUNDUP((D22/4999.99)*10,-1) -> 200 | L22: =IF(J22="N",0,K22) -> 0 | M22: L, QE:16 -UNIT PROPOSSED BER
A23: 2 | B23: IKN400034 | C23: Infusion/ Monitoring Line Organizer System | D23: =VLOOKUP(B23,[13]AssetDetails_UEM!$A$3:$X$1848,22,FALSE) -> 84200 | E23: IKNWOBE26007423 | F23: 05IC113 | G23: 04-May-2026 00:00:00 | H23: 04-May-2026 08:00:00 | I23: NA | J23: N | K23: =ROUNDUP((D23/4999.99)*10,-1) -> 170 | L23: =IF(J23="N",0,K23) -> 0 | M23: L, QE:16- MAINTENANCE DONE AS PER HEPPM CHECKLIST ATTACHED,UNIT FUNCTIONING IN GOOD CONDITION
A24: 3 | B24: IKN400099 | C24: Infusion Pumps, Syringe | D24: =VLOOKUP(B24,[13]AssetDetails_UEM!$A$3:$X$1848,22,FALSE) -> 10225 | E24: IKNWOBE26007424 | F24: 05IC113 | G24: 04-May-2026 00:00:00 | H24: 04-May-2026 09:00:00 | I24: NA | J24: N | K24: =ROUNDUP((D24/4999.99)*10,-1) -> 30 | L24: =IF(J24="N",0,K24) -> 0 | M24: L, QE:16- MAINTENANCE DONE AS PER HEPPM CHECKLIST ATTACHED,UNIT FUNCTIONING IN GOOD CONDITION
A25: 4 | B25: IKN400100 | C25: Infusion Pumps, Syringe | D25: =VLOOKUP(B25,[13]AssetDetails_UEM!$A$3:$X$1848,22,FALSE) -> 10225 | E25: IKNWOBE26007425 | F25: 05IC113 | G25: 04-May-2026 00:00:00 | H25: 04-May-2026 10:00:00 | I25: NA | J25: N | K25: =ROUNDUP((D25/4999.99)*10,-1) -> 30 | L25: =IF(J25="N",0,K25) -> 0 | M25: L, QE:16 -MAINTENANCE DONE AS PER HEPPM CHECKLIST ATTACHED, UNIT FUNCTIONING IN GOOD CONDITION
A26: 5 | B26: IKN400101 | C26: Infusion Pumps, Syringe | D26: =VLOOKUP(B26,[13]AssetDetails_UEM!$A$3:$X$1848,22,FALSE) -> 10225 | E26: IKNWOBE26007426 | F26: 05IC113 | G26: 04-May-2026 00:00:00 | H26: 04-May-2026 11:00:00 | I26: NA | J26: N | K26: =ROUNDUP((D26/4999.99)*10,-1) -> 30 | L26: =IF(J26="N",0,K26) -> 0 | M26: L, QE:16- MAINTENANCE DONE AS PER HEPPM CHECKLIST ATTACHED,UNIT FUNCTIONING IN GOOD CONDITION
A27: 6 | B27: IKN400102 | C27: Infusion Pumps, Syringe | D27: =VLOOKUP(B27,[13]AssetDetails_UEM!$A$3:$X$1848,22,FALSE) -> 10225 | E27: IKNWOBE26007427 | F27: 05IC113 | G27: 04-May-2026 00:00:00 | H27: 04-May-2026 12:00:00 | I27: NA | J27: N | K27: =ROUNDUP((D27/4999.99)*10,-1) -> 30 | L27: =IF(J27="N",0,K27) -> 0 | M27: L, QE:16- MAINTENANCE DONE AS PER HEPPM CHECKLIST ATTACHED,UNIT FUNCTIONING IN GOOD CONDITION
A28: 7 | B28: IKN400103 | C28: Infusion Pumps, Syringe | D28: =VLOOKUP(B28,[13]AssetDetails_UEM!$A$3:$X$1848,22,FALSE) -> 10225 | E28: IKNWOBE26007428 | F28: 05IC113 | G28: 04-May-2026 00:00:00 | H28: 04-May-2026 16:00:00 | I28: NA | J28: N | K28: =ROUNDUP((D28/4999.99)*10,-1) -> 30 | L28: =IF(J28="N",0,K28) -> 0 | M28: L, QE:16- MAINTENANCE DONE AS PER HEPPM CHECKLIST ATTACHED,UNIT FUNCTIONING IN GOOD CONDITION
A29: 8 | B29: IKN400104 | C29: Infusion Pumps, Syringe | D29: =VLOOKUP(B29,[13]AssetDetails_UEM!$A$3:$X$1848,22,FALSE) -> 10225 | E29: IKNWOBE26007429 | F29: 05IC113 | G29: 04-May-2026 00:00:00 | H29: 04-May-2026 15:00:00 | I29: NA | J29: N | K29: =ROUNDUP((D29/4999.99)*10,-1) -> 30 | L29: =IF(J29="N",0,K29) -> 0 | M29: L, QE:16- MAINTENANCE DONE AS PER HEPPM CHECKLIST ATTACHED,UNIT FUNCTIONING IN GOOD CONDITION
A30: 9 | B30: IKN400139 | C30: Infusion Pumps, General-Purpose | D30: =VLOOKUP(B30,[13]AssetDetails_UEM!$A$3:$X$1848,22,FALSE) -> 10825 | E30: IKNWOBE26007430 | F30: 05IC113 | G30: 04-May-2026 00:00:00 | H30: 04-May-2026 16:00:00 | I30: NA | J30: N | K30: =ROUNDUP((D30/4999.99)*10,-1) -> 30 | L30: =IF(J30="N",0,K30) -> 0 | M30: L, QE:16- MAINTENANCE DONE AS PER HEPPM CHECKLIST ATTACHED,UNIT FUNCTIONING IN GOOD CONDITION
A31: 10 | B31: IKN400140 | C31: Infusion Pumps, General-Purpose | D31: =VLOOKUP(B31,[13]AssetDetails_UEM!$A$3:$X$1848,22,FALSE) -> 10825 | E31: IKNWOBE26007431 | F31: 05IC113 | G31: 04-May-2026 00:00:00 | H31: 04-May-2026 17:30:00 | I31: NA | J31: N | K31: =ROUNDUP((D31/4999.99)*10,-1) -> 30 | L31: =IF(J31="N",0,K31) -> 0 | M31: L, QE:16- MAINTENANCE DONE AS PER HEPPM CHECKLIST ATTACHED,UNIT FUNCTIONING IN GOOD CONDITION
A32: 11 | B32: IKN400667 | C32: Stimulators, Electrical, Peripheral Nerve, Acupuncture | D32: =VLOOKUP(B32,[13]AssetDetails_UEM!$A$3:$X$1848,22,FALSE) -> 10725 | E32: IKNWOBE26007432 | F32: 04TC108 | G32: 04-May-2026 00:00:00 | H32: 04-May-2026 15:50:00 | I32: NA | J32: N | K32: =ROUNDUP((D32/4999.99)*10,-1) -> 30 | L32: =IF(J32="N",0,K32) -> 0 | M32: L, QE:16- PPM DONE AS PER HEPPM CHECKLIST
A33: 12 | B33: IKN400670 | C33: Stimulators, Electrical, Peripheral Nerve, Acupuncture | D33: =VLOOKUP(B33,[13]AssetDetails_UEM!$A$3:$X$1848,22,FALSE) -> 10725 | E33: IKNWOBE26007433 | F33: 04TC129 | G33: 04-May-2026 00:00:00 | H33: 04-May-2026 15:50:00 | I33: NA | J33: N | K33: =ROUNDUP((D33/4999.99)*10,-1) -> 30 | L33: =IF(J33="N",0,K33) -> 0 | M33: L, QE:16- PPM DONE AS PER HEPPM CHECKLIST
... A40: 19 | B40: IKN400806 | C40: Cystoscopes, Flexible | D40: =VLOOKUP(B40,[13]AssetDetails_UEM!$A$3:$X$1848,22,FALSE) -> 37408 | E40: IKNWOBE26007440 | F40: 01RT233 | G40: 04-May-2026 00:00:00 | H40: 04-May-2026 20:00:00 | I40: NA | J40: N | K40: =ROUNDUP((D40/4999.99)*10,-1) -> 80 | L40: =IF(J40="N",0,K40) -> 0 | M40: L, QE:16- MAINTENANCE DONE AS PER HEPPM CHECKLIST ATTACHED,UNIT FUNCTIONING IN GOOD CONDITION
A41: 20 | B41: IKN400961 | C41: Physiologic Monitoring Systems, Acute Care | D41: =VLOOKUP(B41,[13]AssetDetails_UEM!$A$3:$X$1848,22,FALSE) -> 87400 | E41: IKNWOBE26007441 | F41: 01RT212 | G41: 04-May-2026 00:00:00 | H41: 46146.417 | I41: NA | J41: N | K41: =ROUNDUP((D41/4999.99)*10,-1) -> 180 | L41: =IF(J41="N",0,K41) -> 0 | M41: AN-QE:16, PPM DONE AS PER HEPPM CHECKLIST
A42: 21 | B42: IKN400226 | C42: Infusion Pumps, General-Purpose | D42: =VLOOKUP(B42,[13]AssetDetails_UEM!$A$3:$X$1848,22,FALSE) -> 10825 | E42: IKNWOBE26007443 | F42: 09WJ126 | G42: 06-May-2026 00:00:00 | H42: 06-May-2026 08:00:00 | I42: NA | J42: N | K42: =ROUNDUP((D42/4999.99)*10,-1) -> 30 | L42: =IF(J42="N",0,K42) -> 0 | M42: L, QE:16- PPM DONE AS PERCHECKLIST
A43: 22 | B43: IKN400227 | C43: Infusion Pumps, General-Purpose | D43: =VLOOKUP(B43,[13]AssetDetails_UEM!$A$3:$X$1848,22,FALSE) -> 10825 | E43: IKNWOBE26007444 | F43: 09WJ126 | G43: 06-May-2026 00:00:00 | H43: 06-May-2026 10:00:00 | I43: NA | J43: N | K43: =ROUNDUP((D43/4999.99)*10,-1) -> 30 | L43: =IF(J43="N",0,K43) -> 0 | M43: L, QE:16- PPM DONE AS PERCHECKLIST
A44: 23 | B44: IKN400228 | C44: Infusion Pumps, General-Purpose | D44: =VLOOKUP(B44,[13]AssetDetails_UEM!$A$3:$X$1848,22,FALSE) -> 10825 | E44: IKNWOBE26007445 | F44: 09WJ126 | G44: 06-May-2026 00:00:00 | H44: 06-May-2026 11:00:00 | I44: NA | J44: N | K44: =ROUNDUP((D44/4999.99)*10,-1) -> 30 | L44: =IF(J44="N",0,K44) -> 0 | M44: L, QE:16- PPM DONE AS PERCHECKLIST AT 09WJ222 9B
A45: 24 | B45: IKN400229 | C45: Infusion Pumps, General-Purpose | D45: =VLOOKUP(B45,[13]AssetDetails_UEM!$A$3:$X$1848,22,FALSE) -> 10825 | E45: IKNWOBE26007446 | F45: 09WJ126 | G45: 06-May-2026 00:00:00 | H45: 06-May-2026 12:00:00 | I45: NA | J45: N | K45: =ROUNDUP((D45/4999.99)*10,-1) -> 30 | L45: =IF(J45="N",0,K45) -> 0 | M45: L, QE:16- PPM DONE AS PERCHECKLIST,
A46: 25 | B46: IKN400304 | C46: Incubators, Laboratory, Thermocycling | D46: =VLOOKUP(B46,[13]AssetDetails_UEM!$A$3:$X$1848,22,FALSE) -> 16240 | E46: IKNWOBE26007447 | F46: 03NM112 | G46: 07-May-2026 00:00:00 | H46: 07-May-2026 11:00:00 | I46: NA | J46: N | K46: =ROUNDUP((D46/4999.99)*10,-1) -> 40 | L46: =IF(J46="N",0,K46) -> 0 | M46: AN- QE:16, PPM DONE AS PER HEPPM CHECKLIST
A47: 26 | B47: IKN400714 | C47: Incubators, Test Tube, Portable | D47: =VLOOKUP(B47,[13]AssetDetails_UEM!$A$3:$X$1848,22,FALSE) -> 14435 | E47: IKNWOBE26007448 | F47: 04LA132 | G47: 07-May-2026 00:00:00 | H47: 07-May-2026 09:00:00 | I47: NA | J47: N | K47: =ROUNDUP((D47/4999.99)*10,-1) -> 30 | L47: =IF(J47="N",0,K47) -> 0 | M47: AN-QE:16, PPM DONE AS PER HEPPM CHECKLIST
A48: 27 | B48: IKN400717 | C48: Incubators, Test Tube, Portable | D48: =VLOOKUP(B48,[13]AssetDetails_UEM!$A$3:$X$1848,22,FALSE) -> 14435 | E48: IKNWOBE26007449 | F48: 04LA140 | G48: 07-May-2026 00:00:00 | H48: 07-May-2026 10:00:00 | I48: NA | J48: N | K48: =ROUNDUP((D48/4999.99)*10,-1) -> 30 | L48: =IF(J48="N",0,K48) -> 0 | M48: AN- QE:16. PPM DONE AS PER HEPPM CHECKLIST
A49: 28 | B49: IKN402145 | C49: Scanning Systems, Ultrasonic, General-Purpose | D49: =VLOOKUP(B49,[13]AssetDetails_UEM!$A$3:$X$1848,22,FALSE) -> 68500 | E49: IKNWOBE26007450 | F49: 06WC107 | G49: 07-May-2026 00:00:00 | H49: 07-May-2026 15:30:00 | I49: NA | J49: N | K49: =ROUNDUP((D49/4999.99)*10,-1) -> 140 | L49: =IF(J49="N",0,K49) -> 0 | M49: L, QE:16- PPM DONE AS PERCHECKLIST
A50: 29 | B50: IKN402174 | C50: Testers | D50: =VLOOKUP(B50,[13]AssetDetails_UEM!$A$3:$X$1848,22,FALSE) -> 8295.6 | E50: IKNWOBE26007452 | F50: 03ID169 | G50: 08-May-2026 00:00:00 | H50: 08-May-2026 08:30:00 | I50: NA | J50: N | K50: =ROUNDUP((D50/4999.99)*10,-1) -> 20 | L50: =IF(J50="N",0,K50) -> 0 | M50: L, QE:16- UNIT FUNCTIONING OKAY , PPM COMPLETE
A51: 30 | B51: IKN400967 | C51: Linear Accelerators | D51: =VLOOKUP(B51,[13]AssetDetails_UEM!$A$3:$X$1848,22,FALSE) -> 12049370 | E51: IKNWOBE26007453 | F51: 01RT165 | G51: 08-May-2026 00:00:00 | H51: 46150.75 | I51: NA | J51: N | K51: =ROUNDUP((D51/4999.99)*10,-1) -> 24100 | L51: =IF(J51="N",0,K51) -> 0 | M51: AN- QE:16. PPM DONE AS PER HEPPM CHECKLIST
A52: 31 | B52: IKN400737 | C52: Incubators, Laboratory, Thermocycling | D52: =VLOOKUP(B52,[13]AssetDetails_UEM!$A$3:$X$1848,22,FALSE) -> 16240 | E52: IKNWOBE26007454 | F52: 04LA126 | G52: 08-May-2026 00:00:00 | H52: 08-May-2026 10:00:00 | I52: NA | J52: N | K52: =ROUNDUP((D52/4999.99)*10,-1) -> 40 | L52: =IF(J52="N",0,K52) -> 0 | M52: AN- QE:16. PPM DONE AS PER HEPPM CHECKLIST
A53: 32 | B53: IKN400753 | C53: Mixers, Clinical Laboratory | D53: =VLOOKUP(B53,[13]AssetDetails_UEM!$A$3:$X$1848,22,FALSE) -> 1200 | E53: IKNWOBE26007455 | F53: 04LA126 | G53: 08-May-2026 00:00:00 | H53: 08-May-2026 09:30:00 | I53: NA | J53: N | K53: =ROUNDUP((D53/4999.99)*10,-1) -> 10 | L53: =IF(J53="N",0,K53) -> 0 | M53: AN- QE:16. PPM DONE AS PER HEPPM CHECKLIST
A54: 33 | B54: IKN400962 | C54: Physiologic Monitoring Systems, Acute Care | D54: =VLOOKUP(B54,[13]AssetDetails_UEM!$A$3:$X$1848,22,FALSE) -> 87400 | E54: IKNWOBE26007456 | F54: 01RT212 | G54: 08-May-2026 00:00:00 | H54: 46150.625 | I54: NA | J54: N | K54: =ROUNDUP((D54/4999.99)*10,-1) -> 180 | L54: =IF(J54="N",0,K54) -> 0 | M54: AN- QE:16. PPM DONE AS PER HEPPM CHECKLIST
A55: 34 | B55: IKN401003 | C55: Monitors, Bedside, Intracranial Pressure | D55: =VLOOKUP(B55,[13]AssetDetails_UEM!$A$3:$X$1848,22,FALSE) -> 62550 | E55: IKNWOBE26007457 | F55: 05OT169 | G55: 08-May-2026 00:00:00 | H55: 08-May-2026 08:00:00 | I55: NA | J55: N | K55: =ROUNDUP((D55/4999.99)*10,-1) -> 130 | L55: =IF(J55="N",0,K55) -> 0 | M55: L, QE:16- MAINTENANCE DONE AS PER HEPPM CHECKLIST ATTACHED,UNIT FUNCTIONING IN GOOD CONDITION
A56: 35 | B56: IKN401287 | C56: Cameras, Gamma | D56: =VLOOKUP(B56,[13]AssetDetails_UEM!$A$3:$X$1848,22,FALSE) -> 133788 | E56: IKNWOBE26007458 | F56: 03NM153 | G56: 08-May-2026 00:00:00 | H56: 08-May-2026 10:00:00 | I56: NA | J56: N | K56: =ROUNDUP((D56/4999.99)*10,-1) -> 270 | L56: =IF(J56="N",0,K56) -> 0 | M56: L, QE:16- PPM COMPLETE AS PER CHECKLIST.UNIT FUNCTIONING OKAY
A57: 36 | B57: IKN402025 | C57: Scanning Systems, Ultrasonic, General-Purpose | D57: =VLOOKUP(B57,[13]AssetDetails_UEM!$A$3:$X$1848,22,FALSE) -> 125000 | E57: IKNWOBE26007459 | F57: 03ID157 | G57: 08-May-2026 00:00:00 | H57: 08-May-2026 16:15:00 | I57: NA | J57: N | K57: =ROUNDUP((D57/4999.99)*10,-1) -> 260 | L57: =IF(J57="N",0,K57) -> 0 | M57: L, QE:16- PPM COMPLETE AS PER CHECKLIST.UNIT FUNCTIONING OKAY
A58: 37 | B58: IKN402120 | C58: Sedimentation Rate Units | D58: =VLOOKUP(B58,[13]AssetDetails_UEM!$A$3:$X$1848,22,FALSE) -> 10000 | E58: IKNWOBE26007460 | F58: 04LA136 | G58: 08-May-2026 00:00:00 | H58: 08-May-2026 11:30:00 | I58: NA | J58: N | K58: =ROUNDUP((D58/4999.99)*10,-1) -> 30 | L58: =IF(J58="N",0,K58) -> 0 | M58: AN- QE:16. PPM DONE AS PER HEPPM CHECKLIST
A59: 38 | B59: IKN401103 | C59: Lights, Surgical | D59: =VLOOKUP(B59,[13]AssetDetails_UEM!$A$3:$X$1848,22,FALSE) -> 10585 | E59: IKNWOBE26007461 | F59: 06WD124 | G59: 08-May-2026 00:00:00 | H59: 46150.375 | I59: NA | J59: N | K59: =ROUNDUP((D59/4999.99)*10,-1) -> 30 | L59: =IF(J59="N",0,K59) -> 0 | M59: AN- QE:16. PPM DONE AS PER HEPPM CHECKLIST
A60: 39 | B60: IKN400224 | C60: Infusion Pumps, Syringe | D60: =VLOOKUP(B60,[13]AssetDetails_UEM!$A$3:$X$1848,22,FALSE) -> 10225 | E60: IKNWOBE26007462 | F60: 09WJ126 | G60: 11-May-2026 00:00:00 | H60: 11-May-2026 16:00:00 | I60: NA | J60: N | K60: =ROUNDUP((D60/4999.99)*10,-1) -> 30 | L60: =IF(J60="N",0,K60) -> 0 | M60: L, QE:16- PPM DONE AS PERCHECKLIST AT 09WJ222 9B
A61: 40 | B61: IKN400225 | C61: Infusion Pumps, Syringe | D61: =VLOOKUP(B61,[13]AssetDetails_UEM!$A$3:$X$1848,22,FALSE) -> 10225 | E61: IKNWOBE26007463 | F61: 09WJ126 | G61: 11-May-2026 00:00:00 | H61: 11-May-2026 09:00:00 | I61: NA | J61: N | K61: =ROUNDUP((D61/4999.99)*10,-1) -> 30 | L61: =IF(J61="N",0,K61) -> 0 | M61: L, QE:16- PPM DONE AS PERCHECKLIST
A62: 41 | B62: IKN400230 | C62: Infusion Pumps, General-Purpose | D62: =VLOOKUP(B62,[13]AssetDetails_UEM!$A$3:$X$1848,22,FALSE) -> 10825 | E62: IKNWOBE26007464 | F62: 09WJ126 | G62: 11-May-2026 00:00:00 | H62: 11-May-2026 17:40:00 | I62: NA | J62: N | K62: =ROUNDUP((D62/4999.99)*10,-1) -> 30 | L62: =IF(J62="N",0,K62) -> 0 | M62: L, QE:16- PPM DONE AS PERCHECKLIST AT 09WJ222 9B
A63: 42 | B63: IKN400232 | C63: Infusion Pumps, General-Purpose | D63: =VLOOKUP(B63,[13]AssetDetails_UEM!$A$3:$X$1848,22,FALSE) -> 10825 | E63: IKNWOBE26007465 | F63: 09WJ126 | G63: 11-May-2026 00:00:00 | H63: 11-May-2026 10:00:00 | I63: NA | J63: N | K63: =ROUNDUP((D63/4999.99)*10,-1) -> 30 | L63: =IF(J63="N",0,K63) -> 0 | M63: L, QE:16- PPM DONE AS PERCHECKLIST
A64: 43 | B64: IKN400233 | C64: Infusion Pumps, General-Purpose | D64: =VLOOKUP(B64,[13]AssetDetails_UEM!$A$3:$X$1848,22,FALSE) -> 10825 | E64: IKNWOBE26007466 | F64: 09WJ126 | G64: 11-May-2026 00:00:00 | H64: 11-May-2026 11:00:00 | I64: NA | J64: N | K64: =ROUNDUP((D64/4999.99)*10,-1) -> 30 | L64: =IF(J64="N",0,K64) -> 0 | M64: L, QE:16- PPM DONE AS PERCHECKLIST
A65: 44 | B65: IKN400234 | C65: Infusion Pumps, General-Purpose | D65: =VLOOKUP(B65,[13]AssetDetails_UEM!$A$3:$X$1848,22,FALSE) -> 10825 | E65: IKNWOBE26007467 | F65: 09WJ126 | G65: 11-May-2026 00:00:00 | H65: 11-May-2026 08:30:00 | I65: NA | J65: N | K65: =ROUNDUP((D65/4999.99)*10,-1) -> 30 | L65: =IF(J65="N",0,K65) -> 0 | M65: L, QE:16- PPM DONE AS PERCHECKLIST
A66: 45 | B66: IKN400235 | C66: Infusion Pumps, General-Purpose | D66: =VLOOKUP(B66,[13]AssetDetails_UEM!$A$3:$X$1848,22,FALSE) -> 10825 | E66: IKNWOBE26007468 | F66: 09WJ126 | G66: 11-May-2026 00:00:00 | H66: 11-May-2026 13:00:00 | I66: NA | J66: N | K66: =ROUNDUP((D66/4999.99)*10,-1) -> 30 | L66: =IF(J66="N",0,K66) -> 0 | M66: L, QE:16- PPM DONE AS PERCHECKLIST
A67: 46 | B67: IKN400291 | C67: Infusion Pumps, General-Purpose | D67: =VLOOKUP(B67,[13]AssetDetails_UEM!$A$3:$X$1848,22,FALSE) -> 10825 | E67: IKNWOBE26007469 | F67: 08WH121 | G67: 11-May-2026 00:00:00 | H67: 11-May-2026 14:00:00 | I67: NA | J67: N | K67: =ROUNDUP((D67/4999.99)*10,-1) -> 30 | L67: =IF(J67="N",0,K67) -> 0 | M67: L, QE:16- PPM DONE AS PERCHECKLIST
A68: 47 | B68: IKN400296 | C68: Infusion Pumps, General-Purpose | D68: =VLOOKUP(B68,[13]AssetDetails_UEM!$A$3:$X$1848,22,FALSE) -> 10825 | E68: IKNWOBE26007470 | F68: 08WH121 | G68: 11-May-2026 00:00:00 | H68: 11-May-2026 12:00:00 | I68: NA | J68: N | K68: =ROUNDUP((D68/4999.99)*10,-1) -> 30 | L68: =IF(J68="N",0,K68) -> 0 | M68: L, QE:16- PPM DONE AS PERCHECKLIST
A69: 48 | B69: IKN400297 | C69: Infusion Pumps, General-Purpose | D69: =VLOOKUP(B69,[13]AssetDetails_UEM!$A$3:$X$1848,22,FALSE) -> 10825 | E69: IKNWOBE26007471 | F69: 08WH121 | G69: 11-May-2026 00:00:00 | H69: 11-May-2026 15:00:00 | I69: NA | J69: N | K69: =ROUNDUP((D69/4999.99)*10,-1) -> 30 | L69: =IF(J69="N",0,K69) -> 0 | M69: L, QE:16- PPM DONE AS PERCHECKLIST
A70: 49 | B70: IKN400311 | C70: Infusion Pumps, General-Purpose | D70: =VLOOKUP(B70,[13]AssetDetails_UEM!$A$3:$X$1848,22,FALSE) -> 10825 | E70: IKNWOBE26007472 | F70: 08WH121 | G70: 11-May-2026 00:00:00 | H70: 11-May-2026 08:00:00 | I70: NA | J70: N | K70: =ROUNDUP((D70/4999.99)*10,-1) -> 30 | L70: =IF(J70="N",0,K70) -> 0 | M70: L, QE:16- PPM DONE AS PERCHECKLIST
A71: 50 | B71: IKN400718 | C71: Baths, Water, Laboratory | D71: =VLOOKUP(B71,[13]AssetDetails_UEM!$A$3:$X$1848,22,FALSE) -> 4210 | E71: IKNWOBE26007475 | F71: 04LA140 | G71: 12-May-2026 00:00:00 | H71: 12-May-2026 15:00:00 | I71: NA | J71: N | K71: =ROUNDUP((D71/4999.99)*10,-1) -> 10 | L71: =IF(J71="N",0,K71) -> 0 | M71: AN- QE:16. PPM DONE AS PER HEPPM CHECKLIST ATTACHED
... A113: 92 | B113: IKN400008 | C113: Physiologic Monitoring Systems, Acute Care | D113: =VLOOKUP(B113,[13]AssetDetails_UEM!$A$3:$X$1848,22,FALSE) -> 87400 | E113: IKNWOBE26007526 | F113: 01AE119 | G113: 19-May-2026 00:00:00 | H113: 19-May-2026 11:00:00 | I113: NA | J113: N | K113: =ROUNDUP((D113/4999.99)*10,-1) -> 180 | L113: =IF(J113="N",0,K113) -> 0 | M113: L, QE:16- MAINTENANCE DONE AS PER HEPPM ATTACHED
A114: 93 | B114: IKN400340 | C114: Mattress Systems, Alternating-Pressure | D114: =VLOOKUP(B114,[13]AssetDetails_UEM!$A$3:$X$1848,22,FALSE) -> 28630 | E114: IKNWOBE26007527 | F114: 07WF121 | G114: 46161 | H114: 28-May-2026 19:30:00 | I114: 46182 | J114: N | K114: =ROUNDUP((D114/4999.99)*10,-1) -> 60 | L114: =IF(J114="N",0,K114) -> 0 | M114: L, QE:16- PPM HAS BEEN COMPLETE AS PER HEPPM CHECKLIST
A115: 94 | B115: IKN400353 | C115: Monitors, Physiologic, Vital Signs | D115: =VLOOKUP(B115,[13]AssetDetails_UEM!$A$3:$X$1848,22,FALSE) -> 18765 | E115: IKNWOBE26007528 | F115: 07WF133 | G115: 19-May-2026 00:00:00 | H115: 19-May-2026 14:30:00 | I115: NA | J115: N | K115: =ROUNDUP((D115/4999.99)*10,-1) -> 40 | L115: =IF(J115="N",0,K115) -> 0 | M115: L, QE:16- PPM HAS BEEN COMPLETE AS PER HEPPM CHECKLIST
A116: 95 | B116: IKN400360 | C116: Lights, Surgical | D116: =VLOOKUP(B116,[13]AssetDetails_UEM!$A$3:$X$1848,22,FALSE) -> 5050 | E116: IKNWOBE26007529 | F116: 07WE113 | G116: 19-May-2026 00:00:00 | H116: 19-May-2026 09:00:00 | I116: NA | J116: N | K116: =ROUNDUP((D116/4999.99)*10,-1) -> 20 | L116: =IF(J116="N",0,K116) -> 0 | M116: L, QE:16- PPM HAS BEEN COMPLETE AS PER HEPPM CHECKLIST
A117: 96 | B117: IKN402219 | C117: Laser Imagers | D117: =VLOOKUP(B117,[13]AssetDetails_UEM!$A$3:$X$1848,22,FALSE) -> #N/A | E117: IKNWOBE26007530 | F117: 03ID111 | G117: 19-May-2026 00:00:00 | H117: 19-May-2026 14:00:00 | I117: NA | J117: N | K117: =ROUNDUP((D117/4999.99)*10,-1) -> #N/A | L117: =IF(J117="N",0,K117) -> 0 | M117: L, QE:16- PPM COMPLETE BY VENDOR .UNIT TESTED OKAY
A118: 97 | B118: IKN402210 | C118: Scanning Systems, Magnetic Resonance Imaging, Full-Body | D118: =VLOOKUP(B118,[13]AssetDetails_UEM!$A$3:$X$1848,22,FALSE) -> #N/A | E118: IKNWOBE26007532 | F118: 03ID111 | G118: 20-May-2026 00:00:00 | H118: 20-May-2026 15:00:00 | I118: NA | J118: N | K118: =ROUNDUP((D118/4999.99)*10,-1) -> #N/A | L118: =IF(J118="N",0,K118) -> 0 | M118: L, QE:16- PPM COMPLETE AS PER CHECKLIST. TESTED OKAY
A119: 98 | B119: IKN402211 | C119: Anesthesia Units | D119: =VLOOKUP(B119,[13]AssetDetails_UEM!$A$3:$X$1848,22,FALSE) -> #N/A | E119: IKNWOBE26007533 | F119: 03ID111 | G119: 20-May-2026 00:00:00 | H119: 20-May-2026 10:00:00 | I119: NA | J119: N | K119: =ROUNDUP((D119/4999.99)*10,-1) -> #N/A | L119: =IF(J119="N",0,K119) -> 0 | M119: L, QE:16- PPM COMPLETE AS PER CHECKLIST. TESTED OKAY
A120: 99 | B120: IKN400036 | C120: Infusion/ Monitoring Line Organizer System | D120: =VLOOKUP(B120,[13]AssetDetails_UEM!$A$3:$X$1848,22,FALSE) -> 84200 | E120: IKNWOBE26007535 | F120: 05IC115 | G120: 20-May-2026 00:00:00 | H120: 20-May-2026 08:00:00 | I120: NA | J120: N | K120: =ROUNDUP((D120/4999.99)*10,-1) -> 170 | L120: =IF(J120="N",0,K120) -> 0 | M120: L, QE:16- MAINTENANCE DONE AS PER HEPPM CHECKLIST ATTACHED,UNIT FUNCTIONING AND WORKING IN GOOD CONDITION
A121: 100 | B121: IKN400083 | C121: Pumps, Enteral Feeding | D121: =VLOOKUP(B121,[13]AssetDetails_UEM!$A$3:$X$1848,22,FALSE) -> 6615 | E121: IKNWOBE26007536 | F121: 05IC115 | G121: 20-May-2026 00:00:00 | H121: 20-May-2026 09:00:00 | I121: NA | J121: N | K121: =ROUNDUP((D121/4999.99)*10,-1) -> 20 | L121: =IF(J121="N",0,K121) -> 0 | M121: L, QE:16- MAINTENANCE DONE ACCORDING TO HEPPM CHECKLIST ATTACHED,UNIT FUNCTIONING IN GOOD CONDITION
A122: 101 | B122: IKN400111 | C122: Infusion Pumps, Syringe | D122: =VLOOKUP(B122,[13]AssetDetails_UEM!$A$3:$X$1848,22,FALSE) -> 10225 | E122: IKNWOBE26007537 | F122: 05IC115 | G122: 20-May-2026 00:00:00 | H122: 20-May-2026 10:00:00 | I122: NA | J122: N | K122: =ROUNDUP((D122/4999.99)*10,-1) -> 30 | L122: =IF(J122="N",0,K122) -> 0 | M122: L, QE:16- MAINTENANCE DONE AS PER HEPPM CHECKLIST ATTACHED,UNIT FUNCTIONING IN GOOD CONDITION
A123: 102 | B123: IKN400112 | C123: Infusion Pumps, Syringe | D123: =VLOOKUP(B123,[13]AssetDetails_UEM!$A$3:$X$1848,22,FALSE) -> 10225 | E123: IKNWOBE26007538 | F123: 05IC115 | G123: 20-May-2026 00:00:00 | H123: 20-May-2026 08:30:00 | I123: NA | J123: N | K123: =ROUNDUP((D123/4999.99)*10,-1) -> 30 | L123: =IF(J123="N",0,K123) -> 0 | M123: L, QE:16- UNIT ALREADY BEYOND ECONOMIC REPAIR (BER) , UNIT CANNOT BE USED
A124: 103 | B124: IKN400113 | C124: Infusion Pumps, Syringe | D124: =VLOOKUP(B124,[13]AssetDetails_UEM!$A$3:$X$1848,22,FALSE) -> 10225 | E124: IKNWOBE26007539 | F124: 05IC115 | G124: 20-May-2026 00:00:00 | H124: 20-May-2026 11:00:00 | I124: NA | J124: N | K124: =ROUNDUP((D124/4999.99)*10,-1) -> 30 | L124: =IF(J124="N",0,K124) -> 0 | M124: L, QE:16- MAINTENANCE DONE ACCORDING TO HEPPM CHECKLIST ATTACHED,UNIT FUNCTIONING IN GOOD CONDITION
A125: 104 | B125: IKN400114 | C125: Infusion Pumps, Syringe | D125: =VLOOKUP(B125,[13]AssetDetails_UEM!$A$3:$X$1848,22,FALSE) -> 10225 | E125: IKNWOBE26007540 | F125: 05IC115 | G125: 20-May-2026 00:00:00 | H125: 20-May-2026 12:00:00 | I125: NA | J125: N | K125: =ROUNDUP((D125/4999.99)*10,-1) -> 30 | L125: =IF(J125="N",0,K125) -> 0 | M125: L, QE:16- MAINTENANCE DONE AS PER HEPPM CHECKLIST ATTACHED,UNIT FUNCTIONING IN GOOD CONDITION
A126: 105 | B126: IKN400115 | C126: Infusion Pumps, Syringe | D126: =VLOOKUP(B126,[13]AssetDetails_UEM!$A$3:$X$1848,22,FALSE) -> 10225 | E126: IKNWOBE26007541 | F126: 05IC115 | G126: 20-May-2026 00:00:00 | H126: 20-May-2026 14:00:00 | I126: NA | J126: N | K126: =ROUNDUP((D126/4999.99)*10,-1) -> 30 | L126: =IF(J126="N",0,K126) -> 0 | M126: L, QE:16- MAINTENANCE DONE AS PER HEPPM CHECKLIST ATTACHED,UNIT FUNCTIONING IN GOOD CONDITION
... A134: 113 | B134: IKN400870 | C134: Warming Units, Patient, Forced-Air | D134: =VLOOKUP(B134,[13]AssetDetails_UEM!$A$3:$X$1848,22,FALSE) -> 4950 | E134: IKNWOBE26007549 | F134: 01RT118 | G134: 20-May-2026 00:00:00 | H134: 20-May-2026 13:15:00 | I134: NA | J134: N | K134: =ROUNDUP((D134/4999.99)*10,-1) -> 10 | L134: =IF(J134="N",0,K134) -> 0 | M134: L, QE:16- MAINTENANCE DONE AS PER HEPPM CHECKLIST ATTACHED
A135: 114 | B135: IKN400963 | C135: Warming Units, Patient, Radiant, Adult | D135: =VLOOKUP(B135,[13]AssetDetails_UEM!$A$3:$X$1848,22,FALSE) -> 12630 | E135: IKNWOBE26007550 | F135: 01RT212 | G135: 20-May-2026 00:00:00 | H135: 46162.556 | I135: NA | J135: N | K135: =ROUNDUP((D135/4999.99)*10,-1) -> 30 | L135: =IF(J135="N",0,K135) -> 0 | M135: L, QE:16- MAINTENANCE DONE AS PER HEPPM CHECKLIST ATTACHED
A136: 115 | B136: IKN400969 | C136: Warming Units, Patient, Forced-Air | D136: =VLOOKUP(B136,[13]AssetDetails_UEM!$A$3:$X$1848,22,FALSE) -> 15515 | E136: IKNWOBE26007551 | F136: 01RT116 | G136: 20-May-2026 00:00:00 | H136: 46162.458 | I136: NA | J136: N | K136: =ROUNDUP((D136/4999.99)*10,-1) -> 40 | L136: =IF(J136="N",0,K136) -> 0 | M136: L, QE:16- MAINTENANCE DONE AS PER HEPPM CHECKLIST ATTACHED
A137: 116 | B137: IKN400868 | C137: Television Monitors | D137: =VLOOKUP(B137,[13]AssetDetails_UEM!$A$3:$X$1848,22,FALSE) -> 7000 | E137: IKNWOBE26007552 | F137: 05OT167 | G137: 21-May-2026 00:00:00 | H137: 21-May-2026 09:00:00 | I137: NA | J137: N | K137: =ROUNDUP((D137/4999.99)*10,-1) -> 20 | L137: =IF(J137="N",0,K137) -> 0 | M137: L, QE:16- ROUTINE INSPECTION DONE AS PER CHECKLIST ATTACHED. UNIT FUNCTIONING IN GOOD CONDITION
A138: 117 | B138: IKN400798 | C138: Radiographic Systems, Digital | D138: =VLOOKUP(B138,[13]AssetDetails_UEM!$A$3:$X$1848,22,FALSE) -> 1958605 | E138: IKNWOBE26007553 | F138: 03ID181 | G138: 22-May-2026 00:00:00 | H138: 18-May-2026 16:00:00 | I138: NA | J138: N | K138: =ROUNDUP((D138/4999.99)*10,-1) -> 3920 | L138: =IF(J138="N",0,K138) -> 0 | M138: L, QE:16- QC COMPLETE BY VENDOR. TESTED OKAY
A139: 118 | B139: IKN400799 | C139: Radiographic Systems, Digital | D139: =VLOOKUP(B139,[13]AssetDetails_UEM!$A$3:$X$1848,22,FALSE) -> 1958605 | E139: IKNWOBE26007554 | F139: 03ID186 | G139: 22-May-2026 00:00:00 | H139: 22-May-2026 08:00:00 | I139: NA | J139: N | K139: =ROUNDUP((D139/4999.99)*10,-1) -> 3920 | L139: =IF(J139="N",0,K139) -> 0 | M139: L, QE:16- QC NOT DONE. UNIT ALREADY DISMANTLE
A140: 119 | B140: IKN400833 | C140: Radiographic/Fluoroscopic Units, Mobile | D140: =VLOOKUP(B140,[13]AssetDetails_UEM!$A$3:$X$1848,22,FALSE) -> 1163300 | E140: IKNWOBE26007555 | F140: 01RT233 | G140: 22-May-2026 00:00:00 | H140: 46164.583 | I140: NA | J140: N | K140: =ROUNDUP((D140/4999.99)*10,-1) -> 2330 | L140: =IF(J140="N",0,K140) -> 0 | M140: L, QE:16- QC DONE AS PER JOBSHEET BY VENDOR ATTACHED.
A141: 120 | B141: IKN400674 | C141: Lights, Infrared | D141: =VLOOKUP(B141,[13]AssetDetails_UEM!$A$3:$X$1848,22,FALSE) -> 7050 | E141: IKNWOBE26007556 | F141: 04TC127 | G141: 22-May-2026 00:00:00 | H141: 22-May-2026 08:30:00 | I141: NA | J141: N | K141: =ROUNDUP((D141/4999.99)*10,-1) -> 20 | L141: =IF(J141="N",0,K141) -> 0 | M141: L, QE:12- UNIT PROPOSER TO BER
A142: 121 | B142: IKN400677 | C142: Lights, Infrared | D142: =VLOOKUP(B142,[13]AssetDetails_UEM!$A$3:$X$1848,22,FALSE) -> 7050 | E142: IKNWOBE26007557 | F142: 04TC129 | G142: 22-May-2026 00:00:00 | H142: 22-May-2026 08:30:00 | I142: NA | J142: N | K142: =ROUNDUP((D142/4999.99)*10,-1) -> 20 | L142: =IF(J142="N",0,K142) -> 0 | M142: L, QE:16-UNIT PROPOSED BER
A143: 122 | B143: IKN400736 | C143: Incubators, Laboratory, Thermocycling | D143: =VLOOKUP(B143,[13]AssetDetails_UEM!$A$3:$X$1848,22,FALSE) -> 16240 | E143: IKNWOBE26007558 | F143: 04LA126 | G143: 22-May-2026 00:00:00 | H143: 22-May-2026 10:00:00 | I143: NA | J143: N | K143: =ROUNDUP((D143/4999.99)*10,-1) -> 40 | L143: =IF(J143="N",0,K143) -> 0 | M143: L, QE:16- PPM DONE AS PER HEPPM CHECKLIST ATTACHED
A144: 123 | B144: IKN400871 | C144: Warming Units, Patient, Forced-Air | D144: =VLOOKUP(B144,[13]AssetDetails_UEM!$A$3:$X$1848,22,FALSE) -> 4950 | E144: IKNWOBE26007559 | F144: 01RT159 | G144: 22-May-2026 00:00:00 | H144: 22-May-2026 08:00:00 | I144: NA | J144: N | K144: =ROUNDUP((D144/4999.99)*10,-1) -> 10 | L144: =IF(J144="N",0,K144) -> 0 | M144: L, QE:16- MAINTENANCE DONE AS PER HEPPM CHECKLIST ATTACHED
A145: 124 | B145: IKN401004 | C145: Hand Drills, Surgical | D145: =VLOOKUP(B145,[13]AssetDetails_UEM!$A$3:$X$1848,22,FALSE) -> 227540 | E145: IKNWOBE26007560 | F145: 05OT169 | G145: 22-May-2026 00:00:00 | H145: 22-May-2026 09:00:00 | I145: NA | J145: N | K145: =ROUNDUP((D145/4999.99)*10,-1) -> 460 | L145: =IF(J145="N",0,K145) -> 0 | M145: L, QE:16- MAINTENANCE DONE AS PER HEPPM CHECKLIST ATTACHED - UNIT FUNCTIONING IN GOOD CONDITON
A146: 125 | B146: IKN400965 | C146: Linear Accelerators | D146: =VLOOKUP(B146,[13]AssetDetails_UEM!$A$3:$X$1848,22,FALSE) -> 19351760 | E146: IKNWOBE26007561 | F146: 01RT177 | G146: 23-May-2026 00:00:00 | H146: 46157.771 | I146: NA | J146: N | K146: =ROUNDUP((D146/4999.99)*10,-1) -> 38710 | L146: =IF(J146="N",0,K146) -> 0 | M146: L, QE:16- MAINTENANCE DONE AS PER HEPPM CHECKLIST ATTACHED,UNIT FUNCTIONING IN GOOD CONDITION. BY TRANSMEDIC. | N146: VENDOR DO EARLY
A147: 126 | B147: IKN400037 | C147: Infusion/ Monitoring Line Organizer System | D147: =VLOOKUP(B147,[13]AssetDetails_UEM!$A$3:$X$1848,22,FALSE) -> 84200 | E147: IKNWOBE26007563 | F147: 05IC116 | G147: 25-May-2026 00:00:00 | H147: 25-May-2026 08:00:00 | I147: NA | J147: N | K147: =ROUNDUP((D147/4999.99)*10,-1) -> 170 | L147: =IF(J147="N",0,K147) -> 0 | M147: L, QE:16- MAINTENANCE DONE AS PER HEPPM CHECKLIST ATTACHED,UNIT FUNCTIONING IN GOOD CONDITION
A148: 127 | B148: IKN400084 | C148: Pumps, Enteral Feeding | D148: =VLOOKUP(B148,[13]AssetDetails_UEM!$A$3:$X$1848,22,FALSE) -> 6615 | E148: IKNWOBE26007564 | F148: 05IC116 | G148: 25-May-2026 00:00:00 | H148: 25-May-2026 09:00:00 | I148: NA | J148: N | K148: =ROUNDUP((D148/4999.99)*10,-1) -> 20 | L148: =IF(J148="N",0,K148) -> 0 | M148: L, QE:16- MAINTENANCE DONE ACCORDING HEPPM CHECKLIST ATTACHED,UNIT FUNCTIONING IN GOOD CONDITION
A149: 128 | B149: IKN400117 | C149: Infusion Pumps, Syringe | D149: =VLOOKUP(B149,[13]AssetDetails_UEM!$A$3:$X$1848,22,FALSE) -> 10225 | E149: IKNWOBE26007565 | F149: 05IC116 | G149: 25-May-2026 00:00:00 | H149: 25-May-2026 10:00:00 | I149: NA | J149: N | K149: =ROUNDUP((D149/4999.99)*10,-1) -> 30 | L149: =IF(J149="N",0,K149) -> 0 | M149: L, QE:16- MAINTENANCE DONE AS PER HEPPM CHECKLIST ATTACHED,UNIT FUNCTIONING IN GOOD CONDITION
A150: 129 | B150: IKN400118 | C150: Infusion Pumps, Syringe | D150: =VLOOKUP(B150,[13]AssetDetails_UEM!$A$3:$X$1848,22,FALSE) -> 10225 | E150: IKNWOBE26007566 | F150: 05IC116 | G150: 25-May-2026 00:00:00 | H150: 25-May-2026 11:00:00 | I150: NA | J150: N | K150: =ROUNDUP((D150/4999.99)*10,-1) -> 30 | L150: =IF(J150="N",0,K150) -> 0 | M150: L, QE:16 -MAINTENANCE DONE AS PER HEPPM CHECKLIST ATTACHED, UNIT FUNCTIONING IN GOOD CONDITION
A151: 130 | B151: IKN400119 | C151: Infusion Pumps, Syringe | D151: =VLOOKUP(B151,[13]AssetDetails_UEM!$A$3:$X$1848,22,FALSE) -> 10225 | E151: IKNWOBE26007567 | F151: 05IC116 | G151: 25-May-2026 00:00:00 | H151: 25-May-2026 12:00:00 | I151: NA | J151: N | K151: =ROUNDUP((D151/4999.99)*10,-1) -> 30 | L151: =IF(J151="N",0,K151) -> 0 | M151: L, QE:16- MAINTENANCE DONE AS PER HEPPM CHECKLIST ATTACHED,UNIT FUNCTIONING IN GOOD CONDITION
A152: 131 | B152: IKN400120 | C152: Infusion Pumps, Syringe | D152: =VLOOKUP(B152,[13]AssetDetails_UEM!$A$3:$X$1848,22,FALSE) -> 10225 | E152: IKNWOBE26007568 | F152: 05IC116 | G152: 25-May-2026 00:00:00 | H152: 25-May-2026 14:00:00 | I152: NA | J152: N | K152: =ROUNDUP((D152/4999.99)*10,-1) -> 30 | L152: =IF(J152="N",0,K152) -> 0 | M152: L, QE:16- MAINTENANCE DONE AS PER HEPPM CHECKLIST ATTACHED,UNIT FUNCTIONING IN GOOD CONDITION
A153: 132 | B153: IKN400121 | C153: Infusion Pumps, Syringe | D153: =VLOOKUP(B153,[13]AssetDetails_UEM!$A$3:$X$1848,22,FALSE) -> 10225 | E153: IKNWOBE26007569 | F153: 05IC116 | G153: 25-May-2026 00:00:00 | H153: 25-May-2026 15:00:00 | I153: NA | J153: N | K153: =ROUNDUP((D153/4999.99)*10,-1) -> 30 | L153: =IF(J153="N",0,K153) -> 0 | M153: L, QE:16- MAINTENANCE DONE AS PER HEPPM CHECKLIST ATTACHED,UNIT FUNCTIONING IN GOOD CONDITION
A154: 133 | B154: IKN400122 | C154: Infusion Pumps, Syringe | D154: =VLOOKUP(B154,[13]AssetDetails_UEM!$A$3:$X$1848,22,FALSE) -> 10225 | E154: IKNWOBE26007570 | F154: 05IC116 | G154: 25-May-2026 00:00:00 | H154: 25-May-2026 16:00:00 | I154: NA | J154: N | K154: =ROUNDUP((D154/4999.99)*10,-1) -> 30 | L154: =IF(J154="N",0,K154) -> 0 | M154: L, QE:16- MAINTENANCE DONE AS PER HEPPM CHECKLIST ATTACHED,UNIT FUNCTIONING IN GOOD CONDITION
A155: 134 | B155: IKN400145 | C155: Infusion Pumps, General-Purpose | D155: =VLOOKUP(B155,[13]AssetDetails_UEM!$A$3:$X$1848,22,FALSE) -> 10825 | E155: IKNWOBE26007571 | F155: 05IC116 | G155: 25-May-2026 00:00:00 | H155: 25-May-2026 17:40:00 | I155: NA | J155: N | K155: =ROUNDUP((D155/4999.99)*10,-1) -> 30 | L155: =IF(J155="N",0,K155) -> 0 | M155: L, QE:16- MAINTENANCE DONE AS PER HEPPM CHECKLIST ATTACHED,UNIT FUNCTIONING IN GOOD CONDITION
A156: 135 | B156: IKN400146 | C156: Infusion Pumps, General-Purpose | D156: =VLOOKUP(B156,[13]AssetDetails_UEM!$A$3:$X$1848,22,FALSE) -> 10825 | E156: IKNWOBE26007572 | F156: 05IC116 | G156: 25-May-2026 00:00:00 | H156: 25-May-2026 18:40:00 | I156: NA | J156: N | K156: =ROUNDUP((D156/4999.99)*10,-1) -> 30 | L156: =IF(J156="N",0,K156) -> 0 | M156: L, QE:16- MAINTENANCE DONE AS PER HEPPM CHECKLIST ATTACHED,UNIT FUNCTIONING IN GOOD CONDITION
A157: 136 | B157: IKN401260 | C157: Mattress Systems, Alternating-Pressure | D157: =VLOOKUP(B157,[13]AssetDetails_UEM!$A$3:$X$1848,22,FALSE) -> 28630 | E157: IKNWOBE26007573 | F157: 05WB113 | G157: 25-May-2026 00:00:00 | H157: 25-May-2026 09:00:00 | I157: NA | J157: N | K157: =ROUNDUP((D157/4999.99)*10,-1) -> 60 | L157: =IF(J157="N",0,K157) -> 0 | M157: L, QE:16- PPM HAS BEEN COMPLETE AS PER HEPPM CHECKLIST
A158: 137 | B158: IKN402072 | C158: Dispensers, Liquid, Laboratory | D158: =VLOOKUP(B158,[13]AssetDetails_UEM!$A$3:$X$1848,22,FALSE) -> 148000 | E158: IKNWOBE26007574 | F158: 04LA131 | G158: 25-May-2026 00:00:00 | H158: 25-May-2026 10:00:00 | I158: NA | J158: N | K158: =ROUNDUP((D158/4999.99)*10,-1) -> 300 | L158: =IF(J158="N",0,K158) -> 0 | M158: L, QE:16- PPM DONE AS PER HEPPM CHECKLIST ATTACHED
... A177: 156 | B177: IKN401173 | C177: Tables, Operating | D177: =VLOOKUP(B177,[13]AssetDetails_UEM!$A$3:$X$1848,22,FALSE) -> 240330 | E177: IKNWOBE26007594 | F177: 01RT278 | G177: 26-May-2026 00:00:00 | H177: 26-May-2026 15:00:00 | I177: NA | J177: N | K177: =ROUNDUP((D177/4999.99)*10,-1) -> 490 | L177: =IF(J177="N",0,K177) -> 0 | M177: L, QE:16- MAINTENANCE DONE AS PER HEPPM CHECKLIST ATTACHED
A178: 157 | B178: IKN400020 | C178: Aspirators | D178: =VLOOKUP(B178,[13]AssetDetails_UEM!$A$3:$X$1848,22,FALSE) -> 7580 | E178: IKNWOBE26007595 | F178: 01AE118 | G178: 29-May-2026 00:00:00 | H178: 46171.458 | I178: NA | J178: N | K178: =ROUNDUP((D178/4999.99)*10,-1) -> 20 | L178: =IF(J178="N",0,K178) -> 0 | M178: L, QE:16- PPM DONE AS PER HEPPM CHECKLIST ATTACHED
A179: 158 | B179: IKN400021 | C179: Aspirators | D179: =VLOOKUP(B179,[13]AssetDetails_UEM!$A$3:$X$1848,22,FALSE) -> 7580 | E179: IKNWOBE26007596 | F179: 01AE119 | G179: 29-May-2026 00:00:00 | H179: 29-May-2026 09:40:00 | I179: NA | J179: N | K179: =ROUNDUP((D179/4999.99)*10,-1) -> 20 | L179: =IF(J179="N",0,K179) -> 0 | M179: L, QE:16- MAINTENANCE DONE AS PER HEPPM CHECKLIST ATTACHED
...

Sheet B4-UPTIME
A1: MINISTRY OF HEALTH
A2: Deduction Mapping Report Biomedical Engineering Maintenance Services (BEMS)
A3: INDICATOR B.4 UPTIME GUARANTEE
B5: HOSPITAL NAME : | C5: INSTITUT KANSER NEGARA | N5: MONTH/YEAR : | U5: 46143
B7: STATE : | C7: WILAYAH PERSEKUTUAN PUTRAJAYA | N7: BEMS MONTHLY FEE (RM)@ 97.5% : | U7: =BEMSdar!E11 -> 1329813.2
B9: COMPANY : | C9: AMBANG WIRA SDN BHD | N9: FMS MONTHLY FEE (RM) @ 2.5% : | U9: =BEMSdar!E13 -> 34097.773
A11: Notes:
A12: 1) Deduction Ringgit Equivalent is based on Appendix 11 of the Agreement, Section B3 Key Deduction Indicators for BEMS
A13: 2) Deduction Value for 1st cut off is Deduction Ringgit Equivalent (per event)
A14: 3) Deduction Value for 2nd cut off is Deduction Ringgit Equivalent (per event) multiply by 2
A15: 4) Display only asset affected by deduction
A17: No. | B17: Asset No | C17: Type Code | D17: Type Description | E17: Asset Purchase cost (RM) | F17: Asset Age | G17: TRKPI % | H17: Uptime % | T17: Deduction Ringgit Equivalent (RM) | U17: Previous Deduction (Month) | W17: Deduction for the month (Y/N) | Y17: Deduction Value (RM) | AA17: Total Deduction (RM) | AB17: Remarks
H18: Jan | I18: Feb | J18: Mar | K18: Apr | L18: May | M18: Jun | N18: Jul | O18: Aug | P18: Sep | Q18: Oct | R18: Nov | S18: Dec | U18: 1st | V18: 2nd | W18: 1st | X18: 2nd | Y18: 1st | Z18: 2nd
A19: 1 | B19: IKN400440 | C19: 16-173 | D19: Sphygmomanometers, Electronic, Automatic | E19: 4510 | F19: 13 | G19: 88 | H19: 99.82733 | I19: 99.78 | J19: - | K19: - | L19: - | T19: =ROUNDUP((E19/4999.99)*10,-1) -> 10 | U19: N | V19: N | W19: N | X19: N | Y19: =IF(W19="Y",T19,0) -> 0 | Z19: =IF(X19="Y",T19*2,0) -> 0 | AA19: =Y19+Z19 -> 0
A20: 2 | B20: IKN400645 | C20: 13-215 | D20: Infusion Pumps, General-Purpose | E20: 10825 | F20: 13 | G20: 88 | H20: 99.961971 | I20: 99.93 | J20: - | K20: - | L20: - | T20: =ROUNDUP((E20/4999.99)*10,-1) -> 30 | U20: N | V20: N | W20: N | X20: N | Y20: =IF(W20="Y",T20,0) -> 0 | Z20: =IF(X20="Y",T20*2,0) -> 0 | AA20: =Y20+Z20 -> 0
A21: 3 | B21: IKN401714 | C21: 13-215 | D21: Infusion Pumps, General-Purpose | E21: 5800 | F21: 8 | G21: 95 | H21: 99.962034 | I21: 99.93 | J21: - | K21: - | L21: - | T21: =ROUNDUP((E21/4999.99)*10,-1) -> 20 | U21: Y | V21: Y | W21: N | X21: N | Y21: =IF(W21="Y",T21,0) -> 0 | Z21: =IF(X21="Y",T21*2,0) -> 0 | AA21: =Y21+Z21 -> 0
A22: 4 | B22: IKN400446 | C22: 13-215 | D22: Infusion Pumps, General-Purpose | E22: 10825 | F22: 13 | G22: 88 | H22: 99.65 | I22: 99.68 | J22: 98.553172 | K22: - | L22: - | T22: =ROUNDUP((E22/4999.99)*10,-1) -> 30 | U22: N | V22: N | W22: N | X22: N | Y22: =IF(W22="Y",T22,0) -> 0 | Z22: =IF(X22="Y",T22*2,0) -> 0 | AA22: =Y22+Z22 -> 0
A23: 5 | B23: IKN400366 | C23: 13-215 | D23: Infusion Pumps, General-Purpose | E23: 10825 | F23: 13 | G23: 88 | H23: 99.65 | I23: 99.68 | J23: 99.330998 | K23: 99.04 | L23: - | T23: =ROUNDUP((E23/4999.99)*10,-1) -> 30 | U23: N | V23: N | W23: N | X23: N | Y23: =IF(W23="Y",T23,0) -> 0 | Z23: =IF(X23="Y",T23*2,0) -> 0 | AA23: =Y23+Z23 -> 0
A24: 6 | B24: IKN402165 | C24: 13-215 | D24: Infusion Pumps, General-Purpose | E24: 10825 | F24: 13 | G24: 88 | H24: 99.65 | I24: 99.45 | J24: - | K24: - | L24: - | T24: =ROUNDUP((E24/4999.99)*10,-1) -> 30 | U24: N | V24: N | W24: N | X24: N | Y24: =IF(W24="Y",T24,0) -> 0 | Z24: =IF(X24="Y",T24*2,0) -> 0 | AA24: =Y24+Z24 -> 0
A25: 7 | B25: IKN400565 | C25: 12-649 | D25: Physiologic Monitoring Systems, Stress Exercise | E25: 138350 | F25: 13 | G25: 88 | H25: 99.65 | I25: 99.56 | J25: - | K25: - | L25: 99.617707 | T25: =ROUNDUP((E25/4999.99)*10,-1) -> 280 | U25: N | V25: N | W25: N | X25: N | Y25: =IF(W25="Y",T25,0) -> 0 | Z25: =IF(X25="Y",T25*2,0) -> 0 | AA25: =Y25+Z25 -> 0
A26: 8 | B26: IKN400439 | C26: 16-173 | D26: Sphygmomanometers, Electronic, Automatic | E26: 4510 | F26: 13 | G26: 88 | H26: 99.65 | I26: 99.53 | J26: - | K26: - | L26: - | T26: =ROUNDUP((E26/4999.99)*10,-1) -> 10 | U26: N | V26: N | W26: N | X26: N | Y26: =IF(W26="Y",T26,0) -> 0 | Z26: =IF(X26="Y",T26*2,0) -> 0 | AA26: =Y26+Z26 -> 0
A27: 9 | B27: IKN401076 | C27: 12-306 | D27: Lavage Units, Surgical | E27: 5000 | F27: 13 | G27: 85 | H27: 99.65 | I27: 99.35 | J27: - | K27: - | L27: - | T27: =ROUNDUP((E27/4999.99)*10,-1) -> 20 | U27: N | V27: N | W27: N | X27: N | Y27: =IF(W27="Y",T27,0) -> 0 | Z27: =IF(X27="Y",T27*2,0) -> 0 | AA27: =Y27+Z27 -> 0
A28: 10 | B28: IKN402147 | C28: 15-605 | D28: Testers (Ion Chamber Set) | E28: 142000 | F28: 4 | G28: 96 | H28: 99.65 | I28: 99.39 | J28: - | K28: - | L28: - | T28: =ROUNDUP((E28/4999.99)*10,-1) -> 290 | U28: N | V28: N | W28: N | X28: N | Y28: =IF(W28="Y",T28,0) -> 0 | Z28: =IF(X28="Y",T28*2,0) -> 0 | AA28: =Y28+Z28 -> 0
A29: 11 | B29: IKN401071 | C29: 18-034 | D29: Video Image Processors, Endoscopic | E29: 80000 | F29: 13 | G29: 88 | H29: 99.65 | I29: 99.35 | J29: - | K29: - | L29: 99.990964 | T29: =ROUNDUP((E29/4999.99)*10,-1) -> 170 | U29: Y | V29: Y | W29: N | X29: N | Y29: =IF(W29="Y",T29,0) -> 0 | Z29: =IF(X29="Y",T29*2,0) -> 0 | AA29: =Y29+Z29 -> 0
A30: 12 | B30: IKN402081 | C30: 13-215 | D30: Infusion Pumps, General-Purpose | E30: 3500 | F30: 5 | G30: 95 | H30: 99.65 | I30: 99.68 | J30: 99.330998 | K30: 98.99 | L30: - | T30: =ROUNDUP((E30/4999.99)*10,-1) -> 10 | U30: N | V30: N | W30: N | X30: N | Y30: =IF(W30="Y",T30,0) -> 0 | Z30: =IF(X30="Y",T30*2,0) -> 0 | AA30: =Y30+Z30 -> 0
A31: 13 | B31: IKN401353 | C31: 11-758 | D31: Radiographic/Fluoroscopic Units, Mobile | E31: 399000 | F31: 10 | G31: 88 | H31: 99.65 | I31: - | J31: - | K31: 99.970764 | L31: 99.83783 | T31: =ROUNDUP((E31/4999.99)*10,-1) -> 800 | U31: N | V31: N | W31: N | X31: N | Y31: =IF(W31="Y",T31,0) -> 0 | Z31: =IF(X31="Y",T31*2,0) -> 0 | AA31: =Y31+Z31 -> 0
A32: 14 | B32: IKN400422 | C32: 13-215 | D32: Infusion Pumps, General-Purpose | E32: 10825 | F32: 13 | G32: 88 | H32: 99.65 | I32: 99.68 | J32: 99.330998 | K32: 98.87 | L32: - | T32: =ROUNDUP((E32/4999.99)*10,-1) -> 30 | U32: Y | V32: N | W32: N | X32: N | Y32: =IF(W32="Y",T32,0) -> 0 | Z32: =IF(X32="Y",T32*2,0) -> 0 | AA32: =Y32+Z32 -> 0 | AB32: RW
A33: 15 | B33: IKN400482 | C33: 13-215 | D33: Infusion Pumps, General-Purpose | E33: 10825 | F33: 13 | G33: 88 | H33: 99.65 | I33: 99.61 | J33: - | K33: - | L33: - | T33: =ROUNDUP((E33/4999.99)*10,-1) -> 30 | U33: N | V33: N | W33: N | X33: N | Y33: =IF(W33="Y",T33,0) -> 0 | Z33: =IF(X33="Y",T33*2,0) -> 0 | AA33: =Y33+Z33 -> 0
A34: 16 | B34: IKN400782 | C34: 17-679 | D34: Laser Imagers | E34: 83100 | F34: 13 | G34: 85 | H34: 99.65 | I34: 99.51 | J34: - | K34: - | L34: - | T34: =ROUNDUP((E34/4999.99)*10,-1) -> 170 | U34: N | V34: N | W34: N | X34: N | Y34: =IF(W34="Y",T34,0) -> 0 | Z34: =IF(X34="Y",T34*2,0) -> 0 | AA34: =Y34+Z34 -> 0
A35: 17 | B35: IKN400653 | C35: 16-173 | D35: Sphygmomanometers, Electronic, Automatic | E35: 4510 | F35: 12 | G35: 88 | H35: - | I35: 99.8 | J35: 99.385529 | K35: 99.37 | L35: - | T35: =ROUNDUP((E35/4999.99)*10,-1) -> 10 | U35: N | V35: N | W35: N | X35: N | Y35: =IF(W35="Y",T35,0) -> 0 | Z35: =IF(X35="Y",T35*2,0) -> 0 | AA35: =Y35+Z35 -> 0
A36: 18 | B36: IKN400171 | C36: 17-429 | D36: Ventilators, Intensive Care | E36: 151560 | F36: 12 | G36: 88 | H36: - | I36: 99.78 | J36: 99.425417 | K36: 99.08 | L36: 98.970548 | T36: =ROUNDUP((E36/4999.99)*10,-1) -> 310 | U36: N | V36: N | W36: N | X36: N | Y36: =IF(W36="Y",T36,0) -> 0 | Z36: =IF(X36="Y",T36*2,0) -> 0 | AA36: =Y36+Z36 -> 0
A37: 19 | B37: IKN400168 | C37: 17-429 | D37: Ventilators, Intensive Care | E37: 151560 | F37: 12 | G37: 88 | H37: - | I37: 99.9 | J37: 99.550176 | K37: 99.21 | L37: 99.090819 | T37: =ROUNDUP((E37/4999.99)*10,-1) -> 310 | U37: Y | V37: Y | W37: N | X37: N | Y37: =IF(W37="Y",T37,0) -> 0 | Z37: =IF(X37="Y",T37*2,0) -> 0 | AA37: =Y37+Z37 -> 0
A38: 20 | B38: IKN402184 | C38: 12-647 | D38: Physiologic Monitoring Systems, Acute Care | E38: 100000 | F38: 2 | G38: 99 | H38: - | I38: - | J38: 99.677138 | K38: 99.5 | L38: - | T38: =ROUNDUP((E38/4999.99)*10,-1) -> 210 | U38: N | V38: N | W38: N | X38: N | Y38: =IF(W38="Y",T38,0) -> 0 | Z38: =IF(X38="Y",T38*2,0) -> 0 | AA38: =Y38+Z38 -> 0
A39: 21 | B39: IKN400787 | C39: 13-272 | D39: Radiographic Units, Mobile | E39: 1149550 | F39: 13 | G39: 88 | H39: - | I39: - | J39: 99.824328 | K39: 99.48 | L39: 99.330051 | T39: =ROUNDUP((E39/4999.99)*10,-1) -> 2300 | U39: N | V39: N | W39: N | X39: N | Y39: =IF(W39="Y",T39,0) -> 0 | Z39: =IF(X39="Y",T39*2,0) -> 0 | AA39: =Y39+Z39 -> 0
A40: 22 | B40: IKN400937 | C40: 16-173 | D40: Sphygmomanometers, Electronic, Automatic | E40: 336 | F40: 13 | G40: 88 | H40: - | I40: - | J40: 99.916396 | K40: 99.58 | L40: 99.226016 | T40: =ROUNDUP((E40/4999.99)*10,-1) -> 10 | U40: Y | V40: N | W40: N | X40: N | Y40: =IF(W40="Y",T40,0) -> 0 | Z40: =IF(X40="Y",T40*2,0) -> 0 | AA40: =Y40+Z40 -> 0
A41: 23 | B41: IKN401007 | C41: 15-999 | D41: Washers, Flexible Endoscope | E41: 126300 | F41: 13 | G41: 85 | H41: - | I41: - | J41: 99.925846 | K41: 99.59 | L41: 99.235336 | T41: =ROUNDUP((E41/4999.99)*10,-1) -> 260 | U41: N | V41: N | W41: N | X41: N | Y41: =IF(W41="Y",T41,0) -> 0 | Z41: =IF(X41="Y",T41*2,0) -> 0 | AA41: =Y41+Z41 -> 0
A42: 24 | B42: IKN400293 | C42: 17-148 | D42: Oximeters, Pulse | E42: 5410 | F42: 13 | G42: 88 | H42: - | I42: - | J42: 99.935425 | K42: 99.93 | L42: - | T42: =ROUNDUP((E42/4999.99)*10,-1) -> 20 | U42: Y | V42: N | W42: N | X42: N
A43: 25 | B43: IKN400029 | C43: 12-647 | D43: Physiologic Monitoring Systems, Acute Care | E43: 105850 | F43: 13 | G43: 88 | H43: - | I43: - | J43: 99.946764 | K43: 99.95 | L43: - | T43: =ROUNDUP((E43/4999.99)*10,-1) -> 220 | U43: N | V43: N | W43: N | X43: N | Y43: =IF(W43="Y",T43,0) -> 0 | Z43: =IF(X43="Y",T43*2,0) -> 0 | AA43: =Y43+Z43 -> 0
A44: 26 | B44: IKN400722 | C44: 15-104 | D44: Analyzers, Laboratory, Hematology, Platelet Aggregation | E44: 42100 | F44: 13 | G44: 85 | H44: - | I44: - | J44: 99.981897 | K44: 99.91 | L44: - | T44: =ROUNDUP((E44/4999.99)*10,-1) -> 90 | U44: N | V44: N | W44: N | X44: N | Y44: =IF(W44="Y",T44,0) -> 0 | Z44: =IF(X44="Y",T44*2,0) -> 0 | AA44: =Y44+Z44 -> 0
A45: 27 | B45: IKN400200 | C45: 18-147 | D45: Mattress Systems, Alternating-Pressure | E45: 28630 | F45: 13 | G45: 85 | H45: - | I45: - | J45: - | K45: 99.664774 | L45: 99.314497 | T45: =ROUNDUP((E45/4999.99)*10,-1) -> 60 | U45: N | V45: N | W45: N | X45: N | Y45: =IF(W45="Y",T45,0) -> 0 | Z45: =IF(X45="Y",T45*2,0) -> 0 | AA45: =Y45+Z45 -> 0
A46: 28 | B46: IKN402139 | C46: 15-073 | D46: Bronchoscopes, Flexible | E46: 58000 | F46: 4 | G46: 96 | H46: - | I46: - | J46: - | K46: 99.732224 | L46: 99.381474 | T46: =ROUNDUP((E46/4999.99)*10,-1) -> 120 | U46: N | V46: N | W46: N | X46: N | Y46: =IF(W46="Y",T46,0) -> 0 | Z46: =IF(X46="Y",T46*2,0) -> 0 | AA46: =Y46+Z46 -> 0
A47: 29 | B47: IKN400973 | C47: 13-469 | D47: Scanning Systems, Computed Tomography | E47: 3557530 | F47: 13 | G47: 85 | H47: - | I47: - | J47: - | K47: 99.765565 | L47: 99.599192 | T47: =ROUNDUP((E47/4999.99)*10,-1) -> 7120 | U47: N | V47: N | W47: N | X47: N | Y47: =IF(W47="Y",T47,0) -> 0 | Z47: =IF(X47="Y",T47*2,0) -> 0 | AA47: =Y47+Z47 -> 0
A48: 30 | B48: IKN401261 | C48: 18-147 | D48: Mattress Systems, Alternating-Pressure | E48: 28630 | F48: 13 | G48: 85 | H48: - | I48: - | J48: - | K48: 99.963397 | L48: 99.611021 | T48: =ROUNDUP((E48/4999.99)*10,-1) -> 60 | U48: N | V48: N | W48: N | X48: N | Y48: =IF(W48="Y",T48,0) -> 0 | Z48: =IF(X48="Y",T48*2,0) -> 0 | AA48: =Y48+Z48 -> 0
A49: 31 | B49: IKN400762 | C49: 17-916 | D49: Analyzers, Laboratory, Immunoassay, Chemiluminescent | E49: 1443450 | F49: 13 | G49: 85 | H49: - | I49: - | J49: - | K49: 99.767538 | L49: 99.416539 | T49: =ROUNDUP((E49/4999.99)*10,-1) -> 2890 | U49: N | V49: N | W49: N | X49: N | Y49: =IF(W49="Y",T49,0) -> 0 | Z49: =IF(X49="Y",T49*2,0) -> 0 | AA49: =Y49+Z49 -> 0
A50: 32 | B50: IKN400565 | C50: 12-649 | D50: Physiologic Monitoring Systems, Stress Exercise | E50: 138350 | F50: 13 | G50: 88 | H50: - | I50: - | J50: - | K50: 99.97013 | L50: 99.617707 | T50: =ROUNDUP((E50/4999.99)*10,-1) -> 280 | U50: N | V50: N | W50: N | X50: N | Y50: =IF(W50="Y",T50,0) -> 0 | Z50: =IF(X50="Y",T50*2,0) -> 0 | AA50: =Y50+Z50 -> 0
A51: 33 | B51: IKN400758 | C51: 16-378 | D51: Analyzers, Laboratory, Urine, Automated | E51: 36080 | F51: 13 | G51: 85 | H51: - | I51: - | J51: - | K51: 99.984552 | L51: 99.919918 | T51: =ROUNDUP((E51/4999.99)*10,-1) -> 80 | U51: N | V51: N | W51: N | X51: N | Y51: =IF(W51="Y",T51,0) -> 0 | Z51: =IF(X51="Y",T51*2,0) -> 0 | AA51: =Y51+Z51 -> 0
A52: 34 | B52: IKN401071 | C52: 18-034 | D52: Video Image Processors, Endoscopic | E52: 80000 | F52: 13 | G52: 88 | H52: - | I52: - | J52: - | K52: 99.996679 | L52: 99.990964 | T52: =ROUNDUP((E52/4999.99)*10,-1) -> 170 | U52: N | V52: N | W52: N | X52: N | Y52: =IF(W52="Y",T52,0) -> 0 | Z52: =IF(X52="Y",T52*2,0) -> 0 | AA52: =Y52+Z52 -> 0
A53: 35 | B53: IKN400828 | C53: 10-134 | D53: Anesthesia Units | E53: 144345 | F53: 13 | G53: 88 | H53: - | I53: - | J53: - | K53: - | L53: 99.813514 | T53: =ROUNDUP((E53/4999.99)*10,-1) -> 290 | U53: N | V53: N | W53: N | X53: N | Y53: =IF(W53="Y",T53,0) -> 0 | Z53: =IF(X53="Y",T53*2,0) -> 0 | AA53: =Y53+Z53 -> 0
A54: 36 | B54: IKN400756 | C54: 15-098 | D54: Analyzers, Laboratory, Hematology, Coagulation, Automated | E54: 105860 | F54: 13 | G54: 85 | H54: - | I54: - | J54: - | K54: - | L54: 99.857659 | T54: =ROUNDUP((E54/4999.99)*10,-1) -> 220 | U54: N | V54: N | W54: N | X54: N | Y54: =IF(W54="Y",T54,0) -> 0 | Z54: =IF(X54="Y",T54*2,0) -> 0 | AA54: =Y54+Z54 -> 0
A55: 37 | B55: IKN400579 | C55: 12-660 | D55: Radiation Monitors | E55: 23270 | F55: 13 | G55: 85 | H55: - | I55: - | J55: - | K55: - | L55: 99.881237 | T55: =ROUNDUP((E55/4999.99)*10,-1) -> 50 | U55: N | V55: N | W55: N | X55: N | Y55: =IF(W55="Y",T55,0) -> 0 | Z55: =IF(X55="Y",T55*2,0) -> 0 | AA55: =Y55+Z55 -> 0
A56: 38 | B56: IKN400997 | C56: 12-660 | D56: Radiation Monitors | E56: 112855 | F56: 13 | G56: 85 | H56: - | I56: - | J56: - | K56: - | L56: 99.962169 | T56: =ROUNDUP((E56/4999.99)*10,-1) -> 230 | U56: N | V56: N | W56: N | X56: N | Y56: =IF(W56="Y",T56,0) -> 0 | Z56: =IF(X56="Y",T56*2,0) -> 0 | AA56: =Y56+Z56 -> 0
A57: 39 | B57: IKN400563 | C57: 12-660 | D57: Radiation Monitors | E57: 112855 | F57: 13 | G57: 85 | H57: - | I57: - | J57: - | K57: - | L57: 99.970764 | T57: =ROUNDUP((E57/4999.99)*10,-1) -> 230 | U57: N | V57: N | W57: N | X57: N | Y57: =IF(W57="Y",T57,0) -> 0 | Z57: =IF(X57="Y",T57*2,0) -> 0 | AA57: =Y57+Z57 -> 0
A58: TOTAL DEDUCTION FOR IND. B.4: | AA58: =SUM(AA19:AA34) -> 0
I106: 0 days, 1 hrs, 8 mins | K106: 31-Mar-2026 09:30:00 | L106: 31-Mar-2026 10:00:00 | V106: M-REPLACE NEW BATTERY ,UNIT TEST FUNCTIONING WELL. UNIT PROPOSE TO BER DUE TO AUDATED TECHNOLOGY
V109: PO : ETA :
V110: CHARGER FAULTY WAITING PARTS FROM VENDOR (B BROUN) PO : ETA :
V111: LCD BOARD FAULTY WAITING PARTS FROM VENDOR PO : ETA :
