Workbook
Name _05_04_2009: #REF!
Name _05_04_2009: #REF!
Name _05_04_2009: #REF!
Name _05_04_2009: #REF!
Name _05_04_2009: #REF!
Name a: '[1]Term Outstanding Payment'!#REF!
Name a: '[1]Term Outstanding Payment'!#REF!
Name a: '[1]Term Outstanding Payment'!#REF!
Name a: '[1]Term Outstanding Payment'!#REF!
Name a: '[1]Term Outstanding Payment'!#REF!
Name AA: #REF!
Name AA: #REF!
Name AA: #REF!
Name AA: #REF!
Name AA: #REF!
Name aaa: #REF!
Name aaa: #REF!
Name aaa: #REF!
Name aaa: #REF!
Name aaa: #REF!
Name aaaaa: #REF!
Name aaaaa: #REF!
Name aaaaa: #REF!
Name aaaaa: #REF!
Name aaaaa: #REF!
Name aaaaaaaaaa: #REF!
Name aaaaaaaaaa: #REF!
Name aaaaaaaaaa: #REF!
Name aaaaaaaaaa: #REF!
Name AAAAAAAAAAAAA: #REF!
Name AAAAAAAAAAAAA: #REF!
Name AAAAAAAAAAAAA: #REF!
Name AAAAAAAAAAAAA: #REF!
Name AAAAAAAAAAAAAAAAAA: #REF!
Name AAAAAAAAAAAAAAAAAA: #REF!
Name AAAAAAAAAAAAAAAAAA: #REF!
Name AAAAAAAAAAAAAAAAAA: #REF!
Name AAAAAAAAAAAAAAAAAAAAA: #REF!
Name AAAAAAAAAAAAAAAAAAAAA: #REF!
Name AAAAAAAAAAAAAAAAAAAAA: #REF!
Name AAAAAAAAAAAAAAAAAAAAA: #REF!
Name AAAAAAAAAAAAAAAAAAAAAAAAAAA: #REF!
Name AAAAAAAAAAAAAAAAAAAAAAAAAAA: #REF!
Name AAAAAAAAAAAAAAAAAAAAAAAAAAA: #REF!
Name AAAAAAAAAAAAAAAAAAAAAAAAAAA: #REF!
Name AAAAAAAAAAAAAAAAAAAAAAAAAAAA: #REF!
Name AAAAAAAAAAAAAAAAAAAAAAAAAAAA: #REF!
Name AAAAAAAAAAAAAAAAAAAAAAAAAAAA: #REF!
Name AAAAAAAAAAAAAAAAAAAAAAAAAAAA: #REF!
Name AAAAAAAAAAAAAAAAAAAAAAAAAAAAAA: #REF!
Name AAAAAAAAAAAAAAAAAAAAAAAAAAAAAA: #REF!
Name AAAAAAAAAAAAAAAAAAAAAAAAAAAAAA: #REF!
Name AAAAAAAAAAAAAAAAAAAAAAAAAAAAAA: #REF!
Name AAAAAAAAAAAAAAAAAAAAAAAAAAAAAAA: #REF!
Name AAAAAAAAAAAAAAAAAAAAAAAAAAAAAAA: #REF!
Name AAAAAAAAAAAAAAAAAAAAAAAAAAAAAAA: #REF!
Name AAAAAAAAAAAAAAAAAAAAAAAAAAAAAAA: #REF!
Name AAAAAAAAAAAAAAAAAAAAAAAAAAAAAAAAA: #REF!
Name AAAAAAAAAAAAAAAAAAAAAAAAAAAAAAAAA: #REF!
Name AAAAAAAAAAAAAAAAAAAAAAAAAAAAAAAAA: #REF!

Sheet KDI
A1: Indicator No. | B1: Indicator | E1: Frequency of Deduction | F1: Biomedical Equipment Purchase Cost (RM) | H1: Deduction Range Value (RM) | J1: Maximum Demerit Point per Work Order
F2: From | G2: To
A3: B.1 | B3: The Company shall respond to the request within the specified time frame | E3: Per event | F3: 0.00 5,000.00 10,000.00 15,000.00 20,000.00 25,000.00 30,000.00 35,000.00 40,000.00 > 45,000.00 | G3: 4,999.99 9,999.99 14,999.99 19,999.99 24,999.99 29,999.99 34,999.99 39,999.99 44,999.99 | H3: 10.00 20.00 30.00 40.00 50.00 60.00 70.00 80.00 90.00 100.00 | J3: 1
A4: B.2 | B4: The Company shall carry out repairs to restore faulty medical equipment to a specified condition when it fails to function as per manufacturer’s specification within seven (7) working days. | E4: Per day | F4: 0.00 5,000.00 10,000.00 15,000.00 20,000.00 25,000.00 30,000.00 35,000.00 40,000.00 > 45,000.00 | G4: 4,999.99 9,999.99 14,999.99 19,999.99 24,999.99 29,999.99 34,999.99 39,999.99 44,999.99 | H4: 10.00 20.00 30.00 40.00 50.00 60.00 70.00 80.00 90.00 100.00 | J4: Number of working days for the month
A5: B.3 | B5: The Company shall carry out scheduled maintenance as per schedule in accordance to the procedure as specified in Agreement. Scheduled maintenance shall include complete safety and performance tests. | E5: Per event | F5: 0.00 5,000.00 10,000.00 15,000.00 20,000.00 25,000.00 30,000.00 35,000.00 40,000.00 45,000.00 | G5: 4,999.99 9,999.99 14,999.99 19,999.99 24,999.99 29,999.99 34,999.99 39,999.99 44,999.99 49,999.99 | H5: 10.00 20.00 30.00 40.00 50.00 60.00 70.00 80.00 90.00 100.00 | J5: 1
F6: For every RM 5,000 increment of equipment cost, an increase of RM10 will be applied subsequently
A7: B.4 | B7: The Company shall ensure biomedical equipment meets the uptime target as set in the Agreement. | E7: Per event | H7: 1st level of Uptime Target (TRKPI) | I7: 2nd level of Uptime Target (80%) | J7: 2
F8: 0.00 5,000.00 10,000.00 15,000.00 20,000.00 25,000.00 30,000.00 35,000.00 40,000.00 45,000.00 | G8: 4,999.99 9,999.99 14,999.99 19,999.99 24,999.99 29,999.99 34,999.99 39,999.99 44,999.99 49,999.99 | H8: 10.00 20.00 30.00 40.00 50.00 60.00 70.00 80.00 90.00 100.00 | I8: 20.00 40.00 60.00 80.00 100.00 120.00 140.00 160.00 180.00 200.00
F9: For every RM 5,000 increment of equipment cost, an increase of RM10 will be applied subsequently for 1st Uptime Target and an increase of RM20 for 2nd Uptime Target will be applied subsequently
A10: B.5 | B10: The Company shall attend and witness T&C and manage biomedical equipment within the warranty period. | E10: Per event | F10: 0.00 5,000.00 10,000.00 15,000.00 20,000.00 25,000.00 30,000.00 35,000.00 40,000.00 45,000.00 | G10: 4,999.99 9,999.99 14,999.99 19,999.99 24,999.99 29,999.99 34,999.99 39,999.99 44,999.99 49,999.99 | H10: 10.00 20.00 30.00 40.00 50.00 60.00 70.00 80.00 90.00 100.00 | J10: 1
F11: For every RM 5,000 increment of equipment cost, an increase of RM10 will be applied subsequently

Sheet Public Holiday
A1: ­
A2: Tarikh | B2: Hari | C2: Cuti | D2: Negeri Berkenaan
A4: 46023 | B4: Khamis | C4: Tahun Baru | D4: Putrajaya
A6: 46070 | B6: Selasa | C6: Tahun Baru Cina | D6: Putrajaya
A8: 46071 | B8: Rabu | C8: Tahun Baru Cina Hari Kedua | D8: Putrajaya
A10: 46055 | B10: Isnin | C10: Hari Wilayah Persekutuan | D10: Putrajaya
A12: 46055 | B12: Isnin | C12: Hari Thaipusam | D12: Putrajaya
A14: 46088 | B14: Sabtu | C14: Hari Nuzul Al-Quran | D14: Putrajaya
A16: 46101 | B16: Sabtu | C16: Hari Raya Aidilfitri | D16: Putrajaya
A18: 46102 | B18: Sabtu | C18: Hari Raya Aidilfitri | D18: Putrajaya
A20: 46103 | B20: Ahad | C20: Hari Raya Aidilfitri Hari Kedua | D20: Putrajaya
A22: 46104 | B22: Ahad | C22: Hari Raya Aidilfitri Hari Kedua | D22: Putrajaya
A24: 46143 | B24: Jumaat | C24: Hari Pekerja | D24: Putrajaya
A26: 46173 | B26: Ahad | C26: Hari Wesak | D26: Putrajaya
... A46: 46381 | B46: Jumaat | C46: Hari Krismas | D46: Putrajaya
A49: * Subject to change (Tertakluk kepada perubahan), TBC - To be confirmed

Sheet BEMSdar
A1: MINISTRY OF HEALTH
A2: Deduction Mapping Report Biomedical Engineering Maintenance Services (BEMS)
D5: HOSPITAL NAME : | E5: Institut Kanser Negara | I5: STATE: | J5: W.P. Putrajaya
D7: MONTH/YEAR : | E7: 46082 | I7: COMPANY: | J7: Ambang Wira Sdn Bhd
A9: MONTHLY SERVICE FEE (RM) : | E9: 1363910.9
A11: BEMS MONTHLY FEE (RM) @ 97.5% : | E11: =97.5%*E9 -> 1329813.2
A13: FMS MONTHLY FEE (RM) @ 2.5% : | E13: =2.5%*E9 -> 34097.773
A17: No | B17: Key Deduction Indicators | I17: Frequency | L17: Deduction Value (RM) | N17: Deduction % | O17: Performance Level (%)
A19: B.1 | B19: All service requests shall be responded by the Company’s trained technical personal within the timeframe as stipulated in the Agreement. | I19: Per event | L19: 0 | N19: 0 | O19: =100-N19 -> 100
A20: B.2 | B20: All unscheduled maintenance works including relevant maintenance calibration, safety tests and functional checks shall be completed within seven (7) working days. | I20: Per day | L20: ='B1&B2 UNSCHEDULED'!U103 -> 500 | N20: =L20/$E$11% -> 0.037599267 | O20: =100-N20 -> 99.962401
A21: B.3 | B21: Scheduled maintenance shall be carried out as per schedule and according to the procedure as specified in the Agreement. Scheduled maintenance shall include complete safety and performance tests. | I21: Per event | L21: ='B3-SCHEDULED'!L264 -> 440 | N21: =L21/$E$11% -> 0.033087355 | O21: =100-N21 -> 99.966913
A22: B.4 | B22: All biomedical equipment shall be functioning and maintained to ensure uptime target as specified in the TRKPI are met. | I22: Per event | L22: 0 | N22: =L22/$E$11% -> 0 | O22: =100-N22 -> 100
A23: B.5 | B23: T&C and Warranty Management of newly introduced biomedical shall be managed and performed according to the Agreement and related acts, standards and regulations. | I23: Per event | L23: ='B5-T&C'!O21 -> 0 | N23: =L23/$E$11% -> 0 | O23: =100-N23 -> 100
A24: Total | L24: =SUM(L19:M23) -> 940 | N24: =SUM(N19:N23) -> 0.070686622 | O24: =100-N24 -> 99.929313
C27: Prepared by: | I27: Verified by:
C31: Siti Norsaliana Binti Abu Khalid | I31: Mohd Shahrulnizam bin Tarmizi
C32: Head of BEMS | I32: Facility Manager
C33: Ambang Wira Sdn Bhd- Institut Kanser Negara | I33: Ambang Wira Sdn Bhd- Institut Kanser Negara
C34: Date: | I34: Date:

Sheet B1&B2 UNSCHEDULED
A2: MINISTRY OF HEALTH
A3: Deduction Mapping Report Biomedical Engineering Maintenance Services (BEMS)
A4: INDICATOR B.1 RESPONSE TIME & B.2 REPAIR TIME
A6: HOSPITAL NAME: | C6: INSTITUT KANSER NEGARA | I6: FIRST DATE OF THE MONTH : | M6: 46082 | Q6: (For Calculation)
A8: STATE: | C8: WILAYAH PERSEKUTUAN PUTRAJAYA | I8: LAST DATE OF THE MONTH : | M8: 46112 | Q8: (For Calculation)
A10: COMPANY: | C10: AMBANG WIRA SDN BHD | I10: BEMS MONTHLY FEE (RM) @ 97.5% : | M10: =BEMSdar!E11 -> 1329813.2
A12: MONTH/YEAR: | C12: 46082 | I12: FMS MONTHLY FEE (RM) @ 2.5% : | M12: =BEMSdar!E13 -> 34097.773
A14: Notes:
A15: 1) Deduction Ringgit Equivalent is based on Appendix 11 of the Agreement, Section B3 Key Deduction Indicators for BEMS
A16: 2) Deduction Value for Indicator B.1 is Deduction Ringgit Equivalent (per event)
A17: 3) Total Repair Time includes weekend & public holiday
A18: 4) Demerit Point for Indicator B.2 is calculated based on completion date against request date, less by 7 working days
A19: 5) Deduction Value for Indicator B.2 is Demerit Point multiply by Deduction Ringgit Equivalent
A21: No | B21: Asset No | C21: Asset Description | D21: Asset Purchase Price (RM) | E21: Work Order No. | F21: User Location | G21: Work Order/ Complaint Details | H21: Response Category (Emergency/ Normal) | I21: Total Response Time (minutes) | J21: Work Request Date | K21: Response Time (Minutes) | L21: Work Completion Date | M21: Deduction Ringgit Equivalent (RM) | N21: Indicator B.1 | Q21: Indicator B.2
N22: Validate Status (Y/N) | O22: Deduction Value (RM) | P22: Remarks/ Exemption | Q22: Validate Status (Y/N) | R22: Total Repair Time (day) | S22: Last date of 7 working days (dd/mm/yy) | T22: Demerit Point | U22: Deduction Value (RM) | V22: Remarks/ Exemption
A23: Current Month (Work Order Completed)
A24: 1 | B24: IKN400762 | C24: =VLOOKUP(B24,[14]AssetDetails_UEM!$A$3:$AH$1849,6,FALSE) -> Analyzers, Laboratory, Immunoassay, Chemiluminescent | D24: =VLOOKUP(B24,[14]AssetDetails_UEM!$A$3:$AK$1849,22,FALSE) -> 1443450 | E24: IKNWIBE26003941 | F24: 04LA133 | G24: MACHINE ARCHITECT'WASTE TANK'-PATHOLOGY ARAS 4 | H24: Normal | I24: 0 days, 0 hrs, 42 mins | J24: 01-Mar-2026 08:18:00 | K24: 01-Mar-2026 09:00:00 | L24: 01-Mar-2026 10:30:00 | M24: =IF(D24>44999.99,100,ROUNDUP((D24/4999.99)*10,-1)) -> 100 | N24: N | O24: ='[15]B1& B2 UNSCHEDULED'!$O$24 -> 0 | Q24: N | R24: =IF(L24="",AKHIR-J24,L24-J24+1) -> 1.0916667 | S24: =WORKDAY(J24,6,AKHIR) -> 46090 | T24: 0 | U24: =IF(Q24="N",0,M24*T24) -> 0 | V24: CLEAN UP THE TUBING , DO DAILY MAINTENANCE ,CHECKED ,TESTED OKAY AND FIT TO USE
A25: 2 | B25: IKN400353 | C25: =VLOOKUP(B25,[14]AssetDetails_UEM!$A$3:$AH$1849,6,FALSE) -> Monitors, Physiologic, Vital Signs | D25: =VLOOKUP(B25,[14]AssetDetails_UEM!$A$3:$AK$1849,22,FALSE) -> 18765 | E25: IKNWIBE26003944 | F25: 07WF133 | G25: CUFF BP SET TERKOYAK 7B | H25: Normal | I25: 0 days, 0 hrs, 21 mins | J25: 01-Mar-2026 11:39:00 | K25: 01-Mar-2026 12:00:00 | L25: 01-Mar-2026 18:00:00 | M25: =IF(D25>44999.99,100,ROUNDUP((D25/4999.99)*10,-1)) -> 40 | N25: N | O25: ='[15]B1& B2 UNSCHEDULED'!$O$24 -> 0 | Q25: N | R25: =IF(L25="",AKHIR-J25,L25-J25+1) -> 1.2645833 | S25: =WORKDAY(J25,6,AKHIR) -> 46090 | T25: 0 | U25: =IF(Q25="N",0,M25*T25) -> 0 | V25: REPLACE NEW CONNECTOR HOSE,REPLACE THE CUFF.TESTED OKAY ,INFLATE WELL
A26: 3 | B26: NA | C26: RIPPLE MATTRESS | D26: NA | E26: IKNWIBE26003945 | F26: 09WJ237 | G26: SPRING LOCK ANGIN RIPPLE MATTRESS ROSAK(NO SIRI:NB355553)-9A | H26: Normal | I26: 0 days, 0 hrs, 33 mins | J26: 01-Mar-2026 16:27:00 | K26: 01-Mar-2026 17:00:00 | L26: 02-Mar-2026 21:30:00 | M26: 0 | N26: N | O26: ='[15]B1& B2 UNSCHEDULED'!$O$24 -> 0 | Q26: N | R26: =IF(L26="",AKHIR-J26,L26-J26+1) -> 2.2104167 | S26: =WORKDAY(J26,6,AKHIR) -> 46090 | T26: 0 | U26: =IF(Q26="N",0,M26*T26) -> 0 | V26: FOUND IN LOCKING PIN MISSING.REPLACED NEW LOCKING PIN.TESTED OKAY AND FIT TO USE
A27: 4 | B27: IKN400762 | C27: =VLOOKUP(B27,[14]AssetDetails_UEM!$A$3:$AH$1849,6,FALSE) -> Analyzers, Laboratory, Immunoassay, Chemiluminescent | D27: =VLOOKUP(B27,[14]AssetDetails_UEM!$A$3:$AK$1849,22,FALSE) -> 1443450 | E27: IKNWIBE26004000 | F27: 04LA133 | G27: MESIN ARCHITECT INTERNAL WASTE TANK FULL - PATTHOLOGI ARAS 4 | H27: Normal | I27: 0 days, 0 hrs, 11 mins | J27: 02-Mar-2026 09:29:00 | K27: 02-Mar-2026 09:40:00 | L27: 02-Mar-2026 23:00:00 | M27: =IF(D27>44999.99,100,ROUNDUP((D27/4999.99)*10,-1)) -> 100 | N27: N | O27: ='[15]B1& B2 UNSCHEDULED'!$O$24 -> 0 | Q27: N | R27: =IF(L27="",AKHIR-J27,L27-J27+1) -> 1.5631944 | S27: =WORKDAY(J27,6,AKHIR) -> 46091 | T27: 0 | U27: =IF(Q27="N",0,M27*T27) -> 0 | V27: CLEAN LOW CONTRATION WASTE TANK,TUBING
A28: 5 | B28: IKN400787 | C28: =VLOOKUP(B28,[14]AssetDetails_UEM!$A$3:$AH$1849,6,FALSE) -> Radiographic Units, Mobile | D28: =VLOOKUP(B28,[14]AssetDetails_UEM!$A$3:$AK$1849,22,FALSE) -> 1149550 | E28: IKNWIBE26004021 | F28: 03ID106 | G28: MESIN TIDAK BOLEH HANTAR GAMBAR MELALUI WIFI - RADIOLOGI ARAS 3 | H28: Normal | I28: 0 days, 0 hrs, 12 mins | J28: 02-Mar-2026 15:28:00 | K28: 02-Mar-2026 15:40:00 | L28: 02-Mar-2026 16:00:00 | M28: =IF(D28>44999.99,100,ROUNDUP((D28/4999.99)*10,-1)) -> 100 | N28: N | O28: ='[15]B1& B2 UNSCHEDULED'!$O$24 -> 0 | Q28: N | R28: =IF(L28="",AKHIR-J28,L28-J28+1) -> 1.0222222 | S28: =WORKDAY(J28,6,AKHIR) -> 46091 | T28: 0 | U28: =IF(Q28="N",0,M28*T28) -> 0 | V28: RECONECT WIFI AND TESTED OKAY.
A29: 6 | B29: IKN400049 | C29: =VLOOKUP(B29,[14]AssetDetails_UEM!$A$3:$AH$1849,6,FALSE) -> Physiologic Monitoring Systems, Acute Care | D29: =VLOOKUP(B29,[14]AssetDetails_UEM!$A$3:$AK$1849,22,FALSE) -> 119690 | E29: IKNWIBE26004154 | F29: 05IC131 | G29: MONITOR BLANK - ICU ARAS 5 | H29: Normal | I29: 0 days, 0 hrs, 13 mins | J29: 03-Mar-2026 17:57:00 | K29: 03-Mar-2026 18:10:00 | L29: 03-Mar-2026 21:40:00 | M29: =IF(D29>44999.99,100,ROUNDUP((D29/4999.99)*10,-1)) -> 100 | N29: N | O29: ='[15]B1& B2 UNSCHEDULED'!$O$24 -> 0 | Q29: N | R29: =IF(L29="",AKHIR-J29,L29-J29+1) -> 1.1548611 | S29: =WORKDAY(J29,6,AKHIR) -> 46092 | T29: 0 | U29: =IF(Q29="N",0,M29*T29) -> 0 | V29: FOUND SWITH FOR MODERN NOT TURN ON.TURN ON AND TESTED FUNCTIONING OKAY
A30: 7 | B30: IKN402166 | C30: =VLOOKUP(B30,[14]AssetDetails_UEM!$A$3:$AH$1849,6,FALSE) -> Mattress Systems, Alternating-Pressure | D30: =VLOOKUP(B30,[14]AssetDetails_UEM!$A$3:$AK$1849,22,FALSE) -> 4000 | E30: IKNWIBE26004156 | F30: 05WB149 | G30: RIPPLE MATTRESS BERBUNYI - WAD 5A | H30: Normal | I30: 0 days, 0 hrs, 10 mins | J30: 03-Mar-2026 18:35:00 | K30: 46084.781 | L30: 05-Mar-2026 10:00:00 | M30: =IF(D30>44999.99,100,ROUNDUP((D30/4999.99)*10,-1)) -> 10 | N30: N | O30: ='[15]B1& B2 UNSCHEDULED'!$O$24 -> 0 | Q30: N | R30: =IF(L30="",AKHIR-J30,L30-J30+1) -> 2.6423611 | S30: =WORKDAY(J30,6,AKHIR) -> 46092 | T30: 0 | U30: =IF(Q30="N",0,M30*T30) -> 0 | V30: REPLACE NEW CELL.CHECKED AND TESTED OKAY.FUNCTIONING .NO MORE ALARM
A31: 8 | B31: IKN400386 | C31: =VLOOKUP(B31,[14]AssetDetails_UEM!$A$3:$AH$1849,6,FALSE) -> Physiologic Monitoring Systems, Acute Care | D31: =VLOOKUP(B31,[14]AssetDetails_UEM!$A$3:$AK$1849,22,FALSE) -> 44510 | E31: IKNWIBE26004223 | F31: 07WE113 | G31: BP CUFF TIDAK BOLEH GUNA - WAD 7A | H31: Normal | I31: 0 days, 1 hrs, 5 mins | J31: 04-Mar-2026 09:40:00 | K31: 04-Mar-2026 10:45:00 | L31: 04-Mar-2026 11:15:00 | M31: =IF(D31>44999.99,100,ROUNDUP((D31/4999.99)*10,-1)) -> 90 | N31: N | O31: ='[15]B1& B2 UNSCHEDULED'!$O$24 -> 0 | Q31: N | R31: =IF(L31="",AKHIR-J31,L31-J31+1) -> 1.0659722 | S31: =WORKDAY(J31,6,AKHIR) -> 46093 | T31: 0 | U31: =IF(Q31="N",0,M31*T31) -> 0 | V31: RESEAT MODULE AND NIBP CABLE.TESTED ,CUFF CAN INFLATE
A32: 9 | B32: IKN400387 | C32: =VLOOKUP(B32,[14]AssetDetails_UEM!$A$3:$AH$1849,6,FALSE) -> Sphygmomanometers, Electronic, Automatic | D32: =VLOOKUP(B32,[14]AssetDetails_UEM!$A$3:$AK$1849,22,FALSE) -> 4510 | E32: IKNWIBE26004224 | F32: 07WE143 | G32: BP CUFF BATERI TIDAK BERFUNGSI- 7A | H32: Normal | I32: 0 days, 0 hrs, 18 mins | J32: 04-Mar-2026 09:42:00 | K32: 04-Mar-2026 10:00:00 | L32: 10-Mar-2026 15:00:00 | M32: =IF(D32>44999.99,100,ROUNDUP((D32/4999.99)*10,-1)) -> 10 | N32: N | O32: ='[15]B1& B2 UNSCHEDULED'!$O$24 -> 0 | Q32: N | R32: 5 | S32: =WORKDAY(J32,6,AKHIR) -> 46093 | T32: 0 | U32: =IF(Q32="N",0,M32*T32) -> 0 | V32: UNDER MONITORING. V2,REPLACE NEW BATTERY AND NEED FURTHER MONITORING WHETHER THE BATTERY CAN SUSTAIN WITHOUT CHARGE OR NOT. V3, MACHINE FUNCTIONING AND BATTERY CAN SUSTAIN LONGER.FEEDBACK FROM USER CHECKED AND TESTED
A33: 10 | B33: IKN401027 | C33: =VLOOKUP(B33,[14]AssetDetails_UEM!$A$3:$AH$1849,6,FALSE) -> Tables, Operating | D33: =VLOOKUP(B33,[14]AssetDetails_UEM!$A$3:$AK$1849,22,FALSE) -> 239350 | E33: IKNWIBE26004225 | F33: 05OT120 | G33: TABLE OPERATING CANNOT FUCTION AND CANNOT USE- GOT ARAS 5 | H33: Normal | I33: 0 days, 0 hrs, 9 mins | J33: 04-Mar-2026 09:51:00 | K33: 46085.417 | L33: 05-Mar-2026 10:00:00 | M33: =IF(D33>44999.99,100,ROUNDUP((D33/4999.99)*10,-1)) -> 100 | N33: N | O33: ='[15]B1& B2 UNSCHEDULED'!$O$24 -> 0 | Q33: N | R33: =IF(L33="",AKHIR-J33,L33-J33+1) -> 2.00625 | S33: =WORKDAY(J33,6,AKHIR) -> 46093 | T33: 0 | U33: =IF(Q33="N",0,M33*T33) -> 0 | V33: REPLACED NEW POWER SUPPLY CABLE, UNIT TEST AND FUNCTIONING IN GOOD CONDITION
A34: 11 | B34: IKN400454 | C34: =VLOOKUP(B34,[14]AssetDetails_UEM!$A$3:$AH$1849,6,FALSE) -> Mattress Systems, Alternating-Pressure | D34: =VLOOKUP(B34,[14]AssetDetails_UEM!$A$3:$AK$1849,22,FALSE) -> 28630 | E34: IKNWIBE26004226 | F34: 06WC113 | G34: HOSE RIPPLE MATTRESS LOOSE - WAD 6A | H34: Normal | I34: 0 days, 0 hrs, 26 mins | J34: 04-Mar-2026 10:34:00 | K34: 04-Mar-2026 11:00:00 | L34: 04-Mar-2026 12:00:00 | M34: =IF(D34>44999.99,100,ROUNDUP((D34/4999.99)*10,-1)) -> 60 | N34: N | O34: ='[15]B1& B2 UNSCHEDULED'!$O$24 -> 0 | Q34: N | R34: =IF(L34="",AKHIR-J34,L34-J34+1) -> 1.0597222 | S34: =WORKDAY(J34,6,AKHIR) -> 46093 | T34: 0 | U34: =IF(Q34="N",0,M34*T34) -> 0 | V34: CHANGE NEW CLIP HOSE,MAKE SURE IT TIGHT ,TEST HOSE OK.UNIT FIT TO USE
A35: 12 | B35: IKN400762 | C35: =VLOOKUP(B35,[14]AssetDetails_UEM!$A$3:$AH$1849,6,FALSE) -> Analyzers, Laboratory, Immunoassay, Chemiluminescent | D35: =VLOOKUP(B35,[14]AssetDetails_UEM!$A$3:$AK$1849,22,FALSE) -> 1443450 | E35: IKNWIBE26004236 | F35: 04LA133 | G35: PIPETEER MOVEMEMENT LLESTRIK AT MIDDLE REAGENT STEP NUMBER - PATOLOGI ARAS | H35: Normal | I35: 0 days, 0 hrs, 6 mins | J35: 04-Mar-2026 12:54:00 | K35: 46085.542 | L35: 46093.542 | M35: =IF(D35>44999.99,100,ROUNDUP((D35/4999.99)*10,-1)) -> 100 | N35: N | O35: ='[15]B1& B2 UNSCHEDULED'!$O$24 -> 0 | Q35: N | R35: 7 | S35: =WORKDAY(J35,6,AKHIR) -> 46093 | T35: 0 | U35: =IF(Q35="N",0,M35*T35) -> 0 | V35: REAGENT PROBE ERROR. REALLIGMENT REAGENT PROBE, RUN CAL, QC AND OK
A36: 13 | B36: IKN400757 | C36: =VLOOKUP(B36,[14]AssetDetails_UEM!$A$3:$AH$1849,6,FALSE) -> Analyzers, Laboratory, Hematology, Cell Counting, Automated | D36: =VLOOKUP(B36,[14]AssetDetails_UEM!$A$3:$AK$1849,22,FALSE) -> 565350 | E36: IKNWIBE26004317 | F36: 04LA131 | G36: USER TRAINING HEMATOLOGY ANALYZER - IKN400757 | H36: User Training | I36: 0 days, 0 hrs, 09 mins | J36: 05-Mar-2026 09:51:00 | K36: 46086.417 | L36: 05-Mar-2026 11:00:00 | M36: =IF(D36>44999.99,100,ROUNDUP((D36/4999.99)*10,-1)) -> 100 | N36: N | O36: ='[15]B1& B2 UNSCHEDULED'!$O$24 -> 0 | Q36: N | R36: =IF(L36="",AKHIR-J36,L36-J36+1) -> 1.0479167 | S36: =WORKDAY(J36,6,AKHIR) -> 46094 | T36: 0 | U36: =IF(Q36="N",0,M36*T36) -> 0 | V36: USER TRAINING DONE
A37: 14 | B37: IKN402179 | C37: =VLOOKUP(B37,[14]AssetDetails_UEM!$A$3:$AH$1849,6,FALSE) -> Scanning Systems, Computed Tomography/ Positron Emission Tomography | D37: =VLOOKUP(B37,[14]AssetDetails_UEM!$A$3:$AK$1849,22,FALSE) -> 3410390 | E37: IKNWIBE26004321 | F37: 03NM161 | G37: REQ- CHECK XELERIS | H37: Normal | I37: 0 days, 0 hrs, 10 mins | J37: 05-Mar-2026 08:30:00 | K37: 05-Mar-2026 08:40:00 | L37: 05-Mar-2026 09:00:00 | M37: =IF(D37>44999.99,100,ROUNDUP((D37/4999.99)*10,-1)) -> 100 | N37: N | O37: ='[15]B1& B2 UNSCHEDULED'!$O$24 -> 0 | Q37: N | R37: =IF(L37="",AKHIR-J37,L37-J37+1) -> 1.0208333 | S37: =WORKDAY(J37,6,AKHIR) -> 46094 | T37: 0 | U37: =IF(Q37="N",0,M37*T37) -> 0 | V37: VENDOR RUN LFW RESTRORE THE BACKUP CONFIGURATION. RE-CONFIGURE THE DICOM PARAMETER. QUERY AND RETRIEVED PASSED
A38: 15 | B38: IKN400799 | C38: =VLOOKUP(B38,[14]AssetDetails_UEM!$A$3:$AH$1849,6,FALSE) -> Radiographic Systems, Digital | D38: =VLOOKUP(B38,[14]AssetDetails_UEM!$A$3:$AK$1849,22,FALSE) -> 1958605 | E38: IKNWIBE26004404 | F38: 03ID186 | G38: HANDLE GRID MACHINE XRAY TERCABUT - BILIK XRAY ARAS 3 | H38: Normal | I38: 0 days, 0 hrs, 15 mins | J38: 46087.375 | K38: 06-Mar-2026 09:15:00 | L38: 06-Mar-2026 10:00:00 | M38: =IF(D38>44999.99,100,ROUNDUP((D38/4999.99)*10,-1)) -> 100 | N38: N | O38: ='[15]B1& B2 UNSCHEDULED'!$O$24 -> 0 | Q38: N | R38: =IF(L38="",AKHIR-J38,L38-J38+1) -> 1.0416667 | S38: =WORKDAY(J38,6,AKHIR) -> 46097 | T38: 0 | U38: =IF(Q38="N",0,M38*T38) -> 0 | V38: REPLACED BATTERIES FOR REMOTED CONTROL , TESTED FUNCTIONING OKAY
A39: 16 | B39: IKN400967 | C39: =VLOOKUP(B39,[14]AssetDetails_UEM!$A$3:$AH$1849,6,FALSE) -> Linear Accelerators | D39: =VLOOKUP(B39,[14]AssetDetails_UEM!$A$3:$AK$1849,22,FALSE) -> 12049370 | E39: IKNWIBE26004417 | F39: 01RT164 | G39: PC DAN MONITOR IMAGE REVIEW DI LINAC 2 TERPADAM - RADIOTERAPI ARAS 1 (KKN/IKN/H/13/5032) | H39: Normal | I39: 0 days, 0 hrs, 6 mins | J39: 06-Mar-2026 11:09:00 | K39: 06-Mar-2026 11:15:00 | L39: 06-Mar-2026 13:00:00 | M39: =IF(D39>44999.99,100,ROUNDUP((D39/4999.99)*10,-1)) -> 100 | N39: N | O39: ='[15]B1& B2 UNSCHEDULED'!$O$24 -> 0 | Q39: N | R39: =IF(L39="",AKHIR-J39,L39-J39+1) -> 1.0770833 | S39: =WORKDAY(J39,6,AKHIR) -> 46097 | T39: 0 | U39: =IF(Q39="N",0,M39*T39) -> 0 | V39: RESET ALL CABLE AND CONECTORS. TESTED OKAY , AND UNIT LEFT IN FULLY FUNCTIONALITY.
A40: 17 | B40: IKN400956 | C40: =VLOOKUP(B40,[14]AssetDetails_UEM!$A$3:$AH$1849,6,FALSE) -> Linear Accelerators | D40: =VLOOKUP(B40,[14]AssetDetails_UEM!$A$3:$AK$1849,22,FALSE) -> 21961900 | E40: IKNWIBE26004420 | F40: 01RT172 | G40: POWER TRIP - ERROR FLOW PUMP KFIL - RADIOTERAPI | H40: Normal | I40: 0 days, 0 hrs, 28 mins | J40: 06-Mar-2026 12:02:00 | K40: 06-Mar-2026 12:30:00 | L40: 11-Mar-2026 15:00:00 | M40: =IF(D40>44999.99,100,ROUNDUP((D40/4999.99)*10,-1)) -> 100 | N40: N | O40: ='[15]B1& B2 UNSCHEDULED'!$O$24 -> 0 | Q40: N | R40: 4 | S40: =WORKDAY(J40,6,AKHIR) -> 46097 | T40: 0 | U40: =IF(Q40="N",0,M40*T40) -> 0 | V40: RUN BACKUP CHILLER FOR TEMPORARY. REPLACED WITH NEW WATER PUMP AND TEST OK. UNIT LEFT IN FULLY FUNCTIONING.
A41: 18 | B41: IKN402157 | C41: =VLOOKUP(B41,[14]AssetDetails_UEM!$A$3:$AH$1849,6,FALSE) -> Infusion Pumps, General-Purpose | D41: =VLOOKUP(B41,[14]AssetDetails_UEM!$A$3:$AK$1849,22,FALSE) -> 3500 | E41: IKNWIBE26004424 | F41: 08WH107 | G41: MESIN INFUSION KELUAR "ERR 205" - 8B | H41: Normal | I41: 0 days, 0 hrs, 17 mins | J41: 06-Mar-2026 16:23:00 | K41: 46087.694 | L41: 09-Mar-2026 19:15:00 | M41: =IF(D41>44999.99,100,ROUNDUP((D41/4999.99)*10,-1)) -> 10 | N41: N | O41: ='[15]B1& B2 UNSCHEDULED'!$O$24 -> 0 | Q41: N | R41: 2 | S41: =WORKDAY(J41,6,AKHIR) -> 46097 | T41: 0 | U41: =IF(Q41="N",0,M41*T41) -> 0 | V41: TROUBLESHOOT BY CHECKING / BATTERY IN RANGE , CONDUCTED FUNCTIONAL TEST AND INFUSION SIMULATION TEST FOR 2 HOURS. NO ERROR AT ALL. UNIT READY FOR USE.
A42: 19 | B42: NA | C42: Linear Accelerators | D42: 0 | E42: IKNWIBE26004425 | F42: 01RT183 | G42: MESIN LINAC 5 KELUAR BGM - RADIOTERAPI (KKM/IKN/H/25/152) | H42: Normal | I42: 0 days, 0 hrs, 20 mins | J42: 06-Mar-2026 17:00:00 | K42: 06-Mar-2026 17:20:00 | L42: 08-Mar-2026 16:30:00 | M42: =IF(D42>44999.99,100,ROUNDUP((D42/4999.99)*10,-1)) -> 0 | N42: N | O42: ='[15]B1& B2 UNSCHEDULED'!$O$24 -> 0 | Q42: N | R42: 2 | S42: =WORKDAY(J42,6,AKHIR) -> 46097 | T42: 0 | U42: =IF(Q42="N",0,M42*T42) -> 0 | V42: M-REPLACED ION CHAMBER SECONDARY RESOLVER BY VENDOR AND UNIT WERE BACK TO NORMAL CONDITION.UNIT LEFT IN FULL FUNCTIONALITY (ASSET NEW, DW)
A43: 20 | B43: IKN400690 | C43: =VLOOKUP(B43,[14]AssetDetails_UEM!$A$3:$AH$1849,6,FALSE) -> Pumps, Enteral Feeding | D43: =VLOOKUP(B43,[14]AssetDetails_UEM!$A$3:$AK$1849,22,FALSE) -> 6615 | E43: IKNWIBE26004436 | F43: 05IC113 | G43: KANGAROO PUMP TIDAK BERFUNGSI - ICU | H43: Normal | I43: 0 days, 0 hrs, 16 mins | J43: 07-Mar-2026 13:14:00 | K43: 07-Mar-2026 13:30:00 | L43: 13-Mar-2026 14:30:00 | M43: =IF(D43>44999.99,100,ROUNDUP((D43/4999.99)*10,-1)) -> 20 | N43: N | O43: ='[15]B1& B2 UNSCHEDULED'!$O$24 -> 0 | Q43: N | R43: 5 | S43: =WORKDAY(J43,6,AKHIR) -> 46097 | T43: 0 | U43: =IF(Q43="N",0,M43*T43) -> 0 | V43: REPLACE NEW CHARGER FOR FEEDING PUMP.UNIT TEST AND FUNCTIONING IN GOOD CONDITION
A44: 21 | B44: IKN400082 | C44: =VLOOKUP(B44,[14]AssetDetails_UEM!$A$3:$AH$1849,6,FALSE) -> Pumps, Enteral Feeding | D44: =VLOOKUP(B44,[14]AssetDetails_UEM!$A$3:$AK$1849,22,FALSE) -> 6615 | E44: IKNWIBE26004437 | F44: 05IC114 | G44: PENUTUP BIRU KANGAROO PUMP TIADA - ICU ARAS 5 | H44: Normal | I44: 0 days, 0 hrs, 15 mins | J44: 07-Mar-2026 13:15:00 | K44: 07-Mar-2026 13:30:00 | L44: 11-Mar-2026 16:00:00 | M44: =IF(D44>44999.99,100,ROUNDUP((D44/4999.99)*10,-1)) -> 20 | N44: N | O44: ='[15]B1& B2 UNSCHEDULED'!$O$24 -> 0 | Q44: N | R44: 3 | S44: =WORKDAY(J44,6,AKHIR) -> 46097 | T44: 0 | U44: =IF(Q44="N",0,M44*T44) -> 0 | V44: FOUND SIDE COVER AT DEPARTMENT , ATTACHED BACK SIDE COVER TO MAIN UNIT
A45: 22 | B45: IKN400967 | C45: =VLOOKUP(B45,[14]AssetDetails_UEM!$A$3:$AH$1849,6,FALSE) -> Linear Accelerators | D45: =VLOOKUP(B45,[14]AssetDetails_UEM!$A$3:$AK$1849,22,FALSE) -> 12049370 | E45: IKNWIBE26004514 | F45: 01RT165 | G45: MLC STUCK (LINAC 2) - RADIOTERAPI ARAS 1 | H45: Normal | I45: 0 days, 0 hrs, 15 mins | J45: 09-Mar-2026 08:30:00 | K45: 09-Mar-2026 08:45:00 | L45: 09-Mar-2026 12:00:00 | M45: =IF(D45>44999.99,100,ROUNDUP((D45/4999.99)*10,-1)) -> 100 | N45: N | O45: ='[15]B1& B2 UNSCHEDULED'!$O$24 -> 0 | Q45: N | R45: =IF(L45="",AKHIR-J45,L45-J45+1) -> 1.1458333 | S45: =WORKDAY(J45,6,AKHIR) -> 46098 | T45: 0 | U45: =IF(Q45="N",0,M45*T45) -> 0 | V45: REPLACED WITH NEW LEAF MOTOR AND TESTED OK. UNIT LEFT IN FULL FUNCTIONALITY
A46: 23 | B46: IKN400967 | C46: =VLOOKUP(B46,[14]AssetDetails_UEM!$A$3:$AH$1849,6,FALSE) -> Linear Accelerators | D46: =VLOOKUP(B46,[14]AssetDetails_UEM!$A$3:$AK$1849,22,FALSE) -> 12049370 | E46: IKNWIBE26004627 | F46: 01RT165 | G46: MACHINE LINAC 2 ERROR FAULT (5) | H46: Normal | I46: 0 days, 0 hrs, 18 mins | J46: 10-Mar-2026 07:42:00 | K46: 10-Mar-2026 08:00:00 | L46: 10-Mar-2026 11:00:00 | M46: =IF(D46>44999.99,100,ROUNDUP((D46/4999.99)*10,-1)) -> 100 | N46: N | O46: ='[15]B1& B2 UNSCHEDULED'!$O$24 -> 0 | Q46: N | R46: =IF(L46="",AKHIR-J46,L46-J46+1) -> 1.1375 | S46: =WORKDAY(J46,6,AKHIR) -> 46099 | T46: 0 | U46: =IF(Q46="N",0,M46*T46) -> 0 | V46: REBOOT AND RESTART XV GENERATOR. SYSTEM BACK TO NORMAL CONDITION AND UNIT LEFT IN FULL FUNCTIONALITY
A47: 24 | B47: IKN400293 | C47: =VLOOKUP(B47,[14]AssetDetails_UEM!$A$3:$AH$1849,6,FALSE) -> Oximeters, Pulse | D47: =VLOOKUP(B47,[14]AssetDetails_UEM!$A$3:$AK$1849,22,FALSE) -> 5410 | E47: IKNWIBE26004633 | F47: 08WH121 | G47: MACHINE SPO2 BATTERY FAULT- 8B | H47: Normal | I47: 0 days, 0 hrs, 37 mins | J47: 10-Mar-2026 09:23:00 | K47: 46091.417 | L47: 10-Mar-2026 11:00:00 | M47: =IF(D47>44999.99,100,ROUNDUP((D47/4999.99)*10,-1)) -> 20 | N47: N | O47: ='[15]B1& B2 UNSCHEDULED'!$O$24 -> 0 | Q47: N | R47: =IF(L47="",AKHIR-J47,L47-J47+1) -> 1.0673611 | S47: =WORKDAY(J47,6,AKHIR) -> 46099 | T47: 0 | U47: =IF(Q47="N",0,M47*T47) -> 0 | V47: REPLACE NEW BATTERY , TEST OK.
A48: 25 | B48: IKN400967 | C48: =VLOOKUP(B48,[14]AssetDetails_UEM!$A$3:$AH$1849,6,FALSE) -> Linear Accelerators | D48: =VLOOKUP(B48,[14]AssetDetails_UEM!$A$3:$AK$1849,22,FALSE) -> 12049370 | E48: IKNWIBE26004638 | F48: 01RT165 | G48: MACHINE LINAC 2- WATER PRESSURE LOW (5.0) | H48: Normal | I48: 0 days, 0 hrs, 10 mins | J48: 10-Mar-2026 10:50:00 | K48: 10-Mar-2026 11:00:00 | L48: 10-Mar-2026 12:30:00 | M48: =IF(D48>44999.99,100,ROUNDUP((D48/4999.99)*10,-1)) -> 100 | N48: N | O48: ='[15]B1& B2 UNSCHEDULED'!$O$24 -> 0 | Q48: N | R48: =IF(L48="",AKHIR-J48,L48-J48+1) -> 1.0694444 | S48: =WORKDAY(J48,6,AKHIR) -> 46099 | T48: 0 | U48: =IF(Q48="N",0,M48*T48) -> 0 | V48: REFILL WITH DISTILED WATER PRESSURE INTO THE CHAMBER UNTILL REACH THE TARGET PRESSURE. UNIT LEFT IN FULL FUNCTIONALITY
A49: 26 | B49: IKN400442 | C49: =VLOOKUP(B49,[14]AssetDetails_UEM!$A$3:$AH$1849,6,FALSE) -> Infusion Pumps, Syringe | D49: =VLOOKUP(B49,[14]AssetDetails_UEM!$A$3:$AK$1849,22,FALSE) -> 10225 | E49: IKNWIBE26004644 | F49: 07WE143 | G49: USER TRAINING SYRING PUMP-SAFE HANDLING AND OPERATION | H49: User Training | I49: 0 days, 0 hrs, 10 mins | J49: 10-Mar-2026 10:00:00 | K49: 46091.424 | L49: 10-Mar-2026 12:00:00 | M49: =IF(D49>44999.99,100,ROUNDUP((D49/4999.99)*10,-1)) -> 30 | N49: N | O49: ='[15]B1& B2 UNSCHEDULED'!$O$24 -> 0 | Q49: N | R49: =IF(L49="",AKHIR-J49,L49-J49+1) -> 1.0833333 | S49: =WORKDAY(J49,6,AKHIR) -> 46099 | T49: 0 | U49: =IF(Q49="N",0,M49*T49) -> 0 | V49: TRAINING AND PROPER OPERATION TO ALL SATFF NURSE, PRORIDING GUIDANCE ON THE SAFE HANDLING AND PROPER OPERATION OF THE SYRINGE PUMP MACHINE
A50: 27 | B50: IKN400443 | C50: =VLOOKUP(B50,[14]AssetDetails_UEM!$A$3:$AH$1849,6,FALSE) -> Infusion Pumps, Syringe | D50: =VLOOKUP(B50,[14]AssetDetails_UEM!$A$3:$AK$1849,22,FALSE) -> 10225 | E50: IKNWIBE26004645 | F50: 07WF143 | G50: USER TRAINING SYRING PUMP-SAFE HANDLING AND OPERATION | H50: User Training | I50: 0 days, 0 hrs, 10 mins | J50: 10-Mar-2026 12:00:00 | K50: 46091.507 | L50: 10-Mar-2026 14:00:00 | M50: =IF(D50>44999.99,100,ROUNDUP((D50/4999.99)*10,-1)) -> 30 | N50: N | O50: ='[15]B1& B2 UNSCHEDULED'!$O$24 -> 0 | Q50: N | R50: =IF(L50="",AKHIR-J50,L50-J50+1) -> 1.0833333 | S50: =WORKDAY(J50,6,AKHIR) -> 46099 | T50: 0 | U50: =IF(Q50="N",0,M50*T50) -> 0 | V50: TRAINING DELIVERED TO ALL STAFF NURSE,PRIORIDING GUIDANCE ON THE SAFE HANDLING AND PROPER OPERATION OF THE SRYING PUMP MACHINE
A51: 28 | B51: IKN400263 | C51: =VLOOKUP(B51,[14]AssetDetails_UEM!$A$3:$AH$1849,6,FALSE) -> Oximeters, Pulse | D51: =VLOOKUP(B51,[14]AssetDetails_UEM!$A$3:$AK$1849,22,FALSE) -> 5410 | E51: IKNWIBE26004655 | F51: 08WG113 | G51: PORTABLE SPO2 NOT FUNCTION (KKM/IKN/H/13/2551) -8A | H51: Normal | I51: 0 days, 0 hrs, 12 mins | J51: 10-Mar-2026 17:03:00 | K51: 46091.719 | L51: 10-Mar-2026 17:40:00 | M51: =IF(D51>44999.99,100,ROUNDUP((D51/4999.99)*10,-1)) -> 20 | N51: N | O51: ='[15]B1& B2 UNSCHEDULED'!$O$24 -> 0 | Q51: N | R51: =IF(L51="",AKHIR-J51,L51-J51+1) -> 1.0256944 | S51: =WORKDAY(J51,6,AKHIR) -> 46099 | T51: 0 | U51: =IF(Q51="N",0,M51*T51) -> 0 | V51: REPLACE NEW BATTERY , TEST UNIT OK.
A52: 29 | B52: IKN400387 | C52: =VLOOKUP(B52,[14]AssetDetails_UEM!$A$3:$AH$1849,6,FALSE) -> Sphygmomanometers, Electronic, Automatic | D52: =VLOOKUP(B52,[14]AssetDetails_UEM!$A$3:$AK$1849,22,FALSE) -> 4510 | E52: IKNWIBE26004710 | F52: 07WE143 | G52: BP SET BATTERY FAULT-7A | H52: Normal | I52: 0 days, 0 hrs, 8 mins | J52: 11-Mar-2026 08:22:00 | K52: 11-Mar-2026 08:30:00 | L52: 11-Mar-2026 09:30:00 | M52: =IF(D52>44999.99,100,ROUNDUP((D52/4999.99)*10,-1)) -> 10 | N52: N | O52: ='[15]B1& B2 UNSCHEDULED'!$O$24 -> 0 | Q52: N | R52: =IF(L52="",AKHIR-J52,L52-J52+1) -> 1.0472222 | S52: =WORKDAY(J52,6,AKHIR) -> 46100 | T52: 0 | U52: =IF(Q52="N",0,M52*T52) -> 0 | V52: REPLACE NEW CHARGER ADAPTER , TESTED AND CHECKED. UNIT ABLE TO CHARGE.
A53: 30 | B53: IKN401048 | C53: =VLOOKUP(B53,[14]AssetDetails_UEM!$A$3:$AH$1849,6,FALSE) -> Warming Units, Patient, Radiant, Adult | D53: =VLOOKUP(B53,[14]AssetDetails_UEM!$A$3:$AK$1849,22,FALSE) -> 12630 | E53: IKNWIBE26004715 | F53: 05OT159 | G53: RADIANT WARMER TIDAK PANAS-GOT ARAS 5 | H53: Normal | I53: 0 days, 0 hrs, 8 mins | J53: 11-Mar-2026 09:07:00 | K53: 46092.385 | L53: 11-Mar-2026 09:30:00 | M53: =IF(D53>44999.99,100,ROUNDUP((D53/4999.99)*10,-1)) -> 30 | N53: N | O53: ='[15]B1& B2 UNSCHEDULED'!$O$24 -> 0 | Q53: N | R53: =IF(L53="",AKHIR-J53,L53-J53+1) -> 1.0159722 | S53: =WORKDAY(J53,6,AKHIR) -> 46100 | T53: 0 | U53: =IF(Q53="N",0,M53*T53) -> 0 | V53: ADJUSTR THE SETTING OF WARMER UNIT TO HIGH , UNIT TEST AND FUNCTIONING IN GOOD CONDITION
A54: 31 | B54: IKN400167 | C54: =VLOOKUP(B54,[14]AssetDetails_UEM!$A$3:$AH$1849,6,FALSE) -> Ventilators, Intensive Care | D54: =VLOOKUP(B54,[14]AssetDetails_UEM!$A$3:$AK$1849,22,FALSE) -> 151560 | E54: IKNWIBE26004732 | F54: 05IC114 | G54: VENTILATOR OXYGEN PROBLEM-ICU ARAS 5 | H54: Normal | I54: 0 days, 0 hrs, 21 mins | J54: 11-Mar-2026 14:34:00 | K54: 46092.625 | L54: 11-Mar-2026 15:30:00 | M54: =IF(D54>44999.99,100,ROUNDUP((D54/4999.99)*10,-1)) -> 100 | N54: N | O54: ='[15]B1& B2 UNSCHEDULED'!$O$24 -> 0 | Q54: N | R54: =IF(L54="",AKHIR-J54,L54-J54+1) -> 1.0388889 | S54: =WORKDAY(J54,6,AKHIR) -> 46100 | T54: 0 | U54: =IF(Q54="N",0,M54*T54) -> 0 | V54: REPLACE OXYGEN SENSOR , DEVICE CHECK PASSED. UNIT FUNCTIONING IN GOOD CONDITION
A55: 32 | B55: IKN401024 | C55: =VLOOKUP(B55,[14]AssetDetails_UEM!$A$3:$AH$1849,6,FALSE) -> Infusion Pumps, Syringe | D55: =VLOOKUP(B55,[14]AssetDetails_UEM!$A$3:$AK$1849,22,FALSE) -> 10225 | E55: IKNWIBE26004733 | F55: 05OT120 | G55: HANGER SYRINGE PUMP LOOSE-GOT ARAS 5 | H55: Normal | I55: 0 days, 0 hrs, 6 mins | J55: 11-Mar-2026 14:39:00 | K55: 46092.615 | L55: 11-Mar-2026 14:45:00 | M55: =IF(D55>44999.99,100,ROUNDUP((D55/4999.99)*10,-1)) -> 30 | N55: N | O55: ='[15]B1& B2 UNSCHEDULED'!$O$24 -> 0 | Q55: N | R55: =IF(L55="",AKHIR-J55,L55-J55+1) -> 1.0041667 | S55: =WORKDAY(J55,6,AKHIR) -> 46100 | T55: 0 | U55: =IF(Q55="N",0,M55*T55) -> 0 | V55: REPLACE NEW HANGER
A56: 33 | B56: IKN400956 | C56: =VLOOKUP(B56,[14]AssetDetails_UEM!$A$3:$AH$1849,6,FALSE) -> Linear Accelerators | D56: =VLOOKUP(B56,[14]AssetDetails_UEM!$A$3:$AK$1849,22,FALSE) -> 21961900 | E56: IKNWIBE26004734 | F56: 01RT172 | G56: LINAC 3 -KFIL PUMP FLOW | H56: Normal | I56: 0 days, 0 hrs, 35 mins | J56: 11-Mar-2026 14:46:00 | K56: 11-Mar-2026 15:21:00 | L56: 11-Mar-2026 16:00:00 | M56: =IF(D56>44999.99,100,ROUNDUP((D56/4999.99)*10,-1)) -> 100 | N56: N | O56: ='[15]B1& B2 UNSCHEDULED'!$O$24 -> 0 | Q56: N | R56: =IF(L56="",AKHIR-J56,L56-J56+1) -> 1.0513889 | S56: =WORKDAY(J56,6,AKHIR) -> 46100 | T56: 0 | U56: =IF(Q56="N",0,M56*T56) -> 0 | V56: FLUSHING TO REMOVE AIR CLOGS AND BUBBLES. PRESSURE BACK TO NORMAL AND UNIT RUNNING IN NORMAL CONDITIONS.
A57: 34 | B57: IKN400761 | C57: =VLOOKUP(B57,[14]AssetDetails_UEM!$A$3:$AH$1849,6,FALSE) -> Analyzers, Laboratory, Clinical Chemistry, Automated | D57: =VLOOKUP(B57,[14]AssetDetails_UEM!$A$3:$AK$1849,22,FALSE) -> 421005 | E57: IKNWIBE26004792 | F57: 04LA133 | G57: MACHINE COBAS ERROR -PATHOLOGY ARAS 4 | H57: Normal | I57: 0 days, 0 hrs, 20 mins | J57: 12-Mar-2026 08:27:00 | K57: 12-Mar-2026 08:47:00 | L57: 12-Mar-2026 09:47:00 | M57: =IF(D57>44999.99,100,ROUNDUP((D57/4999.99)*10,-1)) -> 100 | N57: N | O57: ='[15]B1& B2 UNSCHEDULED'!$O$24 -> 0 | Q57: N | R57: =IF(L57="",AKHIR-J57,L57-J57+1) -> 1.0555556 | S57: =WORKDAY(J57,6,AKHIR) -> 46101 | T57: 0 | U57: =IF(Q57="N",0,M57*T57) -> 0 | V57: P - RESTART THE UNIT , RUN SAMPLE NO ERROR
A58: 35 | B58: IKN400140 | C58: =VLOOKUP(B58,[14]AssetDetails_UEM!$A$3:$AH$1849,6,FALSE) -> Infusion Pumps, General-Purpose | D58: =VLOOKUP(B58,[14]AssetDetails_UEM!$A$3:$AK$1849,22,FALSE) -> 10825 | E58: IKNWIBE26004814 | F58: 05IC113 | G58: VOLUMETRIC CHARGING TIDAK MASUK - ICU | H58: Normal | I58: 0 days, 1 hrs, 5 mins | J58: 12-Mar-2026 16:55:00 | K58: 12-Mar-2026 18:00:00 | L58: 12-Mar-2026 21:00:00 | M58: =IF(D58>44999.99,100,ROUNDUP((D58/4999.99)*10,-1)) -> 30 | N58: N | O58: ='[15]B1& B2 UNSCHEDULED'!$O$24 -> 0 | Q58: N | R58: =IF(L58="",AKHIR-J58,L58-J58+1) -> 1.1701389 | S58: =WORKDAY(J58,6,AKHIR) -> 46101 | T58: 0 | U58: =IF(Q58="N",0,M58*T58) -> 0 | V58: NSPECT MACHINE FOUND CABLE DISPLAY HAS FLUID, CLEAN CABLE DISPLAY. INSPECT BOARD OK, TIGHTEN CONNECTION CABLE TO BOARD MACHINE FUNCTIONING WELL , UNIT READY TO USE
A59: 36 | B59: IKN400917 | C59: =VLOOKUP(B59,[14]AssetDetails_UEM!$A$3:$AH$1849,6,FALSE) -> Electrocardiographs, Multichannel, Interpretative | D59: =VLOOKUP(B59,[14]AssetDetails_UEM!$A$3:$AK$1849,22,FALSE) -> 25260 | E59: IKNWIBE26004881 | F59: 03OC135 | G59: ECG TIDAK BOLEH EXPORT KE MOSAIQ - KLINIK ONKOLOGI | H59: Normal | I59: 0 days, 0 hrs, 43 mins | J59: 13-Mar-2026 09:07:00 | K59: 13-Mar-2026 09:50:00 | L59: 17-Mar-2026 16:00:00 | M59: =IF(D59>44999.99,100,ROUNDUP((D59/4999.99)*10,-1)) -> 60 | N59: N | O59: ='[15]B1& B2 UNSCHEDULED'!$O$24 -> 0 | Q59: N | R59: 3 | S59: =WORKDAY(J59,6,AKHIR) -> 46104 | T59: 0 | U59: =IF(Q59="N",0,M59*T59) -> 0 | V59: RECONFIGURE THE MACHINE AND IT CHECKED THE ISSUE. UNIT TESTED OKAY UNDER MONITORING
A60: 37 | B60: IKN400407 | C60: =VLOOKUP(B60,[14]AssetDetails_UEM!$A$3:$AH$1849,6,FALSE) -> Mattress Systems, Alternating-Pressure | D60: =VLOOKUP(B60,[14]AssetDetails_UEM!$A$3:$AK$1849,22,FALSE) -> 28630 | E60: IKNWIBE26004885 | F60: 06WD153 | G60: WAYAR SAMBUNGAN RIPPLE MATTRESS ROSAK (KAUNTER) - 6B | H60: Normal | I60: 0 days, 0 hrs, 45 mins | J60: 13-Mar-2026 10:45:00 | K60: 13-Mar-2026 11:30:00 | L60: 13-Mar-2026 12:30:00 | M60: =IF(D60>44999.99,100,ROUNDUP((D60/4999.99)*10,-1)) -> 60 | N60: N | O60: ='[15]B1& B2 UNSCHEDULED'!$O$24 -> 0 | Q60: N | R60: =IF(L60="",AKHIR-J60,L60-J60+1) -> 1.0729167 | S60: =WORKDAY(J60,6,AKHIR) -> 46104 | T60: 0 | U60: =IF(Q60="N",0,M60*T60) -> 0 | V60: DO PHYSICAL INSPECTION OK , CHECK FUSE OK. TEST PASSED
A61: 38 | B61: IKN400967 | C61: =VLOOKUP(B61,[14]AssetDetails_UEM!$A$3:$AH$1849,6,FALSE) -> Linear Accelerators | D61: =VLOOKUP(B61,[14]AssetDetails_UEM!$A$3:$AK$1849,22,FALSE) -> 12049370 | E61: IKNWIBE26004969 | F61: 01RT165 | G61: WATER TEMPERATURE NAIK (LINAC 2) - RADIOTERAPI | H61: Normal | I61: 0 days, 0 hrs, 26 mins | J61: 16-Mar-2026 07:34:00 | K61: 16-Mar-2026 08:00:00 | L61: 16-Mar-2026 09:12:00 | M61: =IF(D61>44999.99,100,ROUNDUP((D61/4999.99)*10,-1)) -> 100 | N61: N | O61: ='[15]B1& B2 UNSCHEDULED'!$O$24 -> 0 | Q61: N | R61: =IF(L61="",AKHIR-J61,L61-J61+1) -> 1.0680556 | S61: =WORKDAY(J61,6,AKHIR) -> 46105 | T61: 0 | U61: =IF(Q61="N",0,M61*T61) -> 0 | V61: FLUSHING THE AIR THRU CHILLER SYSTEM AND WATER BACK TO NORMAL PRESSURE. UNIT LEFT IN GOOD WORKING CONDITIONS.
A62: 39 | B62: IKN400495 | C62: Linear Accelerators | D62: RM20,550.421.50 | E62: IKNWIBE26004972 | F62: 05WB143 | G62: BP CUFF BOCOR - 5A | H62: Normal | I62: 0 days, 0 hrs, 13 mins | J62: 16-Mar-2026 08:17:00 | K62: 16-Mar-2026 08:30:00 | L62: 16-Mar-2026 09:00:00 | M62: =IF(D62>44999.99,100,ROUNDUP((D62/4999.99)*10,-1)) -> 100 | N62: N | O62: ='[15]B1& B2 UNSCHEDULED'!$O$24 -> 0 | Q62: N | R62: =IF(L62="",AKHIR-J62,L62-J62+1) -> 1.0298611 | S62: =WORKDAY(J62,6,AKHIR) -> 46105 | T62: 0 | U62: =IF(Q62="N",0,M62*T62) -> 0 | V62: REPLACE NEW CUFF.TESTED OKAY AND FUNCTIONING
A63: 40 | B63: IKN400757 | C63: =VLOOKUP(B63,[14]AssetDetails_UEM!$A$3:$AH$1849,6,FALSE) -> Analyzers, Laboratory, Hematology, Cell Counting, Automated | D63: =VLOOKUP(B63,[14]AssetDetails_UEM!$A$3:$AK$1849,22,FALSE) -> 565350 | E63: IKNWIBE26004982 | F63: 04LA131 | G63: MESIN SP10 PRESSURE ERROR - PATOLOGI | H63: Normal | I63: 0 days, 0 hrs, 10 mins | J63: 16-Mar-2026 09:50:00 | K63: 16-Mar-2026 10:00:00 | L63: 16-Mar-2026 15:00:00 | M63: =IF(D63>44999.99,100,ROUNDUP((D63/4999.99)*10,-1)) -> 100 | N63: N | O63: ='[15]B1& B2 UNSCHEDULED'!$O$24 -> 0 | Q63: N | R63: =IF(L63="",AKHIR-J63,L63-J63+1) -> 1.2152778 | S63: =WORKDAY(J63,6,AKHIR) -> 46105 | T63: 0 | U63: =IF(Q63="N",0,M63*T63) -> 0 | V63: ADJUST REGULATOR TO SETTING THE PRESSURE 0.05MP
A64: 41 | B64: IKN400956 | C64: =VLOOKUP(B64,[14]AssetDetails_UEM!$A$3:$AH$1849,6,FALSE) -> Linear Accelerators | D64: =VLOOKUP(B64,[14]AssetDetails_UEM!$A$3:$AK$1849,22,FALSE) -> 21961900 | E64: IKNWIBE26005006 | F64: 01RT172 | G64: CONNECTION ERROR DARI PC SEQUENCER KE 4D TREATMENT CONSOLE - RADIOTERAPI (P- WO UNDER IT , ENG IMRAN) | H64: Normal | I64: 0 days, 0 hrs, 7 mins | J64: 16-Mar-2026 16:23:00 | K64: 16-Mar-2026 16:30:00 | L64: 16-Mar-2026 18:30:00 | M64: =IF(D64>44999.99,100,ROUNDUP((D64/4999.99)*10,-1)) -> 100 | N64: N | O64: ='[15]B1& B2 UNSCHEDULED'!$O$24 -> 0 | Q64: N | R64: =IF(L64="",AKHIR-J64,L64-J64+1) -> 1.0881944 | S64: =WORKDAY(J64,6,AKHIR) -> 46105 | T64: 0 | U64: =IF(Q64="N",0,M64*T64) -> 0 | V64: RESIT ALL CABLE AND CONNECTOR AND COMMUNICATION RETURNS TO NORMAL.
A65: 42 | B65: IKN400798 | C65: =VLOOKUP(B65,[14]AssetDetails_UEM!$A$3:$AH$1849,6,FALSE) -> Radiographic Systems, Digital | D65: =VLOOKUP(B65,[14]AssetDetails_UEM!$A$3:$AK$1849,22,FALSE) -> 1958605 | E65: IKNWIBE26005159 | F65: 03ID181 | G65: MEJA XRAY MESIN TRUCK - RADIOLOGI ARAS 3 | H65: Normal | I65: 0 days, 0 hrs, 13 mins | J65: 17-Mar-2026 14:07:00 | K65: 17-Mar-2026 14:20:00 | L65: 17-Mar-2026 16:00:00 | M65: =IF(D65>44999.99,100,ROUNDUP((D65/4999.99)*10,-1)) -> 100 | N65: N | O65: ='[15]B1& B2 UNSCHEDULED'!$O$24 -> 0 | Q65: N | R65: =IF(L65="",AKHIR-J65,L65-J65+1) -> 1.0784722 | S65: =WORKDAY(J65,6,AKHIR) -> 46106 | T65: 0 | U65: =IF(Q65="N",0,M65*T65) -> 0 | V65: TESTED OKAY, RESET TABLE AND MACHINE FUNCTIONING OKAY.
A66: 43 | B66: IKN401353 | C66: =VLOOKUP(B66,[14]AssetDetails_UEM!$A$3:$AH$1849,6,FALSE) -> Radiographic/Fluoroscopic Units, Mobile | D66: =VLOOKUP(B66,[14]AssetDetails_UEM!$A$3:$AK$1849,22,FALSE) -> 399000 | E66: IKNWIBE26005299 | F66: 05OT159 | G66: MESIN TIDAK HIDUP | H66: Normal | I66: 0 days, 0 hrs, 10 mins | J66: 17-Mar-2026 13:45:00 | K66: 17-Mar-2026 13:55:00 | L66: 17-Mar-2026 15:50:00 | M66: =IF(D66>44999.99,100,ROUNDUP((D66/4999.99)*10,-1)) -> 100 | N66: N | O66: ='[15]B1& B2 UNSCHEDULED'!$O$24 -> 0 | Q66: N | R66: =IF(L66="",AKHIR-J66,L66-J66+1) -> 1.0868056 | S66: =WORKDAY(J66,6,AKHIR) -> 46106 | T66: 0 | U66: =IF(Q66="N",0,M66*T66) -> 0 | V66: REPORT TO FEMS , CHECKED SUPPLY OKAY. TEST MACHINE FUNCTIONING OKAY.
A67: 44 | B67: IKN400292 | C67: =VLOOKUP(B67,[14]AssetDetails_UEM!$A$3:$AH$1849,6,FALSE) -> Infusion Pumps, General-Purpose | D67: =VLOOKUP(B67,[14]AssetDetails_UEM!$A$3:$AK$1849,22,FALSE) -> 10825 | E67: IKNWIBE26005349 | F67: 08WH121 | G67: CHARGER INFUSION PUMP PUTUS- 8A | H67: Normal | I67: 0 days, 0 hrs, 32 mins | J67: 18-Mar-2026 06:28:00 | K67: 18-Mar-2026 06:28:00 | L67: 46107.417 | M67: =IF(D67>44999.99,100,ROUNDUP((D67/4999.99)*10,-1)) -> 30 | N67: N | O67: ='[15]B1& B2 UNSCHEDULED'!$O$24 -> 0 | Q67: Y | R67: 7 | S67: 46111 | T67: 0 | U67: =IF(Q67="N",0,M67*T67) -> 0 | V67: CHARGER FAULTY WAITING PARTS FROM VENDOR (B BROUN). DONE REPLACED NEW CHARGER FOR BP AND TESTED OK.
A68: 45 | B68: IKN400956 | C68: =VLOOKUP(B68,[14]AssetDetails_UEM!$A$3:$AH$1849,6,FALSE) -> Linear Accelerators | D68: =VLOOKUP(B68,[14]AssetDetails_UEM!$A$3:$AK$1849,22,FALSE) -> 21961900 | E68: IKNWIBE26005351 | F68: 01RT172 | G68: MESIN CRED & NOVALIS 4DITC TIDAK CONNECT - RADIOTERAPI | H68: Normal | I68: 0 days, 0 hrs, 9 mins | J68: 18-Mar-2026 07:51:00 | K68: 18-Mar-2026 08:00:00 | L68: 18-Mar-2026 09:17:00 | M68: =IF(D68>44999.99,100,ROUNDUP((D68/4999.99)*10,-1)) -> 100 | N68: N | O68: ='[15]B1& B2 UNSCHEDULED'!$O$24 -> 0 | Q68: N | R68: =IF(L68="",AKHIR-J68,L68-J68+1) -> 1.0597222 | S68: =WORKDAY(J68,6,AKHIR) -> 46107 | T68: 0 | U68: =IF(Q68="N",0,M68*T68) -> 0 | V68: FOUND THAT THE SWITCH FOR NETWORK HAVE CONFLICT, PLUG THE CONNECTION TO THE WALL PORT AND SYSTEM BACK TO NORMAL. UNIT LEFT IN WORKING PROPERLY.
A69: 46 | B69: IKN400978 | C69: =VLOOKUP(B69,[14]AssetDetails_UEM!$A$3:$AH$1849,6,FALSE) -> Scanning Systems, Computed Tomography | D69: =VLOOKUP(B69,[14]AssetDetails_UEM!$A$3:$AK$1849,22,FALSE) -> 3557530 | E69: IKNWIBE26005383 | F69: 01RT116 | G69: MESIN CT SIM 1 AUTO OFF - RADDIOTERAPI ARAS 1 | H69: Normal | I69: 0 days, 0 hrs, 14 mins | J69: 18-Mar-2026 09:01:00 | K69: 18-Mar-2026 09:15:00 | L69: 18-Mar-2026 09:45:00 | M69: =IF(D69>44999.99,100,ROUNDUP((D69/4999.99)*10,-1)) -> 100 | N69: N | O69: ='[15]B1& B2 UNSCHEDULED'!$O$24 -> 0 | Q69: N | R69: =IF(L69="",AKHIR-J69,L69-J69+1) -> 1.0305556 | S69: =WORKDAY(J69,6,AKHIR) -> 46107 | T69: 0 | U69: =IF(Q69="N",0,M69*T69) -> 0 | V69: REBOOT AND RESTART WHOLE SYSTEM. UNIT BACK TO NORMAL CONDITION AND TESTED OK. UNIT LEFT IN GOOD / FULLY FUNCTIONALITY
A70: 47 | B70: IKN400973 | C70: =VLOOKUP(B70,[14]AssetDetails_UEM!$A$3:$AH$1849,6,FALSE) -> Scanning Systems, Computed Tomography | D70: =VLOOKUP(B70,[14]AssetDetails_UEM!$A$3:$AK$1849,22,FALSE) -> 3557530 | E70: IKNWIBE26005384 | F70: 01RT118 | G70: CT SIM 2 SENTINEL UNABLE TO CONNECT TO SERVER - RADIOTERAPI ARAS 1 | H70: Normal | I70: 0 days, 0 hrs, 12 mins | J70: 18-Mar-2026 09:03:00 | K70: 18-Mar-2026 09:15:00 | L70: 18-Mar-2026 09:45:00 | M70: =IF(D70>44999.99,100,ROUNDUP((D70/4999.99)*10,-1)) -> 100 | N70: N | O70: ='[15]B1& B2 UNSCHEDULED'!$O$24 -> 0 | Q70: N | R70: =IF(L70="",AKHIR-J70,L70-J70+1) -> 1.0291667 | S70: =WORKDAY(J70,6,AKHIR) -> 46107 | T70: 0 | U70: =IF(Q70="N",0,M70*T70) -> 0 | V70: FOUND THIS ISSUES RELATED WITH C-RAD AT LINAC 3 / NOVALIS. MOVED TO WALL PORT AND SYSTEM BACK TO NORMAL. UNIT LEFT IN GOOD WORKING CONDITION
A71: 48 | B71: IKN402025 | C71: =VLOOKUP(B71,[14]AssetDetails_UEM!$A$3:$AH$1849,6,FALSE) -> Scanning Systems, Ultrasonic, General-Purpose | D71: =VLOOKUP(B71,[14]AssetDetails_UEM!$A$3:$AK$1849,22,FALSE) -> 125000 | E71: IKNWIBE26005385 | F71: 03ID157 | G71: MACHINE NOT CHARGING | H71: Normal | I71: 0 days, 0 hrs, 50 mins | J71: 18-Mar-2026 08:30:00 | K71: 18-Mar-2026 09:20:00 | L71: 18-Mar-2026 10:20:00 | M71: =IF(D71>44999.99,100,ROUNDUP((D71/4999.99)*10,-1)) -> 100 | N71: N | O71: ='[15]B1& B2 UNSCHEDULED'!$O$24 -> 0 | Q71: N | R71: =IF(L71="",AKHIR-J71,L71-J71+1) -> 1.0763889 | S71: =WORKDAY(J71,6,AKHIR) -> 46107 | T71: 0 | U71: =IF(Q71="N",0,M71*T71) -> 0 | V71: REPLACED POWER CARD. TESTED OKAY.
A72: 49 | B72: IKN400310 | C72: =VLOOKUP(B72,[14]AssetDetails_UEM!$A$3:$AH$1849,6,FALSE) -> Sphygmomanometers, Electronic, Automatic | D72: =VLOOKUP(B72,[14]AssetDetails_UEM!$A$3:$AK$1849,22,FALSE) -> 4510 | E72: IKNWIBE26005425 | F72: 08WH143 | G72: CLIP BP CUFF PATAH - 8B | H72: Normal | I72: 0 days, 0 hrs, 58 mins | J72: 18-Mar-2026 14:32:00 | K72: 18-Mar-2026 15:30:00 | L72: 18-Mar-2026 18:30:00 | M72: =IF(D72>44999.99,100,ROUNDUP((D72/4999.99)*10,-1)) -> 10 | N72: N | O72: ='[15]B1& B2 UNSCHEDULED'!$O$24 -> 0 | Q72: N | R72: =IF(L72="",AKHIR-J72,L72-J72+1) -> 1.1652778 | S72: =WORKDAY(J72,6,AKHIR) -> 46107 | T72: 0 | U72: =IF(Q72="N",0,M72*T72) -> 0 | V72: REPLACE NEW CONNECTOR AND CUFF , MAKE SURE FIT TO USE
A73: 50 | B73: IKN402210 | C73: Scanning Systems, Magnetic Resonance imaging, full-body | D73: 10494120 | E73: IKNWIBE26005426 | F73: 03ID111 | G73: CM - MAGNIFI CALIBRATION (MRI) | H73: Corrective Maintenance (CM) | I73: 0 days, 0 hrs, 15 mins | J73: 18-Mar-2026 14:00:00 | K73: 18-Mar-2026 14:15:00 | L73: 18-Mar-2026 18:00:00 | M73: =IF(D73>44999.99,100,ROUNDUP((D73/4999.99)*10,-1)) -> 100 | N73: N | O73: ='[15]B1& B2 UNSCHEDULED'!$O$24 -> 0 | Q73: N | R73: =IF(L73="",AKHIR-J73,L73-J73+1) -> 1.1666667 | S73: =WORKDAY(J73,6,AKHIR) -> 46107 | T73: 0 | U73: =IF(Q73="N",0,M73*T73) -> 0 | V73: YEARLY MAGNIFI CALIBRATION DONE BY VENDOR. TESTED , PASSED.
A74: 51 | B74: IKN400956 | C74: Linear Accelerators | D74: 21961900 | E74: IKNWIBE26005483 | F74: 01RT172 | G74: POWER TRIP (MACHINE NOVALIS) - RADIOTERAPI | H74: Normal | I74: 0 days, 0 hrs, 8 mins | J74: 19-Mar-2026 13:32:00 | K74: 19-Mar-2026 13:40:00 | L74: 19-Mar-2026 14:20:00 | M74: =IF(D74>44999.99,100,ROUNDUP((D74/4999.99)*10,-1)) -> 100 | N74: N | O74: ='[15]B1& B2 UNSCHEDULED'!$O$24 -> 0 | Q74: N | R74: =IF(L74="",AKHIR-J74,L74-J74+1) -> 1.0333333 | S74: =WORKDAY(J74,6,AKHIR) -> 46108 | T74: 0 | U74: =IF(Q74="N",0,M74*T74) -> 0 | V74: M-RESET BREAKER AND POWER SUPPLY BACK TO NORMAL CONDITIONS.UNIT LEST IN FULL FUNCTIONALITY
A75: 52 | B75: IKN400465 | C75: =VLOOKUP(B75,[14]AssetDetails_UEM!$A$3:$AH$1849,6,FALSE) -> Electrocardiographs, Multichannel, Interpretative | D75: =VLOOKUP(B75,[14]AssetDetails_UEM!$A$3:$AK$1849,22,FALSE) -> 25260 | E75: IKNWIBE26005487 | F75: 05WB107 | G75: TROLI ECG PENYANGKUT WAYAR LOGGAR- WAD 5A | H75: Normal | I75: 0 days, 0 hrs, 20 mins | J75: 19-Mar-2026 20:55:00 | K75: 19-Mar-2026 21:15:00 | L75: 19-Mar-2026 22:00:00 | M75: =IF(D75>44999.99,100,ROUNDUP((D75/4999.99)*10,-1)) -> 60 | N75: N | O75: ='[15]B1& B2 UNSCHEDULED'!$O$24 -> 0 | Q75: N | R75: =IF(L75="",AKHIR-J75,L75-J75+1) -> 1.0451389 | S75: =WORKDAY(J75,6,AKHIR) -> 46108 | T75: 0 | U75: =IF(Q75="N",0,M75*T75) -> 0 | V75: TIGHTHEN THE MODULE HANGER/ HOLDER SCREW ACCORDING.ADD WASHER FOR MORE FIRM AND TIGHT
A76: 53 | B76: IKN400486 | C76: =VLOOKUP(B76,[14]AssetDetails_UEM!$A$3:$AH$1849,6,FALSE) -> Mattress Systems, Alternating-Pressure | D76: =VLOOKUP(B76,[14]AssetDetails_UEM!$A$3:$AK$1849,22,FALSE) -> 28630 | E76: IKNWIBE26005565 | F76: 05WB113 | G76: KEPALA PLUG RIPPLE MATTRESS BENGKOK- 5A | H76: Normal | I76: 0 days, 0 hrs, 14 mins | J76: 22-Mar-2026 21:59:00 | K76: 46103.926 | L76: 22-Mar-2026 23:00:00 | M76: =IF(D76>44999.99,100,ROUNDUP((D76/4999.99)*10,-1)) -> 60 | N76: N | O76: ='[15]B1& B2 UNSCHEDULED'!$O$24 -> 0 | Q76: N | R76: =IF(L76="",AKHIR-J76,L76-J76+1) -> 1.0423611 | S76: =WORKDAY(J76,6,AKHIR) -> 46111 | T76: 0 | U76: =IF(Q76="N",0,M76*T76) -> 0 | V76: REPLACED WITH NEW 5A PLUGTOP AND TESTED,PASS. UNIT LEFT IN FULL FUNCTIONALITY
A77: 54 | B77: IKN400967 | C77: =VLOOKUP(B77,[14]AssetDetails_UEM!$A$3:$AH$1849,6,FALSE) -> Linear Accelerators | D77: =VLOOKUP(B77,[14]AssetDetails_UEM!$A$3:$AK$1849,22,FALSE) -> 12049370 | E77: IKNWIBE26005634 | F77: 01RT165 | G77: LINAC 2 PROBLEM 'SAIZ MONITORING MENGECIL DAN SISTEM IVIEW GP TIDAK BOLEH BUKA' | H77: Normal | I77: 0 days, 0 hrs, 42 mins | J77: 24-Mar-2026 07:18:00 | K77: 24-Mar-2026 08:00:00 | L77: 24-Mar-2026 08:30:00 | M77: =IF(D77>44999.99,100,ROUNDUP((D77/4999.99)*10,-1)) -> 100 | N77: N | O77: ='[15]B1& B2 UNSCHEDULED'!$O$24 -> 0 | Q77: N | R77: =IF(L77="",AKHIR-J77,L77-J77+1) -> 1.05 | S77: =WORKDAY(J77,6,AKHIR) -> 46114 | T77: 0 | U77: =IF(Q77="N",0,M77*T77) -> 0 | V77: TIGHTEN AND RESIT ALL CABLE CONNECTORS DISPLAY / SCREEN BACK AS USUAL. REPLACED WITH OTHER BACKUP UPS FOR XVI AND IVIEW ABLE TO TURN ON
A78: 55 | B78: IKN400967 | C78: =VLOOKUP(B78,[14]AssetDetails_UEM!$A$3:$AH$1849,6,FALSE) -> Linear Accelerators | D78: =VLOOKUP(B78,[14]AssetDetails_UEM!$A$3:$AK$1849,22,FALSE) -> 12049370 | E78: IKNWIBE26005636 | F78: 01RT165 | G78: LINAC 2 'VACCUM TARGET DROP' | H78: Normal | I78: 0 days, 0 hrs, 6 mins | J78: 24-Mar-2026 08:19:00 | K78: 24-Mar-2026 08:25:00 | L78: 24-Mar-2026 09:30:00 | M78: =IF(D78>44999.99,100,ROUNDUP((D78/4999.99)*10,-1)) -> 100 | N78: N | O78: ='[15]B1& B2 UNSCHEDULED'!$O$24 -> 0 | Q78: N | R78: =IF(L78="",AKHIR-J78,L78-J78+1) -> 1.0493056 | S78: =WORKDAY(J78,6,AKHIR) -> 46114 | T78: 0 | U78: =IF(Q78="N",0,M78*T78) -> 0 | V78: ADD WATER PRESSURE TO THE DESIRED VALUE (0.8 BAR) AND VACUUM TARGET BACK TO NORMAL CONDITION. UNIT LEFT IN GOOD WORKING CONDITION
A79: 56 | B79: IKN401525 | C79: =VLOOKUP(B79,[14]AssetDetails_UEM!$A$3:$AH$1849,6,FALSE) -> Chairs, Examination/Treatment, Dentistry | D79: =VLOOKUP(B79,[14]AssetDetails_UEM!$A$3:$AK$1849,22,FALSE) -> 72000 | E79: IKNWIBE26005803 | F79: 03MC107 | G79: CHAIR DENTAL LEAKING- MDC ARAS 3 | H79: Normal | I79: 0 days, 0 hrs, 3 mins | J79: 26-Mar-2026 14:37:00 | K79: 26-Mar-2026 14:40:00 | L79: 26-Mar-2026 15:15:00 | M79: =IF(D79>44999.99,100,ROUNDUP((D79/4999.99)*10,-1)) -> 100 | N79: N | O79: ='[15]B1& B2 UNSCHEDULED'!$O$24 -> 0 | Q79: N | R79: =IF(L79="",AKHIR-J79,L79-J79+1) -> 1.0263889 | S79: =WORKDAY(J79,6,AKHIR) -> 46118 | T79: 0 | U79: =IF(Q79="N",0,M79*T79) -> 0 | V79: RETIGHTHEN THE CONNECTOR, TESTED THE FUNCTIONING OF BLOWER AND WATER.NO LEAKING OCCUR,UNIT IN GOOD CONDITION
A80: 57 | B80: IKN401246 | C80: Linear Accelerators | D80: RM20,550.421.50 | E80: IKNWIBE26005894 | F80: 01RT156 | G80: CM-MONOCO MONTLY CHECKING | H80: Corrective Maintenance (CM) | I80: 0 days, 0 hrs, 25 mins | J80: 27-Mar-2026 10:00:00 | K80: 46108.434 | L80: 46108.51 | M80: =IF(D80>44999.99,100,ROUNDUP((D80/4999.99)*10,-1)) -> 100 | N80: N | O80: ='[15]B1& B2 UNSCHEDULED'!$O$24 -> 0 | Q80: N | R80: =IF(L80="",AKHIR-J80,L80-J80+1) -> 1.09375 | S80: =WORKDAY(J80,6,AKHIR) -> 46119 | T80: 0 | U80: =IF(Q80="N",0,M80*T80) -> 0 | V80: MONTLY CHECKING AS PER VENDOR ATTACHMENT
A81: 58 | B81: IKN400774 | C81: =VLOOKUP(B81,[14]AssetDetails_UEM!$A$3:$AH$1849,6,FALSE) -> Scanning Systems, Computed Tomography | D81: =VLOOKUP(B81,[14]AssetDetails_UEM!$A$3:$AK$1849,22,FALSE) -> 4605710 | E81: IKNWIBE26005895 | F81: 03ID156 | G81: CM-MYRIAN MONTHLY CHECKING | H81: Corrective Maintenance (CM) | I81: 0 days, 0 hrs, 10 mins | J81: 27-Mar-2026 10:00:00 | K81: 27-Mar-2026 10:10:00 | L81: 27-Mar-2026 14:00:00 | M81: =IF(D81>44999.99,100,ROUNDUP((D81/4999.99)*10,-1)) -> 100 | N81: N | O81: ='[15]B1& B2 UNSCHEDULED'!$O$24 -> 0 | Q81: N | R81: =IF(L81="",AKHIR-J81,L81-J81+1) -> 1.1666667 | S81: =WORKDAY(J81,6,AKHIR) -> 46119 | T81: 0 | U81: =IF(Q81="N",0,M81*T81) -> 0 | V81: MYRIAN MONTHLY CHECKING COMPLETED BY VENDOR. FUNCTIONING OKAY.
A82: 59 | B82: IKN400365 | C82: =VLOOKUP(B82,[14]AssetDetails_UEM!$A$3:$AH$1849,6,FALSE) -> Infusion Pumps, Syringe | D82: =VLOOKUP(B82,[14]AssetDetails_UEM!$A$3:$AK$1849,22,FALSE) -> 10225 | E82: IKNWIBE26005926 | F82: 07WE113 | G82: PLUMGER SYRINGE TIDAK BOLEH TUTUP - 7A | H82: Normal | I82: 0 days, 0 hrs, 3 mins | J82: 29-Mar-2026 16:17:00 | K82: 29-Mar-2026 16:20:00 | L82: 29-Mar-2026 18:30:00 | M82: =IF(D82>44999.99,100,ROUNDUP((D82/4999.99)*10,-1)) -> 30 | N82: N | O82: ='[15]B1& B2 UNSCHEDULED'!$O$24 -> 0 | Q82: N | R82: =IF(L82="",AKHIR-J82,L82-J82+1) -> 1.0923611 | S82: =WORKDAY(J82,6,AKHIR) -> 46119 | T82: 0 | U82: =IF(Q82="N",0,M82*T82) -> 0 | V82: OPEN PLUNGER BOARD,RESEAT CABLE. POP UP ALARM BATTERY EMPTY BUT THE BATTERY INDICATOR ALREADY FULL. V2, TRIED SWAP NEW BATTERY,PLUNGER CAN CLOSE AND WORKING IN GOOD CONDITION.TESTED OKAY
A83: 60 | B83: IKN400064 | C83: =VLOOKUP(B83,[14]AssetDetails_UEM!$A$3:$AH$1849,6,FALSE) -> Infusion Pumps, Patient-Controlled Analgesic | D83: =VLOOKUP(B83,[14]AssetDetails_UEM!$A$3:$AK$1849,22,FALSE) -> 16840 | E83: IKNWIBE26005990 | F83: 05IC108 | G83: PCA BUTTON TIDAK BERFUNGSI - ICU ARAS 5 | H83: Normal | I83: 0 days, 0 hrs, 20 mins | J83: 30-Mar-2026 12:55:00 | K83: 30-Mar-2026 13:15:00 | L83: 30-Mar-2026 14:30:00 | M83: =IF(D83>44999.99,100,ROUNDUP((D83/4999.99)*10,-1)) -> 40 | N83: N | O83: ='[15]B1& B2 UNSCHEDULED'!$O$24 -> 0 | Q83: N | R83: =IF(L83="",AKHIR-J83,L83-J83+1) -> 1.0659722 | S83: =WORKDAY(J83,6,AKHIR) -> 46120 | T83: 0 | U83: =IF(Q83="N",0,M83*T83) -> 0 | V83: REPLACE NEW PCA BUTTON, UNIT TEST AND FUNCTIONING IN GOOD CONDITION
A84: 61 | B84: IKN400262 | C84: Scales, Patient, Floor | D84: 9380 | E84: IKNWIBE26006059 | F84: 08WG113 | G84: 2 UNIT SPO2 PORTABLE TIDAK DETECT (IKN400263 & IKN400262) - WAD ONKOLOGI ARAS 8 (8A) | H84: Normal | I84: 0 days, 1 hrs, 18 mins | J84: 31-Mar-2026 08:12:00 | K84: 31-Mar-2026 09:30:00 | L84: 31-Mar-2026 10:30:00 | M84: =IF(D84>44999.99,100,ROUNDUP((D84/4999.99)*10,-1)) -> 20 | N84: N | O84: ='[15]B1& B2 UNSCHEDULED'!$O$24 -> 0 | Q84: N | R84: =IF(L84="",AKHIR-J84,L84-J84+1) -> 1.0958333 | S84: =WORKDAY(J84,6,AKHIR) -> 46120 | T84: 0 | U84: =IF(Q84="N",0,M84*T84) -> 0 | V84: M-REPLACE NEW BATTERY ,TEST UNIT FUNCTIONING WELL.UNIT PROPOSED ANDATED TECHNOLOGY
A85: 62 | B85: IKN400263 | C85: =VLOOKUP(B85,[14]AssetDetails_UEM!$A$3:$AH$1849,6,FALSE) -> Oximeters, Pulse | D85: =VLOOKUP(B85,[14]AssetDetails_UEM!$A$3:$AK$1849,22,FALSE) -> 5410 | E85: IKNWIBE26006061 | F85: 08WG113 | G85: 2 UNIT SPO2 PORTABLE TIDAK DETECT - WAD ONKOLOGI ARAS 8 (8A) | H85: Normal | I85: 0 days, 1 hrs, 8 mins | J85: 31-Mar-2026 08:22:00 | K85: 31-Mar-2026 09:30:00 | L85: 31-Mar-2026 10:00:00 | M85: =IF(D85>44999.99,100,ROUNDUP((D85/4999.99)*10,-1)) -> 20 | N85: N | O85: ='[15]B1& B2 UNSCHEDULED'!$O$24 -> 0 | Q85: N | R85: =IF(L85="",AKHIR-J85,L85-J85+1) -> 1.0680556 | S85: =WORKDAY(J85,6,AKHIR) -> 46120 | T85: 0 | U85: =IF(Q85="N",0,M85*T85) -> 0 | V85: M-REPLACE NEW BATTERY ,UNIT TEST FUNCTIONING WELL. UNIT PROPOSE TO BER DUE TO AUDATED TECHNOLOGY
A86: Current Month (Work Order Open)
A87: 1 | B87: IKN402184 | C87: =VLOOKUP(B87,[14]AssetDetails_UEM!$A$3:$AH$1849,6,FALSE) -> Physiologic Monitoring Systems, Acute Care | D87: =VLOOKUP(B87,[14]AssetDetails_UEM!$A$3:$AK$1849,22,FALSE) -> RM100,00.00 | E87: IKNWIBE26004149 | F87: 03NM161 | G87: USER REQ- CHECKING ECG | H87: Normal | I87: 0 days, 0 hrs, 10 mins | J87: 03-Mar-2026 15:00:00 | K87: 46084.632 | L87: 46112.958 | M87: =IF(D87>44999.99,100,ROUNDUP((D87/4999.99)*10,-1)) -> 100 | N87: N | O87: ='[15]B1& B2 UNSCHEDULED'!$O$24 -> 0 | Q87: Y | R87: =IF(L87="",AKHIR-J87,L87-J87+1) -> 29.333345 | S87: =WORKDAY(J87,6,AKHIR) -> 46092 | T87: 20 | U87: 0 | V87: ECG CABLE FAULTY. WAITING PARTS FROM VENDOR(WELCH ALLYN) QUO : 6/3/2026 Po done 11/3/26
A88: 2 | B88: IKN400787 | C88: =VLOOKUP(B88,[14]AssetDetails_UEM!$A$3:$AH$1849,6,FALSE) -> Radiographic Units, Mobile | D88: =VLOOKUP(B88,[14]AssetDetails_UEM!$A$3:$AK$1849,22,FALSE) -> 1149550 | E88: IKNWIBE26005007 | F88: 03ID106 | G88: CM - TUBE HEAD NOT FULLY LOCK | H88: Normal | I88: 0 days, 0 hrs, 10 mins | J88: 16-Mar-2026 14:00:00 | K88: 46097.59 | L88: 46112.958 | M88: =IF(D88>44999.99,100,ROUNDUP((D88/4999.99)*10,-1)) -> 100 | N88: N | O88: ='[15]B1& B2 UNSCHEDULED'!$O$24 -> 0 | Q88: Y | R88: =IF(L88="",AKHIR-J88,L88-J88+1) -> 16.375012 | S88: =WORKDAY(J88,6,AKHIR)+2 -> 46107 | T88: 5 | U88: =IF(Q88="N",0,M88*T88) -> 500 | V88: TUBE HEAD NOT FULLY LOCK WAITING PARTS FROM VENDOR (CARESTREAM) & UPDATE THE ETA. | W88: hutang service report best contact
A89: 3 | B89: IKN400937 | C89: =VLOOKUP(B89,[14]AssetDetails_UEM!$A$3:$AH$1849,6,FALSE) -> Sphygmomanometers, Electronic, Automatic | D89: =VLOOKUP(B89,[14]AssetDetails_UEM!$A$3:$AK$1849,22,FALSE) -> 336 | E89: IKNWIBE26005651 | F89: 03MC127 | G89: BP Set Screen Blinking - MBC Aras 3 | H89: Normal | I89: 0 days, 0 hrs, 04 mins | J89: 24-Mar-2026 16:04:00 | K89: 46105.674 | L89: 46112.958 | M89: =IF(D89>44999.99,100,ROUNDUP((D89/4999.99)*10,-1)) -> 10 | N89: N | O89: ='[15]B1& B2 UNSCHEDULED'!$O$24 -> 0 | Q89: N | R89: =IF(L89="",AKHIR-J89,L89-J89+1) -> 8.2889005 | S89: =WORKDAY(J89,5,AKHIR) -> 46113 | T89: 0 | U89: =IF(Q89="N",0,M89*T89) -> 0 | V89: LCD BOARD FAULTY WAITING PARTS FROM VENDOR (Welch Allyn) Quotation:30/3/2026 PO: 71520, 31/3/2026 ETA : End of April
A90: 4 | B90: IKN401007 | C90: =VLOOKUP(B90,[14]AssetDetails_UEM!$A$3:$AH$1849,6,FALSE) -> Washers, Flexible Endoscope | D90: =VLOOKUP(B90,[14]AssetDetails_UEM!$A$3:$AK$1849,22,FALSE) -> 126300 | E90: IKNWIBE26005707 | F90: 03MC111 | G90: MESIN REPROCESSING KELUAR ERROR E61 | H90: Normal | I90: 0 days, 0 hrs, 17 mins | J90: 25-Mar-2026 11:58:00 | K90: 46106.51 | L90: 46112.958 | M90: =IF(D90>44999.99,100,ROUNDUP((D90/4999.99)*10,-1)) -> 100 | N90: N | O90: ='[15]B1& B2 UNSCHEDULED'!$O$24 -> 0 | Q90: N | R90: =IF(L90="",AKHIR-J90,L90-J90+1) -> 7.4597338 | S90: =WORKDAY(J90,5,AKHIR) -> 46114 | T90: 0 | U90: =IF(Q90="N",0,M90*T90) -> 0 | V90: VENDOR DONE TROUBLESHOOT ON 26/3/2026 & 6/3/2026 (OLYMPUS) & WAITING THE QUOTATION. SUSPECT THE SENSOR FAULTY.
A91: 5 | B91: IKN400293 | C91: =VLOOKUP(B91,[14]AssetDetails_UEM!$A$3:$AH$1849,6,FALSE) -> Oximeters, Pulse | D91: =VLOOKUP(B91,[14]AssetDetails_UEM!$A$3:$AK$1849,22,FALSE) -> 5410 | E91: IKNWIBE26005774 | F91: 08WH121 | G91: MACHINE SPO2 BATTERY FAULT- 8B | H91: Normal | I91: 0 days, 0 hrs, 22 mins | J91: 26-Mar-2026 08:08:00 | K91: 26-Mar-2026 08:30:00 | L91: 01-Apr-2026 13:00:00 | M91: =IF(D91>44999.99,100,ROUNDUP((D91/4999.99)*10,-1)) -> 20 | N91: N | O91: ='[15]B1& B2 UNSCHEDULED'!$O$24 -> 0 | Q91: N | R91: 5 | S91: 46115 | T91: 0 | U91: =IF(Q91="N",0,M91*T91) -> 0 | V91: M-REPLACE NEW BATTERY .PROPOSE UNIT TO BER DUE TO AUDATED TECHNOLOGY. Closed on 1/4/2026
A92: 6 | B92: IKN400029 | C92: =VLOOKUP(B92,[14]AssetDetails_UEM!$A$3:$AH$1849,6,FALSE) -> Physiologic Monitoring Systems, Acute Care | D92: =VLOOKUP(B92,[14]AssetDetails_UEM!$A$3:$AK$1849,22,FALSE) -> 105850 | E92: IKNWIBE26005898 | F92: 05IC140 | G92: NO LAN CONNECTION | H92: Normal | I92: 0 days, 1 hrs, 00 mins | J92: 27-Mar-2026 08:00:00 | K92: 46108.375 | L92: 46114.667 | M92: =IF(D92>44999.99,100,ROUNDUP((D92/4999.99)*10,-1)) -> 100 | N92: N | O92: ='[15]B1& B2 UNSCHEDULED'!$O$24 -> 0 | Q92: N | R92: 5 | S92: 46116 | T92: 0 | U92: =IF(Q92="N",0,M92*T92) -> 0 | V92: NO CONNECTION, LAN CABLE . CREATE IP ADDRESS AND ADJUST THE CONNECTOR OF INTERNET BOX.
A93: 7 | B93: IKN400722 | C93: =VLOOKUP(B93,[14]AssetDetails_UEM!$A$3:$AH$1849,6,FALSE) -> Analyzers, Laboratory, Hematology, Platelet Aggregation | D93: =VLOOKUP(B93,[14]AssetDetails_UEM!$A$3:$AK$1849,22,FALSE) -> 42100 | E93: IKNWIBE26005982 | F93: 04LA141 | G93: PLATELET AGITATOR LOW BATTERY & HIGH TEMPERATURE - PATOLOGI ARAS 4 | H93: Normal | I93: 0 days, 1 hrs, 00 mins | J93: 30-Mar-2026 09:55:00 | K93: 30-Mar-2026 09:55:00 | L93: 46119.667 | M93: =IF(D93>44999.99,100,ROUNDUP((D93/4999.99)*10,-1)) -> 90 | N93: N | O93: ='[15]B1& B2 UNSCHEDULED'!$O$24 -> 0 | Q93: N | R93: 7 | S93: =WORKDAY(J93,5,AKHIR) -> 46119 | T93: 0 | U93: =IF(Q93="N",0,M93*T93) -> 0 | V93: TEMPERATURE HIGH FROM MACHINE, TOUP GAS AND CHECK NO LEAKING.
A94: Previous Month (Work Order Closed)
A95: 1 | B95: IKN400446 | C95: =VLOOKUP(B95,[14]AssetDetails_UEM!$A$3:$AH$1849,6,FALSE) -> Infusion Pumps, General-Purpose | D95: =VLOOKUP(B95,[14]AssetDetails_UEM!$A$3:$AK$1849,22,FALSE) -> 10825 | E95: IKNWIBE25020556 | F95: 06WC113 | G95: DOOR INFUSSION PUMP CANNOT CLOSE - WAD 6A | H95: Normal | I95: 0 days, 0 hrs, 38 mins | J95: 09-Nov-2025 20:02:00 | K95: 45970.861 | L95: 46099.438 | M95: =IF(D95>44999.99,100,ROUNDUP((D95/4999.99)*10,-1)) -> 30 | N95: N | O95: ='[15]B1& B2 UNSCHEDULED'!$O$24 -> 0 | Q95: Y | R95: =IF(L95="",AKHIR-J95,L95-J95+1) -> 129.60278 | S95: =WORKDAY(J95,6,AKHIR)+1 -> 45979 | T95: 28 | U95: 0 | V95: UPSTREAM / DOWN STREAM SENSOR FAULTY SENT TO Bbraun DN:19/11/25 PO12152725 4/12/25 UNIT SENT OUT TO BRAUN FOR REPAIR WORK. ALL DEFECTIVE PARTS WERE CHANGE BY B BRAUN. | W95: Po
A96: 2 | B96: IKN400653 | C96: =VLOOKUP(B96,[14]AssetDetails_UEM!$A$3:$AH$1849,6,FALSE) -> Sphygmomanometers, Electronic, Automatic | D96: =VLOOKUP(B96,[14]AssetDetails_UEM!$A$3:$AK$1849,22,FALSE) -> 4510 | E96: IKNWIBE26002388 | F96: 04DO131 | G96: CUFF BP SET TIDAK BERFUNGSI | H96: Normal | I96: 0 days, 0 hrs, 22 mins | J96: 05-Feb-2026 20:08:00 | K96: 46058.854 | L96: 02-Apr-2026 16:00:00 | M96: =IF(D96>44999.99,100,ROUNDUP((D96/4999.99)*10,-1)) -> 10 | N96: N | O96: ='[15]B1& B2 UNSCHEDULED'!$O$24 -> 0 | Q96: Y | R96: =IF(L96="",AKHIR-J96,L96-J96+1) -> 56.827778 | S96: =WORKDAY(J96,6,AKHIR) -> 46066 | T96: 15 | U96: 0 | V96: Quotation received : 18/02/26 PO Date : 19/2/26 Waiting Parts (housing) ETA : End of Mac 2026 M-REPLACE NEW KEYPAD BOARD HOUSING. TESTED OKAY AND FUNCTIONING IN GOOD CONDITION | W96: Po
A97: Previous Month (Work Order Open)
A98: 1 | B98: IKN400366 | C98: =VLOOKUP(B98,[14]AssetDetails_UEM!$A$3:$AH$1849,6,FALSE) -> Infusion Pumps, General-Purpose | D98: =VLOOKUP(B98,[14]AssetDetails_UEM!$A$3:$AK$1849,22,FALSE) -> 10825 | E98: IKNWIBE25020728 | F98: 07WE113 | G98: INFUSION PUMP CANNOT OPEN - WAD 7A | H98: NORMAL | I98: 0 days, 0 hrs, 30 mins | J98: 11-Nov-2025 20:30:00 | K98: 45972.875 | L98: 46112.958 | M98: =IF(D98>44999.99,100,ROUNDUP((D98/4999.99)*10,-1)) -> 30 | N98: N | O98: ='[15]B1& B2 UNSCHEDULED'!$O$24 -> 0 | Q98: Y | R98: =IF(L98="",AKHIR-J98,L98-J98+1) -> 141.10418 | S98: =WORKDAY(J98,6,AKHIR) -> 45980 | T98: 31 | U98: 0 | V98: Sent to Bbraun DN:19/11/25 PO : 12153225 ; 5/12/25 ETA : Middle April 2026
A99: 2 | B99: IKN402081 | C99: Infusion Pumps, General-Purpose | D99: 3500 | E99: IKNWIBE25023258 | F99: 04DO111 | G99: INFUSION PUMP NOT FUNCTION -DAYCARE | H99: NORMAL | I99: 0 days, 0 hrs, 12 mins | J99: 46009.721 | K99: 18-Dec-2025 17:30:00 | L99: 46112.958 | M99: =IF(D99>44999.99,100,ROUNDUP((D99/4999.99)*10,-1)) -> 10 | N99: N | O99: ='[15]B1& B2 UNSCHEDULED'!$O$24 -> 0 | Q99: Y | R99: =IF(L99="",AKHIR-J99,L99-J99+1) -> 104.23751 | S99: 46020 | T99: 31 | U99: 0 | V99: Quotation received : 9/02/26 PO Date :PO :011001026 ; 5/1/26 Waiting Parts from Insan Damai ETA : Middle April 2026
A100: 3 | B100: IKN400422 | C100: Infusion Pumps, General-Purpose | D100: 10825 | E100: IKNWIBE25023728 | F100: 06WD153 | G100: INFUSION PUMP SCREEN TAK KELUAR TULISAN - WAD 6B | H100: NORMAL | I100: 0 days, 0 hrs, 54 mins | J100: 27-Dec-2025 13:56:00 | K100: 27-Dec-2025 14:50:00 | L100: 46112.958 | M100: =IF(D100>44999.99,100,ROUNDUP((D100/4999.99)*10,-1)) -> 30 | N100: N | O100: ='[15]B1& B2 UNSCHEDULED'!$O$24 -> 0 | Q100: N | R100: =IF(L100="",AKHIR-J100,L100-J100+1) -> 95.377789 | S100: 46028 | T100: 31 | U100: =IF(Q100="N",0,M100*T100) -> 0 | V100: TA done on 20/2/26.Quotation send to IKN done. Request repair under RIW | W100: Close wo
A101: 4 | B101: IKN400171 | C101: =VLOOKUP(B101,[14]AssetDetails_UEM!$A$3:$AH$1849,6,FALSE) -> Ventilators, Intensive Care | D101: =VLOOKUP(B101,[14]AssetDetails_UEM!$A$3:$AK$1849,22,FALSE) -> 151560 | E101: IKNWIBE26002579 | F101: 05IC131 | G101: DEVICE FAILURE | H101: Normal | I101: 0 days, 0 hrs, 10 mins | J101: 09-Feb-2026 09:00:00 | K101: 46062.382 | L101: 46112.958 | M101: =IF(D101>44999.99,100,ROUNDUP((D101/4999.99)*10,-1)) -> 100 | N101: N | O101: ='[15]B1& B2 UNSCHEDULED'!$O$24 -> 0 | Q101: Y | R101: =IF(L101="",AKHIR-J101,L101-J101+1) -> 51.583345 | S101: =WORKDAY(J101,6,AKHIR) -> 46070 | T101: 0 | U101: =IF(Q101="N",0,M101*T101) -> 0 | V101: Quotation received : 9/02/26 PO Date : 17/2/26 Waiting Parts (from German) ETA : Middle April 2026 | W101: PO
A102: 5 | B102: IKN400168 | C102: =VLOOKUP(B102,[14]AssetDetails_UEM!$A$3:$AH$1849,6,FALSE) -> Ventilators, Intensive Care | D102: =VLOOKUP(B102,[14]AssetDetails_UEM!$A$3:$AK$1849,22,FALSE) -> 151560 | E102: IKNWIBE26003259 | F102: 05IC115 | G102: LCD BLANK - ICU ARAS 5 | H102: Normal | I102: 0 days, 0 hrs, 10 mins | J102: 20-Feb-2026 10:00:00 | K102: 46073.424 | L102: 46112.958 | M102: =IF(D102>44999.99,100,ROUNDUP((D102/4999.99)*10,-1)) -> 100 | N102: N | O102: ='[15]B1& B2 UNSCHEDULED'!$O$24 -> 0 | Q102: Y | R102: =IF(L102="",AKHIR-J102,L102-J102+1) -> 40.541678 | S102: =WORKDAY(J102,6,AKHIR) -> 46083 | T102: 0 | U102: =IF(Q102="N",0,M102*T102) -> 0 | V102: Quotation received : 25-26/02/26 PO Date : 26/2/26 Waiting Parts (Display board) ETA : Middle April 2026 | W102: PO
O103: - | P103: TOTAL DEDUCTION FOR IND. B.2: | U103: =SUM(U24:U102) -> 500
V104: =38-17 -> 21

Sheet B3-SCHEDULED
A3: MINISTRY OF HEALTH
A4: Deduction Mapping Report Biomedical Engineering Maintenance Services (BEMS)
A5: INDICATOR B.3 SCHEDULED MAINTENANCE
A7: HOSPITAL NAME : | C7: INSTITUT KANSER NEGARA | H7: MONTH/YEAR : | J7: 46082
B9: STATE : | C9: WILAYAH PERSEKUTUAN PUTRAJAYA | G9: BEMS MONTHLY FEE (RM) @ 97.5% : | J9: =BEMSdar!E11 -> 1329813.2
B11: COMPANY : | C11: AMBANG WIRA SDN BHD | G11: FMS MONTHLY FEE (RM) @ 2.5% : | J11: =BEMSdar!E13 -> 34097.773
A13: Notes:
A14: 1) Deduction Ringgit Equivalent is based on Appendix 11 of the Agreement, Section B3 Key Deduction Indicators for BEMS
A15: 2) Deduction Value for Indicator B.3 is Deduction Ringgit Equivalent (per event)
A16: 3) Rescheduled Date is the final rescheduled date if there are multiple rescheduling
A17: 4) Display only asset affected by deduction
A19: No | B19: Asset No | C19: Asset Description | D19: Asset Purchase Price (RM) | E19: Work Order No. | F19: User Location | G19: Scheduled Start Date | H19: Maintenance Date | I19: Rescheduled Date | J19: Validate Status (Y/N) | K19: Deduction Ringgit Equivalent (RM) | L19: Indicator B.3
L20: Deduction Value (RM) | M20: Remarks/ Exemption
A21: Current Month (Closed)
A22: 1 | B22: IKN400173 | C22: Ventilators, Transport | D22: =VLOOKUP(B22,[14]AssetDetails_UEM!$A$3:$X$1848,22,FALSE) -> 60150 | E22: IKNWOBE26003369 | F22: 05IC106 | G22: 46083 | H22: 02-Mar-2026 08:30:00 | I22: NA | J22: N | K22: =ROUNDUP((D22/4999.99)*10,-1) -> 130 | L22: =IF(J22="N",0,K22) -> 0 | M22: P- QE:16, MAINTENANCE DONE ACCORDING TO HEPPM CHECKLIST ATTACHED
A23: 2 | B23: IKN400210 | C23: Electrocardiographs, Multichannel, Interpretative | D23: =VLOOKUP(B23,[14]AssetDetails_UEM!$A$3:$X$1848,22,FALSE) -> 25260 | E23: IKNWOBE26003370 | F23: 09WJ130 | G23: 02-Mar-2026 00:00:00 | H23: 02-Mar-2026 10:30:00 | I23: NA | J23: N | K23: =ROUNDUP((D23/4999.99)*10,-1) -> 60 | L23: =IF(J23="N",0,K23) -> 0 | M23: M,QE:16-PPMDONE AS CHECKLIST ATTACHED
A24: 3 | B24: IKN400223 | C24: Electrocardiographs, Multichannel, Interpretative | D24: =VLOOKUP(B24,[14]AssetDetails_UEM!$A$3:$X$1848,22,FALSE) -> 25260 | E24: IKNWOBE26003371 | F24: 09WJ222 | G24: 02-Mar-2026 00:00:00 | H24: 02-Mar-2026 11:50:00 | I24: NA | J24: N | K24: =ROUNDUP((D24/4999.99)*10,-1) -> 60 | L24: =IF(J24="N",0,K24) -> 0 | M24: M,QE:16-PPM DONE AS PERCHECKLIST ATTACHED
A25: 4 | B25: IKN400732 | C25: pH Meters | D25: =VLOOKUP(B25,[14]AssetDetails_UEM!$A$3:$X$1848,22,FALSE) -> 8000 | E25: IKNWOBE26003372 | F25: 04LA127 | G25: 02-Mar-2026 00:00:00 | H25: 02-Mar-2026 15:00:00 | I25: NA | J25: N | K25: =ROUNDUP((D25/4999.99)*10,-1) -> 20 | L25: =IF(J25="N",0,K25) -> 0 | M25: M,QE:16-PPM DONE AS PER HEPPM CHECKLIST ATTACHED
A26: 5 | B26: IKN401017 | C26: Anesthesia Units | D26: =VLOOKUP(B26,[14]AssetDetails_UEM!$A$3:$X$1848,22,FALSE) -> 144345 | E26: IKNWOBE26003373 | F26: 05OT120 | G26: 02-Mar-2026 00:00:00 | H26: 02-Mar-2026 14:00:00 | I26: NA | J26: N | K26: =ROUNDUP((D26/4999.99)*10,-1) -> 290 | L26: =IF(J26="N",0,K26) -> 0 | M26: P - QE:16, MAINTENANCE DONE AD PER HEPPM CHECKLIST ATTACHED
A27: 6 | B27: IKN400349 | C27: Sphygmomanometers, Electronic, Automatic | D27: =VLOOKUP(B27,[14]AssetDetails_UEM!$A$3:$X$1848,22,FALSE) -> 4510 | E27: IKNWOBE26003374 | F27: 07WF143 | G27: 03-Mar-2026 00:00:00 | H27: 03-Mar-2026 14:00:00 | I27: NA | J27: N | K27: =ROUNDUP((D27/4999.99)*10,-1) -> 10 | L27: =IF(J27="N",0,K27) -> 0 | M27: L, QE:16-PPM HAS BEEN COMPLETE AS PER HEPPM CHECKLIST
A28: 7 | B28: IKN400350 | C28: Sphygmomanometers, Electronic, Automatic | D28: =VLOOKUP(B28,[14]AssetDetails_UEM!$A$3:$X$1848,22,FALSE) -> 4510 | E28: IKNWOBE26003375 | F28: 07WF143 | G28: 03-Mar-2026 00:00:00 | H28: 03-Mar-2026 13:00:00 | I28: NA | J28: N | K28: =ROUNDUP((D28/4999.99)*10,-1) -> 10 | L28: =IF(J28="N",0,K28) -> 0 | M28: L, QE:16-PPM HAS BEEN COMPLETE AS PER HEPPM CHECKLIST
A29: 8 | B29: IKN400813 | C29: Physiologic Monitoring Systems, Acute Care | D29: =VLOOKUP(B29,[14]AssetDetails_UEM!$A$3:$X$1848,22,FALSE) -> 44510 | E29: IKNWOBE26003376 | F29: 01RT238 | G29: 03-Mar-2026 00:00:00 | H29: 03-Mar-2026 08:00:00 | I29: NA | J29: N | K29: =ROUNDUP((D29/4999.99)*10,-1) -> 90 | L29: =IF(J29="N",0,K29) -> 0 | M29: MAINTENANCE DONE ACCORDING TO HEPPM CHECKLIST ATTACHED
A30: 9 | B30: IKN400814 | C30: Physiologic Monitoring Systems, Acute Care | D30: =VLOOKUP(B30,[14]AssetDetails_UEM!$A$3:$X$1848,22,FALSE) -> 44510 | E30: IKNWOBE26003377 | F30: 01RT238 | G30: 03-Mar-2026 00:00:00 | H30: 03-Mar-2026 09:00:00 | I30: NA | J30: N | K30: =ROUNDUP((D30/4999.99)*10,-1) -> 90 | L30: =IF(J30="N",0,K30) -> 0 | M30: P - QE:16, MAINTENANCE DONE ACCORDING TO HEPPM CHECKLIST ATTACHED
A31: 10 | B31: IKN400815 | C31: Physiologic Monitoring Systems, Acute Care | D31: =VLOOKUP(B31,[14]AssetDetails_UEM!$A$3:$X$1848,22,FALSE) -> 44510 | E31: IKNWOBE26003378 | F31: 01RT238 | G31: 03-Mar-2026 00:00:00 | H31: 03-Mar-2026 10:00:00 | I31: NA | J31: N | K31: =ROUNDUP((D31/4999.99)*10,-1) -> 90 | L31: =IF(J31="N",0,K31) -> 0 | M31: P-QE:16, MAINTENANCE DONE ACCORDING TO HEPPM CHECKLLIST ATTACHED
A32: 11 | B32: IKN400849 | C32: Physiologic Monitoring Systems, Acute Care | D32: =VLOOKUP(B32,[14]AssetDetails_UEM!$A$3:$X$1848,22,FALSE) -> 119690 | E32: IKNWOBE26003379 | F32: 01RT278 | G32: 03-Mar-2026 00:00:00 | H32: 03-Mar-2026 12:00:00 | I32: NA | J32: N | K32: =ROUNDUP((D32/4999.99)*10,-1) -> 240 | L32: =IF(J32="N",0,K32) -> 0 | M32: P - QE:16, MAINTENANCE DONE AS PER HEPPM CHECKLIST ATTACHED
A33: 12 | B33: IKN400968 | C33: Warming Units, Patient, Forced-Air | D33: =VLOOKUP(B33,[14]AssetDetails_UEM!$A$3:$X$1848,22,FALSE) -> 15515 | E33: IKNWOBE26003380 | F33: 01RT238 | G33: 03-Mar-2026 00:00:00 | H33: 03-Mar-2026 13:00:00 | I33: NA | J33: N | K33: =ROUNDUP((D33/4999.99)*10,-1) -> 40 | L33: =IF(J33="N",0,K33) -> 0 | M33: P - QE:16, MAINTENANCE DONE AS PER HEPPM CHECKLIST ATTACHED
A34: 13 | B34: IKN400977 | C34: Warming Units, Patient, Forced-Air | D34: =VLOOKUP(B34,[14]AssetDetails_UEM!$A$3:$X$1848,22,FALSE) -> 15515 | E34: IKNWOBE26003381 | F34: 01RT238 | G34: 03-Mar-2026 00:00:00 | H34: 03-Mar-2026 14:00:00 | I34: NA | J34: N | K34: =ROUNDUP((D34/4999.99)*10,-1) -> 40 | L34: =IF(J34="N",0,K34) -> 0 | M34: P - QE:16, MAINTENANCE DONE ACCORDING TO HEPPM CHECKLIST ATTACHED
... A37: 16 | B37: IKN400387 | C37: Sphygmomanometers, Electronic, Automatic | D37: =VLOOKUP(B37,[14]AssetDetails_UEM!$A$3:$X$1848,22,FALSE) -> 4510 | E37: IKNWOBE26003384 | F37: 07WE143 | G37: 04-Mar-2026 00:00:00 | H37: 04-Mar-2026 11:50:00 | I37: NA | J37: N | K37: =ROUNDUP((D37/4999.99)*10,-1) -> 10 | L37: =IF(J37="N",0,K37) -> 0 | M37: L, QE:16-PPM HAS BEEN COMPLETE AS PER HEPPM CHECKLIST
A38: 17 | B38: IKN400389 | C38: Sphygmomanometers, Electronic, Automatic | D38: =VLOOKUP(B38,[14]AssetDetails_UEM!$A$3:$X$1848,22,FALSE) -> 4510 | E38: IKNWOBE26003385 | F38: 07WE143 | G38: 46085 | H38: 09-Mar-2026 09:00:00 | I38: 46092 | J38: N | K38: =ROUNDUP((D38/4999.99)*10,-1) -> 10 | L38: =IF(J38="N",0,K38) -> 0 | M38: P - (ASSET IN USE) PPM HAS BEEN COMPLETED AS PER HEPPM CHECKLIST
A39: 18 | B39: IKN400636 | C39: Infusion Pumps, Syringe | D39: =VLOOKUP(B39,[14]AssetDetails_UEM!$A$3:$X$1848,22,FALSE) -> 10225 | E39: IKNWOBE26003386 | F39: 04DO121 | G39: 04-Mar-2026 00:00:00 | H39: 04-Mar-2026 11:00:00 | I39: NA | J39: N | K39: =ROUNDUP((D39/4999.99)*10,-1) -> 30 | L39: =IF(J39="N",0,K39) -> 0 | M39: M,QE:16- PPM DONE AS PER HEPPM CHECKLIST ATTACHED
A40: 19 | B40: IKN400637 | C40: Infusion Pumps, Syringe | D40: =VLOOKUP(B40,[14]AssetDetails_UEM!$A$3:$X$1848,22,FALSE) -> 10225 | E40: IKNWOBE26003387 | F40: 04DO121 | G40: 04-Mar-2026 00:00:00 | H40: 04-Mar-2026 15:00:00 | I40: NA | J40: N | K40: =ROUNDUP((D40/4999.99)*10,-1) -> 30 | L40: =IF(J40="N",0,K40) -> 0 | M40: M,QE:16-PPM DONE AS PER HEPPM CHECKLIST ATTACHED
A41: 20 | B41: IKN400638 | C41: Infusion Pumps, Syringe | D41: =VLOOKUP(B41,[14]AssetDetails_UEM!$A$3:$X$1848,22,FALSE) -> 10225 | E41: IKNWOBE26003388 | F41: 04DO121 | G41: 04-Mar-2026 00:00:00 | H41: 04-Mar-2026 12:00:00 | I41: NA | J41: N | K41: =ROUNDUP((D41/4999.99)*10,-1) -> 30 | L41: =IF(J41="N",0,K41) -> 0 | M41: M,QE:16-PPM DONE AS PER HEPPM CHECKLIST ATTACHED
A42: 21 | B42: IKN400639 | C42: Infusion Pumps, Syringe | D42: =VLOOKUP(B42,[14]AssetDetails_UEM!$A$3:$X$1848,22,FALSE) -> 10225 | E42: IKNWOBE26003389 | F42: 04DO121 | G42: 04-Mar-2026 00:00:00 | H42: 04-Mar-2026 10:00:00 | I42: NA | J42: N | K42: =ROUNDUP((D42/4999.99)*10,-1) -> 30 | L42: =IF(J42="N",0,K42) -> 0 | M42: M,QE:16-PPM DONE AS PER HEPPM CHECKLIST ATTACHED
A43: 22 | B43: IKN400641 | C43: Infusion Pumps, Syringe | D43: =VLOOKUP(B43,[14]AssetDetails_UEM!$A$3:$X$1848,22,FALSE) -> 10225 | E43: IKNWOBE26003390 | F43: 04DO121 | G43: 04-Mar-2026 00:00:00 | H43: 04-Mar-2026 14:00:00 | I43: NA | J43: N | K43: =ROUNDUP((D43/4999.99)*10,-1) -> 30 | L43: =IF(J43="N",0,K43) -> 0 | M43: M,QE:16-PPM DONE AS PER HEPPM CHECKLIST ATTACHED
A44: 23 | B44: IKN400816 | C44: Physiologic Monitoring Systems, Acute Care | D44: =VLOOKUP(B44,[14]AssetDetails_UEM!$A$3:$X$1848,22,FALSE) -> 44510 | E44: IKNWOBE26003391 | F44: 01RT238 | G44: 04-Mar-2026 00:00:00 | H44: 04-Mar-2026 11:00:00 | I44: NA | J44: N | K44: =ROUNDUP((D44/4999.99)*10,-1) -> 90 | L44: =IF(J44="N",0,K44) -> 0 | M44: P - QE:16, MAINTENANCE DONE AS PER HEPPM CHECKLIST ATTACHED
A45: 24 | B45: IKN400204 | C45: Aspirators | D45: =VLOOKUP(B45,[14]AssetDetails_UEM!$A$3:$X$1848,22,FALSE) -> 10705 | E45: IKNWOBE26003392 | F45: 09WJ126 | G45: 05-Mar-2026 00:00:00 | H45: 05-Mar-2026 15:15:00 | I45: NA | J45: N | K45: =ROUNDUP((D45/4999.99)*10,-1) -> 30 | L45: =IF(J45="N",0,K45) -> 0 | M45: M,QE:16-PPM DONE AS PERCHECKLIST
A46: 25 | B46: IKN400334 | C46: Infusion Pumps, General-Purpose | D46: =VLOOKUP(B46,[14]AssetDetails_UEM!$A$3:$X$1848,22,FALSE) -> 10825 | E46: IKNWOBE26003393 | F46: 07WF121 | G46: 46086 | H46: 10-Mar-2026 11:00:00 | I46: 46093 | J46: N | K46: =ROUNDUP((D46/4999.99)*10,-1) -> 30 | L46: =IF(J46="N",0,K46) -> 0 | M46: P - (ASSET IN USE) PPM HAS BEEN COMPLETED AS PER HEPPM CHECKLIST
A47: 26 | B47: IKN400364 | C47: Infusion Pumps, Syringe | D47: =VLOOKUP(B47,[14]AssetDetails_UEM!$A$3:$X$1848,22,FALSE) -> 10225 | E47: IKNWOBE26003394 | F47: 07WE113 | G47: 46086 | H47: 09-Mar-2026 14:00:00 | I47: 46093 | J47: N | K47: =ROUNDUP((D47/4999.99)*10,-1) -> 30 | L47: =IF(J47="N",0,K47) -> 0 | M47: P - (ASSET IN USE) PPM HAS BEEN COMPLETED AS PER HEPPM CHECKLIST
A48: 27 | B48: IKN400450 | C48: Mattress Systems, Alternating-Pressure | D48: =VLOOKUP(B48,[14]AssetDetails_UEM!$A$3:$X$1848,22,FALSE) -> 28630 | E48: IKNWOBE26003395 | F48: 06WC113 | G48: 05-Mar-2026 00:00:00 | H48: 05-Mar-2026 14:00:00 | I48: NA | J48: N | K48: =ROUNDUP((D48/4999.99)*10,-1) -> 60 | L48: =IF(J48="N",0,K48) -> 0 | M48: M,QE:16-PPM DONE AS PERCHECKLIST
A49: 28 | B49: IKN400451 | C49: Mattress Systems, Alternating-Pressure | D49: =VLOOKUP(B49,[14]AssetDetails_UEM!$A$3:$X$1848,22,FALSE) -> 28630 | E49: IKNWOBE26003396 | F49: 06WC113 | G49: 05-Mar-2026 00:00:00 | H49: 05-Mar-2026 12:00:00 | I49: NA | J49: N | K49: =ROUNDUP((D49/4999.99)*10,-1) -> 60 | L49: =IF(J49="N",0,K49) -> 0 | M49: M,QE:16-PPM DONE AS PERCHECKLIST
A50: 29 | B50: IKN400452 | C50: Mattress Systems, Alternating-Pressure | D50: =VLOOKUP(B50,[14]AssetDetails_UEM!$A$3:$X$1848,22,FALSE) -> 28630 | E50: IKNWOBE26003397 | F50: 06WC113 | G50: 05-Mar-2026 00:00:00 | H50: 05-Mar-2026 13:00:00 | I50: NA | J50: N | K50: =ROUNDUP((D50/4999.99)*10,-1) -> 60 | L50: =IF(J50="N",0,K50) -> 0 | M50: M,QE:16-PPM DONE AS PERCHECKLIST
A51: 30 | B51: IKN400453 | C51: Mattress Systems, Alternating-Pressure | D51: =VLOOKUP(B51,[14]AssetDetails_UEM!$A$3:$X$1848,22,FALSE) -> 28630 | E51: IKNWOBE26003398 | F51: 06WC113 | G51: 05-Mar-2026 00:00:00 | H51: 05-Mar-2026 11:00:00 | I51: NA | J51: N | K51: =ROUNDUP((D51/4999.99)*10,-1) -> 60 | L51: =IF(J51="N",0,K51) -> 0 | M51: M,QE:16-PPM DONE AS PERCHECKLIST
A52: 31 | B52: IKN400454 | C52: Mattress Systems, Alternating-Pressure | D52: =VLOOKUP(B52,[14]AssetDetails_UEM!$A$3:$X$1848,22,FALSE) -> 28630 | E52: IKNWOBE26003399 | F52: 06WC113 | G52: 05-Mar-2026 00:00:00 | H52: 05-Mar-2026 10:00:00 | I52: NA | J52: N | K52: =ROUNDUP((D52/4999.99)*10,-1) -> 60 | L52: =IF(J52="N",0,K52) -> 0 | M52: M,QE:16-PPM DONE AS PER CHECKLIST
A53: 32 | B53: IKN400455 | C53: Mattress Systems, Alternating-Pressure | D53: =VLOOKUP(B53,[14]AssetDetails_UEM!$A$3:$X$1848,22,FALSE) -> 28630 | E53: IKNWOBE26003400 | F53: 06WC113 | G53: 05-Mar-2026 00:00:00 | H53: 05-Mar-2026 09:00:00 | I53: NA | J53: N | K53: =ROUNDUP((D53/4999.99)*10,-1) -> 60 | L53: =IF(J53="N",0,K53) -> 0 | M53: M,QE:16-PPM DONE AS PER CHECKLIST
A54: 33 | B54: IKN400469 | C54: Lights, Surgical | D54: =VLOOKUP(B54,[14]AssetDetails_UEM!$A$3:$X$1848,22,FALSE) -> 5050 | E54: IKNWOBE26003401 | F54: 05WB113 | G54: 05-Mar-2026 00:00:00 | H54: 05-Mar-2026 13:00:00 | I54: NA | J54: N | K54: =ROUNDUP((D54/4999.99)*10,-1) -> 20 | L54: =IF(J54="N",0,K54) -> 0 | M54: P - PPM HAS BEEN COMPLETED AS PER HEPPM CHECKLIST
A55: 34 | B55: IKN400470 | C55: Lights, Surgical | D55: =VLOOKUP(B55,[14]AssetDetails_UEM!$A$3:$X$1848,22,FALSE) -> 5050 | E55: IKNWOBE26003402 | F55: 05WB113 | G55: 05-Mar-2026 00:00:00 | H55: 05-Mar-2026 14:00:00 | I55: NA | J55: N | K55: =ROUNDUP((D55/4999.99)*10,-1) -> 20 | L55: =IF(J55="N",0,K55) -> 0 | M55: P - PPM HAS BEEN COMPLETED AS PER HEPPM CHECKLIST
A56: 35 | B56: IKN400780 | C56: Warming Units, Patient, Forced-Air | D56: =VLOOKUP(B56,[14]AssetDetails_UEM!$A$3:$X$1848,22,FALSE) -> 15515 | E56: IKNWOBE26003403 | F56: 03ID167 | G56: 05-Mar-2026 00:00:00 | H56: 05-Mar-2026 08:00:00 | I56: NA | J56: N | K56: =ROUNDUP((D56/4999.99)*10,-1) -> 40 | L56: =IF(J56="N",0,K56) -> 0 | M56: M, QE:16- PPM COMPLETED AS PER CHECKLIST.UNIT TESTED OKAY
A57: 36 | B57: IKN400781 | C57: Warming Units, Patient, Forced-Air | D57: =VLOOKUP(B57,[14]AssetDetails_UEM!$A$3:$X$1848,22,FALSE) -> 15515 | E57: IKNWOBE26003404 | F57: 03ID167 | G57: 05-Mar-2026 00:00:00 | H57: 05-Mar-2026 09:00:00 | I57: NA | J57: N | K57: =ROUNDUP((D57/4999.99)*10,-1) -> 40 | L57: =IF(J57="N",0,K57) -> 0 | M57: M,QE:16-PPM COMPLETED AS PER CHECKLIST.UNIT TESTED OKAY
A58: 37 | B58: IKN401101 | C58: Lights, Surgical | D58: =VLOOKUP(B58,[14]AssetDetails_UEM!$A$3:$X$1848,22,FALSE) -> 10585 | E58: IKNWOBE26003406 | F58: 05WB107 | G58: 05-Mar-2026 00:00:00 | H58: 05-Mar-2026 12:00:00 | I58: NA | J58: N | K58: =ROUNDUP((D58/4999.99)*10,-1) -> 30 | L58: =IF(J58="N",0,K58) -> 0 | M58: P - PPM HAS BEEN COMPLETED AS PER HEPPM CHECKLIST
A59: 38 | B59: IKN400185 | C59: Warming Units, Patient, Forced-Air | D59: =VLOOKUP(B59,[14]AssetDetails_UEM!$A$3:$X$1848,22,FALSE) -> 15515 | E59: IKNWOBE26003407 | F59: 05IC131 | G59: 06-Mar-2026 00:00:00 | H59: 06-Mar-2026 08:00:00 | I59: NA | J59: N | K59: =ROUNDUP((D59/4999.99)*10,-1) -> 40 | L59: =IF(J59="N",0,K59) -> 0 | M59: P - QE:16, MAINTENANCE DONE AS PER HEPPM CHECKLIST ATTACHED
... A63: 42 | B63: IKN400919 | C63: Sphygmomanometers, Electronic, Automatic | D63: =VLOOKUP(B63,[14]AssetDetails_UEM!$A$3:$X$1848,22,FALSE) -> 4510 | E63: IKNWOBE26003411 | F63: 03MC108 | G63: 06-Mar-2026 00:00:00 | H63: 06-Mar-2026 11:00:00 | I63: NA | J63: N | K63: =ROUNDUP((D63/4999.99)*10,-1) -> 10 | L63: =IF(J63="N",0,K63) -> 0 | M63: L, QE:16- PPM HAS BEEN COMPLETE AS PER HEPPM CHECKLIST
A64: 43 | B64: IKN401000 | C64: Laser Imagers | D64: =VLOOKUP(B64,[14]AssetDetails_UEM!$A$3:$X$1848,22,FALSE) -> 80000 | E64: IKNWOBE26003412 | F64: 03NM166 | G64: 46090 | H64: 10-Mar-2026 10:00:00 | I64: 46097 | J64: N | K64: =ROUNDUP((D64/4999.99)*10,-1) -> 170 | L64: =IF(J64="N",0,K64) -> 0 | M64: M,QE:16-(VENDOR NOT AVAILABLE) PPM COMPLETED BY VENDOR.UNIT TESTED OKAY.
A65: 44 | B65: IKN400778 | C65: Physiologic Monitoring Systems, Acute Care | D65: =VLOOKUP(B65,[14]AssetDetails_UEM!$A$3:$X$1848,22,FALSE) -> 44510 | E65: IKNWOBE26003413 | F65: 03ID167 | G65: 09-Mar-2026 00:00:00 | H65: 09-Mar-2026 15:00:00 | I65: NA | J65: N | K65: =ROUNDUP((D65/4999.99)*10,-1) -> 90 | L65: =IF(J65="N",0,K65) -> 0 | M65: M,QE:16-PPM COMPLETED AS PER CHECKLIST.UNIT TESTED OKAY
A66: 45 | B66: IKN400789 | C66: Physiologic Monitoring Systems, Acute Care | D66: =VLOOKUP(B66,[14]AssetDetails_UEM!$A$3:$X$1848,22,FALSE) -> 20000 | E66: IKNWOBE26003414 | F66: 03ID156 | G66: 09-Mar-2026 00:00:00 | H66: 09-Mar-2026 14:00:00 | I66: NA | J66: N | K66: =ROUNDUP((D66/4999.99)*10,-1) -> 50 | L66: =IF(J66="N",0,K66) -> 0 | M66: M,QE:16-PPM COMPLETED AS PER CHECKLIST.UNIT TESTED OKAY
A67: 46 | B67: IKN400779 | C67: Physiologic Monitoring Systems, Acute Care | D67: =VLOOKUP(B67,[14]AssetDetails_UEM!$A$3:$X$1848,22,FALSE) -> 20000 | E67: IKNWOBE26003415 | F67: 03ID164 | G67: 09-Mar-2026 00:00:00 | H67: 09-Mar-2026 16:00:00 | I67: NA | J67: N | K67: =ROUNDUP((D67/4999.99)*10,-1) -> 50 | L67: =IF(J67="N",0,K67) -> 0 | M67: M,QE:16-PPM COMPLETED AS PER CHECKLIST.UNIT TESTED OKAY
A68: 47 | B68: IKN400766 | C68: Radiographic Units, Mobile | D68: =VLOOKUP(B68,[14]AssetDetails_UEM!$A$3:$X$1848,22,FALSE) -> 1149550 | E68: IKNWOBE26003416 | F68: 03ID106 | G68: 46091 | H68: 16-Mar-2026 11:00:00 | I68: 46098 | J68: N | K68: =ROUNDUP((D68/4999.99)*10,-1) -> 2300 | L68: =IF(J68="N",0,K68) -> 0 | M68: M,QE:16- (ASSET IN USE) QC COMPLETED BY VENDOR
A69: 48 | B69: IKN400787 | C69: Radiographic Units, Mobile | D69: =VLOOKUP(B69,[14]AssetDetails_UEM!$A$3:$X$1848,22,FALSE) -> 1149550 | E69: IKNWOBE26003417 | F69: 03ID106 | G69: 46091 | H69: 46097.375 | I69: 46098 | J69: N | K69: =ROUNDUP((D69/4999.99)*10,-1) -> 2300 | L69: =IF(J69="N",0,K69) -> 0 | M69: M,QE:16-(ASSET IN USE) QC COMPLETED BY VENDOR
A70: 49 | B70: IKN400182 | C70: Warming Units, Patient, Forced-Air | D70: =VLOOKUP(B70,[14]AssetDetails_UEM!$A$3:$X$1848,22,FALSE) -> 15515 | E70: IKNWOBE26003418 | F70: 05IC115 | G70: 10-Mar-2026 00:00:00 | H70: 10-Mar-2026 08:30:00 | I70: NA | J70: N | K70: =ROUNDUP((D70/4999.99)*10,-1) -> 40 | L70: =IF(J70="N",0,K70) -> 0 | M70: P - MAINTENANCE DONE AS PER HEPPM CHECKLIST ATTACHED
A71: 50 | B71: IKN400184 | C71: Warming Units, Patient, Forced-Air | D71: =VLOOKUP(B71,[14]AssetDetails_UEM!$A$3:$X$1848,22,FALSE) -> 15515 | E71: IKNWOBE26003419 | F71: 05IC129 | G71: 10-Mar-2026 00:00:00 | H71: 10-Mar-2026 09:30:00 | I71: NA | J71: N | K71: =ROUNDUP((D71/4999.99)*10,-1) -> 40 | L71: =IF(J71="N",0,K71) -> 0 | M71: P - MAINTENANCE DONE AS PER HEPPM CHECKLIST ATTACHED
A72: 51 | B72: IKN400187 | C72: Sphygmomanometers, Electronic, Automatic | D72: =VLOOKUP(B72,[14]AssetDetails_UEM!$A$3:$X$1848,22,FALSE) -> 4510 | E72: IKNWOBE26003420 | F72: 05IC140 | G72: 10-Mar-2026 00:00:00 | H72: 10-Mar-2026 10:30:00 | I72: NA | J72: N | K72: =ROUNDUP((D72/4999.99)*10,-1) -> 10 | L72: =IF(J72="N",0,K72) -> 0 | M72: P - MAINTENANCE DONE AS PER HEPPM CHECKLIST ATTACHED
A73: 52 | B73: IKN400327 | C73: Infusion Pumps, Syringe | D73: =VLOOKUP(B73,[14]AssetDetails_UEM!$A$3:$X$1848,22,FALSE) -> 10225 | E73: IKNWOBE26003421 | F73: 07WF121 | G73: 10-Mar-2026 00:00:00 | H73: 10-Mar-2026 12:00:00 | I73: NA | J73: N | K73: =ROUNDUP((D73/4999.99)*10,-1) -> 30 | L73: =IF(J73="N",0,K73) -> 0 | M73: P - PPM HAS BEEN COMPLETED AS PER HEPPM CHECKLIST
A74: 53 | B74: IKN400644 | C74: Infusion Pumps, General-Purpose | D74: =VLOOKUP(B74,[14]AssetDetails_UEM!$A$3:$X$1848,22,FALSE) -> 10825 | E74: IKNWOBE26003422 | F74: 04DO121 | G74: 10-Mar-2026 00:00:00 | H74: 10-Mar-2026 10:00:00 | I74: NA | J74: N | K74: =ROUNDUP((D74/4999.99)*10,-1) -> 30 | L74: =IF(J74="N",0,K74) -> 0 | M74: M,QE:16-PPM DONE AS PER HEPPM CHECKLIST ATTACHED
A75: 54 | B75: IKN400650 | C75: Infusion Pumps, General-Purpose | D75: =VLOOKUP(B75,[14]AssetDetails_UEM!$A$3:$X$1848,22,FALSE) -> 10825 | E75: IKNWOBE26003423 | F75: 04DO124 | G75: 10-Mar-2026 00:00:00 | H75: 10-Mar-2026 09:00:00 | I75: NA | J75: N | K75: =ROUNDUP((D75/4999.99)*10,-1) -> 30 | L75: =IF(J75="N",0,K75) -> 0 | M75: M,QE:16-PPM DONE AS PER HEPPM CHECKLIST ATTACHED
A76: 55 | B76: IKN401041 | C76: Warming Units, Patient, Radiant, Adult | D76: =VLOOKUP(B76,[14]AssetDetails_UEM!$A$3:$X$1848,22,FALSE) -> 12630 | E76: IKNWOBE26003424 | F76: 05OT159 | G76: 10-Mar-2026 00:00:00 | H76: 10-Mar-2026 13:30:00 | I76: NA | J76: N | K76: =ROUNDUP((D76/4999.99)*10,-1) -> 30 | L76: =IF(J76="N",0,K76) -> 0 | M76: P - MAINTENANCE DONE AS PER HEPPM CHECKLIST ATTACHED
A77: 56 | B77: IKN401042 | C77: Warming Units, Patient, Radiant, Adult | D77: =VLOOKUP(B77,[14]AssetDetails_UEM!$A$3:$X$1848,22,FALSE) -> 12630 | E77: IKNWOBE26003425 | F77: 05OT159 | G77: 10-Mar-2026 00:00:00 | H77: 10-Mar-2026 12:30:00 | I77: NA | J77: N | K77: =ROUNDUP((D77/4999.99)*10,-1) -> 30 | L77: =IF(J77="N",0,K77) -> 0 | M77: P - MAINTENANCE DONE AS PER HEPPM CHECKLIST ATTACHED
A78: 57 | B78: IKN401047 | C78: Warming Units, Patient, Radiant, Adult | D78: =VLOOKUP(B78,[14]AssetDetails_UEM!$A$3:$X$1848,22,FALSE) -> 12630 | E78: IKNWOBE26003426 | F78: 05OT159 | G78: 10-Mar-2026 00:00:00 | H78: 10-Mar-2026 12:30:00 | I78: NA | J78: N | K78: =ROUNDUP((D78/4999.99)*10,-1) -> 30 | L78: =IF(J78="N",0,K78) -> 0 | M78: P - MAINTENANCE DONE AS PER HEPPM CHECKLIST ATTACHED
A79: 58 | B79: IKN401048 | C79: Warming Units, Patient, Radiant, Adult | D79: =VLOOKUP(B79,[14]AssetDetails_UEM!$A$3:$X$1848,22,FALSE) -> 12630 | E79: IKNWOBE26003427 | F79: 05OT159 | G79: 10-Mar-2026 00:00:00 | H79: 10-Mar-2026 11:30:00 | I79: NA | J79: N | K79: =ROUNDUP((D79/4999.99)*10,-1) -> 30 | L79: =IF(J79="N",0,K79) -> 0 | M79: P - MAINTENANCE DONE AS PER HEPPM CHECKLIST ATTACHED
A80: 59 | B80: IKN401250 | C80: pH Meters | D80: =VLOOKUP(B80,[14]AssetDetails_UEM!$A$3:$X$1848,22,FALSE) -> 8000 | E80: IKNWOBE26003428 | F80: 03NM138 | G80: 10-Mar-2026 00:00:00 | H80: 10-Mar-2026 15:00:00 | I80: NA | J80: N | K80: =ROUNDUP((D80/4999.99)*10,-1) -> 20 | L80: =IF(J80="N",0,K80) -> 0 | M80: M,QE:16-PPM COMPLETED AS PER CHECKLIST.UNIT TESTED OKAY
A81: 60 | B81: IKN401251 | C81: pH Meters | D81: =VLOOKUP(B81,[14]AssetDetails_UEM!$A$3:$X$1848,22,FALSE) -> 8000 | E81: IKNWOBE26003429 | F81: 03NM138 | G81: 10-Mar-2026 00:00:00 | H81: 10-Mar-2026 15:50:00 | I81: NA | J81: N | K81: =ROUNDUP((D81/4999.99)*10,-1) -> 20 | L81: =IF(J81="N",0,K81) -> 0 | M81: M,QE:16-PPM COMPLETED AS PER CHECKLIST.UNIT TESTED OKAY
... A135: 114 | B135: IKN402111 | C135: Infusion Pumps, General-Purpose | D135: =VLOOKUP(B135,[14]AssetDetails_UEM!$A$3:$X$1848,22,FALSE) -> 3500 | E135: IKNWOBE26003496 | F135: 05WB113 | G135: 18-Mar-2026 00:00:00 | H135: 18-Mar-2026 09:00:00 | I135: NA | J135: N | K135: =ROUNDUP((D135/4999.99)*10,-1) -> 10 | L135: =IF(J135="N",0,K135) -> 0 | M135: M,QE:16-PPM HAS BEEN COMPLETED AS PER HEPPM CHECKLIST
A136: 115 | B136: IKN402112 | C136: Infusion Pumps, General-Purpose | D136: =VLOOKUP(B136,[14]AssetDetails_UEM!$A$3:$X$1848,22,FALSE) -> 3500 | E136: IKNWOBE26003497 | F136: 05WB113 | G136: 46099 | H136: 26-Mar-2026 19:00:00 | I136: 46107 | J136: N | K136: =ROUNDUP((D136/4999.99)*10,-1) -> 10 | L136: =IF(J136="N",0,K136) -> 0 | M136: M,QE:(ASSET IN USE) 16-PPM HAS BEEN COMPLETED AS PER HEPPM CHECKLIST
A137: 116 | B137: IKN402212 | C137: Infusion/ Monitoring Line Organizer System | D137: =VLOOKUP(B137,[14]AssetDetails_UEM!$A$3:$X$1848,22,FALSE) -> #N/A | E137: IKNWOBE26003498 | F137: 03ID111 | G137: 18-Mar-2026 00:00:00 | H137: 26-Feb-2026 10:00:00 | I137: 46107 | J137: N | K137: =ROUNDUP((D137/4999.99)*10,-1) -> #N/A | L137: =IF(J137="N",0,K137) -> 0 | M137: P - QE:16 , (VENDOR AVAILABLE) MAINTENANCE DONE AS PER CHECKLIST ATTACHED AND UNIT TESTED OKAY.
A138: 117 | B138: IKN402220 | C138: Infusion Pumps, General-Purpose | D138: =VLOOKUP(B138,[14]AssetDetails_UEM!$A$3:$X$1848,22,FALSE) -> #N/A | E138: IKNWOBE26003499 | F138: 03ID111 | G138: 18-Mar-2026 00:00:00 | H138: 26-Feb-2026 10:00:00 | I138: 46107 | J138: N | K138: =ROUNDUP((D138/4999.99)*10,-1) -> #N/A | L138: =IF(J138="N",0,K138) -> 0 | M138: P - QE:16 , (VENDOR AVAILABLE) MAINTENANCE DONE AS PER CHECKLIST ATTACHED AND UNIT TESTED OKAY.
A139: 118 | B139: IKN402221 | C139: Infusion Pumps, Syringe | D139: =VLOOKUP(B139,[14]AssetDetails_UEM!$A$3:$X$1848,22,FALSE) -> #N/A | E139: IKNWOBE26003500 | F139: 03ID111 | G139: 18-Mar-2026 00:00:00 | H139: 26-Feb-2026 10:00:00 | I139: 46107 | J139: N | K139: =ROUNDUP((D139/4999.99)*10,-1) -> #N/A | L139: =IF(J139="N",0,K139) -> 0 | M139: P - QE:16 , (VENDOR AVAILABLE) PPM COMPLETED BY VENDOR AND UNIT TESTED OKAY.
A140: 119 | B140: IKN402222 | C140: Infusion Pumps, Syringe | D140: =VLOOKUP(B140,[14]AssetDetails_UEM!$A$3:$X$1848,22,FALSE) -> #N/A | E140: IKNWOBE26003501 | F140: 03ID111 | G140: 18-Mar-2026 00:00:00 | H140: 26-Feb-2026 10:00:00 | I140: 46107 | J140: N | K140: =ROUNDUP((D140/4999.99)*10,-1) -> #N/A | L140: =IF(J140="N",0,K140) -> 0 | M140: P - QE:16 , (VENDOR AVAILABLE) PPM COMPLETED BY VENDOR. UNIT FUNCTIONING OKAY.
A141: 120 | B141: IKN402224 | C141: Infusion Pumps, Syringe | D141: =VLOOKUP(B141,[14]AssetDetails_UEM!$A$3:$X$1848,22,FALSE) -> #N/A | E141: IKNWOBE26003502 | F141: 03ID111 | G141: 18-Mar-2026 00:00:00 | H141: 26-Feb-2026 10:00:00 | I141: 46107 | J141: N | K141: =ROUNDUP((D141/4999.99)*10,-1) -> #N/A | L141: =IF(J141="N",0,K141) -> 0 | M141: P - QE:16 , (VENDOR AVAILABLE) PPM COMPLETED BY VENDOR. UNIT FUNCTIONING OKAY.
A142: 121 | B142: IKN400326 | C142: Infusion Pumps, Syringe | D142: =VLOOKUP(B142,[14]AssetDetails_UEM!$A$3:$X$1848,22,FALSE) -> 10225 | E142: IKNWOBE26003503 | F142: 07WF121 | G142: 19-Mar-2026 00:00:00 | H142: 19-Mar-2026 08:30:00 | I142: NA | J142: N | K142: =ROUNDUP((D142/4999.99)*10,-1) -> 30 | L142: =IF(J142="N",0,K142) -> 0 | M142: P - PPM HAS BEEN COMPLETED AS PER HEPPM CHECKLIST
A143: 122 | B143: IKN400656 | C143: Infusion Pumps, Syringe | D143: =VLOOKUP(B143,[14]AssetDetails_UEM!$A$3:$X$1848,22,FALSE) -> 10225 | E143: IKNWOBE26003505 | F143: 04DO138 | G143: 19-Mar-2026 00:00:00 | H143: 19-Mar-2026 14:00:00 | I143: NA | J143: N | K143: =ROUNDUP((D143/4999.99)*10,-1) -> 30 | L143: =IF(J143="N",0,K143) -> 0 | M143: M,QE:16-PPM DONE AS PER HEPPM CHECKLIST ATTACHED
A144: 123 | B144: IKN401045 | C144: Physiologic Monitoring Systems, Acute Care | D144: =VLOOKUP(B144,[14]AssetDetails_UEM!$A$3:$X$1848,22,FALSE) -> 87400 | E144: IKNWOBE26003506 | F144: 05OT159 | G144: 19-Mar-2026 00:00:00 | H144: 19-Mar-2026 09:00:00 | I144: NA | J144: N | K144: =ROUNDUP((D144/4999.99)*10,-1) -> 180 | L144: =IF(J144="N",0,K144) -> 0 | M144: M,QE:16-MAINTENANCE DONE AS PER HEPPM CHECKLIST ATTACHED
A145: 124 | B145: IKN401050 | C145: Physiologic Monitoring Systems, Acute Care | D145: =VLOOKUP(B145,[14]AssetDetails_UEM!$A$3:$X$1848,22,FALSE) -> 87400 | E145: IKNWOBE26003507 | F145: 05OT159 | G145: 19-Mar-2026 00:00:00 | H145: 19-Mar-2026 08:00:00 | I145: NA | J145: N | K145: =ROUNDUP((D145/4999.99)*10,-1) -> 180 | L145: =IF(J145="N",0,K145) -> 0 | M145: M,QE:16-MAINTENANCE DONE AS PER HEPPM CHECKLIST ATTACHED
A146: 125 | B146: IKN401059 | C146: Physiologic Monitoring Systems, Acute Care | D146: =VLOOKUP(B146,[14]AssetDetails_UEM!$A$3:$X$1848,22,FALSE) -> 44510 | E146: IKNWOBE26003508 | F146: 05OT128 | G146: 19-Mar-2026 00:00:00 | H146: 19-Mar-2026 11:00:00 | I146: NA | J146: N | K146: =ROUNDUP((D146/4999.99)*10,-1) -> 90 | L146: =IF(J146="N",0,K146) -> 0 | M146: M,QE:16-MAINTENANCE DONE AS PER HEPPM CHECKLIST ATTACHED
A147: 126 | B147: IKN401060 | C147: Physiologic Monitoring Systems, Acute Care | D147: =VLOOKUP(B147,[14]AssetDetails_UEM!$A$3:$X$1848,22,FALSE) -> 44510 | E147: IKNWOBE26003509 | F147: 05OT128 | G147: 19-Mar-2026 00:00:00 | H147: 19-Mar-2026 10:00:00 | I147: NA | J147: N | K147: =ROUNDUP((D147/4999.99)*10,-1) -> 90 | L147: =IF(J147="N",0,K147) -> 0 | M147: M,QE:16-MAINTENANCE DONE ACCORDING TO HEPPM CHECKLIST ATTACHED
A148: 127 | B148: IKN402091 | C148: Gastroscopes, Flexible, Video | D148: =VLOOKUP(B148,[14]AssetDetails_UEM!$A$3:$X$1848,22,FALSE) -> 66000 | E148: IKNWOBE26003510 | F148: 03MC108 | G148: 19-Mar-2026 00:00:00 | H148: 19-Mar-2026 15:00:00 | I148: NA | J148: N | K148: =ROUNDUP((D148/4999.99)*10,-1) -> 140 | L148: =IF(J148="N",0,K148) -> 0 | M148: M,QE:16-PPM HAS BEEN COMPLETED AS PER HEPPM CHECKLIST
A149: 128 | B149: IKN402092 | C149: Infusion Pumps, General-Purpose | D149: =VLOOKUP(B149,[14]AssetDetails_UEM!$A$3:$X$1848,22,FALSE) -> 3500 | E149: IKNWOBE26003511 | F149: 04DO119 | G149: 19-Mar-2026 00:00:00 | H149: 19-Mar-2026 11:00:00 | I149: NA | J149: N | K149: =ROUNDUP((D149/4999.99)*10,-1) -> 10 | L149: =IF(J149="N",0,K149) -> 0 | M149: M,QE:16-PPM DONE AS PER HEPPM CHECKLIST ATTACHED
A150: 129 | B150: IKN402093 | C150: Infusion Pumps, General-Purpose | D150: =VLOOKUP(B150,[14]AssetDetails_UEM!$A$3:$X$1848,22,FALSE) -> 3500 | E150: IKNWOBE26003512 | F150: 04DO119 | G150: 19-Mar-2026 00:00:00 | H150: 19-Mar-2026 15:00:00 | I150: NA | J150: N | K150: =ROUNDUP((D150/4999.99)*10,-1) -> 10 | L150: =IF(J150="N",0,K150) -> 0 | M150: M,QE:16-PPM DONE AS PER HEPPM CHECKLIST ATTACHED
A151: 130 | B151: IKN402107 | C151: Infusion Pumps, General-Purpose | D151: =VLOOKUP(B151,[14]AssetDetails_UEM!$A$3:$X$1848,22,FALSE) -> 3500 | E151: IKNWOBE26003513 | F151: 07WF121 | G151: 19-Mar-2026 00:00:00 | H151: 19-Mar-2026 10:00:00 | I151: NA | J151: N | K151: =ROUNDUP((D151/4999.99)*10,-1) -> 10 | L151: =IF(J151="N",0,K151) -> 0 | M151: P - PPM HAS BEEN COMPLETED AS PER HEPPM CHECKLIST
A152: 131 | B152: IKN402108 | C152: Infusion Pumps, General-Purpose | D152: =VLOOKUP(B152,[14]AssetDetails_UEM!$A$3:$X$1848,22,FALSE) -> 3500 | E152: IKNWOBE26003514 | F152: 07WF121 | G152: 19-Mar-2026 00:00:00 | H152: 19-Mar-2026 11:00:00 | I152: NA | J152: N | K152: =ROUNDUP((D152/4999.99)*10,-1) -> 10 | L152: =IF(J152="N",0,K152) -> 0 | M152: P - PPM HAS BEEN COMPLETED AS PER HEPPM CHECKLIST
A153: 132 | B153: IKN402109 | C153: Infusion Pumps, General-Purpose | D153: =VLOOKUP(B153,[14]AssetDetails_UEM!$A$3:$X$1848,22,FALSE) -> 3500 | E153: IKNWOBE26003515 | F153: 08WH121 | G153: 19-Mar-2026 00:00:00 | H153: 19-Mar-2026 09:00:00 | I153: NA | J153: N | K153: =ROUNDUP((D153/4999.99)*10,-1) -> 10 | L153: =IF(J153="N",0,K153) -> 0 | M153: M,QE:16-PPM DONE AS PERCHECKLIST
... A162: 141 | B162: IKN400440 | C162: Sphygmomanometers, Electronic, Automatic | D162: =VLOOKUP(B162,[14]AssetDetails_UEM!$A$3:$X$1848,22,FALSE) -> 4510 | E162: IKNWOBE26003527 | F162: 06WC143 | G162: 23-Mar-2026 00:00:00 | H162: 23-Mar-2026 12:00:00 | I162: NA | J162: N | K162: =ROUNDUP((D162/4999.99)*10,-1) -> 10 | L162: =IF(J162="N",0,K162) -> 0 | M162: M,QE:16-PPM DONE AS PERCHECKLIST
A163: 142 | B163: IKN400772 | C163: Warming Units, Patient, Radiant, Adult | D163: =VLOOKUP(B163,[14]AssetDetails_UEM!$A$3:$X$1848,22,FALSE) -> 12630 | E163: IKNWOBE26003528 | F163: 03ID109 | G163: 46105 | H163: 30-Mar-2026 14:00:00 | I163: 46112 | J163: N | K163: =ROUNDUP((D163/4999.99)*10,-1) -> 30 | L163: =IF(J163="N",0,K163) -> 0 | M163: M,QE:16-(ASSET NOT FOUND)PPM COMPLETED AS PERCHECKLIST
A164: 143 | B164: IKN400029 | C164: Physiologic Monitoring Systems, Acute Care | D164: =VLOOKUP(B164,[14]AssetDetails_UEM!$A$3:$X$1848,22,FALSE) -> 105850 | E164: IKNWOBE26003529 | F164: 05IC140 | G164: 24-Mar-2026 00:00:00 | H164: 24-Mar-2026 08:30:00 | I164: NA | J164: N | K164: =ROUNDUP((D164/4999.99)*10,-1) -> 220 | L164: =IF(J164="N",0,K164) -> 0 | M164: M,QE:16-MAINTENANCE DONE AS PER HEPPM CHECKLIST ATTACHED.UNIT FUNCTIONING IN GOOD CONDITION
A165: 144 | B165: IKN400315 | C165: Aspirators | D165: =VLOOKUP(B165,[14]AssetDetails_UEM!$A$3:$X$1848,22,FALSE) -> 5052 | E165: IKNWOBE26003530 | F165: 07WF107 | G165: 24-Mar-2026 00:00:00 | H165: 24-Mar-2026 16:00:00 | I165: NA | J165: N | K165: =ROUNDUP((D165/4999.99)*10,-1) -> 20 | L165: =IF(J165="N",0,K165) -> 0 | M165: M,QE:16-PPM HAS BEEN COMPLETED AS PER HEPPM CHECKLIST
A166: 145 | B166: IKN400344 | C166: Aspirators | D166: =VLOOKUP(B166,[14]AssetDetails_UEM!$A$3:$X$1848,22,FALSE) -> 10705 | E166: IKNWOBE26003532 | F166: 07WF121 | G166: 24-Mar-2026 00:00:00 | H166: 24-Mar-2026 18:00:00 | I166: NA | J166: N | K166: =ROUNDUP((D166/4999.99)*10,-1) -> 30 | L166: =IF(J166="N",0,K166) -> 0 | M166: M,QE:16-PPM HAS BEEN COMPLETED AS PER HEPPM CHECKLIST
A167: 146 | B167: IKN400442 | C167: Infusion Pumps, Syringe | D167: =VLOOKUP(B167,[14]AssetDetails_UEM!$A$3:$X$1848,22,FALSE) -> 10225 | E167: IKNWOBE26003533 | F167: 06WC113 | G167: 24-Mar-2026 00:00:00 | H167: 24-Mar-2026 12:00:00 | I167: NA | J167: N | K167: =ROUNDUP((D167/4999.99)*10,-1) -> 30 | L167: =IF(J167="N",0,K167) -> 0 | M167: M,QE:16-PPM DONE AS PERCHECKLIST
A168: 147 | B168: IKN400640 | C168: Infusion Pumps, Syringe | D168: =VLOOKUP(B168,[14]AssetDetails_UEM!$A$3:$X$1848,22,FALSE) -> 10225 | E168: IKNWOBE26003534 | F168: 04DO121 | G168: 24-Mar-2026 00:00:00 | H168: 24-Mar-2026 11:00:00 | I168: NA | J168: N | K168: =ROUNDUP((D168/4999.99)*10,-1) -> 30 | L168: =IF(J168="N",0,K168) -> 0 | M168: M,QE:16-PPM DONE AS PER HEPPM CHECKLIST ATTACHED
A169: 148 | B169: IKN400936 | C169: Sphygmomanometers, Electronic, Automatic | D169: =VLOOKUP(B169,[14]AssetDetails_UEM!$A$3:$X$1848,22,FALSE) -> 336 | E169: IKNWOBE26003535 | F169: 03MC121 | G169: 24-Mar-2026 00:00:00 | H169: 24-Mar-2026 08:00:00 | I169: NA | J169: N | K169: =ROUNDUP((D169/4999.99)*10,-1) -> 10 | L169: =IF(J169="N",0,K169) -> 0 | M169: M,QE:16-PPM HAS BEEN COMPLETED AS PER HEPPM CHECKLIST
A170: 149 | B170: IKN400938 | C170: Sphygmomanometers, Electronic, Automatic | D170: =VLOOKUP(B170,[14]AssetDetails_UEM!$A$3:$X$1848,22,FALSE) -> 336 | E170: IKNWOBE26003537 | F170: 03MC128 | G170: 24-Mar-2026 00:00:00 | H170: 24-Mar-2026 09:00:00 | I170: NA | J170: N | K170: =ROUNDUP((D170/4999.99)*10,-1) -> 10 | L170: =IF(J170="N",0,K170) -> 0 | M170: M,QE:16-PPM HAS BEEN COMPLETED AS PER HEPPM CHECKLIST
A171: 150 | B171: IKN401098 | C171: Lights, Surgical | D171: =VLOOKUP(B171,[14]AssetDetails_UEM!$A$3:$X$1848,22,FALSE) -> 10585 | E171: IKNWOBE26003538 | F171: 05IC116 | G171: 24-Mar-2026 00:00:00 | H171: 24-Mar-2026 13:30:00 | I171: NA | J171: N | K171: =ROUNDUP((D171/4999.99)*10,-1) -> 30 | L171: =IF(J171="N",0,K171) -> 0 | M171: M,QE:16-MAINTENANCE DONE AS PER HEPPM CHECKLIST ATTACHED.UNIT FUNCTIONING IN GOOD CONDITION
A172: 151 | B172: IKN401099 | C172: Lights, Surgical | D172: =VLOOKUP(B172,[14]AssetDetails_UEM!$A$3:$X$1848,22,FALSE) -> 10585 | E172: IKNWOBE26003539 | F172: 05IC129 | G172: 24-Mar-2026 00:00:00 | H172: 24-Mar-2026 12:30:00 | I172: NA | J172: N | K172: =ROUNDUP((D172/4999.99)*10,-1) -> 30 | L172: =IF(J172="N",0,K172) -> 0 | M172: M,QE:16-MAINTENANCE DONE AS PER HEPPM CHECKLIST ATTACHED.UNIT FUNCTIONING IN GOOD CONDITION
A173: 152 | B173: IKN401111 | C173: Lights, Surgical | D173: =VLOOKUP(B173,[14]AssetDetails_UEM!$A$3:$X$1848,22,FALSE) -> 10585 | E173: IKNWOBE26003540 | F173: 05IC113 | G173: 24-Mar-2026 00:00:00 | H173: 24-Mar-2026 11:30:00 | I173: NA | J173: N | K173: =ROUNDUP((D173/4999.99)*10,-1) -> 30 | L173: =IF(J173="N",0,K173) -> 0 | M173: M,QE:16-MAINTENANCE DONE AS PER HEPPM CHECKLIST ATTACHED.UNIT FUNCTIONING IN GOOD CONDITION
...

Sheet B4-UPTIME
A1: MINISTRY OF HEALTH
A2: Deduction Mapping Report Biomedical Engineering Maintenance Services (BEMS)
A3: INDICATOR B.4 UPTIME GUARANTEE
B5: HOSPITAL NAME : | C5: INSTITUT KANSER NEGARA | N5: MONTH/YEAR : | U5: 46082
B7: STATE : | C7: WILAYAH PERSEKUTUAN PUTRAJAYA | N7: BEMS MONTHLY FEE (RM)@ 97.5% : | U7: =[13]BEMSdar!E11 -> 1437864.8
B9: COMPANY : | C9: AMBANG WIRA SDN BHD | N9: FMS MONTHLY FEE (RM) @ 2.5% : | U9: =[13]BEMSdar!E13 -> 36868.327
A11: Notes:
A12: 1) Deduction Ringgit Equivalent is based on Appendix 11 of the Agreement, Section B3 Key Deduction Indicators for BEMS
A13: 2) Deduction Value for 1st cut off is Deduction Ringgit Equivalent (per event)
A14: 3) Deduction Value for 2nd cut off is Deduction Ringgit Equivalent (per event) multiply by 2
A15: 4) Display only asset affected by deduction
A17: No. | B17: Asset No | C17: Type Code | D17: Type Description | E17: Asset Purchase cost (RM) | F17: Asset Age | G17: TRKPI % | H17: Uptime % | T17: Deduction Ringgit Equivalent (RM) | U17: Previous Deduction (Month) | W17: Deduction for the month (Y/N) | Y17: Deduction Value (RM) | AA17: Total Deduction (RM) | AB17: Remarks
H18: Jan | I18: Feb | J18: Mar | K18: Apr | L18: May | M18: Jun | N18: Jul | O18: Aug | P18: Sep | Q18: Oct | R18: Nov | S18: Dec | U18: 1st | V18: 2nd | W18: 1st | X18: 2nd | Y18: 1st | Z18: 2nd
A19: 1 | B19: IKN400440 | C19: 16-173 | D19: Sphygmomanometers, Electronic, Automatic | E19: 4510 | F19: 13 | G19: 88 | H19: 99.82733 | I19: 99.78 | J19: - | T19: =ROUNDUP((E19/4999.99)*10,-1) -> 10 | U19: N | V19: N | W19: N | X19: N | Y19: =IF(W19="Y",T19,0) -> 0 | Z19: =IF(X19="Y",T19*2,0) -> 0 | AA19: =Y19+Z19 -> 0
A20: 2 | B20: IKN400645 | C20: 13-215 | D20: Infusion Pumps, General-Purpose | E20: 10825 | F20: 13 | G20: 88 | H20: 99.961971 | I20: 99.93 | J20: - | T20: =ROUNDUP((E20/4999.99)*10,-1) -> 30 | U20: N | V20: N | W20: N | X20: N | Y20: =IF(W20="Y",T20,0) -> 0 | Z20: =IF(X20="Y",T20*2,0) -> 0 | AA20: =Y20+Z20 -> 0
A21: 3 | B21: IKN401714 | C21: 13-215 | D21: Infusion Pumps, General-Purpose | E21: 5800 | F21: 8 | G21: 95 | H21: 99.962034 | I21: 99.93 | J21: - | T21: =ROUNDUP((E21/4999.99)*10,-1) -> 20 | U21: Y | V21: Y | W21: N | X21: N | Y21: =IF(W21="Y",T21,0) -> 0 | Z21: =IF(X21="Y",T21*2,0) -> 0 | AA21: =Y21+Z21 -> 0
A22: 4 | B22: IKN400446 | C22: 13-215 | D22: Infusion Pumps, General-Purpose | E22: 10825 | F22: 13 | G22: 88 | H22: 99.65 | I22: 99.68 | J22: 98.553172 | T22: =ROUNDUP((E22/4999.99)*10,-1) -> 30 | U22: N | V22: N | W22: N | X22: N | Y22: =IF(W22="Y",T22,0) -> 0 | Z22: =IF(X22="Y",T22*2,0) -> 0 | AA22: =Y22+Z22 -> 0
A23: 5 | B23: IKN400366 | C23: 13-215 | D23: Infusion Pumps, General-Purpose | E23: 10825 | F23: 13 | G23: 88 | H23: 99.65 | I23: 99.68 | J23: 99.330998 | T23: =ROUNDUP((E23/4999.99)*10,-1) -> 30 | U23: N | V23: N | W23: N | X23: N | Y23: =IF(W23="Y",T23,0) -> 0 | Z23: =IF(X23="Y",T23*2,0) -> 0 | AA23: =Y23+Z23 -> 0
A24: 6 | B24: IKN402165 | C24: 13-215 | D24: Infusion Pumps, General-Purpose | E24: 10825 | F24: 13 | G24: 88 | H24: 99.65 | I24: 99.45 | J24: - | T24: =ROUNDUP((E24/4999.99)*10,-1) -> 30 | U24: N | V24: N | W24: N | X24: N | Y24: =IF(W24="Y",T24,0) -> 0 | Z24: =IF(X24="Y",T24*2,0) -> 0 | AA24: =Y24+Z24 -> 0
A25: 7 | B25: IKN400565 | C25: 12-649 | D25: Physiologic Monitoring Systems, Stress Exercise | E25: 138350 | F25: 13 | G25: 88 | H25: 99.65 | I25: 99.56 | J25: - | T25: =ROUNDUP((E25/4999.99)*10,-1) -> 280 | U25: N | V25: N | W25: N | X25: N | Y25: =IF(W25="Y",T25,0) -> 0 | Z25: =IF(X25="Y",T25*2,0) -> 0 | AA25: =Y25+Z25 -> 0
A26: 8 | B26: IKN400439 | C26: 16-173 | D26: Sphygmomanometers, Electronic, Automatic | E26: 4510 | F26: 13 | G26: 88 | H26: 99.65 | I26: 99.53 | J26: - | T26: =ROUNDUP((E26/4999.99)*10,-1) -> 10 | U26: N | V26: N | W26: N | X26: N | Y26: =IF(W26="Y",T26,0) -> 0 | Z26: =IF(X26="Y",T26*2,0) -> 0 | AA26: =Y26+Z26 -> 0
A27: 9 | B27: IKN401076 | C27: 12-306 | D27: Lavage Units, Surgical | E27: 5000 | F27: 13 | G27: 85 | H27: 99.65 | I27: 99.35 | J27: - | T27: =ROUNDUP((E27/4999.99)*10,-1) -> 20 | U27: N | V27: N | W27: N | X27: N | Y27: =IF(W27="Y",T27,0) -> 0 | Z27: =IF(X27="Y",T27*2,0) -> 0 | AA27: =Y27+Z27 -> 0
A28: 10 | B28: IKN402147 | C28: 15-605 | D28: Testers (Ion Chamber Set) | E28: 142000 | F28: 4 | G28: 96 | H28: 99.65 | I28: 99.39 | J28: - | T28: =ROUNDUP((E28/4999.99)*10,-1) -> 290 | U28: N | V28: N | W28: N | X28: N | Y28: =IF(W28="Y",T28,0) -> 0 | Z28: =IF(X28="Y",T28*2,0) -> 0 | AA28: =Y28+Z28 -> 0
A29: 11 | B29: IKN401071 | C29: 18-034 | D29: Video Image Processors, Endoscopic | E29: 80000 | F29: 13 | G29: 88 | H29: 99.65 | I29: 99.35 | J29: - | T29: =ROUNDUP((E29/4999.99)*10,-1) -> 170 | U29: Y | V29: Y | W29: N | X29: N | Y29: =IF(W29="Y",T29,0) -> 0 | Z29: =IF(X29="Y",T29*2,0) -> 0 | AA29: =Y29+Z29 -> 0
A30: 12 | B30: IKN402081 | C30: 13-215 | D30: Infusion Pumps, General-Purpose | E30: 3500 | F30: 5 | G30: 95 | H30: 99.65 | I30: 99.68 | J30: 99.330998 | T30: =ROUNDUP((E30/4999.99)*10,-1) -> 10 | U30: N | V30: N | W30: N | X30: N | Y30: =IF(W30="Y",T30,0) -> 0 | Z30: =IF(X30="Y",T30*2,0) -> 0 | AA30: =Y30+Z30 -> 0
A31: 13 | B31: IKN401353 | C31: 11-758 | D31: Radiographic/Fluoroscopic Units, Mobile | E31: 399000 | F31: 10 | G31: 88 | H31: 99.65 | I31: - | J31: - | T31: =ROUNDUP((E31/4999.99)*10,-1) -> 800 | U31: N | V31: N | W31: N | X31: N | Y31: =IF(W31="Y",T31,0) -> 0 | Z31: =IF(X31="Y",T31*2,0) -> 0 | AA31: =Y31+Z31 -> 0
A32: 14 | B32: IKN400422 | C32: 13-215 | D32: Infusion Pumps, General-Purpose | E32: 10825 | F32: 13 | G32: 88 | H32: 99.65 | I32: 99.68 | J32: 99.330998 | T32: =ROUNDUP((E32/4999.99)*10,-1) -> 30 | U32: Y | V32: N | W32: N | X32: N | Y32: =IF(W32="Y",T32,0) -> 0 | Z32: =IF(X32="Y",T32*2,0) -> 0 | AA32: =Y32+Z32 -> 0
A33: 15 | B33: IKN400482 | C33: 13-215 | D33: Infusion Pumps, General-Purpose | E33: 10825 | F33: 13 | G33: 88 | H33: 99.65 | I33: 99.61 | J33: - | T33: =ROUNDUP((E33/4999.99)*10,-1) -> 30 | U33: N | V33: N | W33: N | X33: N | Y33: =IF(W33="Y",T33,0) -> 0 | Z33: =IF(X33="Y",T33*2,0) -> 0 | AA33: =Y33+Z33 -> 0
A34: 16 | B34: IKN400782 | C34: 17-679 | D34: Laser Imagers | E34: 83100 | F34: 13 | G34: 85 | H34: 99.65 | I34: 99.51 | J34: - | T34: =ROUNDUP((E34/4999.99)*10,-1) -> 170 | U34: N | V34: N | W34: N | X34: N | Y34: =IF(W34="Y",T34,0) -> 0 | Z34: =IF(X34="Y",T34*2,0) -> 0 | AA34: =Y34+Z34 -> 0
A35: 17 | B35: IKN400653 | C35: 16-173 | D35: Sphygmomanometers, Electronic, Automatic | E35: 4510 | F35: 12 | G35: 88 | H35: - | I35: 99.8 | J35: 99.385529 | T35: =ROUNDUP((E35/4999.99)*10,-1) -> 10 | U35: N | V35: N | W35: N | X35: N | Y35: =IF(W35="Y",T35,0) -> 0 | Z35: =IF(X35="Y",T35*2,0) -> 0 | AA35: =Y35+Z35 -> 0
A36: 18 | B36: IKN400171 | C36: 17-429 | D36: Ventilators, Intensive Care | E36: 151560 | F36: 12 | G36: 88 | H36: - | I36: 99.78 | J36: 99.425417 | T36: =ROUNDUP((E36/4999.99)*10,-1) -> 310 | U36: N | V36: N | W36: N | X36: N | Y36: =IF(W36="Y",T36,0) -> 0 | Z36: =IF(X36="Y",T36*2,0) -> 0 | AA36: =Y36+Z36 -> 0
A37: 19 | B37: IKN400168 | C37: 17-429 | D37: Ventilators, Intensive Care | E37: 151560 | F37: 12 | G37: 88 | H37: - | I37: 99.9 | J37: 99.550176 | T37: =ROUNDUP((E37/4999.99)*10,-1) -> 310 | U37: Y | V37: Y | W37: N | X37: N | Y37: =IF(W37="Y",T37,0) -> 0 | Z37: =IF(X37="Y",T37*2,0) -> 0 | AA37: =Y37+Z37 -> 0
A38: 20 | B38: IKN402184 | C38: 12-647 | D38: Physiologic Monitoring Systems, Acute Care | E38: 100000 | F38: 2 | G38: 99 | H38: - | I38: - | J38: 99.677138 | T38: =ROUNDUP((E38/4999.99)*10,-1) -> 210 | U38: N | V38: N | W38: N | X38: N | Y38: =IF(W38="Y",T38,0) -> 0 | Z38: =IF(X38="Y",T38*2,0) -> 0 | AA38: =Y38+Z38 -> 0
A39: 21 | B39: IKN400787 | C39: 13-272 | D39: Radiographic Units, Mobile | E39: 1149550 | F39: 13 | G39: 88 | H39: - | I39: - | J39: 99.824328 | T39: =ROUNDUP((E39/4999.99)*10,-1) -> 2300 | U39: N | V39: N | W39: N | X39: N | Y39: =IF(W39="Y",T39,0) -> 0 | Z39: =IF(X39="Y",T39*2,0) -> 0 | AA39: =Y39+Z39 -> 0
A40: 22 | B40: IKN400937 | C40: 16-173 | D40: Sphygmomanometers, Electronic, Automatic | E40: 336 | F40: 13 | G40: 88 | H40: - | I40: - | J40: 99.916396 | T40: =ROUNDUP((E40/4999.99)*10,-1) -> 10 | U40: Y | V40: N | W40: N | X40: N | Y40: =IF(W40="Y",T40,0) -> 0 | Z40: =IF(X40="Y",T40*2,0) -> 0 | AA40: =Y40+Z40 -> 0
A41: 23 | B41: IKN401007 | C41: 15-999 | D41: Washers, Flexible Endoscope | E41: 126300 | F41: 13 | G41: 85 | H41: - | I41: - | J41: 99.925846 | T41: =ROUNDUP((E41/4999.99)*10,-1) -> 260 | U41: N | V41: N | W41: N | X41: N | Y41: =IF(W41="Y",T41,0) -> 0 | Z41: =IF(X41="Y",T41*2,0) -> 0 | AA41: =Y41+Z41 -> 0
A42: 24 | B42: IKN400293 | C42: 17-148 | D42: Oximeters, Pulse | E42: 5410 | F42: 13 | G42: 88 | H42: - | I42: - | J42: 99.935425 | T42: =ROUNDUP((E42/4999.99)*10,-1) -> 20 | U42: Y | V42: N | W42: N | X42: N
A43: 25 | B43: IKN400029 | C43: 12-647 | D43: Physiologic Monitoring Systems, Acute Care | E43: 105850 | F43: 13 | G43: 88 | H43: - | I43: - | J43: 99.946764 | T43: =ROUNDUP((E43/4999.99)*10,-1) -> 220 | U43: N | V43: N | W43: N | X43: N | Y43: =IF(W43="Y",T43,0) -> 0 | Z43: =IF(X43="Y",T43*2,0) -> 0 | AA43: =Y43+Z43 -> 0
A44: 26 | B44: IKN400722 | C44: 15-104 | D44: Analyzers, Laboratory, Hematology, Platelet Aggregation | E44: 42100 | F44: 13 | G44: 85 | H44: - | I44: - | J44: 99.981897 | T44: =ROUNDUP((E44/4999.99)*10,-1) -> 90 | U44: N | V44: N | W44: N | X44: N | Y44: =IF(W44="Y",T44,0) -> 0 | Z44: =IF(X44="Y",T44*2,0) -> 0 | AA44: =Y44+Z44 -> 0
A45: TOTAL DEDUCTION FOR IND. B.4: | AA45: =SUM(AA19:AA34) -> 0
I93: 0 days, 1 hrs, 8 mins | K93: 31-Mar-2026 09:30:00 | L93: 31-Mar-2026 10:00:00 | V93: M-REPLACE NEW BATTERY ,UNIT TEST FUNCTIONING WELL. UNIT PROPOSE TO BER DUE TO AUDATED TECHNOLOGY
V96: PO : ETA :
V97: CHARGER FAULTY WAITING PARTS FROM VENDOR (B BROUN) PO : ETA :
V98: LCD BOARD FAULTY WAITING PARTS FROM VENDOR PO : ETA :
